Workbook
Name NgonorreaePost: '2017-2022'!#REF!
Name subcategoria: categorias!$B:$B
Name POST: '2017-2022'!$A:$K
Name Estado: categorias!$C$2:$C$65536
Name SegmentaciónDeDatos_PubYear: #REF!
Name EXCLUIDAS: Excluidas!$A$1:$K$463
Name NgonorreaePre: '2012-2017'!$A$1:$K$534
Name categoria: categorias!$A:$A
Name KEYWORDS: 'Palabras claves'!$A:$K
Name SegmentaciónDeDatos_Alerta1: #REF!
Name PREALERTA: '2012-2017'!$A$1:$O$540
Name PRE: '2012-2017'!$A:$K
Name SegmentaciónDeDatos_KeyWords: #REF!
Name PalabrasClave: 'Palabras claves'!$K$1:$K$1371
Name EXCL: Excluidas!$A:$K
Name POSTALERTA: '2017-2022'!$A$1:$B$857
Name TablaNgonoreae: '2012-2022'!$A$1:$K$4211

Sheet DashBoard
C2: Rickettsia spp 2012-2022
C3: Total de publicaciones de | F3: =C2 -> Rickettsia spp 2012-2022 | G3: : | H3: =COUNTA('2012-2022'!A$1:A$873064)-1 -> 7031
D5: Publicaciones por Año | I5: Categorías y Subcategorías
D17: Publicaciones por mes

Sheet categorias
A1: Categorias | B1: Subcategorias | C1: Estados
A2: 1) Reporte de cepas resistentes | B2: 2a) Productos naturales | C2: Revisar
A3: 2) Nuevos tratamientos | B3: 2b) Péptidos | C3: Listo
A4: 3) Inmunizacióm | B4: 2c) Droga de diseño | C4: Excluir
A5: 4) otros | B5: 2d) Anticuerpos | C5: Otros-A
B6: 2e) Bacteriófagos | C6: Otros-B
B7: 2f) Estrategias antivirulencia | C7: Otros-C
B8: 2g) nueva combinación de ATB | C8: Otros-D

Sheet TablasDinamicas
B1: Etiquetas de fila | C1: Cuenta de Title | E1: Cuenta de Title | I1: Categoria | J1: subcategoria | K1: Cuenta de Title
B2: PreAlerta | C2: 2899 | E2: PubYear | F2: PubMonth | G2: Total | I2: 1) Interacción huésped-patógeno | J2: (en blanco) | K2: 2 | L2: 1) Interacción huésped-patógeno | M2: (en blanco) | N2: =GETPIVOTDATA("Title",$I$1,"Categoria",L2,"subcategoria",M2) -> #REF! | P2: Etiquetas de fila | Q2: Cuenta de Title | S2: Etiquetas de fila | T2: Cuenta de Title | V2: Etiquetas de fila | W2: Cuenta de Title
B3: PostAlerta | C3: 3619 | E3: 2017 | F3: Jan | G3: 69 | I3: Total 1) Interacción huésped-patógeno | K3: 2 | L3: 2) Reporte de cepas resistentes | M3: (en blanco) | N3: =GETPIVOTDATA("Title",$I$1,"Categoria",L3,"subcategoria",M3) -> #REF! | P3: (en blanco) | Q3: 7031 | T3: 0
B4: Excluido | C4: 513 | F4: Feb | G4: 61 | I4: 2) Reporte de cepas resistentes | J4: (en blanco) | K4: 2 | L4: 3) Casos clínicos | M4: (en blanco) | N4: =GETPIVOTDATA("Title",$I$1,"Categoria",L4,"subcategoria",M4) -> #REF! | P4: Total general | Q4: 7031 | S4: 2012 | T4: 428
B5: Total general | C5: 7031 | F5: Mar | G5: 76 | I5: Total 2) Reporte de cepas resistentes | K5: 2 | L5: 4) Nuevos tratamientos | M5: 4a) Productos naturales | N5: =GETPIVOTDATA("Title",$I$1,"Categoria",L5,"subcategoria",M5) -> #REF! | S5: 2013 | T5: 558 | V5: S/PalabrasClaves | W5: 6782
F6: Apr | G6: 42 | I6: 3) Casos clínicos | J6: (en blanco) | K6: 2 | L6: 4) Nuevos tratamientos | M6: 4b) Péptidos | N6: =GETPIVOTDATA("Title",$I$1,"Categoria",L6,"subcategoria",M6) -> #REF! | S6: 2014 | T6: 596 | V6: Excluido | W6: 469
F7: May | G7: 39 | I7: Total 3) Casos clínicos | K7: 2 | L7: 4) Nuevos tratamientos | M7: 4c) Droga de diseño | N7: =GETPIVOTDATA("Title",$I$1,"Categoria",L7,"subcategoria",M7) -> #REF! | S7: 2015 | T7: 583 | V7: PostAlerta | W7: 3504
F8: Jun | G8: 65 | I8: 4) Nuevos tratamientos | J8: 4a) Productos naturales | K8: 1 | L8: 4) Nuevos tratamientos | M8: 4d) Anticuerpos | N8: =GETPIVOTDATA("Title",$I$1,"Categoria",L8,"subcategoria",M8) -> #REF! | S8: 2016 | T8: 699 | V8: PreAlerta | W8: 2809
F9: Jul | G9: 45 | J9: 4b) Péptidos | K9: 1 | L9: 4) Nuevos tratamientos | M9: 4e) Bacteriófagos | N9: =GETPIVOTDATA("Title",$I$1,"Categoria",L9,"subcategoria",M9) -> #REF! | S9: 2017 | T9: 654 | V9: (en blanco)
F10: Aug | G10: 61 | J10: 4c) Droga de diseño | K10: 2 | L10: 4) Nuevos tratamientos | M10: 4f) Estrategias antivirulencia | N10: =GETPIVOTDATA("Title",$I$1,"Categoria",L10,"subcategoria",M10) -> #REF! | S10: 2018 | T10: 751 | V10: (en blanco)
F11: Sep | G11: 47 | J11: 4d) Anticuerpos | K11: 1 | S11: 2019 | T11: 700 | V11: Total general | W11: 6782
F12: Oct | G12: 43 | J12: 4e) Bacteriófagos | K12: 1 | S12: 2020 | T12: 762
F13: Nov | G13: 59 | J13: 4f) Estrategias antivirulencia | K13: 1 | S13: 2021 | T13: 785
F14: Dec | G14: 58 | I14: Total 4) Nuevos tratamientos | K14: 7 | S14: 2022 | T14: 258
F15: ver paper | G15: 11 | I15: (en blanco) | J15: (en blanco) | K15: 6769 | S15: 2023 | T15: 8
E16: Total 2017 | G16: 676 | I16: Total (en blanco) | K16: 6769 | S16: (en blanco) | T16: 0
E17: (en blanco) | F17: (en blanco) | I17: Total general | K17: 6782 | S17: Total general | T17: 6782
E18: Total (en blanco)
E19: Total general | G19: 676

Sheet 2012-2022
A1: PMID | B1: Title | C1: Authors | D1: Citation | E1: First Author | F1: Journal/Book | G1: Publication Year | H1: Create Date | I1: PMCID | J1: NIHMS ID | K1: DOI | L1: Alerta | M1: KeyWords | N1: Categoria | O1: subcategoria | P1: fecha de publicación | Q1: Estado | R1: PubYear | S1: PubMonth | T1: Abstract | U1: 1) Reporte de cepas resistentes? | V1: 2) Nuevos tratamientos | W1: 3) Inmunización | X1: Justificacion (no mas de 140 caracteres)
A2: 26467958 | B2: Modification of Insect and Arachnid Behaviours by Vertically Transmitted Endosymbionts: Infections as Drivers of Behavioural Change and Evolutionary Novelty | C2: Goodacre SL, Martin OY. | D2: Insects. 2012 Feb 29;3(1):246-61. doi: 10.3390/insects3010246. | E2: Goodacre SL | F2: Insects | G2: 2012 | H2: 42293 | I2: PMC4553626 | K2: 10.3390/insects3010246 | L2: =IF(ISNUMBER(VLOOKUP(A2,EXCL,1,FALSE)),"Excluido",IF(ISNUMBER(VLOOKUP(A2,POST,1,FALSE)),"PostAlerta",IF(ISNUMBER(VLOOKUP(A2,PRE,1,FALSE)),"PreAlerta",""))) -> Excluido | M2: =IF(ISNUMBER(VLOOKUP(A2,KEYWORDS,1,FALSE)),"C/PalabrasClaves","S/PalabrasClaves") -> S/PalabrasClaves | N2: =IF(ISNUMBER(SEARCH("TREATMENT", B2)), "4) Nuevos tratamientos", "") | P2: 2012 Feb 29 | R2: =LEFT('2012-2022'!$P2,4) -> 2012 | S2: Feb
A3: 21668575 | B3: Histopathological diagnosis of Japanese spotted fever using formalin-fixed, paraffin-embedded skin biopsy specimens: usefulness of immunohistochemistry and real-time PCR analysis | C3: Tamakuma K, Mizutani Y, Ito M, Shiogama K, Inada K, Miyamoto K, Utsunomiya H, Mahara F, Tsutsumi Y. | D3: Clin Microbiol Infect. 2012 Mar;18(3):260-7. doi: 10.1111/j.1469-0691.2011.03569.x. Epub 2011 Jun 10. | E3: Tamakuma K | F3: Clin Microbiol Infect | G3: 2012 | H3: 40709 | K3: 10.1111/j.1469-0691.2011.03569.x | L3: =IF(ISNUMBER(VLOOKUP(A3,EXCL,1,FALSE)),"Excluido",IF(ISNUMBER(VLOOKUP(A3,POST,1,FALSE)),"PostAlerta",IF(ISNUMBER(VLOOKUP(A3,PRE,1,FALSE)),"PreAlerta",""))) -> PreAlerta | M3: =IF(ISNUMBER(VLOOKUP(A3,KEYWORDS,1,FALSE)),"C/PalabrasClaves","S/PalabrasClaves") -> S/PalabrasClaves | N3: =IF(ISNUMBER(SEARCH("TREATMENT", B3)), "4) Nuevos tratamientos", "") | P3: 2012 Mar | R3: =LEFT('2012-2022'!$P3,4) -> 2012 | S3: Mar
A4: 21781141 | B4: Expression of heat shock proteins and subolesin affects stress responses, Anaplasma phagocytophilum infection and questing behaviour in the tick, Ixodes scapularis | C4: Busby AT, Ayllón N, Kocan KM, Blouin EF, de la Fuente G, Galindo RC, Villar M, de la Fuente J. | D4: Med Vet Entomol. 2012 Mar;26(1):92-102. doi: 10.1111/j.1365-2915.2011.00973.x. Epub 2011 Jul 22. | E4: Busby AT | F4: Med Vet Entomol | G4: 2012 | H4: 40750 | K4: 10.1111/j.1365-2915.2011.00973.x | L4: =IF(ISNUMBER(VLOOKUP(A4,EXCL,1,FALSE)),"Excluido",IF(ISNUMBER(VLOOKUP(A4,POST,1,FALSE)),"PostAlerta",IF(ISNUMBER(VLOOKUP(A4,PRE,1,FALSE)),"PreAlerta",""))) -> PreAlerta | M4: =IF(ISNUMBER(A4),(IF(ISNUMBER(VLOOKUP(A4,KEYWORDS,1,FALSE)),"C/PalabrasClaves","S/PalabrasClaves")),"") -> S/PalabrasClaves | N4: =IF(ISNUMBER(SEARCH("TREATMENT", B4)), "4) Nuevos tratamientos", "") | P4: 2012 Mar | R4: =LEFT('2012-2022'!$P4,4) -> 2012 | S4: Mar
A5: 21785920 | B5: Diplorickettsia massiliensis as a human pathogen | C5: Subramanian G, Mediannikov O, Angelakis E, Socolovschi C, Kaplanski G, Martzolff L, Raoult D. | D5: Eur J Clin Microbiol Infect Dis. 2012 Mar;31(3):365-9. doi: 10.1007/s10096-011-1318-7. Epub 2011 Jul 22. | E5: Subramanian G | F5: Eur J Clin Microbiol Infect Dis | G5: 2012 | H5: 40750 | K5: 10.1007/s10096-011-1318-7 | L5: =IF(ISNUMBER(VLOOKUP(A5,EXCL,1,FALSE)),"Excluido",IF(ISNUMBER(VLOOKUP(A5,POST,1,FALSE)),"PostAlerta",IF(ISNUMBER(VLOOKUP(A5,PRE,1,FALSE)),"PreAlerta",""))) -> PreAlerta | M5: =IF(ISNUMBER(A5),(IF(ISNUMBER(VLOOKUP(A5,KEYWORDS,1,FALSE)),"C/PalabrasClaves","S/PalabrasClaves")),"") -> S/PalabrasClaves | N5: =IF(ISNUMBER(SEARCH("TREATMENT", B5)), "4) Nuevos tratamientos", "") | P5: 2012 Mar | R5: =LEFT('2012-2022'!$P5,4) -> 2012 | S5: Mar
A6: 21842137 | B6: Correlations among Anaplasma marginale parasitemia and markers of oxidative stress in crossbred calves | C6: De UK, Dey S, Banerjee PS, Sahoo M. | D6: Trop Anim Health Prod. 2012 Mar;44(3):385-8. doi: 10.1007/s11250-011-9938-6. Epub 2011 Aug 13. | E6: De UK | F6: Trop Anim Health Prod | G6: 2012 | H6: 40771 | K6: 10.1007/s11250-011-9938-6 | L6: =IF(ISNUMBER(VLOOKUP(A6,EXCL,1,FALSE)),"Excluido",IF(ISNUMBER(VLOOKUP(A6,POST,1,FALSE)),"PostAlerta",IF(ISNUMBER(VLOOKUP(A6,PRE,1,FALSE)),"PreAlerta",""))) -> PreAlerta | M6: =IF(ISNUMBER(A6),(IF(ISNUMBER(VLOOKUP(A6,KEYWORDS,1,FALSE)),"C/PalabrasClaves","S/PalabrasClaves")),"") -> S/PalabrasClaves | N6: =IF(ISNUMBER(SEARCH("TREATMENT", B6)), "4) Nuevos tratamientos", "") | P6: 2012 Mar | R6: =LEFT('2012-2022'!$P6,4) -> 2012 | S6: Mar
A7: 21934703 | B7: Occasional males in parthenogenetic populations of Asobara japonica (Hymenoptera: Braconidae): low Wolbachia titer or incomplete coadaptation? | C7: Reumer BM, van Alphen JJ, Kraaijeveld K. | D7: Heredity (Edinb). 2012 Mar;108(3):341-6. doi: 10.1038/hdy.2011.82. Epub 2011 Sep 21. | E7: Reumer BM | F7: Heredity (Edinb) | G7: 2012 | H7: 40808 | I7: PMC3282404 | K7: 10.1038/hdy.2011.82 | L7: =IF(ISNUMBER(VLOOKUP(A7,EXCL,1,FALSE)),"Excluido",IF(ISNUMBER(VLOOKUP(A7,POST,1,FALSE)),"PostAlerta",IF(ISNUMBER(VLOOKUP(A7,PRE,1,FALSE)),"PreAlerta",""))) -> PreAlerta | M7: =IF(ISNUMBER(A7),(IF(ISNUMBER(VLOOKUP(A7,KEYWORDS,1,FALSE)),"C/PalabrasClaves","S/PalabrasClaves")),"") -> S/PalabrasClaves | N7: =IF(ISNUMBER(SEARCH("TREATMENT", B7)), "4) Nuevos tratamientos", "") | P7: 2012 Mar | R7: =LEFT('2012-2022'!$P7,4) -> 2012 | S7: Mar
A8: 21938022 | B8: Unveiling in situ interactions between marine protists and bacteria through single cell sequencing | C8: Martinez-Garcia M, Brazel D, Poulton NJ, Swan BK, Gomez ML, Masland D, Sieracki ME, Stepanauskas R. | D8: ISME J. 2012 Mar;6(3):703-7. doi: 10.1038/ismej.2011.126. Epub 2011 Sep 22. | E8: Martinez-Garcia M | F8: ISME J | G8: 2012 | H8: 40809 | I8: PMC3280149 | K8: 10.1038/ismej.2011.126 | L8: =IF(ISNUMBER(VLOOKUP(A8,EXCL,1,FALSE)),"Excluido",IF(ISNUMBER(VLOOKUP(A8,POST,1,FALSE)),"PostAlerta",IF(ISNUMBER(VLOOKUP(A8,PRE,1,FALSE)),"PreAlerta",""))) -> PreAlerta | M8: =IF(ISNUMBER(A8),(IF(ISNUMBER(VLOOKUP(A8,KEYWORDS,1,FALSE)),"C/PalabrasClaves","S/PalabrasClaves")),"") -> S/PalabrasClaves | N8: =IF(ISNUMBER(SEARCH("TREATMENT", B8)), "4) Nuevos tratamientos", "") | P8: 2012 Mar | R8: =LEFT('2012-2022'!$P8,4) -> 2012 | S8: Mar
A9: 22022815 | B9: Detection of Rickettsia parkeri and Candidatus Rickettsia andeanae in Amblyomma maculatum Gulf Coast ticks collected from humans in the United States | C9: Jiang J, Stromdahl EY, Richards AL. | D9: Vector Borne Zoonotic Dis. 2012 Mar;12(3):175-82. doi: 10.1089/vbz.2011.0614. Epub 2011 Oct 24. | E9: Jiang J | F9: Vector Borne Zoonotic Dis | G9: 2012 | H9: 40842 | K9: 10.1089/vbz.2011.0614 | L9: =IF(ISNUMBER(VLOOKUP(A9,EXCL,1,FALSE)),"Excluido",IF(ISNUMBER(VLOOKUP(A9,POST,1,FALSE)),"PostAlerta",IF(ISNUMBER(VLOOKUP(A9,PRE,1,FALSE)),"PreAlerta",""))) -> PreAlerta | M9: =IF(ISNUMBER(A9),(IF(ISNUMBER(VLOOKUP(A9,KEYWORDS,1,FALSE)),"C/PalabrasClaves","S/PalabrasClaves")),"") -> S/PalabrasClaves | N9: =IF(ISNUMBER(SEARCH("TREATMENT", B9)), "4) Nuevos tratamientos", "") | P9: 2012 Mar | R9: =LEFT('2012-2022'!$P9,4) -> 2012 | S9: Mar
A10: 22076027 | B10: Cross-effects of nickel contamination and parasitism on zebra mussel physiology | C10: Minguez L, Boiché A, Sroda S, Mastitsky S, Brulé N, Bouquerel J, Giambérini L. | D10: Ecotoxicology. 2012 Mar;21(2):538-47. doi: 10.1007/s10646-011-0814-y. Epub 2011 Nov 12. | E10: Minguez L | F10: Ecotoxicology | G10: 2012 | H10: 40862 | K10: 10.1007/s10646-011-0814-y | L10: =IF(ISNUMBER(VLOOKUP(A10,EXCL,1,FALSE)),"Excluido",IF(ISNUMBER(VLOOKUP(A10,POST,1,FALSE)),"PostAlerta",IF(ISNUMBER(VLOOKUP(A10,PRE,1,FALSE)),"PreAlerta",""))) -> PreAlerta | M10: =IF(ISNUMBER(A10),(IF(ISNUMBER(VLOOKUP(A10,KEYWORDS,1,FALSE)),"C/PalabrasClaves","S/PalabrasClaves")),"") -> S/PalabrasClaves | N10: =IF(ISNUMBER(SEARCH("TREATMENT", B10)), "4) Nuevos tratamientos", "") | P10: 2012 Mar | R10: =LEFT('2012-2022'!$P10,4) -> 2012 | S10: Mar
A11: 22159737 | B11: Polyclonal antibody against conserved sequences of mce1A protein blocks MTB infection in macrophages | C11: Sivagnanam S, Namasivayam N, Chellam R. | D11: Appl Microbiol Biotechnol. 2012 Mar;93(6):2463-73. doi: 10.1007/s00253-011-3754-9. Epub 2011 Dec 13. | E11: Sivagnanam S | F11: Appl Microbiol Biotechnol | G11: 2012 | H11: 40891 | K11: 10.1007/s00253-011-3754-9 | L11: =IF(ISNUMBER(VLOOKUP(A11,EXCL,1,FALSE)),"Excluido",IF(ISNUMBER(VLOOKUP(A11,POST,1,FALSE)),"PostAlerta",IF(ISNUMBER(VLOOKUP(A11,PRE,1,FALSE)),"PreAlerta",""))) -> PreAlerta | M11: =IF(ISNUMBER(A11),(IF(ISNUMBER(VLOOKUP(A11,KEYWORDS,1,FALSE)),"C/PalabrasClaves","S/PalabrasClaves")),"") -> S/PalabrasClaves | N11: =IF(ISNUMBER(SEARCH("TREATMENT", B11)), "4) Nuevos tratamientos", "") | P11: 2012 Mar | R11: =LEFT('2012-2022'!$P11,4) -> 2012 | S11: Mar
A12: 22172602 | B12: Infections with Wolbachia and Spiroplasma in the Scathophagidae and other Muscoidea | C12: Martin OY, Gubler A, Wimmer C, Germann C, Bernasconi MV. | D12: Infect Genet Evol. 2012 Mar;12(2):315-23. doi: 10.1016/j.meegid.2011.11.012. Epub 2011 Dec 8. | E12: Martin OY | F12: Infect Genet Evol | G12: 2012 | H12: 40894 | K12: 10.1016/j.meegid.2011.11.012 | L12: =IF(ISNUMBER(VLOOKUP(A12,EXCL,1,FALSE)),"Excluido",IF(ISNUMBER(VLOOKUP(A12,POST,1,FALSE)),"PostAlerta",IF(ISNUMBER(VLOOKUP(A12,PRE,1,FALSE)),"PreAlerta",""))) -> PreAlerta | M12: =IF(ISNUMBER(A12),(IF(ISNUMBER(VLOOKUP(A12,KEYWORDS,1,FALSE)),"C/PalabrasClaves","S/PalabrasClaves")),"") -> S/PalabrasClaves | N12: =IF(ISNUMBER(SEARCH("TREATMENT", B12)), "4) Nuevos tratamientos", "") | P12: 2012 Mar | R12: =LEFT('2012-2022'!$P12,4) -> 2012 | S12: Mar
A13: 22205824 | B13: "Candidatus Neoehrlichia mikurensis," Anaplasma phagocytophilum, and lyme disease spirochetes in questing european vector ticks and in feeding ticks removed from people | C13: Richter D, Matuschka FR. | D13: J Clin Microbiol. 2012 Mar;50(3):943-7. doi: 10.1128/JCM.05802-11. Epub 2012 Jan 11. | E13: Richter D | F13: J Clin Microbiol | G13: 2012 | H13: 40907 | I13: PMC3295140 | K13: 10.1128/JCM.05802-11 | L13: =IF(ISNUMBER(VLOOKUP(A13,EXCL,1,FALSE)),"Excluido",IF(ISNUMBER(VLOOKUP(A13,POST,1,FALSE)),"PostAlerta",IF(ISNUMBER(VLOOKUP(A13,PRE,1,FALSE)),"PreAlerta",""))) -> PreAlerta | M13: =IF(ISNUMBER(A13),(IF(ISNUMBER(VLOOKUP(A13,KEYWORDS,1,FALSE)),"C/PalabrasClaves","S/PalabrasClaves")),"") -> S/PalabrasClaves | N13: =IF(ISNUMBER(SEARCH("TREATMENT", B13)), "4) Nuevos tratamientos", "") | P13: 2012 Mar | R13: =LEFT('2012-2022'!$P13,4) -> 2012 | S13: Mar
A14: 22210220 | B14: Wolbachia strain wAlbB enhances infection by the rodent malaria parasite Plasmodium berghei in Anopheles gambiae mosquitoes | C14: Hughes GL, Vega-Rodriguez J, Xue P, Rasgon JL. | D14: Appl Environ Microbiol. 2012 Mar;78(5):1491-5. doi: 10.1128/AEM.06751-11. Epub 2011 Dec 30. | E14: Hughes GL | F14: Appl Environ Microbiol | G14: 2012 | H14: 40911 | I14: PMC3294472 | K14: 10.1128/AEM.06751-11 | L14: =IF(ISNUMBER(VLOOKUP(A14,EXCL,1,FALSE)),"Excluido",IF(ISNUMBER(VLOOKUP(A14,POST,1,FALSE)),"PostAlerta",IF(ISNUMBER(VLOOKUP(A14,PRE,1,FALSE)),"PreAlerta",""))) -> PreAlerta | M14: =IF(ISNUMBER(A14),(IF(ISNUMBER(VLOOKUP(A14,KEYWORDS,1,FALSE)),"C/PalabrasClaves","S/PalabrasClaves")),"") -> S/PalabrasClaves | N14: =IF(ISNUMBER(SEARCH("TREATMENT", B14)), "4) Nuevos tratamientos", "") | P14: 2012 Mar | R14: =LEFT('2012-2022'!$P14,4) -> 2012 | S14: Mar
A15: 22214329 | B15: Wolbachia and its implications for the immunopathology of filariasis | C15: Genchi C, Kramer LH, Sassera D, Bandi C. | D15: Endocr Metab Immune Disord Drug Targets. 2012 Mar;12(1):53-6. doi: 10.2174/187153012799279108. | E15: Genchi C | F15: Endocr Metab Immune Disord Drug Targets | G15: 2012 | H15: 40913 | K15: 10.2174/187153012799279108 | L15: =IF(ISNUMBER(VLOOKUP(A15,EXCL,1,FALSE)),"Excluido",IF(ISNUMBER(VLOOKUP(A15,POST,1,FALSE)),"PostAlerta",IF(ISNUMBER(VLOOKUP(A15,PRE,1,FALSE)),"PreAlerta",""))) -> Excluido | M15: =IF(ISNUMBER(A15),(IF(ISNUMBER(VLOOKUP(A15,KEYWORDS,1,FALSE)),"C/PalabrasClaves","S/PalabrasClaves")),"") -> S/PalabrasClaves | N15: =IF(ISNUMBER(SEARCH("TREATMENT", B15)), "4) Nuevos tratamientos", "") | P15: 2012 Mar | R15: =LEFT('2012-2022'!$P15,4) -> 2012 | S15: Mar
A16: 22219313 | B16: Prospective evaluation of commercial antibody-based rapid tests in combination with a loop-mediated isothermal amplification PCR assay for detection of Orientia tsutsugamushi during the acute phase of scrub typhus infection | C16: Blacksell SD, Paris DH, Chierakul W, Wuthiekanun V, Teeratakul A, Kantipong P, Day NP. | D16: Clin Vaccine Immunol. 2012 Mar;19(3):391-5. doi: 10.1128/CVI.05478-11. Epub 2012 Jan 4. | E16: Blacksell SD | F16: Clin Vaccine Immunol | G16: 2012 | H16: 40914 | I16: PMC3294598 | K16: 10.1128/CVI.05478-11 | L16: =IF(ISNUMBER(VLOOKUP(A16,EXCL,1,FALSE)),"Excluido",IF(ISNUMBER(VLOOKUP(A16,POST,1,FALSE)),"PostAlerta",IF(ISNUMBER(VLOOKUP(A16,PRE,1,FALSE)),"PreAlerta",""))) -> PreAlerta | M16: =IF(ISNUMBER(A16),(IF(ISNUMBER(VLOOKUP(A16,KEYWORDS,1,FALSE)),"C/PalabrasClaves","S/PalabrasClaves")),"") -> S/PalabrasClaves | N16: =IF(ISNUMBER(SEARCH("TREATMENT", B16)), "4) Nuevos tratamientos", "") | P16: 2012 Mar | R16: =LEFT('2012-2022'!$P16,4) -> 2012 | S16: Mar
A17: 22222114 | B17: Rickettsiae in arthropods collected from the North African Hedgehog (Atelerix algirus) and the desert hedgehog (Paraechinus aethiopicus) in Algeria | C17: Khaldi M, Socolovschi C, Benyettou M, Barech G, Biche M, Kernif T, Raoult D, Parola P. | D17: Comp Immunol Microbiol Infect Dis. 2012 Mar;35(2):117-22. doi: 10.1016/j.cimid.2011.11.007. Epub 2012 Jan 4. | E17: Khaldi M | F17: Comp Immunol Microbiol Infect Dis | G17: 2012 | H17: 40915 | K17: 10.1016/j.cimid.2011.11.007 | L17: =IF(ISNUMBER(VLOOKUP(A17,EXCL,1,FALSE)),"Excluido",IF(ISNUMBER(VLOOKUP(A17,POST,1,FALSE)),"PostAlerta",IF(ISNUMBER(VLOOKUP(A17,PRE,1,FALSE)),"PreAlerta",""))) -> PreAlerta | M17: =IF(ISNUMBER(A17),(IF(ISNUMBER(VLOOKUP(A17,KEYWORDS,1,FALSE)),"C/PalabrasClaves","S/PalabrasClaves")),"") -> S/PalabrasClaves | N17: =IF(ISNUMBER(SEARCH("TREATMENT", B17)), "4) Nuevos tratamientos", "") | P17: 2012 Mar | R17: =LEFT('2012-2022'!$P17,4) -> 2012 | S17: Mar
A18: 22257655 | B18: A case of rickettsialpox in Northern Europe | C18: Renvoisé A, van't Wout JW, van der Schroeff JG, Beersma MF, Raoult D. | D18: Int J Infect Dis. 2012 Mar;16(3):e221-2. doi: 10.1016/j.ijid.2011.11.009. Epub 2012 Jan 17. | E18: Renvoisé A | F18: Int J Infect Dis | G18: 2012 | H18: 40928 | K18: 10.1016/j.ijid.2011.11.009 | L18: =IF(ISNUMBER(VLOOKUP(A18,EXCL,1,FALSE)),"Excluido",IF(ISNUMBER(VLOOKUP(A18,POST,1,FALSE)),"PostAlerta",IF(ISNUMBER(VLOOKUP(A18,PRE,1,FALSE)),"PreAlerta",""))) -> PreAlerta | M18: =IF(ISNUMBER(A18),(IF(ISNUMBER(VLOOKUP(A18,KEYWORDS,1,FALSE)),"C/PalabrasClaves","S/PalabrasClaves")),"") -> S/PalabrasClaves | N18: =IF(ISNUMBER(SEARCH("TREATMENT", B18)), "4) Nuevos tratamientos", "") | P18: 2012 Mar | R18: =LEFT('2012-2022'!$P18,4) -> 2012 | S18: Mar
A19: 22266203 | B19: Presence and distribution of the endosymbiont Wolbachia among Solenopsis spp. (Hymenoptera: Formicidae) from Brazil and its evolutionary history | C19: Martins C, Souza RF, Bueno OC. | D19: J Invertebr Pathol. 2012 Mar;109(3):287-96. doi: 10.1016/j.jip.2012.01.001. Epub 2012 Jan 12. | E19: Martins C | F19: J Invertebr Pathol | G19: 2012 | H19: 40932 | K19: 10.1016/j.jip.2012.01.001 | L19: =IF(ISNUMBER(VLOOKUP(A19,EXCL,1,FALSE)),"Excluido",IF(ISNUMBER(VLOOKUP(A19,POST,1,FALSE)),"PostAlerta",IF(ISNUMBER(VLOOKUP(A19,PRE,1,FALSE)),"PreAlerta",""))) -> PreAlerta | M19: =IF(ISNUMBER(A19),(IF(ISNUMBER(VLOOKUP(A19,KEYWORDS,1,FALSE)),"C/PalabrasClaves","S/PalabrasClaves")),"") -> S/PalabrasClaves | N19: =IF(ISNUMBER(SEARCH("TREATMENT", B19)), "4) Nuevos tratamientos", "") | P19: 2012 Mar | R19: =LEFT('2012-2022'!$P19,4) -> 2012 | S19: Mar
A20: 22268975 | B20: Integration of molecular, ecological, morphological and endosymbiont data for species delimitation within the Pnigalio soemius complex (Hymenoptera: Eulophidae) | C20: Gebiola M, Gómez-Zurita J, Monti MM, Navone P, Bernardo U. | D20: Mol Ecol. 2012 Mar;21(5):1190-208. doi: 10.1111/j.1365-294X.2011.05428.x. Epub 2012 Jan 23. | E20: Gebiola M | F20: Mol Ecol | G20: 2012 | H20: 40933 | K20: 10.1111/j.1365-294X.2011.05428.x | L20: =IF(ISNUMBER(VLOOKUP(A20,EXCL,1,FALSE)),"Excluido",IF(ISNUMBER(VLOOKUP(A20,POST,1,FALSE)),"PostAlerta",IF(ISNUMBER(VLOOKUP(A20,PRE,1,FALSE)),"PreAlerta",""))) -> PreAlerta | M20: =IF(ISNUMBER(A20),(IF(ISNUMBER(VLOOKUP(A20,KEYWORDS,1,FALSE)),"C/PalabrasClaves","S/PalabrasClaves")),"") -> S/PalabrasClaves | N20: =IF(ISNUMBER(SEARCH("TREATMENT", B20)), "4) Nuevos tratamientos", "") | P20: 2012 Mar | R20: =LEFT('2012-2022'!$P20,4) -> 2012 | S20: Mar
A21: 22277830 | B21: New Rickettsia sp. in tsetse flies from Senegal | C21: Mediannikov O, Audoly G, Diatta G, Trape JF, Raoult D. | D21: Comp Immunol Microbiol Infect Dis. 2012 Mar;35(2):145-50. doi: 10.1016/j.cimid.2011.12.011. Epub 2012 Jan 23. | E21: Mediannikov O | F21: Comp Immunol Microbiol Infect Dis | G21: 2012 | H21: 40935 | K21: 10.1016/j.cimid.2011.12.011 | L21: =IF(ISNUMBER(VLOOKUP(A21,EXCL,1,FALSE)),"Excluido",IF(ISNUMBER(VLOOKUP(A21,POST,1,FALSE)),"PostAlerta",IF(ISNUMBER(VLOOKUP(A21,PRE,1,FALSE)),"PreAlerta",""))) -> PreAlerta | M21: =IF(ISNUMBER(A21),(IF(ISNUMBER(VLOOKUP(A21,KEYWORDS,1,FALSE)),"C/PalabrasClaves","S/PalabrasClaves")),"") -> S/PalabrasClaves | N21: =IF(ISNUMBER(SEARCH("TREATMENT", B21)), "4) Nuevos tratamientos", "") | P21: 2012 Mar | R21: =LEFT('2012-2022'!$P21,4) -> 2012 | S21: Mar
A22: 22282331 | B22: Tetracyclines and pain | C22: Bastos LF, de Oliveira AC, Watkins LR, Moraes MF, Coelho MM. | D22: Naunyn Schmiedebergs Arch Pharmacol. 2012 Mar;385(3):225-41. doi: 10.1007/s00210-012-0727-1. Epub 2012 Jan 27. | E22: Bastos LF | F22: Naunyn Schmiedebergs Arch Pharmacol | G22: 2012 | H22: 40936 | K22: 10.1007/s00210-012-0727-1 | L22: =IF(ISNUMBER(VLOOKUP(A22,EXCL,1,FALSE)),"Excluido",IF(ISNUMBER(VLOOKUP(A22,POST,1,FALSE)),"PostAlerta",IF(ISNUMBER(VLOOKUP(A22,PRE,1,FALSE)),"PreAlerta",""))) -> Excluido | M22: =IF(ISNUMBER(A22),(IF(ISNUMBER(VLOOKUP(A22,KEYWORDS,1,FALSE)),"C/PalabrasClaves","S/PalabrasClaves")),"") -> C/PalabrasClaves | N22: =IF(ISNUMBER(SEARCH("TREATMENT", B22)), "4) Nuevos tratamientos", "") | P22: 2012 Mar | R22: =LEFT('2012-2022'!$P22,4) -> 2012 | S22: Mar
A23: 22293464 | B23: Diversity and phylogenetic analysis of endosymbiotic bacteria from field caught Bemisia tabaci from different locations of North India based on 16S rDNA library screening | C23: Singh ST, Priya NG, Kumar J, Rana VS, Ellango R, Joshi A, Priyadarshini G, Asokan R, Rajagopal R. | D23: Infect Genet Evol. 2012 Mar;12(2):411-9. doi: 10.1016/j.meegid.2012.01.015. Epub 2012 Jan 24. | E23: Singh ST | F23: Infect Genet Evol | G23: 2012 | H23: 40941 | K23: 10.1016/j.meegid.2012.01.015 | L23: =IF(ISNUMBER(VLOOKUP(A23,EXCL,1,FALSE)),"Excluido",IF(ISNUMBER(VLOOKUP(A23,POST,1,FALSE)),"PostAlerta",IF(ISNUMBER(VLOOKUP(A23,PRE,1,FALSE)),"PreAlerta",""))) -> PreAlerta | M23: =IF(ISNUMBER(A23),(IF(ISNUMBER(VLOOKUP(A23,KEYWORDS,1,FALSE)),"C/PalabrasClaves","S/PalabrasClaves")),"") -> S/PalabrasClaves | N23: =IF(ISNUMBER(SEARCH("TREATMENT", B23)), "4) Nuevos tratamientos", "") | P23: 2012 Mar | R23: =LEFT('2012-2022'!$P23,4) -> 2012 | S23: Mar
A24: 22305337 | B24: Molecular detection and characterization of Anaplasma phagocytophilum strains | C24: Paulauskas A, Radzijevskaja J, Rosef O. | D24: Comp Immunol Microbiol Infect Dis. 2012 Mar;35(2):187-95. doi: 10.1016/j.cimid.2012.01.001. Epub 2012 Feb 3. | E24: Paulauskas A | F24: Comp Immunol Microbiol Infect Dis | G24: 2012 | H24: 40946 | K24: 10.1016/j.cimid.2012.01.001 | L24: =IF(ISNUMBER(VLOOKUP(A24,EXCL,1,FALSE)),"Excluido",IF(ISNUMBER(VLOOKUP(A24,POST,1,FALSE)),"PostAlerta",IF(ISNUMBER(VLOOKUP(A24,PRE,1,FALSE)),"PreAlerta",""))) -> PreAlerta | M24: =IF(ISNUMBER(A24),(IF(ISNUMBER(VLOOKUP(A24,KEYWORDS,1,FALSE)),"C/PalabrasClaves","S/PalabrasClaves")),"") -> S/PalabrasClaves | N24: =IF(ISNUMBER(SEARCH("TREATMENT", B24)), "4) Nuevos tratamientos", "") | P24: 2012 Mar | R24: =LEFT('2012-2022'!$P24,4) -> 2012 | S24: Mar
A25: 22321996 | B25: Human granulocytic anaplasmosis in eastern France: clinical presentation and laboratory diagnosis | C25: Koebel C, Kern A, Edouard S, Hoang AT, Celestin N, Hansmann Y, Jaulhac B, Brouqui P, De Martino SJ. | D25: Diagn Microbiol Infect Dis. 2012 Mar;72(3):214-8. doi: 10.1016/j.diagmicrobio.2011.12.005. | E25: Koebel C | F25: Diagn Microbiol Infect Dis | G25: 2012 | H25: 40950 | K25: 10.1016/j.diagmicrobio.2011.12.005 | L25: =IF(ISNUMBER(VLOOKUP(A25,EXCL,1,FALSE)),"Excluido",IF(ISNUMBER(VLOOKUP(A25,POST,1,FALSE)),"PostAlerta",IF(ISNUMBER(VLOOKUP(A25,PRE,1,FALSE)),"PreAlerta",""))) -> PreAlerta | M25: =IF(ISNUMBER(A25),(IF(ISNUMBER(VLOOKUP(A25,KEYWORDS,1,FALSE)),"C/PalabrasClaves","S/PalabrasClaves")),"") -> S/PalabrasClaves | N25: =IF(ISNUMBER(SEARCH("TREATMENT", B25)), "4) Nuevos tratamientos", "") | P25: 2012 Mar | R25: =LEFT('2012-2022'!$P25,4) -> 2012 | S25: Mar
A26: 22369153 | B26: Genomics of epidemic pathogens | C26: Georgiades K. | D26: Clin Microbiol Infect. 2012 Mar;18(3):213-7. doi: 10.1111/j.1469-0691.2012.03781.x. | E26: Georgiades K | F26: Clin Microbiol Infect | G26: 2012 | H26: 40968 | K26: 10.1111/j.1469-0691.2012.03781.x | L26: =IF(ISNUMBER(VLOOKUP(A26,EXCL,1,FALSE)),"Excluido",IF(ISNUMBER(VLOOKUP(A26,POST,1,FALSE)),"PostAlerta",IF(ISNUMBER(VLOOKUP(A26,PRE,1,FALSE)),"PreAlerta",""))) -> Excluido | M26: =IF(ISNUMBER(A26),(IF(ISNUMBER(VLOOKUP(A26,KEYWORDS,1,FALSE)),"C/PalabrasClaves","S/PalabrasClaves")),"") -> S/PalabrasClaves | N26: =IF(ISNUMBER(SEARCH("TREATMENT", B26)), "4) Nuevos tratamientos", "") | P26: 2012 Mar | R26: =LEFT('2012-2022'!$P26,4) -> 2012 | S26: Mar
A27: 22374949 | B27: Complete genome sequence of Rickettsia slovaca, the agent of tick-borne lymphadenitis | C27: Fournier PE, El Karkouri K, Robert C, Médigue C, Raoult D. | D27: J Bacteriol. 2012 Mar;194(6):1612. doi: 10.1128/JB.06625-11. | E27: Fournier PE | F27: J Bacteriol | G27: 2012 | H27: 40969 | I27: PMC3294842 | K27: 10.1128/JB.06625-11 | L27: =IF(ISNUMBER(VLOOKUP(A27,EXCL,1,FALSE)),"Excluido",IF(ISNUMBER(VLOOKUP(A27,POST,1,FALSE)),"PostAlerta",IF(ISNUMBER(VLOOKUP(A27,PRE,1,FALSE)),"PreAlerta",""))) -> PreAlerta | M27: =IF(ISNUMBER(A27),(IF(ISNUMBER(VLOOKUP(A27,KEYWORDS,1,FALSE)),"C/PalabrasClaves","S/PalabrasClaves")),"") -> S/PalabrasClaves | N27: =IF(ISNUMBER(SEARCH("TREATMENT", B27)), "4) Nuevos tratamientos", "") | P27: 2012 Mar | R27: =LEFT('2012-2022'!$P27,4) -> 2012 | S27: Mar
A28: 22376001 | B28: Absence of linkage disequilibria between chromosomal arrangements and mtDNA haplotypes in natural populations of Drosophila subobscura from the Balkan Peninsula | C28: Jelić M, Castro JA, Kurbalija Novičić Z, Kenig B, Dimitrijević D, Savić Veselinović M, Jovanović M, Milovanović D, Stamenković-Radak M, Andjelković M. | D28: Genome. 2012 Mar;55(3):214-21. doi: 10.1139/g2012-004. Epub 2012 Feb 29. | E28: Jelić M | F28: Genome | G28: 2012 | H28: 40970 | K28: 10.1139/g2012-004 | L28: =IF(ISNUMBER(VLOOKUP(A28,EXCL,1,FALSE)),"Excluido",IF(ISNUMBER(VLOOKUP(A28,POST,1,FALSE)),"PostAlerta",IF(ISNUMBER(VLOOKUP(A28,PRE,1,FALSE)),"PreAlerta",""))) -> PreAlerta | M28: =IF(ISNUMBER(A28),(IF(ISNUMBER(VLOOKUP(A28,KEYWORDS,1,FALSE)),"C/PalabrasClaves","S/PalabrasClaves")),"") -> S/PalabrasClaves | N28: =IF(ISNUMBER(SEARCH("TREATMENT", B28)), "4) Nuevos tratamientos", "") | P28: 2012 Mar | R28: =LEFT('2012-2022'!$P28,4) -> 2012 | S28: Mar
A29: 22379331 | B29: Persistence of Orientia tsutsugamushi in humans | C29: Chung MH, Lee JS, Baek JH, Kim M, Kang JS. | D29: J Korean Med Sci. 2012 Mar;27(3):231-5. doi: 10.3346/jkms.2012.27.3.231. Epub 2012 Feb 23. | E29: Chung MH | F29: J Korean Med Sci | G29: 2012 | H29: 40970 | I29: PMC3286767 | K29: 10.3346/jkms.2012.27.3.231 | L29: =IF(ISNUMBER(VLOOKUP(A29,EXCL,1,FALSE)),"Excluido",IF(ISNUMBER(VLOOKUP(A29,POST,1,FALSE)),"PostAlerta",IF(ISNUMBER(VLOOKUP(A29,PRE,1,FALSE)),"PreAlerta",""))) -> PreAlerta | M29: =IF(ISNUMBER(A29),(IF(ISNUMBER(VLOOKUP(A29,KEYWORDS,1,FALSE)),"C/PalabrasClaves","S/PalabrasClaves")),"") -> S/PalabrasClaves | N29: =IF(ISNUMBER(SEARCH("TREATMENT", B29)), "4) Nuevos tratamientos", "") | P29: 2012 Mar | R29: =LEFT('2012-2022'!$P29,4) -> 2012 | S29: Mar
A30: 22380432 | B30: Maintenance of a male-killing Wolbachia in Drosophila innubila by male-killing dependent and male-killing independent mechanisms | C30: Unckless RL, Jaenike J. | D30: Evolution. 2012 Mar;66(3):678-689. doi: 10.1111/j.1558-5646.2011.01485.x. Epub 2011 Nov 11. | E30: Unckless RL | F30: Evolution | G30: 2012 | H30: 40971 | K30: 10.1111/j.1558-5646.2011.01485.x | L30: =IF(ISNUMBER(VLOOKUP(A30,EXCL,1,FALSE)),"Excluido",IF(ISNUMBER(VLOOKUP(A30,POST,1,FALSE)),"PostAlerta",IF(ISNUMBER(VLOOKUP(A30,PRE,1,FALSE)),"PreAlerta",""))) -> PreAlerta | M30: =IF(ISNUMBER(A30),(IF(ISNUMBER(VLOOKUP(A30,KEYWORDS,1,FALSE)),"C/PalabrasClaves","S/PalabrasClaves")),"") -> S/PalabrasClaves | N30: =IF(ISNUMBER(SEARCH("TREATMENT", B30)), "4) Nuevos tratamientos", "") | P30: 2012 Mar | R30: =LEFT('2012-2022'!$P30,4) -> 2012 | S30: Mar
A31: 22386178 | B31: Clinical findings and diagnosis in human granulocytic anaplasmosis: a case series from Massachusetts | C31: Weil AA, Baron EL, Brown CM, Drapkin MS. | D31: Mayo Clin Proc. 2012 Mar;87(3):233-9. doi: 10.1016/j.mayocp.2011.09.008. | E31: Weil AA | F31: Mayo Clin Proc | G31: 2012 | H31: 40974 | I31: PMC3498394 | K31: 10.1016/j.mayocp.2011.09.008 | L31: =IF(ISNUMBER(VLOOKUP(A31,EXCL,1,FALSE)),"Excluido",IF(ISNUMBER(VLOOKUP(A31,POST,1,FALSE)),"PostAlerta",IF(ISNUMBER(VLOOKUP(A31,PRE,1,FALSE)),"PreAlerta",""))) -> PreAlerta | M31: =IF(ISNUMBER(A31),(IF(ISNUMBER(VLOOKUP(A31,KEYWORDS,1,FALSE)),"C/PalabrasClaves","S/PalabrasClaves")),"") -> S/PalabrasClaves | N31: =IF(ISNUMBER(SEARCH("TREATMENT", B31)), "4) Nuevos tratamientos", "") | P31: 2012 Mar | R31: =LEFT('2012-2022'!$P31,4) -> 2012 | S31: Mar
A32: 22392278 | B32: Preliminary analysis to target pyruvate phosphate dikinase from wolbachia endosymbiont of Brugia malayi for designing anti-filarial agents | C32: Palayam M, Lakshminarayanan K, Radhakrishnan M, Krishnaswamy G. | D32: Interdiscip Sci. 2012 Mar;4(1):74-82. doi: 10.1007/s12539-011-0109-2. Epub 2012 Mar 6. | E32: Palayam M | F32: Interdiscip Sci | G32: 2012 | H32: 40975 | K32: 10.1007/s12539-011-0109-2 | L32: =IF(ISNUMBER(VLOOKUP(A32,EXCL,1,FALSE)),"Excluido",IF(ISNUMBER(VLOOKUP(A32,POST,1,FALSE)),"PostAlerta",IF(ISNUMBER(VLOOKUP(A32,PRE,1,FALSE)),"PreAlerta",""))) -> PreAlerta | M32: =IF(ISNUMBER(A32),(IF(ISNUMBER(VLOOKUP(A32,KEYWORDS,1,FALSE)),"C/PalabrasClaves","S/PalabrasClaves")),"") -> C/PalabrasClaves | N32: =IF(ISNUMBER(SEARCH("TREATMENT", B32)), "4) Nuevos tratamientos", "") | P32: 2012 Mar | R32: =LEFT('2012-2022'!$P32,4) -> 2012 | S32: Mar
A33: 22484753 | B33: Rickettsial diseases in central India | C33: Mohta A. | D33: Indian Pediatr. 2012 Mar;49(3):251; discussion 251-2. | E33: Mohta A | F33: Indian Pediatr | G33: 2012 | H33: 41009 | L33: =IF(ISNUMBER(VLOOKUP(A33,EXCL,1,FALSE)),"Excluido",IF(ISNUMBER(VLOOKUP(A33,POST,1,FALSE)),"PostAlerta",IF(ISNUMBER(VLOOKUP(A33,PRE,1,FALSE)),"PreAlerta",""))) -> PreAlerta | M33: =IF(ISNUMBER(A33),(IF(ISNUMBER(VLOOKUP(A33,KEYWORDS,1,FALSE)),"C/PalabrasClaves","S/PalabrasClaves")),"") -> S/PalabrasClaves | N33: =IF(ISNUMBER(SEARCH("TREATMENT", B33)), "4) Nuevos tratamientos", "") | P33: 2012 Mar | R33: =LEFT('2012-2022'!$P33,4) -> 2012 | S33: Mar
A34: 22515036 | B34: Seroprevalence and bacteremia [corrected] of Anaplasma phagocytophilum in cats from Bavaria and Lower Saxony (Germany) | C34: Hamel D, Bondarenko A, Silaghi C, Nolte I, Pfister K. | D34: Berl Munch Tierarztl Wochenschr. 2012 Mar-Apr;125(3-4):163-7. | E34: Hamel D | F34: Berl Munch Tierarztl Wochenschr | G34: 2012 | H34: 41020 | L34: =IF(ISNUMBER(VLOOKUP(A34,EXCL,1,FALSE)),"Excluido",IF(ISNUMBER(VLOOKUP(A34,POST,1,FALSE)),"PostAlerta",IF(ISNUMBER(VLOOKUP(A34,PRE,1,FALSE)),"PreAlerta",""))) -> PreAlerta | M34: =IF(ISNUMBER(A34),(IF(ISNUMBER(VLOOKUP(A34,KEYWORDS,1,FALSE)),"C/PalabrasClaves","S/PalabrasClaves")),"") -> S/PalabrasClaves | N34: =IF(ISNUMBER(SEARCH("TREATMENT", B34)), "4) Nuevos tratamientos", "") | P34: 2012 Apr | R34: =LEFT('2012-2022'!$P34,4) -> 2012 | S34: Apr
A35: 22543604 | B35: Comparative seroprevalences of bovine trypanosomiasis and anaplasmosis in five states of Malaysia | C35: Rahman WA, Fong S, Chandrawathani P, Nurulaini R, Zaini CM, Premalaatha B. | D35: Trop Biomed. 2012 Mar;29(1):65-70. | E35: Rahman WA | F35: Trop Biomed | G35: 2012 | H35: 41030 | L35: =IF(ISNUMBER(VLOOKUP(A35,EXCL,1,FALSE)),"Excluido",IF(ISNUMBER(VLOOKUP(A35,POST,1,FALSE)),"PostAlerta",IF(ISNUMBER(VLOOKUP(A35,PRE,1,FALSE)),"PreAlerta",""))) -> PreAlerta | M35: =IF(ISNUMBER(A35),(IF(ISNUMBER(VLOOKUP(A35,KEYWORDS,1,FALSE)),"C/PalabrasClaves","S/PalabrasClaves")),"") -> S/PalabrasClaves | N35: =IF(ISNUMBER(SEARCH("TREATMENT", B35)), "4) Nuevos tratamientos", "") | P35: 2012 Mar | R35: =LEFT('2012-2022'!$P35,4) -> 2012 | S35: Mar
A36: 22585246 | B36: Pleuropulmonary scrub typhus: a summary of Thai cases | C36: Wiwanitkit S, Wiwanitkit V. | D36: J Vector Borne Dis. 2012 Mar;49(1):48. | E36: Wiwanitkit S | F36: J Vector Borne Dis | G36: 2012 | H36: 41045 | L36: =IF(ISNUMBER(VLOOKUP(A36,EXCL,1,FALSE)),"Excluido",IF(ISNUMBER(VLOOKUP(A36,POST,1,FALSE)),"PostAlerta",IF(ISNUMBER(VLOOKUP(A36,PRE,1,FALSE)),"PreAlerta",""))) -> PreAlerta | M36: =IF(ISNUMBER(A36),(IF(ISNUMBER(VLOOKUP(A36,KEYWORDS,1,FALSE)),"C/PalabrasClaves","S/PalabrasClaves")),"") -> S/PalabrasClaves | N36: =IF(ISNUMBER(SEARCH("TREATMENT", B36)), "4) Nuevos tratamientos", "") | P36: 2012 Mar | R36: =LEFT('2012-2022'!$P36,4) -> 2012 | S36: Mar
A37: 22595273 | B37: Molecular detection and analysis of spotted fever group Rickettsia in patients with fever and rash at a tertiary care centre in Tamil Nadu, India | C37: Prakash JA, Sohan Lal T, Rosemol V, Verghese VP, Pulimood SA, Reller M, Dumler JS. | D37: Pathog Glob Health. 2012 Mar;106(1):40-5. doi: 10.1179/2047773212Y.0000000001. | E37: Prakash JA | F37: Pathog Glob Health | G37: 2012 | H37: 41048 | I37: PMC4001510 | K37: 10.1179/2047773212Y.0000000001 | L37: =IF(ISNUMBER(VLOOKUP(A37,EXCL,1,FALSE)),"Excluido",IF(ISNUMBER(VLOOKUP(A37,POST,1,FALSE)),"PostAlerta",IF(ISNUMBER(VLOOKUP(A37,PRE,1,FALSE)),"PreAlerta",""))) -> PreAlerta | M37: =IF(ISNUMBER(A37),(IF(ISNUMBER(VLOOKUP(A37,KEYWORDS,1,FALSE)),"C/PalabrasClaves","S/PalabrasClaves")),"") -> S/PalabrasClaves | N37: =IF(ISNUMBER(SEARCH("TREATMENT", B37)), "4) Nuevos tratamientos", "") | P37: 2012 Mar | R37: =LEFT('2012-2022'!$P37,4) -> 2012 | S37: Mar
A38: 22383821 | B38: Didier Raoult profile. Sound and fury in the microbiology lab | C38: Mary C. | D38: Science. 2012 Mar 2;335(6072):1033-5. doi: 10.1126/science.335.6072.1033. | E38: Mary C | F38: Science | G38: 2012 | H38: 40971 | K38: 10.1126/science.335.6072.1033 | L38: =IF(ISNUMBER(VLOOKUP(A38,EXCL,1,FALSE)),"Excluido",IF(ISNUMBER(VLOOKUP(A38,POST,1,FALSE)),"PostAlerta",IF(ISNUMBER(VLOOKUP(A38,PRE,1,FALSE)),"PreAlerta",""))) -> PreAlerta | M38: =IF(ISNUMBER(A38),(IF(ISNUMBER(VLOOKUP(A38,KEYWORDS,1,FALSE)),"C/PalabrasClaves","S/PalabrasClaves")),"") -> S/PalabrasClaves | N38: =IF(ISNUMBER(SEARCH("TREATMENT", B38)), "4) Nuevos tratamientos", "") | P38: 2012 Mar 2 | R38: =LEFT('2012-2022'!$P38,4) -> 2012 | S38: Mar
A39: 22401583 | B39: First case of Anaplasma platys infection in a dog from Croatia | C39: Dyachenko V, Pantchev N, Balzer HJ, Meyersen A, Straubinger RK. | D39: Parasit Vectors. 2012 Mar 9;5:49. doi: 10.1186/1756-3305-5-49. | E39: Dyachenko V | F39: Parasit Vectors | G39: 2012 | H39: 40978 | I39: PMC3315729 | K39: 10.1186/1756-3305-5-49 | L39: =IF(ISNUMBER(VLOOKUP(A39,EXCL,1,FALSE)),"Excluido",IF(ISNUMBER(VLOOKUP(A39,POST,1,FALSE)),"PostAlerta",IF(ISNUMBER(VLOOKUP(A39,PRE,1,FALSE)),"PreAlerta",""))) -> PreAlerta | M39: =IF(ISNUMBER(A39),(IF(ISNUMBER(VLOOKUP(A39,KEYWORDS,1,FALSE)),"C/PalabrasClaves","S/PalabrasClaves")),"") -> S/PalabrasClaves | N39: =IF(ISNUMBER(SEARCH("TREATMENT", B39)), "4) Nuevos tratamientos", "") | P39: 2012 Mar 9 | R39: =LEFT('2012-2022'!$P39,4) -> 2012 | S39: Mar
A40: 22433114 | B40: Long term impact of large scale community-directed delivery of doxycycline for the treatment of onchocerciasis | C40: Tamarozzi F, Tendongfor N, Enyong PA, Esum M, Faragher B, Wanji S, Taylor MJ. | D40: Parasit Vectors. 2012 Mar 20;5:53. doi: 10.1186/1756-3305-5-53. | E40: Tamarozzi F | F40: Parasit Vectors | G40: 2012 | H40: 40990 | I40: PMC3350421 | K40: 10.1186/1756-3305-5-53 | L40: =IF(ISNUMBER(VLOOKUP(A40,EXCL,1,FALSE)),"Excluido",IF(ISNUMBER(VLOOKUP(A40,POST,1,FALSE)),"PostAlerta",IF(ISNUMBER(VLOOKUP(A40,PRE,1,FALSE)),"PreAlerta",""))) -> PreAlerta | M40: =IF(ISNUMBER(A40),(IF(ISNUMBER(VLOOKUP(A40,KEYWORDS,1,FALSE)),"C/PalabrasClaves","S/PalabrasClaves")),"") -> S/PalabrasClaves | P40: 2012 Mar 20 | R40: =LEFT('2012-2022'!$P40,4) -> 2012 | S40: Mar
A41: 22192469 | B41: Constraints on the use of lifespan-shortening Wolbachia to control dengue fever | C41: Schraiber JG, Kaczmarczyk AN, Kwok R, Park M, Silverstein R, Rutaganira FU, Aggarwal T, Schwemmer MA, Hom CL, Grosberg RK, Schreiber SJ. | D41: J Theor Biol. 2012 Mar 21;297:26-32. doi: 10.1016/j.jtbi.2011.12.006. Epub 2011 Dec 16. | E41: Schraiber JG | F41: J Theor Biol | G41: 2012 | H41: 40901 | K41: 10.1016/j.jtbi.2011.12.006 | L41: =IF(ISNUMBER(VLOOKUP(A41,EXCL,1,FALSE)),"Excluido",IF(ISNUMBER(VLOOKUP(A41,POST,1,FALSE)),"PostAlerta",IF(ISNUMBER(VLOOKUP(A41,PRE,1,FALSE)),"PreAlerta",""))) -> PreAlerta | M41: =IF(ISNUMBER(A41),(IF(ISNUMBER(VLOOKUP(A41,KEYWORDS,1,FALSE)),"C/PalabrasClaves","S/PalabrasClaves")),"") -> S/PalabrasClaves | N41: =IF(ISNUMBER(SEARCH("TREATMENT", B41)), "4) Nuevos tratamientos", "") | P41: 2012 Mar 21 | R41: =LEFT('2012-2022'!$P41,4) -> 2012 | S41: Mar
A42: 21940118 | B42: Acute phase response in cattle infected with Anaplasma marginale | C42: Nazifi S, Razavi SM, Kaviani F, Rakhshandehroo E. | D42: Vet Microbiol. 2012 Mar 23;155(2-4):267-71. doi: 10.1016/j.vetmic.2011.08.024. Epub 2011 Aug 31. | E42: Nazifi S | F42: Vet Microbiol | G42: 2012 | H42: 40810 | K42: 10.1016/j.vetmic.2011.08.024 | L42: =IF(ISNUMBER(VLOOKUP(A42,EXCL,1,FALSE)),"Excluido",IF(ISNUMBER(VLOOKUP(A42,POST,1,FALSE)),"PostAlerta",IF(ISNUMBER(VLOOKUP(A42,PRE,1,FALSE)),"PreAlerta",""))) -> PreAlerta | M42: =IF(ISNUMBER(A42),(IF(ISNUMBER(VLOOKUP(A42,KEYWORDS,1,FALSE)),"C/PalabrasClaves","S/PalabrasClaves")),"") -> S/PalabrasClaves | N42: =IF(ISNUMBER(SEARCH("TREATMENT", B42)), "4) Nuevos tratamientos", "") | P42: 2012 Mar 23 | R42: =LEFT('2012-2022'!$P42,4) -> 2012 | S42: Mar
A43: 22452970 | B43: Occurrence and identification of risk areas of Ixodes ricinus-borne pathogens: a cost-effectiveness analysis in north-eastern Italy | C43: Capelli G, Ravagnan S, Montarsi F, Ciocchetta S, Cazzin S, Porcellato E, Babiker AM, Cassini R, Salviato A, Cattoli G, Otranto D. | D43: Parasit Vectors. 2012 Mar 27;5:61. doi: 10.1186/1756-3305-5-61. | E43: Capelli G | F43: Parasit Vectors | G43: 2012 | H43: 40997 | I43: PMC3337281 | K43: 10.1186/1756-3305-5-61 | L43: =IF(ISNUMBER(VLOOKUP(A43,EXCL,1,FALSE)),"Excluido",IF(ISNUMBER(VLOOKUP(A43,POST,1,FALSE)),"PostAlerta",IF(ISNUMBER(VLOOKUP(A43,PRE,1,FALSE)),"PreAlerta",""))) -> PreAlerta | M43: =IF(ISNUMBER(A43),(IF(ISNUMBER(VLOOKUP(A43,KEYWORDS,1,FALSE)),"C/PalabrasClaves","S/PalabrasClaves")),"") -> S/PalabrasClaves | N43: =IF(ISNUMBER(SEARCH("TREATMENT", B43)), "4) Nuevos tratamientos", "") | P43: 2012 Mar 27 | R43: =LEFT('2012-2022'!$P43,4) -> 2012 | S43: Mar
A44: 22462408 | B44: Dose-response model of murine typhus (Rickettsia typhi): time post inoculation and host age dependency analysis | C44: Tamrakar SB, Huang Y, Teske SS, Haas CN. | D44: BMC Infect Dis. 2012 Mar 30;12:77. doi: 10.1186/1471-2334-12-77. | E44: Tamrakar SB | F44: BMC Infect Dis | G44: 2012 | H44: 41002 | I44: PMC3359249 | K44: 10.1186/1471-2334-12-77 | L44: =IF(ISNUMBER(VLOOKUP(A44,EXCL,1,FALSE)),"Excluido",IF(ISNUMBER(VLOOKUP(A44,POST,1,FALSE)),"PostAlerta",IF(ISNUMBER(VLOOKUP(A44,PRE,1,FALSE)),"PreAlerta",""))) -> Excluido | M44: =IF(ISNUMBER(A44),(IF(ISNUMBER(VLOOKUP(A44,KEYWORDS,1,FALSE)),"C/PalabrasClaves","S/PalabrasClaves")),"") -> S/PalabrasClaves | N44: =IF(ISNUMBER(SEARCH("TREATMENT", B44)), "4) Nuevos tratamientos", "") | P44: 2012 Mar 30 | R44: =LEFT('2012-2022'!$P44,4) -> 2012 | S44: Mar
A45: 21947341 | B45: Longitudinal field study on bovine Babesia spp. and Anaplasma phagocytophilum infections during a grazing season in Belgium | C45: Lempereur L, Lebrun M, Cuvelier P, Sépult G, Caron Y, Saegerman C, Shiels B, Losson B. | D45: Parasitol Res. 2012 Apr;110(4):1525-30. doi: 10.1007/s00436-011-2657-0. Epub 2011 Sep 27. | E45: Lempereur L | F45: Parasitol Res | G45: 2012 | H45: 40814 | K45: 10.1007/s00436-011-2657-0 | L45: =IF(ISNUMBER(VLOOKUP(A45,EXCL,1,FALSE)),"Excluido",IF(ISNUMBER(VLOOKUP(A45,POST,1,FALSE)),"PostAlerta",IF(ISNUMBER(VLOOKUP(A45,PRE,1,FALSE)),"PreAlerta",""))) -> PreAlerta | M45: =IF(ISNUMBER(A45),(IF(ISNUMBER(VLOOKUP(A45,KEYWORDS,1,FALSE)),"C/PalabrasClaves","S/PalabrasClaves")),"") -> S/PalabrasClaves | N45: =IF(ISNUMBER(SEARCH("TREATMENT", B45)), "4) Nuevos tratamientos", "") | P45: 2012 Apr | R45: =LEFT('2012-2022'!$P45,4) -> 2012 | S45: Mar
A46: 21947342 | B46: Epidemiological aspects on vector-borne infections in stray and pet dogs from Romania and Hungary with focus on Babesia spp | C46: Hamel D, Silaghi C, Lescai D, Pfister K. | D46: Parasitol Res. 2012 Apr;110(4):1537-45. doi: 10.1007/s00436-011-2659-y. Epub 2011 Sep 27. | E46: Hamel D | F46: Parasitol Res | G46: 2012 | H46: 40814 | K46: 10.1007/s00436-011-2659-y | L46: =IF(ISNUMBER(VLOOKUP(A46,EXCL,1,FALSE)),"Excluido",IF(ISNUMBER(VLOOKUP(A46,POST,1,FALSE)),"PostAlerta",IF(ISNUMBER(VLOOKUP(A46,PRE,1,FALSE)),"PreAlerta",""))) -> PreAlerta | M46: =IF(ISNUMBER(A46),(IF(ISNUMBER(VLOOKUP(A46,KEYWORDS,1,FALSE)),"C/PalabrasClaves","S/PalabrasClaves")),"") -> S/PalabrasClaves | N46: =IF(ISNUMBER(SEARCH("TREATMENT", B46)), "4) Nuevos tratamientos", "") | P46: 2012 Apr | R46: =LEFT('2012-2022'!$P46,4) -> 2012 | S46: Apr
A47: 22032328 | B47: Absence of Wolbachia endobacteria in Chandlerella quiscali, an avian filarial parasite | C47: McNulty SN, Fischer K, Mehus JO, Vaughan JA, Tkach VV, Weil GJ, Fischer PU. | D47: J Parasitol. 2012 Apr;98(2):382-7. doi: 10.1645/GE-2879.1. Epub 2011 Oct 27. | E47: McNulty SN | F47: J Parasitol | G47: 2012 | H47: 40845 | I47: PMC5000782 | J47: NIHMS811498 | K47: 10.1645/GE-2879.1 | L47: =IF(ISNUMBER(VLOOKUP(A47,EXCL,1,FALSE)),"Excluido",IF(ISNUMBER(VLOOKUP(A47,POST,1,FALSE)),"PostAlerta",IF(ISNUMBER(VLOOKUP(A47,PRE,1,FALSE)),"PreAlerta",""))) -> PreAlerta | M47: =IF(ISNUMBER(A47),(IF(ISNUMBER(VLOOKUP(A47,KEYWORDS,1,FALSE)),"C/PalabrasClaves","S/PalabrasClaves")),"") -> S/PalabrasClaves | N47: =IF(ISNUMBER(SEARCH("TREATMENT", B47)), "4) Nuevos tratamientos", "") | P47: 2012 Apr | R47: =LEFT('2012-2022'!$P47,4) -> 2012 | S47: Apr
A48: 22140099 | B48: Crystal structure of the DNA-bound VapBC2 antitoxin/toxin pair from Rickettsia felis | C48: Maté MJ, Vincentelli R, Foos N, Raoult D, Cambillau C, Ortiz-Lombardía M. | D48: Nucleic Acids Res. 2012 Apr;40(7):3245-58. doi: 10.1093/nar/gkr1167. Epub 2011 Dec 2. | E48: Maté MJ | F48: Nucleic Acids Res | G48: 2012 | H48: 40883 | I48: PMC3326315 | K48: 10.1093/nar/gkr1167 | L48: =IF(ISNUMBER(VLOOKUP(A48,EXCL,1,FALSE)),"Excluido",IF(ISNUMBER(VLOOKUP(A48,POST,1,FALSE)),"PostAlerta",IF(ISNUMBER(VLOOKUP(A48,PRE,1,FALSE)),"PreAlerta",""))) -> PreAlerta | M48: =IF(ISNUMBER(A48),(IF(ISNUMBER(VLOOKUP(A48,KEYWORDS,1,FALSE)),"C/PalabrasClaves","S/PalabrasClaves")),"") -> S/PalabrasClaves | N48: =IF(ISNUMBER(SEARCH("TREATMENT", B48)), "4) Nuevos tratamientos", "") | P48: 2012 Apr | R48: =LEFT('2012-2022'!$P48,4) -> 2012 | S48: Apr
A49: 22188208 | B49: Rickettsia parkeri invasion of diverse host cells involves an Arp2/3 complex, WAVE complex and Rho-family GTPase-dependent pathway | C49: Reed SC, Serio AW, Welch MD. | D49: Cell Microbiol. 2012 Apr;14(4):529-45. doi: 10.1111/j.1462-5822.2011.01739.x. Epub 2012 Jan 16. | E49: Reed SC | F49: Cell Microbiol | G49: 2012 | H49: 40900 | I49: PMC3302968 | J49: NIHMS344637 | K49: 10.1111/j.1462-5822.2011.01739.x | L49: =IF(ISNUMBER(VLOOKUP(A49,EXCL,1,FALSE)),"Excluido",IF(ISNUMBER(VLOOKUP(A49,POST,1,FALSE)),"PostAlerta",IF(ISNUMBER(VLOOKUP(A49,PRE,1,FALSE)),"PreAlerta",""))) -> PreAlerta | M49: =IF(ISNUMBER(A49),(IF(ISNUMBER(VLOOKUP(A49,KEYWORDS,1,FALSE)),"C/PalabrasClaves","S/PalabrasClaves")),"") -> S/PalabrasClaves | N49: =IF(ISNUMBER(SEARCH("TREATMENT", B49)), "4) Nuevos tratamientos", "") | P49: 2012 Apr | R49: =LEFT('2012-2022'!$P49,4) -> 2012 | S49: Apr
A50: 22212234 | B50: Subversion of NPC1 pathway of cholesterol transport by Anaplasma phagocytophilum | C50: Xiong Q, Rikihisa Y. | D50: Cell Microbiol. 2012 Apr;14(4):560-76. doi: 10.1111/j.1462-5822.2011.01742.x. Epub 2012 Feb 8. | E50: Xiong Q | F50: Cell Microbiol | G50: 2012 | H50: 40912 | I50: PMC3604884 | J50: NIHMS346696 | K50: 10.1111/j.1462-5822.2011.01742.x | L50: =IF(ISNUMBER(VLOOKUP(A50,EXCL,1,FALSE)),"Excluido",IF(ISNUMBER(VLOOKUP(A50,POST,1,FALSE)),"PostAlerta",IF(ISNUMBER(VLOOKUP(A50,PRE,1,FALSE)),"PreAlerta",""))) -> PreAlerta | M50: =IF(ISNUMBER(A50),(IF(ISNUMBER(VLOOKUP(A50,KEYWORDS,1,FALSE)),"C/PalabrasClaves","S/PalabrasClaves")),"") -> S/PalabrasClaves | N50: =IF(ISNUMBER(SEARCH("TREATMENT", B50)), "4) Nuevos tratamientos", "") | P50: 2012 Apr | R50: =LEFT('2012-2022'!$P50,4) -> 2012 | S50: Apr
A51: 22214269 | B51: Detection of Anaplasma phagocytophilum in ixodid ticks from equine-inhabited sites in the Southeastern United States | C51: Roellig DM, Fang QQ. | D51: Vector Borne Zoonotic Dis. 2012 Apr;12(4):330-2. doi: 10.1089/vbz.2011.0757. Epub 2012 Jan 3. | E51: Roellig DM | F51: Vector Borne Zoonotic Dis | G51: 2012 | H51: 40913 | K51: 10.1089/vbz.2011.0757 | L51: =IF(ISNUMBER(VLOOKUP(A51,EXCL,1,FALSE)),"Excluido",IF(ISNUMBER(VLOOKUP(A51,POST,1,FALSE)),"PostAlerta",IF(ISNUMBER(VLOOKUP(A51,PRE,1,FALSE)),"PreAlerta",""))) -> PreAlerta | M51: =IF(ISNUMBER(A51),(IF(ISNUMBER(VLOOKUP(A51,KEYWORDS,1,FALSE)),"C/PalabrasClaves","S/PalabrasClaves")),"") -> S/PalabrasClaves | N51: =IF(ISNUMBER(SEARCH("TREATMENT", B51)), "4) Nuevos tratamientos", "") | P51: 2012 Apr | R51: =LEFT('2012-2022'!$P51,4) -> 2012 | S51: Apr
A52: 22217177 | B52: Epidemiology and control of human granulocytic anaplasmosis: a systematic review | C52: Jin H, Wei F, Liu Q, Qian J. | D52: Vector Borne Zoonotic Dis. 2012 Apr;12(4):269-74. doi: 10.1089/vbz.2011.0753. Epub 2012 Jan 4. | E52: Jin H | F52: Vector Borne Zoonotic Dis | G52: 2012 | H52: 40914 | K52: 10.1089/vbz.2011.0753 | L52: =IF(ISNUMBER(VLOOKUP(A52,EXCL,1,FALSE)),"Excluido",IF(ISNUMBER(VLOOKUP(A52,POST,1,FALSE)),"PostAlerta",IF(ISNUMBER(VLOOKUP(A52,PRE,1,FALSE)),"PreAlerta",""))) -> Excluido | M52: =IF(ISNUMBER(A52),(IF(ISNUMBER(VLOOKUP(A52,KEYWORDS,1,FALSE)),"C/PalabrasClaves","S/PalabrasClaves")),"") -> S/PalabrasClaves | N52: =IF(ISNUMBER(SEARCH("TREATMENT", B52)), "4) Nuevos tratamientos", "") | P52: 2012 Apr | R52: =LEFT('2012-2022'!$P52,4) -> 2012 | S52: Apr
A53: 22221256 | B53: Molecular characterization and tissue-specific gene expression of Dermacentor variabilis α-catenin in response to rickettsial infection | C53: Sunyakumthorn P, Petchampai N, Kearney MT, Sonenshine DE, Macaluso KR. | D53: Insect Mol Biol. 2012 Apr;21(2):197-204. doi: 10.1111/j.1365-2583.2011.01126.x. Epub 2012 Jan 6. | E53: Sunyakumthorn P | F53: Insect Mol Biol | G53: 2012 | H53: 40915 | I53: PMC3299920 | J53: NIHMS340488 | K53: 10.1111/j.1365-2583.2011.01126.x | L53: =IF(ISNUMBER(VLOOKUP(A53,EXCL,1,FALSE)),"Excluido",IF(ISNUMBER(VLOOKUP(A53,POST,1,FALSE)),"PostAlerta",IF(ISNUMBER(VLOOKUP(A53,PRE,1,FALSE)),"PreAlerta",""))) -> PreAlerta | M53: =IF(ISNUMBER(A53),(IF(ISNUMBER(VLOOKUP(A53,KEYWORDS,1,FALSE)),"C/PalabrasClaves","S/PalabrasClaves")),"") -> S/PalabrasClaves | N53: =IF(ISNUMBER(SEARCH("TREATMENT", B53)), "4) Nuevos tratamientos", "") | P53: 2012 Apr | R53: =LEFT('2012-2022'!$P53,4) -> 2012 | S53: Apr
A54: 22225423 | B54: Spotted fever group Rickettsia in Yunnan Province, China | C54: Liang CW, Zhao JB, Li J, Chang LT, Yu HL, Zhang LX, Zhang LJ, Yu XJ. | D54: Vector Borne Zoonotic Dis. 2012 Apr;12(4):281-6. doi: 10.1089/vbz.2011.0835. Epub 2012 Jan 6. | E54: Liang CW | F54: Vector Borne Zoonotic Dis | G54: 2012 | H54: 40918 | K54: 10.1089/vbz.2011.0835 | L54: =IF(ISNUMBER(VLOOKUP(A54,EXCL,1,FALSE)),"Excluido",IF(ISNUMBER(VLOOKUP(A54,POST,1,FALSE)),"PostAlerta",IF(ISNUMBER(VLOOKUP(A54,PRE,1,FALSE)),"PreAlerta",""))) -> PreAlerta | M54: =IF(ISNUMBER(A54),(IF(ISNUMBER(VLOOKUP(A54,KEYWORDS,1,FALSE)),"C/PalabrasClaves","S/PalabrasClaves")),"") -> S/PalabrasClaves | N54: =IF(ISNUMBER(SEARCH("TREATMENT", B54)), "4) Nuevos tratamientos", "") | P54: 2012 Apr | R54: =LEFT('2012-2022'!$P54,4) -> 2012 | S54: Apr
A55: 22252875 | B55: Infection with Anaplasma phagocytophilum activates the phosphatidylinositol 3-Kinase/Akt and NF-κB survival pathways in neutrophil granulocytes | C55: Sarkar A, Hellberg L, Bhattacharyya A, Behnen M, Wang K, Lord JM, Möller S, Kohler M, Solbach W, Laskay T. | D55: Infect Immun. 2012 Apr;80(4):1615-23. doi: 10.1128/IAI.05219-11. Epub 2012 Jan 17. | E55: Sarkar A | F55: Infect Immun | G55: 2012 | H55: 40927 | I55: PMC3318406 | K55: 10.1128/IAI.05219-11 | L55: =IF(ISNUMBER(VLOOKUP(A55,EXCL,1,FALSE)),"Excluido",IF(ISNUMBER(VLOOKUP(A55,POST,1,FALSE)),"PostAlerta",IF(ISNUMBER(VLOOKUP(A55,PRE,1,FALSE)),"PreAlerta",""))) -> PreAlerta | M55: =IF(ISNUMBER(A55),(IF(ISNUMBER(VLOOKUP(A55,KEYWORDS,1,FALSE)),"C/PalabrasClaves","S/PalabrasClaves")),"") -> S/PalabrasClaves | N55: =IF(ISNUMBER(SEARCH("TREATMENT", B55)), "4) Nuevos tratamientos", "") | P55: 2012 Apr | R55: =LEFT('2012-2022'!$P55,4) -> 2012 | S55: Apr
A56: 22286986 | B56: Factors driving the abundance of ixodes ricinus ticks and the prevalence of zoonotic I. ricinus-borne pathogens in natural foci | C56: Ruiz-Fons F, Fernández-de-Mera IG, Acevedo P, Gortázar C, de la Fuente J. | D56: Appl Environ Microbiol. 2012 Apr;78(8):2669-76. doi: 10.1128/AEM.06564-11. Epub 2012 Jan 27. | E56: Ruiz-Fons F | F56: Appl Environ Microbiol | G56: 2012 | H56: 40939 | I56: PMC3318823 | K56: 10.1128/AEM.06564-11 | L56: =IF(ISNUMBER(VLOOKUP(A56,EXCL,1,FALSE)),"Excluido",IF(ISNUMBER(VLOOKUP(A56,POST,1,FALSE)),"PostAlerta",IF(ISNUMBER(VLOOKUP(A56,PRE,1,FALSE)),"PreAlerta",""))) -> PreAlerta | M56: =IF(ISNUMBER(A56),(IF(ISNUMBER(VLOOKUP(A56,KEYWORDS,1,FALSE)),"C/PalabrasClaves","S/PalabrasClaves")),"") -> S/PalabrasClaves | N56: =IF(ISNUMBER(SEARCH("TREATMENT", B56)), "4) Nuevos tratamientos", "") | P56: 2012 Apr | R56: =LEFT('2012-2022'!$P56,4) -> 2012 | S56: Apr
A57: 22327584 | B57: Pathogen prevalence in ticks collected from the vegetation and livestock in Nigeria | C57: Reye AL, Arinola OG, Hübschen JM, Muller CP. | D57: Appl Environ Microbiol. 2012 Apr;78(8):2562-8. doi: 10.1128/AEM.06686-11. Epub 2012 Feb 10. | E57: Reye AL | F57: Appl Environ Microbiol | G57: 2012 | H57: 40953 | I57: PMC3318832 | K57: 10.1128/AEM.06686-11 | L57: =IF(ISNUMBER(VLOOKUP(A57,EXCL,1,FALSE)),"Excluido",IF(ISNUMBER(VLOOKUP(A57,POST,1,FALSE)),"PostAlerta",IF(ISNUMBER(VLOOKUP(A57,PRE,1,FALSE)),"PreAlerta",""))) -> PreAlerta | M57: =IF(ISNUMBER(A57),(IF(ISNUMBER(VLOOKUP(A57,KEYWORDS,1,FALSE)),"C/PalabrasClaves","S/PalabrasClaves")),"") -> S/PalabrasClaves | N57: =IF(ISNUMBER(SEARCH("TREATMENT", B57)), "4) Nuevos tratamientos", "") | P57: 2012 Apr | R57: =LEFT('2012-2022'!$P57,4) -> 2012 | S57: Apr
A58: 22354925 | B58: Fatal ehrlichial myocarditis in a healthy adolescent: a case report and review of the literature | C58: Havens NS, Kinnear BR, Mató S. | D58: Clin Infect Dis. 2012 Apr;54(8):e113-4. doi: 10.1093/cid/cis032. Epub 2012 Feb 21. | E58: Havens NS | F58: Clin Infect Dis | G58: 2012 | H58: 40962 | K58: 10.1093/cid/cis032 | L58: =IF(ISNUMBER(VLOOKUP(A58,EXCL,1,FALSE)),"Excluido",IF(ISNUMBER(VLOOKUP(A58,POST,1,FALSE)),"PostAlerta",IF(ISNUMBER(VLOOKUP(A58,PRE,1,FALSE)),"PreAlerta",""))) -> Excluido | M58: =IF(ISNUMBER(A58),(IF(ISNUMBER(VLOOKUP(A58,KEYWORDS,1,FALSE)),"C/PalabrasClaves","S/PalabrasClaves")),"") -> S/PalabrasClaves | N58: =IF(ISNUMBER(SEARCH("TREATMENT", B58)), "4) Nuevos tratamientos", "") | P58: 2012 Apr | R58: =LEFT('2012-2022'!$P58,4) -> 2012 | S58: Apr
A59: 22360386 | B59: Human louse-transmitted infectious diseases | C59: Badiaga S, Brouqui P. | D59: Clin Microbiol Infect. 2012 Apr;18(4):332-7. doi: 10.1111/j.1469-0691.2012.03778.x. Epub 2012 Feb 23. | E59: Badiaga S | F59: Clin Microbiol Infect | G59: 2012 | H59: 40964 | K59: 10.1111/j.1469-0691.2012.03778.x | L59: =IF(ISNUMBER(VLOOKUP(A59,EXCL,1,FALSE)),"Excluido",IF(ISNUMBER(VLOOKUP(A59,POST,1,FALSE)),"PostAlerta",IF(ISNUMBER(VLOOKUP(A59,PRE,1,FALSE)),"PreAlerta",""))) -> Excluido | M59: =IF(ISNUMBER(A59),(IF(ISNUMBER(VLOOKUP(A59,KEYWORDS,1,FALSE)),"C/PalabrasClaves","S/PalabrasClaves")),"") -> S/PalabrasClaves | N59: =IF(ISNUMBER(SEARCH("TREATMENT", B59)), "4) Nuevos tratamientos", "") | P59: 2012 Apr | R59: =LEFT('2012-2022'!$P59,4) -> 2012 | S59: Apr
A60: 22368278 | B60: Obligate symbionts activate immune system development in the tsetse fly | C60: Weiss BL, Maltz M, Aksoy S. | D60: J Immunol. 2012 Apr 1;188(7):3395-403. doi: 10.4049/jimmunol.1103691. Epub 2012 Feb 24. | E60: Weiss BL | F60: J Immunol | G60: 2012 | H60: 40967 | I60: PMC3311772 | J60: NIHMS354929 | K60: 10.4049/jimmunol.1103691 | L60: =IF(ISNUMBER(VLOOKUP(A60,EXCL,1,FALSE)),"Excluido",IF(ISNUMBER(VLOOKUP(A60,POST,1,FALSE)),"PostAlerta",IF(ISNUMBER(VLOOKUP(A60,PRE,1,FALSE)),"PreAlerta",""))) -> PreAlerta | M60: =IF(ISNUMBER(A60),(IF(ISNUMBER(VLOOKUP(A60,KEYWORDS,1,FALSE)),"C/PalabrasClaves","S/PalabrasClaves")),"") -> S/PalabrasClaves | N60: =IF(ISNUMBER(SEARCH("TREATMENT", B60)), "4) Nuevos tratamientos", "") | P60: 2012 Apr 1 | R60: =LEFT('2012-2022'!$P60,4) -> 2012 | S60: Apr
A61: 22408242 | B61: Whole-genome sequence of Wolbachia strain wAlbB, an endosymbiont of tiger mosquito vector Aedes albopictus | C61: Mavingui P, Valiente Moro C, Tran-Van V, Wisniewski-Dyé F, Raquin V, Minard G, Tran FH, Voronin D, Rouy Z, Bustos P, Lozano L, Barbe V, González V. | D61: J Bacteriol. 2012 Apr;194(7):1840. doi: 10.1128/JB.00036-12. | E61: Mavingui P | F61: J Bacteriol | G61: 2012 | H61: 40981 | I61: PMC3302458 | K61: 10.1128/JB.00036-12 | L61: =IF(ISNUMBER(VLOOKUP(A61,EXCL,1,FALSE)),"Excluido",IF(ISNUMBER(VLOOKUP(A61,POST,1,FALSE)),"PostAlerta",IF(ISNUMBER(VLOOKUP(A61,PRE,1,FALSE)),"PreAlerta",""))) -> PreAlerta | M61: =IF(ISNUMBER(A61),(IF(ISNUMBER(VLOOKUP(A61,KEYWORDS,1,FALSE)),"C/PalabrasClaves","S/PalabrasClaves")),"") -> S/PalabrasClaves | N61: =IF(ISNUMBER(SEARCH("TREATMENT", B61)), "4) Nuevos tratamientos", "") | P61: 2012 Apr | R61: =LEFT('2012-2022'!$P61,4) -> 2012 | S61: Apr
A62: 22431531 | B62: Two cases of transfusion-transmitted Anaplasma phagocytophilum | C62: Annen K, Friedman K, Eshoa C, Horowitz M, Gottschall J, Straus T. | D62: Am J Clin Pathol. 2012 Apr;137(4):562-5. doi: 10.1309/AJCP4E4VQQQOZIAQ. | E62: Annen K | F62: Am J Clin Pathol | G62: 2012 | H62: 40989 | K62: 10.1309/AJCP4E4VQQQOZIAQ | L62: =IF(ISNUMBER(VLOOKUP(A62,EXCL,1,FALSE)),"Excluido",IF(ISNUMBER(VLOOKUP(A62,POST,1,FALSE)),"PostAlerta",IF(ISNUMBER(VLOOKUP(A62,PRE,1,FALSE)),"PreAlerta",""))) -> PreAlerta | M62: =IF(ISNUMBER(A62),(IF(ISNUMBER(VLOOKUP(A62,KEYWORDS,1,FALSE)),"C/PalabrasClaves","S/PalabrasClaves")),"") -> S/PalabrasClaves | N62: =IF(ISNUMBER(SEARCH("TREATMENT", B62)), "4) Nuevos tratamientos", "") | P62: 2012 Apr | R62: =LEFT('2012-2022'!$P62,4) -> 2012 | S62: Apr
A63: 22443327 | B63: Canine vector-borne disease pathogens in dogs from south-east Queensland and north-east Northern Territory | C63: Hii SF, Kopp SR, Thompson MF, O'Leary CA, Rees RL, Traub RJ. | D63: Aust Vet J. 2012 Apr;90(4):130-5. doi: 10.1111/j.1751-0813.2012.00898.x. | E63: Hii SF | F63: Aust Vet J | G63: 2012 | H63: 40995 | K63: 10.1111/j.1751-0813.2012.00898.x | L63: =IF(ISNUMBER(VLOOKUP(A63,EXCL,1,FALSE)),"Excluido",IF(ISNUMBER(VLOOKUP(A63,POST,1,FALSE)),"PostAlerta",IF(ISNUMBER(VLOOKUP(A63,PRE,1,FALSE)),"PreAlerta",""))) -> PreAlerta | M63: =IF(ISNUMBER(A63),(IF(ISNUMBER(VLOOKUP(A63,KEYWORDS,1,FALSE)),"C/PalabrasClaves","S/PalabrasClaves")),"") -> S/PalabrasClaves | N63: =IF(ISNUMBER(SEARCH("TREATMENT", B63)), "4) Nuevos tratamientos", "") | P63: 2012 Apr | R63: =LEFT('2012-2022'!$P63,4) -> 2012 | S63: Apr
A64: 22445929 | B64: Seasonal activity and tick-borne pathogen infection rates of Ixodes ricinus ticks in Hungary | C64: Egyed L, Elő P, Sréter-Lancz Z, Széll Z, Balogh Z, Sréter T. | D64: Ticks Tick Borne Dis. 2012 Apr;3(2):90-4. doi: 10.1016/j.ttbdis.2012.01.002. Epub 2012 Mar 23. | E64: Egyed L | F64: Ticks Tick Borne Dis | G64: 2012 | H64: 40995 | K64: 10.1016/j.ttbdis.2012.01.002 | L64: =IF(ISNUMBER(VLOOKUP(A64,EXCL,1,FALSE)),"Excluido",IF(ISNUMBER(VLOOKUP(A64,POST,1,FALSE)),"PostAlerta",IF(ISNUMBER(VLOOKUP(A64,PRE,1,FALSE)),"PreAlerta",""))) -> PreAlerta | M64: =IF(ISNUMBER(A64),(IF(ISNUMBER(VLOOKUP(A64,KEYWORDS,1,FALSE)),"C/PalabrasClaves","S/PalabrasClaves")),"") -> S/PalabrasClaves | N64: =IF(ISNUMBER(SEARCH("TREATMENT", B64)), "4) Nuevos tratamientos", "") | P64: 2012 Apr | R64: =LEFT('2012-2022'!$P64,4) -> 2012 | S64: Apr
A65: 22449515 | B65: Scrub typhus: pathophysiology, clinical manifestations and prognosis | C65: Rajapakse S, Rodrigo C, Fernando D. | D65: Asian Pac J Trop Med. 2012 Apr;5(4):261-4. doi: 10.1016/S1995-7645(12)60036-4. | E65: Rajapakse S | F65: Asian Pac J Trop Med | G65: 2012 | H65: 40996 | K65: 10.1016/S1995-7645(12)60036-4 | L65: =IF(ISNUMBER(VLOOKUP(A65,EXCL,1,FALSE)),"Excluido",IF(ISNUMBER(VLOOKUP(A65,POST,1,FALSE)),"PostAlerta",IF(ISNUMBER(VLOOKUP(A65,PRE,1,FALSE)),"PreAlerta",""))) -> Excluido | M65: =IF(ISNUMBER(A65),(IF(ISNUMBER(VLOOKUP(A65,KEYWORDS,1,FALSE)),"C/PalabrasClaves","S/PalabrasClaves")),"") -> S/PalabrasClaves | N65: =IF(ISNUMBER(SEARCH("TREATMENT", B65)), "4) Nuevos tratamientos", "") | P65: 2012 Apr | R65: =LEFT('2012-2022'!$P65,4) -> 2012 | S65: Apr
A66: 22469314 | B66: Rickettsia monacensis as cause of Mediterranean spotted fever-like illness, Italy | C66: Madeddu G, Mancini F, Caddeo A, Ciervo A, Babudieri S, Maida I, Fiori ML, Rezza G, Mura MS. | D66: Emerg Infect Dis. 2012 Apr;18(4):702-4. doi: 10.3201/eid1804.111583. | E66: Madeddu G | F66: Emerg Infect Dis | G66: 2012 | H66: 41003 | I66: PMC3309684 | K66: 10.3201/eid1804.111583 | L66: =IF(ISNUMBER(VLOOKUP(A66,EXCL,1,FALSE)),"Excluido",IF(ISNUMBER(VLOOKUP(A66,POST,1,FALSE)),"PostAlerta",IF(ISNUMBER(VLOOKUP(A66,PRE,1,FALSE)),"PreAlerta",""))) -> PreAlerta | M66: =IF(ISNUMBER(A66),(IF(ISNUMBER(VLOOKUP(A66,KEYWORDS,1,FALSE)),"C/PalabrasClaves","S/PalabrasClaves")),"") -> S/PalabrasClaves | N66: =IF(ISNUMBER(SEARCH("TREATMENT", B66)), "4) Nuevos tratamientos", "") | P66: 2012 Apr | R66: =LEFT('2012-2022'!$P66,4) -> 2012 | S66: Apr
A67: 22487426 | B67: Prevalence of Rickettsia spp., Anaplasma phagocytophilum, and Coxiella burnetii in adult Ixodes ricinus ticks from 29 study areas in central and southern Sweden | C67: Wallménius K, Pettersson JH, Jaenson TG, Nilsson K. | D67: Ticks Tick Borne Dis. 2012 Apr;3(2):100-6. doi: 10.1016/j.ttbdis.2011.11.003. Epub 2012 Jan 9. | E67: Wallménius K | F67: Ticks Tick Borne Dis | G67: 2012 | H67: 41010 | K67: 10.1016/j.ttbdis.2011.11.003 | L67: =IF(ISNUMBER(VLOOKUP(A67,EXCL,1,FALSE)),"Excluido",IF(ISNUMBER(VLOOKUP(A67,POST,1,FALSE)),"PostAlerta",IF(ISNUMBER(VLOOKUP(A67,PRE,1,FALSE)),"PreAlerta",""))) -> PreAlerta | M67: =IF(ISNUMBER(A67),(IF(ISNUMBER(VLOOKUP(A67,KEYWORDS,1,FALSE)),"C/PalabrasClaves","S/PalabrasClaves")),"") -> S/PalabrasClaves | N67: =IF(ISNUMBER(SEARCH("TREATMENT", B67)), "4) Nuevos tratamientos", "") | P67: 2012 Apr | R67: =LEFT('2012-2022'!$P67,4) -> 2012 | S67: Apr
A68: 22492134 | B68: Scrub typhus without eruption | C68: Yoshimoto T, Yoshimoto T. | D68: Am J Trop Med Hyg. 2012 Apr;86(4):559. doi: 10.4269/ajtmh.2012.11-0616. | E68: Yoshimoto T | F68: Am J Trop Med Hyg | G68: 2012 | H68: 41011 | I68: PMC3403754 | K68: 10.4269/ajtmh.2012.11-0616 | L68: =IF(ISNUMBER(VLOOKUP(A68,EXCL,1,FALSE)),"Excluido",IF(ISNUMBER(VLOOKUP(A68,POST,1,FALSE)),"PostAlerta",IF(ISNUMBER(VLOOKUP(A68,PRE,1,FALSE)),"PreAlerta",""))) -> PreAlerta | M68: =IF(ISNUMBER(A68),(IF(ISNUMBER(VLOOKUP(A68,KEYWORDS,1,FALSE)),"C/PalabrasClaves","S/PalabrasClaves")),"") -> S/PalabrasClaves | N68: =IF(ISNUMBER(SEARCH("TREATMENT", B68)), "4) Nuevos tratamientos", "") | P68: 2012 Apr | R68: =LEFT('2012-2022'!$P68,4) -> 2012 | S68: Apr
A69: 22492158 | B69: Detection of rickettsioses and Q fever in Sri Lanka | C69: Angelakis E, Munasinghe A, Yaddehige I, Liyanapathirana V, Thevanesam V, Bregliano A, Socolovschi C, Edouard S, Fournier PE, Raoult D, Parola P. | D69: Am J Trop Med Hyg. 2012 Apr;86(4):711-2. doi: 10.4269/ajtmh.2012.11-0424. | E69: Angelakis E | F69: Am J Trop Med Hyg | G69: 2012 | H69: 41011 | I69: PMC3403782 | K69: 10.4269/ajtmh.2012.11-0424 | L69: =IF(ISNUMBER(VLOOKUP(A69,EXCL,1,FALSE)),"Excluido",IF(ISNUMBER(VLOOKUP(A69,POST,1,FALSE)),"PostAlerta",IF(ISNUMBER(VLOOKUP(A69,PRE,1,FALSE)),"PreAlerta",""))) -> PreAlerta | M69: =IF(ISNUMBER(A69),(IF(ISNUMBER(VLOOKUP(A69,KEYWORDS,1,FALSE)),"C/PalabrasClaves","S/PalabrasClaves")),"") -> S/PalabrasClaves | N69: =IF(ISNUMBER(SEARCH("TREATMENT", B69)), "4) Nuevos tratamientos", "") | P69: 2012 Apr | R69: =LEFT('2012-2022'!$P69,4) -> 2012 | S69: Apr
A70: 22511280 | B70: [African tick bite fever--rickettsiosis after holiday in South Africa] | C70: Schleenvoigt BT, Keller P, Stallmach A, Pletz MW. | D70: Dtsch Med Wochenschr. 2012 Apr;137(17):891-3. doi: 10.1055/s-0032-1304902. Epub 2012 Apr 17. | E70: Schleenvoigt BT | F70: Dtsch Med Wochenschr | G70: 2012 | H70: 41018 | K70: 10.1055/s-0032-1304902 | L70: =IF(ISNUMBER(VLOOKUP(A70,EXCL,1,FALSE)),"Excluido",IF(ISNUMBER(VLOOKUP(A70,POST,1,FALSE)),"PostAlerta",IF(ISNUMBER(VLOOKUP(A70,PRE,1,FALSE)),"PreAlerta",""))) -> PreAlerta | M70: =IF(ISNUMBER(A70),(IF(ISNUMBER(VLOOKUP(A70,KEYWORDS,1,FALSE)),"C/PalabrasClaves","S/PalabrasClaves")),"") -> S/PalabrasClaves | N70: =IF(ISNUMBER(SEARCH("TREATMENT", B70)), "4) Nuevos tratamientos", "") | P70: 2012 Apr | R70: =LEFT('2012-2022'!$P70,4) -> 2012 | S70: Apr
A71: 22563611 | B71: Direct detection of Ehrlichia canis by PCR in the conjunctiva of a dog with bilateral anterior uveitis | C71: Walser-Reinhard L, Schaarschmidt-Kiener D, Forster JL, Matheis F, Spiess B. | D71: Schweiz Arch Tierheilkd. 2012 Apr;154(4):149-52. doi: 10.1024/0036-7281/a000318. | E71: Walser-Reinhard L | F71: Schweiz Arch Tierheilkd | G71: 2012 | H71: 41037 | K71: 10.1024/0036-7281/a000318 | L71: =IF(ISNUMBER(VLOOKUP(A71,EXCL,1,FALSE)),"Excluido",IF(ISNUMBER(VLOOKUP(A71,POST,1,FALSE)),"PostAlerta",IF(ISNUMBER(VLOOKUP(A71,PRE,1,FALSE)),"PreAlerta",""))) -> PreAlerta | M71: =IF(ISNUMBER(A71),(IF(ISNUMBER(VLOOKUP(A71,KEYWORDS,1,FALSE)),"C/PalabrasClaves","S/PalabrasClaves")),"") -> S/PalabrasClaves | N71: =IF(ISNUMBER(SEARCH("TREATMENT", B71)), "4) Nuevos tratamientos", "") | P71: 2012 Apr | R71: =LEFT('2012-2022'!$P71,4) -> 2012 | S71: Apr
A72: 22565079 | B72: Pediatric Scrub typhus in South Sikkim | C72: Gupta N, Mittal V, Gurung B, Sherpa U. | D72: Indian Pediatr. 2012 Apr;49(4):322-4. | E72: Gupta N | F72: Indian Pediatr | G72: 2012 | H72: 41038 | L72: =IF(ISNUMBER(VLOOKUP(A72,EXCL,1,FALSE)),"Excluido",IF(ISNUMBER(VLOOKUP(A72,POST,1,FALSE)),"PostAlerta",IF(ISNUMBER(VLOOKUP(A72,PRE,1,FALSE)),"PreAlerta",""))) -> PreAlerta | M72: =IF(ISNUMBER(A72),(IF(ISNUMBER(VLOOKUP(A72,KEYWORDS,1,FALSE)),"C/PalabrasClaves","S/PalabrasClaves")),"") -> S/PalabrasClaves | N72: =IF(ISNUMBER(SEARCH("TREATMENT", B72)), "4) Nuevos tratamientos", "") | P72: 2012 Apr | R72: =LEFT('2012-2022'!$P72,4) -> 2012 | S72: Apr
A73: 22566732 | B73: First case of scrub typhus with meningoencephalitis from Kerala: An emerging infectious threat | C73: Saifudheen K, Kumar KG, Jose J, Veena V, Gafoor VA. | D73: Ann Indian Acad Neurol. 2012 Apr;15(2):141-4. doi: 10.4103/0972-2327.95002. | E73: Saifudheen K | F73: Ann Indian Acad Neurol | G73: 2012 | H73: 41038 | I73: PMC3345595 | K73: 10.4103/0972-2327.95002 | L73: =IF(ISNUMBER(VLOOKUP(A73,EXCL,1,FALSE)),"Excluido",IF(ISNUMBER(VLOOKUP(A73,POST,1,FALSE)),"PostAlerta",IF(ISNUMBER(VLOOKUP(A73,PRE,1,FALSE)),"PreAlerta",""))) -> PreAlerta | M73: =IF(ISNUMBER(A73),(IF(ISNUMBER(VLOOKUP(A73,KEYWORDS,1,FALSE)),"C/PalabrasClaves","S/PalabrasClaves")),"") -> S/PalabrasClaves | N73: =IF(ISNUMBER(SEARCH("TREATMENT", B73)), "4) Nuevos tratamientos", "") | P73: 2012 Apr | R73: =LEFT('2012-2022'!$P73,4) -> 2012 | S73: Apr
A74: 22590684 | B74: Megalocytiviruses | C74: Kurita J, Nakajima K. | D74: Viruses. 2012 Apr;4(4):521-38. doi: 10.3390/v4040521. Epub 2012 Apr 10. | E74: Kurita J | F74: Viruses | G74: 2012 | H74: 41046 | I74: PMC3347321 | K74: 10.3390/v4040521 | L74: =IF(ISNUMBER(VLOOKUP(A74,EXCL,1,FALSE)),"Excluido",IF(ISNUMBER(VLOOKUP(A74,POST,1,FALSE)),"PostAlerta",IF(ISNUMBER(VLOOKUP(A74,PRE,1,FALSE)),"PreAlerta",""))) -> Excluido | M74: =IF(ISNUMBER(A74),(IF(ISNUMBER(VLOOKUP(A74,KEYWORDS,1,FALSE)),"C/PalabrasClaves","S/PalabrasClaves")),"") -> S/PalabrasClaves | N74: =IF(ISNUMBER(SEARCH("TREATMENT", B74)), "4) Nuevos tratamientos", "") | P74: 2012 Apr | R74: =LEFT('2012-2022'!$P74,4) -> 2012 | S74: Apr
A75: 22664504 | B75: Serological evidence of rickettsial infections in Delhi | C75: Mittal V, Gupta N, Bhattacharya D, Kumar K, Ichhpujani RL, Singh S, Chhabra M, Rana UV. | D75: Indian J Med Res. 2012 Apr;135(4):538-41. | E75: Mittal V | F75: Indian J Med Res | G75: 2012 | H75: 41066 | I75: PMC3385240 | L75: =IF(ISNUMBER(VLOOKUP(A75,EXCL,1,FALSE)),"Excluido",IF(ISNUMBER(VLOOKUP(A75,POST,1,FALSE)),"PostAlerta",IF(ISNUMBER(VLOOKUP(A75,PRE,1,FALSE)),"PreAlerta",""))) -> PreAlerta | M75: =IF(ISNUMBER(A75),(IF(ISNUMBER(VLOOKUP(A75,KEYWORDS,1,FALSE)),"C/PalabrasClaves","S/PalabrasClaves")),"") -> S/PalabrasClaves | N75: =IF(ISNUMBER(SEARCH("TREATMENT", B75)), "4) Nuevos tratamientos", "") | P75: 2012 Apr | R75: =LEFT('2012-2022'!$P75,4) -> 2012 | S75: Apr
A76: 22693777 | B76: Murine typhus: endemic Rickettsia in southwest Texas | C76: Liddell PW, Sparks MJ. | D76: Clin Lab Sci. 2012 Spring;25(2):81-7. | E76: Liddell PW | F76: Clin Lab Sci | G76: 2012 | H76: 41075 | L76: =IF(ISNUMBER(VLOOKUP(A76,EXCL,1,FALSE)),"Excluido",IF(ISNUMBER(VLOOKUP(A76,POST,1,FALSE)),"PostAlerta",IF(ISNUMBER(VLOOKUP(A76,PRE,1,FALSE)),"PreAlerta",""))) -> PreAlerta | M76: =IF(ISNUMBER(A76),(IF(ISNUMBER(VLOOKUP(A76,KEYWORDS,1,FALSE)),"C/PalabrasClaves","S/PalabrasClaves")),"") -> S/PalabrasClaves | N76: =IF(ISNUMBER(SEARCH("TREATMENT", B76)), "4) Nuevos tratamientos", "") | P76: 2012 Spring | R76: =LEFT('2012-2022'!$P76,4) -> 2012 | S76: Spring
A77: 22774502 | B77: [Natural focal tick-borne transmissive infections in the children of Perm Territory: differential diagnosis algorithm] | C77: Merzlova NB, Samarov MN. | D77: Med Parazitol (Mosk). 2012 Apr-Jun;(2):23-7. | E77: Merzlova NB | F77: Med Parazitol (Mosk) | G77: 2012 | H77: 41101 | L77: =IF(ISNUMBER(VLOOKUP(A77,EXCL,1,FALSE)),"Excluido",IF(ISNUMBER(VLOOKUP(A77,POST,1,FALSE)),"PostAlerta",IF(ISNUMBER(VLOOKUP(A77,PRE,1,FALSE)),"PreAlerta",""))) -> PreAlerta | M77: =IF(ISNUMBER(A77),(IF(ISNUMBER(VLOOKUP(A77,KEYWORDS,1,FALSE)),"C/PalabrasClaves","S/PalabrasClaves")),"") -> S/PalabrasClaves | N77: =IF(ISNUMBER(SEARCH("TREATMENT", B77)), "4) Nuevos tratamientos", "") | P77: 2012 Apr-Jun | R77: =LEFT('2012-2022'!$P77,4) -> 2012 | S77: Jun
A78: 22800633 | B78: [Analysis of epidemic features of scrub typhus between year 2006 and 2010 in Shandong province, China] | C78: Ding L, Li Z, Wang XJ, Ding SJ, Zhang M, Zhao ZT. | D78: Zhonghua Yu Fang Yi Xue Za Zhi. 2012 Apr;46(4):338-42. | E78: Ding L | F78: Zhonghua Yu Fang Yi Xue Za Zhi | G78: 2012 | H78: 41108 | L78: =IF(ISNUMBER(VLOOKUP(A78,EXCL,1,FALSE)),"Excluido",IF(ISNUMBER(VLOOKUP(A78,POST,1,FALSE)),"PostAlerta",IF(ISNUMBER(VLOOKUP(A78,PRE,1,FALSE)),"PreAlerta",""))) -> PreAlerta | M78: =IF(ISNUMBER(A78),(IF(ISNUMBER(VLOOKUP(A78,KEYWORDS,1,FALSE)),"C/PalabrasClaves","S/PalabrasClaves")),"") -> S/PalabrasClaves | N78: =IF(ISNUMBER(SEARCH("TREATMENT", B78)), "4) Nuevos tratamientos", "") | P78: 2012 Apr | R78: =LEFT('2012-2022'!$P78,4) -> 2012 | S78: Apr
A79: 22832744 | B79: In vitro cultivation of Anaplasma marginale and A. phagocytophilum in tick cell lines: a review | C79: Passos LM. | D79: Rev Bras Parasitol Vet. 2012 Apr-Jun;21(2):81-6. doi: 10.1590/s1984-29612012000200002. | E79: Passos LM | F79: Rev Bras Parasitol Vet | G79: 2012 | H79: 41117 | K79: 10.1590/s1984-29612012000200002 | L79: =IF(ISNUMBER(VLOOKUP(A79,EXCL,1,FALSE)),"Excluido",IF(ISNUMBER(VLOOKUP(A79,POST,1,FALSE)),"PostAlerta",IF(ISNUMBER(VLOOKUP(A79,PRE,1,FALSE)),"PreAlerta",""))) -> Excluido | M79: =IF(ISNUMBER(A79),(IF(ISNUMBER(VLOOKUP(A79,KEYWORDS,1,FALSE)),"C/PalabrasClaves","S/PalabrasClaves")),"") -> S/PalabrasClaves | N79: =IF(ISNUMBER(SEARCH("TREATMENT", B79)), "4) Nuevos tratamientos", "") | P79: 2012 Apr-Jun | R79: =LEFT('2012-2022'!$P79,4) -> 2012 | S79: Jun
A80: 22832750 | B80: Evaluating the effectiveness of an inactivated vaccine from Anaplasma marginale derived from tick cell culture | C80: Lasmar PV, Carvalho AÚ, Facury Filho EJ, Bastos CV, Ribeiro MF. | D80: Rev Bras Parasitol Vet. 2012 Apr-Jun;21(2):112-7. doi: 10.1590/s1984-29612012000200008. | E80: Lasmar PV | F80: Rev Bras Parasitol Vet | G80: 2012 | H80: 41117 | K80: 10.1590/s1984-29612012000200008 | L80: =IF(ISNUMBER(VLOOKUP(A80,EXCL,1,FALSE)),"Excluido",IF(ISNUMBER(VLOOKUP(A80,POST,1,FALSE)),"PostAlerta",IF(ISNUMBER(VLOOKUP(A80,PRE,1,FALSE)),"PreAlerta",""))) -> Excluido | M80: =IF(ISNUMBER(A80),(IF(ISNUMBER(VLOOKUP(A80,KEYWORDS,1,FALSE)),"C/PalabrasClaves","S/PalabrasClaves")),"") -> S/PalabrasClaves | N80: =IF(ISNUMBER(SEARCH("TREATMENT", B80)), "4) Nuevos tratamientos", "") | P80: 2012 Apr-Jun | R80: =LEFT('2012-2022'!$P80,4) -> 2012 | S80: Jun
A81: 24031883 | B81: Detection of Wolbachia (Alphaproteobacteria: rickettsiales) in three species of terrestrial isopods (crustacea: isopoda: oniscidea) in Brazil | C81: Zimmermann BL, Almerão MP, Bouchon D, Araujo PB. | D81: Braz J Microbiol. 2012 Apr;43(2):711-5. doi: 10.1590/S1517-83822012000200036. Epub 2012 Jun 1. | E81: Zimmermann BL | F81: Braz J Microbiol | G81: 2012 | H81: 41531 | I81: PMC3768838 | K81: 10.1590/S1517-83822012000200036 | L81: =IF(ISNUMBER(VLOOKUP(A81,EXCL,1,FALSE)),"Excluido",IF(ISNUMBER(VLOOKUP(A81,POST,1,FALSE)),"PostAlerta",IF(ISNUMBER(VLOOKUP(A81,PRE,1,FALSE)),"PreAlerta",""))) -> PreAlerta | M81: =IF(ISNUMBER(A81),(IF(ISNUMBER(VLOOKUP(A81,KEYWORDS,1,FALSE)),"C/PalabrasClaves","S/PalabrasClaves")),"") -> S/PalabrasClaves | N81: =IF(ISNUMBER(SEARCH("TREATMENT", B81)), "4) Nuevos tratamientos", "") | P81: 2012 Apr | R81: =LEFT('2012-2022'!$P81,4) -> 2012 | S81: Apr
A82: 22497736 | B82: The expression of one ankyrin pk2 allele of the WO prophage is correlated with the Wolbachia feminizing effect in isopods | C82: Pichon S, Bouchon D, Liu C, Chen L, Garrett RA, Grève P. | D82: BMC Microbiol. 2012 Apr 12;12:55. doi: 10.1186/1471-2180-12-55. | E82: Pichon S | F82: BMC Microbiol | G82: 2012 | H82: 41013 | I82: PMC3431249 | K82: 10.1186/1471-2180-12-55 | L82: =IF(ISNUMBER(VLOOKUP(A82,EXCL,1,FALSE)),"Excluido",IF(ISNUMBER(VLOOKUP(A82,POST,1,FALSE)),"PostAlerta",IF(ISNUMBER(VLOOKUP(A82,PRE,1,FALSE)),"PreAlerta",""))) -> PreAlerta | M82: =IF(ISNUMBER(A82),(IF(ISNUMBER(VLOOKUP(A82,KEYWORDS,1,FALSE)),"C/PalabrasClaves","S/PalabrasClaves")),"") -> S/PalabrasClaves | N82: =IF(ISNUMBER(SEARCH("TREATMENT", B82)), "4) Nuevos tratamientos", "") | P82: 2012 Apr 12 | R82: =LEFT('2012-2022'!$P82,4) -> 2012 | S82: Apr
A83: 22515314 | B83: Prevalence of Neoehrlichia mikurensis in ticks and rodents from North-west Europe | C83: Jahfari S, Fonville M, Hengeveld P, Reusken C, Scholte EJ, Takken W, Heyman P, Medlock JM, Heylen D, Kleve J, Sprong H. | D83: Parasit Vectors. 2012 Apr 19;5:74. doi: 10.1186/1756-3305-5-74. | E83: Jahfari S | F83: Parasit Vectors | G83: 2012 | H83: 41020 | I83: PMC3395572 | K83: 10.1186/1756-3305-5-74 | L83: =IF(ISNUMBER(VLOOKUP(A83,EXCL,1,FALSE)),"Excluido",IF(ISNUMBER(VLOOKUP(A83,POST,1,FALSE)),"PostAlerta",IF(ISNUMBER(VLOOKUP(A83,PRE,1,FALSE)),"PreAlerta",""))) -> PreAlerta | M83: =IF(ISNUMBER(A83),(IF(ISNUMBER(VLOOKUP(A83,KEYWORDS,1,FALSE)),"C/PalabrasClaves","S/PalabrasClaves")),"") -> S/PalabrasClaves | N83: =IF(ISNUMBER(SEARCH("TREATMENT", B83)), "4) Nuevos tratamientos", "") | P83: 2012 Apr 19 | R83: =LEFT('2012-2022'!$P83,4) -> 2012 | S83: Apr
A84: 22526723 | B84: Tick-borne fever caused by Anaplasma phagocytophilum in Germany: first laboratory confirmed case in a dairy cattle herd | C84: Nieder M, Silaghi C, Hamel D, Pfister K, Schmäschke R, Pfeffer M. | D84: Tierarztl Prax Ausg G Grosstiere Nutztiere. 2012 Apr 24;40(2):101-6. | E84: Nieder M | F84: Tierarztl Prax Ausg G Grosstiere Nutztiere | G84: 2012 | H84: 41024 | L84: =IF(ISNUMBER(VLOOKUP(A84,EXCL,1,FALSE)),"Excluido",IF(ISNUMBER(VLOOKUP(A84,POST,1,FALSE)),"PostAlerta",IF(ISNUMBER(VLOOKUP(A84,PRE,1,FALSE)),"PreAlerta",""))) -> PreAlerta | M84: =IF(ISNUMBER(A84),(IF(ISNUMBER(VLOOKUP(A84,KEYWORDS,1,FALSE)),"C/PalabrasClaves","S/PalabrasClaves")),"") -> S/PalabrasClaves | N84: =IF(ISNUMBER(SEARCH("TREATMENT", B84)), "4) Nuevos tratamientos", "") | P84: 2012 Apr 24 | R84: =LEFT('2012-2022'!$P84,4) -> 2012 | S84: Apr
A85: 22531297 | B85: Population genetic structure of Aedes polynesiensis in the Society Islands of French Polynesia: implications for control using a Wolbachia-based autocidal strategy | C85: Brelsfoard CL, Dobson SL. | D85: Parasit Vectors. 2012 Apr 24;5:80. doi: 10.1186/1756-3305-5-80. | E85: Brelsfoard CL | F85: Parasit Vectors | G85: 2012 | H85: 41025 | I85: PMC3349601 | K85: 10.1186/1756-3305-5-80 | L85: =IF(ISNUMBER(VLOOKUP(A85,EXCL,1,FALSE)),"Excluido",IF(ISNUMBER(VLOOKUP(A85,POST,1,FALSE)),"PostAlerta",IF(ISNUMBER(VLOOKUP(A85,PRE,1,FALSE)),"PreAlerta",""))) -> PreAlerta | M85: =IF(ISNUMBER(A85),(IF(ISNUMBER(VLOOKUP(A85,KEYWORDS,1,FALSE)),"C/PalabrasClaves","S/PalabrasClaves")),"") -> S/PalabrasClaves | N85: =IF(ISNUMBER(SEARCH("TREATMENT", B85)), "4) Nuevos tratamientos", "") | P85: 2012 Apr 24 | R85: =LEFT('2012-2022'!$P85,4) -> 2012 | S85: Apr
A86: 22534530 | B86: Vector control: The last bite | C86: Gravitz L. | D86: Nature. 2012 Apr 25;484(7395):S26-7. doi: 10.1038/484S26a. | E86: Gravitz L | F86: Nature | G86: 2012 | H86: 41026 | K86: 10.1038/484S26a | L86: =IF(ISNUMBER(VLOOKUP(A86,EXCL,1,FALSE)),"Excluido",IF(ISNUMBER(VLOOKUP(A86,POST,1,FALSE)),"PostAlerta",IF(ISNUMBER(VLOOKUP(A86,PRE,1,FALSE)),"PreAlerta",""))) -> PreAlerta | M86: =IF(ISNUMBER(A86),(IF(ISNUMBER(VLOOKUP(A86,KEYWORDS,1,FALSE)),"C/PalabrasClaves","S/PalabrasClaves")),"") -> S/PalabrasClaves | N86: =IF(ISNUMBER(SEARCH("TREATMENT", B86)), "4) Nuevos tratamientos", "") | P86: 2012 Apr 25 | R86: =LEFT('2012-2022'!$P86,4) -> 2012 | S86: Apr
A87: 22214272 | B87: A new Rickettsia species found in fleas collected from human dwellings and from domestic cats and dogs in Senegal | C87: Roucher C, Mediannikov O, Diatta G, Trape JF, Raoult D. | D87: Vector Borne Zoonotic Dis. 2012 May;12(5):360-5. doi: 10.1089/vbz.2011.0734. Epub 2012 Jan 3. | E87: Roucher C | F87: Vector Borne Zoonotic Dis | G87: 2012 | H87: 40913 | K87: 10.1089/vbz.2011.0734 | L87: =IF(ISNUMBER(VLOOKUP(A87,EXCL,1,FALSE)),"Excluido",IF(ISNUMBER(VLOOKUP(A87,POST,1,FALSE)),"PostAlerta",IF(ISNUMBER(VLOOKUP(A87,PRE,1,FALSE)),"PreAlerta",""))) -> PreAlerta | M87: =IF(ISNUMBER(A87),(IF(ISNUMBER(VLOOKUP(A87,KEYWORDS,1,FALSE)),"C/PalabrasClaves","S/PalabrasClaves")),"") -> S/PalabrasClaves | N87: =IF(ISNUMBER(SEARCH("TREATMENT", B87)), "4) Nuevos tratamientos", "") | P87: 2012 May | R87: =LEFT('2012-2022'!$P87,4) -> 2012 | S87: May
A88: 22217182 | B88: Molecular detection of spotted fever group rickettsiae associated with ixodid ticks in Egypt | C88: Abdel-Shafy S, Allam NA, Mediannikov O, Parola P, Raoult D. | D88: Vector Borne Zoonotic Dis. 2012 May;12(5):346-59. doi: 10.1089/vbz.2010.0241. Epub 2012 Jan 4. | E88: Abdel-Shafy S | F88: Vector Borne Zoonotic Dis | G88: 2012 | H88: 40914 | K88: 10.1089/vbz.2010.0241 | L88: =IF(ISNUMBER(VLOOKUP(A88,EXCL,1,FALSE)),"Excluido",IF(ISNUMBER(VLOOKUP(A88,POST,1,FALSE)),"PostAlerta",IF(ISNUMBER(VLOOKUP(A88,PRE,1,FALSE)),"PreAlerta",""))) -> PreAlerta | M88: =IF(ISNUMBER(A88),(IF(ISNUMBER(VLOOKUP(A88,KEYWORDS,1,FALSE)),"C/PalabrasClaves","S/PalabrasClaves")),"") -> S/PalabrasClaves | N88: =IF(ISNUMBER(SEARCH("TREATMENT", B88)), "4) Nuevos tratamientos", "") | P88: 2012 May | R88: =LEFT('2012-2022'!$P88,4) -> 2012 | S88: May
A89: 22226382 | B89: Adaptive immunity to Anaplasma pathogens and immune dysregulation: implications for bacterial persistence | C89: Brown WC. | D89: Comp Immunol Microbiol Infect Dis. 2012 May;35(3):241-52. doi: 10.1016/j.cimid.2011.12.002. Epub 2012 Jan 4. | E89: Brown WC | F89: Comp Immunol Microbiol Infect Dis | G89: 2012 | H89: 40918 | I89: PMC3327808 | J89: NIHMS348171 | K89: 10.1016/j.cimid.2011.12.002 | L89: =IF(ISNUMBER(VLOOKUP(A89,EXCL,1,FALSE)),"Excluido",IF(ISNUMBER(VLOOKUP(A89,POST,1,FALSE)),"PostAlerta",IF(ISNUMBER(VLOOKUP(A89,PRE,1,FALSE)),"PreAlerta",""))) -> Excluido | M89: =IF(ISNUMBER(A89),(IF(ISNUMBER(VLOOKUP(A89,KEYWORDS,1,FALSE)),"C/PalabrasClaves","S/PalabrasClaves")),"") -> S/PalabrasClaves | N89: =IF(ISNUMBER(SEARCH("TREATMENT", B89)), "4) Nuevos tratamientos", "") | P89: 2012 May | R89: =LEFT('2012-2022'!$P89,4) -> 2012 | S89: May
A90: 22244519 | B90: Prevalence of livestock diseases and their impact on livelihoods in Central Equatoria State, Southern Sudan | C90: Malak AK, Mpoke L, Banak J, Muriuki S, Skilton RA, Odongo D, Sunter J, Kiara H. | D90: Prev Vet Med. 2012 May 1;104(3-4):216-23. doi: 10.1016/j.prevetmed.2011.12.001. Epub 2012 Jan 13. | E90: Malak AK | F90: Prev Vet Med | G90: 2012 | H90: 40925 | K90: 10.1016/j.prevetmed.2011.12.001 | L90: =IF(ISNUMBER(VLOOKUP(A90,EXCL,1,FALSE)),"Excluido",IF(ISNUMBER(VLOOKUP(A90,POST,1,FALSE)),"PostAlerta",IF(ISNUMBER(VLOOKUP(A90,PRE,1,FALSE)),"PreAlerta",""))) -> PreAlerta | M90: =IF(ISNUMBER(A90),(IF(ISNUMBER(VLOOKUP(A90,KEYWORDS,1,FALSE)),"C/PalabrasClaves","S/PalabrasClaves")),"") -> S/PalabrasClaves | N90: =IF(ISNUMBER(SEARCH("TREATMENT", B90)), "4) Nuevos tratamientos", "") | P90: 2012 May 1 | R90: =LEFT('2012-2022'!$P90,4) -> 2012 | S90: May
A91: 22349945 | B91: Capybaras and ticks in the urban areas of Uberlândia, Minas Gerais, Brazil: ecological aspects for the epidemiology of tick-borne diseases | C91: Queirogas VL, Del Claro K, Nascimento AR, Szabó MP. | D91: Exp Appl Acarol. 2012 May;57(1):75-82. doi: 10.1007/s10493-012-9533-1. Epub 2012 Feb 16. | E91: Queirogas VL | F91: Exp Appl Acarol | G91: 2012 | H91: 40961 | K91: 10.1007/s10493-012-9533-1 | L91: =IF(ISNUMBER(VLOOKUP(A91,EXCL,1,FALSE)),"Excluido",IF(ISNUMBER(VLOOKUP(A91,POST,1,FALSE)),"PostAlerta",IF(ISNUMBER(VLOOKUP(A91,PRE,1,FALSE)),"PreAlerta",""))) -> PreAlerta | M91: =IF(ISNUMBER(A91),(IF(ISNUMBER(VLOOKUP(A91,KEYWORDS,1,FALSE)),"C/PalabrasClaves","S/PalabrasClaves")),"") -> S/PalabrasClaves | N91: =IF(ISNUMBER(SEARCH("TREATMENT", B91)), "4) Nuevos tratamientos", "") | P91: 2012 May | R91: =LEFT('2012-2022'!$P91,4) -> 2012 | S91: May
A92: 22389475 | B92: Postgenomic analyses reveal development of infectious Anaplasma phagocytophilum during transmission from ticks to mice | C92: Mastronunzio JE, Kurscheid S, Fikrig E. | D92: J Bacteriol. 2012 May;194(9):2238-47. doi: 10.1128/JB.06791-11. Epub 2012 Mar 2. | E92: Mastronunzio JE | F92: J Bacteriol | G92: 2012 | H92: 40974 | I92: PMC3347074 | K92: 10.1128/JB.06791-11 | L92: =IF(ISNUMBER(VLOOKUP(A92,EXCL,1,FALSE)),"Excluido",IF(ISNUMBER(VLOOKUP(A92,POST,1,FALSE)),"PostAlerta",IF(ISNUMBER(VLOOKUP(A92,PRE,1,FALSE)),"PreAlerta",""))) -> PreAlerta | M92: =IF(ISNUMBER(A92),(IF(ISNUMBER(VLOOKUP(A92,KEYWORDS,1,FALSE)),"C/PalabrasClaves","S/PalabrasClaves")),"") -> S/PalabrasClaves | N92: =IF(ISNUMBER(SEARCH("TREATMENT", B92)), "4) Nuevos tratamientos", "") | P92: 2012 May | R92: =LEFT('2012-2022'!$P92,4) -> 2012 | S92: May
A93: 22392926 | B93: Susceptibility of inbred mice to Rickettsia parkeri | C93: Grasperge BJ, Reif KE, Morgan TD, Sunyakumthorn P, Bynog J, Paddock CD, Macaluso KR. | D93: Infect Immun. 2012 May;80(5):1846-52. doi: 10.1128/IAI.00109-12. Epub 2012 Mar 5. | E93: Grasperge BJ | F93: Infect Immun | G93: 2012 | H93: 40975 | I93: PMC3347444 | K93: 10.1128/IAI.00109-12 | L93: =IF(ISNUMBER(VLOOKUP(A93,EXCL,1,FALSE)),"Excluido",IF(ISNUMBER(VLOOKUP(A93,POST,1,FALSE)),"PostAlerta",IF(ISNUMBER(VLOOKUP(A93,PRE,1,FALSE)),"PreAlerta",""))) -> PreAlerta | M93: =IF(ISNUMBER(A93),(IF(ISNUMBER(VLOOKUP(A93,KEYWORDS,1,FALSE)),"C/PalabrasClaves","S/PalabrasClaves")),"") -> S/PalabrasClaves | N93: =IF(ISNUMBER(SEARCH("TREATMENT", B93)), "4) Nuevos tratamientos", "") | P93: 2012 May | R93: =LEFT('2012-2022'!$P93,4) -> 2012 | S93: May
A94: 22407681 | B94: Role of the lizard Teira dugesii as a potential host for Ixodes ricinus tick-borne pathogens | C94: De Sousa R, Lopes de Carvalho I, Santos AS, Bernardes C, Milhano N, Jesus J, Menezes D, Núncio MS. | D94: Appl Environ Microbiol. 2012 May;78(10):3767-9. doi: 10.1128/AEM.07945-11. Epub 2012 Mar 9. | E94: De Sousa R | F94: Appl Environ Microbiol | G94: 2012 | H94: 40981 | I94: PMC3346372 | K94: 10.1128/AEM.07945-11 | L94: =IF(ISNUMBER(VLOOKUP(A94,EXCL,1,FALSE)),"Excluido",IF(ISNUMBER(VLOOKUP(A94,POST,1,FALSE)),"PostAlerta",IF(ISNUMBER(VLOOKUP(A94,PRE,1,FALSE)),"PreAlerta",""))) -> PreAlerta | M94: =IF(ISNUMBER(A94),(IF(ISNUMBER(VLOOKUP(A94,KEYWORDS,1,FALSE)),"C/PalabrasClaves","S/PalabrasClaves")),"") -> S/PalabrasClaves | N94: =IF(ISNUMBER(SEARCH("TREATMENT", B94)), "4) Nuevos tratamientos", "") | P94: 2012 May | R94: =LEFT('2012-2022'!$P94,4) -> 2012 | S94: May
A95: 22433115 | B95: Chikungunya virus impacts the diversity of symbiotic bacteria in mosquito vector | C95: Zouache K, Michelland RJ, Failloux AB, Grundmann GL, Mavingui P. | D95: Mol Ecol. 2012 May;21(9):2297-309. doi: 10.1111/j.1365-294X.2012.05526.x. Epub 2012 Mar 20. | E95: Zouache K | F95: Mol Ecol | G95: 2012 | H95: 40990 | K95: 10.1111/j.1365-294X.2012.05526.x | L95: =IF(ISNUMBER(VLOOKUP(A95,EXCL,1,FALSE)),"Excluido",IF(ISNUMBER(VLOOKUP(A95,POST,1,FALSE)),"PostAlerta",IF(ISNUMBER(VLOOKUP(A95,PRE,1,FALSE)),"PreAlerta",""))) -> PreAlerta | M95: =IF(ISNUMBER(A95),(IF(ISNUMBER(VLOOKUP(A95,KEYWORDS,1,FALSE)),"C/PalabrasClaves","S/PalabrasClaves")),"") -> S/PalabrasClaves | N95: =IF(ISNUMBER(SEARCH("TREATMENT", B95)), "4) Nuevos tratamientos", "") | P95: 2012 May | R95: =LEFT('2012-2022'!$P95,4) -> 2012 | S95: May
A96: 22493192 | B96: Sequence and annotation of Rickettsia sibirica sibirica genome | C96: Sentausa E, El Karkouri K, Robert C, Raoult D, Fournier PE. | D96: J Bacteriol. 2012 May;194(9):2377. doi: 10.1128/JB.00150-12. | E96: Sentausa E | F96: J Bacteriol | G96: 2012 | H96: 41011 | I96: PMC3347044 | K96: 10.1128/JB.00150-12 | L96: =IF(ISNUMBER(VLOOKUP(A96,EXCL,1,FALSE)),"Excluido",IF(ISNUMBER(VLOOKUP(A96,POST,1,FALSE)),"PostAlerta",IF(ISNUMBER(VLOOKUP(A96,PRE,1,FALSE)),"PreAlerta",""))) -> PreAlerta | M96: =IF(ISNUMBER(A96),(IF(ISNUMBER(VLOOKUP(A96,KEYWORDS,1,FALSE)),"C/PalabrasClaves","S/PalabrasClaves")),"") -> S/PalabrasClaves | N96: =IF(ISNUMBER(SEARCH("TREATMENT", B96)), "4) Nuevos tratamientos", "") | P96: 2012 May | R96: =LEFT('2012-2022'!$P96,4) -> 2012 | S96: May
A97: 22493199 | B97: Genome sequence of "Rickettsia sibirica subsp. mongolitimonae" | C97: Sentausa E, El Karkouri K, Robert C, Raoult D, Fournier PE. | D97: J Bacteriol. 2012 May;194(9):2389-90. doi: 10.1128/JB.00239-12. | E97: Sentausa E | F97: J Bacteriol | G97: 2012 | H97: 41011 | I97: PMC3347047 | K97: 10.1128/JB.00239-12 | L97: =IF(ISNUMBER(VLOOKUP(A97,EXCL,1,FALSE)),"Excluido",IF(ISNUMBER(VLOOKUP(A97,POST,1,FALSE)),"PostAlerta",IF(ISNUMBER(VLOOKUP(A97,PRE,1,FALSE)),"PreAlerta",""))) -> PreAlerta | M97: =IF(ISNUMBER(A97),(IF(ISNUMBER(VLOOKUP(A97,KEYWORDS,1,FALSE)),"C/PalabrasClaves","S/PalabrasClaves")),"") -> S/PalabrasClaves | N97: =IF(ISNUMBER(SEARCH("TREATMENT", B97)), "4) Nuevos tratamientos", "") | P97: 2012 May | R97: =LEFT('2012-2022'!$P97,4) -> 2012 | S97: May
A98: 22516455 | B98: Unsuspected rickettsioses among patients with acute febrile illness, Sri Lanka, 2007 | C98: Reller ME, Bodinayake C, Nagahawatte A, Devasiri V, Kodikara-Arachichi W, Strouse JJ, Flom JE, Østbye T, Woods CW, Dumler JS. | D98: Emerg Infect Dis. 2012 May;18(5):825-9. doi: 10.3201/eid1805.111563. | E98: Reller ME | F98: Emerg Infect Dis | G98: 2012 | H98: 41020 | I98: PMC3358078 | K98: 10.3201/eid1805.111563 | L98: =IF(ISNUMBER(VLOOKUP(A98,EXCL,1,FALSE)),"Excluido",IF(ISNUMBER(VLOOKUP(A98,POST,1,FALSE)),"PostAlerta",IF(ISNUMBER(VLOOKUP(A98,PRE,1,FALSE)),"PreAlerta",""))) -> PreAlerta | M98: =IF(ISNUMBER(A98),(IF(ISNUMBER(VLOOKUP(A98,KEYWORDS,1,FALSE)),"C/PalabrasClaves","S/PalabrasClaves")),"") -> S/PalabrasClaves | N98: =IF(ISNUMBER(SEARCH("TREATMENT", B98)), "4) Nuevos tratamientos", "") | P98: 2012 May | R98: =LEFT('2012-2022'!$P98,4) -> 2012 | S98: May
A99: 22532262 | B99: [Vacation and tropical dermatoses] | C99: Fischer M, Reinel D. | D99: Hautarzt. 2012 May;63(5):396-403. doi: 10.1007/s00105-011-2258-y. | E99: Fischer M | F99: Hautarzt | G99: 2012 | H99: 41025 | K99: 10.1007/s00105-011-2258-y | L99: =IF(ISNUMBER(VLOOKUP(A99,EXCL,1,FALSE)),"Excluido",IF(ISNUMBER(VLOOKUP(A99,POST,1,FALSE)),"PostAlerta",IF(ISNUMBER(VLOOKUP(A99,PRE,1,FALSE)),"PreAlerta",""))) -> PreAlerta | M99: =IF(ISNUMBER(A99),(IF(ISNUMBER(VLOOKUP(A99,KEYWORDS,1,FALSE)),"C/PalabrasClaves","S/PalabrasClaves")),"") -> S/PalabrasClaves | N99: =IF(ISNUMBER(SEARCH("TREATMENT", B99)), "4) Nuevos tratamientos", "") | P99: 2012 May | R99: =LEFT('2012-2022'!$P99,4) -> 2012 | S99: May
A100: 22535934 | B100: Genomic comparison of Rickettsia helvetica and other Rickettsia species | C100: Dong X, El Karkouri K, Robert C, Gavory F, Raoult D, Fournier PE. | D100: J Bacteriol. 2012 May;194(10):2751. doi: 10.1128/JB.00299-12. | E100: Dong X | F100: J Bacteriol | G100: 2012 | H100: 41026 | I100: PMC3347184 | K100: 10.1128/JB.00299-12 | L100: =IF(ISNUMBER(VLOOKUP(A100,EXCL,1,FALSE)),"Excluido",IF(ISNUMBER(VLOOKUP(A100,POST,1,FALSE)),"PostAlerta",IF(ISNUMBER(VLOOKUP(A100,PRE,1,FALSE)),"PreAlerta",""))) -> PreAlerta | M100: =IF(ISNUMBER(A100),(IF(ISNUMBER(VLOOKUP(A100,KEYWORDS,1,FALSE)),"C/PalabrasClaves","S/PalabrasClaves")),"") -> S/PalabrasClaves | N100: =IF(ISNUMBER(SEARCH("TREATMENT", B100)), "4) Nuevos tratamientos", "") | P100: 2012 May | R100: =LEFT('2012-2022'!$P100,4) -> 2012 | S100: May
...

Sheet 2012-2017
A1: PMID | B1: Title | C1: Authors | D1: Citation | E1: First Author | F1: Journal/Book | G1: Publication Year | H1: Create Date | I1: PMCID | J1: NIHMS ID | K1: DOI
A2: 26467958 | B2: Modification of Insect and Arachnid Behaviours by Vertically Transmitted Endosymbionts: Infections as Drivers of Behavioural Change and Evolutionary Novelty | C2: Goodacre SL, Martin OY. | D2: Insects. 2012 Feb 29;3(1):246-61. doi: 10.3390/insects3010246. | E2: Goodacre SL | F2: Insects | G2: 2012 | H2: 42293 | I2: PMC4553626 | K2: 10.3390/insects3010246
A3: 21668575 | B3: Histopathological diagnosis of Japanese spotted fever using formalin-fixed, paraffin-embedded skin biopsy specimens: usefulness of immunohistochemistry and real-time PCR analysis | C3: Tamakuma K, Mizutani Y, Ito M, Shiogama K, Inada K, Miyamoto K, Utsunomiya H, Mahara F, Tsutsumi Y. | D3: Clin Microbiol Infect. 2012 Mar;18(3):260-7. doi: 10.1111/j.1469-0691.2011.03569.x. Epub 2011 Jun 10. | E3: Tamakuma K | F3: Clin Microbiol Infect | G3: 2012 | H3: 40709 | K3: 10.1111/j.1469-0691.2011.03569.x
A4: 21781141 | B4: Expression of heat shock proteins and subolesin affects stress responses, Anaplasma phagocytophilum infection and questing behaviour in the tick, Ixodes scapularis | C4: Busby AT, Ayllón N, Kocan KM, Blouin EF, de la Fuente G, Galindo RC, Villar M, de la Fuente J. | D4: Med Vet Entomol. 2012 Mar;26(1):92-102. doi: 10.1111/j.1365-2915.2011.00973.x. Epub 2011 Jul 22. | E4: Busby AT | F4: Med Vet Entomol | G4: 2012 | H4: 40750 | K4: 10.1111/j.1365-2915.2011.00973.x
A5: 21785920 | B5: Diplorickettsia massiliensis as a human pathogen | C5: Subramanian G, Mediannikov O, Angelakis E, Socolovschi C, Kaplanski G, Martzolff L, Raoult D. | D5: Eur J Clin Microbiol Infect Dis. 2012 Mar;31(3):365-9. doi: 10.1007/s10096-011-1318-7. Epub 2011 Jul 22. | E5: Subramanian G | F5: Eur J Clin Microbiol Infect Dis | G5: 2012 | H5: 40750 | K5: 10.1007/s10096-011-1318-7
A6: 21842137 | B6: Correlations among Anaplasma marginale parasitemia and markers of oxidative stress in crossbred calves | C6: De UK, Dey S, Banerjee PS, Sahoo M. | D6: Trop Anim Health Prod. 2012 Mar;44(3):385-8. doi: 10.1007/s11250-011-9938-6. Epub 2011 Aug 13. | E6: De UK | F6: Trop Anim Health Prod | G6: 2012 | H6: 40771 | K6: 10.1007/s11250-011-9938-6
A7: 21934703 | B7: Occasional males in parthenogenetic populations of Asobara japonica (Hymenoptera: Braconidae): low Wolbachia titer or incomplete coadaptation? | C7: Reumer BM, van Alphen JJ, Kraaijeveld K. | D7: Heredity (Edinb). 2012 Mar;108(3):341-6. doi: 10.1038/hdy.2011.82. Epub 2011 Sep 21. | E7: Reumer BM | F7: Heredity (Edinb) | G7: 2012 | H7: 40808 | I7: PMC3282404 | K7: 10.1038/hdy.2011.82
A8: 21938022 | B8: Unveiling in situ interactions between marine protists and bacteria through single cell sequencing | C8: Martinez-Garcia M, Brazel D, Poulton NJ, Swan BK, Gomez ML, Masland D, Sieracki ME, Stepanauskas R. | D8: ISME J. 2012 Mar;6(3):703-7. doi: 10.1038/ismej.2011.126. Epub 2011 Sep 22. | E8: Martinez-Garcia M | F8: ISME J | G8: 2012 | H8: 40809 | I8: PMC3280149 | K8: 10.1038/ismej.2011.126
A9: 22022815 | B9: Detection of Rickettsia parkeri and Candidatus Rickettsia andeanae in Amblyomma maculatum Gulf Coast ticks collected from humans in the United States | C9: Jiang J, Stromdahl EY, Richards AL. | D9: Vector Borne Zoonotic Dis. 2012 Mar;12(3):175-82. doi: 10.1089/vbz.2011.0614. Epub 2011 Oct 24. | E9: Jiang J | F9: Vector Borne Zoonotic Dis | G9: 2012 | H9: 40842 | K9: 10.1089/vbz.2011.0614
A10: 22076027 | B10: Cross-effects of nickel contamination and parasitism on zebra mussel physiology | C10: Minguez L, Boiché A, Sroda S, Mastitsky S, Brulé N, Bouquerel J, Giambérini L. | D10: Ecotoxicology. 2012 Mar;21(2):538-47. doi: 10.1007/s10646-011-0814-y. Epub 2011 Nov 12. | E10: Minguez L | F10: Ecotoxicology | G10: 2012 | H10: 40862 | K10: 10.1007/s10646-011-0814-y
A11: 22159737 | B11: Polyclonal antibody against conserved sequences of mce1A protein blocks MTB infection in macrophages | C11: Sivagnanam S, Namasivayam N, Chellam R. | D11: Appl Microbiol Biotechnol. 2012 Mar;93(6):2463-73. doi: 10.1007/s00253-011-3754-9. Epub 2011 Dec 13. | E11: Sivagnanam S | F11: Appl Microbiol Biotechnol | G11: 2012 | H11: 40891 | K11: 10.1007/s00253-011-3754-9
A12: 22172602 | B12: Infections with Wolbachia and Spiroplasma in the Scathophagidae and other Muscoidea | C12: Martin OY, Gubler A, Wimmer C, Germann C, Bernasconi MV. | D12: Infect Genet Evol. 2012 Mar;12(2):315-23. doi: 10.1016/j.meegid.2011.11.012. Epub 2011 Dec 8. | E12: Martin OY | F12: Infect Genet Evol | G12: 2012 | H12: 40894 | K12: 10.1016/j.meegid.2011.11.012
A13: 22205824 | B13: "Candidatus Neoehrlichia mikurensis," Anaplasma phagocytophilum, and lyme disease spirochetes in questing european vector ticks and in feeding ticks removed from people | C13: Richter D, Matuschka FR. | D13: J Clin Microbiol. 2012 Mar;50(3):943-7. doi: 10.1128/JCM.05802-11. Epub 2012 Jan 11. | E13: Richter D | F13: J Clin Microbiol | G13: 2012 | H13: 40907 | I13: PMC3295140 | K13: 10.1128/JCM.05802-11
A14: 22210220 | B14: Wolbachia strain wAlbB enhances infection by the rodent malaria parasite Plasmodium berghei in Anopheles gambiae mosquitoes | C14: Hughes GL, Vega-Rodriguez J, Xue P, Rasgon JL. | D14: Appl Environ Microbiol. 2012 Mar;78(5):1491-5. doi: 10.1128/AEM.06751-11. Epub 2011 Dec 30. | E14: Hughes GL | F14: Appl Environ Microbiol | G14: 2012 | H14: 40911 | I14: PMC3294472 | K14: 10.1128/AEM.06751-11
A15: 22214329 | B15: Wolbachia and its implications for the immunopathology of filariasis | C15: Genchi C, Kramer LH, Sassera D, Bandi C. | D15: Endocr Metab Immune Disord Drug Targets. 2012 Mar;12(1):53-6. doi: 10.2174/187153012799279108. | E15: Genchi C | F15: Endocr Metab Immune Disord Drug Targets | G15: 2012 | H15: 40913 | K15: 10.2174/187153012799279108
A16: 22219313 | B16: Prospective evaluation of commercial antibody-based rapid tests in combination with a loop-mediated isothermal amplification PCR assay for detection of Orientia tsutsugamushi during the acute phase of scrub typhus infection | C16: Blacksell SD, Paris DH, Chierakul W, Wuthiekanun V, Teeratakul A, Kantipong P, Day NP. | D16: Clin Vaccine Immunol. 2012 Mar;19(3):391-5. doi: 10.1128/CVI.05478-11. Epub 2012 Jan 4. | E16: Blacksell SD | F16: Clin Vaccine Immunol | G16: 2012 | H16: 40914 | I16: PMC3294598 | K16: 10.1128/CVI.05478-11
A17: 22222114 | B17: Rickettsiae in arthropods collected from the North African Hedgehog (Atelerix algirus) and the desert hedgehog (Paraechinus aethiopicus) in Algeria | C17: Khaldi M, Socolovschi C, Benyettou M, Barech G, Biche M, Kernif T, Raoult D, Parola P. | D17: Comp Immunol Microbiol Infect Dis. 2012 Mar;35(2):117-22. doi: 10.1016/j.cimid.2011.11.007. Epub 2012 Jan 4. | E17: Khaldi M | F17: Comp Immunol Microbiol Infect Dis | G17: 2012 | H17: 40915 | K17: 10.1016/j.cimid.2011.11.007
A18: 22257655 | B18: A case of rickettsialpox in Northern Europe | C18: Renvoisé A, van't Wout JW, van der Schroeff JG, Beersma MF, Raoult D. | D18: Int J Infect Dis. 2012 Mar;16(3):e221-2. doi: 10.1016/j.ijid.2011.11.009. Epub 2012 Jan 17. | E18: Renvoisé A | F18: Int J Infect Dis | G18: 2012 | H18: 40928 | K18: 10.1016/j.ijid.2011.11.009
A19: 22266203 | B19: Presence and distribution of the endosymbiont Wolbachia among Solenopsis spp. (Hymenoptera: Formicidae) from Brazil and its evolutionary history | C19: Martins C, Souza RF, Bueno OC. | D19: J Invertebr Pathol. 2012 Mar;109(3):287-96. doi: 10.1016/j.jip.2012.01.001. Epub 2012 Jan 12. | E19: Martins C | F19: J Invertebr Pathol | G19: 2012 | H19: 40932 | K19: 10.1016/j.jip.2012.01.001
A20: 22268975 | B20: Integration of molecular, ecological, morphological and endosymbiont data for species delimitation within the Pnigalio soemius complex (Hymenoptera: Eulophidae) | C20: Gebiola M, Gómez-Zurita J, Monti MM, Navone P, Bernardo U. | D20: Mol Ecol. 2012 Mar;21(5):1190-208. doi: 10.1111/j.1365-294X.2011.05428.x. Epub 2012 Jan 23. | E20: Gebiola M | F20: Mol Ecol | G20: 2012 | H20: 40933 | K20: 10.1111/j.1365-294X.2011.05428.x
A21: 22277830 | B21: New Rickettsia sp. in tsetse flies from Senegal | C21: Mediannikov O, Audoly G, Diatta G, Trape JF, Raoult D. | D21: Comp Immunol Microbiol Infect Dis. 2012 Mar;35(2):145-50. doi: 10.1016/j.cimid.2011.12.011. Epub 2012 Jan 23. | E21: Mediannikov O | F21: Comp Immunol Microbiol Infect Dis | G21: 2012 | H21: 40935 | K21: 10.1016/j.cimid.2011.12.011
A22: 22282331 | B22: Tetracyclines and pain | C22: Bastos LF, de Oliveira AC, Watkins LR, Moraes MF, Coelho MM. | D22: Naunyn Schmiedebergs Arch Pharmacol. 2012 Mar;385(3):225-41. doi: 10.1007/s00210-012-0727-1. Epub 2012 Jan 27. | E22: Bastos LF | F22: Naunyn Schmiedebergs Arch Pharmacol | G22: 2012 | H22: 40936 | K22: 10.1007/s00210-012-0727-1
A23: 22293464 | B23: Diversity and phylogenetic analysis of endosymbiotic bacteria from field caught Bemisia tabaci from different locations of North India based on 16S rDNA library screening | C23: Singh ST, Priya NG, Kumar J, Rana VS, Ellango R, Joshi A, Priyadarshini G, Asokan R, Rajagopal R. | D23: Infect Genet Evol. 2012 Mar;12(2):411-9. doi: 10.1016/j.meegid.2012.01.015. Epub 2012 Jan 24. | E23: Singh ST | F23: Infect Genet Evol | G23: 2012 | H23: 40941 | K23: 10.1016/j.meegid.2012.01.015
A24: 22305337 | B24: Molecular detection and characterization of Anaplasma phagocytophilum strains | C24: Paulauskas A, Radzijevskaja J, Rosef O. | D24: Comp Immunol Microbiol Infect Dis. 2012 Mar;35(2):187-95. doi: 10.1016/j.cimid.2012.01.001. Epub 2012 Feb 3. | E24: Paulauskas A | F24: Comp Immunol Microbiol Infect Dis | G24: 2012 | H24: 40946 | K24: 10.1016/j.cimid.2012.01.001
A25: 22321996 | B25: Human granulocytic anaplasmosis in eastern France: clinical presentation and laboratory diagnosis | C25: Koebel C, Kern A, Edouard S, Hoang AT, Celestin N, Hansmann Y, Jaulhac B, Brouqui P, De Martino SJ. | D25: Diagn Microbiol Infect Dis. 2012 Mar;72(3):214-8. doi: 10.1016/j.diagmicrobio.2011.12.005. | E25: Koebel C | F25: Diagn Microbiol Infect Dis | G25: 2012 | H25: 40950 | K25: 10.1016/j.diagmicrobio.2011.12.005
A26: 22369153 | B26: Genomics of epidemic pathogens | C26: Georgiades K. | D26: Clin Microbiol Infect. 2012 Mar;18(3):213-7. doi: 10.1111/j.1469-0691.2012.03781.x. | E26: Georgiades K | F26: Clin Microbiol Infect | G26: 2012 | H26: 40968 | K26: 10.1111/j.1469-0691.2012.03781.x
A27: 22374949 | B27: Complete genome sequence of Rickettsia slovaca, the agent of tick-borne lymphadenitis | C27: Fournier PE, El Karkouri K, Robert C, Médigue C, Raoult D. | D27: J Bacteriol. 2012 Mar;194(6):1612. doi: 10.1128/JB.06625-11. | E27: Fournier PE | F27: J Bacteriol | G27: 2012 | H27: 40969 | I27: PMC3294842 | K27: 10.1128/JB.06625-11
A28: 22376001 | B28: Absence of linkage disequilibria between chromosomal arrangements and mtDNA haplotypes in natural populations of Drosophila subobscura from the Balkan Peninsula | C28: Jelić M, Castro JA, Kurbalija Novičić Z, Kenig B, Dimitrijević D, Savić Veselinović M, Jovanović M, Milovanović D, Stamenković-Radak M, Andjelković M. | D28: Genome. 2012 Mar;55(3):214-21. doi: 10.1139/g2012-004. Epub 2012 Feb 29. | E28: Jelić M | F28: Genome | G28: 2012 | H28: 40970 | K28: 10.1139/g2012-004
A29: 22379331 | B29: Persistence of Orientia tsutsugamushi in humans | C29: Chung MH, Lee JS, Baek JH, Kim M, Kang JS. | D29: J Korean Med Sci. 2012 Mar;27(3):231-5. doi: 10.3346/jkms.2012.27.3.231. Epub 2012 Feb 23. | E29: Chung MH | F29: J Korean Med Sci | G29: 2012 | H29: 40970 | I29: PMC3286767 | K29: 10.3346/jkms.2012.27.3.231
A30: 22380432 | B30: Maintenance of a male-killing Wolbachia in Drosophila innubila by male-killing dependent and male-killing independent mechanisms | C30: Unckless RL, Jaenike J. | D30: Evolution. 2012 Mar;66(3):678-689. doi: 10.1111/j.1558-5646.2011.01485.x. Epub 2011 Nov 11. | E30: Unckless RL | F30: Evolution | G30: 2012 | H30: 40971 | K30: 10.1111/j.1558-5646.2011.01485.x
A31: 22386178 | B31: Clinical findings and diagnosis in human granulocytic anaplasmosis: a case series from Massachusetts | C31: Weil AA, Baron EL, Brown CM, Drapkin MS. | D31: Mayo Clin Proc. 2012 Mar;87(3):233-9. doi: 10.1016/j.mayocp.2011.09.008. | E31: Weil AA | F31: Mayo Clin Proc | G31: 2012 | H31: 40974 | I31: PMC3498394 | K31: 10.1016/j.mayocp.2011.09.008
A32: 22392278 | B32: Preliminary analysis to target pyruvate phosphate dikinase from wolbachia endosymbiont of Brugia malayi for designing anti-filarial agents | C32: Palayam M, Lakshminarayanan K, Radhakrishnan M, Krishnaswamy G. | D32: Interdiscip Sci. 2012 Mar;4(1):74-82. doi: 10.1007/s12539-011-0109-2. Epub 2012 Mar 6. | E32: Palayam M | F32: Interdiscip Sci | G32: 2012 | H32: 40975 | K32: 10.1007/s12539-011-0109-2
A33: 22484753 | B33: Rickettsial diseases in central India | C33: Mohta A. | D33: Indian Pediatr. 2012 Mar;49(3):251; discussion 251-2. | E33: Mohta A | F33: Indian Pediatr | G33: 2012 | H33: 41009
A34: 22515036 | B34: Seroprevalence and bacteremia [corrected] of Anaplasma phagocytophilum in cats from Bavaria and Lower Saxony (Germany) | C34: Hamel D, Bondarenko A, Silaghi C, Nolte I, Pfister K. | D34: Berl Munch Tierarztl Wochenschr. 2012 Mar-Apr;125(3-4):163-7. | E34: Hamel D | F34: Berl Munch Tierarztl Wochenschr | G34: 2012 | H34: 41020
A35: 22543604 | B35: Comparative seroprevalences of bovine trypanosomiasis and anaplasmosis in five states of Malaysia | C35: Rahman WA, Fong S, Chandrawathani P, Nurulaini R, Zaini CM, Premalaatha B. | D35: Trop Biomed. 2012 Mar;29(1):65-70. | E35: Rahman WA | F35: Trop Biomed | G35: 2012 | H35: 41030
A36: 22585246 | B36: Pleuropulmonary scrub typhus: a summary of Thai cases | C36: Wiwanitkit S, Wiwanitkit V. | D36: J Vector Borne Dis. 2012 Mar;49(1):48. | E36: Wiwanitkit S | F36: J Vector Borne Dis | G36: 2012 | H36: 41045
A37: 22595273 | B37: Molecular detection and analysis of spotted fever group Rickettsia in patients with fever and rash at a tertiary care centre in Tamil Nadu, India | C37: Prakash JA, Sohan Lal T, Rosemol V, Verghese VP, Pulimood SA, Reller M, Dumler JS. | D37: Pathog Glob Health. 2012 Mar;106(1):40-5. doi: 10.1179/2047773212Y.0000000001. | E37: Prakash JA | F37: Pathog Glob Health | G37: 2012 | H37: 41048 | I37: PMC4001510 | K37: 10.1179/2047773212Y.0000000001
A38: 22383821 | B38: Didier Raoult profile. Sound and fury in the microbiology lab | C38: Mary C. | D38: Science. 2012 Mar 2;335(6072):1033-5. doi: 10.1126/science.335.6072.1033. | E38: Mary C | F38: Science | G38: 2012 | H38: 40971 | K38: 10.1126/science.335.6072.1033
A39: 22401583 | B39: First case of Anaplasma platys infection in a dog from Croatia | C39: Dyachenko V, Pantchev N, Balzer HJ, Meyersen A, Straubinger RK. | D39: Parasit Vectors. 2012 Mar 9;5:49. doi: 10.1186/1756-3305-5-49. | E39: Dyachenko V | F39: Parasit Vectors | G39: 2012 | H39: 40978 | I39: PMC3315729 | K39: 10.1186/1756-3305-5-49
A40: 22433114 | B40: Long term impact of large scale community-directed delivery of doxycycline for the treatment of onchocerciasis | C40: Tamarozzi F, Tendongfor N, Enyong PA, Esum M, Faragher B, Wanji S, Taylor MJ. | D40: Parasit Vectors. 2012 Mar 20;5:53. doi: 10.1186/1756-3305-5-53. | E40: Tamarozzi F | F40: Parasit Vectors | G40: 2012 | H40: 40990 | I40: PMC3350421 | K40: 10.1186/1756-3305-5-53
A41: 22192469 | B41: Constraints on the use of lifespan-shortening Wolbachia to control dengue fever | C41: Schraiber JG, Kaczmarczyk AN, Kwok R, Park M, Silverstein R, Rutaganira FU, Aggarwal T, Schwemmer MA, Hom CL, Grosberg RK, Schreiber SJ. | D41: J Theor Biol. 2012 Mar 21;297:26-32. doi: 10.1016/j.jtbi.2011.12.006. Epub 2011 Dec 16. | E41: Schraiber JG | F41: J Theor Biol | G41: 2012 | H41: 40901 | K41: 10.1016/j.jtbi.2011.12.006
A42: 21940118 | B42: Acute phase response in cattle infected with Anaplasma marginale | C42: Nazifi S, Razavi SM, Kaviani F, Rakhshandehroo E. | D42: Vet Microbiol. 2012 Mar 23;155(2-4):267-71. doi: 10.1016/j.vetmic.2011.08.024. Epub 2011 Aug 31. | E42: Nazifi S | F42: Vet Microbiol | G42: 2012 | H42: 40810 | K42: 10.1016/j.vetmic.2011.08.024
A43: 22452970 | B43: Occurrence and identification of risk areas of Ixodes ricinus-borne pathogens: a cost-effectiveness analysis in north-eastern Italy | C43: Capelli G, Ravagnan S, Montarsi F, Ciocchetta S, Cazzin S, Porcellato E, Babiker AM, Cassini R, Salviato A, Cattoli G, Otranto D. | D43: Parasit Vectors. 2012 Mar 27;5:61. doi: 10.1186/1756-3305-5-61. | E43: Capelli G | F43: Parasit Vectors | G43: 2012 | H43: 40997 | I43: PMC3337281 | K43: 10.1186/1756-3305-5-61
A44: 22462408 | B44: Dose-response model of murine typhus (Rickettsia typhi): time post inoculation and host age dependency analysis | C44: Tamrakar SB, Huang Y, Teske SS, Haas CN. | D44: BMC Infect Dis. 2012 Mar 30;12:77. doi: 10.1186/1471-2334-12-77. | E44: Tamrakar SB | F44: BMC Infect Dis | G44: 2012 | H44: 41002 | I44: PMC3359249 | K44: 10.1186/1471-2334-12-77
A45: 21947341 | B45: Longitudinal field study on bovine Babesia spp. and Anaplasma phagocytophilum infections during a grazing season in Belgium | C45: Lempereur L, Lebrun M, Cuvelier P, Sépult G, Caron Y, Saegerman C, Shiels B, Losson B. | D45: Parasitol Res. 2012 Apr;110(4):1525-30. doi: 10.1007/s00436-011-2657-0. Epub 2011 Sep 27. | E45: Lempereur L | F45: Parasitol Res | G45: 2012 | H45: 40814 | K45: 10.1007/s00436-011-2657-0
A46: 21947342 | B46: Epidemiological aspects on vector-borne infections in stray and pet dogs from Romania and Hungary with focus on Babesia spp | C46: Hamel D, Silaghi C, Lescai D, Pfister K. | D46: Parasitol Res. 2012 Apr;110(4):1537-45. doi: 10.1007/s00436-011-2659-y. Epub 2011 Sep 27. | E46: Hamel D | F46: Parasitol Res | G46: 2012 | H46: 40814 | K46: 10.1007/s00436-011-2659-y
A47: 22032328 | B47: Absence of Wolbachia endobacteria in Chandlerella quiscali, an avian filarial parasite | C47: McNulty SN, Fischer K, Mehus JO, Vaughan JA, Tkach VV, Weil GJ, Fischer PU. | D47: J Parasitol. 2012 Apr;98(2):382-7. doi: 10.1645/GE-2879.1. Epub 2011 Oct 27. | E47: McNulty SN | F47: J Parasitol | G47: 2012 | H47: 40845 | I47: PMC5000782 | J47: NIHMS811498 | K47: 10.1645/GE-2879.1
A48: 22140099 | B48: Crystal structure of the DNA-bound VapBC2 antitoxin/toxin pair from Rickettsia felis | C48: Maté MJ, Vincentelli R, Foos N, Raoult D, Cambillau C, Ortiz-Lombardía M. | D48: Nucleic Acids Res. 2012 Apr;40(7):3245-58. doi: 10.1093/nar/gkr1167. Epub 2011 Dec 2. | E48: Maté MJ | F48: Nucleic Acids Res | G48: 2012 | H48: 40883 | I48: PMC3326315 | K48: 10.1093/nar/gkr1167
A49: 22188208 | B49: Rickettsia parkeri invasion of diverse host cells involves an Arp2/3 complex, WAVE complex and Rho-family GTPase-dependent pathway | C49: Reed SC, Serio AW, Welch MD. | D49: Cell Microbiol. 2012 Apr;14(4):529-45. doi: 10.1111/j.1462-5822.2011.01739.x. Epub 2012 Jan 16. | E49: Reed SC | F49: Cell Microbiol | G49: 2012 | H49: 40900 | I49: PMC3302968 | J49: NIHMS344637 | K49: 10.1111/j.1462-5822.2011.01739.x
A50: 22212234 | B50: Subversion of NPC1 pathway of cholesterol transport by Anaplasma phagocytophilum | C50: Xiong Q, Rikihisa Y. | D50: Cell Microbiol. 2012 Apr;14(4):560-76. doi: 10.1111/j.1462-5822.2011.01742.x. Epub 2012 Feb 8. | E50: Xiong Q | F50: Cell Microbiol | G50: 2012 | H50: 40912 | I50: PMC3604884 | J50: NIHMS346696 | K50: 10.1111/j.1462-5822.2011.01742.x
A51: 22214269 | B51: Detection of Anaplasma phagocytophilum in ixodid ticks from equine-inhabited sites in the Southeastern United States | C51: Roellig DM, Fang QQ. | D51: Vector Borne Zoonotic Dis. 2012 Apr;12(4):330-2. doi: 10.1089/vbz.2011.0757. Epub 2012 Jan 3. | E51: Roellig DM | F51: Vector Borne Zoonotic Dis | G51: 2012 | H51: 40913 | K51: 10.1089/vbz.2011.0757
A52: 22217177 | B52: Epidemiology and control of human granulocytic anaplasmosis: a systematic review | C52: Jin H, Wei F, Liu Q, Qian J. | D52: Vector Borne Zoonotic Dis. 2012 Apr;12(4):269-74. doi: 10.1089/vbz.2011.0753. Epub 2012 Jan 4. | E52: Jin H | F52: Vector Borne Zoonotic Dis | G52: 2012 | H52: 40914 | K52: 10.1089/vbz.2011.0753
A53: 22221256 | B53: Molecular characterization and tissue-specific gene expression of Dermacentor variabilis α-catenin in response to rickettsial infection | C53: Sunyakumthorn P, Petchampai N, Kearney MT, Sonenshine DE, Macaluso KR. | D53: Insect Mol Biol. 2012 Apr;21(2):197-204. doi: 10.1111/j.1365-2583.2011.01126.x. Epub 2012 Jan 6. | E53: Sunyakumthorn P | F53: Insect Mol Biol | G53: 2012 | H53: 40915 | I53: PMC3299920 | J53: NIHMS340488 | K53: 10.1111/j.1365-2583.2011.01126.x
A54: 22225423 | B54: Spotted fever group Rickettsia in Yunnan Province, China | C54: Liang CW, Zhao JB, Li J, Chang LT, Yu HL, Zhang LX, Zhang LJ, Yu XJ. | D54: Vector Borne Zoonotic Dis. 2012 Apr;12(4):281-6. doi: 10.1089/vbz.2011.0835. Epub 2012 Jan 6. | E54: Liang CW | F54: Vector Borne Zoonotic Dis | G54: 2012 | H54: 40918 | K54: 10.1089/vbz.2011.0835
A55: 22252875 | B55: Infection with Anaplasma phagocytophilum activates the phosphatidylinositol 3-Kinase/Akt and NF-κB survival pathways in neutrophil granulocytes | C55: Sarkar A, Hellberg L, Bhattacharyya A, Behnen M, Wang K, Lord JM, Möller S, Kohler M, Solbach W, Laskay T. | D55: Infect Immun. 2012 Apr;80(4):1615-23. doi: 10.1128/IAI.05219-11. Epub 2012 Jan 17. | E55: Sarkar A | F55: Infect Immun | G55: 2012 | H55: 40927 | I55: PMC3318406 | K55: 10.1128/IAI.05219-11
A56: 22286986 | B56: Factors driving the abundance of ixodes ricinus ticks and the prevalence of zoonotic I. ricinus-borne pathogens in natural foci | C56: Ruiz-Fons F, Fernández-de-Mera IG, Acevedo P, Gortázar C, de la Fuente J. | D56: Appl Environ Microbiol. 2012 Apr;78(8):2669-76. doi: 10.1128/AEM.06564-11. Epub 2012 Jan 27. | E56: Ruiz-Fons F | F56: Appl Environ Microbiol | G56: 2012 | H56: 40939 | I56: PMC3318823 | K56: 10.1128/AEM.06564-11
A57: 22327584 | B57: Pathogen prevalence in ticks collected from the vegetation and livestock in Nigeria | C57: Reye AL, Arinola OG, Hübschen JM, Muller CP. | D57: Appl Environ Microbiol. 2012 Apr;78(8):2562-8. doi: 10.1128/AEM.06686-11. Epub 2012 Feb 10. | E57: Reye AL | F57: Appl Environ Microbiol | G57: 2012 | H57: 40953 | I57: PMC3318832 | K57: 10.1128/AEM.06686-11
A58: 22354925 | B58: Fatal ehrlichial myocarditis in a healthy adolescent: a case report and review of the literature | C58: Havens NS, Kinnear BR, Mató S. | D58: Clin Infect Dis. 2012 Apr;54(8):e113-4. doi: 10.1093/cid/cis032. Epub 2012 Feb 21. | E58: Havens NS | F58: Clin Infect Dis | G58: 2012 | H58: 40962 | K58: 10.1093/cid/cis032
A59: 22360386 | B59: Human louse-transmitted infectious diseases | C59: Badiaga S, Brouqui P. | D59: Clin Microbiol Infect. 2012 Apr;18(4):332-7. doi: 10.1111/j.1469-0691.2012.03778.x. Epub 2012 Feb 23. | E59: Badiaga S | F59: Clin Microbiol Infect | G59: 2012 | H59: 40964 | K59: 10.1111/j.1469-0691.2012.03778.x
A60: 22368278 | B60: Obligate symbionts activate immune system development in the tsetse fly | C60: Weiss BL, Maltz M, Aksoy S. | D60: J Immunol. 2012 Apr 1;188(7):3395-403. doi: 10.4049/jimmunol.1103691. Epub 2012 Feb 24. | E60: Weiss BL | F60: J Immunol | G60: 2012 | H60: 40967 | I60: PMC3311772 | J60: NIHMS354929 | K60: 10.4049/jimmunol.1103691
A61: 22408242 | B61: Whole-genome sequence of Wolbachia strain wAlbB, an endosymbiont of tiger mosquito vector Aedes albopictus | C61: Mavingui P, Valiente Moro C, Tran-Van V, Wisniewski-Dyé F, Raquin V, Minard G, Tran FH, Voronin D, Rouy Z, Bustos P, Lozano L, Barbe V, González V. | D61: J Bacteriol. 2012 Apr;194(7):1840. doi: 10.1128/JB.00036-12. | E61: Mavingui P | F61: J Bacteriol | G61: 2012 | H61: 40981 | I61: PMC3302458 | K61: 10.1128/JB.00036-12
A62: 22431531 | B62: Two cases of transfusion-transmitted Anaplasma phagocytophilum | C62: Annen K, Friedman K, Eshoa C, Horowitz M, Gottschall J, Straus T. | D62: Am J Clin Pathol. 2012 Apr;137(4):562-5. doi: 10.1309/AJCP4E4VQQQOZIAQ. | E62: Annen K | F62: Am J Clin Pathol | G62: 2012 | H62: 40989 | K62: 10.1309/AJCP4E4VQQQOZIAQ
A63: 22443327 | B63: Canine vector-borne disease pathogens in dogs from south-east Queensland and north-east Northern Territory | C63: Hii SF, Kopp SR, Thompson MF, O'Leary CA, Rees RL, Traub RJ. | D63: Aust Vet J. 2012 Apr;90(4):130-5. doi: 10.1111/j.1751-0813.2012.00898.x. | E63: Hii SF | F63: Aust Vet J | G63: 2012 | H63: 40995 | K63: 10.1111/j.1751-0813.2012.00898.x
A64: 22445929 | B64: Seasonal activity and tick-borne pathogen infection rates of Ixodes ricinus ticks in Hungary | C64: Egyed L, Elő P, Sréter-Lancz Z, Széll Z, Balogh Z, Sréter T. | D64: Ticks Tick Borne Dis. 2012 Apr;3(2):90-4. doi: 10.1016/j.ttbdis.2012.01.002. Epub 2012 Mar 23. | E64: Egyed L | F64: Ticks Tick Borne Dis | G64: 2012 | H64: 40995 | K64: 10.1016/j.ttbdis.2012.01.002
A65: 22449515 | B65: Scrub typhus: pathophysiology, clinical manifestations and prognosis | C65: Rajapakse S, Rodrigo C, Fernando D. | D65: Asian Pac J Trop Med. 2012 Apr;5(4):261-4. doi: 10.1016/S1995-7645(12)60036-4. | E65: Rajapakse S | F65: Asian Pac J Trop Med | G65: 2012 | H65: 40996 | K65: 10.1016/S1995-7645(12)60036-4
A66: 22469314 | B66: Rickettsia monacensis as cause of Mediterranean spotted fever-like illness, Italy | C66: Madeddu G, Mancini F, Caddeo A, Ciervo A, Babudieri S, Maida I, Fiori ML, Rezza G, Mura MS. | D66: Emerg Infect Dis. 2012 Apr;18(4):702-4. doi: 10.3201/eid1804.111583. | E66: Madeddu G | F66: Emerg Infect Dis | G66: 2012 | H66: 41003 | I66: PMC3309684 | K66: 10.3201/eid1804.111583
A67: 22487426 | B67: Prevalence of Rickettsia spp., Anaplasma phagocytophilum, and Coxiella burnetii in adult Ixodes ricinus ticks from 29 study areas in central and southern Sweden | C67: Wallménius K, Pettersson JH, Jaenson TG, Nilsson K. | D67: Ticks Tick Borne Dis. 2012 Apr;3(2):100-6. doi: 10.1016/j.ttbdis.2011.11.003. Epub 2012 Jan 9. | E67: Wallménius K | F67: Ticks Tick Borne Dis | G67: 2012 | H67: 41010 | K67: 10.1016/j.ttbdis.2011.11.003
A68: 22492134 | B68: Scrub typhus without eruption | C68: Yoshimoto T, Yoshimoto T. | D68: Am J Trop Med Hyg. 2012 Apr;86(4):559. doi: 10.4269/ajtmh.2012.11-0616. | E68: Yoshimoto T | F68: Am J Trop Med Hyg | G68: 2012 | H68: 41011 | I68: PMC3403754 | K68: 10.4269/ajtmh.2012.11-0616
A69: 22492158 | B69: Detection of rickettsioses and Q fever in Sri Lanka | C69: Angelakis E, Munasinghe A, Yaddehige I, Liyanapathirana V, Thevanesam V, Bregliano A, Socolovschi C, Edouard S, Fournier PE, Raoult D, Parola P. | D69: Am J Trop Med Hyg. 2012 Apr;86(4):711-2. doi: 10.4269/ajtmh.2012.11-0424. | E69: Angelakis E | F69: Am J Trop Med Hyg | G69: 2012 | H69: 41011 | I69: PMC3403782 | K69: 10.4269/ajtmh.2012.11-0424
A70: 22511280 | B70: [African tick bite fever--rickettsiosis after holiday in South Africa] | C70: Schleenvoigt BT, Keller P, Stallmach A, Pletz MW. | D70: Dtsch Med Wochenschr. 2012 Apr;137(17):891-3. doi: 10.1055/s-0032-1304902. Epub 2012 Apr 17. | E70: Schleenvoigt BT | F70: Dtsch Med Wochenschr | G70: 2012 | H70: 41018 | K70: 10.1055/s-0032-1304902
A71: 22563611 | B71: Direct detection of Ehrlichia canis by PCR in the conjunctiva of a dog with bilateral anterior uveitis | C71: Walser-Reinhard L, Schaarschmidt-Kiener D, Forster JL, Matheis F, Spiess B. | D71: Schweiz Arch Tierheilkd. 2012 Apr;154(4):149-52. doi: 10.1024/0036-7281/a000318. | E71: Walser-Reinhard L | F71: Schweiz Arch Tierheilkd | G71: 2012 | H71: 41037 | K71: 10.1024/0036-7281/a000318
A72: 22565079 | B72: Pediatric Scrub typhus in South Sikkim | C72: Gupta N, Mittal V, Gurung B, Sherpa U. | D72: Indian Pediatr. 2012 Apr;49(4):322-4. | E72: Gupta N | F72: Indian Pediatr | G72: 2012 | H72: 41038
A73: 22566732 | B73: First case of scrub typhus with meningoencephalitis from Kerala: An emerging infectious threat | C73: Saifudheen K, Kumar KG, Jose J, Veena V, Gafoor VA. | D73: Ann Indian Acad Neurol. 2012 Apr;15(2):141-4. doi: 10.4103/0972-2327.95002. | E73: Saifudheen K | F73: Ann Indian Acad Neurol | G73: 2012 | H73: 41038 | I73: PMC3345595 | K73: 10.4103/0972-2327.95002
A74: 22590684 | B74: Megalocytiviruses | C74: Kurita J, Nakajima K. | D74: Viruses. 2012 Apr;4(4):521-38. doi: 10.3390/v4040521. Epub 2012 Apr 10. | E74: Kurita J | F74: Viruses | G74: 2012 | H74: 41046 | I74: PMC3347321 | K74: 10.3390/v4040521
A75: 22664504 | B75: Serological evidence of rickettsial infections in Delhi | C75: Mittal V, Gupta N, Bhattacharya D, Kumar K, Ichhpujani RL, Singh S, Chhabra M, Rana UV. | D75: Indian J Med Res. 2012 Apr;135(4):538-41. | E75: Mittal V | F75: Indian J Med Res | G75: 2012 | H75: 41066 | I75: PMC3385240
A76: 22693777 | B76: Murine typhus: endemic Rickettsia in southwest Texas | C76: Liddell PW, Sparks MJ. | D76: Clin Lab Sci. 2012 Spring;25(2):81-7. | E76: Liddell PW | F76: Clin Lab Sci | G76: 2012 | H76: 41075
A77: 22774502 | B77: [Natural focal tick-borne transmissive infections in the children of Perm Territory: differential diagnosis algorithm] | C77: Merzlova NB, Samarov MN. | D77: Med Parazitol (Mosk). 2012 Apr-Jun;(2):23-7. | E77: Merzlova NB | F77: Med Parazitol (Mosk) | G77: 2012 | H77: 41101
A78: 22800633 | B78: [Analysis of epidemic features of scrub typhus between year 2006 and 2010 in Shandong province, China] | C78: Ding L, Li Z, Wang XJ, Ding SJ, Zhang M, Zhao ZT. | D78: Zhonghua Yu Fang Yi Xue Za Zhi. 2012 Apr;46(4):338-42. | E78: Ding L | F78: Zhonghua Yu Fang Yi Xue Za Zhi | G78: 2012 | H78: 41108
A79: 22832744 | B79: In vitro cultivation of Anaplasma marginale and A. phagocytophilum in tick cell lines: a review | C79: Passos LM. | D79: Rev Bras Parasitol Vet. 2012 Apr-Jun;21(2):81-6. doi: 10.1590/s1984-29612012000200002. | E79: Passos LM | F79: Rev Bras Parasitol Vet | G79: 2012 | H79: 41117 | K79: 10.1590/s1984-29612012000200002
A80: 22832750 | B80: Evaluating the effectiveness of an inactivated vaccine from Anaplasma marginale derived from tick cell culture | C80: Lasmar PV, Carvalho AÚ, Facury Filho EJ, Bastos CV, Ribeiro MF. | D80: Rev Bras Parasitol Vet. 2012 Apr-Jun;21(2):112-7. doi: 10.1590/s1984-29612012000200008. | E80: Lasmar PV | F80: Rev Bras Parasitol Vet | G80: 2012 | H80: 41117 | K80: 10.1590/s1984-29612012000200008
A81: 24031883 | B81: Detection of Wolbachia (Alphaproteobacteria: rickettsiales) in three species of terrestrial isopods (crustacea: isopoda: oniscidea) in Brazil | C81: Zimmermann BL, Almerão MP, Bouchon D, Araujo PB. | D81: Braz J Microbiol. 2012 Apr;43(2):711-5. doi: 10.1590/S1517-83822012000200036. Epub 2012 Jun 1. | E81: Zimmermann BL | F81: Braz J Microbiol | G81: 2012 | H81: 41531 | I81: PMC3768838 | K81: 10.1590/S1517-83822012000200036
A82: 22497736 | B82: The expression of one ankyrin pk2 allele of the WO prophage is correlated with the Wolbachia feminizing effect in isopods | C82: Pichon S, Bouchon D, Liu C, Chen L, Garrett RA, Grève P. | D82: BMC Microbiol. 2012 Apr 12;12:55. doi: 10.1186/1471-2180-12-55. | E82: Pichon S | F82: BMC Microbiol | G82: 2012 | H82: 41013 | I82: PMC3431249 | K82: 10.1186/1471-2180-12-55
A83: 22515314 | B83: Prevalence of Neoehrlichia mikurensis in ticks and rodents from North-west Europe | C83: Jahfari S, Fonville M, Hengeveld P, Reusken C, Scholte EJ, Takken W, Heyman P, Medlock JM, Heylen D, Kleve J, Sprong H. | D83: Parasit Vectors. 2012 Apr 19;5:74. doi: 10.1186/1756-3305-5-74. | E83: Jahfari S | F83: Parasit Vectors | G83: 2012 | H83: 41020 | I83: PMC3395572 | K83: 10.1186/1756-3305-5-74
A84: 22526723 | B84: Tick-borne fever caused by Anaplasma phagocytophilum in Germany: first laboratory confirmed case in a dairy cattle herd | C84: Nieder M, Silaghi C, Hamel D, Pfister K, Schmäschke R, Pfeffer M. | D84: Tierarztl Prax Ausg G Grosstiere Nutztiere. 2012 Apr 24;40(2):101-6. | E84: Nieder M | F84: Tierarztl Prax Ausg G Grosstiere Nutztiere | G84: 2012 | H84: 41024
A85: 22531297 | B85: Population genetic structure of Aedes polynesiensis in the Society Islands of French Polynesia: implications for control using a Wolbachia-based autocidal strategy | C85: Brelsfoard CL, Dobson SL. | D85: Parasit Vectors. 2012 Apr 24;5:80. doi: 10.1186/1756-3305-5-80. | E85: Brelsfoard CL | F85: Parasit Vectors | G85: 2012 | H85: 41025 | I85: PMC3349601 | K85: 10.1186/1756-3305-5-80
A86: 22534530 | B86: Vector control: The last bite | C86: Gravitz L. | D86: Nature. 2012 Apr 25;484(7395):S26-7. doi: 10.1038/484S26a. | E86: Gravitz L | F86: Nature | G86: 2012 | H86: 41026 | K86: 10.1038/484S26a
A87: 22214272 | B87: A new Rickettsia species found in fleas collected from human dwellings and from domestic cats and dogs in Senegal | C87: Roucher C, Mediannikov O, Diatta G, Trape JF, Raoult D. | D87: Vector Borne Zoonotic Dis. 2012 May;12(5):360-5. doi: 10.1089/vbz.2011.0734. Epub 2012 Jan 3. | E87: Roucher C | F87: Vector Borne Zoonotic Dis | G87: 2012 | H87: 40913 | K87: 10.1089/vbz.2011.0734
A88: 22217182 | B88: Molecular detection of spotted fever group rickettsiae associated with ixodid ticks in Egypt | C88: Abdel-Shafy S, Allam NA, Mediannikov O, Parola P, Raoult D. | D88: Vector Borne Zoonotic Dis. 2012 May;12(5):346-59. doi: 10.1089/vbz.2010.0241. Epub 2012 Jan 4. | E88: Abdel-Shafy S | F88: Vector Borne Zoonotic Dis | G88: 2012 | H88: 40914 | K88: 10.1089/vbz.2010.0241
A89: 22226382 | B89: Adaptive immunity to Anaplasma pathogens and immune dysregulation: implications for bacterial persistence | C89: Brown WC. | D89: Comp Immunol Microbiol Infect Dis. 2012 May;35(3):241-52. doi: 10.1016/j.cimid.2011.12.002. Epub 2012 Jan 4. | E89: Brown WC | F89: Comp Immunol Microbiol Infect Dis | G89: 2012 | H89: 40918 | I89: PMC3327808 | J89: NIHMS348171 | K89: 10.1016/j.cimid.2011.12.002
A90: 22244519 | B90: Prevalence of livestock diseases and their impact on livelihoods in Central Equatoria State, Southern Sudan | C90: Malak AK, Mpoke L, Banak J, Muriuki S, Skilton RA, Odongo D, Sunter J, Kiara H. | D90: Prev Vet Med. 2012 May 1;104(3-4):216-23. doi: 10.1016/j.prevetmed.2011.12.001. Epub 2012 Jan 13. | E90: Malak AK | F90: Prev Vet Med | G90: 2012 | H90: 40925 | K90: 10.1016/j.prevetmed.2011.12.001
A91: 22349945 | B91: Capybaras and ticks in the urban areas of Uberlândia, Minas Gerais, Brazil: ecological aspects for the epidemiology of tick-borne diseases | C91: Queirogas VL, Del Claro K, Nascimento AR, Szabó MP. | D91: Exp Appl Acarol. 2012 May;57(1):75-82. doi: 10.1007/s10493-012-9533-1. Epub 2012 Feb 16. | E91: Queirogas VL | F91: Exp Appl Acarol | G91: 2012 | H91: 40961 | K91: 10.1007/s10493-012-9533-1
A92: 22389475 | B92: Postgenomic analyses reveal development of infectious Anaplasma phagocytophilum during transmission from ticks to mice | C92: Mastronunzio JE, Kurscheid S, Fikrig E. | D92: J Bacteriol. 2012 May;194(9):2238-47. doi: 10.1128/JB.06791-11. Epub 2012 Mar 2. | E92: Mastronunzio JE | F92: J Bacteriol | G92: 2012 | H92: 40974 | I92: PMC3347074 | K92: 10.1128/JB.06791-11
A93: 22392926 | B93: Susceptibility of inbred mice to Rickettsia parkeri | C93: Grasperge BJ, Reif KE, Morgan TD, Sunyakumthorn P, Bynog J, Paddock CD, Macaluso KR. | D93: Infect Immun. 2012 May;80(5):1846-52. doi: 10.1128/IAI.00109-12. Epub 2012 Mar 5. | E93: Grasperge BJ | F93: Infect Immun | G93: 2012 | H93: 40975 | I93: PMC3347444 | K93: 10.1128/IAI.00109-12
A94: 22407681 | B94: Role of the lizard Teira dugesii as a potential host for Ixodes ricinus tick-borne pathogens | C94: De Sousa R, Lopes de Carvalho I, Santos AS, Bernardes C, Milhano N, Jesus J, Menezes D, Núncio MS. | D94: Appl Environ Microbiol. 2012 May;78(10):3767-9. doi: 10.1128/AEM.07945-11. Epub 2012 Mar 9. | E94: De Sousa R | F94: Appl Environ Microbiol | G94: 2012 | H94: 40981 | I94: PMC3346372 | K94: 10.1128/AEM.07945-11
A95: 22433115 | B95: Chikungunya virus impacts the diversity of symbiotic bacteria in mosquito vector | C95: Zouache K, Michelland RJ, Failloux AB, Grundmann GL, Mavingui P. | D95: Mol Ecol. 2012 May;21(9):2297-309. doi: 10.1111/j.1365-294X.2012.05526.x. Epub 2012 Mar 20. | E95: Zouache K | F95: Mol Ecol | G95: 2012 | H95: 40990 | K95: 10.1111/j.1365-294X.2012.05526.x
A96: 22493192 | B96: Sequence and annotation of Rickettsia sibirica sibirica genome | C96: Sentausa E, El Karkouri K, Robert C, Raoult D, Fournier PE. | D96: J Bacteriol. 2012 May;194(9):2377. doi: 10.1128/JB.00150-12. | E96: Sentausa E | F96: J Bacteriol | G96: 2012 | H96: 41011 | I96: PMC3347044 | K96: 10.1128/JB.00150-12
A97: 22493199 | B97: Genome sequence of "Rickettsia sibirica subsp. mongolitimonae" | C97: Sentausa E, El Karkouri K, Robert C, Raoult D, Fournier PE. | D97: J Bacteriol. 2012 May;194(9):2389-90. doi: 10.1128/JB.00239-12. | E97: Sentausa E | F97: J Bacteriol | G97: 2012 | H97: 41011 | I97: PMC3347047 | K97: 10.1128/JB.00239-12
A98: 22516455 | B98: Unsuspected rickettsioses among patients with acute febrile illness, Sri Lanka, 2007 | C98: Reller ME, Bodinayake C, Nagahawatte A, Devasiri V, Kodikara-Arachichi W, Strouse JJ, Flom JE, Østbye T, Woods CW, Dumler JS. | D98: Emerg Infect Dis. 2012 May;18(5):825-9. doi: 10.3201/eid1805.111563. | E98: Reller ME | F98: Emerg Infect Dis | G98: 2012 | H98: 41020 | I98: PMC3358078 | K98: 10.3201/eid1805.111563
A99: 22532262 | B99: [Vacation and tropical dermatoses] | C99: Fischer M, Reinel D. | D99: Hautarzt. 2012 May;63(5):396-403. doi: 10.1007/s00105-011-2258-y. | E99: Fischer M | F99: Hautarzt | G99: 2012 | H99: 41025 | K99: 10.1007/s00105-011-2258-y
A100: 22535934 | B100: Genomic comparison of Rickettsia helvetica and other Rickettsia species | C100: Dong X, El Karkouri K, Robert C, Gavory F, Raoult D, Fournier PE. | D100: J Bacteriol. 2012 May;194(10):2751. doi: 10.1128/JB.00299-12. | E100: Dong X | F100: J Bacteriol | G100: 2012 | H100: 41026 | I100: PMC3347184 | K100: 10.1128/JB.00299-12
...

Sheet 2017-2022
A1: PMID | B1: Title | C1: Authors | D1: Citation | E1: First Author | F1: Journal/Book | G1: Publication Year | H1: Create Date | I1: PMCID | J1: NIHMS ID | K1: DOI
A2: 28241043 | B2: Use of eschar swabbing for the molecular diagnosis and genotyping of Orientia tsutsugamushi causing scrub typhus in Quang Nam province, Vietnam | C2: Le Viet N, Laroche M, Thi Pham HL, Viet NL, Mediannikov O, Raoult D, Parola P. | D2: PLoS Negl Trop Dis. 2017 Feb 27;11(2):e0005397. doi: 10.1371/journal.pntd.0005397. eCollection 2017 Feb. | E2: Le Viet N | F2: PLoS Negl Trop Dis | G2: 2017 | H2: 42794 | I2: PMC5344524 | K2: 10.1371/journal.pntd.0005397
A3: 28241784 | B3: Genetic profiling for Anaplasma and Ehrlichia species in ticks collected in the Eastern Cape Province of South Africa | C3: Iweriebor BC, Mmbaga EJ, Adegborioye A, Igwaran A, Obi LC, Okoh AI. | D3: BMC Microbiol. 2017 Feb 27;17(1):45. doi: 10.1186/s12866-017-0955-0. | E3: Iweriebor BC | F3: BMC Microbiol | G3: 2017 | H3: 42795 | I3: PMC5327538 | K3: 10.1186/s12866-017-0955-0
A4: 28241782 | B4: Molecular detection and identification of Wolbachia in three species of the genus Lutzomyia on the Colombian Caribbean coast | C4: Vivero RJ, Cadavid-Restrepo G, Herrera CX, Soto SI. | D4: Parasit Vectors. 2017 Feb 28;10(1):110. doi: 10.1186/s13071-017-2031-x. | E4: Vivero RJ | F4: Parasit Vectors | G4: 2017 | H4: 42795 | I4: PMC5329942 | K4: 10.1186/s13071-017-2031-x
A5: 27628851 | B5: Two-sex mosquito model for the persistence of Wolbachia | C5: Xue L, Manore CA, Thongsripong P, Hyman JM. | D5: J Biol Dyn. 2017 Mar;11(sup1):216-237. doi: 10.1080/17513758.2016.1229051. Epub 2016 Sep 14. | E5: Xue L | F5: J Biol Dyn | G5: 2017 | H5: 42629 | K5: 10.1080/17513758.2016.1229051
A6: 27731327 | B6: Incomplete offspring sex bias in Australian populations of the butterfly Eurema hecabe | C6: Kemp DJ, Thomson FE, Edwards W, Iturbe-Ormaetxe I. | D6: Heredity (Edinb). 2017 Mar;118(3):284-292. doi: 10.1038/hdy.2016.85. Epub 2016 Oct 12. | E6: Kemp DJ | F6: Heredity (Edinb) | G6: 2017 | H6: 42656 | I6: PMC5315524 | K6: 10.1038/hdy.2016.85
A7: 27773866 | B7: Rickettsia parkeri and "Candidatus Rickettsia andeanae" in Questing Amblyomma maculatum (Acari: Ixodidae) From Mississippi | C7: Lee JK, Moraru GM, Stokes JV, Wills RW, Mitchell E, Unz E, Moore-Henderson B, Harper AB, Varela-Stokes AS. | D7: J Med Entomol. 2017 Mar 1;54(2):476-480. doi: 10.1093/jme/tjw175. | E7: Lee JK | F7: J Med Entomol | G7: 2017 | H7: 42668 | I7: PMC5850715 | K7: 10.1093/jme/tjw175
A8: 27939332 | B8: Phylogenetic relationship and genotypic variability in Anaplasma marginale strains causing anaplasmosis in India | C8: George N, Bhandari V, Sharma P. | D8: Infect Genet Evol. 2017 Mar;48:71-75. doi: 10.1016/j.meegid.2016.11.028. Epub 2016 Dec 6. | E8: George N | F8: Infect Genet Evol | G8: 2017 | H8: 42717 | K8: 10.1016/j.meegid.2016.11.028
A9: 27986544 | B9: "Candidatus Rickettsia asemboensis" in Rhipicephalus sanguineus ticks, Brazil | C9: Dall'Agnol B, Souza U, Webster A, Weck B, Stenzel B, Labruna M, Klafke G, Martins JR, Ferreira CAS, Reck J. | D9: Acta Trop. 2017 Mar;167:18-20. doi: 10.1016/j.actatropica.2016.12.008. Epub 2016 Dec 13. | E9: Dall'Agnol B | F9: Acta Trop | G9: 2017 | H9: 42722 | K9: 10.1016/j.actatropica.2016.12.008
A10: 27986546 | B10: Molecular epidemiological survey of bacterial and parasitic pathogens in hard ticks from eastern China | C10: Liu XY, Gong XY, Zheng C, Song QY, Chen T, Wang J, Zheng J, Deng HK, Zheng KY. | D10: Acta Trop. 2017 Mar;167:26-30. doi: 10.1016/j.actatropica.2016.12.010. Epub 2016 Dec 13. | E10: Liu XY | F10: Acta Trop | G10: 2017 | H10: 42722 | K10: 10.1016/j.actatropica.2016.12.010
A11: 27992288 | B11: Survey for Rickettsiae Within Fleas of Great Gerbils, Almaty Oblast, Kazakhstan | C11: Sansyzbayev Y, Nurmakhanov T, Berdibekov A, Vilkova A, Yeskhodzhayev O, St John HK, Jiang J, Farris CM, Richards AL. | D11: Vector Borne Zoonotic Dis. 2017 Mar;17(3):172-178. doi: 10.1089/vbz.2016.2049. Epub 2016 Dec 19. | E11: Sansyzbayev Y | F11: Vector Borne Zoonotic Dis | G11: 2017 | H11: 42724 | K11: 10.1089/vbz.2016.2049
A12: 27992293 | B12: Molecular Characterization of Anaplasma sp. in Free-Living Gray Brockets (Mazama gouazoubira) | C12: Mongruel AC, Benevenute JL, André MR, Carrasco AO, Machado RZ, Seki MC. | D12: Vector Borne Zoonotic Dis. 2017 Mar;17(3):165-171. doi: 10.1089/vbz.2016.2026. Epub 2016 Dec 19. | E12: Mongruel AC | F12: Vector Borne Zoonotic Dis | G12: 2017 | H12: 42724 | K12: 10.1089/vbz.2016.2026
A13: 27993973 | B13: Anaplasma marginale Outer Membrane Protein A Is an Adhesin That Recognizes Sialylated and Fucosylated Glycans and Functionally Depends on an Essential Binding Domain | C13: Hebert KS, Seidman D, Oki AT, Izac J, Emani S, Oliver LD Jr,, Miller DP, Tegels BK, Kannagi R, Marconi RT, Carlyon JA. | D13: Infect Immun. 2017 Feb 23;85(3):e00968-16. doi: 10.1128/IAI.00968-16. Print 2017 Mar. | E13: Hebert KS | F13: Infect Immun | G13: 2017 | H13: 42725 | I13: PMC5328490 | K13: 10.1128/IAI.00968-16
A14: 28011722 | B14: Evaluation of Doxycycline-Laden Oral Bait and Topical Fipronil Delivered in a Single Bait Box to Control Ixodes scapularis (Acari: Ixodidae) and Reduce Borrelia burgdorferi and Anaplasma phagocytophilum Infection in Small Mammal Reservoirs and Host-Seeking Ticks | C14: Dolan MC, Schulze TL, Jordan RA, Schulze CJ, Ullmann AJ, Hojgaard A, Williams MA, Piesman J. | D14: J Med Entomol. 2017 Mar 1;54(2):403-410. doi: 10.1093/jme/tjw194. | E14: Dolan MC | F14: J Med Entomol | G14: 2017 | H14: 42729 | I14: PMC5968630 | K14: 10.1093/jme/tjw194
A15: 28012903 | B15: Multiple-host pathogens in domestic hunting dogs in Nicaragua's Bosawás Biosphere Reserve | C15: Fiorello CV, Straub MH, Schwartz LM, Liu J, Campbell A, Kownacki AK, Foley JE. | D15: Acta Trop. 2017 Mar;167:183-190. doi: 10.1016/j.actatropica.2016.12.020. Epub 2016 Dec 21. | E15: Fiorello CV | F15: Acta Trop | G15: 2017 | H15: 42730 | K15: 10.1016/j.actatropica.2016.12.020
A16: 28026894 | B16: By their own devices: invasive Argentine ants have shifted diet without clear aid from symbiotic microbes | C16: Hu Y, Holway DA, Łukasik P, Chau L, Kay AD, LeBrun EG, Miller KA, Sanders JG, Suarez AV, Russell JA. | D16: Mol Ecol. 2017 Mar;26(6):1608-1630. doi: 10.1111/mec.13991. Epub 2017 Jan 27. | E16: Hu Y | F16: Mol Ecol | G16: 2017 | H16: 42732 | K16: 10.1111/mec.13991
A17: 28027580 | B17: Effects of predation and nutrient enrichment on the success and microbiome of a foundational coral | C17: Shaver EC, Shantz AA, McMinds R, Burkepile DE, Vega Thurber RL, Silliman BR. | D17: Ecology. 2017 Mar;98(3):830-839. doi: 10.1002/ecy.1709. | E17: Shaver EC | F17: Ecology | G17: 2017 | H17: 42732 | K17: 10.1002/ecy.1709
A18: 28031350 | B18: A Molecular Survey for Francisella tularensis and Rickettsia spp. in Haemaphysalis leporispalustris (Acari: Ixodidae) in Northern California | C18: Roth T, Lane RS, Foley J. | D18: J Med Entomol. 2017 Mar 1;54(2):492-495. doi: 10.1093/jme/tjw202. | E18: Roth T | F18: J Med Entomol | G18: 2017 | H18: 42734 | K18: 10.1093/jme/tjw202
A19: 28031351 | B19: Evaluation of Gulf Coast Ticks (Acari: Ixodidae) for Ehrlichia and Anaplasma Species | C19: Allerdice ME, Hecht JA, Karpathy SE, Paddock CD. | D19: J Med Entomol. 2017 Mar 1;54(2):481-484. doi: 10.1093/jme/tjw176. | E19: Allerdice ME | F19: J Med Entomol | G19: 2017 | H19: 42734 | K19: 10.1093/jme/tjw176
A20: 28044222 | B20: Scrub typhus: radiological and clinical findings in abdominopelvic involvement | C20: Kim KY, Song JS, Park EH, Jin GY. | D20: Jpn J Radiol. 2017 Mar;35(3):101-108. doi: 10.1007/s11604-016-0607-6. Epub 2017 Jan 2. | E20: Kim KY | F20: Jpn J Radiol | G20: 2017 | H20: 42739 | K20: 10.1007/s11604-016-0607-6
A21: 28063832 | B21: The risk of exposure to rickettsial infections and human granulocytic anaplasmosis associated with Ixodes ricinus tick bites in humans in Romania: A multiannual study | C21: Matei IA, Kalmár Z, Lupşe M, D'Amico G, Ionică AM, Dumitrache MO, Gherman CM, Mihalca AD. | D21: Ticks Tick Borne Dis. 2017 Mar;8(3):375-378. doi: 10.1016/j.ttbdis.2016.12.013. Epub 2016 Dec 29. | E21: Matei IA | F21: Ticks Tick Borne Dis | G21: 2017 | H21: 42744 | K21: 10.1016/j.ttbdis.2016.12.013
A22: 28089651 | B22: Canine tick-borne pathogens in Cyprus and a unique canine case of multiple co-infections | C22: Attipa C, Hicks CAE, Barker EN, Christodoulou V, Neofytou K, Mylonakis ME, Siarkou VI, Vingopoulou EI, Soutter F, Chochlakis D, Psaroulaki A, Papasouliotis K, Tasker S. | D22: Ticks Tick Borne Dis. 2017 Mar;8(3):341-346. doi: 10.1016/j.ttbdis.2016.12.006. Epub 2016 Dec 26. | E22: Attipa C | F22: Ticks Tick Borne Dis | G22: 2017 | H22: 42752 | I22: PMC5315763 | K22: 10.1016/j.ttbdis.2016.12.006
A23: 28109769 | B23: Molecular typing and diagnosis of Anaplasma spp. closely related to Anaplasma phagocytophilum in ruminants from Tunisia | C23: Ben Said M, Belkahia H, El Mabrouk N, Saidani M, Ben Hassen M, Alberti A, Zobba R, Bouattour S, Bouattour A, Messadi L. | D23: Ticks Tick Borne Dis. 2017 Mar;8(3):412-422. doi: 10.1016/j.ttbdis.2017.01.005. Epub 2017 Jan 16. | E23: Ben Said M | F23: Ticks Tick Borne Dis | G23: 2017 | H23: 42758 | K23: 10.1016/j.ttbdis.2017.01.005
A24: 28110915 | B24: Detection of Rickettsia hoogstraalii, Rickettsia helvetica, Rickettsia massiliae, Rickettsia slovaca and Rickettsia aeschlimannii in ticks from Sardinia, Italy | C24: Chisu V, Leulmi H, Masala G, Piredda M, Foxi C, Parola P. | D24: Ticks Tick Borne Dis. 2017 Mar;8(3):347-352. doi: 10.1016/j.ttbdis.2016.12.007. Epub 2016 Dec 15. | E24: Chisu V | F24: Ticks Tick Borne Dis | G24: 2017 | H24: 42759 | K24: 10.1016/j.ttbdis.2016.12.007
A25: 28111714 | B25: Pyrosequencing based assessment of bacterial diversity in Turkish Rhipicephalus annulatus and Dermacentor marginatus ticks (Acari: Ixodidae) | C25: Tekin S, Dowd SE, Davinic M, Bursali A, Keskin A. | D25: Parasitol Res. 2017 Mar;116(3):1055-1061. doi: 10.1007/s00436-017-5387-0. Epub 2017 Jan 22. | E25: Tekin S | F25: Parasitol Res | G25: 2017 | H25: 42759 | K25: 10.1007/s00436-017-5387-0
A26: 28115665 | B26: Successfully Managed Acute Transverse Myelitis Related to Scrub Typhus and Serial Image Findings | C26: Yun JS, Song JS, Choi EJ, Hwang JH, Lee CS, Park EH. | D26: Am J Trop Med Hyg. 2017 Mar;96(3):557-560. doi: 10.4269/ajtmh.16-0524. Epub 2017 Apr 6. | E26: Yun JS | F26: Am J Trop Med Hyg | G26: 2017 | H26: 42760 | I26: PMC5361527 | K26: 10.4269/ajtmh.16-0524
A27: 28131594 | B27: Detection of Borrelia miyamotoi and other tick-borne pathogens in human clinical specimens and Ixodes scapularis ticks in New York State, 2012-2015 | C27: Wroblewski D, Gebhardt L, Prusinski MA, Meehan LJ, Halse TA, Musser KA. | D27: Ticks Tick Borne Dis. 2017 Mar;8(3):407-411. doi: 10.1016/j.ttbdis.2017.01.004. Epub 2017 Jan 16. | E27: Wroblewski D | F27: Ticks Tick Borne Dis | G27: 2017 | H27: 42765 | K27: 10.1016/j.ttbdis.2017.01.004
A28: 28143697 | B28: First detection of tick-borne pathogens of dogs from Malta | C28: Licari E, Takács N, Solymosi N, Farkas R. | D28: Ticks Tick Borne Dis. 2017 Mar;8(3):396-399. doi: 10.1016/j.ttbdis.2017.01.002. Epub 2017 Jan 18. | E28: Licari E | F28: Ticks Tick Borne Dis | G28: 2017 | H28: 42768 | K28: 10.1016/j.ttbdis.2017.01.002
A29: 28169172 | B29: Molecular characterisation of Anaplasma species from African buffalo (Syncerus caffer) in Kruger National Park, South Africa | C29: Sisson D, Hufschmid J, Jolles A, Beechler B, Jabbar A. | D29: Ticks Tick Borne Dis. 2017 Mar;8(3):400-406. doi: 10.1016/j.ttbdis.2017.01.003. Epub 2017 Jan 17. | E29: Sisson D | F29: Ticks Tick Borne Dis | G29: 2017 | H29: 42774 | K29: 10.1016/j.ttbdis.2017.01.003
A30: 28244333 | B30: Seasonally biased or single-habitat sampling is not informative on the real prevalence of Dermacentor reticulatus-borne rickettsiae - A pilot study | C30: Hornok S, Meli ML, Gönczi E, Hofmann-Lehmann R. | D30: Acta Vet Hung. 2017 Mar;65(1):81-88. doi: 10.1556/004.2017.008. | E30: Hornok S | F30: Acta Vet Hung | G30: 2017 | H30: 42795 | K30: 10.1556/004.2017.008
A31: 28248294 | B31: A Wolbachia deubiquitylating enzyme induces cytoplasmic incompatibility | C31: Beckmann JF, Ronau JA, Hochstrasser M. | D31: Nat Microbiol. 2017 Mar 1;2:17007. doi: 10.1038/nmicrobiol.2017.7. | E31: Beckmann JF | F31: Nat Microbiol | G31: 2017 | H31: 42796 | I31: PMC5336136 | J31: NIHMS842725 | K31: 10.1038/nmicrobiol.2017.7
A32: 28248955 | B32: First identification of Rickettsia helvetica in questing ticks from a French Northern Brittany Forest | C32: Bonnet SI, Paul RE, Bischoff E, Cote M, Le Naour E. | D32: PLoS Negl Trop Dis. 2017 Mar 1;11(3):e0005416. doi: 10.1371/journal.pntd.0005416. eCollection 2017 Mar. | E32: Bonnet SI | F32: PLoS Negl Trop Dis | G32: 2017 | H32: 42796 | I32: PMC5348082 | K32: 10.1371/journal.pntd.0005416
A33: 28248956 | B33: Diversification of Orientia tsutsugamushi genotypes by intragenic recombination and their potential expansion in endemic areas | C33: Kim G, Ha NY, Min CK, Kim HI, Yen NT, Lee KH, Oh I, Kang JS, Choi MS, Kim IS, Cho NH. | D33: PLoS Negl Trop Dis. 2017 Mar 1;11(3):e0005408. doi: 10.1371/journal.pntd.0005408. eCollection 2017 Mar. | E33: Kim G | F33: PLoS Negl Trop Dis | G33: 2017 | H33: 42796 | I33: PMC5348041 | K33: 10.1371/journal.pntd.0005408
A34: 28284610 | B34: Association of Ehrlichia canis, Hemotropic Mycoplasma spp. and Anaplasma platys and severe anemia in dogs in Thailand | C34: Kaewmongkol G, Lukkana N, Yangtara S, Kaewmongkol S, Thengchaisri N, Sirinarumitr T, Jittapalapong S, Fenwick SG. | D34: Vet Microbiol. 2017 Mar;201:195-200. doi: 10.1016/j.vetmic.2017.01.022. Epub 2017 Jan 21. | E34: Kaewmongkol G | F34: Vet Microbiol | G34: 2017 | H34: 42807 | K34: 10.1016/j.vetmic.2017.01.022
A35: 28284620 | B35: The genetic characteristics and evolution of Tembusu virus | C35: Lei W, Guo X, Fu S, Feng Y, Tao X, Gao X, Song J, Yang Z, Zhou H, Liang G. | D35: Vet Microbiol. 2017 Mar;201:32-41. doi: 10.1016/j.vetmic.2017.01.003. Epub 2017 Jan 4. | E35: Lei W | F35: Vet Microbiol | G35: 2017 | H35: 42807 | K35: 10.1016/j.vetmic.2017.01.003
A36: 28291501 | B36: Lateral Flow Rapid Test for Accurate and Early Diagnosis of Scrub Typhus: A Febrile Illness of Historically Military Importance in the Pacific Rim | C36: Chao CC, Zhangm Z, Weissenberger G, Chen HW, Ching WM. | D36: Mil Med. 2017 Mar;182(S1):369-375. doi: 10.7205/MILMED-D-16-00091. | E36: Chao CC | F36: Mil Med | G36: 2017 | H36: 42809 | K36: 10.7205/MILMED-D-16-00091
A37: 28299286 | B37: The Rickettsia conorii Adr1 Interacts with the C-Terminus of Human Vitronectin in a Salt-Sensitive Manner | C37: Fish AI, Riley SP, Singh B, Riesbeck K, Martinez JJ. | D37: Front Cell Infect Microbiol. 2017 Mar 1;7:61. doi: 10.3389/fcimb.2017.00061. eCollection 2017. | E37: Fish AI | F37: Front Cell Infect Microbiol | G37: 2017 | H37: 42811 | I37: PMC5331051 | K37: 10.3389/fcimb.2017.00061
A38: 28333306 | B38: Protein aggregation in Ehrlichia chaffeensis during infection of mammalian cells | C38: Kuczynska-Wisnik D, Cheng C, Ganta RR, Zolkiewski M. | D38: FEMS Microbiol Lett. 2017 Mar 1;364(6):fnx059. doi: 10.1093/femsle/fnx059. | E38: Kuczynska-Wisnik D | F38: FEMS Microbiol Lett | G38: 2017 | H38: 42818 | I38: PMC5399918 | K38: 10.1093/femsle/fnx059
A39: 28531311 | B39: The genotypes of Orientia tsutsugamushi, identified in scrub typhus patients in northern Vietnam | C39: Nguyen HLK, Pham HTT, Nguyen TV, Hoang PV, Le MTQ, Takemura T, Hasebe F, Hayasaka D, Yamada A, Hotta K. | D39: Trans R Soc Trop Med Hyg. 2017 Mar 1;111(3):137-139. doi: 10.1093/trstmh/trx022. | E39: Nguyen HLK | F39: Trans R Soc Trop Med Hyg | G39: 2017 | H39: 42878 | K39: 10.1093/trstmh/trx022
A40: 28559729 | B40: Biosynthesis of Oxytetracycline by Streptomyces rimosus: Past, Present and Future Directions in the Development of Tetracycline Antibiotics | C40: Petković H, Lukežič T, Šušković J. | D40: Food Technol Biotechnol. 2017 Mar;55(1):3-13. doi: 10.17113/ftb.55.01.17.4617. | E40: Petković H | F40: Food Technol Biotechnol | G40: 2017 | H40: 42887 | I40: PMC5434370 | K40: 10.17113/ftb.55.01.17.4617
A41: 28816212 | B41: Scrub typhus: A prospective, observational study during an outbreak in Rajasthan, India | C41: Takhar RP, Bunkar ML, Arya S, Mirdha N, Mohd A. | D41: Natl Med J India. 2017 Mar-Apr;30(2):69-72. | E41: Takhar RP | F41: Natl Med J India | G41: 2017 | H41: 42965
A42: 28257433 | B42: A comparison of nonlinear mixed models and response to selection of tick-infestation on lambs | C42: Sae-Lim P, Grøva L, Olesen I, Varona L. | D42: PLoS One. 2017 Mar 3;12(3):e0172711. doi: 10.1371/journal.pone.0172711. eCollection 2017. | E42: Sae-Lim P | F42: PLoS One | G42: 2017 | H42: 42798 | I42: PMC5336382 | K42: 10.1371/journal.pone.0172711
A43: 28259176 | B43: Molecular and serological evidence of flea-associated typhus group and spotted fever group rickettsial infections in Madagascar | C43: Rakotonanahary RJ, Harrison A, Maina AN, Jiang J, Richards AL, Rajerison M, Telfer S. | D43: Parasit Vectors. 2017 Mar 4;10(1):125. doi: 10.1186/s13071-017-2061-4. | E43: Rakotonanahary RJ | F43: Parasit Vectors | G43: 2017 | H43: 42800 | I43: PMC5336680 | K43: 10.1186/s13071-017-2061-4
A44: 28260341 | B44: [Study of epidemic area on Tsutsugamushi disease in Taizhou from 2013 to 2014] | C44: He YL, Yang HY, Yu CX, Zhang X, Yi QH, Ma ZL, Cha J, Xu XB, Zhang Q, Dai WJ, Qian WJ, Yin J, Zhu SJ, Xu Z. | D44: Zhonghua Yu Fang Yi Xue Za Zhi. 2017 Mar 6;51(3):252-256. doi: 10.3760/cma.j.issn.0253-9624.2017.03.012. | E44: He YL | F44: Zhonghua Yu Fang Yi Xue Za Zhi | G44: 2017 | H44: 42800 | K44: 10.3760/cma.j.issn.0253-9624.2017.03.012
A45: 28262718 | B45: The RNAi pathway plays a small part in Wolbachia-mediated blocking of dengue virus in mosquito cells | C45: Terradas G, Joubert DA, McGraw EA. | D45: Sci Rep. 2017 Mar 6;7:43847. doi: 10.1038/srep43847. | E45: Terradas G | F45: Sci Rep | G45: 2017 | H45: 42801 | I45: PMC5338330 | K45: 10.1038/srep43847
A46: 28264003 | B46: Significance of major international seaports in the distribution of murine typhus in Taiwan | C46: Kuo CC, Wardrop N, Chang CT, Wang HC, Atkinson PM. | D46: PLoS Negl Trop Dis. 2017 Mar 6;11(3):e0005430. doi: 10.1371/journal.pntd.0005430. eCollection 2017 Mar. | E46: Kuo CC | F46: PLoS Negl Trop Dis | G46: 2017 | H46: 42801 | I46: PMC5354449 | K46: 10.1371/journal.pntd.0005430
A47: 28321389 | B47: Host FIH-Mediated Asparaginyl Hydroxylation of Translocated Legionella pneumophila Effectors | C47: Price C, Merchant M, Jones S, Best A, Von Dwingelo J, Lawrenz MB, Alam N, Schueler-Furman O, Kwaik YA. | D47: Front Cell Infect Microbiol. 2017 Mar 6;7:54. doi: 10.3389/fcimb.2017.00054. eCollection 2017. | E47: Price C | F47: Front Cell Infect Microbiol | G47: 2017 | H47: 42816 | I47: PMC5337513 | K47: 10.3389/fcimb.2017.00054
A48: 28266601 | B48: Incomplete removal of Wolbachia with tetracycline has two-edged reproductive effects in the thelytokous wasp Encarsia formosa (Hymenoptera: Aphelinidae) | C48: Wang XX, Qi LD, Jiang R, Du YZ, Li YX. | D48: Sci Rep. 2017 Mar 7;7:44014. doi: 10.1038/srep44014. | E48: Wang XX | F48: Sci Rep | G48: 2017 | H48: 42802 | I48: PMC5339822 | K48: 10.1038/srep44014
A49: 28267749 | B49: The microbiome composition of Aedes aegypti is not critical for Wolbachia-mediated inhibition of dengue virus | C49: Audsley MD, Ye YH, McGraw EA. | D49: PLoS Negl Trop Dis. 2017 Mar 7;11(3):e0005426. doi: 10.1371/journal.pntd.0005426. eCollection 2017 Mar. | E49: Audsley MD | F49: PLoS Negl Trop Dis | G49: 2017 | H49: 42802 | I49: PMC5357062 | K49: 10.1371/journal.pntd.0005426
A50: 28267780 | B50: The Eurasian otter (Lutra lutra) as a potential host for rickettsial pathogens in southern Italy | C50: Santoro M, D'Alessio N, Cerrone A, Lucibelli MG, Borriello G, Aloise G, Auriemma C, Riccone N, Galiero G. | D50: PLoS One. 2017 Mar 7;12(3):e0173556. doi: 10.1371/journal.pone.0173556. eCollection 2017. | E50: Santoro M | F50: PLoS One | G50: 2017 | H50: 42802 | I50: PMC5340359 | K50: 10.1371/journal.pone.0173556
A51: 28270232 | B51: Melting pot of tick-borne zoonoses: the European hedgehog contributes to the maintenance of various tick-borne diseases in natural cycles urban and suburban areas | C51: Jahfari S, Ruyts SC, Frazer-Mendelewska E, Jaarsma R, Verheyen K, Sprong H. | D51: Parasit Vectors. 2017 Mar 7;10(1):134. doi: 10.1186/s13071-017-2065-0. | E51: Jahfari S | F51: Parasit Vectors | G51: 2017 | H51: 42803 | I51: PMC5341398 | K51: 10.1186/s13071-017-2065-0
A52: 28241146 | B52: Prophage WO genes recapitulate and enhance Wolbachia-induced cytoplasmic incompatibility | C52: LePage DP, Metcalf JA, Bordenstein SR, On J, Perlmutter JI, Shropshire JD, Layton EM, Funkhouser-Jones LJ, Beckmann JF, Bordenstein SR. | D52: Nature. 2017 Mar 9;543(7644):243-247. doi: 10.1038/nature21391. Epub 2017 Feb 27. | E52: LePage DP | F52: Nature | G52: 2017 | H52: 42794 | I52: PMC5358093 | J52: NIHMS843527 | K52: 10.1038/nature21391
A53: 28274248 | B53: A Bayesian spatio-temporal model for forecasting the prevalence of antibodies to Ehrlichia species in domestic dogs within the contiguous United States | C53: Liu Y, Lund RB, Nordone SK, Yabsley MJ, McMahan CS. | D53: Parasit Vectors. 2017 Mar 9;10(1):138. doi: 10.1186/s13071-017-2068-x. | E53: Liu Y | F53: Parasit Vectors | G53: 2017 | H53: 42804 | I53: PMC5343545 | K53: 10.1186/s13071-017-2068-x
A54: 28282373 | B54: Murine models of scrub typhus associated with host control of Orientia tsutsugamushi infection | C54: Mendell NL, Bouyer DH, Walker DH. | D54: PLoS Negl Trop Dis. 2017 Mar 10;11(3):e0005453. doi: 10.1371/journal.pntd.0005453. eCollection 2017 Mar. | E54: Mendell NL | F54: PLoS Negl Trop Dis | G54: 2017 | H54: 42805 | I54: PMC5362142 | K54: 10.1371/journal.pntd.0005453
A55: 28285583 | B55: Molecular detection of vector-borne pathogens in blood and splenic samples from dogs with splenic disease | C55: Movilla R, Altet L, Serrano L, Tabar MD, Roura X. | D55: Parasit Vectors. 2017 Mar 13;10(1):131. doi: 10.1186/s13071-017-2074-z. | E55: Movilla R | F55: Parasit Vectors | G55: 2017 | H55: 42808 | I55: PMC5346854 | K55: 10.1186/s13071-017-2074-z
A56: 28285585 | B56: Searching for Lyme borreliosis in Australia: results of a canine sentinel study | C56: Irwin PJ, Robertson ID, Westman ME, Perkins M, Straubinger RK. | D56: Parasit Vectors. 2017 Mar 13;10(1):114. doi: 10.1186/s13071-017-2058-z. | E56: Irwin PJ | F56: Parasit Vectors | G56: 2017 | H56: 42808 | I56: PMC5346834 | K56: 10.1186/s13071-017-2058-z
A57: 28285586 | B57: Serological evidence of exposure to Rickettsia felis and Rickettsia typhi in Australian veterinarians | C57: Teoh YT, Hii SF, Stevenson MA, Graves S, Rees R, Stenos J, Traub RJ. | D57: Parasit Vectors. 2017 Mar 13;10(1):129. doi: 10.1186/s13071-017-2075-y. | E57: Teoh YT | F57: Parasit Vectors | G57: 2017 | H57: 42808 | I57: PMC5346837 | K57: 10.1186/s13071-017-2075-y
A58: 28285593 | B58: The enzootic life-cycle of Borrelia burgdorferi (sensu lato) and tick-borne rickettsiae: an epidemiological study on wild-living small mammals and their ticks from Saxony, Germany | C58: Obiegala A, Król N, Oltersdorf C, Nader J, Pfeffer M. | D58: Parasit Vectors. 2017 Mar 13;10(1):115. doi: 10.1186/s13071-017-2053-4. | E58: Obiegala A | F58: Parasit Vectors | G58: 2017 | H58: 42808 | I58: PMC5346851 | K58: 10.1186/s13071-017-2053-4
A59: 28285597 | B59: Prevalence study and risk factor analysis of selected bacterial, protozoal and viral, including vector-borne, pathogens in cats from Cyprus | C59: Attipa C, Papasouliotis K, Solano-Gallego L, Baneth G, Nachum-Biala Y, Sarvani E, Knowles TG, Mengi S, Morris D, Helps C, Tasker S. | D59: Parasit Vectors. 2017 Mar 13;10(1):130. doi: 10.1186/s13071-017-2063-2. | E59: Attipa C | F59: Parasit Vectors | G59: 2017 | H59: 42808 | I59: PMC5346881 | K59: 10.1186/s13071-017-2063-2
A60: 28286343 | B60: Symbiosis: Wolbachia's matchmaking secret revealed | C60: Hofer U. | D60: Nat Rev Microbiol. 2017 Mar 13;15(4):194-195. doi: 10.1038/nrmicro.2017.25. | E60: Hofer U | F60: Nat Rev Microbiol | G60: 2017 | H60: 42808 | K60: 10.1038/nrmicro.2017.25
A61: 28348982 | B61: Tick-Pathogen Ensembles: Do Molecular Interactions Lead Ecological Innovation? | C61: Cabezas-Cruz A, Estrada-Peña A, Rego RO, De la Fuente J. | D61: Front Cell Infect Microbiol. 2017 Mar 13;7:74. doi: 10.3389/fcimb.2017.00074. eCollection 2017. | E61: Cabezas-Cruz A | F61: Front Cell Infect Microbiol | G61: 2017 | H61: 42823 | I61: PMC5346557 | K61: 10.3389/fcimb.2017.00074
A62: 28289173 | B62: Child Neurology: Rocky Mountain spotted fever encephalitis | C62: Bradshaw MJ, Lalor KB, Vu N, Pruthi S, Bloch KC. | D62: Neurology. 2017 Mar 14;88(11):e92-e95. doi: 10.1212/WNL.0000000000003722. | E62: Bradshaw MJ | F62: Neurology | G62: 2017 | H62: 42809 | K62: 10.1212/WNL.0000000000003722
A63: 28291780 | B63: Removing the needle from the haystack: Enrichment of Wolbachia endosymbiont transcripts from host nematode RNA by Cappable-seq™ | C63: Luck AN, Slatko BE, Foster JM. | D63: PLoS One. 2017 Mar 14;12(3):e0173186. doi: 10.1371/journal.pone.0173186. eCollection 2017. | E63: Luck AN | F63: PLoS One | G63: 2017 | H63: 42809 | I63: PMC5349465 | K63: 10.1371/journal.pone.0173186
A64: 28031280 | B64: Proteolytic Cleavage of the Immunodominant Outer Membrane Protein rOmpA in Rickettsia rickettsii | C64: Noriea NF, Clark TR, Mead D, Hackstadt T. | D64: J Bacteriol. 2017 Feb 28;199(6):e00826-16. doi: 10.1128/JB.00826-16. Print 2017 Mar 15. | E64: Noriea NF | F64: J Bacteriol | G64: 2017 | H64: 42734 | I64: PMC5331673 | K64: 10.1128/JB.00826-16
A65: 28288773 | B65: Serological detection of antibodies to Anaplasma spp., Borrelia burgdorferi sensu lato and Ehrlichia canis and of Dirofilaria immitis antigen in dogs from Costa Rica | C65: Montenegro VM, Bonilla MC, Kaminsky D, Romero-Zúñiga JJ, Siebert S, Krämer F. | D65: Vet Parasitol. 2017 Mar 15;236:97-107. doi: 10.1016/j.vetpar.2017.02.009. Epub 2017 Feb 14. | E65: Montenegro VM | F65: Vet Parasitol | G65: 2017 | H65: 42809 | K65: 10.1016/j.vetpar.2017.02.009
A66: 28361787 | B66: IAP Guidelines on Rickettsial Diseases in Children | C66: Rathi N, Kulkarni A, Yewale V; For Indian Academy of Pediatrics Guidelines on Rickettsial Diseases in Children Committee. | D66: Indian Pediatr. 2017 Mar 15;54(3):223-229. doi: 10.1007/s13312-017-1035-0. | E66: Rathi N | F66: Indian Pediatr | G66: 2017 | H66: 42826 | K66: 10.1007/s13312-017-1035-0
A67: 28398677 | B67: Preparing for biological threats: Addressing the needs of pregnant women | C67: Watson AK, Ellington S, Nelson C, Treadwell T, Jamieson DJ, Meaney-Delman DM. | D67: Birth Defects Res. 2017 Mar 15;109(5):391-398. doi: 10.1002/bdr2.1016. | E67: Watson AK | F67: Birth Defects Res | G67: 2017 | H67: 42837 | K67: 10.1002/bdr2.1016
A68: 28298245 | B68: Serological and molecular prevalence of canine vector-borne diseases (CVBDs) in Korea | C68: Suh GH, Ahn KS, Ahn JH, Kim HJ, Leutenegger C, Shin S. | D68: Parasit Vectors. 2017 Mar 16;10(1):146. doi: 10.1186/s13071-017-2076-x. | E68: Suh GH | F68: Parasit Vectors | G68: 2017 | H68: 42811 | I68: PMC5353868 | K68: 10.1186/s13071-017-2076-x
A69: 28303006 | B69: Short-Course, High-Dose Rifampicin Achieves Wolbachia Depletion Predictive of Curative Outcomes in Preclinical Models of Lymphatic Filariasis and Onchocerciasis | C69: Aljayyoussi G, Tyrer HE, Ford L, Sjoberg H, Pionnier N, Waterhouse D, Davies J, Gamble J, Metuge H, Cook DAN, Steven A, Sharma R, Guimaraes AF, Clare RH, Cassidy A, Johnston KL, Myhill L, Hayward L, Wanji S, Turner JD, Taylor MJ, Ward SA. | D69: Sci Rep. 2017 Mar 16;7(1):210. doi: 10.1038/s41598-017-00322-5. | E69: Aljayyoussi G | F69: Sci Rep | G69: 2017 | H69: 42812 | I69: PMC5428297 | K69: 10.1038/s41598-017-00322-5
A70: 30755946 | B70: Complicated Lemierre Syndrome Caused by Streptococcus gordonii and Possible Rickettsial Co-Infection in a Patient with Thrombophilia Predisposition | C70: Ioannou A, Dimitriou D, Dimitriou P, Katsios A, Petrikkos G. | D70: Eur J Case Rep Intern Med. 2017 Mar 17;4(5):000606. doi: 10.12890/2017_000606. eCollection 2017. | E70: Ioannou A | F70: Eur J Case Rep Intern Med | G70: 2017 | H70: 43510 | I70: PMC6346786 | K70: 10.12890/2017_000606
A71: 28378977 | B71: Prevalence of infections and co-infections with 6 pathogens in Dermacentor reticulatus ticks collected in eastern Poland | C71: Zając V, Wójcik-Fatla A, Sawczyn A, Cisak E, Sroka J, Kloc A, Zając Z, Buczek A, Dutkiewicz J, Bartosik K. | D71: Ann Agric Environ Med. 2017 Mar 21;24(1):26-32. doi: 10.5604/12321966.1233893. | E71: Zając V | F71: Ann Agric Environ Med | G71: 2017 | H71: 42831 | K71: 10.5604/12321966.1233893
A72: 28378988 | B72: Serological evidence of exposure to zoonotic tick-borne bacteria in pheasants (Phasianus colchicus) | C72: Ebani VV, Bertelloni F, Mani P. | D72: Ann Agric Environ Med. 2017 Mar 22;24(1):82-85. doi: 10.5604/12321966.1234004. | E72: Ebani VV | F72: Ann Agric Environ Med | G72: 2017 | H72: 42831 | K72: 10.5604/12321966.1234004
A73: 28340608 | B73: Molecular evidence of Rickettsia spp. in ixodid ticks and rodents in suburban, natural and rural habitats in Slovakia | C73: Minichová L, Hamšíková Z, Mahríková L, Slovák M, Kocianová E, Kazimírová M, Škultéty Ľ, Štefanidesová K, Špitalská E. | D73: Parasit Vectors. 2017 Mar 24;10(1):158. doi: 10.1186/s13071-017-2094-8. | E73: Minichová L | F73: Parasit Vectors | G73: 2017 | H73: 42820 | I73: PMC5366151 | K73: 10.1186/s13071-017-2094-8
A74: 28355307 | B74: Mediterranean spotted fever in Spain, 1997-2014: Epidemiological situation based on hospitalization records | C74: Herrador Z, Fernandez-Martinez A, Gomez-Barroso D, León I, Vieira C, Muro A, Benito A. | D74: PLoS One. 2017 Mar 29;12(3):e0174745. doi: 10.1371/journal.pone.0174745. eCollection 2017. | E74: Herrador Z | F74: PLoS One | G74: 2017 | H74: 42824 | I74: PMC5371374 | K74: 10.1371/journal.pone.0174745
A75: 28358880 | B75: Defining Brugia malayi and Wolbachia symbiosis by stage-specific dual RNA-seq | C75: Grote A, Voronin D, Ding T, Twaddle A, Unnasch TR, Lustigman S, Ghedin E. | D75: PLoS Negl Trop Dis. 2017 Mar 30;11(3):e0005357. doi: 10.1371/journal.pntd.0005357. eCollection 2017 Mar. | E75: Grote A | F75: PLoS Negl Trop Dis | G75: 2017 | H75: 42825 | I75: PMC5373514 | K75: 10.1371/journal.pntd.0005357
A76: 28424664 | B76: Spotted Fever: Epidemiology and Vector-Rickettsia-Host Relationship in Rio de Janeiro State | C76: Montenegro DC, Bitencourth K, de Oliveira SV, Borsoi AP, Cardoso KM, Sousa MSB, Giordano-Dias C, Amorim M, Serra-Freire NM, Gazêta GS, Brazil RP. | D76: Front Microbiol. 2017 Mar 30;8:505. doi: 10.3389/fmicb.2017.00505. eCollection 2017. | E76: Montenegro DC | F76: Front Microbiol | G76: 2017 | H76: 42846 | I76: PMC5371726 | K76: 10.3389/fmicb.2017.00505
A77: 28302989 | B77: Bacterial Microbiota Associated with the Glacier Ice Worm Is Dominated by Both Worm-Specific and Glacier-Derived Facultative Lineages | C77: Murakami T, Segawa T, Dial R, Takeuchi N, Kohshima S, Hongoh Y. | D77: Microbes Environ. 2017 Mar 31;32(1):32-39. doi: 10.1264/jsme2.ME16158. Epub 2017 Mar 9. | E77: Murakami T | F77: Microbes Environ | G77: 2017 | H77: 42812 | I77: PMC5371072 | K77: 10.1264/jsme2.ME16158
A78: 28368858 | B78: Epidemiological evaluation of Mediterranean spotted fever in children of the Karak province in south Jordan | C78: Nafi O, Tarawnah Y, Tarawnah A. | D78: J Infect Dev Ctries. 2017 Mar 31;11(3):242-246. doi: 10.3855/jidc.8154. | E78: Nafi O | F78: J Infect Dev Ctries | G78: 2017 | H78: 42829 | K78: 10.3855/jidc.8154
A79: 27935594 | B79: Plantmediated horizontal transmission of Wolbachia between whiteflies | C79: Li SJ, Ahmed MZ, Lv N, Shi PQ, Wang XM, Huang JL, Qiu BL. | D79: ISME J. 2017 Apr;11(4):1019-1028. doi: 10.1038/ismej.2016.164. Epub 2016 Dec 9. | E79: Li SJ | F79: ISME J | G79: 2017 | H79: 42714 | I79: PMC5364347 | K79: 10.1038/ismej.2016.164
A80: 27966221 | B80: Determination of the microbial community features of Haemaphysalis flava in different developmental stages by high-throughput sequencing | C80: Duan D, Cheng T. | D80: J Basic Microbiol. 2017 Apr;57(4):302-308. doi: 10.1002/jobm.201600557. Epub 2016 Dec 14. | E80: Duan D | F80: J Basic Microbiol | G80: 2017 | H80: 42719 | K80: 10.1002/jobm.201600557
A81: 28011315 | B81: Purpura from a Tick Bite | C81: Iyer AS, O'Horo JC, Thompson R. | D81: Am J Med. 2017 Apr;130(4):e131-e132. doi: 10.1016/j.amjmed.2016.11.024. Epub 2016 Dec 21. | E81: Iyer AS | F81: Am J Med | G81: 2017 | H81: 42729 | K81: 10.1016/j.amjmed.2016.11.024
A82: 28036138 | B82: Early diagnosis of Ehrlichia ewingii infection in a lung transplant recipient by peripheral blood smear | C82: Regunath H, Rojas-Moreno C, Olano JP, Hammer RD, Salzer W. | D82: Transpl Infect Dis. 2017 Apr;19(2). doi: 10.1111/tid.12652. Epub 2017 Feb 15. | E82: Regunath H | F82: Transpl Infect Dis | G82: 2017 | H82: 42735 | K82: 10.1111/tid.12652
A83: 28055326 | B83: Prevalence and Distribution of Human and Tick Infections with the Ehrlichia muris-Like Agent and Anaplasma phagocytophilum in Wisconsin, 2009-2015 | C83: Murphy DS, Lee X, Larson SR, Johnson DK, Loo T, Paskewitz SM. | D83: Vector Borne Zoonotic Dis. 2017 Apr;17(4):229-236. doi: 10.1089/vbz.2016.2055. Epub 2017 Jan 5. | E83: Murphy DS | F83: Vector Borne Zoonotic Dis | G83: 2017 | H83: 42741 | K83: 10.1089/vbz.2016.2055
A84: 28055333 | B84: Differences in Clinical and Laboratory Features for Different Genotypes of Orientia tsutsugamushi in Guangzhou, Southern China | C84: Wei Y, Ma Y, Luo L, Wu X, Huang Y, Li X, Yang Z. | D84: Vector Borne Zoonotic Dis. 2017 Apr;17(4):260-267. doi: 10.1089/vbz.2016.2045. Epub 2017 Jan 5. | E84: Wei Y | F84: Vector Borne Zoonotic Dis | G84: 2017 | H84: 42741 | K84: 10.1089/vbz.2016.2045
A85: 28072914 | B85: Presence of Pathogenic Rickettsiae and Protozoan in Samples of Raw Milk from Cows, Goats, and Sheep | C85: Cisak E, Zając V, Sroka J, Sawczyn A, Kloc A, Dutkiewicz J, Wójcik-Fatla A. | D85: Foodborne Pathog Dis. 2017 Apr;14(4):189-194. doi: 10.1089/fpd.2016.2203. Epub 2017 Jan 10. | E85: Cisak E | F85: Foodborne Pathog Dis | G85: 2017 | H85: 42746 | K85: 10.1089/fpd.2016.2203
A86: 28077317 | B86: Zoonotic pathogens in Atlantic Forest wild rodents in Brazil: Bartonella and Coxiella infections | C86: Rozental T, Ferreira MS, Guterres A, Mares-Guia MA, Teixeira BR, Gonçalves J, Bonvicino CR, D'Andrea PS, de Lemos ER. | D86: Acta Trop. 2017 Apr;168:64-73. doi: 10.1016/j.actatropica.2017.01.003. Epub 2017 Jan 8. | E86: Rozental T | F86: Acta Trop | G86: 2017 | H86: 42748 | K86: 10.1016/j.actatropica.2017.01.003
A87: 28082006 | B87: Molecular diversity of Wolbachia in Lepidoptera: Prevalent allelic content and high recombination of MLST genes | C87: Ilinsky Y, Kosterin OE. | D87: Mol Phylogenet Evol. 2017 Apr;109:164-179. doi: 10.1016/j.ympev.2016.12.034. Epub 2017 Jan 8. | E87: Ilinsky Y | F87: Mol Phylogenet Evol | G87: 2017 | H87: 42749 | K87: 10.1016/j.ympev.2016.12.034
A88: 28087534 | B88: Mechanisms of Horizontal Cell-to-Cell Transfer of Wolbachia spp. in Drosophila melanogaster | C88: White PM, Pietri JE, Debec A, Russell S, Patel B, Sullivan W. | D88: Appl Environ Microbiol. 2017 Mar 17;83(7):e03425-16. doi: 10.1128/AEM.03425-16. Print 2017 Apr 1. | E88: White PM | F88: Appl Environ Microbiol | G88: 2017 | H88: 42750 | I88: PMC5359480 | K88: 10.1128/AEM.03425-16
A89: 28115672 | B89: Rickettsia felis Infection in Febrile Children, Ghana | C89: Sothmann P, Keller C, Krumkamp R, Kreuels B, Aldrich C, Sarpong N, Steierberg S, Winter D, Boahen KG, Owusu-Dabo E, May J, Eibach D. | D89: Am J Trop Med Hyg. 2017 Apr;96(4):783-785. doi: 10.4269/ajtmh.16-0754. Epub 2017 Jan 23. | E89: Sothmann P | F89: Am J Trop Med Hyg | G89: 2017 | H89: 42760 | I89: PMC5392620 | K89: 10.4269/ajtmh.16-0754
A90: 28118097 | B90: A Loop-Mediated Isothermal Amplification Assay Targeting 16S rRNA Gene for Rapid Detection of Anaplasma phagocytophilum Infection in Sheep and Goats | C90: Wang J, Zhang Y, Wang X, Cui Y, Yan Y, Wang R, Jian F, Zhang L, Ning C. | D90: J Parasitol. 2017 Apr;103(2):187-192. doi: 10.1645/16-158. Epub 2017 Jan 24. | E90: Wang J | F90: J Parasitol | G90: 2017 | H90: 42760 | K90: 10.1645/16-158
A91: 28122249 | B91: Genetic diversity and molecular epidemiology of Anaplasma | C91: Battilani M, De Arcangeli S, Balboni A, Dondi F. | D91: Infect Genet Evol. 2017 Apr;49:195-211. doi: 10.1016/j.meegid.2017.01.021. Epub 2017 Jan 22. | E91: Battilani M | F91: Infect Genet Evol | G91: 2017 | H91: 42761 | K91: 10.1016/j.meegid.2017.01.021
A92: 28130168 | B92: Anaplasma platys-like strains in ruminants from Tunisia | C92: Ben Said M, Belkahia H, El Mabrouk N, Saidani M, Alberti A, Zobba R, Cherif A, Mahjoub T, Bouattour A, Messadi L. | D92: Infect Genet Evol. 2017 Apr;49:226-233. doi: 10.1016/j.meegid.2017.01.023. Epub 2017 Jan 24. | E92: Ben Said M | F92: Infect Genet Evol | G92: 2017 | H92: 42764 | K92: 10.1016/j.meegid.2017.01.023
A93: 28135131 | B93: HEALTH SURVEY OF FREE-RANGING RACCOONS (PROCYON LOTOR) IN CENTRAL PARK, NEW YORK, NEW YORK, USA: IMPLICATIONS FOR HUMAN AND DOMESTIC ANIMAL HEALTH | C93: Rainwater KL, Marchese K, Slavinski S, Humberg LA, Dubovi EJ, Jarvis JA, McAloose D, Calle PP. | D93: J Wildl Dis. 2017 Apr;53(2):272-284. doi: 10.7589/2016-05-096. Epub 2017 Jan 30. | E93: Rainwater KL | F93: J Wildl Dis | G93: 2017 | H93: 42766 | K93: 10.7589/2016-05-096
A94: 28151084 | B94: Molecular Detection of Anaplasma phagocytophilum in Wild Cervids and Hares in China | C94: Yang J, Liu Z, Niu Q, Luo J, Wang X, Yin H. | D94: J Wildl Dis. 2017 Apr;53(2):420-423. doi: 10.7589/2016-09-215. Epub 2017 Feb 2. | E94: Yang J | F94: J Wildl Dis | G94: 2017 | H94: 42769 | K94: 10.7589/2016-09-215
A95: 28156001 | B95: Zika virus infection and Wolbachia (comment on DOI: 10.1002/bies.201600175) | C95: Joob B, Wiwanitkit V. | D95: Bioessays. 2017 Apr;39(4). doi: 10.1002/bies.201600267. Epub 2017 Feb 3. | E95: Joob B | F95: Bioessays | G95: 2017 | H95: 42770 | K95: 10.1002/bies.201600267
A96: 28159754 | B96: Reliance of Wolbachia on High Rates of Host Proteolysis Revealed by a Genome-Wide RNAi Screen of Drosophila Cells | C96: White PM, Serbus LR, Debec A, Codina A, Bray W, Guichet A, Lokey RS, Sullivan W. | D96: Genetics. 2017 Apr;205(4):1473-1488. doi: 10.1534/genetics.116.198903. Epub 2017 Feb 3. | E96: White PM | F96: Genetics | G96: 2017 | H96: 42771 | I96: PMC5378107 | K96: 10.1534/genetics.116.198903
A97: 28181227 | B97: Independent cytoplasmic incompatibility induced by Cardinium and Wolbachia maintains endosymbiont coinfections in haplodiploid thrips populations | C97: Nguyen DT, Morrow JL, Spooner-Hart RN, Riegler M. | D97: Evolution. 2017 Apr;71(4):995-1008. doi: 10.1111/evo.13197. Epub 2017 Mar 11. | E97: Nguyen DT | F97: Evolution | G97: 2017 | H97: 42776 | K97: 10.1111/evo.13197
A98: 28322701 | B98: Typhus Group Rickettsiosis, Texas, USA, 2003-2013 | C98: Murray KO, Evert N, Mayes B, Fonken E, Erickson T, Garcia MN, Sidwa T. | D98: Emerg Infect Dis. 2017 Apr;23(4):645-648. doi: 10.3201/eid2304.160958. | E98: Murray KO | F98: Emerg Infect Dis | G98: 2017 | H98: 42816 | I98: PMC5367421 | K98: 10.3201/eid2304.160958
A99: 28417248 | B99: Ticks and tick-borne pathogens of dogs along an elevational and land-use gradient in Chiriquí province, Panamá | C99: Ferrell AM, Brinkerhoff RJ, Bernal J, Bermúdez SE. | D99: Exp Appl Acarol. 2017 Apr;71(4):371-385. doi: 10.1007/s10493-017-0116-z. Epub 2017 Apr 17. | E99: Ferrell AM | F99: Exp Appl Acarol | G99: 2017 | H99: 42844 | K99: 10.1007/s10493-017-0116-z
A100: 28504099 | B100: Zoonotic intestinal parasites and vector-borne pathogens in Italian shelter and kennel dogs | C100: Traversa D, Di Cesare A, Simonato G, Cassini R, Merola C, Diakou A, Halos L, Beugnet F, Frangipane di Regalbono A. | D100: Comp Immunol Microbiol Infect Dis. 2017 Apr;51:69-75. doi: 10.1016/j.cimid.2017.04.003. Epub 2017 Apr 21. | E100: Traversa D | F100: Comp Immunol Microbiol Infect Dis | G100: 2017 | H100: 42871 | K100: 10.1016/j.cimid.2017.04.003
...

Sheet Palabras claves
A1: PMID | B1: Title | C1: Authors | D1: Citation | E1: First Author | F1: Journal/Book | G1: Publication Year | H1: Create Date | I1: PMCID | J1: NIHMS ID | K1: DOI | L1: Alerta
A2: 22282331 | B2: Tetracyclines and pain | C2: Bastos LF, de Oliveira AC, Watkins LR, Moraes MF, Coelho MM. | D2: Naunyn Schmiedebergs Arch Pharmacol. 2012 Mar;385(3):225-41. doi: 10.1007/s00210-012-0727-1. Epub 2012 Jan 27. | E2: Bastos LF | F2: Naunyn Schmiedebergs Arch Pharmacol | G2: 2012 | H2: 40936 | K2: 10.1007/s00210-012-0727-1 | L2: =IF(ISNUMBER(VLOOKUP(A2,PRE,1,FALSE)),"PreAlerta",IF(ISNUMBER(VLOOKUP(A2,POST,1,FALSE)),"PostAlerta",IF(ISNUMBER(VLOOKUP(A2,EXCL,1,FALSE)),"Excluida","no incluido"))) -> PreAlerta
A3: 22392278 | B3: Preliminary analysis to target pyruvate phosphate dikinase from wolbachia endosymbiont of Brugia malayi for designing anti-filarial agents | C3: Palayam M, Lakshminarayanan K, Radhakrishnan M, Krishnaswamy G. | D3: Interdiscip Sci. 2012 Mar;4(1):74-82. doi: 10.1007/s12539-011-0109-2. Epub 2012 Mar 6. | E3: Palayam M | F3: Interdiscip Sci | G3: 2012 | H3: 40975 | K3: 10.1007/s12539-011-0109-2 | L3: =IF(ISNUMBER(VLOOKUP(A3,PRE,1,FALSE)),"PreAlerta",IF(ISNUMBER(VLOOKUP(A3,POST,1,FALSE)),"PostAlerta",IF(ISNUMBER(VLOOKUP(A3,EXCL,1,FALSE)),"Excluida","no incluido"))) -> PreAlerta
A4: 22617213 | B4: Contribution of NK cells to the innate phase of host protection against an intracellular bacterium targeting systemic endothelium | C4: Fang R, Ismail N, Walker DH. | D4: Am J Pathol. 2012 Jul;181(1):185-95. doi: 10.1016/j.ajpath.2012.03.020. Epub 2012 May 19. | E4: Fang R | F4: Am J Pathol | G4: 2012 | H4: 41053 | I4: PMC3388147 | K4: 10.1016/j.ajpath.2012.03.020 | L4: =IF(ISNUMBER(VLOOKUP(A4,PRE,1,FALSE)),"PreAlerta",IF(ISNUMBER(VLOOKUP(A4,POST,1,FALSE)),"PostAlerta",IF(ISNUMBER(VLOOKUP(A4,EXCL,1,FALSE)),"Excluida","no incluido"))) -> PreAlerta
A5: 23077805 | B5: Susceptibility of Wolbachia, an endosymbiont of Brugia malayi microfilariae, to doxycycline determined by quantitative PCR assay | C5: Sungpradit S, Chatsuwan T, Nuchprayoon S. | D5: Southeast Asian J Trop Med Public Health. 2012 Jul;43(4):841-50. | E5: Sungpradit S | F5: Southeast Asian J Trop Med Public Health | G5: 2012 | H5: 41202 | L5: =IF(ISNUMBER(VLOOKUP(A5,PRE,1,FALSE)),"PreAlerta",IF(ISNUMBER(VLOOKUP(A5,POST,1,FALSE)),"PostAlerta",IF(ISNUMBER(VLOOKUP(A5,EXCL,1,FALSE)),"Excluida","no incluido"))) -> PreAlerta
A6: 22586066 | B6: Corallopyronin A specifically targets and depletes essential obligate Wolbachia endobacteria from filarial nematodes in vivo | C6: Schiefer A, Schmitz A, Schäberle TF, Specht S, Lämmer C, Johnston KL, Vassylyev DG, König GM, Hoerauf A, Pfarr K. | D6: J Infect Dis. 2012 Jul 15;206(2):249-57. doi: 10.1093/infdis/jis341. Epub 2012 May 14. | E6: Schiefer A | F6: J Infect Dis | G6: 2012 | H6: 41045 | I6: PMC3490692 | K6: 10.1093/infdis/jis341 | L6: =IF(ISNUMBER(VLOOKUP(A6,PRE,1,FALSE)),"PreAlerta",IF(ISNUMBER(VLOOKUP(A6,POST,1,FALSE)),"PostAlerta",IF(ISNUMBER(VLOOKUP(A6,EXCL,1,FALSE)),"Excluida","no incluido"))) -> PreAlerta
A7: 22415481 | B7: The role of cytoskeleton, components of inositol phospholipid signaling pathway and iron in Ehrlichia canis in vitro proliferation | C7: Levenhagen MA, Alves RN, Rieck SE, Labruna MB, Beletti ME. | D7: Vet Res Commun. 2012 Sep;36(3):195-9. doi: 10.1007/s11259-012-9525-y. Epub 2012 Mar 14. | E7: Levenhagen MA | F7: Vet Res Commun | G7: 2012 | H7: 40983 | K7: 10.1007/s11259-012-9525-y | L7: =IF(ISNUMBER(VLOOKUP(A7,PRE,1,FALSE)),"PreAlerta",IF(ISNUMBER(VLOOKUP(A7,POST,1,FALSE)),"PostAlerta",IF(ISNUMBER(VLOOKUP(A7,EXCL,1,FALSE)),"Excluida","no incluido"))) -> PreAlerta
A8: 22843518 | B8: Antiviral protection and the importance of Wolbachia density and tissue tropism in Drosophila simulans | C8: Osborne SE, Iturbe-Ormaetxe I, Brownlie JC, O'Neill SL, Johnson KN. | D8: Appl Environ Microbiol. 2012 Oct;78(19):6922-9. doi: 10.1128/AEM.01727-12. Epub 2012 Jul 27. | E8: Osborne SE | F8: Appl Environ Microbiol | G8: 2012 | H8: 41121 | I8: PMC3457512 | K8: 10.1128/AEM.01727-12 | L8: =IF(ISNUMBER(VLOOKUP(A8,PRE,1,FALSE)),"PreAlerta",IF(ISNUMBER(VLOOKUP(A8,POST,1,FALSE)),"PostAlerta",IF(ISNUMBER(VLOOKUP(A8,EXCL,1,FALSE)),"Excluida","no incluido"))) -> PreAlerta
A9: 23096683 | B9: In silico characterization of three two-component systems of Ehrlichia canis and evaluation of a natural plant-derived inhibitor | C9: Santos EV, Silva G, Cardozo GP, Bitencourt TA, França SC, Fachin AL, Marins M. | D9: Genet Mol Res. 2012 Oct 4;11(4):3576-84. doi: 10.4238/2012.October.4.5. | E9: Santos EV | F9: Genet Mol Res | G9: 2012 | H9: 41208 | K9: 10.4238/2012.October.4.5 | L9: =IF(ISNUMBER(VLOOKUP(A9,PRE,1,FALSE)),"PreAlerta",IF(ISNUMBER(VLOOKUP(A9,POST,1,FALSE)),"PostAlerta",IF(ISNUMBER(VLOOKUP(A9,EXCL,1,FALSE)),"Excluida","no incluido"))) -> PreAlerta
A10: 22889830 | B10: The genome of the heartworm, Dirofilaria immitis, reveals drug and vaccine targets | C10: Godel C, Kumar S, Koutsovoulos G, Ludin P, Nilsson D, Comandatore F, Wrobel N, Thompson M, Schmid CD, Goto S, Bringaud F, Wolstenholme A, Bandi C, Epe C, Kaminsky R, Blaxter M, Mäser P. | D10: FASEB J. 2012 Nov;26(11):4650-61. doi: 10.1096/fj.12-205096. Epub 2012 Aug 13. | E10: Godel C | F10: FASEB J | G10: 2012 | H10: 41136 | I10: PMC3475251 | K10: 10.1096/fj.12-205096 | L10: =IF(ISNUMBER(VLOOKUP(A10,PRE,1,FALSE)),"PreAlerta",IF(ISNUMBER(VLOOKUP(A10,POST,1,FALSE)),"PostAlerta",IF(ISNUMBER(VLOOKUP(A10,EXCL,1,FALSE)),"Excluida","no incluido"))) -> PreAlerta
A11: 23244493 | B11: Acaricidal activity of ethanolic extract from aerial parts of Tagetes patula L. (Asteraceae) against larvae and engorged adult females of Rhipicephalus sanguineus (Latreille, 1806) | C11: Politi FA, Figueira GM, Araújo AM, Sampieri BR, Mathias MI, Szabó MP, Bechara GH, Dos Santos LC, Vilegas W, Pietro RC. | D11: Parasit Vectors. 2012 Dec 17;5:295. doi: 10.1186/1756-3305-5-295. | E11: Politi FA | F11: Parasit Vectors | G11: 2012 | H11: 41262 | I11: PMC3533920 | K11: 10.1186/1756-3305-5-295 | L11: =IF(ISNUMBER(VLOOKUP(A11,PRE,1,FALSE)),"PreAlerta",IF(ISNUMBER(VLOOKUP(A11,POST,1,FALSE)),"PostAlerta",IF(ISNUMBER(VLOOKUP(A11,EXCL,1,FALSE)),"Excluida","no incluido"))) -> PreAlerta
A12: 23079772 | B12: Recombinant translation initiation factor-1 of Wolbachia is an immunogenic excretory secretory protein that elicits Th2 mediated immune protection against Brugia malayi | C12: Nag JK, Shrivastava N, Gupta J, Misra-Bhattacharya S. | D12: Comp Immunol Microbiol Infect Dis. 2013 Jan;36(1):25-38. doi: 10.1016/j.cimid.2012.09.004. Epub 2012 Oct 15. | E12: Nag JK | F12: Comp Immunol Microbiol Infect Dis | G12: 2013 | H12: 41202 | K12: 10.1016/j.cimid.2012.09.004 | L12: =IF(ISNUMBER(VLOOKUP(A12,PRE,1,FALSE)),"PreAlerta",IF(ISNUMBER(VLOOKUP(A12,POST,1,FALSE)),"PostAlerta",IF(ISNUMBER(VLOOKUP(A12,EXCL,1,FALSE)),"Excluida","no incluido"))) -> PreAlerta
A13: 23271364 | B13: Wolbachia from the planthopper Laodelphax striatellus establishes a robust, persistent, streptomycin-resistant infection in clonal mosquito cells | C13: Fallon AM, Baldridge GD, Higgins LA, Witthuhn BA. | D13: In Vitro Cell Dev Biol Anim. 2013 Jan;49(1):66-73. doi: 10.1007/s11626-012-9571-3. Epub 2012 Dec 28. | E13: Fallon AM | F13: In Vitro Cell Dev Biol Anim | G13: 2013 | H13: 41272 | I13: PMC3630504 | J13: NIHMS457436 | K13: 10.1007/s11626-012-9571-3 | L13: =IF(ISNUMBER(VLOOKUP(A13,PRE,1,FALSE)),"PreAlerta",IF(ISNUMBER(VLOOKUP(A13,POST,1,FALSE)),"PostAlerta",IF(ISNUMBER(VLOOKUP(A13,EXCL,1,FALSE)),"Excluida","no incluido"))) -> PreAlerta
A14: 23555728 | B14: wFlu: characterization and evaluation of a native Wolbachia from the mosquito Aedes fluviatilis as a potential vector control agent | C14: Baton LA, Pacidônio EC, Gonçalves DS, Moreira LA. | D14: PLoS One. 2013;8(3):e59619. doi: 10.1371/journal.pone.0059619. Epub 2013 Mar 26. | E14: Baton LA | F14: PLoS One | G14: 2013 | H14: 41369 | I14: PMC3608659 | K14: 10.1371/journal.pone.0059619 | L14: =IF(ISNUMBER(VLOOKUP(A14,PRE,1,FALSE)),"PreAlerta",IF(ISNUMBER(VLOOKUP(A14,POST,1,FALSE)),"PostAlerta",IF(ISNUMBER(VLOOKUP(A14,EXCL,1,FALSE)),"Excluida","no incluido"))) -> PreAlerta
A15: 24135158 | B15: The efficacy of Advantix® to prevent transmission of Ehrlichia canis to dogs by Rhipicephalus sanguineus ticks | C15: Fourie JJ, Luus HG, Stanneck D, Jongejan F. | D15: Parasite. 2013;20:36. doi: 10.1051/parasite/2013037. Epub 2013 Oct 21. | E15: Fourie JJ | F15: Parasite | G15: 2013 | H15: 41566 | I15: PMC3798889 | K15: 10.1051/parasite/2013037 | L15: =IF(ISNUMBER(VLOOKUP(A15,PRE,1,FALSE)),"PreAlerta",IF(ISNUMBER(VLOOKUP(A15,POST,1,FALSE)),"PostAlerta",IF(ISNUMBER(VLOOKUP(A15,EXCL,1,FALSE)),"Excluida","no incluido"))) -> PreAlerta
A16: 23316486 | B16: Approaches to vaccines against Orientia tsutsugamushi | C16: Valbuena G, Walker DH. | D16: Front Cell Infect Microbiol. 2013 Jan 4;2:170. doi: 10.3389/fcimb.2012.00170. eCollection 2012. | E16: Valbuena G | F16: Front Cell Infect Microbiol | G16: 2013 | H16: 41289 | I16: PMC3539663 | K16: 10.3389/fcimb.2012.00170 | L16: =IF(ISNUMBER(VLOOKUP(A16,PRE,1,FALSE)),"PreAlerta",IF(ISNUMBER(VLOOKUP(A16,POST,1,FALSE)),"PostAlerta",IF(ISNUMBER(VLOOKUP(A16,EXCL,1,FALSE)),"Excluida","no incluido"))) -> PreAlerta
A17: 23398406 | B17: The symbiotic role of Wolbachia in Onchocercidae and its impact on filariasis | C17: Bouchery T, Lefoulon E, Karadjian G, Nieguitsila A, Martin C. | D17: Clin Microbiol Infect. 2013 Feb;19(2):131-40. doi: 10.1111/1469-0691.12069. | E17: Bouchery T | F17: Clin Microbiol Infect | G17: 2013 | H17: 41318 | K17: 10.1111/1469-0691.12069 | L17: =IF(ISNUMBER(VLOOKUP(A17,PRE,1,FALSE)),"PreAlerta",IF(ISNUMBER(VLOOKUP(A17,POST,1,FALSE)),"PostAlerta",IF(ISNUMBER(VLOOKUP(A17,EXCL,1,FALSE)),"Excluida","no incluido"))) -> PreAlerta
A18: 23394970 | B18: Decontamination of mycoplasma-contaminated Orientia tsutsugamushi strains by repeating passages through cell cultures with antibiotics | C18: Ogawa M, Uchiyama T, Satoh M, Ando S. | D18: BMC Microbiol. 2013 Feb 8;13:32. doi: 10.1186/1471-2180-13-32. | E18: Ogawa M | F18: BMC Microbiol | G18: 2013 | H18: 41317 | I18: PMC3598641 | K18: 10.1186/1471-2180-13-32 | L18: =IF(ISNUMBER(VLOOKUP(A18,PRE,1,FALSE)),"PreAlerta",IF(ISNUMBER(VLOOKUP(A18,POST,1,FALSE)),"PostAlerta",IF(ISNUMBER(VLOOKUP(A18,EXCL,1,FALSE)),"Excluida","no incluido"))) -> PreAlerta
A19: 23438747 | B19: A selective inhibitor of heme biosynthesis in endosymbiotic bacteria elicits antifilarial activity in vitro | C19: Lentz CS, Halls V, Hannam JS, Niebel B, Strübing U, Mayer G, Hoerauf A, Famulok M, Pfarr KM. | D19: Chem Biol. 2013 Feb 21;20(2):177-87. doi: 10.1016/j.chembiol.2012.11.009. | E19: Lentz CS | F19: Chem Biol | G19: 2013 | H19: 41332 | K19: 10.1016/j.chembiol.2012.11.009 | L19: =IF(ISNUMBER(VLOOKUP(A19,PRE,1,FALSE)),"PreAlerta",IF(ISNUMBER(VLOOKUP(A19,POST,1,FALSE)),"PostAlerta",IF(ISNUMBER(VLOOKUP(A19,EXCL,1,FALSE)),"Excluida","no incluido"))) -> PreAlerta
A20: 23262214 | B20: Filamentation temperature-sensitive protein Z (FtsZ) of Wolbachia, endosymbiont of Wuchereria bancrofti: a potential target for anti-filarial chemotherapy | C20: Sharma R, Hoti SL, Vasuki V, Sankari T, Meena RL, Das PK. | D20: Acta Trop. 2013 Mar;125(3):330-8. doi: 10.1016/j.actatropica.2012.12.004. Epub 2012 Dec 19. | E20: Sharma R | F20: Acta Trop | G20: 2013 | H20: 41268 | K20: 10.1016/j.actatropica.2012.12.004 | L20: =IF(ISNUMBER(VLOOKUP(A20,PRE,1,FALSE)),"PreAlerta",IF(ISNUMBER(VLOOKUP(A20,POST,1,FALSE)),"PostAlerta",IF(ISNUMBER(VLOOKUP(A20,EXCL,1,FALSE)),"Excluida","no incluido"))) -> PreAlerta
A21: 23210448 | B21: Wolbachia filarial interactions | C21: Taylor MJ, Voronin D, Johnston KL, Ford L. | D21: Cell Microbiol. 2013 Apr;15(4):520-6. doi: 10.1111/cmi.12084. Epub 2012 Dec 24. | E21: Taylor MJ | F21: Cell Microbiol | G21: 2013 | H21: 41249 | K21: 10.1111/cmi.12084 | L21: =IF(ISNUMBER(VLOOKUP(A21,PRE,1,FALSE)),"PreAlerta",IF(ISNUMBER(VLOOKUP(A21,POST,1,FALSE)),"PostAlerta",IF(ISNUMBER(VLOOKUP(A21,EXCL,1,FALSE)),"Excluida","no incluido"))) -> PreAlerta
A22: 23440444 | B22: Direct and indirect plant defenses are not suppressed by endosymbionts of a specialist root herbivore | C22: Robert CA, Frank DL, Leach KA, Turlings TC, Hibbard BE, Erb M. | D22: J Chem Ecol. 2013 Apr;39(4):507-15. doi: 10.1007/s10886-013-0264-5. Epub 2013 Feb 26. | E22: Robert CA | F22: J Chem Ecol | G22: 2013 | H22: 41332 | K22: 10.1007/s10886-013-0264-5 | L22: =IF(ISNUMBER(VLOOKUP(A22,PRE,1,FALSE)),"PreAlerta",IF(ISNUMBER(VLOOKUP(A22,POST,1,FALSE)),"PostAlerta",IF(ISNUMBER(VLOOKUP(A22,EXCL,1,FALSE)),"Excluida","no incluido"))) -> PreAlerta
A23: 23678256 | B23: Inappropriateness of quinolone in scrub typhus treatment due to gyrA mutation in Orientia tsutsugamushi Boryong strain | C23: Jang HC, Choi SM, Jang MO, Ahn JH, Kim UJ, Kang SJ, Shin JH, Choy HE, Jung SI, Park KH. | D23: J Korean Med Sci. 2013 May;28(5):667-71. doi: 10.3346/jkms.2013.28.5.667. Epub 2013 May 2. | E23: Jang HC | F23: J Korean Med Sci | G23: 2013 | H23: 41411 | I23: PMC3653077 | K23: 10.3346/jkms.2013.28.5.667 | L23: =IF(ISNUMBER(VLOOKUP(A23,PRE,1,FALSE)),"PreAlerta",IF(ISNUMBER(VLOOKUP(A23,POST,1,FALSE)),"PostAlerta",IF(ISNUMBER(VLOOKUP(A23,EXCL,1,FALSE)),"Excluida","no incluido"))) -> PreAlerta
A24: 23113940 | B24: Infection, growth and maintenance of Wolbachia pipientis in clonal and non-clonal Aedes albopictus cell cultures | C24: Khoo CC, Venard CM, Fu Y, Mercer DR, Dobson SL. | D24: Bull Entomol Res. 2013 Jun;103(3):251-60. doi: 10.1017/S0007485312000648. Epub 2012 Nov 1. | E24: Khoo CC | F24: Bull Entomol Res | G24: 2013 | H24: 41215 | K24: 10.1017/S0007485312000648 | L24: =IF(ISNUMBER(VLOOKUP(A24,PRE,1,FALSE)),"PreAlerta",IF(ISNUMBER(VLOOKUP(A24,POST,1,FALSE)),"PostAlerta",IF(ISNUMBER(VLOOKUP(A24,EXCL,1,FALSE)),"Excluida","no incluido"))) -> PreAlerta
A25: 23406008 | B25: Pharmacokinetics, pharmacodynamics and therapeutics of pradofloxacin in the dog and cat | C25: Lees P. | D25: J Vet Pharmacol Ther. 2013 Jun;36(3):209-21. doi: 10.1111/jvp.12036. Epub 2013 Feb 14. | E25: Lees P | F25: J Vet Pharmacol Ther | G25: 2013 | H25: 41320 | K25: 10.1111/jvp.12036 | L25: =IF(ISNUMBER(VLOOKUP(A25,PRE,1,FALSE)),"PreAlerta",IF(ISNUMBER(VLOOKUP(A25,POST,1,FALSE)),"PostAlerta",IF(ISNUMBER(VLOOKUP(A25,EXCL,1,FALSE)),"Excluida","no incluido"))) -> PreAlerta
A26: 23508761 | B26: Chemical characterization and acaricide potential of essential oil from aerial parts of Tagetes patula L. (Asteraceae) against engorged adult females of Rhipicephalus sanguineus (Latreille, 1806) | C26: Politi FA, de Souza-Moreira TM, Rodrigues ER, de Queiroz GM, Figueira GM, Januário AH, Berenger JM, Socolovschi C, Parola P, Pietro RC. | D26: Parasitol Res. 2013 Jun;112(6):2261-8. doi: 10.1007/s00436-013-3386-3. Epub 2013 Mar 19. | E26: Politi FA | F26: Parasitol Res | G26: 2013 | H26: 41353 | K26: 10.1007/s00436-013-3386-3 | L26: =IF(ISNUMBER(VLOOKUP(A26,PRE,1,FALSE)),"PreAlerta",IF(ISNUMBER(VLOOKUP(A26,POST,1,FALSE)),"PostAlerta",IF(ISNUMBER(VLOOKUP(A26,EXCL,1,FALSE)),"Excluida","no incluido"))) -> PreAlerta
A27: 23584755 | B27: The ClpP peptidase of Wolbachia endobacteria is a novel target for drug development against filarial infections | C27: Schiefer A, Vollmer J, Lämmer C, Specht S, Lentz C, Ruebsamen-Schaeff H, Brötz-Oesterhelt H, Hoerauf A, Pfarr K. | D27: J Antimicrob Chemother. 2013 Aug;68(8):1790-800. doi: 10.1093/jac/dkt105. Epub 2013 Apr 12. | E27: Schiefer A | F27: J Antimicrob Chemother | G27: 2013 | H27: 41380 | K27: 10.1093/jac/dkt105 | L27: =IF(ISNUMBER(VLOOKUP(A27,PRE,1,FALSE)),"PreAlerta",IF(ISNUMBER(VLOOKUP(A27,POST,1,FALSE)),"PostAlerta",IF(ISNUMBER(VLOOKUP(A27,EXCL,1,FALSE)),"Excluida","no incluido"))) -> PreAlerta
A28: 23719839 | B28: The oxidizing agent, paraquat, is more toxic to Wolbachia than to mosquito host cells | C28: Fallon AM, Kurtz CM, Carroll EM. | D28: In Vitro Cell Dev Biol Anim. 2013 Aug;49(7):501-7. doi: 10.1007/s11626-013-9634-0. Epub 2013 May 30. | E28: Fallon AM | F28: In Vitro Cell Dev Biol Anim | G28: 2013 | H28: 41425 | I28: PMC4383088 | J28: NIHMS675907 | K28: 10.1007/s11626-013-9634-0 | L28: =IF(ISNUMBER(VLOOKUP(A28,PRE,1,FALSE)),"PreAlerta",IF(ISNUMBER(VLOOKUP(A28,POST,1,FALSE)),"PostAlerta",IF(ISNUMBER(VLOOKUP(A28,EXCL,1,FALSE)),"Excluida","no incluido"))) -> PreAlerta
A29: 23733469 | B29: Molecular characterization of an rsmD-like rRNA methyltransferase from the Wolbachia endosymbiont of Brugia malayi and antifilarial activity of specific inhibitors of the enzyme | C29: Rana AK, Chandra S, Siddiqi MI, Misra-Bhattacharya S. | D29: Antimicrob Agents Chemother. 2013 Aug;57(8):3843-56. doi: 10.1128/AAC.02264-12. Epub 2013 Jun 3. | E29: Rana AK | F29: Antimicrob Agents Chemother | G29: 2013 | H29: 41430 | I29: PMC3719755 | K29: 10.1128/AAC.02264-12 | L29: =IF(ISNUMBER(VLOOKUP(A29,PRE,1,FALSE)),"PreAlerta",IF(ISNUMBER(VLOOKUP(A29,POST,1,FALSE)),"PostAlerta",IF(ISNUMBER(VLOOKUP(A29,EXCL,1,FALSE)),"Excluida","no incluido"))) -> PreAlerta
A30: 23951381 | B30: Wolbachia-associated bacterial protection in the mosquito Aedes aegypti | C30: Ye YH, Woolfit M, Rancès E, O'Neill SL, McGraw EA. | D30: PLoS Negl Trop Dis. 2013 Aug 8;7(8):e2362. doi: 10.1371/journal.pntd.0002362. eCollection 2013. | E30: Ye YH | F30: PLoS Negl Trop Dis | G30: 2013 | H30: 41503 | I30: PMC3738474 | K30: 10.1371/journal.pntd.0002362 | L30: =IF(ISNUMBER(VLOOKUP(A30,PRE,1,FALSE)),"PreAlerta",IF(ISNUMBER(VLOOKUP(A30,POST,1,FALSE)),"PostAlerta",IF(ISNUMBER(VLOOKUP(A30,EXCL,1,FALSE)),"Excluida","no incluido"))) -> PreAlerta
A31: 24012123 | B31: New chemotypes for wALADin1-like inhibitors of delta-aminolevulinic acid dehydratase from Wolbachia endobacteria | C31: Lentz CS, Stumpfe D, Bajorath J, Famulok M, Hoerauf A, Pfarr KM. | D31: Bioorg Med Chem Lett. 2013 Oct 15;23(20):5558-62. doi: 10.1016/j.bmcl.2013.08.052. Epub 2013 Aug 20. | E31: Lentz CS | F31: Bioorg Med Chem Lett | G31: 2013 | H31: 41527 | K31: 10.1016/j.bmcl.2013.08.052 | L31: =IF(ISNUMBER(VLOOKUP(A31,PRE,1,FALSE)),"PreAlerta",IF(ISNUMBER(VLOOKUP(A31,POST,1,FALSE)),"PostAlerta",IF(ISNUMBER(VLOOKUP(A31,EXCL,1,FALSE)),"Excluida","no incluido"))) -> PreAlerta
A32: 24166036 | B32: Scrub typhus meningitis or meningoencephalitis | C32: Kim DM, Chung JH, Yun NR, Kim SW, Lee JY, Han MA, Lee YB. | D32: Am J Trop Med Hyg. 2013 Dec;89(6):1206-11. doi: 10.4269/ajtmh.13-0224. Epub 2013 Oct 28. | E32: Kim DM | F32: Am J Trop Med Hyg | G32: 2013 | H32: 41577 | I32: PMC3854902 | K32: 10.4269/ajtmh.13-0224 | L32: =IF(ISNUMBER(VLOOKUP(A32,PRE,1,FALSE)),"PreAlerta",IF(ISNUMBER(VLOOKUP(A32,POST,1,FALSE)),"PostAlerta",IF(ISNUMBER(VLOOKUP(A32,EXCL,1,FALSE)),"Excluida","no incluido"))) -> PreAlerta
A33: 24144475 | B33: Recombinant Ehrlichia P29 protein induces a protective immune response in a mouse model of ehrlichiosis | C33: Thirumalapura NR, Crocquet-Valdes PA, Saito TB, Thomas S, McBride JW, Walker DH. | D33: Vaccine. 2013 Dec 5;31(50):5960-7. doi: 10.1016/j.vaccine.2013.10.036. Epub 2013 Oct 19. | E33: Thirumalapura NR | F33: Vaccine | G33: 2013 | H33: 41570 | I33: PMC3893061 | J33: NIHMS532534 | K33: 10.1016/j.vaccine.2013.10.036 | L33: =IF(ISNUMBER(VLOOKUP(A33,PRE,1,FALSE)),"PreAlerta",IF(ISNUMBER(VLOOKUP(A33,POST,1,FALSE)),"PostAlerta",IF(ISNUMBER(VLOOKUP(A33,EXCL,1,FALSE)),"Excluida","no incluido"))) -> PreAlerta
A34: 23866958 | B34: Anti-Wolbachia drug discovery and development: safe macrofilaricides for onchocerciasis and lymphatic filariasis | C34: Taylor MJ, Hoerauf A, Townson S, Slatko BE, Ward SA. | D34: Parasitology. 2014 Jan;141(1):119-27. doi: 10.1017/S0031182013001108. Epub 2013 Jul 18. | E34: Taylor MJ | F34: Parasitology | G34: 2014 | H34: 41478 | I34: PMC3884836 | K34: 10.1017/S0031182013001108 | L34: =IF(ISNUMBER(VLOOKUP(A34,PRE,1,FALSE)),"PreAlerta",IF(ISNUMBER(VLOOKUP(A34,POST,1,FALSE)),"PostAlerta",IF(ISNUMBER(VLOOKUP(A34,EXCL,1,FALSE)),"Excluida","no incluido"))) -> PreAlerta
A35: 24079981 | B35: Corallopyronin A - a promising antibiotic for treatment of filariasis | C35: Schäberle TF, Schiefer A, Schmitz A, König GM, Hoerauf A, Pfarr K. | D35: Int J Med Microbiol. 2014 Jan;304(1):72-8. doi: 10.1016/j.ijmm.2013.08.010. Epub 2013 Sep 4. | E35: Schäberle TF | F35: Int J Med Microbiol | G35: 2014 | H35: 41549 | K35: 10.1016/j.ijmm.2013.08.010 | L35: =IF(ISNUMBER(VLOOKUP(A35,PRE,1,FALSE)),"PreAlerta",IF(ISNUMBER(VLOOKUP(A35,POST,1,FALSE)),"PostAlerta",IF(ISNUMBER(VLOOKUP(A35,EXCL,1,FALSE)),"Excluida","no incluido"))) -> PreAlerta
A36: 24647254 | B36: A case report of scrub typhus-associated hemophagocytic syndrome and a review of literature | C36: Lin YH, Lin YH, Shi ZY. | D36: Jpn J Infect Dis. 2014;67(2):115-7. doi: 10.7883/yoken.67.115. | E36: Lin YH | F36: Jpn J Infect Dis | G36: 2014 | H36: 41719 | K36: 10.7883/yoken.67.115 | L36: =IF(ISNUMBER(VLOOKUP(A36,PRE,1,FALSE)),"PreAlerta",IF(ISNUMBER(VLOOKUP(A36,POST,1,FALSE)),"PostAlerta",IF(ISNUMBER(VLOOKUP(A36,EXCL,1,FALSE)),"Excluida","no incluido"))) -> PreAlerta
A37: 24443332 | B37: Massive consolidation: a rare manifestation of paediatric Scrub typhus | C37: Manickam K, Sunderkumar S, Chinnaraj S, Sivathanu S. | D37: BMJ Case Rep. 2014 Jan 17;2014:bcr2013200687. doi: 10.1136/bcr-2013-200687. | E37: Manickam K | F37: BMJ Case Rep | G37: 2014 | H37: 41660 | I37: PMC3902318 | K37: 10.1136/bcr-2013-200687 | L37: =IF(ISNUMBER(VLOOKUP(A37,PRE,1,FALSE)),"PreAlerta",IF(ISNUMBER(VLOOKUP(A37,POST,1,FALSE)),"PostAlerta",IF(ISNUMBER(VLOOKUP(A37,EXCL,1,FALSE)),"Excluida","no incluido"))) -> PreAlerta
A38: 24378068 | B38: The spreading process of Ehrlichia canis in macrophages is dependent on actin cytoskeleton, calcium and iron influx and lysosomal evasion | C38: Alves RN, Levenhagen MA, Levenhagen MM, Rieck SE, Labruna MB, Beletti ME. | D38: Vet Microbiol. 2014 Jan 31;168(2-4):442-6. doi: 10.1016/j.vetmic.2013.11.030. Epub 2013 Dec 16. | E38: Alves RN | F38: Vet Microbiol | G38: 2014 | H38: 41640 | K38: 10.1016/j.vetmic.2013.11.030 | L38: =IF(ISNUMBER(VLOOKUP(A38,PRE,1,FALSE)),"PreAlerta",IF(ISNUMBER(VLOOKUP(A38,POST,1,FALSE)),"PostAlerta",IF(ISNUMBER(VLOOKUP(A38,EXCL,1,FALSE)),"Excluida","no incluido"))) -> PreAlerta
A39: 24550643 | B39: In vitro bacteriostatic effects of rifampin on Orientia tsutsugamushi | C39: Im JH, Baek JH, Lee JS, Chung MH, Lee SM, Kang JS. | D39: J Korean Med Sci. 2014 Feb;29(2):183-9. doi: 10.3346/jkms.2014.29.2.183. Epub 2014 Jan 28. | E39: Im JH | F39: J Korean Med Sci | G39: 2014 | H39: 41690 | I39: PMC3923995 | K39: 10.3346/jkms.2014.29.2.183 | L39: =IF(ISNUMBER(VLOOKUP(A39,PRE,1,FALSE)),"PreAlerta",IF(ISNUMBER(VLOOKUP(A39,POST,1,FALSE)),"PostAlerta",IF(ISNUMBER(VLOOKUP(A39,EXCL,1,FALSE)),"Excluida","no incluido"))) -> PreAlerta
A40: 24612569 | B40: Why sulfonamides are contraindicated in Rocky Mountain spotted fever | C40: Ren V, Hsu S. | D40: Dermatol Online J. 2014 Feb 18;20(2):doj_21536. | E40: Ren V | F40: Dermatol Online J | G40: 2014 | H40: 41710 | L40: =IF(ISNUMBER(VLOOKUP(A40,PRE,1,FALSE)),"PreAlerta",IF(ISNUMBER(VLOOKUP(A40,POST,1,FALSE)),"PostAlerta",IF(ISNUMBER(VLOOKUP(A40,EXCL,1,FALSE)),"Excluida","no incluido"))) -> PreAlerta
A41: 24126603 | B41: Immunogenicity of hypothetical highly conserved proteins as novel antigens in Anaplasma marginale | C41: Nuñez PA, Moretta R, Ruybal P, Wilkowsky S, Farber MD. | D41: Curr Microbiol. 2014 Mar;68(3):269-77. doi: 10.1007/s00284-013-0475-6. Epub 2013 Oct 15. | E41: Nuñez PA | F41: Curr Microbiol | G41: 2014 | H41: 41563 | K41: 10.1007/s00284-013-0475-6 | L41: =IF(ISNUMBER(VLOOKUP(A41,PRE,1,FALSE)),"PreAlerta",IF(ISNUMBER(VLOOKUP(A41,POST,1,FALSE)),"PostAlerta",IF(ISNUMBER(VLOOKUP(A41,EXCL,1,FALSE)),"Excluida","no incluido"))) -> PreAlerta
A42: 24241712 | B42: Overcoming the challenges of drug discovery for neglected tropical diseases: the A·WOL experience | C42: Johnston KL, Ford L, Taylor MJ. | D42: J Biomol Screen. 2014 Mar;19(3):335-43. doi: 10.1177/1087057113511270. Epub 2013 Nov 15. | E42: Johnston KL | F42: J Biomol Screen | G42: 2014 | H42: 41597 | K42: 10.1177/1087057113511270 | L42: =IF(ISNUMBER(VLOOKUP(A42,PRE,1,FALSE)),"PreAlerta",IF(ISNUMBER(VLOOKUP(A42,POST,1,FALSE)),"PostAlerta",IF(ISNUMBER(VLOOKUP(A42,EXCL,1,FALSE)),"Excluida","no incluido"))) -> PreAlerta
A43: 24480589 | B43: Localization of a filarial phosphate permease that is up-regulated in response to depletion of essential Wolbachia endobacteria | C43: Arumugam S, Hoerauf A, Pfarr KM. | D43: Exp Parasitol. 2014 Mar;138:30-9. doi: 10.1016/j.exppara.2014.01.006. Epub 2014 Jan 28. | E43: Arumugam S | F43: Exp Parasitol | G43: 2014 | H43: 41671 | K43: 10.1016/j.exppara.2014.01.006 | L43: =IF(ISNUMBER(VLOOKUP(A43,PRE,1,FALSE)),"PreAlerta",IF(ISNUMBER(VLOOKUP(A43,POST,1,FALSE)),"PostAlerta",IF(ISNUMBER(VLOOKUP(A43,EXCL,1,FALSE)),"Excluida","no incluido"))) -> PreAlerta
A44: 24608654 | B44: Identification of Rhipicephalus microplus genes that modulate the infection rate of the rickettsia Anaplasma marginale | C44: Mercado-Curiel RF, Ávila-Ramírez ML, Palmer GH, Brayton KA. | D44: PLoS One. 2014 Mar 7;9(3):e91062. doi: 10.1371/journal.pone.0091062. eCollection 2014. | E44: Mercado-Curiel RF | F44: PLoS One | G44: 2014 | H44: 41709 | I44: PMC3946687 | K44: 10.1371/journal.pone.0091062 | L44: =IF(ISNUMBER(VLOOKUP(A44,PRE,1,FALSE)),"PreAlerta",IF(ISNUMBER(VLOOKUP(A44,POST,1,FALSE)),"PostAlerta",IF(ISNUMBER(VLOOKUP(A44,EXCL,1,FALSE)),"Excluida","no incluido"))) -> PreAlerta
A45: 24252486 | B45: Harnessing mosquito-Wolbachia symbiosis for vector and disease control | C45: Bourtzis K, Dobson SL, Xi Z, Rasgon JL, Calvitti M, Moreira LA, Bossin HC, Moretti R, Baton LA, Hughes GL, Mavingui P, Gilles JR. | D45: Acta Trop. 2014 Apr;132 Suppl:S150-63. doi: 10.1016/j.actatropica.2013.11.004. Epub 2013 Nov 16. | E45: Bourtzis K | F45: Acta Trop | G45: 2014 | H45: 41599 | K45: 10.1016/j.actatropica.2013.11.004 | L45: =IF(ISNUMBER(VLOOKUP(A45,PRE,1,FALSE)),"PreAlerta",IF(ISNUMBER(VLOOKUP(A45,POST,1,FALSE)),"PostAlerta",IF(ISNUMBER(VLOOKUP(A45,EXCL,1,FALSE)),"Excluida","no incluido"))) -> PreAlerta
A46: 24823524 | B46: Acute infectious purpura fulminans due to probable spotted fever | C46: Kundavaram A, Francis NR, Jude AP, Varghese GN. | D46: J Postgrad Med. 2014 Apr-Jun;60(2):198-9. doi: 10.4103/0022-3859.132345. | E46: Kundavaram A | F46: J Postgrad Med | G46: 2014 | H46: 41774 | K46: 10.4103/0022-3859.132345 | L46: =IF(ISNUMBER(VLOOKUP(A46,PRE,1,FALSE)),"PreAlerta",IF(ISNUMBER(VLOOKUP(A46,POST,1,FALSE)),"PostAlerta",IF(ISNUMBER(VLOOKUP(A46,EXCL,1,FALSE)),"Excluida","no incluido"))) -> PreAlerta
A47: 24606864 | B47: Evaluation of humoral and cellular immune response of BALB/c mice immunized with a recombinant fragment of MSP1a from Anaplasma marginale using carbon nanotubes as a carrier molecule | C47: Silvestre BT, Rabelo ÉM, Versiani AF, da Fonseca FG, Silveira JA, Bueno LL, Fujiwara RT, Ribeiro MF. | D47: Vaccine. 2014 Apr 17;32(19):2160-6. doi: 10.1016/j.vaccine.2014.02.062. Epub 2014 Mar 4. | E47: Silvestre BT | F47: Vaccine | G47: 2014 | H47: 41709 | K47: 10.1016/j.vaccine.2014.02.062 | L47: =IF(ISNUMBER(VLOOKUP(A47,PRE,1,FALSE)),"PreAlerta",IF(ISNUMBER(VLOOKUP(A47,POST,1,FALSE)),"PostAlerta",IF(ISNUMBER(VLOOKUP(A47,EXCL,1,FALSE)),"Excluida","no incluido"))) -> PreAlerta
A48: 24831608 | B48: A novel approach to eliminate Wolbachia infections in Nasonia vitripennis revealed different antibiotic resistance between two bacterial strains | C48: Liu HY, Wang YK, Zhi CC, Xiao JH, Huang DW. | D48: FEMS Microbiol Lett. 2014 Jun;355(2):163-9. doi: 10.1111/1574-6968.12471. Epub 2014 May 29. | E48: Liu HY | F48: FEMS Microbiol Lett | G48: 2014 | H48: 41776 | K48: 10.1111/1574-6968.12471 | L48: =IF(ISNUMBER(VLOOKUP(A48,PRE,1,FALSE)),"PreAlerta",IF(ISNUMBER(VLOOKUP(A48,POST,1,FALSE)),"PostAlerta",IF(ISNUMBER(VLOOKUP(A48,EXCL,1,FALSE)),"Excluida","no incluido"))) -> PreAlerta
A49: 24941309 | B49: Cloning, expression and characterization of UDP-N-acetylglucosamine enolpyruvyl transferase (MurA) from Wolbachia endosymbiont of human lymphatic filarial parasite Brugia malayi | C49: Shahab M, Verma M, Pathak M, Mitra K, Misra-Bhattacharya S. | D49: PLoS One. 2014 Jun 18;9(6):e99884. doi: 10.1371/journal.pone.0099884. eCollection 2014. | E49: Shahab M | F49: PLoS One | G49: 2014 | H49: 41809 | I49: PMC4062475 | K49: 10.1371/journal.pone.0099884 | L49: =IF(ISNUMBER(VLOOKUP(A49,PRE,1,FALSE)),"PreAlerta",IF(ISNUMBER(VLOOKUP(A49,POST,1,FALSE)),"PostAlerta",IF(ISNUMBER(VLOOKUP(A49,EXCL,1,FALSE)),"Excluida","no incluido"))) -> PreAlerta
A50: 24945631 | B50: Wolbachia transcription elongation factor "Wol GreA" interacts with α2ββ'σ subunits of RNA polymerase through its dimeric C-terminal domain | C50: Nag JK, Shrivastava N, Chahar D, Gupta CL, Bajpai P, Misra-Bhattacharya S. | D50: PLoS Negl Trop Dis. 2014 Jun 19;8(6):e2930. doi: 10.1371/journal.pntd.0002930. eCollection 2014 Jun. | E50: Nag JK | F50: PLoS Negl Trop Dis | G50: 2014 | H50: 41810 | I50: PMC4063747 | K50: 10.1371/journal.pntd.0002930 | L50: =IF(ISNUMBER(VLOOKUP(A50,PRE,1,FALSE)),"PreAlerta",IF(ISNUMBER(VLOOKUP(A50,POST,1,FALSE)),"PostAlerta",IF(ISNUMBER(VLOOKUP(A50,EXCL,1,FALSE)),"Excluida","no incluido"))) -> PreAlerta
A51: 25046729 | B51: Wolbachia endosymbionts and human disease control | C51: Slatko BE, Luck AN, Dobson SL, Foster JM. | D51: Mol Biochem Parasitol. 2014 Jul;195(2):88-95. doi: 10.1016/j.molbiopara.2014.07.004. Epub 2014 Jul 18. | E51: Slatko BE | F51: Mol Biochem Parasitol | G51: 2014 | H51: 41842 | K51: 10.1016/j.molbiopara.2014.07.004 | L51: =IF(ISNUMBER(VLOOKUP(A51,PRE,1,FALSE)),"PreAlerta",IF(ISNUMBER(VLOOKUP(A51,POST,1,FALSE)),"PostAlerta",IF(ISNUMBER(VLOOKUP(A51,EXCL,1,FALSE)),"Excluida","no incluido"))) -> PreAlerta
A52: 25073644 | B52: Host-directed antimicrobial drugs with broad-spectrum efficacy against intracellular bacterial pathogens | C52: Czyż DM, Potluri LP, Jain-Gupta N, Riley SP, Martinez JJ, Steck TL, Crosson S, Shuman HA, Gabay JE. | D52: mBio. 2014 Jul 29;5(4):e01534-14. doi: 10.1128/mBio.01534-14. | E52: Czyż DM | F52: mBio | G52: 2014 | H52: 41851 | I52: PMC4128363 | K52: 10.1128/mBio.01534-14 | L52: =IF(ISNUMBER(VLOOKUP(A52,PRE,1,FALSE)),"PreAlerta",IF(ISNUMBER(VLOOKUP(A52,POST,1,FALSE)),"PostAlerta",IF(ISNUMBER(VLOOKUP(A52,EXCL,1,FALSE)),"Excluida","no incluido"))) -> PreAlerta
A53: 24924907 | B53: Genomic and comparative genomic analyses of Rickettsia heilongjiangensis provide insight into its evolution and pathogenesis | C53: Duan C, Xiong X, Qi Y, Gong W, Jiao J, Wen B. | D53: Infect Genet Evol. 2014 Aug;26:274-82. doi: 10.1016/j.meegid.2014.05.028. Epub 2014 Jun 10. | E53: Duan C | F53: Infect Genet Evol | G53: 2014 | H53: 41804 | K53: 10.1016/j.meegid.2014.05.028 | L53: =IF(ISNUMBER(VLOOKUP(A53,PRE,1,FALSE)),"PreAlerta",IF(ISNUMBER(VLOOKUP(A53,POST,1,FALSE)),"PostAlerta",IF(ISNUMBER(VLOOKUP(A53,EXCL,1,FALSE)),"Excluida","no incluido"))) -> PreAlerta
A54: 25105893 | B54: Ixodes pacificus ticks maintain embryogenesis and egg hatching after antibiotic treatment of Rickettsia endosymbiont | C54: Kurlovs AH, Li J, Cheng D, Zhong J. | D54: PLoS One. 2014 Aug 8;9(8):e104815. doi: 10.1371/journal.pone.0104815. eCollection 2014. | E54: Kurlovs AH | F54: PLoS One | G54: 2014 | H54: 41860 | I54: PMC4126787 | K54: 10.1371/journal.pone.0104815 | L54: =IF(ISNUMBER(VLOOKUP(A54,PRE,1,FALSE)),"PreAlerta",IF(ISNUMBER(VLOOKUP(A54,POST,1,FALSE)),"PostAlerta",IF(ISNUMBER(VLOOKUP(A54,EXCL,1,FALSE)),"Excluida","no incluido"))) -> PreAlerta
A55: 25114252 | B55: Native microbiome impedes vertical transmission of Wolbachia in Anopheles mosquitoes | C55: Hughes GL, Dodson BL, Johnson RM, Murdock CC, Tsujimoto H, Suzuki Y, Patt AA, Cui L, Nossa CW, Barry RM, Sakamoto JM, Hornett EA, Rasgon JL. | D55: Proc Natl Acad Sci U S A. 2014 Aug 26;111(34):12498-503. doi: 10.1073/pnas.1408888111. Epub 2014 Aug 11. | E55: Hughes GL | F55: Proc Natl Acad Sci U S A | G55: 2014 | H55: 41864 | I55: PMC4151774 | K55: 10.1073/pnas.1408888111 | L55: =IF(ISNUMBER(VLOOKUP(A55,PRE,1,FALSE)),"PreAlerta",IF(ISNUMBER(VLOOKUP(A55,POST,1,FALSE)),"PostAlerta",IF(ISNUMBER(VLOOKUP(A55,EXCL,1,FALSE)),"Excluida","no incluido"))) -> PreAlerta
A56: 24789726 | B56: Depletion of host cell riboflavin reduces Wolbachia levels in cultured mosquito cells | C56: Fallon AM, Baldridge GD, Carroll EM, Kurtz CM. | D56: In Vitro Cell Dev Biol Anim. 2014 Sep;50(8):707-13. doi: 10.1007/s11626-014-9758-x. Epub 2014 May 2. | E56: Fallon AM | F56: In Vitro Cell Dev Biol Anim | G56: 2014 | H56: 41762 | I56: PMC4383090 | J56: NIHMS675914 | K56: 10.1007/s11626-014-9758-x | L56: =IF(ISNUMBER(VLOOKUP(A56,PRE,1,FALSE)),"PreAlerta",IF(ISNUMBER(VLOOKUP(A56,POST,1,FALSE)),"PostAlerta",IF(ISNUMBER(VLOOKUP(A56,EXCL,1,FALSE)),"Excluida","no incluido"))) -> PreAlerta
A57: 24957537 | B57: Rickettsial infections in Southeast Asia: implications for local populace and febrile returned travelers | C57: Aung AK, Spelman DW, Murray RJ, Graves S. | D57: Am J Trop Med Hyg. 2014 Sep;91(3):451-60. doi: 10.4269/ajtmh.14-0191. Epub 2014 Jun 23. | E57: Aung AK | F57: Am J Trop Med Hyg | G57: 2014 | H57: 41815 | I57: PMC4155544 | K57: 10.4269/ajtmh.14-0191 | L57: =IF(ISNUMBER(VLOOKUP(A57,PRE,1,FALSE)),"PreAlerta",IF(ISNUMBER(VLOOKUP(A57,POST,1,FALSE)),"PostAlerta",IF(ISNUMBER(VLOOKUP(A57,EXCL,1,FALSE)),"Excluida","no incluido"))) -> PreAlerta
A58: 25043277 | B58: Phenotype of the anti-Rickettsia CD8(+) T cell response suggests cellular correlates of protection for the assessment of novel antigens | C58: Caro-Gomez E, Gazi M, Cespedes MA, Goez Y, Teixeira B, Valbuena G. | D58: Vaccine. 2014 Sep 3;32(39):4960-7. doi: 10.1016/j.vaccine.2014.07.032. Epub 2014 Jul 18. | E58: Caro-Gomez E | F58: Vaccine | G58: 2014 | H58: 41842 | I58: PMC4138832 | J58: NIHMS614539 | K58: 10.1016/j.vaccine.2014.07.032 | L58: =IF(ISNUMBER(VLOOKUP(A58,PRE,1,FALSE)),"PreAlerta",IF(ISNUMBER(VLOOKUP(A58,POST,1,FALSE)),"PostAlerta",IF(ISNUMBER(VLOOKUP(A58,EXCL,1,FALSE)),"Excluida","no incluido"))) -> PreAlerta
