Workbook
Name categoria: categorias!$A:$A
Name Estado: categorias!$C$2:$C$65536
Name EXCL: Excluidas!$A:$K
Name EXCLUIDAS: Excluidas!$A$1:$K$463
Name KEYWORDS: 'Palabras claves'!$A:$K
Name NgonorreaePre: '2012-2017'!$A$1:$K$1
Name PalabrasClave: 'Palabras claves'!$K$1:$K$1371
Name POST: '2017-2022'!$A:$K
Name POSTALERTA: '2017-2022'!$A$1:$B$1
Name PRE: '2012-2017'!$A:$K
Name PREALERTA: '2012-2017'!$A$1:$O$1
Name SegmentaciónDeDatos_Alerta1: #REF!
Name SegmentaciónDeDatos_KeyWords: #REF!
Name SegmentaciónDeDatos_PubYear: #REF!
Name subcategoria: categorias!$B:$B
Name TablaNgonoreae: #REF!

Sheet DashBoard
C2: C. trachomatis 2012-2022
C3: Total de publicaciones de | F3: =C2 -> C. trachomatis 2012-2022 | G3: : | H3: =COUNTA('2012-2022'!$B$2:$B$15076) -> 4809
D5: Publicaciones por Año | I5: Categorías y Subcategorías
D17: Publicaciones por mes
C34: =IFERROR(__xludf.DUMMYFUNCTION("UNIQUE('2012-2022'!N:N)"),"Categoria") -> Categoria
C36: =IFERROR(__xludf.DUMMYFUNCTION("""COMPUTED_VALUE""")," 1) Reporte de cepas resistentes") -> 1) Reporte de cepas resistentes
C37: =IFERROR(__xludf.DUMMYFUNCTION("""COMPUTED_VALUE"""),"2) Nuevos tratamientos ") -> 2) Nuevos tratamientos | F37: =COUNTIF('2012-2022'!N:N,C37) -> 74
C38: =IFERROR(__xludf.DUMMYFUNCTION("""COMPUTED_VALUE"""),"4) otros") -> 4) otros | F38: =COUNTIF('2012-2022'!N:N,C38) -> 1627
C39: =IFERROR(__xludf.DUMMYFUNCTION("""COMPUTED_VALUE"""),"3) immunization") -> 3) immunization | F39: =COUNTIF('2012-2022'!N:N,C39) -> 72
C40: =IFERROR(__xludf.DUMMYFUNCTION("""COMPUTED_VALUE"""),"Categorias") -> Categorias | F40: =COUNTIF('2012-2022'!N:N,C40) -> 2
C41: =IFERROR(__xludf.DUMMYFUNCTION("""COMPUTED_VALUE"""),"3) Inmunizacióm") -> 3) Inmunizacióm | F41: =COUNTIF('2012-2022'!N:N,C41) -> 1
F42: =COUNTIF('2012-2022'!N:N,C42) -> 0
F43: =COUNTIF('2012-2022'!N:N,C43) -> 0

Sheet categorias
A1: Categorias | B1: Subcategorias | C1: Estados
A2: 1) Reporte de cepas resistentes | B2: 2a) Productos naturales | C2: Revisar
A3: 2) Nuevos tratamientos | B3: 2b) Péptidos | C3: Listo
A4: 3) Inmunizacióm | B4: 2c) Droga de diseño | C4: Excluir
A5: 4) otros | B5: 2d) Anticuerpos | C5: Otros-A
B6: 2e) Bacteriófagos | C6: Otros-B
B7: 2f) Estrategias antivirulencia | C7: Otros-C
B8: 2g) nueva combinación de ATB | C8: Otros-D

Sheet 2012-2022
A1: PMID | B1: Title | C1: Authors | D1: Citation | E1: First Author | F1: Journal/Book | G1: Publication Year | H1: Create Date | I1: PMCID | J1: NIHMS ID | K1: DOI | L1: Alerta | M1: KeyWords | N1: Categoria | O1: subcategoria | P1: fecha de publicación | Q1: Estado | R1: PubYear | S1: PubMonth | T1: Abstract | U1: 1) Antimicrobial Resistance stain | V1: 2) New treatment | W1: 3) Immunization | X1: Human_summary
A2: 22304240 | B2: O(2)-evolving chlorite dismutase as a tool for studying O(2)-utilizing enzymes | C2: Dassama LM, Yosca TH, Conner DA, Lee MH, Blanc B, Streit BR, Green MT, DuBois JL, Krebs C, Bollinger JM Jr. | D2: Biochemistry. 2012 Feb 28;51(8):1607-16. doi: 10.1021/bi201906x. Epub 2012 Feb 13. | E2: Dassama LM | F2: Biochemistry | G2: 2012 | H2: 40946 | I2: PMC3297476 | J2: NIHMS354219 | K2: 10.1021/bi201906x | L2: =IF(ISNUMBER(VLOOKUP(A2,EXCL,1,FALSE)),"Excluido",IF(ISNUMBER(VLOOKUP(A2,POST,1,FALSE)),"PostAlerta",IF(ISNUMBER(VLOOKUP(A2,PRE,1,FALSE)),"PreAlerta",""))) -> PreAlerta | M2: =IF(ISNUMBER(VLOOKUP(A2,KEYWORDS,1,FALSE)),"C/PalabrasClaves","S/PalabrasClaves") -> S/PalabrasClaves | Q2: Revisar
A3: 21848430 | B3: Differing effects of azithromycin and doxycycline on cytokines in cells from Chlamydia trachomatis-infected women | C3: Srivastava P, Bhengraj AR, Jha HC, Vardhan H, Jha R, Singh LC, Salhan S, Mittal A. | D3: DNA Cell Biol. 2012 Mar;31(3):392-401. doi: 10.1089/dna.2011.1333. Epub 2011 Aug 17. | E3: Srivastava P | F3: DNA Cell Biol | G3: 2012 | H3: 40774 | K3: 10.1089/dna.2011.1333 | L3: =IF(ISNUMBER(VLOOKUP(A3,EXCL,1,FALSE)),"Excluido",IF(ISNUMBER(VLOOKUP(A3,POST,1,FALSE)),"PostAlerta",IF(ISNUMBER(VLOOKUP(A3,PRE,1,FALSE)),"PreAlerta",""))) -> PreAlerta | M3: =IF(ISNUMBER(VLOOKUP(A3,KEYWORDS,1,FALSE)),"C/PalabrasClaves","S/PalabrasClaves") -> S/PalabrasClaves | Q3: Revisar
A4: 22042092 | B4: Absence of Swedish new variant Chlamydia trachomatis (nvCT) and C. trachomatis genotype distribution in Gipuzkoa, Spain, 2009-2010 | C4: Piñeiro L, Unemo M, Cilla G. | D4: Acta Derm Venereol. 2012 Mar;92(2):185-6. doi: 10.2340/00015555-1234. | E4: Piñeiro L | F4: Acta Derm Venereol | G4: 2012 | H4: 40849 | K4: 10.2340/00015555-1234 | L4: =IF(ISNUMBER(VLOOKUP(A4,EXCL,1,FALSE)),"Excluido",IF(ISNUMBER(VLOOKUP(A4,POST,1,FALSE)),"PostAlerta",IF(ISNUMBER(VLOOKUP(A4,PRE,1,FALSE)),"PreAlerta",""))) -> PreAlerta | M4: =IF(ISNUMBER(VLOOKUP(A4,KEYWORDS,1,FALSE)),"C/PalabrasClaves","S/PalabrasClaves") -> S/PalabrasClaves | Q4: Listo
A5: 22122734 | B5: Chlamydial infection during trachoma monitoring: are the most difficult-to-reach children more likely to be infected? | C5: Keenan JD, Moncada J, Gebre T, Ayele B, Chen MC, Yu SN, Emerson PM, Stoller NE, McCulloch CE, Gaynor BD, Schachter J. | D5: Trop Med Int Health. 2012 Mar;17(3):392-6. doi: 10.1111/j.1365-3156.2011.02919.x. Epub 2011 Nov 28. | E5: Keenan JD | F5: Trop Med Int Health | G5: 2012 | H5: 40877 | I5: PMC3292692 | J5: NIHMS334303 | K5: 10.1111/j.1365-3156.2011.02919.x | L5: =IF(ISNUMBER(VLOOKUP(A5,EXCL,1,FALSE)),"Excluido",IF(ISNUMBER(VLOOKUP(A5,POST,1,FALSE)),"PostAlerta",IF(ISNUMBER(VLOOKUP(A5,PRE,1,FALSE)),"PreAlerta",""))) -> Excluido | M5: =IF(ISNUMBER(VLOOKUP(A5,KEYWORDS,1,FALSE)),"C/PalabrasClaves","S/PalabrasClaves") -> S/PalabrasClaves | N5: 1) Reporte de cepas resistentes | Q5: Revisar
A6: 22142497 | B6: Prevalence of genital mycoplasmas and ureaplasmas in men younger than 40 years-of-age with acute epididymitis | C6: Ito S, Tsuchiya T, Yasuda M, Yokoi S, Nakano M, Deguchi T. | D6: Int J Urol. 2012 Mar;19(3):234-8. doi: 10.1111/j.1442-2042.2011.02917.x. Epub 2011 Dec 5. | E6: Ito S | F6: Int J Urol | G6: 2012 | H6: 40884 | K6: 10.1111/j.1442-2042.2011.02917.x | L6: =IF(ISNUMBER(VLOOKUP(A6,EXCL,1,FALSE)),"Excluido",IF(ISNUMBER(VLOOKUP(A6,POST,1,FALSE)),"PostAlerta",IF(ISNUMBER(VLOOKUP(A6,PRE,1,FALSE)),"PreAlerta",""))) -> PreAlerta | M6: =IF(ISNUMBER(VLOOKUP(A6,KEYWORDS,1,FALSE)),"C/PalabrasClaves","S/PalabrasClaves") -> S/PalabrasClaves | Q6: Excluir
A7: 22158739 | B7: Identification of antigen-specific antibody responses associated with upper genital tract pathology in mice infected with Chlamydia muridarum | C7: Zeng H, Gong S, Hou S, Zou Q, Zhong G. | D7: Infect Immun. 2012 Mar;80(3):1098-106. doi: 10.1128/IAI.05894-11. Epub 2011 Dec 12. | E7: Zeng H | F7: Infect Immun | G7: 2012 | H7: 40891 | I7: PMC3294672 | K7: 10.1128/IAI.05894-11 | L7: =IF(ISNUMBER(VLOOKUP(A7,EXCL,1,FALSE)),"Excluido",IF(ISNUMBER(VLOOKUP(A7,POST,1,FALSE)),"PostAlerta",IF(ISNUMBER(VLOOKUP(A7,PRE,1,FALSE)),"PreAlerta",""))) -> PreAlerta | M7: =IF(ISNUMBER(VLOOKUP(A7,KEYWORDS,1,FALSE)),"C/PalabrasClaves","S/PalabrasClaves") -> S/PalabrasClaves | Q7: Excluir
A8: 22203235 | B8: Chlamydia pneumoniae entry into epithelial cells by clathrin-independent endocytosis | C8: Korhonen JT, Puolakkainen M, Haveri A, Tammiruusu A, Sarvas M, Lahesmaa R. | D8: Microb Pathog. 2012 Mar;52(3):157-64. doi: 10.1016/j.micpath.2011.12.002. Epub 2011 Dec 21. | E8: Korhonen JT | F8: Microb Pathog | G8: 2012 | H8: 40906 | K8: 10.1016/j.micpath.2011.12.002 | L8: =IF(ISNUMBER(VLOOKUP(A8,EXCL,1,FALSE)),"Excluido",IF(ISNUMBER(VLOOKUP(A8,POST,1,FALSE)),"PostAlerta",IF(ISNUMBER(VLOOKUP(A8,PRE,1,FALSE)),"PreAlerta",""))) -> PreAlerta | M8: =IF(ISNUMBER(VLOOKUP(A8,KEYWORDS,1,FALSE)),"C/PalabrasClaves","S/PalabrasClaves") -> S/PalabrasClaves | Q8: Listo
A9: 22222354 | B9: High-valent [MnFe] and [FeFe] cofactors in ribonucleotide reductases | C9: Leidel N, Popović-Bijelić A, Havelius KG, Chernev P, Voevodskaya N, Gräslund A, Haumann M. | D9: Biochim Biophys Acta. 2012 Mar;1817(3):430-44. doi: 10.1016/j.bbabio.2011.12.008. Epub 2011 Dec 23. | E9: Leidel N | F9: Biochim Biophys Acta | G9: 2012 | H9: 40915 | K9: 10.1016/j.bbabio.2011.12.008 | L9: =IF(ISNUMBER(VLOOKUP(A9,EXCL,1,FALSE)),"Excluido",IF(ISNUMBER(VLOOKUP(A9,POST,1,FALSE)),"PostAlerta",IF(ISNUMBER(VLOOKUP(A9,PRE,1,FALSE)),"PreAlerta",""))) -> PreAlerta | M9: =IF(ISNUMBER(VLOOKUP(A9,KEYWORDS,1,FALSE)),"C/PalabrasClaves","S/PalabrasClaves") -> S/PalabrasClaves | Q9: Revisar
A10: 22285842 | B10: Trachomatous trichiasis and its management in endemic countries | C10: Rajak SN, Collin JR, Burton MJ. | D10: Surv Ophthalmol. 2012 Mar-Apr;57(2):105-35. doi: 10.1016/j.survophthal.2011.08.002. Epub 2012 Jan 27. | E10: Rajak SN | F10: Surv Ophthalmol | G10: 2012 | H10: 40939 | I10: PMC3316859 | K10: 10.1016/j.survophthal.2011.08.002 | L10: =IF(ISNUMBER(VLOOKUP(A10,EXCL,1,FALSE)),"Excluido",IF(ISNUMBER(VLOOKUP(A10,POST,1,FALSE)),"PostAlerta",IF(ISNUMBER(VLOOKUP(A10,PRE,1,FALSE)),"PreAlerta",""))) -> Excluido | M10: =IF(ISNUMBER(VLOOKUP(A10,KEYWORDS,1,FALSE)),"C/PalabrasClaves","S/PalabrasClaves") -> S/PalabrasClaves | N10: 1) Reporte de cepas resistentes | Q10: Revisar
A11: 22316336 | B11: Treatment of chlamydial infections | C11: Hammerschlag MR, Kohlhoff SA. | D11: Expert Opin Pharmacother. 2012 Mar;13(4):545-52. doi: 10.1517/14656566.2012.658776. Epub 2012 Feb 9. | E11: Hammerschlag MR | F11: Expert Opin Pharmacother | G11: 2012 | H11: 40949 | K11: 10.1517/14656566.2012.658776 | L11: =IF(ISNUMBER(VLOOKUP(A11,EXCL,1,FALSE)),"Excluido",IF(ISNUMBER(VLOOKUP(A11,POST,1,FALSE)),"PostAlerta",IF(ISNUMBER(VLOOKUP(A11,PRE,1,FALSE)),"PreAlerta",""))) -> Excluido | M11: =IF(ISNUMBER(VLOOKUP(A11,KEYWORDS,1,FALSE)),"C/PalabrasClaves","S/PalabrasClaves") -> S/PalabrasClaves | N11: 2) Nuevos tratamientos | Q11: Revisar
A12: 22326056 | B12: Review: Targeting trachoma: Strategies to reduce the leading infectious cause of blindness | C12: Baneke A. | D12: Travel Med Infect Dis. 2012 Mar;10(2):92-6. doi: 10.1016/j.tmaid.2012.01.005. Epub 2012 Feb 9. | E12: Baneke A | F12: Travel Med Infect Dis | G12: 2012 | H12: 40953 | K12: 10.1016/j.tmaid.2012.01.005 | L12: =IF(ISNUMBER(VLOOKUP(A12,EXCL,1,FALSE)),"Excluido",IF(ISNUMBER(VLOOKUP(A12,POST,1,FALSE)),"PostAlerta",IF(ISNUMBER(VLOOKUP(A12,PRE,1,FALSE)),"PreAlerta",""))) -> Excluido | M12: =IF(ISNUMBER(VLOOKUP(A12,KEYWORDS,1,FALSE)),"C/PalabrasClaves","S/PalabrasClaves") -> S/PalabrasClaves | Q12: Excluir
A13: 22337116 | B13: Stable Chlamydia prevalence does not exclude increasing burden of disease | C13: Rekart ML, Brunham RC. | D13: Sex Transm Dis. 2012 Mar;39(3):239; author reply 239-40. doi: 10.1097/OLQ.0b013e318244b79c. | E13: Rekart ML | F13: Sex Transm Dis | G13: 2012 | H13: 40956 | K13: 10.1097/OLQ.0b013e318244b79c | L13: =IF(ISNUMBER(VLOOKUP(A13,EXCL,1,FALSE)),"Excluido",IF(ISNUMBER(VLOOKUP(A13,POST,1,FALSE)),"PostAlerta",IF(ISNUMBER(VLOOKUP(A13,PRE,1,FALSE)),"PreAlerta",""))) -> PreAlerta | M13: =IF(ISNUMBER(VLOOKUP(A13,KEYWORDS,1,FALSE)),"C/PalabrasClaves","S/PalabrasClaves") -> S/PalabrasClaves
A14: 22369307 | B14: The use of polymerase chain reaction assay versus cell culture in detecting neonatal chlamydial conjunctivitis | C14: Rafiei Tabatabaei S, Afjeiee SA, Fallah F, Tahami Zanjani N, Shiva F, Tavakkoly Fard A, Shamshiri AR, Karimi A. | D14: Arch Iran Med. 2012 Mar;15(3):171-5. | E14: Rafiei Tabatabaei S | F14: Arch Iran Med | G14: 2012 | H14: 40968 | L14: =IF(ISNUMBER(VLOOKUP(A14,EXCL,1,FALSE)),"Excluido",IF(ISNUMBER(VLOOKUP(A14,POST,1,FALSE)),"PostAlerta",IF(ISNUMBER(VLOOKUP(A14,PRE,1,FALSE)),"PreAlerta",""))) -> PreAlerta | M14: =IF(ISNUMBER(VLOOKUP(A14,KEYWORDS,1,FALSE)),"C/PalabrasClaves","S/PalabrasClaves") -> S/PalabrasClaves | N14: 4) otros
A15: 22382226 | B15: Frequency of Chlamydia trachomatis among male patients with urethritis in northeast of Iran detected by polymerase chain reaction | C15: Ghazvini K, Ahmadnia H, Ghanaat J. | D15: Saudi J Kidney Dis Transpl. 2012 Mar;23(2):316-20. | E15: Ghazvini K | F15: Saudi J Kidney Dis Transpl | G15: 2012 | H15: 40971 | L15: =IF(ISNUMBER(VLOOKUP(A15,EXCL,1,FALSE)),"Excluido",IF(ISNUMBER(VLOOKUP(A15,POST,1,FALSE)),"PostAlerta",IF(ISNUMBER(VLOOKUP(A15,PRE,1,FALSE)),"PreAlerta",""))) -> PreAlerta | M15: =IF(ISNUMBER(VLOOKUP(A15,KEYWORDS,1,FALSE)),"C/PalabrasClaves","S/PalabrasClaves") -> S/PalabrasClaves | N15: 4) otros
A16: 22386127 | B16: Serum interleukin-1β, interleukin-8 and anti-heat shock 60 Chlamydia trachomatis antibodies as markers of ectopic pregnancy | C16: Daponte A, Pournaras S, Deligeoroglou E, Skentou H, Messinis IE. | D16: J Reprod Immunol. 2012 Mar;93(2):102-8. doi: 10.1016/j.jri.2012.01.003. Epub 2012 Mar 2. | E16: Daponte A | F16: J Reprod Immunol | G16: 2012 | H16: 40974 | K16: 10.1016/j.jri.2012.01.003 | L16: =IF(ISNUMBER(VLOOKUP(A16,EXCL,1,FALSE)),"Excluido",IF(ISNUMBER(VLOOKUP(A16,POST,1,FALSE)),"PostAlerta",IF(ISNUMBER(VLOOKUP(A16,PRE,1,FALSE)),"PreAlerta",""))) -> PreAlerta | M16: =IF(ISNUMBER(VLOOKUP(A16,KEYWORDS,1,FALSE)),"C/PalabrasClaves","S/PalabrasClaves") -> S/PalabrasClaves | N16: 4) otros
A17: 22421458 | B17: [Diagnosis and treatment of Chlamydia-induced reactive arthritis] | C17: Zarco Montejo P. | D17: Reumatol Clin. 2012 Mar;8 Suppl 1:S20-5. doi: 10.1016/j.reuma.2011.11.003. Epub 2012 Mar 14. | E17: Zarco Montejo P | F17: Reumatol Clin | G17: 2012 | H17: 40985 | K17: 10.1016/j.reuma.2011.11.003 | L17: =IF(ISNUMBER(VLOOKUP(A17,EXCL,1,FALSE)),"Excluido",IF(ISNUMBER(VLOOKUP(A17,POST,1,FALSE)),"PostAlerta",IF(ISNUMBER(VLOOKUP(A17,PRE,1,FALSE)),"PreAlerta",""))) -> Excluido | M17: =IF(ISNUMBER(VLOOKUP(A17,KEYWORDS,1,FALSE)),"C/PalabrasClaves","S/PalabrasClaves") -> S/PalabrasClaves
A18: 22422335 | B18: Hemostatic properties of the lymph: relationships with occlusion and thrombosis | C18: Lippi G, Favaloro EJ, Cervellin G. | D18: Semin Thromb Hemost. 2012 Mar;38(2):213-21. doi: 10.1055/s-0032-1301418. Epub 2012 Feb 9. | E18: Lippi G | F18: Semin Thromb Hemost | G18: 2012 | H18: 40985 | K18: 10.1055/s-0032-1301418 | L18: =IF(ISNUMBER(VLOOKUP(A18,EXCL,1,FALSE)),"Excluido",IF(ISNUMBER(VLOOKUP(A18,POST,1,FALSE)),"PostAlerta",IF(ISNUMBER(VLOOKUP(A18,PRE,1,FALSE)),"PreAlerta",""))) -> Excluido | M18: =IF(ISNUMBER(VLOOKUP(A18,KEYWORDS,1,FALSE)),"C/PalabrasClaves","S/PalabrasClaves") -> S/PalabrasClaves
A19: 22552464 | B19: Prevalence of cervical Chlamydia trachomatis infection in sexually active adolescents from Salvador, Brazil | C19: Machado MS, Costa e Silva BF, Gomes IL, Santana IU, Grassi MF. | D19: Braz J Infect Dis. 2012 Mar-Apr;16(2):188-91. doi: 10.1590/s1413-86702012000200015. | E19: Machado MS | F19: Braz J Infect Dis | G19: 2012 | H19: 41033 | K19: 10.1590/s1413-86702012000200015 | L19: =IF(ISNUMBER(VLOOKUP(A19,EXCL,1,FALSE)),"Excluido",IF(ISNUMBER(VLOOKUP(A19,POST,1,FALSE)),"PostAlerta",IF(ISNUMBER(VLOOKUP(A19,PRE,1,FALSE)),"PreAlerta",""))) -> PreAlerta | M19: =IF(ISNUMBER(VLOOKUP(A19,KEYWORDS,1,FALSE)),"C/PalabrasClaves","S/PalabrasClaves") -> S/PalabrasClaves | N19: 4) otros
A20: 22650098 | B20: [Prevalence of Chlamydia trachomatis in adults with chronic conjunctivitis in Nisava district] | C20: Indjić N, Igić L, Veselinović D. | D20: Srp Arh Celok Lek. 2012 Mar-Apr;140(3-4):148-52. doi: 10.2298/sarh1204148i. | E20: Indjić N | F20: Srp Arh Celok Lek | G20: 2012 | H20: 41062 | K20: 10.2298/sarh1204148i | L20: =IF(ISNUMBER(VLOOKUP(A20,EXCL,1,FALSE)),"Excluido",IF(ISNUMBER(VLOOKUP(A20,POST,1,FALSE)),"PostAlerta",IF(ISNUMBER(VLOOKUP(A20,PRE,1,FALSE)),"PreAlerta",""))) -> PreAlerta | M20: =IF(ISNUMBER(VLOOKUP(A20,KEYWORDS,1,FALSE)),"C/PalabrasClaves","S/PalabrasClaves") -> S/PalabrasClaves | N20: 4) otros
A21: 22675852 | B21: Risk behaviors and sexually transmitted diseases in gay and heterosexual men attending an STD clinic in Tel Aviv, Israel: a cross-sectional study | C21: Mor Z, Shohat T, Goor Y, Dan M. | D21: Isr Med Assoc J. 2012 Mar;14(3):147-51. | E21: Mor Z | F21: Isr Med Assoc J | G21: 2012 | H21: 41069 | L21: =IF(ISNUMBER(VLOOKUP(A21,EXCL,1,FALSE)),"Excluido",IF(ISNUMBER(VLOOKUP(A21,POST,1,FALSE)),"PostAlerta",IF(ISNUMBER(VLOOKUP(A21,PRE,1,FALSE)),"PreAlerta",""))) -> PreAlerta | M21: =IF(ISNUMBER(VLOOKUP(A21,KEYWORDS,1,FALSE)),"C/PalabrasClaves","S/PalabrasClaves") -> S/PalabrasClaves | N21: 4) otros
A22: 22812177 | B22: [New genovariantes of Chlamydia trachomatis serovar L2 proctitis causing] | C22: Guerra-Infante FM, López-Hurtado M, Villagrana-Zesati R. | D22: Ginecol Obstet Mex. 2012 Mar;80(3):208-17. | E22: Guerra-Infante FM | F22: Ginecol Obstet Mex | G22: 2012 | H22: 41111 | L22: =IF(ISNUMBER(VLOOKUP(A22,EXCL,1,FALSE)),"Excluido",IF(ISNUMBER(VLOOKUP(A22,POST,1,FALSE)),"PostAlerta",IF(ISNUMBER(VLOOKUP(A22,PRE,1,FALSE)),"PreAlerta",""))) -> Excluido | M22: =IF(ISNUMBER(VLOOKUP(A22,KEYWORDS,1,FALSE)),"C/PalabrasClaves","S/PalabrasClaves") -> S/PalabrasClaves
A23: 22263556 | B23: Dendrimer-enabled modulation of gene expression in Chlamydia trachomatis | C23: Mishra MK, Gérard HC, Whittum-Hudson JA, Hudson AP, Kannan RM. | D23: Mol Pharm. 2012 Mar 5;9(3):413-21. doi: 10.1021/mp200512f. Epub 2012 Jan 30. | E23: Mishra MK | F23: Mol Pharm | G23: 2012 | H23: 40932 | K23: 10.1021/mp200512f | L23: =IF(ISNUMBER(VLOOKUP(A23,EXCL,1,FALSE)),"Excluido",IF(ISNUMBER(VLOOKUP(A23,POST,1,FALSE)),"PostAlerta",IF(ISNUMBER(VLOOKUP(A23,PRE,1,FALSE)),"PreAlerta",""))) -> PreAlerta | M23: =IF(ISNUMBER(VLOOKUP(A23,KEYWORDS,1,FALSE)),"C/PalabrasClaves","S/PalabrasClaves") -> S/PalabrasClaves | N23: 4) otros
A24: 22406642 | B24: Whole-genome analysis of diverse Chlamydia trachomatis strains identifies phylogenetic relationships masked by current clinical typing | C24: Harris SR, Clarke IN, Seth-Smith HM, Solomon AW, Cutcliffe LT, Marsh P, Skilton RJ, Holland MJ, Mabey D, Peeling RW, Lewis DA, Spratt BG, Unemo M, Persson K, Bjartling C, Brunham R, de Vries HJ, Morré SA, Speksnijder A, Bébéar CM, Clerc M, de Barbeyrac B, Parkhill J, Thomson NR. | D24: Nat Genet. 2012 Mar 11;44(4):413-9, S1. doi: 10.1038/ng.2214. | E24: Harris SR | F24: Nat Genet | G24: 2012 | H24: 40981 | I24: PMC3378690 | J24: UKMS41052 | K24: 10.1038/ng.2214 | L24: =IF(ISNUMBER(VLOOKUP(A24,EXCL,1,FALSE)),"Excluido",IF(ISNUMBER(VLOOKUP(A24,POST,1,FALSE)),"PostAlerta",IF(ISNUMBER(VLOOKUP(A24,PRE,1,FALSE)),"PreAlerta",""))) -> PreAlerta | M24: =IF(ISNUMBER(VLOOKUP(A24,KEYWORDS,1,FALSE)),"C/PalabrasClaves","S/PalabrasClaves") -> S/PalabrasClaves | N24: 4) otros
A25: 22210633 | B25: Low prevalence of asymptomatic sexually transmitted infections in HIV-infected heterosexuals visiting an HIV clinic in the Netherlands | C25: Heiligenberg M, van der Loeff MF, de Vries HJ, Speksnijder AG, Geerlings SE, Coutinho R, Prins M, Prins JM. | D25: AIDS. 2012 Mar 13;26(5):646-9. doi: 10.1097/QAD.0b013e3283504bbf. | E25: Heiligenberg M | F25: AIDS | G25: 2012 | H25: 40911 | K25: 10.1097/QAD.0b013e3283504bbf | L25: =IF(ISNUMBER(VLOOKUP(A25,EXCL,1,FALSE)),"Excluido",IF(ISNUMBER(VLOOKUP(A25,POST,1,FALSE)),"PostAlerta",IF(ISNUMBER(VLOOKUP(A25,PRE,1,FALSE)),"PreAlerta",""))) -> PreAlerta | M25: =IF(ISNUMBER(VLOOKUP(A25,KEYWORDS,1,FALSE)),"C/PalabrasClaves","S/PalabrasClaves") -> S/PalabrasClaves | N25: 4) otros
A26: 22436137 | B26: Phenotypic and genetic characterisation of bacterial sexually transmitted infections in Bissau, Guinea-Bissau, West Africa: a prospective cohort study | C26: Olsen B, Månsson F, Camara C, Monteiro M, Biai A, Alves A, Andersson S, Norrgren H, Unemo M. | D26: BMJ Open. 2012 Mar 20;2(2):e000636. doi: 10.1136/bmjopen-2011-000636. Print 2012. | E26: Olsen B | F26: BMJ Open | G26: 2012 | H26: 40991 | I26: PMC3329603 | K26: 10.1136/bmjopen-2011-000636 | L26: =IF(ISNUMBER(VLOOKUP(A26,EXCL,1,FALSE)),"Excluido",IF(ISNUMBER(VLOOKUP(A26,POST,1,FALSE)),"PostAlerta",IF(ISNUMBER(VLOOKUP(A26,PRE,1,FALSE)),"PreAlerta",""))) -> PreAlerta | M26: =IF(ISNUMBER(VLOOKUP(A26,KEYWORDS,1,FALSE)),"C/PalabrasClaves","S/PalabrasClaves") -> C/PalabrasClaves | N26: 1) Reporte de cepas resistentes | Q26: Listo | T26: The direct interrogation of fleeting intermediates by rapid-mixing kinetic methods has significantly advanced our understanding of enzymes that utilize dioxygen. The gas's modest aqueous solubility (<2 mM at 1 atm) presents a technical challenge to this approach, because it limits the rate of formation and extent of accumulation of intermediates. This challenge can be overcome by use of the heme enzyme chlorite dismutase (Cld) for the rapid, in situ generation of O(2) at concentrations far exceeding 2 mM. This method was used to define the O(2) concentration dependence of the reaction of the class Ic ribonucleotide reductase (RNR) from Chlamydia trachomatis, in which the enzyme's Mn(IV)/Fe(III) cofactor forms from a Mn(II)/Fe(II) complex and O(2) via a Mn(IV)/Fe(IV) intermediate, at effective O(2) concentrations as high as ~10 mM. With a more soluble receptor, myoglobin, an O(2) adduct accumulated to a concentration of >6 mM in <15 ms. Finally, the C-H-bond-cleaving Fe(IV)-oxo complex, J, in taurine:α-ketoglutarate dioxygenase and superoxo-Fe(2)(III/III) complex, G, in myo-inositol oxygenase, and the tyrosyl-radical-generating Fe(2)(III/IV) intermediate, X, in Escherichia coli RNR, were all accumulated to yields more than twice those previously attained. This means of in situ O(2) evolution permits a >5 mM "pulse" of O(2) to be generated in <1 ms at the easily accessible Cld concentration of 50 μM. It should therefore significantly extend the range of kinetic and spectroscopic experiments that can routinely be undertaken in the study of these enzymes and could also facilitate resolution of mechanistic pathways in cases of either sluggish or thermodynamically unfavorable O(2) addition steps. | U26: Yes | V26: No | W26: No | X26: They conducted a study of 3 types of bacteria, among which they found and characterized C. trachomatis
A27: 22440143 | B27: [WITHDRAWN: Prevalence and associated factors of Chlamydia trachomatis infection in young prisoners of Catalonia, Spain.] | C27: López Corbeto E, Carnicer-Pont D, Lugo R, Gonzalez V, Bascuñana E, Lleopart N, Barbero L, Humet V, Casabona J; Grupo de Estudio CT Prisiones. | D27: Med Clin (Barc). 2012 Mar 21:S0025-7753(12)00137-6. doi: 10.1016/j.medcli.2012.01.024. Online ahead of print. | E27: López Corbeto E | F27: Med Clin (Barc) | G27: 2012 | H27: 40992 | K27: 10.1016/j.medcli.2012.01.024 | L27: =IF(ISNUMBER(VLOOKUP(A27,EXCL,1,FALSE)),"Excluido",IF(ISNUMBER(VLOOKUP(A27,POST,1,FALSE)),"PostAlerta",IF(ISNUMBER(VLOOKUP(A27,PRE,1,FALSE)),"PreAlerta",""))) -> PreAlerta | M27: =IF(ISNUMBER(VLOOKUP(A27,KEYWORDS,1,FALSE)),"C/PalabrasClaves","S/PalabrasClaves") -> S/PalabrasClaves | N27: 4) otros
A28: 22668947 | B28: Inflammatory pathways in cervical cancer - the UCT contribution | C28: Sales KJ, Katz AA. | D28: S Afr Med J. 2012 Mar 23;102(6):493-6. doi: 10.7196/samj.5532. | E28: Sales KJ | F28: S Afr Med J | G28: 2012 | H28: 41067 | K28: 10.7196/samj.5532 | L28: =IF(ISNUMBER(VLOOKUP(A28,EXCL,1,FALSE)),"Excluido",IF(ISNUMBER(VLOOKUP(A28,POST,1,FALSE)),"PostAlerta",IF(ISNUMBER(VLOOKUP(A28,PRE,1,FALSE)),"PreAlerta",""))) -> Excluido | M28: =IF(ISNUMBER(VLOOKUP(A28,KEYWORDS,1,FALSE)),"C/PalabrasClaves","S/PalabrasClaves") -> S/PalabrasClaves
A29: 22341824 | B29: Prevention of sexually transmitted infections in urban communities (Peru PREVEN): a multicomponent community-randomised controlled trial | C29: García PJ, Holmes KK, Cárcamo CP, Garnett GP, Hughes JP, Campos PE, Whittington WL; Peru PREVEN Study Team. | D29: Lancet. 2012 Mar 24;379(9821):1120-8. doi: 10.1016/S0140-6736(11)61846-1. Epub 2012 Feb 15. | E29: García PJ | F29: Lancet | G29: 2012 | H29: 40960 | I29: PMC3315635 | K29: 10.1016/S0140-6736(11)61846-1 | L29: =IF(ISNUMBER(VLOOKUP(A29,EXCL,1,FALSE)),"Excluido",IF(ISNUMBER(VLOOKUP(A29,POST,1,FALSE)),"PostAlerta",IF(ISNUMBER(VLOOKUP(A29,PRE,1,FALSE)),"PreAlerta",""))) -> Excluido | M29: =IF(ISNUMBER(VLOOKUP(A29,KEYWORDS,1,FALSE)),"C/PalabrasClaves","S/PalabrasClaves") -> S/PalabrasClaves
A30: 22456736 | B30: Genome-wide recombination in Chlamydia trachomatis | C30: Joseph SJ, Read TD. | D30: Nat Genet. 2012 Mar 28;44(4):364-6. doi: 10.1038/ng.2225. | E30: Joseph SJ | F30: Nat Genet | G30: 2012 | H30: 40998 | K30: 10.1038/ng.2225 | L30: =IF(ISNUMBER(VLOOKUP(A30,EXCL,1,FALSE)),"Excluido",IF(ISNUMBER(VLOOKUP(A30,POST,1,FALSE)),"PostAlerta",IF(ISNUMBER(VLOOKUP(A30,PRE,1,FALSE)),"PreAlerta",""))) -> PreAlerta | M30: =IF(ISNUMBER(VLOOKUP(A30,KEYWORDS,1,FALSE)),"C/PalabrasClaves","S/PalabrasClaves") -> S/PalabrasClaves | N30: 4) otros
A31: 21938501 | B31: Chlamydial infection in a high risk population: association with vaginal flora patterns | C31: Marconi C, Donders GG, Martin LF, Ramos BR, Duarte MT, Parada CM, Tristão AR, Silva MG. | D31: Arch Gynecol Obstet. 2012 Apr;285(4):1013-8. doi: 10.1007/s00404-011-2085-5. Epub 2011 Sep 22. | E31: Marconi C | F31: Arch Gynecol Obstet | G31: 2012 | H31: 40809 | K31: 10.1007/s00404-011-2085-5 | L31: =IF(ISNUMBER(VLOOKUP(A31,EXCL,1,FALSE)),"Excluido",IF(ISNUMBER(VLOOKUP(A31,POST,1,FALSE)),"PostAlerta",IF(ISNUMBER(VLOOKUP(A31,PRE,1,FALSE)),"PreAlerta",""))) -> PreAlerta | M31: =IF(ISNUMBER(VLOOKUP(A31,KEYWORDS,1,FALSE)),"C/PalabrasClaves","S/PalabrasClaves") -> S/PalabrasClaves | N31: 4) otros
A32: 22141597 | B32: Amoebal host range, host-free survival and disinfection susceptibility of environmental Chlamydiae as compared to Chlamydia trachomatis | C32: Coulon C, Eterpi M, Greub G, Collignon A, McDonnell G, Thomas V. | D32: FEMS Immunol Med Microbiol. 2012 Apr;64(3):364-73. doi: 10.1111/j.1574-695X.2011.00919.x. Epub 2012 Jan 3. | E32: Coulon C | F32: FEMS Immunol Med Microbiol | G32: 2012 | H32: 40884 | K32: 10.1111/j.1574-695X.2011.00919.x | L32: =IF(ISNUMBER(VLOOKUP(A32,EXCL,1,FALSE)),"Excluido",IF(ISNUMBER(VLOOKUP(A32,POST,1,FALSE)),"PostAlerta",IF(ISNUMBER(VLOOKUP(A32,PRE,1,FALSE)),"PreAlerta",""))) -> PreAlerta | M32: =IF(ISNUMBER(VLOOKUP(A32,KEYWORDS,1,FALSE)),"C/PalabrasClaves","S/PalabrasClaves") -> S/PalabrasClaves | N32: 4) otros
A33: 22199134 | B33: Testing the fathers: carrying out HIV and STI tests on partners of pregnant women | C33: Dhairyawan R, Creighton S, Sivyour L, Anderson J. | D33: Sex Transm Infect. 2012 Apr;88(3):184-6. doi: 10.1136/sextrans-2011-050232. Epub 2011 Dec 23. | E33: Dhairyawan R | F33: Sex Transm Infect | G33: 2012 | H33: 40904 | K33: 10.1136/sextrans-2011-050232 | L33: =IF(ISNUMBER(VLOOKUP(A33,EXCL,1,FALSE)),"Excluido",IF(ISNUMBER(VLOOKUP(A33,POST,1,FALSE)),"PostAlerta",IF(ISNUMBER(VLOOKUP(A33,PRE,1,FALSE)),"PreAlerta",""))) -> PreAlerta | M33: =IF(ISNUMBER(VLOOKUP(A33,KEYWORDS,1,FALSE)),"C/PalabrasClaves","S/PalabrasClaves") -> S/PalabrasClaves | N33: 4) otros
A34: 22213681 | B34: The cost and cost-effectiveness of opportunistic screening for Chlamydia trachomatis in Ireland | C34: Gillespie P, O'Neill C, Adams E, Turner K, O'Donovan D, Brugha R, Vaughan D, O'Connell E, Cormican M, Balfe M, Coleman C, Fitzgerald M, Fleming C. | D34: Sex Transm Infect. 2012 Apr;88(3):222-8. doi: 10.1136/sextrans-2011-050067. Epub 2012 Jan 2. | E34: Gillespie P | F34: Sex Transm Infect | G34: 2012 | H34: 40912 | K34: 10.1136/sextrans-2011-050067 | L34: =IF(ISNUMBER(VLOOKUP(A34,EXCL,1,FALSE)),"Excluido",IF(ISNUMBER(VLOOKUP(A34,POST,1,FALSE)),"PostAlerta",IF(ISNUMBER(VLOOKUP(A34,PRE,1,FALSE)),"PreAlerta",""))) -> PreAlerta | M34: =IF(ISNUMBER(VLOOKUP(A34,KEYWORDS,1,FALSE)),"C/PalabrasClaves","S/PalabrasClaves") -> S/PalabrasClaves | N34: 4) otros
A35: 22215696 | B35: Systematic selection of screening participants by risk score in a Chlamydia screening programme is feasible and effective | C35: van den Broek IV, Brouwers EE, Götz HM, van Bergen JE, Op de Coul EL, Fennema JS, Koekenbier RH, Pars LL, van Ravesteijn SM, Hoebe CJ. | D35: Sex Transm Infect. 2012 Apr;88(3):205-11. doi: 10.1136/sextrans-2011-050219. Epub 2012 Jan 3. | E35: van den Broek IV | F35: Sex Transm Infect | G35: 2012 | H35: 40913 | K35: 10.1136/sextrans-2011-050219 | L35: =IF(ISNUMBER(VLOOKUP(A35,EXCL,1,FALSE)),"Excluido",IF(ISNUMBER(VLOOKUP(A35,POST,1,FALSE)),"PostAlerta",IF(ISNUMBER(VLOOKUP(A35,PRE,1,FALSE)),"PreAlerta",""))) -> PreAlerta | M35: =IF(ISNUMBER(VLOOKUP(A35,KEYWORDS,1,FALSE)),"C/PalabrasClaves","S/PalabrasClaves") -> S/PalabrasClaves | N35: 4) otros
A36: 22259215 | B36: Comparison of three assays for detection of Chlamydia trachomatis and Neisseria gonorrhoeae in SurePath Pap samples and the role of pre- and postcytology testing | C36: Chernesky M, Jang D, Portillo E, Smieja M, Kapala J, Doucette C, Sumner J, Ewert R, MacRitchie C, Gilchrist J. | D36: J Clin Microbiol. 2012 Apr;50(4):1281-4. doi: 10.1128/JCM.06595-11. Epub 2012 Jan 18. | E36: Chernesky M | F36: J Clin Microbiol | G36: 2012 | H36: 40928 | I36: PMC3318522 | K36: 10.1128/JCM.06595-11 | L36: =IF(ISNUMBER(VLOOKUP(A36,EXCL,1,FALSE)),"Excluido",IF(ISNUMBER(VLOOKUP(A36,POST,1,FALSE)),"PostAlerta",IF(ISNUMBER(VLOOKUP(A36,PRE,1,FALSE)),"PreAlerta",""))) -> PreAlerta | M36: =IF(ISNUMBER(VLOOKUP(A36,KEYWORDS,1,FALSE)),"C/PalabrasClaves","S/PalabrasClaves") -> S/PalabrasClaves | N36: 4) otros
A37: 22290151 | B37: Chlamydia muridarum T cell antigens and adjuvants that induce protective immunity in mice | C37: Yu H, Karunakaran KP, Jiang X, Shen C, Andersen P, Brunham RC. | D37: Infect Immun. 2012 Apr;80(4):1510-8. doi: 10.1128/IAI.06338-11. Epub 2012 Jan 30. | E37: Yu H | F37: Infect Immun | G37: 2012 | H37: 40940 | I37: PMC3318408 | K37: 10.1128/IAI.06338-11 | L37: =IF(ISNUMBER(VLOOKUP(A37,EXCL,1,FALSE)),"Excluido",IF(ISNUMBER(VLOOKUP(A37,POST,1,FALSE)),"PostAlerta",IF(ISNUMBER(VLOOKUP(A37,PRE,1,FALSE)),"PreAlerta",""))) -> PreAlerta | M37: =IF(ISNUMBER(VLOOKUP(A37,KEYWORDS,1,FALSE)),"C/PalabrasClaves","S/PalabrasClaves") -> C/PalabrasClaves | N37: 3) immunization | Q37: Listo | T37: Major impediments to a Chlamydia vaccine lie in discovering T cell antigens and polarizing adjuvants that stimulate protective immunity. We previously reported the discovery of three T cell antigens (PmpG, PmpF, and RplF) via immunoproteomics that elicited protective immunity in the murine genital tract infection model against Chlamydia infection after adoptive transfer of antigen-pulsed dendritic cells. To expand the T cell antigen repertoire necessary for a Chlamydia vaccine, we evaluated 10 new Chlamydia T cell antigens discovered via immunoproteomics in addition to the 3 antigens reported earlier as a molecular subunit vaccine. We first tested five adjuvants, including three cationic liposome formulations (dimethyldioctadecylammonium bromide-monophosphoryl lipid A [DDA-MPL], DDA-trehalose 6,6'-dibehenate [DDA-TDB {CAF01}], and DDA-monomycolyl glycerol [DDA-MMG {CAF04}]), Montanide ISA720-CpG-ODN1826, and alum using the PmpG protein as a model T cell antigen in the mouse genital tract infection model. The results showed that the cationic liposomal adjuvants DDA-MPL and DDA-TDB elicited the best protective immune responses, characterized by multifunctional CD4(+) T cells coexpressing gamma interferon (IFN-γ) and tumor necrosis factor alpha (TNF-α), and reduced infection by more than 3 logs. Using DDA-MPL as an adjuvant, we found that 7 of 13 Chlamydia T cell antigens (PmpG, PmpE, PmpF, Aasf, RplF, TC0420, and TC0825) conferred protection better than or equal to that of the reference vaccine antigen, major outer membrane protein (MOMP). Pools of membrane/secreted proteins, cytoplasmic proteins, and hypothetical proteins were tested individually or in combination. Immunization with combinations protected as well as the best individual protein in that combination. The T cell antigens and adjuvants discovered in this study are of further interest in the development of a molecularly defined Chlamydia vaccine. | U37: No | V37: No | W37: Yes | X37: They evaluated 10 novel chlamydia T-cell antigens discovered by immunoproteomics, in addition to the 3 antigens previously reported as a molecular subunit vaccine.
A38: 22371042 | B38: Correlation of Atopobium vaginae Amount With Bacterial Vaginosis Markers | C38: Marconi C, Cruciani F, Vitali B, Donders GG. | D38: J Low Genit Tract Dis. 2012 Apr;16(2):127-32. doi: 10.1097/LGT.0b013e31823c79c4. | E38: Marconi C | F38: J Low Genit Tract Dis | G38: 2012 | H38: 40968 | K38: 10.1097/LGT.0b013e31823c79c4 | L38: =IF(ISNUMBER(VLOOKUP(A38,EXCL,1,FALSE)),"Excluido",IF(ISNUMBER(VLOOKUP(A38,POST,1,FALSE)),"PostAlerta",IF(ISNUMBER(VLOOKUP(A38,PRE,1,FALSE)),"PreAlerta",""))) -> PreAlerta | M38: =IF(ISNUMBER(VLOOKUP(A38,KEYWORDS,1,FALSE)),"C/PalabrasClaves","S/PalabrasClaves") -> S/PalabrasClaves | N38: 4) otros
A39: 22384841 | B39: Potential mechanisms for increased HIV-1 transmission across the endocervical epithelium during C. trachomatis infection | C39: Schust DJ, Ibana JA, Buckner LR, Ficarra M, Sugimoto J, Amedee AM, Quayle AJ. | D39: Curr HIV Res. 2012 Apr;10(3):218-27. doi: 10.2174/157016212800618093. | E39: Schust DJ | F39: Curr HIV Res | G39: 2012 | H39: 40974 | I39: PMC3870887 | J39: NIHMS534767 | K39: 10.2174/157016212800618093 | L39: =IF(ISNUMBER(VLOOKUP(A39,EXCL,1,FALSE)),"Excluido",IF(ISNUMBER(VLOOKUP(A39,POST,1,FALSE)),"PostAlerta",IF(ISNUMBER(VLOOKUP(A39,PRE,1,FALSE)),"PreAlerta",""))) -> Excluido | M39: =IF(ISNUMBER(VLOOKUP(A39,KEYWORDS,1,FALSE)),"C/PalabrasClaves","S/PalabrasClaves") -> S/PalabrasClaves
A40: 22416272 | B40: Azithromycin antimicrobial resistance and genital Chlamydia trachomatis infection: duration of therapy may be the key to improving efficacy | C40: Horner PJ. | D40: Sex Transm Infect. 2012 Apr;88(3):154-6. doi: 10.1136/sextrans-2011-050385. | E40: Horner PJ | F40: Sex Transm Infect | G40: 2012 | H40: 40983 | K40: 10.1136/sextrans-2011-050385 | L40: =IF(ISNUMBER(VLOOKUP(A40,EXCL,1,FALSE)),"Excluido",IF(ISNUMBER(VLOOKUP(A40,POST,1,FALSE)),"PostAlerta",IF(ISNUMBER(VLOOKUP(A40,PRE,1,FALSE)),"PreAlerta",""))) -> PreAlerta | M40: =IF(ISNUMBER(VLOOKUP(A40,KEYWORDS,1,FALSE)),"C/PalabrasClaves","S/PalabrasClaves") -> C/PalabrasClaves | N40: 2) Nuevos tratamientos | Q40: Excluir | U40: No | V40: No | W40: No | X40: It is a publishing house
A41: 22419642 | B41: Chlamydia and gonorrhea screening using urine-based nucleic acid amplification testing among males entering New York City jails: a pilot study | C41: Franklin WB, Katyal M, Mahajan R, Parvez FM. | D41: J Correct Health Care. 2012 Apr;18(2):120-30. doi: 10.1177/1078345811435767. Epub 2012 Mar 14. | E41: Franklin WB | F41: J Correct Health Care | G41: 2012 | H41: 40984 | K41: 10.1177/1078345811435767 | L41: =IF(ISNUMBER(VLOOKUP(A41,EXCL,1,FALSE)),"Excluido",IF(ISNUMBER(VLOOKUP(A41,POST,1,FALSE)),"PostAlerta",IF(ISNUMBER(VLOOKUP(A41,PRE,1,FALSE)),"PreAlerta",""))) -> PreAlerta | M41: =IF(ISNUMBER(VLOOKUP(A41,KEYWORDS,1,FALSE)),"C/PalabrasClaves","S/PalabrasClaves") -> S/PalabrasClaves | N41: 4) otros
A42: 22421690 | B42: Periodical antibiotic treatment for the control of gonococcal and chlamydial infections among sex workers in Benin and Ghana: a cluster-randomized placebo-controlled trial | C42: Labbé AC, Pépin J, Khonde N, Dzokoto A, Méda H, Asamoah-Adu C, Mayaud P, Mabey D, Demers E, Alary M. | D42: Sex Transm Dis. 2012 Apr;39(4):253-9. doi: 10.1097/OLQ.0b013e318244aaa0. | E42: Labbé AC | F42: Sex Transm Dis | G42: 2012 | H42: 40985 | K42: 10.1097/OLQ.0b013e318244aaa0 | L42: =IF(ISNUMBER(VLOOKUP(A42,EXCL,1,FALSE)),"Excluido",IF(ISNUMBER(VLOOKUP(A42,POST,1,FALSE)),"PostAlerta",IF(ISNUMBER(VLOOKUP(A42,PRE,1,FALSE)),"PreAlerta",""))) -> Excluido | M42: =IF(ISNUMBER(VLOOKUP(A42,KEYWORDS,1,FALSE)),"C/PalabrasClaves","S/PalabrasClaves") -> S/PalabrasClaves
A43: 22421691 | B43: Estimation of the burden of disease and costs of genital Chlamydia trachomatis infection in Canada | C43: Tuite AR, Jayaraman GC, Allen VG, Fisman DN. | D43: Sex Transm Dis. 2012 Apr;39(4):260-7. doi: 10.1097/OLQ.0b013e31824717ae. | E43: Tuite AR | F43: Sex Transm Dis | G43: 2012 | H43: 40985 | K43: 10.1097/OLQ.0b013e31824717ae | L43: =IF(ISNUMBER(VLOOKUP(A43,EXCL,1,FALSE)),"Excluido",IF(ISNUMBER(VLOOKUP(A43,POST,1,FALSE)),"PostAlerta",IF(ISNUMBER(VLOOKUP(A43,PRE,1,FALSE)),"PreAlerta",""))) -> PreAlerta | M43: =IF(ISNUMBER(VLOOKUP(A43,KEYWORDS,1,FALSE)),"C/PalabrasClaves","S/PalabrasClaves") -> S/PalabrasClaves | N43: 4) otros
A44: 22421693 | B44: The effect of medical male circumcision on urogenital Mycoplasma genitalium among men in Kisumu, Kenya | C44: Mehta SD, Gaydos C, Maclean I, Odoyo-June E, Moses S, Agunda L, Quinn N, Bailey RC. | D44: Sex Transm Dis. 2012 Apr;39(4):276-80. doi: 10.1097/OLQ.0b013e318240189c. | E44: Mehta SD | F44: Sex Transm Dis | G44: 2012 | H44: 40985 | I44: PMC3306596 | J44: NIHMS342151 | K44: 10.1097/OLQ.0b013e318240189c | L44: =IF(ISNUMBER(VLOOKUP(A44,EXCL,1,FALSE)),"Excluido",IF(ISNUMBER(VLOOKUP(A44,POST,1,FALSE)),"PostAlerta",IF(ISNUMBER(VLOOKUP(A44,PRE,1,FALSE)),"PreAlerta",""))) -> Excluido | M44: =IF(ISNUMBER(VLOOKUP(A44,KEYWORDS,1,FALSE)),"C/PalabrasClaves","S/PalabrasClaves") -> S/PalabrasClaves
A45: 22424245 | B45: Chlamydia testing patterns for commercially insured women, 2008 | C45: Tao G, Hoover KW, Kent CK. | D45: Am J Prev Med. 2012 Apr;42(4):337-41. doi: 10.1016/j.amepre.2011.11.013. | E45: Tao G | F45: Am J Prev Med | G45: 2012 | H45: 40988 | K45: 10.1016/j.amepre.2011.11.013 | L45: =IF(ISNUMBER(VLOOKUP(A45,EXCL,1,FALSE)),"Excluido",IF(ISNUMBER(VLOOKUP(A45,POST,1,FALSE)),"PostAlerta",IF(ISNUMBER(VLOOKUP(A45,PRE,1,FALSE)),"PreAlerta",""))) -> PreAlerta | M45: =IF(ISNUMBER(VLOOKUP(A45,KEYWORDS,1,FALSE)),"C/PalabrasClaves","S/PalabrasClaves") -> S/PalabrasClaves | N45: 4) otros
A46: 22561757 | B46: Comparison between ICT and PCR for diagnosis of Chlamydia trachomatis | C46: Khan ER, Hossain MA, Paul SK, Mahmud C, Hasan MM, Rahman MM, Nahar K, Kubayashi N. | D46: Mymensingh Med J. 2012 Apr;21(2):190-4. | E46: Khan ER | F46: Mymensingh Med J | G46: 2012 | H46: 41037 | L46: =IF(ISNUMBER(VLOOKUP(A46,EXCL,1,FALSE)),"Excluido",IF(ISNUMBER(VLOOKUP(A46,POST,1,FALSE)),"PostAlerta",IF(ISNUMBER(VLOOKUP(A46,PRE,1,FALSE)),"PreAlerta",""))) -> PreAlerta | M46: =IF(ISNUMBER(VLOOKUP(A46,KEYWORDS,1,FALSE)),"C/PalabrasClaves","S/PalabrasClaves") -> S/PalabrasClaves | N46: 4) otros
A47: 22707135 | B47: Chlamydia trachomatis serovar distribution and other sexually transmitted coinfections in subjects attending an STD outpatients clinic in Italy | C47: Marangoni A, Foschi C, Nardini P, D'Antuono A, Banzola N, Di Francesco A, Ostanello F, Russo I, Donati M, Cevenini R. | D47: New Microbiol. 2012 Apr;35(2):215-9. Epub 2012 Mar 31. | E47: Marangoni A | F47: New Microbiol | G47: 2012 | H47: 41079 | L47: =IF(ISNUMBER(VLOOKUP(A47,EXCL,1,FALSE)),"Excluido",IF(ISNUMBER(VLOOKUP(A47,POST,1,FALSE)),"PostAlerta",IF(ISNUMBER(VLOOKUP(A47,PRE,1,FALSE)),"PreAlerta",""))) -> PreAlerta | M47: =IF(ISNUMBER(VLOOKUP(A47,KEYWORDS,1,FALSE)),"C/PalabrasClaves","S/PalabrasClaves") -> S/PalabrasClaves | N47: 4) otros
A48: 22471518 | B48: Frequency of Chlamydia trachomatis in Ureaplasma-positive healthy women attending their first prenatal visit in a community hospital in Sapporo, Japan | C48: Yamazaki T, Matsumoto M, Matsuo J, Abe K, Minami K, Yamaguchi H. | D48: BMC Infect Dis. 2012 Apr 2;12:82. doi: 10.1186/1471-2334-12-82. | E48: Yamazaki T | F48: BMC Infect Dis | G48: 2012 | H48: 41004 | I48: PMC3342208 | K48: 10.1186/1471-2334-12-82 | L48: =IF(ISNUMBER(VLOOKUP(A48,EXCL,1,FALSE)),"Excluido",IF(ISNUMBER(VLOOKUP(A48,POST,1,FALSE)),"PostAlerta",IF(ISNUMBER(VLOOKUP(A48,PRE,1,FALSE)),"PreAlerta",""))) -> PreAlerta | M48: =IF(ISNUMBER(VLOOKUP(A48,KEYWORDS,1,FALSE)),"C/PalabrasClaves","S/PalabrasClaves") -> S/PalabrasClaves | N48: 4) otros
A49: 22534388 | B49: Pelvic inflammatory disease | C49: Gradison M. | D49: Am Fam Physician. 2012 Apr 15;85(8):791-6. | E49: Gradison M | F49: Am Fam Physician | G49: 2012 | H49: 41026 | L49: =IF(ISNUMBER(VLOOKUP(A49,EXCL,1,FALSE)),"Excluido",IF(ISNUMBER(VLOOKUP(A49,POST,1,FALSE)),"PostAlerta",IF(ISNUMBER(VLOOKUP(A49,PRE,1,FALSE)),"PreAlerta",""))) -> Excluido | M49: =IF(ISNUMBER(VLOOKUP(A49,KEYWORDS,1,FALSE)),"C/PalabrasClaves","S/PalabrasClaves") -> S/PalabrasClaves
A50: 22387629 | B50: Protection of pigs against genital Chlamydia trachomatis challenge by parenteral or mucosal DNA immunization | C50: Schautteet K, De Clercq E, Jönsson Y, Lagae S, Chiers K, Cox E, Vanrompay D. | D50: Vaccine. 2012 Apr 16;30(18):2869-81. doi: 10.1016/j.vaccine.2012.02.044. Epub 2012 Mar 3. | E50: Schautteet K | F50: Vaccine | G50: 2012 | H50: 40974 | K50: 10.1016/j.vaccine.2012.02.044 | L50: =IF(ISNUMBER(VLOOKUP(A50,EXCL,1,FALSE)),"Excluido",IF(ISNUMBER(VLOOKUP(A50,POST,1,FALSE)),"PostAlerta",IF(ISNUMBER(VLOOKUP(A50,PRE,1,FALSE)),"PreAlerta",""))) -> PreAlerta | M50: =IF(ISNUMBER(VLOOKUP(A50,KEYWORDS,1,FALSE)),"C/PalabrasClaves","S/PalabrasClaves") -> S/PalabrasClaves | N50: 3) immunization | Q50: Listo | T50: The current study evaluates combined aerosol-vaginal delivery of a MOMP-based Chlamydia trachomatis (serovar E) DNA vaccine in a pig genital challenge model. Most non-replicating antigens are rather poor mucosal immunogens in comparison to replicating antigens. Therefore, a mucosal administered DNA vaccine, which actually mimics a live vaccine, could be promising. Protection was promoted by plasmids encoding the porcine granulocyte macrophage-colony stimulating factor (pcDNA3.1zeo::GM-CSF), the Escherichia coli thermo-labile enterotoxin (LT) subunit A (plasmid PJV2004::LTa) and subunit B (plasmid PJV2005::LTb). Mucosal C. trachomatis DNA vaccination induced significant protection against genital C. trachomatis challenge although the infection could not be eradicated. Intradermal immunization was significantly less efficient in protecting experimentally infected pigs. Protection was correlated with efficient T cell priming and significantly higher serum IgA titers following primo vaccination. | U50: No | V50: No | W50: Yes | X50: They use different methods (spray, intradermal) to administer a vaccine.
A51: 22564463 | B51: Mycoplasma genitalium presence, resistance and epidemiology in Greenland | C51: Gesink DC, Mulvad G, Montgomery-Andersen R, Poppel U, Montgomery-Andersen S, Binzer A, Vernich L, Frosst G, Stenz F, Rink E, Olsen OR, Koch A, Jensen JS. | D51: Int J Circumpolar Health. 2012 Apr 16;71:1-8. doi: 10.3402/ijch.v71i0.18203. | E51: Gesink DC | F51: Int J Circumpolar Health | G51: 2012 | H51: 41038 | I51: PMC3417636 | K51: 10.3402/ijch.v71i0.18203 | L51: =IF(ISNUMBER(VLOOKUP(A51,EXCL,1,FALSE)),"Excluido",IF(ISNUMBER(VLOOKUP(A51,POST,1,FALSE)),"PostAlerta",IF(ISNUMBER(VLOOKUP(A51,PRE,1,FALSE)),"PreAlerta",""))) -> PreAlerta | M51: =IF(ISNUMBER(VLOOKUP(A51,KEYWORDS,1,FALSE)),"C/PalabrasClaves","S/PalabrasClaves") -> C/PalabrasClaves | N51: 1) Reporte de cepas resistentes | Q51: Listo | T51: Objectives: Greenland reports the highest rates of chlamydial infection and gonorrhea in the Arctic. Our objective was to determine the presence, and describe the basic epidemiology, of Mycoplasma genitalium for Greenland. Study design: Cross-sectional study. Methods: 314 residents from Nuuk and Sisimiut, between the ages of 15 and 65 years, participated in "Inuulluataarneq" (the Greenland Sexual Health Project) between July 2008 and November 2009. Participants provided self-collected samples for sexually transmitted infection (STI) testing and completed a sexual health survey. Descriptive statistics and logistic regression were used to summarize the basic characteristics of STI cases overall and M. genitalium and Chlamydia trachomatis specifically. Clinically relevant characteristics in each full model were gender (male or female), age (in years), age at sexual debut (in years), number of sexual partners in the past 3 months (continuous) and history of forced sex and community. Results: The overall prevalence of STIs was 19.0%, specifically: 9.8% for M. genitalium and 9.4% for C. trachomatis; 100% of M. genitalium-positive cases carried macrolide resistance determinants. Being female [OR = 3.2; 95% confidence interval (CI): 1.1-9.8] and younger age (OR = 0.9; 95% CI: 0.9-1.0) were associated with M. genitalium positivity. Age was also associated with C. trachomatis (OR = 0.9; 95% CI: 0.8-0.9) and STI positivity overall (OR = 0.9; 95% CI: 0.9-0.9). Conclusions: We observed a high prevalence of M. genitalium and macrolide resistance in this study. A better understanding of M. genitalium sequelae is needed to inform policy around testing, treatment, control and antibiotic use. | U51: No | V51: No | W51: No | X51: The resistant strain is Mycoplasma
A52: 22511109 | B52: [Klamydia or chlamydia, uretritt or urethritt?] | C52: Moi H. | D52: Tidsskr Nor Laegeforen. 2012 Apr 17;132(7):864. doi: 10.4045/tidsskr.12.0025. | E52: Moi H | F52: Tidsskr Nor Laegeforen | G52: 2012 | H52: 41018 | K52: 10.4045/tidsskr.12.0025 | L52: =IF(ISNUMBER(VLOOKUP(A52,EXCL,1,FALSE)),"Excluido",IF(ISNUMBER(VLOOKUP(A52,POST,1,FALSE)),"PostAlerta",IF(ISNUMBER(VLOOKUP(A52,PRE,1,FALSE)),"PreAlerta",""))) -> PreAlerta | M52: =IF(ISNUMBER(VLOOKUP(A52,KEYWORDS,1,FALSE)),"C/PalabrasClaves","S/PalabrasClaves") -> S/PalabrasClaves | Q52: Revisar
A53: 22513915 | B53: Face washing promotion for preventing active trachoma | C53: Ejere HO, Alhassan MB, Rabiu M. | D53: Cochrane Database Syst Rev. 2012 Apr 18;4(4):CD003659. doi: 10.1002/14651858.CD003659.pub3. | E53: Ejere HO | F53: Cochrane Database Syst Rev | G53: 2012 | H53: 41019 | I53: PMC4422487 | J53: NIHMS644957 | K53: 10.1002/14651858.CD003659.pub3 | L53: =IF(ISNUMBER(VLOOKUP(A53,EXCL,1,FALSE)),"Excluido",IF(ISNUMBER(VLOOKUP(A53,POST,1,FALSE)),"PostAlerta",IF(ISNUMBER(VLOOKUP(A53,PRE,1,FALSE)),"PreAlerta",""))) -> Excluido | M53: =IF(ISNUMBER(VLOOKUP(A53,KEYWORDS,1,FALSE)),"C/PalabrasClaves","S/PalabrasClaves") -> C/PalabrasClaves
A54: 22465117 | B54: Chlamydia trachomatis Tarp cooperates with the Arp2/3 complex to increase the rate of actin polymerization | C54: Jiwani S, Ohr RJ, Fischer ER, Hackstadt T, Alvarado S, Romero A, Jewett TJ. | D54: Biochem Biophys Res Commun. 2012 Apr 20;420(4):816-21. doi: 10.1016/j.bbrc.2012.03.080. Epub 2012 Mar 23. | E54: Jiwani S | F54: Biochem Biophys Res Commun | G54: 2012 | H54: 41002 | I54: PMC3334425 | J54: NIHMS366987 | K54: 10.1016/j.bbrc.2012.03.080 | L54: =IF(ISNUMBER(VLOOKUP(A54,EXCL,1,FALSE)),"Excluido",IF(ISNUMBER(VLOOKUP(A54,POST,1,FALSE)),"PostAlerta",IF(ISNUMBER(VLOOKUP(A54,PRE,1,FALSE)),"PreAlerta",""))) -> PreAlerta | M54: =IF(ISNUMBER(VLOOKUP(A54,KEYWORDS,1,FALSE)),"C/PalabrasClaves","S/PalabrasClaves") -> S/PalabrasClaves | N54: 4) otros
A55: 22545922 | B55: Chlamydia screening in England: a qualitative study of the narrative behind the policy | C55: Sheringham J, Baraitser P, Simms I, Hart G, Raine R. | D55: BMC Public Health. 2012 Apr 30;12:317. doi: 10.1186/1471-2458-12-317. | E55: Sheringham J | F55: BMC Public Health | G55: 2012 | H55: 41031 | I55: PMC3458993 | K55: 10.1186/1471-2458-12-317 | L55: =IF(ISNUMBER(VLOOKUP(A55,EXCL,1,FALSE)),"Excluido",IF(ISNUMBER(VLOOKUP(A55,POST,1,FALSE)),"PostAlerta",IF(ISNUMBER(VLOOKUP(A55,PRE,1,FALSE)),"PreAlerta",""))) -> PreAlerta | M55: =IF(ISNUMBER(VLOOKUP(A55,KEYWORDS,1,FALSE)),"C/PalabrasClaves","S/PalabrasClaves") -> S/PalabrasClaves | N55: 4) otros
A56: 21762193 | B56: The effect of bacterial contamination of semen on sperm chromatin integrity and standard semen parameters in men from infertile couples | C56: Rybar R, Prinosilova P, Kopecka V, Hlavicova J, Veznik Z, Zajicova A, Rubes J. | D56: Andrologia. 2012 May;44 Suppl 1:410-8. doi: 10.1111/j.1439-0272.2011.01198.x. Epub 2011 Jul 18. | E56: Rybar R | F56: Andrologia | G56: 2012 | H56: 40743 | K56: 10.1111/j.1439-0272.2011.01198.x | L56: =IF(ISNUMBER(VLOOKUP(A56,EXCL,1,FALSE)),"Excluido",IF(ISNUMBER(VLOOKUP(A56,POST,1,FALSE)),"PostAlerta",IF(ISNUMBER(VLOOKUP(A56,PRE,1,FALSE)),"PreAlerta",""))) -> PreAlerta | M56: =IF(ISNUMBER(VLOOKUP(A56,KEYWORDS,1,FALSE)),"C/PalabrasClaves","S/PalabrasClaves") -> S/PalabrasClaves | N56: 4) otros
A57: 22233276 | B57: Chlamydia trachomatis hijacks intra-Golgi COG complex-dependent vesicle trafficking pathway | C57: Pokrovskaya ID, Szwedo JW, Goodwin A, Lupashina TV, Nagarajan UM, Lupashin VV. | D57: Cell Microbiol. 2012 May;14(5):656-68. doi: 10.1111/j.1462-5822.2012.01747.x. Epub 2012 Feb 15. | E57: Pokrovskaya ID | F57: Cell Microbiol | G57: 2012 | H57: 40920 | I57: PMC3330190 | J57: NIHMS348388 | K57: 10.1111/j.1462-5822.2012.01747.x | L57: =IF(ISNUMBER(VLOOKUP(A57,EXCL,1,FALSE)),"Excluido",IF(ISNUMBER(VLOOKUP(A57,POST,1,FALSE)),"PostAlerta",IF(ISNUMBER(VLOOKUP(A57,PRE,1,FALSE)),"PreAlerta",""))) -> PreAlerta | M57: =IF(ISNUMBER(VLOOKUP(A57,KEYWORDS,1,FALSE)),"C/PalabrasClaves","S/PalabrasClaves") -> S/PalabrasClaves | N57: 4) otros
A58: 22265179 | B58: Transactional sexual relationships, sexually transmitted infection risk, and condom use among young Black Women in peri-urban areas of the Western Cape Province of South Africa | C58: Onoya D, Reddy P, Sifunda S, Lang D, Wingood GM, van den Borne B, Ruiter RA. | D58: Womens Health Issues. 2012 May-Jun;22(3):e277-82. doi: 10.1016/j.whi.2011.11.006. Epub 2012 Jan 21. | E58: Onoya D | F58: Womens Health Issues | G58: 2012 | H58: 40932 | K58: 10.1016/j.whi.2011.11.006 | L58: =IF(ISNUMBER(VLOOKUP(A58,EXCL,1,FALSE)),"Excluido",IF(ISNUMBER(VLOOKUP(A58,POST,1,FALSE)),"PostAlerta",IF(ISNUMBER(VLOOKUP(A58,PRE,1,FALSE)),"PreAlerta",""))) -> PreAlerta | M58: =IF(ISNUMBER(VLOOKUP(A58,KEYWORDS,1,FALSE)),"C/PalabrasClaves","S/PalabrasClaves") -> S/PalabrasClaves | N58: 4) otros
A59: 22293657 | B59: First reported case of the Swedish new variant of Chlamydia trachomatis (nvCT) in Eastern Europe (Russia), and evaluation of Russian nucleic acid amplification tests regarding their ability to detect nvCT | C59: Shipitsyna E, Hadad R, Ryzhkova O, Savicheva A, Domeika M, Unemo M. | D59: Acta Derm Venereol. 2012 May;92(3):330-1. doi: 10.2340/00015555-1269. | E59: Shipitsyna E | F59: Acta Derm Venereol | G59: 2012 | H59: 40941 | K59: 10.2340/00015555-1269 | L59: =IF(ISNUMBER(VLOOKUP(A59,EXCL,1,FALSE)),"Excluido",IF(ISNUMBER(VLOOKUP(A59,POST,1,FALSE)),"PostAlerta",IF(ISNUMBER(VLOOKUP(A59,PRE,1,FALSE)),"PreAlerta",""))) -> PreAlerta | M59: =IF(ISNUMBER(VLOOKUP(A59,KEYWORDS,1,FALSE)),"C/PalabrasClaves","S/PalabrasClaves") -> S/PalabrasClaves | N59: 1) Reporte de cepas resistentes | Q59: Listo | T59: Chlamydia trachomatis infections are the most prevalent bacterial sexually transmitted infections (STIs) worldwide, and are associated with considerable morbidity and socio-economic consequences. The Swedish new variant of C. trachomatis (nvCT), first reported in Sweden in late 2006, contains a 377-bp deletion in the cryptic plasmid that covers the single tar-gets originally utilized in the nucleic acid amplification tests (NAATs) manufactured by Roche Diagnostics (Amplicor, Cobas Amplicor, Cobas TaqMan48) and Abbott Laboratories (Abbott m2000), which at the time were used worldwide (1, 2). In Sweden, the proportion of nvCT, compared with wild type CT (wtCT), was high (7–64% in the different counties) (3, 4), and nvCT accordingly caused thousands of falsely negative diag-noses. The nvCT prevalence in Sweden is still relatively high, and nvCT has been frequently detected in Norway, Finland and Denmark (5, 6). Although genome sequen-cing and phenotypic characterization have shown that nvCT, compared with wtCT, has an unaltered biological fitness in vitro (7), nvCT is rarely reported outside the Nordic countries (5, 7–9). However, knowledge of the nvCT presence beyond the Nordic countries is limited because few recent studies have been performed, many laboratories still cannot detect nvCT, and the ones that can detect nvCT mainly do not distinguish it from wtCT (5, 10, 11). The aims of this study were: (i) to investigate the pre-sence of nvCT in St Petersburg, the largest city in the northwest of Russia and in close geographical proximity to Sweden; and (ii) to assess NAATs used in Russia to diagnose C. trachomatisinfections for their ability to detect nvCT | U59: Yes | V59: No | W59: No | X59: New strain found in Russia
A60: 22350326 | B60: Female genital Chlamydia trachomatis infection: where are we heading? | C60: Mylonas I. | D60: Arch Gynecol Obstet. 2012 May;285(5):1271-85. doi: 10.1007/s00404-012-2240-7. Epub 2012 Feb 19. | E60: Mylonas I | F60: Arch Gynecol Obstet | G60: 2012 | H60: 40961 | K60: 10.1007/s00404-012-2240-7 | L60: =IF(ISNUMBER(VLOOKUP(A60,EXCL,1,FALSE)),"Excluido",IF(ISNUMBER(VLOOKUP(A60,POST,1,FALSE)),"PostAlerta",IF(ISNUMBER(VLOOKUP(A60,PRE,1,FALSE)),"PreAlerta",""))) -> Excluido | M60: =IF(ISNUMBER(VLOOKUP(A60,KEYWORDS,1,FALSE)),"C/PalabrasClaves","S/PalabrasClaves") -> S/PalabrasClaves
A61: 22425040 | B61: Male rat genital tract infection with Chlamydia muridarum has no significant consequence on male fertility | C61: Motrich RD, Sanchez L, Maccioni M, Mackern-Oberti JP, Rivero VE. | D61: J Urol. 2012 May;187(5):1911-7. doi: 10.1016/j.juro.2011.12.055. Epub 2012 Mar 16. | E61: Motrich RD | F61: J Urol | G61: 2012 | H61: 40988 | K61: 10.1016/j.juro.2011.12.055 | L61: =IF(ISNUMBER(VLOOKUP(A61,EXCL,1,FALSE)),"Excluido",IF(ISNUMBER(VLOOKUP(A61,POST,1,FALSE)),"PostAlerta",IF(ISNUMBER(VLOOKUP(A61,PRE,1,FALSE)),"PreAlerta",""))) -> PreAlerta | M61: =IF(ISNUMBER(VLOOKUP(A61,KEYWORDS,1,FALSE)),"C/PalabrasClaves","S/PalabrasClaves") -> S/PalabrasClaves | N61: 4) otros
A62: 22475835 | B62: One in 16 quadrillion: importance of blinding in research reproducibility | C62: Hadgu A, Nordbø SA, Skjeldestad FE. | D62: Epidemiology. 2012 May;23(3):503-4. doi: 10.1097/EDE.0b013e31824da327. | E62: Hadgu A | F62: Epidemiology | G62: 2012 | H62: 41005 | K62: 10.1097/EDE.0b013e31824da327 | L62: =IF(ISNUMBER(VLOOKUP(A62,EXCL,1,FALSE)),"Excluido",IF(ISNUMBER(VLOOKUP(A62,POST,1,FALSE)),"PostAlerta",IF(ISNUMBER(VLOOKUP(A62,PRE,1,FALSE)),"PreAlerta",""))) -> PreAlerta | M62: =IF(ISNUMBER(VLOOKUP(A62,KEYWORDS,1,FALSE)),"C/PalabrasClaves","S/PalabrasClaves") -> S/PalabrasClaves | N62: 4) otros
A63: 22498155 | B63: Men's attitudes towards chlamydia screening: a narrative review | C63: Balfe M, Brugha R, O'Connell E, Vaughan D, O'Donovan D. | D63: Sex Health. 2012 May;9(2):120-30. doi: 10.1071/SH10094. | E63: Balfe M | F63: Sex Health | G63: 2012 | H63: 41013 | K63: 10.1071/SH10094 | L63: =IF(ISNUMBER(VLOOKUP(A63,EXCL,1,FALSE)),"Excluido",IF(ISNUMBER(VLOOKUP(A63,POST,1,FALSE)),"PostAlerta",IF(ISNUMBER(VLOOKUP(A63,PRE,1,FALSE)),"PreAlerta",""))) -> Excluido | M63: =IF(ISNUMBER(VLOOKUP(A63,KEYWORDS,1,FALSE)),"C/PalabrasClaves","S/PalabrasClaves") -> S/PalabrasClaves
A64: 22498164 | B64: Sexual behaviour of inmates with Chlamydia trachomatis infection in the prisons of Catalonia, Spain | C64: Corbeto EL, Carnicer-Pont D, Lugo R, Gonzalez V, Bascuñana E, Lleopart N, Barbero L, Humet V, Casabona J; Chlamydia Study Group In Catalonia Prisons. | D64: Sex Health. 2012 May;9(2):187-9. doi: 10.1071/SH11038. | E64: Corbeto EL | F64: Sex Health | G64: 2012 | H64: 41013 | K64: 10.1071/SH11038 | L64: =IF(ISNUMBER(VLOOKUP(A64,EXCL,1,FALSE)),"Excluido",IF(ISNUMBER(VLOOKUP(A64,POST,1,FALSE)),"PostAlerta",IF(ISNUMBER(VLOOKUP(A64,PRE,1,FALSE)),"PreAlerta",""))) -> PreAlerta | M64: =IF(ISNUMBER(VLOOKUP(A64,KEYWORDS,1,FALSE)),"C/PalabrasClaves","S/PalabrasClaves") -> S/PalabrasClaves | N64: 4) otros
A65: 22498165 | B65: Rectal self-sampling in non-clinical venues for detection of sexually transmissible infections among behaviourally bisexual men | C65: Dodge B, Van Der Pol B, Reece M, Malebranche D, Martinez O, Goncalves G, Schnarrs P, Nix R, Fortenberry JD. | D65: Sex Health. 2012 May;9(2):190-1. doi: 10.1071/SH11068. | E65: Dodge B | F65: Sex Health | G65: 2012 | H65: 41013 | I65: PMC3334864 | J65: NIHMS352832 | K65: 10.1071/SH11068 | L65: =IF(ISNUMBER(VLOOKUP(A65,EXCL,1,FALSE)),"Excluido",IF(ISNUMBER(VLOOKUP(A65,POST,1,FALSE)),"PostAlerta",IF(ISNUMBER(VLOOKUP(A65,PRE,1,FALSE)),"PreAlerta",""))) -> PreAlerta | M65: =IF(ISNUMBER(VLOOKUP(A65,KEYWORDS,1,FALSE)),"C/PalabrasClaves","S/PalabrasClaves") -> S/PalabrasClaves | N65: 4) otros
A66: 22498167 | B66: 'Yes wee can' - a nurse-driven asymptomatic screening program for chlamydia and gonorrhoea in a remote emergency department | C66: Mossenson A, Algie K, Olding M, Garton L, Reeve C. | D66: Sex Health. 2012 May;9(2):194-5. doi: 10.1071/SH11064. | E66: Mossenson A | F66: Sex Health | G66: 2012 | H66: 41013 | K66: 10.1071/SH11064 | L66: =IF(ISNUMBER(VLOOKUP(A66,EXCL,1,FALSE)),"Excluido",IF(ISNUMBER(VLOOKUP(A66,POST,1,FALSE)),"PostAlerta",IF(ISNUMBER(VLOOKUP(A66,PRE,1,FALSE)),"PreAlerta",""))) -> PreAlerta | M66: =IF(ISNUMBER(VLOOKUP(A66,KEYWORDS,1,FALSE)),"C/PalabrasClaves","S/PalabrasClaves") -> S/PalabrasClaves | N66: 4) otros
A67: 22504590 | B67: Effects of screening and partner notification on Chlamydia positivity in the United States: a modeling study | C67: Kretzschmar M, Satterwhite C, Leichliter J, Berman S. | D67: Sex Transm Dis. 2012 May;39(5):325-31. doi: 10.1097/OLQ.0b013e31824e52c2. | E67: Kretzschmar M | F67: Sex Transm Dis | G67: 2012 | H67: 41016 | K67: 10.1097/OLQ.0b013e31824e52c2 | L67: =IF(ISNUMBER(VLOOKUP(A67,EXCL,1,FALSE)),"Excluido",IF(ISNUMBER(VLOOKUP(A67,POST,1,FALSE)),"PostAlerta",IF(ISNUMBER(VLOOKUP(A67,PRE,1,FALSE)),"PreAlerta",""))) -> PreAlerta | M67: =IF(ISNUMBER(VLOOKUP(A67,KEYWORDS,1,FALSE)),"C/PalabrasClaves","S/PalabrasClaves") -> S/PalabrasClaves | N67: 4) otros
A68: 22504608 | B68: Towards more robust estimates of the transmissibility of Chlamydia trachomatis | C68: Althaus CL, Heijne JC, Low N. | D68: Sex Transm Dis. 2012 May;39(5):402-4. doi: 10.1097/OLQ.0b013e318248a550. | E68: Althaus CL | F68: Sex Transm Dis | G68: 2012 | H68: 41016 | K68: 10.1097/OLQ.0b013e318248a550 | L68: =IF(ISNUMBER(VLOOKUP(A68,EXCL,1,FALSE)),"Excluido",IF(ISNUMBER(VLOOKUP(A68,POST,1,FALSE)),"PostAlerta",IF(ISNUMBER(VLOOKUP(A68,PRE,1,FALSE)),"PreAlerta",""))) -> PreAlerta | M68: =IF(ISNUMBER(VLOOKUP(A68,KEYWORDS,1,FALSE)),"C/PalabrasClaves","S/PalabrasClaves") -> S/PalabrasClaves | N68: 4) otros
A69: 22504609 | B69: Sensitivity of 20-minute voiding intervals in men testing for Chlamydia trachomatis | C69: Kwan B, Ryder N, Knight V, Kenigsberg A, McNulty A, Read P, Bourne C. | D69: Sex Transm Dis. 2012 May;39(5):405-6. doi: 10.1097/OLQ.0b013e318248a563. | E69: Kwan B | F69: Sex Transm Dis | G69: 2012 | H69: 41016 | K69: 10.1097/OLQ.0b013e318248a563 | L69: =IF(ISNUMBER(VLOOKUP(A69,EXCL,1,FALSE)),"Excluido",IF(ISNUMBER(VLOOKUP(A69,POST,1,FALSE)),"PostAlerta",IF(ISNUMBER(VLOOKUP(A69,PRE,1,FALSE)),"PreAlerta",""))) -> PreAlerta | M69: =IF(ISNUMBER(VLOOKUP(A69,KEYWORDS,1,FALSE)),"C/PalabrasClaves","S/PalabrasClaves") -> S/PalabrasClaves | N69: 4) otros
A70: 22525912 | B70: Chlamydia trachomatis antigens recognized in women with tubal factor infertility, normal fertility, and acute infection | C70: Budrys NM, Gong S, Rodgers AK, Wang J, Louden C, Shain R, Schenken RS, Zhong G. | D70: Obstet Gynecol. 2012 May;119(5):1009-16. doi: 10.1097/AOG.0b013e3182519326. | E70: Budrys NM | F70: Obstet Gynecol | G70: 2012 | H70: 41024 | I70: PMC4608258 | J70: NIHMS366193 | K70: 10.1097/AOG.0b013e3182519326 | L70: =IF(ISNUMBER(VLOOKUP(A70,EXCL,1,FALSE)),"Excluido",IF(ISNUMBER(VLOOKUP(A70,POST,1,FALSE)),"PostAlerta",IF(ISNUMBER(VLOOKUP(A70,PRE,1,FALSE)),"PreAlerta",""))) -> Excluido | M70: =IF(ISNUMBER(VLOOKUP(A70,KEYWORDS,1,FALSE)),"C/PalabrasClaves","S/PalabrasClaves") -> S/PalabrasClaves
A71: 22563554 | B71: The prevalence of vaginal microorganisms in pregnant women with preterm labor and preterm birth | C71: Choi SJ, Park SD, Jang IH, Uh Y, Lee A. | D71: Ann Lab Med. 2012 May;32(3):194-200. doi: 10.3343/alm.2012.32.3.194. Epub 2012 Apr 18. | E71: Choi SJ | F71: Ann Lab Med | G71: 2012 | H71: 41037 | I71: PMC3339299 | K71: 10.3343/alm.2012.32.3.194 | L71: =IF(ISNUMBER(VLOOKUP(A71,EXCL,1,FALSE)),"Excluido",IF(ISNUMBER(VLOOKUP(A71,POST,1,FALSE)),"PostAlerta",IF(ISNUMBER(VLOOKUP(A71,PRE,1,FALSE)),"PreAlerta",""))) -> PreAlerta | M71: =IF(ISNUMBER(VLOOKUP(A71,KEYWORDS,1,FALSE)),"C/PalabrasClaves","S/PalabrasClaves") -> S/PalabrasClaves | N71: 4) otros
A72: 22578934 | B72: Can mailed swab samples be dry-shipped for the detection of Chlamydia trachomatis, Neisseria gonorrhoeae, and Trichomonas vaginalis by nucleic acid amplification tests? | C72: Gaydos CA, Farshy C, Barnes M, Quinn N, Agreda P, Rivers CA, Schwebke J, Papp J. | D72: Diagn Microbiol Infect Dis. 2012 May;73(1):16-20. doi: 10.1016/j.diagmicrobio.2012.02.008. | E72: Gaydos CA | F72: Diagn Microbiol Infect Dis | G72: 2012 | H72: 41044 | I72: PMC3425852 | J72: NIHMS360474 | K72: 10.1016/j.diagmicrobio.2012.02.008 | L72: =IF(ISNUMBER(VLOOKUP(A72,EXCL,1,FALSE)),"Excluido",IF(ISNUMBER(VLOOKUP(A72,POST,1,FALSE)),"PostAlerta",IF(ISNUMBER(VLOOKUP(A72,PRE,1,FALSE)),"PreAlerta",""))) -> PreAlerta | M72: =IF(ISNUMBER(VLOOKUP(A72,KEYWORDS,1,FALSE)),"C/PalabrasClaves","S/PalabrasClaves") -> S/PalabrasClaves | N72: 4) otros
A73: 22729196 | B73: Mycoplasmateceae species are not found in Fallopian tubes of women with tubo-peritoneal infertility | C73: Costoya A, Morales F, Borda P, Vargas R, Fuhrer J, Salgado N, Cárdenas H, Velasquez L. | D73: Braz J Infect Dis. 2012 May-Jun;16(3):273-8. | E73: Costoya A | F73: Braz J Infect Dis | G73: 2012 | H73: 41086 | L73: =IF(ISNUMBER(VLOOKUP(A73,EXCL,1,FALSE)),"Excluido",IF(ISNUMBER(VLOOKUP(A73,POST,1,FALSE)),"PostAlerta",IF(ISNUMBER(VLOOKUP(A73,PRE,1,FALSE)),"PreAlerta",""))) -> PreAlerta | M73: =IF(ISNUMBER(VLOOKUP(A73,KEYWORDS,1,FALSE)),"C/PalabrasClaves","S/PalabrasClaves") -> S/PalabrasClaves | N73: 4) otros
A74: 22829988 | B74: Comparative screening of Chlamydia trachomatis infection in women population in tehran, iran | C74: Fatholahzadeh B, Bahador A, Haghighi Hasanabad M, Bazarjani F, Haghighi F. | D74: Iran Red Crescent Med J. 2012 May;14(5):289-93. Epub 2012 May 30. | E74: Fatholahzadeh B | F74: Iran Red Crescent Med J | G74: 2012 | H74: 41116 | I74: PMC3398636 | L74: =IF(ISNUMBER(VLOOKUP(A74,EXCL,1,FALSE)),"Excluido",IF(ISNUMBER(VLOOKUP(A74,POST,1,FALSE)),"PostAlerta",IF(ISNUMBER(VLOOKUP(A74,PRE,1,FALSE)),"PreAlerta",""))) -> PreAlerta | M74: =IF(ISNUMBER(VLOOKUP(A74,KEYWORDS,1,FALSE)),"C/PalabrasClaves","S/PalabrasClaves") -> S/PalabrasClaves | N74: 4) otros
A75: 22830280 | B75: [Role of Chlamydia trachomatis and Chlamydophila pneumoniae in damage of eye posterior segment structures] | C75: Chepur SV, Boĭko ÉV, Pozniak AL, Nuralova IV, Mal'tsev DS, Suetov AA. | D75: Zh Mikrobiol Epidemiol Immunobiol. 2012 May-Jun;(3):79-82. | E75: Chepur SV | F75: Zh Mikrobiol Epidemiol Immunobiol | G75: 2012 | H75: 41117 | L75: =IF(ISNUMBER(VLOOKUP(A75,EXCL,1,FALSE)),"Excluido",IF(ISNUMBER(VLOOKUP(A75,POST,1,FALSE)),"PostAlerta",IF(ISNUMBER(VLOOKUP(A75,PRE,1,FALSE)),"PreAlerta",""))) -> PreAlerta | M75: =IF(ISNUMBER(VLOOKUP(A75,KEYWORDS,1,FALSE)),"C/PalabrasClaves","S/PalabrasClaves") -> S/PalabrasClaves | N75: 4) otros
A76: 23065646 | B76: Blindness-causing trachomatous trichiasis biomarkers sighted | C76: Fan H. | D76: Invest Ophthalmol Vis Sci. 2012 May 1;53(6):2560. doi: 10.1167/iovs.12-9835. | E76: Fan H | F76: Invest Ophthalmol Vis Sci | G76: 2012 | H76: 41198 | K76: 10.1167/iovs.12-9835 | L76: =IF(ISNUMBER(VLOOKUP(A76,EXCL,1,FALSE)),"Excluido",IF(ISNUMBER(VLOOKUP(A76,POST,1,FALSE)),"PostAlerta",IF(ISNUMBER(VLOOKUP(A76,PRE,1,FALSE)),"PreAlerta",""))) -> PreAlerta | M76: =IF(ISNUMBER(VLOOKUP(A76,KEYWORDS,1,FALSE)),"C/PalabrasClaves","S/PalabrasClaves") -> S/PalabrasClaves | N76: 4) otros
A77: 22427578 | B77: Genome-wide identification of Chlamydia trachomatis antigens associated with trachomatous trichiasis | C77: Lu C, Holland MJ, Gong S, Peng B, Bailey RL, Mabey DW, Wu Y, Zhong G. | D77: Invest Ophthalmol Vis Sci. 2012 May 14;53(6):2551-9. doi: 10.1167/iovs.11-9212. Print 2012 May. | E77: Lu C | F77: Invest Ophthalmol Vis Sci | G77: 2012 | H77: 40988 | I77: PMC3366722 | K77: 10.1167/iovs.11-9212 | L77: =IF(ISNUMBER(VLOOKUP(A77,EXCL,1,FALSE)),"Excluido",IF(ISNUMBER(VLOOKUP(A77,POST,1,FALSE)),"PostAlerta",IF(ISNUMBER(VLOOKUP(A77,PRE,1,FALSE)),"PreAlerta",""))) -> PreAlerta | M77: =IF(ISNUMBER(VLOOKUP(A77,KEYWORDS,1,FALSE)),"C/PalabrasClaves","S/PalabrasClaves") -> S/PalabrasClaves | N77: 3) immunization | Q77: Listo | T77: Purpose: Chlamydia trachomatis is the leading infectious cause of blindness. The goal of the current study was to search for biomarkers associated with C. trachomatis-induced ocular pathologies. Methods: We used a whole genome scale proteome array to systematically profile antigen specificities of antibody responses to C. trachomatis infection in individuals from trachoma-endemic communities with or without end-stage trachoma (trichiasis) in The Gambia. Results: When 61 trichiasis patients were compared with their control counterparts for overall antibody reactivity with organisms of different chlamydial species, no statistically significant difference was found. Both groups developed significantly higher titers of antibodies against C. trachomatis ocular serovars A and B than ocular serovar C, genital serovar D, or Chlamydia psittaci, whereas the titers of anti-Chlamydia pneumoniae antibodies were the highest. When antisera from 33 trichiasis and 26 control patients (with relatively high titers of antibodies to C. trachomatis ocular serovars) were reacted with 908 C. trachomatis proteins, 447 antigens were recognized by at least 1 of the 59 antisera, and 10 antigens by 50% or more antisera, the latter being designated as immunodominant antigens. More importantly, four antigens were preferentially recognized by the trichiasis group, with antigens CT414, CT667, and CT706 collectively reacting with 30% of trichiasis antisera but none from the normal group, and antigen CT695 reacting with 61% of trichiasis but only 31% of normal antisera. On the other hand, eight antigens were preferentially recognized by the control group, with antigens CT019, CT117, CT301, CT553, CT556, CT571, and CT709 together reacting with 46% of normal antisera and none from the trichiasis group, whereas antigen CT442 reacted with 35% of normal and 19% of trichiasis antisera respectively. Conclusions: The current study, by mapping immunodominant C. trachomatis antigens and identifying antigens associated with both ocular pathology and protection, has provided important information for further understanding chlamydial pathogenesis and the development of subunit vaccines. | U77: No | V77: No | W77: Yes | X77: The current study, by mapping immunodominant C. trachomatis antigens and identifying antigens associated with both ocular pathology and protection, has provided important information for a better understanding of the pathogenesis of chlamydia and the development of subunit vaccines.
A78: 22583480 | B78: The prevalence of Chlamydia trachomatis infection in Australia: a systematic review and meta-analysis | C78: Lewis D, Newton DC, Guy RJ, Ali H, Chen MY, Fairley CK, Hocking JS. | D78: BMC Infect Dis. 2012 May 14;12:113. doi: 10.1186/1471-2334-12-113. | E78: Lewis D | F78: BMC Infect Dis | G78: 2012 | H78: 41045 | I78: PMC3462140 | K78: 10.1186/1471-2334-12-113 | L78: =IF(ISNUMBER(VLOOKUP(A78,EXCL,1,FALSE)),"Excluido",IF(ISNUMBER(VLOOKUP(A78,POST,1,FALSE)),"PostAlerta",IF(ISNUMBER(VLOOKUP(A78,PRE,1,FALSE)),"PreAlerta",""))) -> Excluido | M78: =IF(ISNUMBER(VLOOKUP(A78,KEYWORDS,1,FALSE)),"C/PalabrasClaves","S/PalabrasClaves") -> S/PalabrasClaves
A79: 22586179 | B79: Blindness-causing trachomatous trichiasis biomarkers sighted | C79: Fan H. | D79: Invest Ophthalmol Vis Sci. 2012 May 14;53(6):2560. doi: 10.1167/iovs.12-9835. | E79: Fan H | F79: Invest Ophthalmol Vis Sci | G79: 2012 | H79: 41045 | K79: 10.1167/iovs.12-9835 | L79: =IF(ISNUMBER(VLOOKUP(A79,EXCL,1,FALSE)),"Excluido",IF(ISNUMBER(VLOOKUP(A79,POST,1,FALSE)),"PostAlerta",IF(ISNUMBER(VLOOKUP(A79,PRE,1,FALSE)),"PreAlerta",""))) -> PreAlerta | M79: =IF(ISNUMBER(VLOOKUP(A79,KEYWORDS,1,FALSE)),"C/PalabrasClaves","S/PalabrasClaves") -> S/PalabrasClaves | N79: 4) otros
A80: 22610705 | B80: Comparison of four serological assays for the diagnosis of Chlamydia trachomatis in subfertile women | C80: Muvunyi CM, Claeys L, De Sutter T, De Sutter P, Temmerman M, Van Renterghem L, Claeys G, Padalko E. | D80: J Infect Dev Ctries. 2012 May 14;6(5):396-402. doi: 10.3855/jidc.1740. | E80: Muvunyi CM | F80: J Infect Dev Ctries | G80: 2012 | H80: 41051 | K80: 10.3855/jidc.1740 | L80: =IF(ISNUMBER(VLOOKUP(A80,EXCL,1,FALSE)),"Excluido",IF(ISNUMBER(VLOOKUP(A80,POST,1,FALSE)),"PostAlerta",IF(ISNUMBER(VLOOKUP(A80,PRE,1,FALSE)),"PreAlerta",""))) -> PreAlerta | M80: =IF(ISNUMBER(VLOOKUP(A80,KEYWORDS,1,FALSE)),"C/PalabrasClaves","S/PalabrasClaves") -> S/PalabrasClaves | N80: 4) otros
A81: 22525317 | B81: Derivatives of 8-hydroxyquinoline--antibacterial agents that target intra- and extracellular Gram-negative pathogens | C81: Enquist PA, Gylfe A, Hägglund U, Lindström P, Norberg-Scherman H, Sundin C, Elofsson M. | D81: Bioorg Med Chem Lett. 2012 May 15;22(10):3550-3. doi: 10.1016/j.bmcl.2012.03.096. Epub 2012 Apr 6. | E81: Enquist PA | F81: Bioorg Med Chem Lett | G81: 2012 | H81: 41024 | K81: 10.1016/j.bmcl.2012.03.096 | L81: =IF(ISNUMBER(VLOOKUP(A81,EXCL,1,FALSE)),"Excluido",IF(ISNUMBER(VLOOKUP(A81,POST,1,FALSE)),"PostAlerta",IF(ISNUMBER(VLOOKUP(A81,PRE,1,FALSE)),"PreAlerta",""))) -> PreAlerta | M81: =IF(ISNUMBER(VLOOKUP(A81,KEYWORDS,1,FALSE)),"C/PalabrasClaves","S/PalabrasClaves") -> S/PalabrasClaves | N81: 2) Nuevos tratamientos | O81: 2c) Droga de diseño | Q81: Listo | T81: Small molecule screening identified 5-nitro-7-((4-phenylpiperazine-1-yl-)methyl)quinolin-8-ol INP1750 as a putative inhibitor of type III secretion (T3S) in the Gram-negative pathogen Yersinia pseudotuberculosis. In this study we report structure-activity relationships for inhibition of T3S and show that the most potent compounds target both the extracellular bacterium Y. pseudotuberculosis and the intracellular pathogen Chlamydia trachomatis in cell-based infection models. | U81: No | V81: Yes | W81: No
A82: 22665107 | B82: Prevalence of malaria and sexually transmitted and reproductive tract infections in pregnancy in sub-Saharan Africa: a systematic review | C82: Chico RM, Mayaud P, Ariti C, Mabey D, Ronsmans C, Chandramohan D. | D82: JAMA. 2012 May 16;307(19):2079-86. doi: 10.1001/jama.2012.3428. | E82: Chico RM | F82: JAMA | G82: 2012 | H82: 41066 | K82: 10.1001/jama.2012.3428 | L82: =IF(ISNUMBER(VLOOKUP(A82,EXCL,1,FALSE)),"Excluido",IF(ISNUMBER(VLOOKUP(A82,POST,1,FALSE)),"PostAlerta",IF(ISNUMBER(VLOOKUP(A82,PRE,1,FALSE)),"PreAlerta",""))) -> Excluido | M82: =IF(ISNUMBER(VLOOKUP(A82,KEYWORDS,1,FALSE)),"C/PalabrasClaves","S/PalabrasClaves") -> S/PalabrasClaves
A83: 22919659 | B83: Genotyping markers used for multi locus VNTR analysis with ompA (MLVA-ompA) and multi sequence typing (MST) retain stability in Chlamydia trachomatis | C83: Labiran C, Clarke IN, Cutcliffe LT, Wang Y, Skilton RJ, Persson K, Bjartling C, Herrmann B, Christerson L, Marsh P. | D83: Front Cell Infect Microbiol. 2012 May 17;2:68. doi: 10.3389/fcimb.2012.00068. eCollection 2012. | E83: Labiran C | F83: Front Cell Infect Microbiol | G83: 2012 | H83: 41146 | I83: PMC3417530 | K83: 10.3389/fcimb.2012.00068 | L83: =IF(ISNUMBER(VLOOKUP(A83,EXCL,1,FALSE)),"Excluido",IF(ISNUMBER(VLOOKUP(A83,POST,1,FALSE)),"PostAlerta",IF(ISNUMBER(VLOOKUP(A83,PRE,1,FALSE)),"PreAlerta",""))) -> PreAlerta | M83: =IF(ISNUMBER(VLOOKUP(A83,KEYWORDS,1,FALSE)),"C/PalabrasClaves","S/PalabrasClaves") -> S/PalabrasClaves | N83: 4) otros
A84: 22783236 | B84: Genomic and Biochemical Analysis of the Diaminopimelate and Lysine Biosynthesis Pathway in Verrucomicrobium spinosum: Identification and Partial Characterization of L,L-Diaminopimelate Aminotransferase and UDP-N-Acetylmuramoylalanyl-D-glutamyl-2,6-meso-Diaminopimelate Ligase | C84: Nachar VR, Savka FC, McGroty SE, Donovan KA, North RA, Dobson RC, Buckley LJ, Hudson AO. | D84: Front Microbiol. 2012 May 25;3:183. doi: 10.3389/fmicb.2012.00183. eCollection 2012. | E84: Nachar VR | F84: Front Microbiol | G84: 2012 | H84: 41102 | I84: PMC3390587 | K84: 10.3389/fmicb.2012.00183 | L84: =IF(ISNUMBER(VLOOKUP(A84,EXCL,1,FALSE)),"Excluido",IF(ISNUMBER(VLOOKUP(A84,POST,1,FALSE)),"PostAlerta",IF(ISNUMBER(VLOOKUP(A84,PRE,1,FALSE)),"PreAlerta",""))) -> PreAlerta | M84: =IF(ISNUMBER(VLOOKUP(A84,KEYWORDS,1,FALSE)),"C/PalabrasClaves","S/PalabrasClaves") -> S/PalabrasClaves | N84: 2) Nuevos tratamientos | O84: 2c) Droga de diseño | Q84: Listo | T84: Small molecule screening identified 5-nitro-7-((4-phenylpiperazine-1-yl-)methyl)quinolin-8-ol INP1750 as a putative inhibitor of type III secretion (T3S) in the Gram-negative pathogen Yersinia pseudotuberculosis. In this study we report structure-activity relationships for inhibition of T3S and show that the most potent compounds target both the extracellular bacterium Y. pseudotuberculosis and the intracellular pathogen Chlamydia trachomatis in cell-based infection models. | U84: No | V84: Yes | W84: No | X84: Designer drug used to treat Yersinia and intracellular chlamydia
A85: 22231476 | B85: Biochemical characterisation of the chlamydial MurF ligase, and possible sequence of the chlamydial peptidoglycan pentapeptide stem | C85: Patin D, Bostock J, Chopra I, Mengin-Lecreulx D, Blanot D. | D85: Arch Microbiol. 2012 Jun;194(6):505-12. doi: 10.1007/s00203-011-0784-8. Epub 2012 Jan 10. | E85: Patin D | F85: Arch Microbiol | G85: 2012 | H85: 40919 | K85: 10.1007/s00203-011-0784-8 | L85: =IF(ISNUMBER(VLOOKUP(A85,EXCL,1,FALSE)),"Excluido",IF(ISNUMBER(VLOOKUP(A85,POST,1,FALSE)),"PostAlerta",IF(ISNUMBER(VLOOKUP(A85,PRE,1,FALSE)),"PreAlerta",""))) -> PreAlerta | M85: =IF(ISNUMBER(VLOOKUP(A85,KEYWORDS,1,FALSE)),"C/PalabrasClaves","S/PalabrasClaves") -> S/PalabrasClaves | N85: 4) otros
A86: 22251247 | B86: Modulation of MICA on the surface of Chlamydia trachomatis-infected endocervical epithelial cells promotes NK cell-mediated killing | C86: Ibana JA, Aiyar A, Quayle AJ, Schust DJ. | D86: FEMS Immunol Med Microbiol. 2012 Jun;65(1):32-42. doi: 10.1111/j.1574-695X.2012.00930.x. Epub 2012 Feb 16. | E86: Ibana JA | F86: FEMS Immunol Med Microbiol | G86: 2012 | H86: 40927 | I86: PMC5029121 | J86: NIHMS370203 | K86: 10.1111/j.1574-695X.2012.00930.x | L86: =IF(ISNUMBER(VLOOKUP(A86,EXCL,1,FALSE)),"Excluido",IF(ISNUMBER(VLOOKUP(A86,POST,1,FALSE)),"PostAlerta",IF(ISNUMBER(VLOOKUP(A86,PRE,1,FALSE)),"PreAlerta",""))) -> PreAlerta | M86: =IF(ISNUMBER(VLOOKUP(A86,KEYWORDS,1,FALSE)),"C/PalabrasClaves","S/PalabrasClaves") -> S/PalabrasClaves | N86: 4) otros
A87: 22252417 | B87: Testing for sexually transmitted infections in a population-based sexual health survey: development of an acceptable ethical approach | C87: Field N, Tanton C, Mercer CH, Nicholson S, Soldan K, Beddows S, Ison C, Johnson AM, Sonnenberg P. | D87: J Med Ethics. 2012 Jun;38(6):380-2. doi: 10.1136/medethics-2011-100068. Epub 2012 Jan 17. | E87: Field N | F87: J Med Ethics | G87: 2012 | H87: 40927 | I87: PMC3359520 | K87: 10.1136/medethics-2011-100068 | L87: =IF(ISNUMBER(VLOOKUP(A87,EXCL,1,FALSE)),"Excluido",IF(ISNUMBER(VLOOKUP(A87,POST,1,FALSE)),"PostAlerta",IF(ISNUMBER(VLOOKUP(A87,PRE,1,FALSE)),"PreAlerta",""))) -> PreAlerta | M87: =IF(ISNUMBER(VLOOKUP(A87,KEYWORDS,1,FALSE)),"C/PalabrasClaves","S/PalabrasClaves") -> S/PalabrasClaves | N87: 4) otros
A88: 22267815 | B88: Molecular epidemiology of genital Chlamydia trachomatis infection in Shenzhen, China | C88: Zhang JJ, Zhao GL, Wang F, Hong FC, Luo ZZ, Lan LN, Zhang CL, Peng Y, Liu XL, Feng TJ, Chen XS. | D88: Sex Transm Infect. 2012 Jun;88(4):272-7. doi: 10.1136/sextrans-2011-050163. Epub 2012 Jan 20. | E88: Zhang JJ | F88: Sex Transm Infect | G88: 2012 | H88: 40932 | K88: 10.1136/sextrans-2011-050163 | L88: =IF(ISNUMBER(VLOOKUP(A88,EXCL,1,FALSE)),"Excluido",IF(ISNUMBER(VLOOKUP(A88,POST,1,FALSE)),"PostAlerta",IF(ISNUMBER(VLOOKUP(A88,PRE,1,FALSE)),"PreAlerta",""))) -> PreAlerta | M88: =IF(ISNUMBER(VLOOKUP(A88,KEYWORDS,1,FALSE)),"C/PalabrasClaves","S/PalabrasClaves") -> S/PalabrasClaves | N88: 4) otros
A89: 22277329 | B89: Behavioral and sociodemographic risk factors for serological and DNA evidence of HPV6, 11, 16, 18 infections | C89: Wiley DJ, Masongsong EV, Lu S, Heather L S, Salem B, Giuliano AR, Ault KA, Haupt RM, Brown DR. | D89: Cancer Epidemiol. 2012 Jun;36(3):e183-9. doi: 10.1016/j.canep.2011.12.007. Epub 2012 Jan 25. | E89: Wiley DJ | F89: Cancer Epidemiol | G89: 2012 | H89: 40935 | K89: 10.1016/j.canep.2011.12.007 | L89: =IF(ISNUMBER(VLOOKUP(A89,EXCL,1,FALSE)),"Excluido",IF(ISNUMBER(VLOOKUP(A89,POST,1,FALSE)),"PostAlerta",IF(ISNUMBER(VLOOKUP(A89,PRE,1,FALSE)),"PreAlerta",""))) -> Excluido | M89: =IF(ISNUMBER(VLOOKUP(A89,KEYWORDS,1,FALSE)),"C/PalabrasClaves","S/PalabrasClaves") -> S/PalabrasClaves
A90: 22302695 | B90: Should urologists care for the pharyngeal infection of Neisseria gonorrhoeae or Chlamydia trachomatis when we treat male urethritis? | C90: Hamasuna R, Takahashi S, Uehara S, Matsumoto T. | D90: J Infect Chemother. 2012 Jun;18(3):410-3. doi: 10.1007/s10156-011-0355-6. | E90: Hamasuna R | F90: J Infect Chemother | G90: 2012 | H90: 40943 | K90: 10.1007/s10156-011-0355-6 | L90: =IF(ISNUMBER(VLOOKUP(A90,EXCL,1,FALSE)),"Excluido",IF(ISNUMBER(VLOOKUP(A90,POST,1,FALSE)),"PostAlerta",IF(ISNUMBER(VLOOKUP(A90,PRE,1,FALSE)),"PreAlerta",""))) -> PreAlerta | M90: =IF(ISNUMBER(VLOOKUP(A90,KEYWORDS,1,FALSE)),"C/PalabrasClaves","S/PalabrasClaves") -> S/PalabrasClaves | N90: 4) otros
A91: 22308534 | B91: Sensitivity of Gram stain in the diagnosis of urethritis in men | C91: Orellana MA, Gómez-Lus ML, Lora D. | D91: Sex Transm Infect. 2012 Jun;88(4):284-7. doi: 10.1136/sextrans-2011-050150. Epub 2012 Feb 2. | E91: Orellana MA | F91: Sex Transm Infect | G91: 2012 | H91: 40946 | K91: 10.1136/sextrans-2011-050150 | L91: =IF(ISNUMBER(VLOOKUP(A91,EXCL,1,FALSE)),"Excluido",IF(ISNUMBER(VLOOKUP(A91,POST,1,FALSE)),"PostAlerta",IF(ISNUMBER(VLOOKUP(A91,PRE,1,FALSE)),"PreAlerta",""))) -> PreAlerta | M91: =IF(ISNUMBER(VLOOKUP(A91,KEYWORDS,1,FALSE)),"C/PalabrasClaves","S/PalabrasClaves") -> S/PalabrasClaves | N91: 4) otros
A92: 22317841 | B92: HIV and sexually transmitted infections at the borderlands: situational analysis of sexual health in the Brazilian Amazon | C92: Benzaken A, Sabidó M, Galban E, Rodrigues Dutra DL, Leturiondo AL, Mayaud P. | D92: Sex Transm Infect. 2012 Jun;88(4):294-300. doi: 10.1136/sextrans-2011-050309. Epub 2012 Feb 7. | E92: Benzaken A | F92: Sex Transm Infect | G92: 2012 | H92: 40949 | K92: 10.1136/sextrans-2011-050309 | L92: =IF(ISNUMBER(VLOOKUP(A92,EXCL,1,FALSE)),"Excluido",IF(ISNUMBER(VLOOKUP(A92,POST,1,FALSE)),"PostAlerta",IF(ISNUMBER(VLOOKUP(A92,PRE,1,FALSE)),"PreAlerta",""))) -> PreAlerta | M92: =IF(ISNUMBER(VLOOKUP(A92,KEYWORDS,1,FALSE)),"C/PalabrasClaves","S/PalabrasClaves") -> S/PalabrasClaves | N92: 4) otros
A93: 22328644 | B93: High prevalence of HIV and sexually transmitted infections among male sex workers in Abidjan, Cote d'Ivoire: need for services tailored to their needs | C93: Vuylsteke B, Semde G, Sika L, Crucitti T, Ettiegne Traore V, Buve A, Laga M. | D93: Sex Transm Infect. 2012 Jun;88(4):288-93. doi: 10.1136/sextrans-2011-050276. Epub 2012 Feb 11. | E93: Vuylsteke B | F93: Sex Transm Infect | G93: 2012 | H93: 40953 | I93: PMC3351855 | K93: 10.1136/sextrans-2011-050276 | L93: =IF(ISNUMBER(VLOOKUP(A93,EXCL,1,FALSE)),"Excluido",IF(ISNUMBER(VLOOKUP(A93,POST,1,FALSE)),"PostAlerta",IF(ISNUMBER(VLOOKUP(A93,PRE,1,FALSE)),"PreAlerta",""))) -> PreAlerta | M93: =IF(ISNUMBER(VLOOKUP(A93,KEYWORDS,1,FALSE)),"C/PalabrasClaves","S/PalabrasClaves") -> S/PalabrasClaves | N93: 4) otros
A94: 22361459 | B94: Non-thermal argon plasma is bactericidal for the intracellular bacterial pathogen Chlamydia trachomatis | C94: Ermolaeva SA, Sysolyatina EV, Kolkova NI, Bortsov P, Tuhvatulin AI, Vasiliev MM, Mukhachev AY, Petrov OF, Tetsuji S, Naroditsky BS, Morfill GE, Fortov VE, Grigoriev AI, Zigangirova NA, Gintsburg AL. | D94: J Med Microbiol. 2012 Jun;61(Pt 6):793-799. doi: 10.1099/jmm.0.038117-0. Epub 2012 Feb 23. | E94: Ermolaeva SA | F94: J Med Microbiol | G94: 2012 | H94: 40964 | K94: 10.1099/jmm.0.038117-0 | L94: =IF(ISNUMBER(VLOOKUP(A94,EXCL,1,FALSE)),"Excluido",IF(ISNUMBER(VLOOKUP(A94,POST,1,FALSE)),"PostAlerta",IF(ISNUMBER(VLOOKUP(A94,PRE,1,FALSE)),"PreAlerta",""))) -> PreAlerta | M94: =IF(ISNUMBER(VLOOKUP(A94,KEYWORDS,1,FALSE)),"C/PalabrasClaves","S/PalabrasClaves") -> C/PalabrasClaves | N94: 2) Nuevos tratamientos | Q94: Listo | T94: Non-thermal plasma (NTP) is a flow of partially ionized argon gas at an ambient macroscopic temperature and is microbicidal for bacteria, viruses and fungi. Viability of the Gram-negative obligate intracellular bacterial parasite Chlamydia trachomatis and its host cells was investigated after NTP treatment. NTP treatment of C. trachomatis extracellular elementary bodies (EBs) diminished the concentration of infectious bacteria by a factor of 9×10(4), as established by the parallel infection of murine fibroblast McCoy cells with treated and control EBs. NTP treatment of infected McCoy cells caused disruption of membrane-restricted vacuoles (inclusions), where C. trachomatis intracellular reticulate bodies (RBs) multiply, and a 2×10(6)-fold reduction in the concentration of infectious bacteria. When the samples were covered with magnesium fluoride glass to obstruct plasma particles and UV rays alone were applied, the bactericidal effect was reduced 1.4×10(1)-fold and 5×10(4)-fold for EBs and RBs, respectively. NTP treatment caused the viability of host McCoy cells to diminish by 19%. Therefore, the results obtained demonstrated that (i) both extracellular and intracellular forms of C. trachomatis are sensitive to NTP treatment; (ii) the reduction in concentration of infectious bacteria after NTP treatment of infected cells is superior to the reduction in viability of host cells; and (iii) the effect of NTP on intracellular bacteria does not depend on UV rays. | U94: No | V94: Yes | W94: No | X94: Use of physical agents (Non-thermal plasma) for the treatment of intracellular C. trachomatis
A95: 22370921 | B95: Clinical and microbiological outcomes in treatment of men with non-gonococcal urethritis with a 100-mg twice-daily dose regimen of sitafloxacin | C95: Ito S, Yasuda M, Seike K, Sugawara T, Tsuchiya T, Yokoi S, Nakano M, Deguchi T. | D95: J Infect Chemother. 2012 Jun;18(3):414-8. doi: 10.1007/s10156-012-0392-9. Epub 2012 Feb 28. | E95: Ito S | F95: J Infect Chemother | G95: 2012 | H95: 40968 | K95: 10.1007/s10156-012-0392-9 | L95: =IF(ISNUMBER(VLOOKUP(A95,EXCL,1,FALSE)),"Excluido",IF(ISNUMBER(VLOOKUP(A95,POST,1,FALSE)),"PostAlerta",IF(ISNUMBER(VLOOKUP(A95,PRE,1,FALSE)),"PreAlerta",""))) -> Excluido | M95: =IF(ISNUMBER(VLOOKUP(A95,KEYWORDS,1,FALSE)),"C/PalabrasClaves","S/PalabrasClaves") -> S/PalabrasClaves
A96: 22407226 | B96: Distribution of Chlamydia trachomatis serotypes in clinical urogenital samples from north-eastern Croatia | C96: Bošnjak Z, Džijan S, Pavlinić D, Perić M, Ružman N, Križan IR, Lauc G, Antolović-Požgain A, Burazin J, Vuković D. | D96: Curr Microbiol. 2012 Jun;64(6):552-60. doi: 10.1007/s00284-012-0106-7. Epub 2012 Mar 11. | E96: Bošnjak Z | F96: Curr Microbiol | G96: 2012 | H96: 40981 | K96: 10.1007/s00284-012-0106-7 | L96: =IF(ISNUMBER(VLOOKUP(A96,EXCL,1,FALSE)),"Excluido",IF(ISNUMBER(VLOOKUP(A96,POST,1,FALSE)),"PostAlerta",IF(ISNUMBER(VLOOKUP(A96,PRE,1,FALSE)),"PreAlerta",""))) -> PreAlerta | M96: =IF(ISNUMBER(VLOOKUP(A96,KEYWORDS,1,FALSE)),"C/PalabrasClaves","S/PalabrasClaves") -> S/PalabrasClaves | N96: 4) otros
A97: 22431649 | B97: The recall response induced by genital challenge with Chlamydia muridarum protects the oviduct from pathology but not from reinfection | C97: Riley MM, Zurenski MA, Frazer LC, O'Connell CM, Andrews CW Jr, Mintus M, Darville T. | D97: Infect Immun. 2012 Jun;80(6):2194-203. doi: 10.1128/IAI.00169-12. Epub 2012 Mar 19. | E97: Riley MM | F97: Infect Immun | G97: 2012 | H97: 40989 | I97: PMC3370586 | K97: 10.1128/IAI.00169-12 | L97: =IF(ISNUMBER(VLOOKUP(A97,EXCL,1,FALSE)),"Excluido",IF(ISNUMBER(VLOOKUP(A97,POST,1,FALSE)),"PostAlerta",IF(ISNUMBER(VLOOKUP(A97,PRE,1,FALSE)),"PreAlerta",""))) -> PreAlerta | M97: =IF(ISNUMBER(VLOOKUP(A97,KEYWORDS,1,FALSE)),"C/PalabrasClaves","S/PalabrasClaves") -> S/PalabrasClaves | N97: 3) immunization | Q97: Listo | T97: The significant morbidities of ectopic pregnancy and infertility observed in women after Chlamydia trachomatis genital infection result from ascension of the bacteria from the endocervix to the oviduct, where an overly aggressive inflammatory response leads to chronic scarring and Fallopian tube obstruction. A vaccine to prevent chlamydia-induced disease is urgently needed. An important question for vaccine development is whether sterilizing immunity at the level of the oviduct is essential for protection because of the possibility that a chlamydial component drives a deleterious anamnestic T cell response upon oviduct reinfection. We show that mice inoculated with attenuated plasmid-cured strains of Chlamydia muridarum are protected from oviduct pathology upon challenge with wild-type C. muridarum Nigg despite induction of a response that did not prevent reinfection of the oviduct. Interestingly, repeated abbreviated infections with Nigg also elicited recall responses that protected the oviduct from pathology despite low-level reinfection of this vulnerable tissue site. Challenged mice displayed significant decreases in tissue infiltration of inflammatory leukocytes with marked reductions in frequencies of neutrophils but significant increases in frequencies of CD4 Th1 and CD8 T cells. An anamnestic antibody response was also detected. These data indicate that exposure to a live attenuated chlamydial vaccine or repeated abbreviated genital infection with virulent chlamydiae promotes anamnestic antibody and T cell responses that protect the oviduct from pathology despite a lack of sterilizing immunity at the site. | U97: No | V97: No | W97: Yes | X97: They demonstrated that mice inoculated with attenuated plasmid-cured strains of Chlamydia muridarum are protected from oviduct pathology following challenge with wild-type C. muridarum Nigg despite the induction of a response that did not prevent oviduct reinfection.
A98: 22431650 | B98: PmpG303-311, a protective vaccine epitope that elicits persistent cellular immune responses in Chlamydia muridarum-immune mice | C98: Johnson RM, Yu H, Kerr MS, Slaven JE, Karunakaran KP, Brunham RC. | D98: Infect Immun. 2012 Jun;80(6):2204-11. doi: 10.1128/IAI.06339-11. Epub 2012 Mar 19. | E98: Johnson RM | F98: Infect Immun | G98: 2012 | H98: 40989 | I98: PMC3370596 | K98: 10.1128/IAI.06339-11 | L98: =IF(ISNUMBER(VLOOKUP(A98,EXCL,1,FALSE)),"Excluido",IF(ISNUMBER(VLOOKUP(A98,POST,1,FALSE)),"PostAlerta",IF(ISNUMBER(VLOOKUP(A98,PRE,1,FALSE)),"PreAlerta",""))) -> PreAlerta | M98: =IF(ISNUMBER(VLOOKUP(A98,KEYWORDS,1,FALSE)),"C/PalabrasClaves","S/PalabrasClaves") -> C/PalabrasClaves | N98: 3) immunization | Q98: Listo | T98: Urogenital Chlamydia serovars replicating in reproductive epithelium pose a unique challenge to host immunity and vaccine development. Previous studies have shown that CD4 T cells are necessary and sufficient to clear primary Chlamydia muridarum genital tract infections in the mouse model, making a protective CD4 T cell response a logical endpoint for vaccine development. Our previous proteomics studies identified 13 candidate Chlamydia proteins for subunit vaccines. Of those, PmpG-1 is the most promising vaccine candidate. To further that work, we derived a PmpG(303-311)-specific multifunctional Th1 T cell clone, designated PmpG1.1, from an immune C57BL/6 mouse and used it to investigate the presentation of the PmpG(303-311) epitope by infected epithelial cells. Epithelial presentation of the PmpG(303-311) epitope required bacterial replication, occurred 15 to 18 h postinfection, and was unaffected by gamma interferon (IFN-γ) pretreatment. Unlike epitopes recognized by other Chlamydia-specific CD4 T cell clones, the PmpG(303-311) epitope persisted on splenic antigen-presenting cells (APC) of mice that cleared primary genital tract infections. PmpG1.1 was activated by unmanipulated irradiated splenocytes from immune mice without addition of exogenous Chlamydia antigen, and remarkably, activation of PmpG1.1 by unmanipulated immune splenocytes was stronger 6 months postinfection than it was 3 weeks postinfection. Enhanced presentation of PmpG(303-311) epitope on splenic APC 6 months postinfection reflects some type of "consolidation" of a protective immune response. Understanding the antigen-presenting cell populations responsible for presenting PmpG(303-311) early (3 weeks) and late (6 months) postinfection will likely provide important insights into stable protective immunity against Chlamydia infections of the genital tract. | U98: No | V98: No | W98: Yes | X98: They use a C. protein to trigger immune response
A99: 22446590 | B99: The first performance report for the Bio-Rad Dx CT/NG/MG assay for simultaneous detection of Chlamydia trachomatis, Neisseria gonorrhoeae and Mycoplasma genitalium in urogenital samples | C99: Le Roy C, Le Hen I, Clerc M, Arfel V, Normandin F, Bébéar C, de Barbeyrac B. | D99: J Microbiol Methods. 2012 Jun;89(3):193-7. doi: 10.1016/j.mimet.2012.03.009. Epub 2012 Mar 15. | E99: Le Roy C | F99: J Microbiol Methods | G99: 2012 | H99: 40995 | K99: 10.1016/j.mimet.2012.03.009 | L99: =IF(ISNUMBER(VLOOKUP(A99,EXCL,1,FALSE)),"Excluido",IF(ISNUMBER(VLOOKUP(A99,POST,1,FALSE)),"PostAlerta",IF(ISNUMBER(VLOOKUP(A99,PRE,1,FALSE)),"PreAlerta",""))) -> PreAlerta | M99: =IF(ISNUMBER(VLOOKUP(A99,KEYWORDS,1,FALSE)),"C/PalabrasClaves","S/PalabrasClaves") -> S/PalabrasClaves | N99: 4) otros
A100: 22449336 | B100: Development of multiplex real-time quantitative PCR for simultaneous detection of Chlamydia trachomatis and Ureaplasma parvum | C100: Wei HB, Zou SX, Yang XL, Yang DQ, Chen XD. | D100: Clin Biochem. 2012 Jun;45(9):663-7. doi: 10.1016/j.clinbiochem.2012.03.010. Epub 2012 Mar 17. | E100: Wei HB | F100: Clin Biochem | G100: 2012 | H100: 40996 | K100: 10.1016/j.clinbiochem.2012.03.010 | L100: =IF(ISNUMBER(VLOOKUP(A100,EXCL,1,FALSE)),"Excluido",IF(ISNUMBER(VLOOKUP(A100,POST,1,FALSE)),"PostAlerta",IF(ISNUMBER(VLOOKUP(A100,PRE,1,FALSE)),"PreAlerta",""))) -> PreAlerta | M100: =IF(ISNUMBER(VLOOKUP(A100,KEYWORDS,1,FALSE)),"C/PalabrasClaves","S/PalabrasClaves") -> S/PalabrasClaves | N100: 4) otros
...

Sheet Test
A1: PMID | B1: Title | C1: Categoria | D1: subcategoria | E1: Estado | F1: Abstract | G1: 1) Antimicrobial Resistance stain | H1: 2) New treatment | I1: 3) Immunization | J1: Human_summary
A2: 22436137 | B2: Phenotypic and genetic characterisation of bacterial sexually transmitted infections in Bissau, Guinea-Bissau, West Africa: a prospective cohort study | C2: 1) Reporte de cepas resistentes | E2: Listo | F2: The direct interrogation of fleeting intermediates by rapid-mixing kinetic methods has significantly advanced our understanding of enzymes that utilize dioxygen. The gas's modest aqueous solubility (<2 mM at 1 atm) presents a technical challenge to this approach, because it limits the rate of formation and extent of accumulation of intermediates. This challenge can be overcome by use of the heme enzyme chlorite dismutase (Cld) for the rapid, in situ generation of O(2) at concentrations far exceeding 2 mM. This method was used to define the O(2) concentration dependence of the reaction of the class Ic ribonucleotide reductase (RNR) from Chlamydia trachomatis, in which the enzyme's Mn(IV)/Fe(III) cofactor forms from a Mn(II)/Fe(II) complex and O(2) via a Mn(IV)/Fe(IV) intermediate, at effective O(2) concentrations as high as ~10 mM. With a more soluble receptor, myoglobin, an O(2) adduct accumulated to a concentration of >6 mM in <15 ms. Finally, the C-H-bond-cleaving Fe(IV)-oxo complex, J, in taurine:α-ketoglutarate dioxygenase and superoxo-Fe(2)(III/III) complex, G, in myo-inositol oxygenase, and the tyrosyl-radical-generating Fe(2)(III/IV) intermediate, X, in Escherichia coli RNR, were all accumulated to yields more than twice those previously attained. This means of in situ O(2) evolution permits a >5 mM "pulse" of O(2) to be generated in <1 ms at the easily accessible Cld concentration of 50 μM. It should therefore significantly extend the range of kinetic and spectroscopic experiments that can routinely be undertaken in the study of these enzymes and could also facilitate resolution of mechanistic pathways in cases of either sluggish or thermodynamically unfavorable O(2) addition steps. | G2: Yes | H2: No | I2: No | J2: They conducted a study of 3 types of bacteria, among which they found and characterized C. trachomatis
A3: 22290151 | B3: Chlamydia muridarum T cell antigens and adjuvants that induce protective immunity in mice | C3: 3) immunization | E3: Listo | F3: Major impediments to a Chlamydia vaccine lie in discovering T cell antigens and polarizing adjuvants that stimulate protective immunity. We previously reported the discovery of three T cell antigens (PmpG, PmpF, and RplF) via immunoproteomics that elicited protective immunity in the murine genital tract infection model against Chlamydia infection after adoptive transfer of antigen-pulsed dendritic cells. To expand the T cell antigen repertoire necessary for a Chlamydia vaccine, we evaluated 10 new Chlamydia T cell antigens discovered via immunoproteomics in addition to the 3 antigens reported earlier as a molecular subunit vaccine. We first tested five adjuvants, including three cationic liposome formulations (dimethyldioctadecylammonium bromide-monophosphoryl lipid A [DDA-MPL], DDA-trehalose 6,6'-dibehenate [DDA-TDB {CAF01}], and DDA-monomycolyl glycerol [DDA-MMG {CAF04}]), Montanide ISA720-CpG-ODN1826, and alum using the PmpG protein as a model T cell antigen in the mouse genital tract infection model. The results showed that the cationic liposomal adjuvants DDA-MPL and DDA-TDB elicited the best protective immune responses, characterized by multifunctional CD4(+) T cells coexpressing gamma interferon (IFN-γ) and tumor necrosis factor alpha (TNF-α), and reduced infection by more than 3 logs. Using DDA-MPL as an adjuvant, we found that 7 of 13 Chlamydia T cell antigens (PmpG, PmpE, PmpF, Aasf, RplF, TC0420, and TC0825) conferred protection better than or equal to that of the reference vaccine antigen, major outer membrane protein (MOMP). Pools of membrane/secreted proteins, cytoplasmic proteins, and hypothetical proteins were tested individually or in combination. Immunization with combinations protected as well as the best individual protein in that combination. The T cell antigens and adjuvants discovered in this study are of further interest in the development of a molecularly defined Chlamydia vaccine. | G3: No | H3: No | I3: Yes | J3: They evaluated 10 novel chlamydia T-cell antigens discovered by immunoproteomics, in addition to the 3 antigens previously reported as a molecular subunit vaccine.
A4: 22387629 | B4: Protection of pigs against genital Chlamydia trachomatis challenge by parenteral or mucosal DNA immunization | C4: 3) immunization | E4: Listo | F4: The current study evaluates combined aerosol-vaginal delivery of a MOMP-based Chlamydia trachomatis (serovar E) DNA vaccine in a pig genital challenge model. Most non-replicating antigens are rather poor mucosal immunogens in comparison to replicating antigens. Therefore, a mucosal administered DNA vaccine, which actually mimics a live vaccine, could be promising. Protection was promoted by plasmids encoding the porcine granulocyte macrophage-colony stimulating factor (pcDNA3.1zeo::GM-CSF), the Escherichia coli thermo-labile enterotoxin (LT) subunit A (plasmid PJV2004::LTa) and subunit B (plasmid PJV2005::LTb). Mucosal C. trachomatis DNA vaccination induced significant protection against genital C. trachomatis challenge although the infection could not be eradicated. Intradermal immunization was significantly less efficient in protecting experimentally infected pigs. Protection was correlated with efficient T cell priming and significantly higher serum IgA titers following primo vaccination. | G4: No | H4: No | I4: Yes | J4: They use different methods (spray, intradermal) to administer a vaccine.
A5: 22564463 | B5: Mycoplasma genitalium presence, resistance and epidemiology in Greenland | C5: 1) Reporte de cepas resistentes | E5: Listo | F5: Objectives: Greenland reports the highest rates of chlamydial infection and gonorrhea in the Arctic. Our objective was to determine the presence, and describe the basic epidemiology, of Mycoplasma genitalium for Greenland. Study design: Cross-sectional study. Methods: 314 residents from Nuuk and Sisimiut, between the ages of 15 and 65 years, participated in "Inuulluataarneq" (the Greenland Sexual Health Project) between July 2008 and November 2009. Participants provided self-collected samples for sexually transmitted infection (STI) testing and completed a sexual health survey. Descriptive statistics and logistic regression were used to summarize the basic characteristics of STI cases overall and M. genitalium and Chlamydia trachomatis specifically. Clinically relevant characteristics in each full model were gender (male or female), age (in years), age at sexual debut (in years), number of sexual partners in the past 3 months (continuous) and history of forced sex and community. Results: The overall prevalence of STIs was 19.0%, specifically: 9.8% for M. genitalium and 9.4% for C. trachomatis; 100% of M. genitalium-positive cases carried macrolide resistance determinants. Being female [OR = 3.2; 95% confidence interval (CI): 1.1-9.8] and younger age (OR = 0.9; 95% CI: 0.9-1.0) were associated with M. genitalium positivity. Age was also associated with C. trachomatis (OR = 0.9; 95% CI: 0.8-0.9) and STI positivity overall (OR = 0.9; 95% CI: 0.9-0.9). Conclusions: We observed a high prevalence of M. genitalium and macrolide resistance in this study. A better understanding of M. genitalium sequelae is needed to inform policy around testing, treatment, control and antibiotic use. | G5: No | H5: No | I5: No | J5: The resistant strain is Mycoplasma
A6: 22293657 | B6: First reported case of the Swedish new variant of Chlamydia trachomatis (nvCT) in Eastern Europe (Russia), and evaluation of Russian nucleic acid amplification tests regarding their ability to detect nvCT | C6: 1) Reporte de cepas resistentes | E6: Listo | F6: Chlamydia trachomatis infections are the most prevalent bacterial sexually transmitted infections (STIs) worldwide, and are associated with considerable morbidity and socio-economic consequences. The Swedish new variant of C. trachomatis (nvCT), first reported in Sweden in late 2006, contains a 377-bp deletion in the cryptic plasmid that covers the single tar-gets originally utilized in the nucleic acid amplification tests (NAATs) manufactured by Roche Diagnostics (Amplicor, Cobas Amplicor, Cobas TaqMan48) and Abbott Laboratories (Abbott m2000), which at the time were used worldwide (1, 2). In Sweden, the proportion of nvCT, compared with wild type CT (wtCT), was high (7–64% in the different counties) (3, 4), and nvCT accordingly caused thousands of falsely negative diag-noses. The nvCT prevalence in Sweden is still relatively high, and nvCT has been frequently detected in Norway, Finland and Denmark (5, 6). Although genome sequen-cing and phenotypic characterization have shown that nvCT, compared with wtCT, has an unaltered biological fitness in vitro (7), nvCT is rarely reported outside the Nordic countries (5, 7–9). However, knowledge of the nvCT presence beyond the Nordic countries is limited because few recent studies have been performed, many laboratories still cannot detect nvCT, and the ones that can detect nvCT mainly do not distinguish it from wtCT (5, 10, 11). The aims of this study were: (i) to investigate the pre-sence of nvCT in St Petersburg, the largest city in the northwest of Russia and in close geographical proximity to Sweden; and (ii) to assess NAATs used in Russia to diagnose C. trachomatisinfections for their ability to detect nvCT | G6: Yes | H6: No | I6: No | J6: New strain found in Russia
A7: 22427578 | B7: Genome-wide identification of Chlamydia trachomatis antigens associated with trachomatous trichiasis | C7: 3) immunization | E7: Listo | F7: Purpose: Chlamydia trachomatis is the leading infectious cause of blindness. The goal of the current study was to search for biomarkers associated with C. trachomatis-induced ocular pathologies. Methods: We used a whole genome scale proteome array to systematically profile antigen specificities of antibody responses to C. trachomatis infection in individuals from trachoma-endemic communities with or without end-stage trachoma (trichiasis) in The Gambia. Results: When 61 trichiasis patients were compared with their control counterparts for overall antibody reactivity with organisms of different chlamydial species, no statistically significant difference was found. Both groups developed significantly higher titers of antibodies against C. trachomatis ocular serovars A and B than ocular serovar C, genital serovar D, or Chlamydia psittaci, whereas the titers of anti-Chlamydia pneumoniae antibodies were the highest. When antisera from 33 trichiasis and 26 control patients (with relatively high titers of antibodies to C. trachomatis ocular serovars) were reacted with 908 C. trachomatis proteins, 447 antigens were recognized by at least 1 of the 59 antisera, and 10 antigens by 50% or more antisera, the latter being designated as immunodominant antigens. More importantly, four antigens were preferentially recognized by the trichiasis group, with antigens CT414, CT667, and CT706 collectively reacting with 30% of trichiasis antisera but none from the normal group, and antigen CT695 reacting with 61% of trichiasis but only 31% of normal antisera. On the other hand, eight antigens were preferentially recognized by the control group, with antigens CT019, CT117, CT301, CT553, CT556, CT571, and CT709 together reacting with 46% of normal antisera and none from the trichiasis group, whereas antigen CT442 reacted with 35% of normal and 19% of trichiasis antisera respectively. Conclusions: The current study, by mapping immunodominant C. trachomatis antigens and identifying antigens associated with both ocular pathology and protection, has provided important information for further understanding chlamydial pathogenesis and the development of subunit vaccines. | G7: No | H7: No | I7: Yes | J7: The current study, by mapping immunodominant C. trachomatis antigens and identifying antigens associated with both ocular pathology and protection, has provided important information for a better understanding of the pathogenesis of chlamydia and the development of subunit vaccines.
A8: 22525317 | B8: Derivatives of 8-hydroxyquinoline--antibacterial agents that target intra- and extracellular Gram-negative pathogens | C8: 2) Nuevos tratamientos | D8: 2c) Droga de diseño | E8: Listo | F8: Small molecule screening identified 5-nitro-7-((4-phenylpiperazine-1-yl-)methyl)quinolin-8-ol INP1750 as a putative inhibitor of type III secretion (T3S) in the Gram-negative pathogen Yersinia pseudotuberculosis. In this study we report structure-activity relationships for inhibition of T3S and show that the most potent compounds target both the extracellular bacterium Y. pseudotuberculosis and the intracellular pathogen Chlamydia trachomatis in cell-based infection models. | G8: No | H8: Yes | I8: No
A9: 22783236 | B9: Genomic and Biochemical Analysis of the Diaminopimelate and Lysine Biosynthesis Pathway in Verrucomicrobium spinosum: Identification and Partial Characterization of L,L-Diaminopimelate Aminotransferase and UDP-N-Acetylmuramoylalanyl-D-glutamyl-2,6-meso-Diaminopimelate Ligase | C9: 2) Nuevos tratamientos | D9: 2c) Droga de diseño | E9: Listo | F9: Small molecule screening identified 5-nitro-7-((4-phenylpiperazine-1-yl-)methyl)quinolin-8-ol INP1750 as a putative inhibitor of type III secretion (T3S) in the Gram-negative pathogen Yersinia pseudotuberculosis. In this study we report structure-activity relationships for inhibition of T3S and show that the most potent compounds target both the extracellular bacterium Y. pseudotuberculosis and the intracellular pathogen Chlamydia trachomatis in cell-based infection models. | G9: No | H9: Yes | I9: No | J9: Designer drug used to treat Yersinia and intracellular chlamydia
A10: 22361459 | B10: Non-thermal argon plasma is bactericidal for the intracellular bacterial pathogen Chlamydia trachomatis | C10: 2) Nuevos tratamientos | E10: Listo | F10: Non-thermal plasma (NTP) is a flow of partially ionized argon gas at an ambient macroscopic temperature and is microbicidal for bacteria, viruses and fungi. Viability of the Gram-negative obligate intracellular bacterial parasite Chlamydia trachomatis and its host cells was investigated after NTP treatment. NTP treatment of C. trachomatis extracellular elementary bodies (EBs) diminished the concentration of infectious bacteria by a factor of 9×10(4), as established by the parallel infection of murine fibroblast McCoy cells with treated and control EBs. NTP treatment of infected McCoy cells caused disruption of membrane-restricted vacuoles (inclusions), where C. trachomatis intracellular reticulate bodies (RBs) multiply, and a 2×10(6)-fold reduction in the concentration of infectious bacteria. When the samples were covered with magnesium fluoride glass to obstruct plasma particles and UV rays alone were applied, the bactericidal effect was reduced 1.4×10(1)-fold and 5×10(4)-fold for EBs and RBs, respectively. NTP treatment caused the viability of host McCoy cells to diminish by 19%. Therefore, the results obtained demonstrated that (i) both extracellular and intracellular forms of C. trachomatis are sensitive to NTP treatment; (ii) the reduction in concentration of infectious bacteria after NTP treatment of infected cells is superior to the reduction in viability of host cells; and (iii) the effect of NTP on intracellular bacteria does not depend on UV rays. | G10: No | H10: Yes | I10: No | J10: Use of physical agents (Non-thermal plasma) for the treatment of intracellular C. trachomatis
A11: 22431649 | B11: The recall response induced by genital challenge with Chlamydia muridarum protects the oviduct from pathology but not from reinfection | C11: 3) immunization | E11: Listo | F11: The significant morbidities of ectopic pregnancy and infertility observed in women after Chlamydia trachomatis genital infection result from ascension of the bacteria from the endocervix to the oviduct, where an overly aggressive inflammatory response leads to chronic scarring and Fallopian tube obstruction. A vaccine to prevent chlamydia-induced disease is urgently needed. An important question for vaccine development is whether sterilizing immunity at the level of the oviduct is essential for protection because of the possibility that a chlamydial component drives a deleterious anamnestic T cell response upon oviduct reinfection. We show that mice inoculated with attenuated plasmid-cured strains of Chlamydia muridarum are protected from oviduct pathology upon challenge with wild-type C. muridarum Nigg despite induction of a response that did not prevent reinfection of the oviduct. Interestingly, repeated abbreviated infections with Nigg also elicited recall responses that protected the oviduct from pathology despite low-level reinfection of this vulnerable tissue site. Challenged mice displayed significant decreases in tissue infiltration of inflammatory leukocytes with marked reductions in frequencies of neutrophils but significant increases in frequencies of CD4 Th1 and CD8 T cells. An anamnestic antibody response was also detected. These data indicate that exposure to a live attenuated chlamydial vaccine or repeated abbreviated genital infection with virulent chlamydiae promotes anamnestic antibody and T cell responses that protect the oviduct from pathology despite a lack of sterilizing immunity at the site. | G11: No | H11: No | I11: Yes | J11: They demonstrated that mice inoculated with attenuated plasmid-cured strains of Chlamydia muridarum are protected from oviduct pathology following challenge with wild-type C. muridarum Nigg despite the induction of a response that did not prevent oviduct reinfection.
A12: 22431650 | B12: PmpG303-311, a protective vaccine epitope that elicits persistent cellular immune responses in Chlamydia muridarum-immune mice | C12: 3) immunization | E12: Listo | F12: Urogenital Chlamydia serovars replicating in reproductive epithelium pose a unique challenge to host immunity and vaccine development. Previous studies have shown that CD4 T cells are necessary and sufficient to clear primary Chlamydia muridarum genital tract infections in the mouse model, making a protective CD4 T cell response a logical endpoint for vaccine development. Our previous proteomics studies identified 13 candidate Chlamydia proteins for subunit vaccines. Of those, PmpG-1 is the most promising vaccine candidate. To further that work, we derived a PmpG(303-311)-specific multifunctional Th1 T cell clone, designated PmpG1.1, from an immune C57BL/6 mouse and used it to investigate the presentation of the PmpG(303-311) epitope by infected epithelial cells. Epithelial presentation of the PmpG(303-311) epitope required bacterial replication, occurred 15 to 18 h postinfection, and was unaffected by gamma interferon (IFN-γ) pretreatment. Unlike epitopes recognized by other Chlamydia-specific CD4 T cell clones, the PmpG(303-311) epitope persisted on splenic antigen-presenting cells (APC) of mice that cleared primary genital tract infections. PmpG1.1 was activated by unmanipulated irradiated splenocytes from immune mice without addition of exogenous Chlamydia antigen, and remarkably, activation of PmpG1.1 by unmanipulated immune splenocytes was stronger 6 months postinfection than it was 3 weeks postinfection. Enhanced presentation of PmpG(303-311) epitope on splenic APC 6 months postinfection reflects some type of "consolidation" of a protective immune response. Understanding the antigen-presenting cell populations responsible for presenting PmpG(303-311) early (3 weeks) and late (6 months) postinfection will likely provide important insights into stable protective immunity against Chlamydia infections of the genital tract. | G12: No | H12: No | I12: Yes | J12: They use a C. protein to trigger immune response
A13: 22296995 | B13: More than classical Chlamydia psittaci in urban pigeons | C13: 1) Reporte de cepas resistentes | E13: Listo | F13: In the literature, studies of Chlamydia infection in birds have usually been confined to the search for Chlamydia (C., formerly Chlamydophila) psittaci, so that little is known about the presence of other chlamydial agents. In the present study, cloacal swabs and faeces samples of urban pigeons have been examined by real-time PCR, DNA microarray assays and partial ompA sequencing. Whilst C. psittaci was the predominant chlamydial agent in this pigeon population (75.8% of all Chlamydiaceae positives), the combined use of highly specific and sensitive molecular assays facilitated the detection of atypical serovars of C. psittaci, as well as other species of Chlamydia, such as C. abortus. Detection of C. pecorum and C. trachomatis from an avian host is reported here for the first time. Rather unexpectedly, 19.5% of all Chlamydiaceae-positive cases turned out to be infected with non-classified organisms. The considerable prevalence of these novel agents raises the question of their epidemiological importance and possible role as pathogens. Future surveys in domestic and wild birds will have to take the extended variety of chlamydial organisms into account. | G13: No | H13: No | I13: No | J13: They find a new strain in birds, but it does not talk about resistance
A14: 22682294 | B14: High-throughput proteomic screening identifies Chlamydia trachomatis antigens that are capable of eliciting T cell and antibody responses that provide protection against vaginal challenge | C14: 3) immunization | E14: Listo | F14: A comprehensive proteomic screening technology was previously used to characterize T cell responses to Chlamydia trachomatis infection. In this study, we demonstrated that T cells specific for protein antigens identified through this comprehensive technology home to the site of infection after mucosal challenge with C. trachomatis. In addition, T cell responses to these proteins were elicited in multiple genetic backgrounds. Two protein antigens, CT823 and CT144, were evaluated as vaccine candidates. When administered with AbISCO-100 adjuvant, these antigens stimulated potent CD8(+) T cell responses, polyfunctional T(H)1-polarized CD4(+) T cell responses, and high titer protein-specific T(H)1-skewed antibody responses. Vaccination with either antigen with AbISCO-100 provided long-lived protection against intravaginal challenge with C. trachomatis. Adoptive transfer of immune T cells also conferred protection in the challenge model whereas passive transfer of immune serum did not, indicating the critical role for T cell responses in control of this infection. The ability of these antigens to induce potent immune responses and provide long-lived protection in response to challenge provides a basis for the rational design of a C. trachomatis subunit vaccine. | G14: No | H14: No | I14: Yes | J14: Using two proteins of C. trachomatis they induce an immune response. They find one with greater effectiveness
A15: 22716645 | B15: Nafamostat mesylate, a serine protease inhibitor, demonstrates novel antimicrobial properties and effectiveness in Chlamydia-induced arthritis | C15: 2) Nuevos tratamientos | D15: 2c) Droga de diseño | E15: Listo | F15: Introduction: Effective treatment of reactive arthritis would ideally achieve both control of inflammation and eradication of persisting arthritogenic pathogens. We use a model of experimental Chlamydia trachomatis-induced arthritis (CtIA) to evaluate the effectiveness of nafamostat mesilate (NM), a serine protease inhibitor with complement-modifying effects and anticoagulant properties. To date clinical use of NM has largely been in Asia and has been primarily confined to inflammatory states such as pancreatitis. Methods: In vitro studies examined inhibition of Chlamydia proliferation using fibroblast cell lines as targets and phase contrast microscopy. In vivo studies used an established protocol, experimental CtIA, induced in Lewis rats by injection of synoviocyte-packaged C. trachomatis. NM was dissolved in water and administered by daily intraperitoneal injection at a dose of 10 mg/kg beginning the day prior to the administration of Chlamydia. Readouts in vivo included (i) joint swelling, (ii) histopathology scoring of severity of arthritis, (iii) host clearance of the pathogen (by ELISA, the IDEIA PCE Chlamydia). Results: NM exerted a dose-dependent inhibition of chlamydial proliferation in vitro. Without NM, the mean number of inclusion bodies (IB) per well was 17,886 (± 1415). At 5 μg/mL NM, there were 8,490 (± 756) IB, at 25 μg/mL NM there were 35 IB and at 50 μg/mL NM no IB was observed. Chlamydial antigens in each well along the concentration gradient were assayed by ELISA, demonstrating that at 25 μg/mL NM inhibition of Chlamydia was almost complete. In the experimental arthritis model, joint swelling was significantly reduced with NM treatment: average joint width for the NM-treated animals was 8.55 mm (s.d. ± 0.6578, n = 10) versus 11.18 mm (s.d. ± 0.5672, n = 10) in controls (P < 0.001). Histopathology scoring indicated that NM resulted in a marked attenuation of the inflammatory infiltration and joint damage: mean pathology score in NM-treated animals was 10.9 (± 2.45, n = 11) versus 15.9 (± 1.45, n = 10) in controls (P < 0.0001). With respect to persistence of Chlamydia within the synovial tissues, NM treatment was accompanied by a reduction in the microbial load in the joint: mean optical density (O.D.) for ELISA with NM treatment was 0.05 (± 0.02, n = 4) versus 0.18 (± 0.05, n = 4) in controls (P < 0.001). Conclusions: NM is a protease inhibitor not previously recognized to possess antimicrobial properties. The present study demonstrates for the first time that NM exerts significant impact on C. trachomatis-induced arthritis and suggests that such approaches may prove clinically useful in chronic reactive arthritis. | G15: No | H15: Yes | I15: No | J15: With a drug previously used as a blood thinner, they show that it exerts a significant impact on C. trachomatis-induced arthritis and suggests that such approaches may prove clinically useful in chronic reactive arthritis.
A16: 22421110 | B16: Mapping immunodominant antigens and H-2-linked antibody responses in mice urogenitally infected with Chlamydia muridarum | C16: 3) immunization | E16: Listo | F16: To identify immunodominant antigens and MHC-restricted antibody responses, seven different strains of mice were intravaginally infected with Chlamydia muridarum and compared for antibody responses to 257 C. muridarum proteins. The 7 strains of mice recognized a total of 109 proteins as antigens, of which, 5 antigens (TC0660, TC0727, TC0828, TC0726 & TC0268) were each recognized by 60% or more mice from each mouse strain and thus designated as immunodominant antigens. Furthermore, antibody responses to 19 other antigens displayed strong associations with mouse H-2 haplotypes, including 6 antigens (TC0480, TC0912, TC0229, TCA04, TC0289 & TC0892) whose antibody responses were linked to H-2(b), 8 (TC0035, TC0387, TC0052, TC0781, TC0373, TC0117, TC0066 & TC0396) to H-2(d) and 5 (TC0512, TC0177, TC0589, TC0794 & TC0596) to H-2(k) haplotypes respectively. Interestingly, H-2(b) was negatively associated with antibody responses to most of the antigens that were positively linked to H-2(d) or H-2(k) haplotypes. These results by mapping Chlamydia trachomatis antigens commonly recognized by mice with different strain background and H-2 genes and revealing antigen association with H-2 haplotypes have provided important information for developing chlamydial subunit vaccines and understanding chlamydial pathogenesis. | G16: No | H16: No | I16: Yes | J16: To identify immunodominant antigens and MHC-restricted antibody responses, seven different strains of mice were intravaginally infected with Chlamydia muridarum and antibody responses to 257 C. muridarum proteins were compared.
A17: 22494890 | B17: Engineered phage-based therapeutic materials inhibit Chlamydia trachomatis intracellular infection | C17: 2) Nuevos tratamientos | D17: 2e) Bacteriófagos | E17: Listo | F17: Developing materials that are effective against sexually transmitted pathogens such as Chlamydia trachomatis (Ct) and HIV-1 is challenging both in terms of material selection and improving bio-membrane and cellular permeability at desired mucosal sites. Here, we engineered the prokaryotic bacterial virus (M13 phage) carrying two functional peptides, integrin binding peptide (RGD) and a segment of the polymorphic membrane protein D (PmpD) from Ct, as a phage-based material that can ameliorate Ct infection. Ct is a globally prevalent human pathogen for which there are no effective vaccines or microbicides. We show that engineered phage stably express both RGD motifs and Ct peptides and traffic intracellularly and into the lumen of the inclusion in which the organism resides within the host cell. Engineered phage were able to significantly reduce Ct infection in both HeLa and primary endocervical cells compared with Ct infection alone. Polyclonal antibodies raised against PmpD and co-incubated with constructs prior to infection did not alter the course of infection, indicating that PmpD is responsible for the observed decrease in Ct infection. Our results suggest that phage-based design approaches to vector delivery that overcome mucosal cellular barriers may be effective in preventing Ct and other sexually transmitted pathogens. | G17: No | H17: Yes | I17: No | J17: Treatment with two peptides transported by prokaryotic phages genetically modified to express them
A18: 22937702 | B18: [New approaches to therapy of persistent infections: elimination of intracellular Chlamydai trachomatis by exposure to low temperature argon plasma] | C18: 2) Nuevos tratamientos | E18: Listo | F18: Aim: Study microbicidal activity of low temperature argon plasma (LTP) that is a stream of partially ionized argon having macroscopic temperature of the environment against Chlamydia trachomatis obligate intracellular parasites. Study viability of host cells in parallel. Materials and methods: McCoy line cells infected with C. trachomatis (Bu-434/L2 strain) were exposed to LTP obtained by using atmospheric pressure plasma SHF generator. Intracellular localization of chlamydiae was visualized by luminescent microscopy. Results: Exposure of infected McCoy line cells resulted in the destruction of chlamydia inclusions and practically complete elimination of intracellular bacteria. At the same time LTP exposure did not result in immediate death of host cells, an insignificant reduction of the number of cells was observed 24 hours after the exposure to LTP. Conclusion: The effect of LTP for elimination of intracellular chlamydia without significant changes in viability of eukaryotic host cells was demonstrated. | G18: No | H18: Yes | I18: No | J18: Physical treatment with low-temperature argon plasma to treat intracellular bacteria, in vitro
A19: 22113367 | B19: In vitro antichlamydial activity of garenoxacin against Chlamydia trachomatis | C19: 2) Nuevos tratamientos | D19: 2c) Droga de diseño | E19: Listo | F19: Garenoxacin showed the most potent chlamydial activity against Chlamydia trachomatis D/UW-3/Cx among three tested quinolones and azithromycin. The DNA gyrase genes, gyrA and gyrB, of C. trachomatis D/UW-3/Cx were cloned and the GyrA and GyrB subunits of DNA gyrase protein were separately expressed as histidine-tagged proteins in Escherichia coli. The mean 50% inhibitory concentration (IC(50)) of garenoxacin against the supercoiling activity of C. trachomatis D/UW-3/Cx gyrase was 2.9 ± 0.4 μg/ml, which was the most potent inhibitory activity against DNA gyrase among the quinolones tested in this study. At an extracellular concentration of 0.5 μg/ml, the cellular-to-extracellular concentration ratio of garenoxacin was 15.3 ± 1.3, equivalent to that of moxifloxacin and greater than that of levofloxacin. In a time-kill experiment, after exposure to garenoxacin at a concentration of 0.5 μg/ml at 0-6, 5-11, and 24-30 h after infection, the percentages of recoverable chlamydial inclusion-forming units were 11.1 ± 3.3, 0.6 ± 0.1, and 2.6 ± 0.5%, respectively. On transmission electron microscopy observation, after exposure to garenoxacin at 24-30 h after infection, some C. trachomatis elementary bodies remained in the inclusion body; however, the reticulate bodies were completely disrupted. In conclusion, garenoxacin is expected to be a useful quinolone in the treatment of infectious diseases caused by C. trachomatis. | G19: No | H19: Yes | I19: No | J19: In vitro use of a fluoroquinolone that had not been previously used with C. trachomatis
A20: 22363020 | B20: The first case record of a female patient with bubonic lymphogranuloma venereum (LGV), serovariant L2b | C20: 1) Reporte de cepas resistentes | E20: Listo | F20: Since 2003, a lymphogranuloma venereum epidemic has been reported in The Netherlands and other European countries. This epidemic is caused by Chlamydia trachomatis serovariant L2b and has only been seen in men having sex with men. The authors investigated a woman presenting with a bubo in her right groin. The authors showed by real-time PCR that the woman was infected with C trachomatis, serovariant L2b. This is the first reported case study of a female patient with bubonic lymphogranuloma venereum caused by serovariant L2b, which was probably contracted via her bisexual male partner. | G20: No | H20: No | I20: No | J20: It is a new strain in the region, but sensitive to tanninbiotics
A21: 22455539 | B21: Antimicrobial susceptibility and molecular typing of multiple Chlamydiaceae species isolated from genital infection of women in Egypt | C21: 2) Nuevos tratamientos | E21: Listo | F21: This study investigated the existence of vaginal Chlamydia infection and the prevalence of the disease in symptomatic gynecologically diseased women in Egypt. In addition, the antibiotics penicillin, tetracycline, and erythromycin were evaluated for their in vitro antichlamydial activity of the isolated strains. Vaginal swabs (n=160) were collected from females gynecologically diseased using cotton swabs. Samples were tested for Chlamydia by Vero cells tissue culture, chicken embryo, Gimenez staining, direct fluorescein-conjugated monoclonal antibody staining, and immunoperoxidase. Polymerase chain reaction (PCR) analyses conducted for the presence of chlamydial DNA was used to detect its specific DNA by the omp2 gene. PCR analyses conducted for the presence of chlamydial DNA revealed that 112/160 (70%) were positive for Chlamydiaceae. The specific DNA defined by the omp2 gene identified them as Chlamydia trachomatis (17/112, 15.2%), Chlamydophila psittaci (56/112, 50.0%), and Chlamydophila abortus (40/112, 35.7%). The antibiotics penicillin, tetracycline, and erythromycin at different concentrations were effective in inactivating the viability of Chlamydiaceae isolates. | G21: No | H21: No | I21: No | J21: Routine antibiotic testing is performed, and the strains are sensitive to all
A22: 22517887 | B22: What is the appropriate treatment for the management of rectal Chlamydia trachomatis in men and women? | C22: 2) Nuevos tratamientos | E22: Listo | F22: Background: There is no UK guidance specifically for the management of rectal Chlamydia trachomatis yet there is documented treatment failure with single-dose azithromycin suggesting that test of cure (TOC) and alternative treatment may be needed. Objectives: To evaluate the efficacy of single-dose azithromycin compared with 1 week of doxycycline in the treatment of rectal C trachomatis. Methods: Data were collected prospectively on all patients diagnosed with rectal C trachomatis who received azithromycin 1 g stat between 1 January and 30 June 2010 and between 1 October 2010 and 31 March 2011 following a local change in treatment protocol to 1 week of doxycycline 100 mg twice a day. Information was collected on gender, concurrent sexually transmitted infections, treatment received, re-infection risk, re-treatment and TOC at 6 weeks. Results: 11 patients (26.2%) had a positive TOC following treatment with stat azithromycin. The risk of re-infection was excluded in two, identifying nine of the 11 (81.8%) as treatment failures. Two patients had a positive TOC following treatment with 1 week of doxycycline, both were found to have a risk of re-infection. There was a significantly higher treatment failure rate in patients receiving azithromycin (p=0.0025). Conclusions: A higher treatment failure rate was found following azithromycin for rectal C trachomatis than previously published. If azithromycin is used for treatment of rectal C trachomatis, TOC may be required or alternative treatment with doxycycline may be preferable, but further data are required. | G22: No | H22: No | I22: No | J22: A comparison of doses of antibiotics used (doxycycline vs azothromycin) is made
A23: 22644029 | B23: Resistance to a novel antichlamydial compound is mediated through mutations in Chlamydia trachomatis secY | C23: 1) Reporte de cepas resistentes | D23: 2c) Droga de diseño | E23: Listo | F23: A novel and quantitative high-throughput screening approach was explored as a tool for the identification of novel compounds that inhibit chlamydial growth in mammalian cells. The assay is based on accumulation of a fluorescent marker by intracellular chlamydiae. Its utility was demonstrated by screening 42,000 chemically defined compounds against Chlamydia caviae GPIC. This analysis led to the identification of 40 primary-hit compounds. Five of these compounds were nontoxic to host cells and had similar activities against both C. caviae GPIC and Chlamydia trachomatis. The inhibitory activity of one of the compounds, (3-methoxyphenyl)-(4,4,7-trimethyl-4,5-dihydro-1H-[1,2]dithiolo[3,4-C]quinolin-1-ylidene)amine (MDQA), was chlamydia specific and was selected for further study. Selection for resistance to MDQA led to the generation of three independent resistant clones of C. trachomatis. Amino acid changes in SecY, a protein involved in Sec-dependent secretion in Gram-negative bacteria, were associated with the resistance phenotype. The amino acids changed in each of the resistant mutants are located in the predicted central channel of a SecY crystal structure, based on the known structure of Thermus thermophilus SecY. These experiments model a process that can be used for the discovery of antichlamydial, anti-intracellular, or antibacterial compounds and has led to the identification of compounds that may have utility in both antibiotic discovery and furthering our understanding of chlamydial biology. | G23: No | H23: Yes | I23: No | J23: In the work they find a new treatment based on a drug screening, and they also find 3 strains resistant to this antibiotic
A24: 22669447 | B24: Pre-clinical pharmacokinetics and anti-chlamydial activity of salicylidene acylhydrazide inhibitors of bacterial type III secretion | C24: 2) Nuevos tratamientos | D24: 2c) Droga de diseño | E24: Listo | F24: Salicylidene acylhydrazides belong to a class of compounds shown to inhibit bacterial type III secretion (T3S) in pathogenic Gram-negative bacteria. This class of compounds also inhibits growth and replication of Chlamydiae, strict intracellular bacteria that possess a T3S system. In this study a library of 58 salicylidene acylhydrazides was screened to identify inhibitors of Chlamydia growth. Compounds inhibiting growth of both Chlamydia trachomatis and Chlamydophila pneumoniae were tested for cell toxicity and seven compounds were selected for preliminary pharmacokinetic analysis in mice using cassette dosing. Two compounds, ME0177 and ME0192, were further investigated by individual pharmacokinetic analysis. Compound ME0177 had a relatively high peak plasma concentration (C(max)) and area under curve and therefore may be considered for systemic treatment of Chlamydia infections. The other compound, ME0192, had poor pharmacokinetic properties but the highest anti-chlamydial activity in vitro and therefore was tested for topical treatment in a mouse vaginal infection model. ME0192 administered vaginally significantly reduced the infectious burden of C. trachomatis and the number of infected mice. | G24: No | H24: Yes | I24: No | J24: Variants of salicylidene acylhydrazides evaluated for the treatment of bacteria in vitro and in vivo
A25: 22797690 | B25: Prevalence trends of the new variant of Chlamydia trachomatis in four counties of Sweden in 2007-2011 | C25: 1) Reporte de cepas resistentes | E25: Listo | F25: A new variant of Chlamydia trachomatis (nvCT) was discovered in Sweden in 2006, and it could not be detected by diagnostic systems from Abbott and Roche, whereas the third system used, from Becton Dickinson (BD), detects nvCT. We analyzed 3648 samples from 2 counties that used Roche and 2 counties that used BD methods from 2007 to 2011. After implementation of a Roche method that detects nvCT, its proportion has decreased and converged in the 4 counties but are still at different levels in Roche and BD counties. Future studies are needed to see if nvCT will decline further. | G25: No | H25: No | I25: No | J25: They report a new variant but do not mention resistance
A26: 22824940 | B26: Biodegradable PLGA85/15 nanoparticles as a delivery vehicle for Chlamydia trachomatis recombinant MOMP-187 peptide | C26: 3) immunization | E26: Listo | F26: Development of a Chlamydia trachomatis vaccine has been a formidable task partly because of an ineffective delivery system. Our laboratory has generated a recombinant peptide of C. trachomatis major outer membrane protein (MOMP) (rMOMP-187) and demonstrated that it induced at 20 μg ml(-1) maximal interleukin (IL)-6 and IL-12p40 Th1 cytokines in mouse J774 macrophages. In a continuous pursuit of a C. trachomatis effective vaccine-delivery system, we encapsulated rMOMP-187 in poly(d,l-lactic-co-glycolic acid) (PLGA, 85:15 PLA/PGA ratio) to serve as a nanovaccine candidate. Physiochemical characterizations were assessed by Fourier transform-infrared spectroscopy, atomic force microscopy, Zetasizer, Zeta potential, transmission electron microcopy and differential scanning calorimetry. The encapsulated rMOMP-187 was small (∼200 nm) with an apparently smooth uniform oval structure, thermally stable (54 °C), negatively charged ( - 27.00 mV) and exhibited minimal toxicity at concentrations <250 μg ml (-1) to eukaryotic cells (>95% viable cells) over a 24-72 h period. We achieved a high encapsulation efficiency of rMOMP-187 (∼98%) in PLGA, a loading peptide capacity of 2.7% and a slow release of the encapsulated peptide. Stimulation of J774 macrophages with a concentration as low as 1 μg ml (-1) of encapsulated rMOMP-187 evoked high production levels of the Th1 cytokines IL-6 (874 pg ml(-1)) and IL-12p40 (674 pg ml(-1)) as well as nitric oxide (8 μM) at 24 h post-stimulation, and in a dose-response and time-kinetics manner. Our data indicate the successful encapsulation and characterization of rMOMP-187 in PLGA and, more importantly, that PLGA enhanced the capacity of the peptide to induce Th1 cytokines and NO in vitro. These findings make this nanovaccine an attractive candidate in pursuit of an efficacious vaccine against C. trachomatis. | G26: No | H26: No | I26: Yes | J26: Nanoparticles used to convey a peptide that awakens an immune response
A27: 22795612 | B27: Sperm-mediated host-derived DNA transfer as a new mechanism for immune system evasion of sexually transmitted genital tract pathogens | C27: 3) immunization | E27: Listo | F27: Over one century of extensive efforts directed towards investigating the immune response and the immuno-protection associated with sexually transmitted infections have failed to produce any effective vaccines against most of the major pathogens, among them Neisseria gonorrhea, herpes simplex virus type 2, and Chlamydia trachomatis. Attempts to design and develop protective vaccines against them have also yielded disappointing results. It has long been felt that there might be another yet undiscovered complicating factor, in addition to the recognized difficulties, which might be impeding the development of successful vaccines. Unlike the other body organs and systems, the genital tract and the elements found within it (e.g., spermatozoa) are endowed with unique features, some of which are associated with inherent DNA transferability skills as physiologically required from such an environment. We hypothesize that there is a novel evasion mechanism that involves an unusual sperm-mediated host-derived DNA transfer by which sexually transmitted genital tract microorganisms can express brand new chimeric antigens and epitopes and, by doing so, thus evade the surveillance of the immune system. This hypothesis may describe what would be the long-awaited breakthrough in the search for a vaccine against sexually transmitted infections. It may also assist in developing better-designed vaccines in general, and may have implications on other microorganism-related challenges (e.g., antibiotic resistance). | G27: No | H27: No | I27: No | J27: A potential escape mechanism of the immune response is described
A28: 22855710 | B28: CD4+ T cells are necessary and sufficient to confer protection against Chlamydia trachomatis infection in the murine upper genital tract | C28: 3) immunization | E28: Listo | F28: Chlamydia trachomatis infection is the most common bacterial sexually transmitted disease in the United States. Chlamydia infections that ascend to the upper genital tract can persist, trigger inflammation, and result in serious sequelae such as infertility. However, mouse models in which the vaginal vault is inoculated with C. trachomatis do not recapitulate the course of human disease. These intravaginal infections of the mouse do not ascend efficiently to the upper genital tract, do not cause persistent infection, do not induce significant inflammation, and do not induce significant CD4⁺ T cell infiltration. In this article, we describe a noninvasive transcervical infection model in which we bypass the cervix and directly inoculate C. trachomatis into the uterus. We show that direct C. trachomatis infection of the murine upper genital tract stimulates a robust Chlamydia-specific CD4⁺ T cell response that is both necessary and sufficient to clear infection and provide protection against reinfection. | G28: No | H28: No | I28: No | J28: They show how CD4+ T cells are necessary and sufficient to confer protection against C. trachomatis
A29: 26782047 | B29: Cyto-Insectotoxin 1a from Lachesana tarabaevi Spider Venom Inhibits Chlamydia trachomatis Infection | C29: 2) Nuevos tratamientos | D29: 2a) Productos naturales | E29: Listo | F29: Venom of the ant spider Lachesana tarabaevi contains a wide variety of antimicrobial peptides. Among them, a special place belongs to cyto-insectotoxins, a class of cytolytic molecules showing equally potent antimicrobial and insecticidal effects. We tested one of them, CIT 1a, for ability to suppress Chlamydia trachomatis infection. HEK293 cells were transfected with plasmid vectors harboring the cit 1a gene. Controlled expression of the transgene led to a significant decrease in C. trachomatis viability inside the infected cells. Using proteomic and transcriptomic approaches, we found alterations in protein expression patterns and identified differentially expressed genes in transfected cells. | G29: No | H29: Yes | I29: No | J29: They use the venom of a spider as a treatment for intracellular bacteria, in vitro
A30: 22846397 | B30: In vitro assessment of halobacterial gas vesicles as a Chlamydia vaccine display and delivery system | C30: 3) immunization | E30: Listo | F30: Chlamydia trachomatis is the leading cause of bacterial sexually transmitted disease worldwide and while antibiotic treatment is effective in eliminating the pathogen, up to 70% of all infections are asymptomatic. Despite sustained efforts over the past 2 decades, an effective chlamydial vaccine remains elusive, due in large part to the lack of an effective delivery system. We explored the use of gas vesicles derived from Halobacterium salinarium as a potential display and delivery vehicle for chlamydial antigens of vaccine interest. Various size gene fragments coding for the major outer membrane protein (MOMP), outer membrane complex B (OmcB) and polymorphic outer membrane protein D (PompD) were integrated into and expressed as part of the gas vesicle protein C (gvpC) on the surface of these stable structures. The presence of the recombinant proteins was confirmed by Western blots probed using anti-gvpC and anti-Chlamydia antibodies as well as sera from Chlamydia-positive patients. Tissue culture evaluation revealed stability and a time-dependent degradation of recombinant gas vesicles (r-Gv) in human and animal cell lines. In vitro assessment using human foreskin fibroblasts (HFF) confirmed Toll-like receptor (TLR) 4 and 5 engagement by wild type and r-Gv, leading to MyD88 activation, TNF-α, IL-6 and IL-12 production. The data suggest that r-GV could be an effective, naturally adjuvanting, time-release antigen delivery system for immunologically relevant Chlamydia vaccine antigens which are readily recognized by human immune sera. | G30: No | H30: No | I30: Yes | J30: Their innovation is to use of gas vesicles derived from Halobacterium salinarium as a potential display and delivery vehicle for chlamydial antigens of vaccine interest
A31: 22544308 | B31: Decline of the new Swedish variant of Chlamydia trachomatis after introduction of appropriate testing | C31: 1) Reporte de cepas resistentes | E31: Listo | F31: Objective: The longitudinal epidemiological development of the new variant of Chlamydia trachomatis was studied after appropriate testing procedures had been introduced when the strain was detected in 2006. Methods: The number of cases of the new variant of C trachomatis was followed from 2007 through 2011 from the laboratory records. Testing for C trachomatis is centralised to one laboratory with around 80-85 000 persons being tested annually in a population of 1.1 million. Results: During the 5-year period, 410 973 patients were tested of which 25 723 cases were positive. The proportion of the new variant of all positive cases declined from 30% in 2007 to 6% in 2011. While the number of the new variant of C trachomatis declined, the ordinary wild-type strains remained largely unchanged. Conclusions: A selective decline of the new variant of C trachomatis has occurred after appropriate laboratory testing was introduced. A new balance point between 5% and 10% for the new variant seems to be gradually approached. | G31: No | H31: No | I31: No | J31: They improved the testing method, and they found a variant of C. trachomatis, but sensistive to treatments
A32: 23015646 | B32: Fluorometric high-throughput assay for measuring chlamydial neutralizing antibody | C32: 3) immunization | E32: Listo | F32: This report describes an objective, high-throughput in vitro assay that measures C. trachomatis-neutralizing antibodies. | G32: No | H32: No | I32: Yes | J32: This report describes an objective, high-throughput in vitro assay that measures C. trachomatis-neutralizing antibodies. Even when is not a vaccine itself, is a method to measure antibodies related to the potential vaccines
A33: 23198910 | B33: Chlamydia trachomatis genovar distribution in clinical urogenital specimens from Tunisian patients: high prevalence of C. trachomatis genovar E and mixed infections | C33: 1) Reporte de cepas resistentes | E33: Listo | F33: Background: This epidemiological study was carried out in Sfax (south of Tunisia) and focused on genital Chlamydia trachomatis (C. trachomatis) genovar distribution. Methods: One hundred and thirty seven genital samples from 4067 patients (4.2%) attending the Habib Bourguiba University hospital of Sfax over 12 years (from 2000 to 2011) were found to be C. trachomatis PCR positive by the Cobas Amplicor system. These samples were genotyped by an in house reverse hybridization method. Results: One hundred and eight (78.8%) samples contained only one genovar and 29 (21.2%) samples contained two or three genovars. Genovar E was the most prevalent (70.8%) single genovar and it was detected in 90.6% of all the cases. Genovars J, C and L1-L3 were not detected in our samples whereas ocular genovars A and B were in 5 cases. All the five cases were mixed infections. Men had more mixed infections than women (p=0.02) and were more frequently infected by genovars F and K (p<0.05). No associations between current infection, infertility and the genovar distribution were observed. Patients coinfected with Neisseria gonorrhoeae were also significantly more frequently infected with mixed genovars (p=0.04). Conclusions: In conclusion, we have reported a high prevalence of genovar E and of mixed infections in our study population. Such data could have implications for the control and vaccine development of C. trachomatis in Tunisia. | G33: No | H33: No | I33: No | J33: This report found different genovar distribution, but not related to antibiotic resistance
A34: 22934581 | B34: Transient detection of Chlamydial-specific Th1 memory cells in the peripheral circulation of women with history of Chlamydia trachomatis genital tract infection | C34: 3) immunization | E34: Listo | F34: Problem: Development of safe and effective Chlamydia trachomatis vaccines requires better understanding of the host immune responses elicited by natural infection. Method of study: Peripheral blood mononuclear cells isolated from women with or without history of genital tract chlamydial infection were stimulated with inactivated C. trachomatis elementary bodies (EB) in ELISPOT assays that enumerated frequencies of cells producing interferon (IFN)-γ or interleukin (IL)-17. Results: IFN-γ-positive cells were highest among women sampled 30-60 days after diagnosis of C. trachomatis infection and treatment initiation, while the numbers of IFN-γ-positive cells were equally low among uninfected women and women sampled <30 or >60 days after diagnosis of infection. Conversely, IL-17-positive cell numbers were uniformly low among all participants. Conclusion: Dramatically reduced numbers of Chlamydia-specific Th1 memory cells in the peripheral circulation of study participants sampled more than 2 months after diagnosis, and initiation of treatment provides new insight into the results from C. trachomatis vaccine trials, in which immunization with EB provided only short-lived protection. Our results also suggest that an effective vaccine against this weakly antigenic intracellular pathogen will need to generate immunological memory more durable than that elicited by natural infection. | G34: No | H34: No | I34: Yes | J34: In order to develop a vaccine, they tested the host immune responses elicited by natural infection. They found immunological memory is too short.
A35: 22988022 | B35: Reversible inhibition of Chlamydia trachomatis infection in epithelial cells due to stimulation of P2X(4) receptors | C35: 3) immunization | E35: Listo | F35: Bacterial infections of the mucosal epithelium are a major cause of human disease. The prolonged presence of microbial pathogens stimulates inflammation of the local tissues, which leads to changes in the molecular composition of the extracellular milieu. A well-characterized molecule that is released to the extracellular milieu by stressed or infected cells is extracellular ATP and its ecto-enzymatic degradation products, which function as signaling molecules through ligation of purinergic receptors. There has been little information, however, on the effects of the extracellular metabolites on bacterial growth in inflamed tissues. Millimolar concentrations of ATP have been previously shown to inhibit irreversibly bacterial infection through ligation of P2X(7) receptors. We show here that the proinflammatory mediator, ATP, is released from Chlamydia trachomatis-infected epithelial cells. Moreover, further stimulation of the infected cells with micromolar extracellular ADP or ATP significantly impairs the growth of the bacteria, with a profile characteristic of the involvement of P2X(4) receptors. A specific role for P2X(4) was confirmed using cells overexpressing P2X(4). The chlamydiae remain viable and return to normal growth kinetics after removal of the extracellular stimulus, similar to responses previously described for persistence of chlamydial infection. | G35: No | H35: No | I35: No | J35: stimulation of the infected cells with micromolar extracellular ADP or ATP significantly impairs the growth of the bacteria, with a profile characteristic of the involvement of P2X(4) receptors. They found a reversible inhibithion of C. trachomatis
A36: 23488303 | B36: [Statement of the Polish Gynecological Society Expert Group on the use of Macmiror Complex 500] | C36: 2) Nuevos tratamientos | D36: 2c) Droga de diseño | E36: Listo | F36: The group of experts representing the Polish Gynecologic Society has issued this statement based on the review of available literature on the potential benefits of the use of Macmiror Complex 500 in obstetrical and gynecologic practice. Mixed Vaginitis (MV) eg. the vaginal infection caused by at least two out of the triad of pathogens (fungi, bacteria and Trichomonas Vaginalis [TV]), constitutes the type of vaginitis which is underestimated as for its prevalence. Mixed pathogens are responsible for as much as one third of all vaginal infections. Macmiror Complex 500 contains two active ingredients: nifuratel and nystatin. Macmiror Complex 500 affects all common causes of vulvovaginitis, i.e. bacteria, yeasts and TV. At the same time, it is not effective against Lactobacillus spp., which is a clear advantage in the treatment of vaginal infections. The antibacterial spectrum of nifuratel includes aerobic and anaerobic bacteria. Moreover nifuratel is effective against Chlamydia trachomatis and Mycoplasma spp., it has an anti-trichomonal effect comparable to metranidazole and shows certain activity against Candida spp. Nystatin is effective against Candida albicans and is even very effective against Candida glabrata which is usually more resistant to imidazole antifungal agents. Nystatin's importance is rising due to the current increase of candidoses caused by non-albicans types. This increase is especially perceptible in recurring candidoses. The review of the available literature on the effectiveness of Macmiror Complex 500 in the OB/GYN practice leads to the following conclusions: the exeptionally broad antibacterial and antifungal and trichomonicidal activity of this formulation makes it a drug of choice in cases where MV is suspected. The possibility to treat both partners, favorable safety profile in pregnant patients and the availability of both vaginal ovules and the cream with applicator makes this drug an effective and suitable treatment option in obstetrical and gynecologic practice. | G36: No | H36: Yes | I36: No | J36: They used Macmiror Complex 500, that contains two active ingredients: nifuratel and nystatin, as a broad spectrum treatment for Mixed Vaginitis (MV). Nifuratel is effective against C. trachomatis
A37: 23593733 | B37: [Efficacy and safety of sitafloxacin in patients with urinary tract infections] | C37: 2) Nuevos tratamientos | D37: 2c) Droga de diseño | E37: Listo | F37: Sitafloxacin (STFX, Gracevit 50mg, fine granules 10%), a new quinolone antibacterial agent, was approved in January 2008, and the use-results survey was carried out over the 2 years between December 2008 and November 2010. We studied the efficacy and safety of STFX in 1,452 patients with urinary tract infections (cystitis, pyelonephritis, urethritis). The total efficacy rate for urinary tract infections was 91.4% (1,235/1,351 patients). Efficacy rates, classified by the type of infection, were: uncomplicated cystitis 95.9% (466/486 patients), complicated cystitis 87.2% (511/586 patients), uncomplicated pyelonephritis 96.1% (49/51 patients), complicated pyelonephritis 93.5% (145/155 patients), and urethritis 87.7% (64/73 patients). Efficacy rates were 86.0% (49/57 patients) for non-responders to cephems and 77.4% (48/62 patients) for non-responders to quinolones. The eradication rate of indicated strains was 90.5% (545/602 strains). The eradication rates of major causative bacteria were; Escherichia coli 92.7% (294/317 isolates), Enterococcus faecalis 86.0% (43/50 isolates), Pseudomonas aeruginosa 66.7% (16/24 isolates), Klebsiella pneumoniae 95.2% (20/21 isolates), and Chlamydia trachomatis 88.9% (8/9 isolates). The incidence of adverse drug reactions (ADRs) was 2.71% (37/1,365 cases). Major ADRs were diarrhoea (0.88%, 12 cases) and hepatic function disorders (0.51%, 7 cases). A serious ADR (hepatic function abnormality) was observed in 1 case, and the hepatic function in this patient returned to normal after treatment with STFX was discontinued. In conclusion, these results suggest that STFX is a useful antibacterial agent with an efficacy rate of 91.4% against urinary tract infections, with a minimum efficacy rate of 87.2% (against complicated cystitis), and has no serious problems in its safety profile. | G37: No | H37: Yes | I37: No | J37: Use of a new quinolone of broad spectrum, effective against C. trachomatis
A38: 23593735 | B38: [Efficacy and safety of levofloxacin to non-gonorrheal urethritis] | C38: 2) Nuevos tratamientos | D38: 2c) Droga de diseño | E38: Listo | F38: We investigated the efficacy and safety of levofloxacin (LVFX) 500mg once a day in patients with non-gonorrheal urethritis. Men, aged 20 years or older, with urethritis symptoms, and detection of Chlamydia trachomatis (C. trachomatis) or Mycoplasma genitalium (M. genitalium) by a microbiological examination were eligible for this study. Patients were administered LVFX 500mg, orally, once a day and the dosage period was seven days. We assumed 22 patients for a safety and efficacy analysis. In 22 patients, 17 patients had urethritis with C. trachomatis, 4 patients urethritis with M. genitalium, and one patient mixed infection of C. trachomatis and M. genitalium. In the clinial study, the primary endpoint was set as the bacteriological eradication rate at two to four weeks after completion of treatment. The bacterial eradication rate in the urethritis was 86.4% (19/22). The bacterial eradication rate in the urethritis with C. trachomatis, M. genitalium, and mixed infection of C. trachomatis and M. genitalium were 94.1% (16/17), 50.0% (2/4), 100% (1/1), respectively. A significant difference was not recognized among the three groups. The clinical efficacy at two to four weeks after completion of treatment was 90.9% (20/22). The clinical efficacy rates in the urethritis with C. trachomatis, M. genitalium, and mixed infection of C. trachomatis and M. genitalium were 100% (17/17), 50.0% (2/4), 100% (1/1), respectively. The efficacy rate of urethritis with M. genitalium was significantly low. No adverse drug reactions were observed. These results suggest that once-a-day levofloxacin (500mg) is effective and safe treatment for non-gonorrheal urethritis. | G38: No | H38: Yes | I38: No | J38: They found levofloxacin (a fluoroquinolone) efective to treat he urethritis with C. trachomatis, M. genitalium, and mixed infection of C. trachomatis and M. genitalium
A39: 23045619 | B39: Immunoglobulin-specific responses to Chlamydia elementary bodies in individuals with and at risk for genital chlamydial infection | C39: 3) immunization | E39: Listo | F39: Renewed interest in chlamydia vaccination has revealed the need for a greater understanding of the seroprevalence of chlamydial infection in US populations. We used a Chlamydia trachomatis elementary body (EB)-based enzyme-linked immunosorbent assay to define the characteristics of the humoral immune response and to determine seroprevalence. Two groups were analyzed: one consisting of patients with current, laboratory confirmed, genital chlamydial infection (n = 98) and one group of individuals whose chlamydia infection history was unknown (n = 367). C. trachomatis seropositivity was detected in 90% of the infected group and in 31% of the chlamydia-unknown group. IgG1 and IgG3 comprised the predominant anti-Chlamydia serum antibody responses. Serum IgA1 responses were variably positive, and individuals were rarely positive for anti-chlamydia IgG2, IgG4 or IgA2. The magnitude of the IgG1 and IgG3 responses was greatest in female and African American individuals and was sustained for at least 6 months. Antibody responses were not serovar restricted or confounded by Chlamydia pneumoniae cross-reactivity. | G39: No | H39: No | I39: No | J39: Measurement of the magnitude of the IgG1 and IgG3 responses in patients infected with C. trachomatis
A40: 22959960 | B40: Proteomic identification of immunodominant chlamydial antigens in a mouse model | C40: 3) immunization | E40: Listo | F40: Chlamydia trachomatis is the most common bacterial sexually transmitted pathogen in the world. To identify new vaccine candidates a protein microarray was constructed by expressing the open reading frames (ORFs) from Chlamydia mouse pneumonitis (MoPn). C57BL/6, C3H/HeN and BALB/c mice were immunized either intranasally or intravaginally with live MoPn elementary bodies (EB). Two additional groups were immunized by the intramuscular plus subcutaneous routes with UV-treated EB, using CpG and Montanide as adjuvants to favor a Th1 response, or Alum, to elicit a Th2 response. Serum samples collected from the three strains of mice were tested in the microarray. The array included the expression of 909 proteins from the 921 ORFs of the MoPn genome and plasmid. A total of 530 ORFs were recognized by at least one serum sample. Of these, 36 reacted with sera from the three strains of mice immunized with live EB. These antigens included proteins that were previously described as immunogenic such as MOMP and HSP60. In addition, we uncovered new immunogens, including 11 hypothetical proteins. In summary, we have identified new immunodominant chlamydial proteins that can be tested for their ability to induce protection in animal models and subsequently in humans. | G40: No | H40: No | I40: Yes | J40: Immunization with several ORF. Identification of antigens included proteins that were previously described as immunogenic such as MOMP and HSP60. Also, they found new immunogens, including 11 hypothetical proteins
A41: 23429090 | B41: Difference in distribution of Chlamydia trachomatis genotypes among different provinces: a pilot study from four provinces in China | C41: 1) Reporte de cepas resistentes | E41: Listo | F41: The objective of this study was to assess the distribution of Chlamydia trachomatis genovars in male sexually transmitted disease (STD) clinic patients from 1 province in eastern China (Jiangsu) and 3 provinces in southern China (Guangdong, Guangxi, and Hainan). Urine specimens (n = 140) were collected from 46 public STD clinics in the 4 provinces. Specimens that tested positive for C. trachomatis by polymerase chain reaction were genotyped for the infecting C. trachomatis strain by amplifying and sequencing the genovar-specific ompA gene, which encodes the chlamydial major outer-membrane protein. Nine C. trachomatis genovars were identified from 129 specimens; they consisted of the F (25.6%), E (17.1%), J (16.3%), D (15.5%), G (11.6%), K (5.4%), H (3.9%), I (1.6%), and B (0.8%) genovars. Nine genovars were found in specimens from Guangxi province, 6 were found in specimens from each of Guangdong and Hainan provinces, but only 5 were found in specimens from Jiangsu province. Genovar G/Ga was shown to be endemic among male patients in southern China. | G41: No | H41: No | I41: No | J41: Identification of genovar in a population, without report of antibiotic resistance
A42: 23690681 | B42: Formulation, characterization, and expression of a recombinant MOMP Chlamydia trachomatis DNA vaccine encapsulated in chitosan nanoparticles | C42: 3) immunization | E42: Listo | F42: Chlamydia trachomatis is a bacterial sexually transmitted infection affecting millions of people worldwide. Previous vaccination attempts have employed the recombinant major outer membrane protein (MOMP) of C. trachomatis nonetheless, with limited success, perhaps, due to stability, degradation, and delivery issues. In this study we cloned C. trachomatis recombinant MOMP DNA (DMOMP) and encapsulated it in chitosan nanoparticles (DMCNP) using the complex coacervation technique. Physiochemical characterizations of DMCNP included transmission and scanning electron microcopy, Fourier transform infrared and ultraviolet-visible spectroscopy, and zeta potential. Encapsulated DMOMP was 167-250 nm, with a uniform spherical shape and homogenous morphology, and an encapsulation efficiency > 90%. A slow release pattern of encapsulated DMOMP, especially in acidic solution, was observed over 7 days. The zeta potential of DMCNP was ~8.80 mV, which indicated that it was highly stable. Toxicity studies of DMCNP (25-400 μg/mL) to Cos-7 cells using the MTT assay revealed minimal toxicity over 24-72 hours with >90% viable cells. Ultra-violet visible (UV-vis) spectra indicated encapsulated DMOMP protection by chitosan, whereas agarose gel electrophoresis verified its protection from enzymatic degradation. Expression of MOMP protein in DMCNP-transfected Cos-7 cells was demonstrated via Western blotting and immunofluorescence microscopy. Significantly, intramuscular injection of BALB/c mice with DMCNP confirmed the delivery of encapsulated DMOMP, and expression of the MOMP gene transcript in thigh muscles and spleens. Our data show that encapsulation of DMOMP in biodegradable chitosan nanoparticles imparts stability and protection from enzymatic digestion, and enhances delivery and expression of DMOMP in vitro and in mice. Further investigations of the nanoencapsulated DMCNP vaccine formulation against C. trachomatis in mice are warranted. | G42: No | H42: No | I42: Yes | J42: Assay of a new type of encapsulation oa a know protein. The encapsulation of DMOMP in biodegradable chitosan nanoparticles imparts stability and protection from enzymatic digestion, and enhances delivery and expression of DMOMP in vitro and in mice
A43: 23785233 | B43: Chlamydia trachomatis recombinant MOMP encapsulated in PLGA nanoparticles triggers primarily T helper 1 cellular and antibody immune responses in mice: a desirable candidate nanovaccine | C43: 3) immunization | E43: Listo | F43: We recently demonstrated by in vitro experiments that PLGA (poly D, L-lactide-co-glycolide) potentiates T helper 1 (Th1) immune responses induced by a peptide derived from the recombinant major outer membrane protein (rMOMP) of Chlamydia trachomatis, and may be a promising vaccine delivery system. Herein we evaluated the immune-potentiating potential of PLGA by encapsulating the full-length rMOMP (PLGA-rMOMP), characterizing it in vitro, and investigating its immunogenicity in vivo. Our hypothesis was that PLGA-rMOMP triggers Th1 immune responses in mice, which are desirable prerequisites for a C. trachomatis candidate nanovaccine. Physical-structural characterizations of PLGA-rMOMP revealed its size (approximately 272 nm), zeta potential (-14.30 mV), apparent spherical smooth morphology, and continuous slow release pattern. PLGA potentiated the ability of encapsulated rMOMP to trigger production of cytokines and chemokines by mouse J774 macrophages. Flow cytometric analyses revealed that spleen cells from BALB/c mice immunized with PLGA-rMOMP had elevated numbers of CD4+ and CD8+ T cell subsets, and secreted more rMOMP-specific interferon-gamma (Th1) and interleukin (IL)-12p40 (Th1/Th17) than IL-4 and IL-10 (Th2) cytokines. PLGA-rMOMP-immunized mice produced higher serum immunoglobulin (Ig)G and IgG2a (Th1) than IgG1 (Th2) rMOMP-specific antibodies. Notably, sera from PLGA-rMOMP-immunized mice had a 64-fold higher Th1 than Th2 antibody titer, whereas mice immunized with rMOMP in Freund's adjuvant had only a four-fold higher Th1 than Th2 antibody titer, suggesting primarily induction of a Th1 antibody response in PLGA-rMOMP-immunized mice. Our data underscore PLGA as an effective delivery system for a C. trachomatis vaccine. The capacity of PLGA-rMOMP to trigger primarily Th1 immune responses in mice promotes it as a highly desirable candidate nanovaccine against C. trachomatis | G43: No | H43: No | I43: Yes | J43: Assay of a new type of encapsulation for a known protein. PLGA (poly D, L-lactide-co-glycolide)-MOMP trigger primarily Th1 immune responses in mice
A44: 23882139 | B44: Anti-inflammatory effects of silver-polyvinyl pyrrolidone (Ag-PVP) nanoparticles in mouse macrophages infected with live Chlamydia trachomatis | C44: 2) Nuevos tratamientos | D44: 2c) Droga de diseño | E44: Listo | F44: Chlamydia trachomatis is a very common sexually transmissible infection in both developing and developed countries. A hallmark of C. trachomatis infection is the induction of severe inflammatory responses which play critical roles in its pathogenesis. Antibiotics are the only treatment option currently available for controlling C. trachomatis infection; however, they are efficacious only when administered early after an infection. The objectives of this study are to explore alternative strategies in the control and regulation of inflammatory responses triggered by a C. trachomatis infection. We employed silver-polyvinyl pyrrolidone (Ag-PVP) nanoparticles, which have been shown to possess anti-inflammatory properties, as our target and the in vitro mouse J774 macrophage model of C. trachomatis infection. Our hypothesis is that small sizes of Ag-PVP nanoparticles will control inflammatory mediators triggered by a C. trachomatis infection. Cytotoxicity studies using Ag-PVP nanoparticles of 10, 20, and 80 nm sizes revealed >80% macrophage viability up to a concentration of 6.25 μg/mL, with the 10 nm size being the least toxic. All sizes of Ag-PVP nanoparticles, especially the 10 nm size, reduced the levels of the prototypic cytokines, tumor necrosis factor (TNF) and interleukin (IL)-6, as elicited from C. trachomatis infected macrophages. Additionally, Ag-PVP nanoparticles (10 nm) selectively inhibited a broad spectrum of other cytokines and chemokines produced by infected macrophages. Of significance, Ag-PVP nanoparticles (10 nm) caused perturbations in a variety of upstream (toll like receptor 2 [TLR2], nucleotide-binding oligomerization-protein 2 [NOD2], cluster of differentiation [CD]40, CD80, and CD86) and downstream (IL-1 receptor-associated kinase 3 [IRAK3] and matrix metallopeptidase 9 [MMP9]) inflammatory signaling pathways by downregulating their messenger ribonucleic acid (mRNA) gene transcript expressions as induced by C. trachomatis in macrophages. Collectively, our data provides further evidence for the anti-inflammatory properties of Ag-PVP nanoparticles, and opens new possibilities for smaller sizes of Ag-PVP nanoparticles to be employed as regulators of inflammatory responses induced by C. trachomatis. | G44: No | H44: Yes | I44: Yes | J44: Use of silver-polyvinyl pyrrolidone (Ag-PVP) nanoparticles that show anti-inflammatory properties
A45: 23888605 | B45: Chlamydia trachomatis: TLR4-mediated recognition by human dendritic cells is impaired following oestradiol treatment | C45: 3) immunization | E45: Listo | F45: Genital Chlamydia trachomatis infection creates a substantial reproductive health burden in women. The high incidence of asymptomatic infection often precludes timely antibiotic therapy to control the sequelae of infection, and therefore a vaccine is required. Dendritic cells (DC) are now being used as an adjuvant for vaccine development; however, the fate of C. trachomatis in human DC and differential regulation of cytokine secretion remains unclear. Hence, an in vitro study was performed using C. trachomatis (serovar D) elementary body (EB)-pulsed, monocytederived DCs co-cultured with autologous CD4+ T cells. Secreted cytokines were measured to assess the protective/pathogenic immune response. The effect of (beta-oestradiol in the modulation of DC function and on Toll-like receptor (TLR) gene expression was also studied. Elementary body-pulsed DCs showed induction of protective Th1 immune response with upregulation of TLR4 expression, secretion of interleukin (IL)-6, IL-12 and interferon (IFN)-y, together with upregulation of major histocompatibility complex (MHC) class II, CD83 and CD86. When co-cultured with autologous CD4+T cells, DCs presented chlamydial antigens efficiently, as shown by proliferation of T cells and secretion of IL-2 and IFN gamma, which provide a protective immune response. However; pretreatment of cells with oestradiol significantly reduced TLR4 expression and upregulated IL-10 secretion, modulating the Th1 immune response to a Th2-type response, which may lead to pathogenesis. | G45: No | H45: Yes | I45: Yes | J45: They used an human female hormone, that shown proliferation of T cells and secretion of IL-2 and IFN gamma, which provide a protective immune response
A46: 22855433 | B46: Chlamydia trachomatis prevalence, genotype distribution and identification of the new Swedish variant in Southern Germany | C46: 1) Reporte de cepas resistentes | E46: Listo | F46: Purpose: In Germany, reliable data about the prevalence of urogenital Chlamydia trachomatis infections, causative genotypes, as well as corresponding clinical, demographic and behavioural information are sparse. We, therefore, performed a prospective prevalence study including 1,003 sexually active volunteers of a Southern German city. Methods: Study participants completed a standardised questionnaire and provided first void urine samples for analysis. Our screening strategy included the performance of two nucleic acid amplification tests with different target genes, enabling the detection of the new Swedish variant of C. trachomatis (nvCT). Direct genotyping of positive specimens was performed by sequence analysis of the ompA gene. Results and conclusion: The overall prevalence of C. trachomatis infection was 4.2 % in women and 4.6 % in men. A relatively high prevalence of 8.3 % was found in men older than 25 years. Never using condoms was an independent risk factor for infection. The most common symptom was discharge; however, 64.5 % of infected females and all of the infected men were asymptomatic, supporting the need for screening programmes. The most frequently encountered genotypes were E (46.5 %), F (20.9 %) and K (14.0 %). Since the nvCT was detected in one female student, this is one of the rare studies that reports on the molecular identification of nvCT apart from Sweden. | G46: No | H46: No | I46: No | J46: They studied the prevalence of several strains of C. trachomatis, there is not report of resistance
A47: 23277388 | B47: Antimicrobial peptide from spider venom inhibits Chlamydia trachomatis infection at an early stage | C47: 2) Nuevos tratamientos | D47: 2b) Péptidos | E47: Listo | F47: Antichlamydial activity of cyto-insectotoxin 1a (CIT 1a), representative of a unique class of antimicrobial peptides from the venom of the Central Asian spider Lachesana tarabaevi, was studied. A plasmid vector expressing the cit 1a gene controlled by a human cytomegalovirus tetracycline-dependent promoter was constructed. Impressive inhibition of Chlamydia trachomatis infection in HEK 293 cells transfected by the cit 1a-harboring vector was achieved. With the use of various schemes of cell infection and gene expression induction, it was shown for the first time that an antimicrobial peptide exerts its potent antichlamydial action at an early stage of the pathogen life cycle. | G47: No | H47: Yes | I47: No | J47: A peptide from a spider venom was used to treat C. trachomatis in vitro
A48: 23532978 | B48: Comparative analysis of Chlamydia psittaci genomes reveals the recent emergence of a pathogenic lineage with a broad host range | C48: 1) Reporte de cepas resistentes | E48: Listo | F48: Chlamydia psittaci is an obligate intracellular bacterium. Interest in Chlamydia stems from its high degree of virulence as an intestinal and pulmonary pathogen across a broad range of animals, including humans. C. psittaci human pulmonary infections, referred to as psittacosis, can be life-threatening, which is why the organism was developed as a bioweapon in the 20th century and is listed as a CDC biothreat agent. One remarkable recent result from comparative genomics is the finding of frequent homologous recombination across the genome of the sexually transmitted and trachoma pathogen Chlamydia trachomatis. We sought to determine if similar evolutionary dynamics occurred in C. psittaci. We analyzed 20 C. psittaci genomes from diverse strains representing the nine known serotypes of the organism as well as infections in a range of birds and mammals, including humans. Genome annotation revealed a core genome in all strains of 911 genes. Our analyses showed that C. psittaci has a history of frequently switching hosts and undergoing recombination more often than C. trachomatis. Evolutionary history reconstructions showed genome-wide homologous recombination and evidence of whole-plasmid exchange. Tracking the origins of recombinant segments revealed that some strains have imported DNA from as-yet-unsampled or -unsequenced C. psittaci lineages or other Chlamydiaceae species. Three ancestral populations of C. psittaci were predicted, explaining the current population structure. Molecular clock analysis found that certain strains are part of a clonal epidemic expansion likely introduced into North America by South American bird traders, suggesting that psittacosis is a recently emerged disease originating in New World parrots. | G48: No | H48: No | I48: No | J48: Research of populations of C. pisttaci, no report of resistance
A49: 23303804 | B49: Prevention of Chlamydia-induced infertility by inhibition of local caspase activity | C49: 2) Nuevos tratamientos | E49: Listo | F49: Tubal factor infertility (TFI) represents 36% of female infertility and genital infection by Chlamydia trachomatis (C. trachomatis) is a major cause. Although TFI is associated with host inflammatory responses to bacterial components, the molecular pathogenesis of Chlamydia-induced infertility remains poorly understood. We investigated the hypothesis that activation of specific cysteine proteases, the caspases, during C. trachomatis genital infection causes the disruption of key fertility-promoting molecules required for embryo development and implantation. We analyzed the effect of caspase inhibition on infertility and the integrity of Dicer, a caspase-sensitive, fertility-promoting ribonuclease III enzyme, and key micro-RNAs in the reproductive system. Genital infection with the inflammation- and caspase-inducing, wild-type C. trachomatis serovar L2 led to infertility, but the noninflammation-inducing, plasmid-free strain did not. We confirmed that caspase-mediated apoptotic tissue destruction may contribute to chlamydial pathogenesis. Caspase-1 or -3 deficiency, or local administration of the pan caspase inhibitor, Z-VAD-FMK into normal mice protected against Chlamydia-induced infertility. Finally, the oviducts of infected infertile mice showed evidence of caspase-mediated cleavage inactivation of Dicer and alteration in critical miRNAs that regulate growth, differentiation, and development, including mir-21. These results provide new insight into the molecular pathogenesis of TFI with significant implications for new strategies for treatment and prevention of chlamydial complications. | G49: No | H49: No | I49: No | J49: Study of the mechanism of Tubal factor infertility (TFI) produced by C. trachomatis and the relationship with the activation of specific cysteine proteases,
A50: 23378575 | B50: Chlamydia trachomatis clinical isolates identified as tetracycline resistant do not exhibit resistance in vitro: whole-genome sequencing reveals a mutation in porB but no evidence for tetracycline resistance genes | C50: 1) Reporte de cepas resistentes | E50: Listo | F50: Chlamydia trachomatis is the most common bacterial sexually transmitted infection worldwide and the leading cause of preventable blindness in developing countries. Tetracycline is commonly the drug of choice for treating C. trachomatis infections, but cases of antibiotic resistance in clinical isolates have previously been reported. Here, we used antibiotic resistance assays and whole-genome sequencing to interrogate the hypothesis that two clinical isolates (IU824 and IU888) have acquired mechanisms of antibiotic resistance. Immunofluorescence staining was used to identify C. trachomatis inclusions in cell cultures grown in the presence of tetracycline; however, only antibiotic-free control cultures yielded the strong fluorescence associated with the presence of chlamydial inclusions. Infectivity was lost upon passage of harvested cultures grown in the presence of tetracycline into antibiotic-free medium, so we conclude that these isolates were phenotypically sensitive to tetracycline. Comparisons of the genome and plasmid sequences for the two isolates with tetracycline-sensitive strains did not identify regions of low sequence identity that could accommodate horizontally acquired resistance genes, and the tetracycline binding region of the 16S rRNA gene was identical to that of the sensitive control strains. The porB gene of strain IU824, however, was found to contain a premature stop codon not previously identified, which is noteworthy but unlikely to be related to tetracycline resistance. In conclusion, we found no evidence of tetracycline resistance in the two strains investigated, and it seems most likely that the small, aberrant inclusions previously identified resulted from the high chlamydial load used in the original antibiotic resistance assays. | G50: Yes | H50: No | I50: No | J50: Two clinical isolate were identified as tetracycline resistant, but they did not found evidence in vitro of this resistance
A51: 23416214 | B51: Induction of protective immunity against Chlamydia muridarum intravaginal infection with the chlamydial immunodominant antigen macrophage infectivity potentiator | C51: 3) immunization | E51: Listo | F51: We previously reported that 5 Chlamydia muridarum antigens reacted with antisera from >90% mice urogenitally infected with C. muridarum and they are TC0660 (ABC transporter or ArtJ), TC0727 (outer membrane complex protein B or OmcB), TC0828 (macrophage infectivity potentiator or MIP), TC0726 (inclusion membrane protein or Inc) & TC0268 (hypothetical protein or HP). The orthologs of these antigens in Chlamydia trachomatis were also highly reactive with antisera from women urogenitally infected with C. trachomatis. In the current study, we evaluated these C. muridarum antigens for their ability to induce protection against a C. muridarum intravaginal challenge infection in mice. We found that only MIP induced the most pronounced protection against C. muridarum infection. The protection correlated well with robust C. muridarum MIP-specific antibody and Th1-dominant T cell responses. The MIP-immunized mice displayed significantly reduced live organism shedding from the lower genital tract and highly attenuated inflammatory pathologies in the upper genital tissues. These results demonstrate that MIP, an immunodominant antigen identified by both human and mouse antisera, may be considered a component of a multi-subunit chlamydial vaccine for inducing protective immunity. | G51: No | H51: No | I51: Yes | J51: Assay of 5 different antigens in mice to elicit immune reponse. These results demonstrate that MIP, an immunodominant antigen identified by both human and mouse antisera, may be considered a component of a multi-subunit chlamydial vaccine for inducing protective immunity.
A52: 23414449 | B52: Characterization of in vitro Chlamydia muridarum persistence and utilization in an in vivo mouse model of Chlamydia vaccine | C52: 3) immunization | E52: Listo | F52: Problem: Chlamydia trachomatis genital tract infections are easily treated with antibiotics; however, the majority of infections are asymptomatic and therefore untreated, highlighting the need for a vaccine. Because most infections are asymptomatic, vaccination could potentially be administered to individuals who may have an acute infection at that time. In such individuals, the effect of vaccination on the existing infection is unknown; however, one potential outcome could be the development of a persistent infection. In vitro chlamydial persistence has been well characterized in various strains; however, there have been no reported studies in C. muridarum. Method of study: We performed ultrastructural characterization and transcriptome analysis of selected genes. We then used the transcriptional profiles of the selected genes to examine whether intranasal immunization of mice during an active genital infection would induce persistence in the upper reproductive tract of female mice. Results and conclusions: We found that persistence developed in the oviducts of mice as a result of immunization. This is a significant finding, not only because it is the first time that C. muridarum persistence has been characterized in vitro, but also due to the fact that there is a minimal characterization of in vivo persistence of any chlamydial species. This highlights the importance of the timing of vaccination in individuals. | G52: No | H52: No | I52: Yes | J52: C. muridarum persistence has been characterized in vitro by using ultrastructural characterization and transcriptome analysis of selected genes
A53: 24009891 | B53: Recombinant outer membrane vesicles carrying Chlamydia muridarum HtrA induce antibodies that neutralize chlamydial infection in vitro | C53: 3) immunization | E53: Listo | F53: Background: Outer membrane vesicles (OMVs) are spheroid particles released by all Gram-negative bacteria as a result of the budding out of the outer membrane. Since they carry many of the bacterial surface-associated proteins and feature a potent built-in adjuvanticity, OMVs are being utilized as vaccines, some of which commercially available. Recently, methods for manipulating the protein content of OMVs have been proposed, thus making OMVs a promising platform for recombinant, multivalent vaccines development. Methods: Chlamydia muridarum DO serine protease HtrA, an antigen which stimulates strong humoral and cellular responses in mice and humans, was expressed in Escherichia coli fused to the OmpA leader sequence to deliver it to the OMV compartment. Purified OMVs carrying HtrA (CM rHtrA-OMV) were analyzed for their capacity to induce antibodies capable of neutralizing Chlamydia infection of LLC-MK2 cells in vitro. Results: CM rHtrA-OMV immunization in mice induced antibodies that neutralize Chlamydial invasion as judged by an in vitro infectivity assay. This was remarkably different from what observed with an enzymatically functional recombinant HtrA expressed in, and purified from the E. coli cytoplasm (CM rHtrA). The difference in functionality between anti-CM rHtrA and anti-CM rHtrA-OMV antibodies was associated to a different pattern of protein epitopes recognition. The epitope recognition profile of anti-CM HtrA-OMV antibodies was similar to that induced in mice during Chlamydial infection. Conclusions: When expressed in OMVs HtrA appears to assume a conformation similar to the native one and this results in the elicitation of functional immune responses. These data further support the potentiality of OMVs as vaccine platform. | G53: No | H53: No | I53: Yes | J53: Use of Outer membrane vesicles to prove they induced antibodies that neutralize Chlamydial invasion as judged by an in vitro infectivity assay in mice
A54: 23738030 | B54: Antibody signature of spontaneous clearance of Chlamydia trachomatis ocular infection and partial resistance against re-challenge in a nonhuman primate trachoma model | C54: 3) immunization | E54: Listo | F54: Background: Chlamydia trachomatis is the etiological agent of trachoma the world's leading cause of infectious blindness. Here, we investigate whether protracted clearance of a primary infection in nonhuman primates is attributable to antigenic variation or related to the maturation of the anti-chlamydial humoral immune response specific to chlamydial antigens. Methodology/principal findings: Genomic sequencing of organisms isolated throughout the protracted primary infection revealed that antigenic variation was not related to the inability of monkeys to efficiently resolve their infection. To explore the maturation of the humoral immune response as a possible reason for delayed clearance, sera were analyzed by radioimmunoprecipitation using intrinsically radio-labeled antigens prepared under non-denaturing conditions. Antibody recognition was restricted to the antigenically variable major outer membrane protein (MOMP) and a few antigenically conserved antigens. Recognition of MOMP occurred early post-infection and correlated with reduction in infectious ocular burdens but not with infection eradication. In contrast, antibody recognition of conserved antigens, identified as PmpD, Hsp60, CPAF and Pgp3, appeared late and correlated with infection eradication. Partial immunity to re-challenge was associated with a discernible antibody recall response against all antigens. Antibody recognition of PmpD and CPAF was destroyed by heat treatment while MOMP and Pgp3 were partially affected, indicating that antibody specific to conformational epitopes on these proteins may be important to protective immunity. Conclusions/significance: Our findings suggest that delayed clearance of chlamydial infection in NHP is not the result of antigenic variation but rather a consequence of the gradual maturation of the C. trachomatis antigen-specific humoral immune response. However, we cannot conclude that antibodies specific for these proteins play the primary role in host protective immunity as they could be surrogate markers of T cell immunity. Collectively, our results argue that an efficacious subunit trachoma vaccine might require a combination of these antigens delivered in their native conformation. | G54: No | H54: No | I54: Yes | J54: Investigation of whether protracted clearance of a primary infection in nonhuman primates is attributable to antigenic variation or related to the maturation of the anti-chlamydial humoral immune response specific to chlamydial antigens. Even when they found antibodies for antigens involved, they cannot conclude that antibodies specific for these proteins play the primary role in host protective immunity. They suggest a combination of antigens for a vaccine
A55: 23741420 | B55: Intranasal vaccination with Chlamydia pneumoniae induces cross-species immunity against genital Chlamydia muridarum challenge in mice | C55: 3) immunization | E55: Listo | F55: Chlamydia trachomatis is the most common bacterial sexually transmitted disease in the world and specifically in the United States, with the highest incidence in age-groups 14-19 years. In a subset of females, the C. trachomatis genital infection leads to serious pathological sequelae including pelvic inflammatory disease, ectopic pregnancy, and infertility. Chlamydia pneumoniae, another member of the same genus, is a common cause of community acquired respiratory infection with significant number of children aged 5-14 yr displaying sero-conversion. Since these bacteriae share several antigenic determinants, we evaluated whether intranasal immunization with live C. pneumoniae (1×10(6) inclusion forming units; IFU) in 5 week old female C57BL/6 mice would induce cross-species protection against subsequent intravaginal challenge with Chlamydia muridarum (5×10(4) IFU), which causes a similar genital infection and pathology in mice as C. trachomatis in humans. Mice vaccinated intranasally with live C. pneumoniae, but not mock (PBS) immunized animals, displayed high levels of splenic cellular antigen-specific IFN-γ production and serum antibody response against C. muridarum and C. trachomatis. Mice vaccinated with C. pneumoniae displayed a significant reduction in the vaginal C. muridarum shedding as early as day 12 after secondary i.vag. challenge compared to PBS (mock) immunized mice. At day 19 after C. muridarum challenge, 100% of C. pneumoniae vaccinated mice had cleared the infection compared to none (0%) of the mock immunized mice, which cleared the infection by day 27. At day 80 after C. muridarum challenge, C. pneumoniae vaccinated mice displayed a significant reduction in the incidence (50%) and degree of hydrosalpinx compared to mock immunized animals (100%). These results suggest that respiratory C. pneumoniae infection induces accelerated chlamydial clearance and reduction of oviduct pathology following genital C. muridarum challenge, and may have important implications to the C. trachomatis-induced reproductive disease in humans. | G55: No | H55: No | I55: Yes | J55: Mice vaccinated intranasally with live C. pneumoniae to elicit immune response against Chlamydia muridarum. These results suggest that respiratory C. pneumoniae infection induces accelerated chlamydial clearance and reduction of oviduct pathology following genital C. muridarum challenge, and may have important implications to the C. trachomatis-induced reproductive disease in humans.
A56: 23478971 | B56: Activities of first-choice antimicrobials against gamma interferon-treated Chlamydia trachomatis differ in hypoxia | C56: 2) Nuevos tratamientos | E56: Listo | F56: Gamma interferon (IFN-γ)-mediated host responses play a central role in resolving genital Chlamydia trachomatis infections but may also result in persistence of the pathogen, which shows reduced susceptibility to antimicrobials. The antichlamydial function of IFN-γ is oxygen dependent, and the efficacy of antimicrobials against C. trachomatis is reduced in a low-oxygen environment. In this study, we show that the antichlamydial efficacies of azithromycin and doxycycline differ in IFN-γ-treated cells under hypoxia. | G56: No | H56: No | I56: No | J56: Comparative study of the mechanism of action of the two used antibiotics
A57: 23970750 | B57: Presentation of clinically suspected persistent chlamydial infection: a case series | C57: 1) Reporte de cepas resistentes | E57: Listo | F57: In vivo antimicrobial resistance has yet to be documented in Chlamydia trachomatis; however, there have been anecdotal reports of persistent infection. The purpose of this case series was to describe a group of patients who have persistent chlamydia infection despite adequate treatment and where re-infection was considered unlikely. Patients were selected using a clinical questionnaire. For inclusion patients had to have tested positive for C. trachomatis, at least twice, using a nucleic acid amplification test despite having been fully compliant with at least two rounds of recommended therapy and be deemed to be at low risk of re-infection. Patients were grouped into categories based on sexual behaviour. Twenty-eight patients are included in this case series; 46% declared no sexual contact since initial diagnosis (category 1), a further 36% declaring contact that was considered low risk of re-infection (categories 2-4); 61% showed signs and symptoms at initial presentation increasing to 75% at re-attendance. Thirty-nine percent of patients received azithromycin only while 48% received doxycycline also. This case series identifies patients with persistent chlamydia despite receiving treatment. There is a need for a case definition of clinical treatment failure, development of susceptibility testing methods and guidance on appropriate treatment for patients with persistent infection. | G57: Yes | H57: No | I57: No | J57: This case series identifies patients with persistent chlamydia despite receiving treatment. There is a need for a case definition of clinical treatment failure, development of susceptibility testing methods and guidance on appropriate treatment for patients with persistent infection.
A58: 23470847 | B58: Spontaneous resolution of genital Chlamydia trachomatis infection in women and protection from reinfection | C58: 3) immunization | E58: Listo | F58: The natural history of chlamydia is variable and may include persisting asymptomatic infection, complications, or spontaneous resolution before treatment. Reinfection is common. We evaluated whether spontaneous resolution was associated with decreased reinfection in women returning for treatment of a positive chlamydia screening test. At enrollment, participants were tested for chlamydia, treated with azithromycin, and scheduled for a 6-month follow-up visit for repeat testing. Two hundred participants returned 1 to 12 months after treatment. Spontaneous resolution at enrollment was demonstrated in 44 (22.0%). Reinfection at follow-up occurred in 33 (16.5%), being more frequent in those with persisting infection at enrollment versus spontaneous resolution (31 of 156 [19.9%] vs 2 of 44 [4.5%]; P = .016). Adjusting for age, the odds of reinfection was 4 times higher for participants with persisting infection at enrollment (odds ratio 4.0, 95% confidence interval, 1.1-25.6; P = .034). Chlamydia treatment may attenuate protective immunity in some patients. | G58: No | H58: No | I58: No | J58: They showed Chlamydia treatment may attenuate protective immunity in some patients.
A59: 23904877 | B59: Recent acquisitions in the medical treatment of infertility caused by Chlamydia Trachomatis | C59: 2) Nuevos tratamientos | E59: Listo | F59: The infertility defined as the incapacity of the people to conceive a child in a given period, usually of 1-2 years of sexually unprotected relations, represents a major dysfunction of the genital apparatus. Its frequency is estimated at 10-15% of the couples at the reproductive age. The incidence of sterility is high, a couple out of 10 being sterile. The conjugal sterility is a phenomenon representative for the couple; the woman is responsible for it only in 35-40% of the cases, in 40% of the cases, the male factor is involved. In 20% of the cases, mixed factors are met, both feminine and masculine, and in 5-10% of the cases, the causes cannot be detected. From the multitude of causes of infertility, the infectious factor plays an important role, the Chlamydia infections being lately blamed in the etiology of sterility. The infections due to Chlamydia Trachomatis (CT) represent the most frequent sexually transmitted diseases, which, most of the times lead to sterility. Taking into account the widespread of this bacterium in the sexually active population, the effective treatment of the CT infection is very important. We have selected 200 cases with PID genital infection in the study. All the selected patients had at least 2, 3 and more than 3 inflammation recurrence episodes, this way being considered cases with medium and severe forms of disease. All these selected patients had at least 2, 3 and more than 3 episodes of inflammation recurrence, this way being considered medium and severe disease cases. In conclusion, there is a high clinical efficiency of the azithromycin treatment in PID case. | G59: No | H59: No | I59: No | J59: They used azithromycin to effectively reduce PID
... A62: 23749408 | B62: [Lymphogranuloma venereum: new serovariant L2b and old "groove sign"] | C62: 1) Reporte de cepas resistentes | E62: Listo | F62: An ongoing lymphogranuloma venereum (LGV) outbreak has been reported in several European countries since 2003, related to a new variant L2b. This serovar appears to affect men who have sex with men (MSM), most of them being co-infected with the Human Immunodeficiency Virus (HIV). The secondary stage of LGV may involve lymph nodes and the inguinal form has sometimes been described on each side of the inguinal ligament thus named the "groove sign". We report the case of LGV serovariant L2b acquired by an heterosexual intercourse in an HIV seronegative patient who presented with an inguinal lymph node and a "groove sign". This is an uncommon but suggestive sign of LGV and we suggest that the clinical presentation of L2b LGV might not be so different than other variants and than the 20th century authors' description. Such a new Chlamydia trachomatis variant may circulate in other populations than MSM in Europe and clinical awareness must prevail. | G62: No | H62: No | I62: No | J62: They found a new serovar but sensitive to antibiotics
A63: 23796320 | B63: Identification of a serine protease inhibitor which causes inclusion vacuole reduction and is lethal to Chlamydia trachomatis | C63: 2) Nuevos tratamientos | D63: 2b) Péptidos | E63: Listo | F63: The mechanistic details of the pathogenesis of Chlamydia, an obligate intracellular pathogen of global importance, have eluded scientists due to the scarcity of traditional molecular genetic tools to investigate this organism. Here we report a chemical biology strategy that has uncovered the first essential protease for this organism. Identification and application of a unique CtHtrA inhibitor (JO146) to cultures of Chlamydia resulted in a complete loss of viable elementary body formation. JO146 treatment during the replicative phase of development resulted in a loss of Chlamydia cell morphology, diminishing inclusion size, and ultimate loss of inclusions from the host cells. This completely prevented the formation of viable Chlamydia elementary bodies. In addition to its effect on the human Chlamydia trachomatis strain, JO146 inhibited the viability of the mouse strain, Chlamydia muridarum, both in vitro and in vivo. Thus, we report a chemical biology approach to establish an essential role for Chlamydia CtHtrA. The function of CtHtrA for Chlamydia appears to be essential for maintenance of cell morphology during replicative the phase and these findings provide proof of concept that proteases can be targeted for antimicrobial therapy for intracellular pathogens. | G63: No | H63: Yes | I63: No | J63: Identification and application of a unique CtHtrA inhibitor (JO146) to cultures of Chlamydia resulted in a complete loss of viable elementary body formation. A serine protease inhibitor as a target for antibiotics
A64: 23271498 | B64: In vitro susceptibility of urogenital Chlamydia trachomatis strains in a country with high azithromycin consumption rate | C64: 1) Reporte de cepas resistentes | E64: Listo | F64: Although Chlamydia trachomatis resistance is not of great concern due to its excellent sensitivity to the currently recommended first-line antibiotics (azithromycin and doxycycline), clinical treatment failures have been reported and some of them were linked to laboratory proved resistance. The aim of this study was to determine in vitro susceptibility to azithromycin and doxycycline for 24 urogenital chlamydial strains isolated in Croatia-a country with the highest consumption of azithromycin in Europe and with very high antibiotic prescription rates. Fourteen isolates from cervical swabs, nine from male urethral swabs, and one isolate from expressed prostatic secretion were tested in McCoy cell culture system. All strains were susceptible to azithromycin and doxycycline with minimal inhibitory concentration for azithromycin and doxycycline ranging from 0.064 to 0.125 μg/mL and 0.016 to 0.064 μg/mL, and minimal chlamydicidal concentration ranging from 0.064 to 2.0 μg/mL and 0.032 to 1.0 μg/mL, respectively. Since we still lack information on whether C. trachomatis is evolving in vivo in response to antibiotic selection pressure, this kind of surveillance for resistance is essential in detecting shifts in antimicrobial susceptibilities. | G64: No | H64: No | I64: No | J64: Vigilance of the effective treatments using the typical antibiotics
