Workbook
Name categoria: categorias!$A:$A
Name Estado: categorias!$C$2:$C$65536
Name EXCL: Excluidas!$A:$K
Name EXCLUIDAS: Excluidas!$A$1:$K$463
Name KEYWORDS: 'Palabras claves'!$A:$K
Name NgonorreaePost: '2017-2022'!#REF!
Name NgonorreaePre: '2012-2017'!$A$1:$K$534
Name PalabrasClave: 'Palabras claves'!$K$1:$K$1371
Name POST: '2017-2022'!$A:$K
Name POSTALERTA: '2017-2022'!$A$1:$B$857
Name PRE: '2012-2017'!$A:$K
Name PREALERTA: '2012-2017'!$A$1:$O$540
Name SegmentaciónDeDatos_Alerta1: #REF!
Name SegmentaciónDeDatos_KeyWords: #REF!
Name SegmentaciónDeDatos_PubYear: #REF!
Name subcategoria: categorias!$B:$B
Name TablaNgonoreae: '2012-2022'!$A$1:$K$4211

Sheet DashBoard
C2: H. influenzae 2012-2022
C3: Total de publicaciones de | F3: =C2 -> H. influenzae 2012-2022 | G3: : | H3: =COUNTA('2012-2022'!A$1:A$4444)-1 -> 4443
D5: Publicaciones por Año | I5: Categorías y Subcategorías
D17: Publicaciones por mes
C37: =IFERROR(__xludf.DUMMYFUNCTION("UNIQUE('2012-2022'!N:N)"),"Categoria") -> Categoria
C39: =IFERROR(__xludf.DUMMYFUNCTION("""COMPUTED_VALUE"""),"")
C40: =IFERROR(__xludf.DUMMYFUNCTION("""COMPUTED_VALUE"""),"3) Inmunización") -> 3) Inmunización | F40: =COUNTIF('2012-2022'!N:N,C40) -> 36
C41: =IFERROR(__xludf.DUMMYFUNCTION("""COMPUTED_VALUE"""),"1) Reporte de cepas resistentes") -> 1) Reporte de cepas resistentes | F41: =COUNTIF('2012-2022'!N:N,C41) -> 172
C42: =IFERROR(__xludf.DUMMYFUNCTION("""COMPUTED_VALUE"""),"2) Nuevos tratamientos ") -> 2) Nuevos tratamientos | F42: =COUNTIF('2012-2022'!N:N,C42) -> 115
F43: =COUNTIF('2012-2022'!N:N,C43) -> 0
F44: =COUNTIF('2012-2022'!N:N,C44) -> 0
F45: =COUNTIF('2012-2022'!N:N,C45) -> 0
F46: =COUNTIF('2012-2022'!N:N,C46) -> 0
F47: =SUM(F40:F45) -> 323

Sheet categorias
A1: Categorias | B1: Subcategorias | C1: Estados
A2: 1) Reporte de cepas resistentes | B2: 2a) Productos naturales | C2: Revisar
A3: 2) Nuevos tratamientos | B3: 2b) Péptidos | C3: Listo
A4: 3) Inmunizacióm | B4: 2c) Droga de diseño | C4: Excluir
A5: 4) otros | B5: 2d) Anticuerpos | C5: Otros-A
B6: 2e) Bacteriófagos | C6: Otros-B
B7: 2f) Estrategias antivirulencia | C7: Otros-C
B8: 2g) nueva combinación de ATB | C8: Otros-D

Sheet TablasDinamicas
B1: Etiquetas de fila | C1: Cuenta de Title | E1: Cuenta de Title | I1: Categoria | J1: subcategoria | K1: Cuenta de Title
B2: PreAlerta | C2: 3059 | E2: PubYear | F2: PubMonth | G2: Total | I2: 1) Reporte de cepas resistentes | J2: (en blanco) | K2: 2 | L2: 1) Interacción huésped-patógeno | M2: (en blanco) | N2: =GETPIVOTDATA("Title",$I$1,"Categoria",L2,"subcategoria",M2) -> #REF!
B3: PostAlerta | C3: 4841 | E3: 2014 | F3: Jan | G3: 33 | I3: Total 1) Reporte de cepas resistentes | K3: 2 | L3: 1) Reporte de cepas resistentes | M3: (en blanco) | N3: =GETPIVOTDATA("Title",$I$1,"Categoria",L3,"subcategoria",M3) -> #REF!
B4: Excluido | C4: 708 | F4: Feb | G4: 30 | I4: 2) Nuevos tratamientos | J4: 4d) Anticuerpos | K4: 1 | L4: 3) Casos clínicos | M4: (en blanco) | N4: =GETPIVOTDATA("Title",$I$1,"Categoria",L4,"subcategoria",M4) -> #REF!
B5: Total general | C5: 8608 | F5: Mar | G5: 27 | J5: 4e) Bacteriófagos | K5: 1 | L5: 2) Nuevos tratamientos | M5: 4a) Productos naturales | N5: =GETPIVOTDATA("Title",$I$1,"Categoria",L5,"subcategoria",M5) -> #REF!
F6: Apr | G6: 33 | I6: Total 2) Nuevos tratamientos | K6: 2 | L6: 2) Nuevos tratamientos | M6: 4b) Péptidos | N6: =GETPIVOTDATA("Title",$I$1,"Categoria",L6,"subcategoria",M6) -> #REF!
B7: Etiquetas de fila | C7: Cuenta de Title | F7: May | G7: 26 | I7: (en blanco) | J7: (en blanco) | K7: 3127 | L7: 2) Nuevos tratamientos | M7: 4c) Droga de diseño | N7: =GETPIVOTDATA("Title",$I$1,"Categoria",L7,"subcategoria",M7) -> #REF!
B8: S/PalabrasClaves | C8: 3131 | F8: Jun | G8: 31 | I8: Total (en blanco) | K8: 3127 | L8: 2) Nuevos tratamientos | M8: 4d) Anticuerpos | N8: =GETPIVOTDATA("Title",$I$1,"Categoria",L8,"subcategoria",M8) -> #REF!
B9: Excluido | C9: 152 | F9: Jul | G9: 32 | I9: Total general | K9: 3131 | L9: 2) Nuevos tratamientos | M9: 4e) Bacteriófagos | N9: =GETPIVOTDATA("Title",$I$1,"Categoria",L9,"subcategoria",M9) -> #REF!
B10: PostAlerta | C10: 1883 | F10: Aug | G10: 26 | L10: 2) Nuevos tratamientos | M10: 4f) Estrategias antivirulencia | N10: =GETPIVOTDATA("Title",$I$1,"Categoria",L10,"subcategoria",M10) -> #REF!
B11: PreAlerta | C11: 1096 | F11: Sep | G11: 35
B12: Total general | C12: 3131 | F12: Oct | G12: 39
F13: Nov | G13: 26
B14: Etiquetas de fila | C14: Cuenta de Title | F14: Dec | G14: 34
C15: 2398 | F15: Fall | G15: 1
B16: 2012 | C16: 85 | F16: VerPaper | G16: 24
B17: 2013 | C17: 150 | E17: Total 2014 | G17: 397
B18: 2014 | C18: 129 | E18: Total general | G18: 397
B19: 2015 | C19: 159
B20: 2016 | C20: 161
B21: 2017 | C21: 49
B22: Total general | C22: 3131
B25: Etiquetas de fila | C25: Cuenta de Title
B26: Revisar | C26: 1
B27: (en blanco) | C27: 8607
B28: Total general | C28: 8608

Sheet 2012-2022
A1: PMID | B1: Title | C1: Authors | D1: Citation | E1: Columna1 | F1: Columna2 | G1: Columna3 | H1: Columna4 | I1: Columna5 | J1: Columna6 | K1: Columna7 | L1: Alerta | M1: KeyWords | N1: Categoria | O1: subcategoria | P1: Columna8 | Q1: Estado | R1: PubYear | S1: Mes | T1: Abstract | U1: 1) Antimicrobial Resistance stain | V1: 2) New treatment | W1: 3) Immunization | X1: Human_summary
A2: 36909845 | B2: Real-time PCR has advantages over culture-based methods in identifying major airway bacterial pathogens in chronic obstructive pulmonary disease: Results from three clinical studies in Europe and North America | C2: Schoonbroodt S, Ichanté JL, Boffé S, Devos N, Devaster JM, Taddei L, Rondini S, Arora AK, Pascal T, Malvaux L. | D2: Front Microbiol. 2023 Feb 24 | E2: Schoonbroodt S | F2: Front Microbiol | G2: 2023 | H2: 44998 | I2: PMC10000296 | K2: 10.3389/fmicb.2022.1098133 | L2: =IF(ISNUMBER(VLOOKUP(A2,EXCL,1,FALSE)),"Excluido",IF(ISNUMBER(VLOOKUP(A2,POST,1,FALSE)),"PostAlerta",IF(ISNUMBER(VLOOKUP(A2,PRE,1,FALSE)),"PreAlerta",""))) -> PostAlerta | M2: =IF(ISNUMBER(VLOOKUP(A2,KEYWORDS,1,FALSE)),"C/PalabrasClaves","S/PalabrasClaves") -> S/PalabrasClaves | P2: 2023 Feb 24 | Q2: Excluir | R2: =LEFT(P2,4) -> 2023 | S2: Feb
A3: 36777029 | B3: Dynamics of community-acquired meningitis syndrome outbreaks in southern France | C3: Morsli M, Salipante F, Kerharo Q, Boudet A, Stephan R, Dunyach-Remy C, Zandotti C, Lavigne JP, Drancourt M. | D3: Front Microbiol. 2023 Jan 26 | E3: Morsli M | F3: Front Microbiol | G3: 2023 | H3: 44970 | I3: PMC9909019 | K3: 10.3389/fmicb.2022.1102130 | L3: =IF(ISNUMBER(VLOOKUP(A3,EXCL,1,FALSE)),"Excluido",IF(ISNUMBER(VLOOKUP(A3,POST,1,FALSE)),"PostAlerta",IF(ISNUMBER(VLOOKUP(A3,PRE,1,FALSE)),"PreAlerta",""))) -> PostAlerta | M3: =IF(ISNUMBER(VLOOKUP(A3,KEYWORDS,1,FALSE)),"C/PalabrasClaves","S/PalabrasClaves") -> S/PalabrasClaves | N3: =IF(ISNUMBER(SEARCH("TREATMENT", B3)), "4) Nuevos tratamientos", "") | P3: 2023 Jan 26 | Q3: Excluir | R3: =LEFT(P3,4) -> 2023 | S3: Jan
A4: 36685526 | B4: Comparing the pertussis antibody levels of healthy children immunized with four doses of DTap-IPV/Hib (Pentaxim) combination vaccine and DTaP vaccine in Quzhou, China | C4: Yin Z, Zheng C, Fang Q, Wen T, Wang S, Li J, Gong X, Xiang Z. | D4: Front Immunol. 2023 Jan 6 | E4: Yin Z | F4: Front Immunol | G4: 2023 | H4: 44949 | I4: PMC9852981 | K4: 10.3389/fimmu.2022.1055677 | L4: =IF(ISNUMBER(VLOOKUP(A4,EXCL,1,FALSE)),"Excluido",IF(ISNUMBER(VLOOKUP(A4,POST,1,FALSE)),"PostAlerta",IF(ISNUMBER(VLOOKUP(A4,PRE,1,FALSE)),"PreAlerta",""))) -> PostAlerta | M4: =IF(ISNUMBER(A4),(IF(ISNUMBER(VLOOKUP(A4,KEYWORDS,1,FALSE)),"C/PalabrasClaves","S/PalabrasClaves")),"") -> S/PalabrasClaves | N4: =IF(ISNUMBER(SEARCH("TREATMENT", B4)), "4) Nuevos tratamientos", "") | P4: 2023 Jan 6 | Q4: Excluir | R4: =LEFT(P4,4) -> 2023 | S4: Jan
A5: 34261660 | B5: Metagenomics of the lacrimal sac in primary acquired nasolacrimal duct obstruction: the Lacriome paper 1 | C5: Ali MJ. | D5: Br J Ophthalmol. 2023 Jan | E5: Ali MJ | F5: Br J Ophthalmol | G5: 2023 | H5: 44392 | K5: 10.1136/bjophthalmol-2021-319677 | L5: =IF(ISNUMBER(VLOOKUP(A5,EXCL,1,FALSE)),"Excluido",IF(ISNUMBER(VLOOKUP(A5,POST,1,FALSE)),"PostAlerta",IF(ISNUMBER(VLOOKUP(A5,PRE,1,FALSE)),"PreAlerta",""))) -> PostAlerta | M5: =IF(ISNUMBER(A5),(IF(ISNUMBER(VLOOKUP(A5,KEYWORDS,1,FALSE)),"C/PalabrasClaves","S/PalabrasClaves")),"") -> S/PalabrasClaves | N5: =IF(ISNUMBER(SEARCH("TREATMENT", B5)), "4) Nuevos tratamientos", "") | O5: 4a) Productos naturales | P5: 2023 Jan | Q5: Excluir | R5: =LEFT(P5,4) -> 2023 | S5: Jan
A6: 34654665 | B6: Occurrence of Haemophilus influenzae type b (Hib) meningitis in a 2 month-old infant in the Hib vaccination era | C6: Cho Y, Tomari K, Nagamine T, Fujiwara N. | D6: J Microbiol Immunol Infect. 2022 Jun | E6: Cho Y | F6: J Microbiol Immunol Infect | G6: 2022 | H6: 44485 | K6: 10.1016/j.jmii.2021.09.012 | L6: =IF(ISNUMBER(VLOOKUP(A6,EXCL,1,FALSE)),"Excluido",IF(ISNUMBER(VLOOKUP(A6,POST,1,FALSE)),"PostAlerta",IF(ISNUMBER(VLOOKUP(A6,PRE,1,FALSE)),"PreAlerta",""))) -> PostAlerta | M6: =IF(ISNUMBER(A6),(IF(ISNUMBER(VLOOKUP(A6,KEYWORDS,1,FALSE)),"C/PalabrasClaves","S/PalabrasClaves")),"") -> S/PalabrasClaves | N6: 3) Inmunización | P6: 2022 Jun | Q6: Excluir | R6: =LEFT(P6,4) -> 2022 | S6: Jun | T6: Occurrence of Haemophilus influenzae type b (Hib) meningitis in a 2 month-old infant in the Hib vaccination era | X6: Case of Hib in infant during vaccination era highlights importance of vaccine coverage and efficacy
A7: 34362705 | B7: Septicemia and meningitis associated with Haemophilus influenzae type b vaccine failure | C7: López López S, Del Rosal T, Jiménez Bueno S, Baquero-Artigao F. | D7: Enferm Infecc Microbiol Clin (Engl Ed). 2021 Oct | E7: López López S | F7: Enferm Infecc Microbiol Clin (Engl Ed) | G7: 2021 | H7: 44415 | K7: 10.1016/j.eimce.2021.07.005 | L7: =IF(ISNUMBER(VLOOKUP(A7,EXCL,1,FALSE)),"Excluido",IF(ISNUMBER(VLOOKUP(A7,POST,1,FALSE)),"PostAlerta",IF(ISNUMBER(VLOOKUP(A7,PRE,1,FALSE)),"PreAlerta",""))) -> PostAlerta | M7: =IF(ISNUMBER(A7),(IF(ISNUMBER(VLOOKUP(A7,KEYWORDS,1,FALSE)),"C/PalabrasClaves","S/PalabrasClaves")),"") -> S/PalabrasClaves | N7: 3) Inmunización | P7: 2021 Oct | Q7: Listo | R7: =LEFT(P7,4) -> 2021 | S7: Oct | T7: Septicemia and meningitis associated with Haemophilus influenzae type b vaccine failure | U7: No | V7: No | W7: Yes | X7: Describes a case of Hib septicemia and meningitis after vaccination, highlighting flaws in vaccine efficacy and the need for surveillance.
A8: 35020530 | B8: Systematic review of the efficacy, effectiveness and impact of high-valency pneumococcal conjugate vaccines on otitis media | C8: Izurieta P, Scherbakov M, Nieto Guevara J, Vetter V, Soumahoro L. | D8: Hum Vaccin Immunother. 2022 Dec 31 | E8: Izurieta P | F8: Hum Vaccin Immunother | G8: 2022 | H8: 44573 | I8: PMC8973322 | K8: 10.1080/21645515.2021.2013693 | L8: =IF(ISNUMBER(VLOOKUP(A8,EXCL,1,FALSE)),"Excluido",IF(ISNUMBER(VLOOKUP(A8,POST,1,FALSE)),"PostAlerta",IF(ISNUMBER(VLOOKUP(A8,PRE,1,FALSE)),"PreAlerta",""))) -> Excluido | M8: =IF(ISNUMBER(A8),(IF(ISNUMBER(VLOOKUP(A8,KEYWORDS,1,FALSE)),"C/PalabrasClaves","S/PalabrasClaves")),"") -> S/PalabrasClaves | O8: 4e) Bacteriófagos | P8: 2022 Dec 31 | Q8: Excluir | R8: =LEFT(P8,4) -> 2022 | S8: Dec
A9: 28506825 | B9: Multiple drug resistance in Haemophilus influenzae isolated from patients in Bangkok, Thailand | C9: Tribuddharat C, Srifuengfung S. | D9: J Glob Antimicrob Resist. 2017 Jun | E9: Tribuddharat C | F9: J Glob Antimicrob Resist | G9: 2017 | H9: 42872 | K9: 10.1016/j.jgar.2017.03.003 | L9: =IF(ISNUMBER(VLOOKUP(A9,EXCL,1,FALSE)),"Excluido",IF(ISNUMBER(VLOOKUP(A9,POST,1,FALSE)),"PostAlerta",IF(ISNUMBER(VLOOKUP(A9,PRE,1,FALSE)),"PreAlerta",""))) -> PostAlerta | M9: =IF(ISNUMBER(A9),(IF(ISNUMBER(VLOOKUP(A9,KEYWORDS,1,FALSE)),"C/PalabrasClaves","S/PalabrasClaves")),"") -> C/PalabrasClaves | N9: 1) Reporte de cepas resistentes | P9: 2017 Jun | Q9: Listo | R9: =LEFT(P9,4) -> 2017 | S9: Jun | T9: Multiple drug resistance in Haemophilus influenzae isolated from patients in Bangkok, Thailand | U9: Yes | V9: No | W9: No | X9: The emergence of multi-resistant H. influenzae strains in Bangkok is documented, warning of the spread of antibiotic resistance.
A10: 34270376 | B10: Gaps in knowledge about the vaccine coverage of immunocompromised children: a scoping review | C10: MacDonald SE, Palichuk A, Slater L, Tripp H, Reifferscheid L, Burton C. | D10: Hum Vaccin Immunother. 2022 Dec 31 | E10: MacDonald SE | F10: Hum Vaccin Immunother | G10: 2022 | H10: 44393 | I10: PMC8920240 | K10: 10.1080/21645515.2021.1935169 | L10: =IF(ISNUMBER(VLOOKUP(A10,EXCL,1,FALSE)),"Excluido",IF(ISNUMBER(VLOOKUP(A10,POST,1,FALSE)),"PostAlerta",IF(ISNUMBER(VLOOKUP(A10,PRE,1,FALSE)),"PreAlerta",""))) -> Excluido | M10: =IF(ISNUMBER(A10),(IF(ISNUMBER(VLOOKUP(A10,KEYWORDS,1,FALSE)),"C/PalabrasClaves","S/PalabrasClaves")),"") -> S/PalabrasClaves | N10: =IF(ISNUMBER(SEARCH("TREATMENT", B10)), "4) Nuevos tratamientos", "") | P10: 2022 Dec 31 | Q10: Excluir | R10: =LEFT(P10,4) -> 2022 | S10: Dec
A11: 33735585 | B11: Impact after 10-year use of pneumococcal conjugate vaccine in the Brazilian national immunization program: an updated systematic literature review from 2015 to 2020 | C11: Guzman-Holst A, de Barros E, Rubio P, DeAntonio R, Cintra O, Abreu A. | D11: Hum Vaccin Immunother. 2022 Dec 31 | E11: Guzman-Holst A | F11: Hum Vaccin Immunother | G11: 2022 | H11: 44273 | I11: PMC8920160 | K11: 10.1080/21645515.2021.1879578 | L11: =IF(ISNUMBER(VLOOKUP(A11,EXCL,1,FALSE)),"Excluido",IF(ISNUMBER(VLOOKUP(A11,POST,1,FALSE)),"PostAlerta",IF(ISNUMBER(VLOOKUP(A11,PRE,1,FALSE)),"PreAlerta",""))) -> Excluido | M11: =IF(ISNUMBER(A11),(IF(ISNUMBER(VLOOKUP(A11,KEYWORDS,1,FALSE)),"C/PalabrasClaves","S/PalabrasClaves")),"") -> S/PalabrasClaves | N11: =IF(ISNUMBER(SEARCH("TREATMENT", B11)), "4) Nuevos tratamientos", "") | P11: 2022 Dec 31 | Q11: Excluir | R11: =LEFT(P11,4) -> 2022 | S11: Dec
A12: 27289531 | B12: Increasing resistance to fluoroquinolones among Haemophilus species in Southern Taiwan | C12: Chang CM, Tang HJ, Wang LR, Shih HI, Huang CC, Lee NY, Lee CC, Ko WC. | D12: J Microbiol Immunol Infect. 2017 Apr | E12: Chang CM | F12: J Microbiol Immunol Infect | G12: 2017 | H12: 42534 | K12: 10.1016/j.jmii.2016.04.002 | L12: =IF(ISNUMBER(VLOOKUP(A12,EXCL,1,FALSE)),"Excluido",IF(ISNUMBER(VLOOKUP(A12,POST,1,FALSE)),"PostAlerta",IF(ISNUMBER(VLOOKUP(A12,PRE,1,FALSE)),"PreAlerta",""))) -> PostAlerta | M12: =IF(ISNUMBER(A12),(IF(ISNUMBER(VLOOKUP(A12,KEYWORDS,1,FALSE)),"C/PalabrasClaves","S/PalabrasClaves")),"") -> C/PalabrasClaves | N12: 1) Reporte de cepas resistentes | P12: 2017 Apr | Q12: Listo | R12: =LEFT(P12,4) -> 2017 | S12: Apr | T12: Increasing resistance to fluoroquinolones among Haemophilus species in Southern Taiwan | U12: Yes | V12: No | W12: No | X12: In southern Taiwan, Haemophilus spp. are showing increasing resistance to fluoroquinolones, compromising standard therapies.
A13: 28332810 | B13: Betalaktamresistens hos Haemophilus influenzae | C13: Skaare D. | D13: Tidsskr Nor Laegeforen. 2017 Mar 21 | E13: Skaare D | F13: Tidsskr Nor Laegeforen | G13: 2017 | H13: 42818 | K13: 10.4045/tidsskr.17.0010 | L13: =IF(ISNUMBER(VLOOKUP(A13,EXCL,1,FALSE)),"Excluido",IF(ISNUMBER(VLOOKUP(A13,POST,1,FALSE)),"PostAlerta",IF(ISNUMBER(VLOOKUP(A13,PRE,1,FALSE)),"PreAlerta",""))) -> PostAlerta | M13: =IF(ISNUMBER(A13),(IF(ISNUMBER(VLOOKUP(A13,KEYWORDS,1,FALSE)),"C/PalabrasClaves","S/PalabrasClaves")),"") -> S/PalabrasClaves | N13: 1) Reporte de cepas resistentes | P13: 2017 Mar 21 | Q13: Listo | R13: =LEFT(P13,4) -> 2017 | S13: Mar | T13: Betalaktamresistens hos Haemophilus influenzae | U13: Yes | V13: No | W13: No | X13: Describes the increase in H. influenzae strains with resistance to β-lactams.
A14: 27181174 | B14: Antimicrobial resistance in cystic fibrosis isolates of Haemophilus influenzae | C14: Atkinson CT, Tristram SG. | D14: Br J Biomed Sci. 2016 | E14: Atkinson CT | F14: Br J Biomed Sci | G14: 2016 | H14: 42507 | K14: 10.1080/09674845.2016.1165408 | L14: =IF(ISNUMBER(VLOOKUP(A14,EXCL,1,FALSE)),"Excluido",IF(ISNUMBER(VLOOKUP(A14,POST,1,FALSE)),"PostAlerta",IF(ISNUMBER(VLOOKUP(A14,PRE,1,FALSE)),"PreAlerta",""))) -> PreAlerta | M14: =IF(ISNUMBER(A14),(IF(ISNUMBER(VLOOKUP(A14,KEYWORDS,1,FALSE)),"C/PalabrasClaves","S/PalabrasClaves")),"") -> C/PalabrasClaves | N14: 1) Reporte de cepas resistentes | P14: 2016 | R14: =LEFT(P14,4) -> 2016 | S14: Sci | T14: Antimicrobial resistance in cystic fibrosis isolates of Haemophilus influenzae | U14: Yes | V14: No | W14: No | X14: Antimicrobial resistance in cystic fibrosis Haemophilus influenzae strains presents challenges in the treatment and management of pulmonary infections.
A15: 36466693 | B15: Evaluation of molecular typing for national surveillance of invasive clinical Haemophilus influenzae isolates from Denmark | C15: Slotved HC, Johannesen TB, Stegger M, Fuursted K. | D15: Front Microbiol. 2022 Nov 17 | E15: Slotved HC | F15: Front Microbiol | G15: 2022 | H15: 44900 | I15: PMC9712784 | K15: 10.3389/fmicb.2022.1030242 | L15: =IF(ISNUMBER(VLOOKUP(A15,EXCL,1,FALSE)),"Excluido",IF(ISNUMBER(VLOOKUP(A15,POST,1,FALSE)),"PostAlerta",IF(ISNUMBER(VLOOKUP(A15,PRE,1,FALSE)),"PreAlerta",""))) -> PostAlerta | M15: =IF(ISNUMBER(A15),(IF(ISNUMBER(VLOOKUP(A15,KEYWORDS,1,FALSE)),"C/PalabrasClaves","S/PalabrasClaves")),"") -> S/PalabrasClaves | N15: =IF(ISNUMBER(SEARCH("TREATMENT", B15)), "4) Nuevos tratamientos", "") | P15: 2022 Nov 17 | Q15: Excluir | R15: =LEFT(P15,4) -> 2022 | S15: Nov
A16: 36466632 | B16: Development and clinical application of a endonuclease restriction real-time loop-mediated isothermal amplification (ERT-LAMP) assay for rapid detection of Haemophilus influenzae | C16: Cheng J, Zhou Y, Zhao X, Lu J, Wu J, Wang Y. | D16: Front Microbiol. 2022 Nov 17 | E16: Cheng J | F16: Front Microbiol | G16: 2022 | H16: 44900 | I16: PMC9712716 | K16: 10.3389/fmicb.2022.1037343 | L16: =IF(ISNUMBER(VLOOKUP(A16,EXCL,1,FALSE)),"Excluido",IF(ISNUMBER(VLOOKUP(A16,POST,1,FALSE)),"PostAlerta",IF(ISNUMBER(VLOOKUP(A16,PRE,1,FALSE)),"PreAlerta",""))) -> PostAlerta | M16: =IF(ISNUMBER(A16),(IF(ISNUMBER(VLOOKUP(A16,KEYWORDS,1,FALSE)),"C/PalabrasClaves","S/PalabrasClaves")),"") -> S/PalabrasClaves | N16: =IF(ISNUMBER(SEARCH("TREATMENT", B16)), "4) Nuevos tratamientos", "") | P16: 2022 Nov 17 | Q16: Excluir | R16: =LEFT(P16,4) -> 2022 | S16: Nov
A17: 36355776 | B17: Household fuel use and its association with potential respiratory pathogens among healthy mothers and children in Ethiopia | C17: Tamire M, Addissie A, Gizaw S, Abebe T, Geravandi S, Nilsson S, Gonzales-Siles L, Nordén R, Andersson R, Skovbjerg S. | D17: PLoS One. 2022 Nov 10 | E17: Tamire M | F17: PLoS One | G17: 2022 | H17: 44875 | I17: PMC9648707 | K17: 10.1371/journal.pone.0277348 | L17: =IF(ISNUMBER(VLOOKUP(A17,EXCL,1,FALSE)),"Excluido",IF(ISNUMBER(VLOOKUP(A17,POST,1,FALSE)),"PostAlerta",IF(ISNUMBER(VLOOKUP(A17,PRE,1,FALSE)),"PreAlerta",""))) -> PostAlerta | M17: =IF(ISNUMBER(A17),(IF(ISNUMBER(VLOOKUP(A17,KEYWORDS,1,FALSE)),"C/PalabrasClaves","S/PalabrasClaves")),"") -> S/PalabrasClaves | N17: =IF(ISNUMBER(SEARCH("TREATMENT", B17)), "4) Nuevos tratamientos", "") | P17: 2022 Nov 10 | Q17: Excluir | R17: =LEFT(P17,4) -> 2022 | S17: Nov
A18: 26369355 | B18: Acquired macrolide resistance genes in Haemophilus influenzae?-authors' response | C18: Atkinson CT, Kunde DA, Tristram SG. | D18: J Antimicrob Chemother. 2015 Dec | E18: Atkinson CT | F18: J Antimicrob Chemother | G18: 2015 | H18: 42263 | K18: 10.1093/jac/dkv290 | L18: =IF(ISNUMBER(VLOOKUP(A18,EXCL,1,FALSE)),"Excluido",IF(ISNUMBER(VLOOKUP(A18,POST,1,FALSE)),"PostAlerta",IF(ISNUMBER(VLOOKUP(A18,PRE,1,FALSE)),"PreAlerta",""))) -> PreAlerta | M18: =IF(ISNUMBER(A18),(IF(ISNUMBER(VLOOKUP(A18,KEYWORDS,1,FALSE)),"C/PalabrasClaves","S/PalabrasClaves")),"") -> C/PalabrasClaves | N18: 1) Reporte de cepas resistentes | P18: 2 Dec | R18: =LEFT(P18,4) -> 2 D | S18: Dec | T18: Acquired macrolide resistance genes in Haemophilus influenzae?-authors' response | U18: Yes | V18: No | W18: No | X18: Describes acquired macrolide resistance genes in H. influenzae, key to monitoring and managing resistant strains
A19: 36389175 | B19: Diagnostic value of bronchoalveolar lavage fluid metagenomic next-generation sequencing in pediatric pneumonia | C19: Deng W, Xu H, Wu Y, Li J. | D19: Front Cell Infect Microbiol. 2022 Oct 27 | E19: Deng W | F19: Front Cell Infect Microbiol | G19: 2022 | H19: 44882 | I19: PMC9648200 | K19: 10.3389/fcimb.2022.950531 | L19: =IF(ISNUMBER(VLOOKUP(A19,EXCL,1,FALSE)),"Excluido",IF(ISNUMBER(VLOOKUP(A19,POST,1,FALSE)),"PostAlerta",IF(ISNUMBER(VLOOKUP(A19,PRE,1,FALSE)),"PreAlerta",""))) -> PostAlerta | M19: =IF(ISNUMBER(A19),(IF(ISNUMBER(VLOOKUP(A19,KEYWORDS,1,FALSE)),"C/PalabrasClaves","S/PalabrasClaves")),"") -> S/PalabrasClaves | N19: =IF(ISNUMBER(SEARCH("TREATMENT", B19)), "4) Nuevos tratamientos", "") | P19: 2022 Oct 27 | Q19: Excluir | R19: =LEFT(P19,4) -> 2022 | S19: Oct
A20: 36262970 | B20: Changes in Respiratory Pathogens before and after the COVID-19 Pandemic (2018-2021) | C20: Kim KY, Kim JS, Lee YK, Kim GY, Jung BK. | D20: Biomed Res Int. 2022 Oct 10 | E20: Kim KY | F20: Biomed Res Int | G20: 2022 | H20: 44854 | I20: PMC9576381 | K20: 10.1155/2022/1324052 | L20: =IF(ISNUMBER(VLOOKUP(A20,EXCL,1,FALSE)),"Excluido",IF(ISNUMBER(VLOOKUP(A20,POST,1,FALSE)),"PostAlerta",IF(ISNUMBER(VLOOKUP(A20,PRE,1,FALSE)),"PreAlerta",""))) -> PostAlerta | M20: =IF(ISNUMBER(A20),(IF(ISNUMBER(VLOOKUP(A20,KEYWORDS,1,FALSE)),"C/PalabrasClaves","S/PalabrasClaves")),"") -> S/PalabrasClaves | N20: =IF(ISNUMBER(SEARCH("TREATMENT", B20)), "4) Nuevos tratamientos", "") | P20: 2022 Oct 10 | Q20: Excluir | R20: =LEFT(P20,4) -> 2022 | S20: Oct
A21: 36275016 | B21: Protein domain-dependent vesiculation of Lipoprotein A, a protein that is important in cell wall synthesis and fitness of the human respiratory pathogen Haemophilus influenzae | C21: Jalalvand F, Su YC, Manat G, Chernobrovkin A, Kadari M, Jonsson S, Janousková M, Rutishauser D, Semsey S, Løbner-Olesen A, Sandblad L, Flärdh K, Mengin-Lecreulx D, Zubarev RA, Riesbeck K. | D21: Front Cell Infect Microbiol. 2022 Oct 7 | E21: Jalalvand F | F21: Front Cell Infect Microbiol | G21: 2022 | H21: 44858 | I21: PMC9585305 | K21: 10.3389/fcimb.2022.984955 | L21: =IF(ISNUMBER(VLOOKUP(A21,EXCL,1,FALSE)),"Excluido",IF(ISNUMBER(VLOOKUP(A21,POST,1,FALSE)),"PostAlerta",IF(ISNUMBER(VLOOKUP(A21,PRE,1,FALSE)),"PreAlerta",""))) -> PostAlerta | M21: =IF(ISNUMBER(A21),(IF(ISNUMBER(VLOOKUP(A21,KEYWORDS,1,FALSE)),"C/PalabrasClaves","S/PalabrasClaves")),"") -> S/PalabrasClaves | N21: =IF(ISNUMBER(SEARCH("TREATMENT", B21)), "4) Nuevos tratamientos", "") | P21: 2022 Oct 7 | Q21: Excluir | R21: =LEFT(P21,4) -> 2022 | S21: Oct
A22: 34455901 | B22: Bacterial dacryoadenitis: clinical features, microbiology, and management of 45 cases, with a recent uptick in incidence | C22: Wai KM, Locascio JJ, Wolkow N. | D22: Orbit. 2022 Oct | E22: Wai KM | F22: Orbit | G22: 2022 | H22: 44438 | K22: 10.1080/01676830.2021.1966813 | L22: =IF(ISNUMBER(VLOOKUP(A22,EXCL,1,FALSE)),"Excluido",IF(ISNUMBER(VLOOKUP(A22,POST,1,FALSE)),"PostAlerta",IF(ISNUMBER(VLOOKUP(A22,PRE,1,FALSE)),"PreAlerta",""))) -> PostAlerta | M22: =IF(ISNUMBER(A22),(IF(ISNUMBER(VLOOKUP(A22,KEYWORDS,1,FALSE)),"C/PalabrasClaves","S/PalabrasClaves")),"") -> S/PalabrasClaves | N22: =IF(ISNUMBER(SEARCH("TREATMENT", B22)), "4) Nuevos tratamientos", "") | P22: 2022 Oct | Q22: Excluir | R22: =LEFT(P22,4) -> 2022 | S22: Oct
A23: 26318192 | B23: Comment on: Acquired macrolide resistance genes in Haemophilus influenzae? | C23: Roberts MC, No DB, Soge OO. | D23: J Antimicrob Chemother. 2015 Dec | E23: Roberts MC | F23: J Antimicrob Chemother | G23: 2015 | H23: 42247 | K23: 10.1093/jac/dkv258 | L23: =IF(ISNUMBER(VLOOKUP(A23,EXCL,1,FALSE)),"Excluido",IF(ISNUMBER(VLOOKUP(A23,POST,1,FALSE)),"PostAlerta",IF(ISNUMBER(VLOOKUP(A23,PRE,1,FALSE)),"PreAlerta",""))) -> PreAlerta | M23: =IF(ISNUMBER(A23),(IF(ISNUMBER(VLOOKUP(A23,KEYWORDS,1,FALSE)),"C/PalabrasClaves","S/PalabrasClaves")),"") -> C/PalabrasClaves | N23: 1) Reporte de cepas resistentes | P23: 2 Dec | R23: =LEFT(P23,4) -> 2 D | S23: Dec | T23: Comment on: Acquired macrolide resistance genes in Haemophilus influenzae? | U23: Yes | V23: No | W23: No | X23: Analyzes acquired resistance genes, key to managing macrolide-resistant strains.
A24: 36237430 | B24: Real-time multiple cross displacement amplification assay for rapid and sensitive detection of Haemophilus influenzae | C24: Sun C, Jia N, Huang X, Xiao F, Zhou J, Zhang Y, Fu J, Xu Z, Qu D, Cui X, Wang Y. | D24: Front Cell Infect Microbiol. 2022 Sep 27 | E24: Sun C | F24: Front Cell Infect Microbiol | G24: 2022 | H24: 44848 | I24: PMC9551287 | K24: 10.3389/fcimb.2022.1004183 | L24: =IF(ISNUMBER(VLOOKUP(A24,EXCL,1,FALSE)),"Excluido",IF(ISNUMBER(VLOOKUP(A24,POST,1,FALSE)),"PostAlerta",IF(ISNUMBER(VLOOKUP(A24,PRE,1,FALSE)),"PreAlerta",""))) -> PostAlerta | M24: =IF(ISNUMBER(A24),(IF(ISNUMBER(VLOOKUP(A24,KEYWORDS,1,FALSE)),"C/PalabrasClaves","S/PalabrasClaves")),"") -> S/PalabrasClaves | N24: =IF(ISNUMBER(SEARCH("TREATMENT", B24)), "4) Nuevos tratamientos", "") | P24: 2022 Sep 27 | Q24: Excluir | R24: =LEFT(P24,4) -> 2022 | S24: Sep
A25: 36211411 | B25: Evidence of maternal transfer of antigen-specific antibodies in serum and breast milk to infants at high-risk of S. pneumoniae and H. influenzae disease | C25: Martinovich KM, Seppanen EJ, Bleakley AS, Clark SL, Andrews RM, Richmond PC, Binks MJ, Thornton RB, Kirkham LS. | D25: Front Immunol. 2022 Sep 21 | E25: Martinovich KM | F25: Front Immunol | G25: 2022 | H25: 44844 | I25: PMC9535341 | K25: 10.3389/fimmu.2022.1005344 | L25: =IF(ISNUMBER(VLOOKUP(A25,EXCL,1,FALSE)),"Excluido",IF(ISNUMBER(VLOOKUP(A25,POST,1,FALSE)),"PostAlerta",IF(ISNUMBER(VLOOKUP(A25,PRE,1,FALSE)),"PreAlerta",""))) -> Excluido | M25: =IF(ISNUMBER(A25),(IF(ISNUMBER(VLOOKUP(A25,KEYWORDS,1,FALSE)),"C/PalabrasClaves","S/PalabrasClaves")),"") -> S/PalabrasClaves | N25: =IF(ISNUMBER(SEARCH("TREATMENT", B25)), "4) Nuevos tratamientos", "") | P25: 2022 Sep 21 | Q25: Excluir | R25: =LEFT(P25,4) -> 2022 | S25: Sep
A26: 24826882 | B26: Beware and be aware, haemophilus influenzae betalactamase-negative-ampicillin-resistant is not rare | C26: Abraham PS, Ledochowski S, Rulliat E, Mottard N, Friggeri A. | D26: Minerva Anestesiol. 2014 Nov | E26: Abraham PS | F26: Minerva Anestesiol | G26: 2014 | H26: 41775 | L26: =IF(ISNUMBER(VLOOKUP(A26,EXCL,1,FALSE)),"Excluido",IF(ISNUMBER(VLOOKUP(A26,POST,1,FALSE)),"PostAlerta",IF(ISNUMBER(VLOOKUP(A26,PRE,1,FALSE)),"PreAlerta",""))) -> PreAlerta | M26: =IF(ISNUMBER(A26),(IF(ISNUMBER(VLOOKUP(A26,KEYWORDS,1,FALSE)),"C/PalabrasClaves","S/PalabrasClaves")),"") -> C/PalabrasClaves | N26: 1) Reporte de cepas resistentes | P26: 2014 Nov | R26: =LEFT(P26,4) -> 2014 | S26: Nov | T26: Beware and be aware, haemophilus influenzae betalactamase-negative-ampicillin-resistant is not rare | U26: Yes | V26: No | W26: No | X26: Warns about the resistance of Haemophilus influenzae to ampicillin, highlighting its prevalence despite the absence of beta-lactamase.
A27: 35192786 | B27: Product review on the IMD serogroup B vaccine Bexsero® | C27: Deghmane AE, Taha MK. | D27: Hum Vaccin Immunother. 2022 Dec 31 | E27: Deghmane AE | F27: Hum Vaccin Immunother | G27: 2022 | H27: 44614 | I27: PMC8986181 | K27: 10.1080/21645515.2021.2020043 | L27: =IF(ISNUMBER(VLOOKUP(A27,EXCL,1,FALSE)),"Excluido",IF(ISNUMBER(VLOOKUP(A27,POST,1,FALSE)),"PostAlerta",IF(ISNUMBER(VLOOKUP(A27,PRE,1,FALSE)),"PreAlerta",""))) -> PostAlerta | M27: =IF(ISNUMBER(A27),(IF(ISNUMBER(VLOOKUP(A27,KEYWORDS,1,FALSE)),"C/PalabrasClaves","S/PalabrasClaves")),"") -> S/PalabrasClaves | N27: 3) Inmunización | P27: 2022 Dec 31 | Q27: Listo | R27: =LEFT(P27,4) -> 2022 | S27: Dec | T27: Bexsero® is a multicomponent vaccine composed of four major proteins of Neisseria meningitidis: the fHbp, NHBA, NadA and PorA. This vaccine was licensed against invasive meningococcal disease (IMD) due to serogroup B isolates. When administered alone, Bexsero® showed a safety profile similar to other childhood vaccines. It provides an excellent immunogenicity but that requires booster doses in infants and young children. Although the vaccine does not seem to impact on acquisition of carriage of serogroup B isolates, it confers protection against isolates of serogroup B harboring distinct but cross-reactive variants of fHbp, NadA and NHBA. Primary vaccination schemes in infancy underwent a rapid increase after a toddler booster suggesting an anamnestic response and the establishment of a memory response. As Bexsero® targets sub-capsular proteins that can be conserved regardless the capsule, the vaccine can be effective against non-B isolates such as isolates of serogroups W and X. | U27: No | V27: No | W27: Yes | X27: Because it describes the composition, efficacy, safety profile and immunological response of Bexsero®, a vaccine against invasive meningococcal disease caused by Neisseria meningitidis serogroup B, and its potential effectiveness against other serogroups through immunization directed at conserved subcapsular proteins
A28: 35108152 | B28: Surveillance on the adverse events following immunization with the pentavalent vaccine in Zhejiang, China | C28: Pan X, Lv H, Liang H, Wang Y, Shen L, Chen F, Chen Y, Hu Y. | D28: Hum Vaccin Immunother. 2022 Dec 31 | E28: Pan X | F28: Hum Vaccin Immunother | G28: 2022 | H28: 44594 | I28: PMC8986187 | K28: 10.1080/21645515.2021.2021711 | L28: =IF(ISNUMBER(VLOOKUP(A28,EXCL,1,FALSE)),"Excluido",IF(ISNUMBER(VLOOKUP(A28,POST,1,FALSE)),"PostAlerta",IF(ISNUMBER(VLOOKUP(A28,PRE,1,FALSE)),"PreAlerta",""))) -> PostAlerta | M28: =IF(ISNUMBER(A28),(IF(ISNUMBER(VLOOKUP(A28,KEYWORDS,1,FALSE)),"C/PalabrasClaves","S/PalabrasClaves")),"") -> S/PalabrasClaves | N28: 3) Inmunización | P28: 2022 Dec 31 | Q28: Revisar | R28: =LEFT(P28,4) -> 2022 | S28: Dec | T28: Objectives: The aim of this study is to describe the reporting rate of adverse events following immunization (AEFI) with pentavalent vaccine: diphtheria-pertussis-tetanus-poliomyelitis-Haemophilus influenzae type b (DPT-IPV/Hib), and to determine whether the reporting rate of AEFI following DPT-IPV/Hib was higher than the average level of the other vaccines. Methods: Review and describe the AEFI reported to national adverse event following immunization surveillance system (NAEFISS) in Zhejiang province from 2015 to 2020. Reporting rates of AEFI were calculated by age, city, severity of AEFI, categories of AEFI, and reaction categories. The data mining algorithm used in this study was reporting odds ratio (ROR). A value of ROR‑1.96SE >1 (standard error [SE]) was considered as positive signal. Results: NAEFISS received 5726 AEFI reports following DTP-IPV/Hib, with a reporting rate of 20.01/10000 doses. Of the reported AEFI, 202 were serious vaccine product-related reactions, including two cases of anaphylactic shock, five cases of Guillain Barre Syndrome (GBS) and two cases of acute disseminated encephalomyelitis. The reporting rate of fever/redness/induration was the highest among all the clinical diagnosis (14.97/10000 doses). The positive signals were obtained for allergic rash (ROR-1.96SE: 1.36), febrile convulsion (ROR-1.96SE: 1.32) and GBS (ROR-1.96SE: 1.16). Conclusion: The present findings bolstered that the DTP-IPV/Hib administered as the four-dose schedule was generally well tolerated in Chinese infants as we did not identify any new/unexpected safety concern from the NAEFISS during a six-year timespan. Keywords: AEFI (adverse events following immunization); DPT-IPV/Hib(diphtheria-pertussis-tetanus-poliomyelitis-Hib combined vaccine); safety; surveillance; vaccination. | U28: No | V28: No | W28: Yes | X28: Study on safety and adverse event reporting after vaccine administration key to immunization programs
A29: 34319865 | B29: Impact of pneumococcal conjugate vaccines on healthcare utilization and direct costs for otitis media in children ≤2 years of age in two Swedish regions | C29: Edmondson-Jones M, Dibbern T, Hultberg M, Anell B, Medin E, Feng Y, Talarico C. | D29: Hum Vaccin Immunother. 2022 Dec 31 | E29: Edmondson-Jones M | F29: Hum Vaccin Immunother | G29: 2022 | H29: 44405 | I29: PMC8920213 | K29: 10.1080/21645515.2021.1942712 | L29: =IF(ISNUMBER(VLOOKUP(A29,EXCL,1,FALSE)),"Excluido",IF(ISNUMBER(VLOOKUP(A29,POST,1,FALSE)),"PostAlerta",IF(ISNUMBER(VLOOKUP(A29,PRE,1,FALSE)),"PreAlerta",""))) -> PostAlerta | M29: =IF(ISNUMBER(A29),(IF(ISNUMBER(VLOOKUP(A29,KEYWORDS,1,FALSE)),"C/PalabrasClaves","S/PalabrasClaves")),"") -> S/PalabrasClaves | N29: 3) Inmunización | P29: 2022 Dec 31 | Q29: Listo | R29: =LEFT(P29,4) -> 2022 | S29: Dec | T29: In Sweden, the 7-valent pneumococcal conjugate vaccine (PCV7) was introduced in 2009 and replaced by the pneumococcal non-typeable Haemophilus influenzae protein D conjugate vaccine (PHiD-CV) or the 13- valent PCV (PCV13) from late 2009. We assessed the impact of PCVs on rates of antibiotic prescribing, tympanostomy tube placement (TTP), and healthcare resource utilization and direct costs of physician- diagnosed otitis media/acute otitis media (OM) in children ≤2 years of age living in Skåne (PCV7 then PHiD- CV) or Västra Götalandsregionen (VGR; PCV7 then PCV13). Retrospective cohort study using linked patient- level data from national and regional (Skåne and VGR) healthcare databases in Sweden from July 1, 2005, to December 31, 2013 (NCT02742753). Descriptive time-series analyses showed antibiotic prescriptions and TTP incidence declined after PHiD-CV/PCV13 introduction versus the pre-PCV period. The annualized mean frequencies of antibiotic use, primary care visits, outpatient visits, TTP and myringotomy procedures all decreased after PHiD-CV/PCV13 compared with pre-PCV cohorts. Annualized mean total OM-associated healthcare costs decreased in the PCV7 versus pre-PCV cohorts by 20.0% in Skåne and 10.2% in VGR, and further declined in the PHiD-CV and PCV13 cohorts (20.7% and 15.3%, respectively, relative to the PCV7 cohort), although the duration of PCV7 use differed between regions. Decreases in adjusted annualized cost ratios between cohorts per child susceptible to OM were statistically significant after PCV7 introduction and again with either PHiD-CV or PCV13 introduction in both regions. Following sequential PCV introduction, OM-related healthcare utilization and associated costs decreased in the study regions in Sweden. Plain language summary: What is the context?Otitis media is one of the most frequent reasons for healthcare visits and antibiotic use among young children. Although it is considered as a mild illness, the overall economic burden is substantial due to its high frequency.Otitis media can be caused by different bacteria including Streptococcus pneumoniae, which is also responsible for pneumonia and meningitis. Pneumococcal conjugate vaccines Prevenar (Pfizer Inc.), Synflorix (GSK), and Prevenar 13 (Pfizer Inc.) protect against pneumococcal diseases and reduce its occurrence.However, it is not known how the routine use of these vaccines may affect otitis media-related healthcare resources and costs.What is new?In this study, we assessed trends in rates of healthcare utilization and associated costs due to otitis media in young children before (2005-2008) and after (2009-2013) use of pneumococcal conjugate vaccines. The study was conducted in two Swedish regions; one used Prevenar then Synflorix, while the other used Prevenar then Prevenar 13.We found that compared to the period before pneumococcal conjugate vaccine implementation, the postpneumococcal conjugate vaccine period was associated with:What is the impact on current thinking?The use of pneumococcal conjugate vaccines effectively reduces healthcare utilization and resources associated with otitis mediaThis indirect effect on the reduction of otitis media burden provides further benefit to the implementation of pneumococcal vaccination. Keywords: Cost; Sweden; antibiotics; otitis media; pneumococcal conjugate vaccines. | U29: No | V29: No | W29: Yes | X29: This work is classified in immunization because it evaluates the impact of penumococcal vaccines on the reduction of infections and health resources in children.
A30: 33605846 | B30: Exploring the evidence behind the comparable impact of the pneumococcal conjugate vaccines PHiD-CV and PCV13 on overall pneumococcal disease | C30: Izurieta P, Nieto Guevara J. | D30: Hum Vaccin Immunother. 2022 Dec 31 | E30: Izurieta P | F30: Hum Vaccin Immunother | G30: 2022 | H30: 44246 | I30: PMC8920200 | K30: 10.1080/21645515.2021.1872341 | L30: =IF(ISNUMBER(VLOOKUP(A30,EXCL,1,FALSE)),"Excluido",IF(ISNUMBER(VLOOKUP(A30,POST,1,FALSE)),"PostAlerta",IF(ISNUMBER(VLOOKUP(A30,PRE,1,FALSE)),"PreAlerta",""))) -> PostAlerta | M30: =IF(ISNUMBER(A30),(IF(ISNUMBER(VLOOKUP(A30,KEYWORDS,1,FALSE)),"C/PalabrasClaves","S/PalabrasClaves")),"") -> S/PalabrasClaves | N30: 3) Inmunización | P30: 2022 Dec 31 | Q30: Listo | R30: =LEFT(P30,4) -> 2022 | S30: Dec | T30: The worldwide implementation of pneumococcal conjugate vaccines (PCVs) in children has reduced the overall pneumococcal disease burden. Two PCVs are widely available for infant vaccination: the pneumococcal non-typeable Haemophilus influenzae protein D conjugate vaccine (PHiD-CV) and the 13-valent PCV (PCV13). While these PCVs differ in serotype composition (PCV13 includes polysaccharides of serotypes 3, 6A and 19A; PHiD-CV does not), their impact on the overall pneumococcal disease burden in children is comparable. This commentary summarizes the evidence of comparability between PHiD-CV and PCV13 and explores why differences in serotype composition may not necessarily translate into a differential clinical impact. Both vaccines confer similarly high protection against disease caused by vaccine serotypes and lead to a partial replacement by non-vaccine serotypes. PHiD-CV does not protect against serotype 3 disease (not included in the vaccine) and PCV13's effect on this serotype has been inconsistent. PHiD-CV provides some cross-protection against disease caused by vaccine-related serotype 19A but neither vaccine has fully controlled 19A disease. While protection against 19A is higher for PCV13 than PHiD-CV, replacement by non-PCV13 serotypes in settings with a PCV13 program appears to compensate for this difference. This results in a similar residual overall disease burden with both vaccines. Keywords: PCV10; PCV13; PHiD-CV; Pneumococcal conjugate vaccine; children; invasive pneumococcal disease; otitis media; pneumonia; replacement; serotypes. | U30: No | V30: No | W30: Yes | X30: This work is classified in immunization because it analyzes and compares the effectiveness of two pneumococcal conjugate vaccines, focusing on their impact on disease reduction and protection in children.
A31: 36105805 | B31: The collectin SP-A and its trimeric recombinant fragment protect alveolar epithelial cells from the cytotoxic and proinflammatory effects of human cathelicidin in vitro | C31: de Tapia L, García-Fojeda B, Kronqvist N, Johansson J, Casals C. | D31: Front Immunol. 2022 Aug 29 | E31: de Tapia L | F31: Front Immunol | G31: 2022 | H31: 44819 | I31: PMC9464622 | K31: 10.3389/fimmu.2022.994328 | L31: =IF(ISNUMBER(VLOOKUP(A31,EXCL,1,FALSE)),"Excluido",IF(ISNUMBER(VLOOKUP(A31,POST,1,FALSE)),"PostAlerta",IF(ISNUMBER(VLOOKUP(A31,PRE,1,FALSE)),"PreAlerta",""))) -> PostAlerta | M31: =IF(ISNUMBER(A31),(IF(ISNUMBER(VLOOKUP(A31,KEYWORDS,1,FALSE)),"C/PalabrasClaves","S/PalabrasClaves")),"") -> S/PalabrasClaves | N31: =IF(ISNUMBER(SEARCH("TREATMENT", B31)), "4) Nuevos tratamientos", "") | P31: 2022 Aug 29 | Q31: Excluir | R31: =LEFT(P31,4) -> 2022 | S31: Aug
A32: 36081767 | B32: Biofilm aggregates and the host airway-microbial interface | C32: Hall-Stoodley L, McCoy KS. | D32: Front Cell Infect Microbiol. 2022 Aug 23 | E32: Hall-Stoodley L | F32: Front Cell Infect Microbiol | G32: 2022 | H32: 44813 | I32: PMC9445362 | K32: 10.3389/fcimb.2022.969326 | L32: =IF(ISNUMBER(VLOOKUP(A32,EXCL,1,FALSE)),"Excluido",IF(ISNUMBER(VLOOKUP(A32,POST,1,FALSE)),"PostAlerta",IF(ISNUMBER(VLOOKUP(A32,PRE,1,FALSE)),"PreAlerta",""))) -> Excluido | M32: =IF(ISNUMBER(A32),(IF(ISNUMBER(VLOOKUP(A32,KEYWORDS,1,FALSE)),"C/PalabrasClaves","S/PalabrasClaves")),"") -> S/PalabrasClaves | N32: =IF(ISNUMBER(SEARCH("TREATMENT", B32)), "4) Nuevos tratamientos", "") | P32: 2022 Aug 23 | Q32: Excluir | R32: =LEFT(P32,4) -> 2022 | S32: Aug
A33: 36051551 | B33: Gut microbiome characteristics of comorbid generalized anxiety disorder and functional gastrointestinal disease: Correlation with alexithymia and personality traits | C33: Guo X, Lin F, Yang F, Chen J, Cai W, Zou T. | D33: Front Psychiatry. 2022 Aug 16 | E33: Guo X | F33: Front Psychiatry | G33: 2022 | H33: 44806 | I33: PMC9424665 | K33: 10.3389/fpsyt.2022.946808 | L33: =IF(ISNUMBER(VLOOKUP(A33,EXCL,1,FALSE)),"Excluido",IF(ISNUMBER(VLOOKUP(A33,POST,1,FALSE)),"PostAlerta",IF(ISNUMBER(VLOOKUP(A33,PRE,1,FALSE)),"PreAlerta",""))) -> PostAlerta | M33: =IF(ISNUMBER(A33),(IF(ISNUMBER(VLOOKUP(A33,KEYWORDS,1,FALSE)),"C/PalabrasClaves","S/PalabrasClaves")),"") -> S/PalabrasClaves | N33: =IF(ISNUMBER(SEARCH("TREATMENT", B33)), "4) Nuevos tratamientos", "") | P33: 2022 Aug 16 | Q33: Excluir | R33: =LEFT(P33,4) -> 2022 | S33: Aug
A34: 35983167 | B34: The Microbiome in COPD: Emerging Potential for Microbiome-Targeted Interventions | C34: Millares L, Monso E. | D34: Int J Chron Obstruct Pulmon Dis. 2022 Aug 12 | E34: Millares L | F34: Int J Chron Obstruct Pulmon Dis | G34: 2022 | H34: 44792 | I34: PMC9380728 | K34: 10.2147/COPD.S371958 | L34: =IF(ISNUMBER(VLOOKUP(A34,EXCL,1,FALSE)),"Excluido",IF(ISNUMBER(VLOOKUP(A34,POST,1,FALSE)),"PostAlerta",IF(ISNUMBER(VLOOKUP(A34,PRE,1,FALSE)),"PreAlerta",""))) -> Excluido | M34: =IF(ISNUMBER(A34),(IF(ISNUMBER(VLOOKUP(A34,KEYWORDS,1,FALSE)),"C/PalabrasClaves","S/PalabrasClaves")),"") -> S/PalabrasClaves | N34: =IF(ISNUMBER(SEARCH("TREATMENT", B34)), "4) Nuevos tratamientos", "") | P34: 2022 Aug 12 | Q34: Excluir | R34: =LEFT(P34,4) -> 2022 | S34: Aug
A35: 36034696 | B35: Differentiation of otitis media-causing bacteria and biofilms via Raman spectroscopy and optical coherence tomography | C35: Locke AK, Zaki FR, Fitzgerald ST, Sudhir K, Monroy GL, Choi H, Won J, Mahadevan-Jansen A, Boppart SA. | D35: Front Cell Infect Microbiol. 2022 Aug 10 | E35: Locke AK | F35: Front Cell Infect Microbiol | G35: 2022 | H35: 44802 | I35: PMC9400059 | K35: 10.3389/fcimb.2022.869761 | L35: =IF(ISNUMBER(VLOOKUP(A35,EXCL,1,FALSE)),"Excluido",IF(ISNUMBER(VLOOKUP(A35,POST,1,FALSE)),"PostAlerta",IF(ISNUMBER(VLOOKUP(A35,PRE,1,FALSE)),"PreAlerta",""))) -> PostAlerta | M35: =IF(ISNUMBER(A35),(IF(ISNUMBER(VLOOKUP(A35,KEYWORDS,1,FALSE)),"C/PalabrasClaves","S/PalabrasClaves")),"") -> S/PalabrasClaves | N35: =IF(ISNUMBER(SEARCH("TREATMENT", B35)), "4) Nuevos tratamientos", "") | P35: 2022 Aug 10 | Q35: Excluir | R35: =LEFT(P35,4) -> 2022 | S35: Aug
A36: 36032729 | B36: Bioproduction of propionic acid using levulinic acid by engineered Pseudomonas putida | C36: Tiwari R, Sathesh-Prabu C, Lee SK. | D36: Front Bioeng Biotechnol. 2022 Aug 10 | E36: Tiwari R | F36: Front Bioeng Biotechnol | G36: 2022 | H36: 44802 | I36: PMC9399607 | K36: 10.3389/fbioe.2022.939248 | L36: =IF(ISNUMBER(VLOOKUP(A36,EXCL,1,FALSE)),"Excluido",IF(ISNUMBER(VLOOKUP(A36,POST,1,FALSE)),"PostAlerta",IF(ISNUMBER(VLOOKUP(A36,PRE,1,FALSE)),"PreAlerta",""))) -> PostAlerta | M36: =IF(ISNUMBER(A36),(IF(ISNUMBER(VLOOKUP(A36,KEYWORDS,1,FALSE)),"C/PalabrasClaves","S/PalabrasClaves")),"") -> S/PalabrasClaves | N36: =IF(ISNUMBER(SEARCH("TREATMENT", B36)), "4) Nuevos tratamientos", "") | P36: 2022 Aug 10 | Q36: Excluir | R36: =LEFT(P36,4) -> 2022 | S36: Aug
A37: 35947593 | B37: Childhood meningitis in rural Gambia: 10 years of population-based surveillance | C37: Ikumapayi UN, Hill PC, Hossain I, Olatunji Y, Ndiaye M, Badji H, Manjang A, Salaudeen R, Ceesay L, Adegbola RA, Greenwood BM, Mackenzie GA. | D37: PLoS One. 2022 Aug 10 | E37: Ikumapayi UN | F37: PLoS One | G37: 2022 | H37: 44783 | I37: PMC9365145 | K37: 10.1371/journal.pone.0265299 | L37: =IF(ISNUMBER(VLOOKUP(A37,EXCL,1,FALSE)),"Excluido",IF(ISNUMBER(VLOOKUP(A37,POST,1,FALSE)),"PostAlerta",IF(ISNUMBER(VLOOKUP(A37,PRE,1,FALSE)),"PreAlerta",""))) -> PostAlerta | M37: =IF(ISNUMBER(A37),(IF(ISNUMBER(VLOOKUP(A37,KEYWORDS,1,FALSE)),"C/PalabrasClaves","S/PalabrasClaves")),"") -> S/PalabrasClaves | N37: =IF(ISNUMBER(SEARCH("TREATMENT", B37)), "4) Nuevos tratamientos", "") | P37: 2022 Aug 10 | Q37: Excluir | R37: =LEFT(P37,4) -> 2022 | S37: Aug
A38: 36043149 | B38: Common Pathogens and Drug Resistance of Neonatal Pneumonia with New Multichannel Sensor | C38: Dong X, Zhou P, Zhu G. | D38: Contrast Media Mol Imaging. 2022 Aug 8 | E38: Dong X | F38: Contrast Media Mol Imaging | G38: 2022 | H38: 44804 | I38: PMC9377937 | K38: 10.1155/2022/2208636 | L38: =IF(ISNUMBER(VLOOKUP(A38,EXCL,1,FALSE)),"Excluido",IF(ISNUMBER(VLOOKUP(A38,POST,1,FALSE)),"PostAlerta",IF(ISNUMBER(VLOOKUP(A38,PRE,1,FALSE)),"PreAlerta",""))) -> PostAlerta | M38: =IF(ISNUMBER(A38),(IF(ISNUMBER(VLOOKUP(A38,KEYWORDS,1,FALSE)),"C/PalabrasClaves","S/PalabrasClaves")),"") -> C/PalabrasClaves | N38: 1) Reporte de cepas resistentes | P38: 2022 Aug 8 | Q38: Excluir | R38: =LEFT(P38,4) -> 2022 | S38: Aug
A39: 35881575 | B39: Occurrence of influenza and bacterial infections in cancer patients receiving radiotherapy in Ghana | C39: Arjarquah AK, Obodai E, Anie HA, Osei MA, Odoom JK, Bonney JHK, Behene E, Kotey EN, Aboagye J, Nyarko SO, Bentum J, Yeboah C, Kumordjie S, Agbodzi B, Attiku K, Mawuli G, Letizia A, Ampofo WK, Quaye O. | D39: PLoS One. 2022 Jul 26 | E39: Arjarquah AK | F39: PLoS One | G39: 2022 | H39: 44768 | I39: PMC9321433 | K39: 10.1371/journal.pone.0271877 | L39: =IF(ISNUMBER(VLOOKUP(A39,EXCL,1,FALSE)),"Excluido",IF(ISNUMBER(VLOOKUP(A39,POST,1,FALSE)),"PostAlerta",IF(ISNUMBER(VLOOKUP(A39,PRE,1,FALSE)),"PreAlerta",""))) -> PostAlerta | M39: =IF(ISNUMBER(A39),(IF(ISNUMBER(VLOOKUP(A39,KEYWORDS,1,FALSE)),"C/PalabrasClaves","S/PalabrasClaves")),"") -> S/PalabrasClaves | N39: =IF(ISNUMBER(SEARCH("TREATMENT", B39)), "4) Nuevos tratamientos", "") | P39: 2022 Jul 26 | Q39: Excluir | R39: =LEFT(P39,4) -> 2022 | S39: Jul
A40: 36578495 | B40: Inhibition of the different complement pathways has varying impacts on the serum bactericidal activity and opsonophagocytosis against Haemophilus influenzae type b | C40: Muri L, Schubart A, Thorburn C, Zamurovic N, Holbro T, Kammüller M, Pluschke G, Ispasanie E. | D40: Front Immunol. 2022 Dec 12 | E40: Muri L | F40: Front Immunol | G40: 2022 | H40: 44924 | I40: PMC9791579 | K40: 10.3389/fimmu.2022.1020580 | L40: =IF(ISNUMBER(VLOOKUP(A40,EXCL,1,FALSE)),"Excluido",IF(ISNUMBER(VLOOKUP(A40,POST,1,FALSE)),"PostAlerta",IF(ISNUMBER(VLOOKUP(A40,PRE,1,FALSE)),"PreAlerta",""))) -> PostAlerta | M40: =IF(ISNUMBER(A40),(IF(ISNUMBER(VLOOKUP(A40,KEYWORDS,1,FALSE)),"C/PalabrasClaves","S/PalabrasClaves")),"") -> C/PalabrasClaves | N40: 3) Inmunización | P40: 2022 Dec 12 | Q40: Revisar | R40: =LEFT(P40,4) -> 2022 | S40: Dec | T40: Defense against Haemophilus influenzae type b (Hib) is dependent on antibodies and complement, which mediate both serum bactericidal activity (SBA) and opsonophagocytosis. Here we evaluated the influence of capsule-specific antibodies and complement inhibitors targeting the central component C3, the alternative pathway (AP; fB, fD), the lectin pathway (LP; MASP-2) and the terminal pathway (C5) on both effector functions. Findings may be relevant for the treatment of certain diseases caused by dysregulation of the complement system, where inhibitors of complement factors C3 or C5 are used. Inhibitors against other complement components are being evaluated as potential alternative treatment options that may carry a reduced risk of infection by encapsulated bacteria. Serum and reconstituted blood of healthy adults were tested for bactericidal activity before and after vaccination with the Hib capsule-conjugate vaccine ActHIB. Most sera had bactericidal activity prior to vaccination, but vaccination significantly enhanced SBA titers. Independently of the vaccination status, both C3 and C5 inhibition abrogated SBA, whereas inhibition of the LP had no effect. AP inhibition had a major inhibitory effect on SBA of pre- vaccination serum, but vaccination mitigated this inhibition for all disease isolates tested. Despite this, SBA-mediated killing of some Hib isolates remained retarded. Even for the most serum-resistant isolate, SBA was the dominating defense mechanism in reconstituted whole blood, as addition of blood cells to the serum did not enhance bacterial killing. Limited Fc receptor-mediated opsonophagocytosis was unmasked when bacterial killing by the membrane attack complex was blocked. In the presence of C3 or C5 inhibitors, addition of post-vaccination, but not of pre-vaccination serum to the blood cells triggered opsonophagocytosis, leading to suppression of bacterial multiplication. Taken together, our data indicate that for host defense against Hib, killing by SBA is more efficient than by blood cell opsonophagocytosis. However, additional defense mechanisms, such as bacterial clearance by spleen and liver, may play an important role in preventing Hib-mediated sepsis, in particular for Hib isolates with increased serum-resistance. Results indicate potentially improved safety profile of AP inhibitors over C3 and C5 inhibitors as alternative therapeutic agents in patients with increased susceptibility to Hib infection. Keywords: Haemophilus influenzae type b; alternative pathway (AP); complement inhibitors; immunotherapy; opsonophagocytosis; serum bactericidal activity (SBA); vaccination. | U40: No | V40: No | W40: Yes | X40: This work is classified in immunization because it analyzes how vaccination with Hib enhances the immune response, potentiating the antibody- and complement-mediated bactericidal activity against Haemophilus influenzae type b.
A41: 35935372 | B41: Intrapleural injection of urokinase in the treatment of acute Haemophilus influenza empyema in children: A case report and literature review | C41: Yang L, Zhu Y, Wu G. | D41: Front Pediatr. 2022 Jul 22 | E41: Yang L | F41: Front Pediatr | G41: 2022 | H41: 44781 | I41: PMC9352951 | K41: 10.3389/fped.2022.882005 | L41: =IF(ISNUMBER(VLOOKUP(A41,EXCL,1,FALSE)),"Excluido",IF(ISNUMBER(VLOOKUP(A41,POST,1,FALSE)),"PostAlerta",IF(ISNUMBER(VLOOKUP(A41,PRE,1,FALSE)),"PreAlerta",""))) -> PostAlerta | M41: =IF(ISNUMBER(A41),(IF(ISNUMBER(VLOOKUP(A41,KEYWORDS,1,FALSE)),"C/PalabrasClaves","S/PalabrasClaves")),"") -> S/PalabrasClaves | P41: 2022 Jul 22 | R41: =LEFT(P41,4) -> 2022 | S41: Jul
A42: 36530676 | B42: Molecular epidemiology and antimicrobial resistance of Haemophilus influenzae in Guiyang, Guizhou, China | C42: Zhou Y, Wang Y, Cheng J, Zhao X, Liang Y, Wu J. | D42: Front Public Health. 2022 Dec 1 | E42: Zhou Y | F42: Front Public Health | G42: 2022 | H42: 44914 | I42: PMC9751421 | K42: 10.3389/fpubh.2022.947051 | L42: =IF(ISNUMBER(VLOOKUP(A42,EXCL,1,FALSE)),"Excluido",IF(ISNUMBER(VLOOKUP(A42,POST,1,FALSE)),"PostAlerta",IF(ISNUMBER(VLOOKUP(A42,PRE,1,FALSE)),"PreAlerta",""))) -> PostAlerta | M42: =IF(ISNUMBER(A42),(IF(ISNUMBER(VLOOKUP(A42,KEYWORDS,1,FALSE)),"C/PalabrasClaves","S/PalabrasClaves")),"") -> C/PalabrasClaves | N42: 1) Reporte de cepas resistentes | P42: 2022 Dec 1 | Q42: Listo | R42: =LEFT(P42,4) -> 2022 | S42: Dec | T42: Background: The widespread use of antimicrobials and Haemophilus influenzae type b (Hib) vaccine worldwide has altered the epidemiological patterns of invasive H. influenzae. Nonetheless, little is currently known on the epidemiological characteristics of H. influenzae in Guiyang, Guizhou, China. Objective: To determine the serotype distribution, antimicrobial resistance and Multilocus Sequence Typing (MLST) of H. influenzae in hospitalized patients in Guiyang City. Methods: A total of 196 clinical isolates from hospitalized patients were collected. Serotypes were determined according to the specific capsule gene, bexA, amplified by PCR. According to the guidelines of Clinical and Laboratory Standards Institute (CLSI) 2020 drug susceptibility tested, and the results determined. The chromogenic cephalosporin nitrocefin method was used to detect β-lactamase production, β-lactamase negative, ampicillin-resistant (BLNAR) strains were detected by PCR amplification and sequencing of the penicillin-binding protein 3 (PBP3) locus of ftsI. Multilocus Sequence Typing was performed for molecular typing. Results: All isolates studied were non-typeable H. influenzae (NTHi). Most patients originated from the pediatrics department (78.6%, 154/196), and suffered from lung with respiratory tract infection (pneumonia and bronchitis, 68.4%, 134/196). The resistance rates of ampicillin, cefaclor and azithromycin were 71.4% (140/196), 36.7% (72/196) and 34.2% (67/196), respectively. 40.3% (79/196) of strains were β-lactamase positive ampicillin-resistant (BLPAR). All BLPAR carried the TEM-1 gene. 9.2% (18/196) were β-lactamase negative ampicillin-resistant strains (BLNAR). The PBP3 mutation was detected in the ampicillin-resistant strains (n = 113), of which 18 belonged to group IIa. A total of 49 sequence types (ST) and 23 clonal complexes (CC) were detected, among which CC107 (ST107, n = 27; ST1002, n = 5; ST1218, n = 5) was the most frequent clonal complexes. BLPAR isolates mostly belonged to ST107 (20/79), while BLNAR was predominantly distributed in ST12 (5/18). Conclusion: H. influenzae infections are predominately caused by genetically diverse NTHi among hospitalized patients in Guiyang. The prevalence of β-lactamase production and PBP3 mutation may contribute to the high local ampicillin resistance rate. Keywords: Haemophilus influenzae; antimicrobial resistance; ftsI gene; molecular epidemiology; multilocus sequence type | U42: Yes | V42: No | W42: No | X42: Analyzes resistance, genes and strain distribution, focused on clinical epidemiology, not on vaccine effects or immune responses.
A43: 36466507 | B43: Parental preference for Haemophilus influenzae type b vaccination in Zhejiang Province, China: A discrete choice experiment | C43: Wang X, Feng Y, Zhang Q, Ye L, Cao M, Liu P, Liu S, Li S, Zhang J. | D43: Front Public Health. 2022 Nov 2 | E43: Wang X | F43: Front Public Health | G43: 2022 | H43: 44900 | I43: PMC9710483 | K43: 10.3389/fpubh.2022.967693 | L43: =IF(ISNUMBER(VLOOKUP(A43,EXCL,1,FALSE)),"Excluido",IF(ISNUMBER(VLOOKUP(A43,POST,1,FALSE)),"PostAlerta",IF(ISNUMBER(VLOOKUP(A43,PRE,1,FALSE)),"PreAlerta",""))) -> PostAlerta | M43: =IF(ISNUMBER(A43),(IF(ISNUMBER(VLOOKUP(A43,KEYWORDS,1,FALSE)),"C/PalabrasClaves","S/PalabrasClaves")),"") -> S/PalabrasClaves | N43: 3) Inmunización | P43: 2022 Nov 2 | Q43: Listo | R43: =LEFT(P43,4) -> 2022 | S43: Nov | T43: Background: China is the only country in the world that has not included the Haemophilus influenzae type b (Hib) vaccine in its National Immunization Program, making it more difficult to eliminate Hib-related diseases through Hib vaccination. It is necessary to study parental preferences for Hib vaccination to optimize vaccine promotion strategies in China. Objective: This study aimed to investigate Chinese parental preference for five attributes of Hib vaccination, i.e., the place of origin, effectiveness, adverse event, doctors' recommendation, and the price of full vaccination when making a decision to vaccinate their children under 2 years old. Methods: A cross-sectional survey was conducted in two cities in Zhejiang Province from November to December in 2020 using a discrete choice experiment (DCE). A mixed logit model was used to estimate participating parents' preference for Hib vaccination attributes included in the DCE. Subgroup analysis and probability analysis were also conducted to capture the heterogeneity and trade-off of parental preference for Hib vaccination. Results: Data from 6,168 observations were included in the analyses. Parents of children are, on average, more likely to voice a positive preference for Hib vaccination. Such attributes of Hib vaccination as effectiveness and doctor's recommendation have a significant positive influence on parents' preference for Hib vaccination, while imported vaccines, adverse events, and the price of full vaccination have a significant negative influence on parents' preference. Parents with different demographic characteristics also existed heterogeneities in preference for Hib vaccination. Parents will make a trade-off on price if the Hib vaccine has a good performance on effectiveness and safety. Conclusion: The study found that, regardless of the place of origin of the Hib vaccine, parents with children under 2 years old prefer to compromise on price if the vaccine has a better effectiveness and safety profile. A proactive recommendation from doctors would strengthen their willingness for Hib vaccination. These findings help aid the development of communication strategies with parents for Hib vaccination in China. Keywords: Chinese parents; Hib vaccination; discrete choice experiment; immunization policy; mixed logit model; parental preference. | U43: No | V43: No | W43: Yes | X43: Informs on the preference or not of parents for the use of the vaccine against Haemophilus influenzae type b (Hib) in children under 2 years of age.
A44: 36170255 | B44: Streptococcus pyogenes can support or inhibit growth of Haemophilus influenzae by supplying or restricting extracellular NAD | C44: Lee H, Edgar RJ, Lichtenstein IJ, Velarde JJ, Korotkova N, Wessels MR. | D44: PLoS One. 2022 Sep 28 | E44: Lee H | F44: PLoS One | G44: 2022 | H44: 44832 | I44: PMC9518897 | K44: 10.1371/journal.pone.0270697 | L44: =IF(ISNUMBER(VLOOKUP(A44,EXCL,1,FALSE)),"Excluido",IF(ISNUMBER(VLOOKUP(A44,POST,1,FALSE)),"PostAlerta",IF(ISNUMBER(VLOOKUP(A44,PRE,1,FALSE)),"PreAlerta",""))) -> PostAlerta | M44: =IF(ISNUMBER(A44),(IF(ISNUMBER(VLOOKUP(A44,KEYWORDS,1,FALSE)),"C/PalabrasClaves","S/PalabrasClaves")),"") -> S/PalabrasClaves | N44: 1) Reporte de cepas resistentes | P44: 2022 Sep 28 | Q44: Listo | R44: =LEFT(P44,4) -> 2022 | S44: Sep | T44: Nicotinamide adenine dinucleotide (NAD+) is an essential co-factor for cellular metabolism and serves as a substrate in enzymatic processes. NAD+ is produced by de novo synthesis or salvage pathways in nearly all bacterial species. Haemophilus influenzae lacks the capacity for de novo synthesis, so it is dependent on import of NAD+ from the external environment or salvage biosynthetic pathways for recycling of NAD+ precursors and breakdown products. However, the actual sources of NAD+ utilized by H. influenzae in the respiratory tract are not well defined. In this study, we found that a variety of bacteria, including species found in the upper airway of humans, released NAD+ that was readily detectable in extracellular culture fluid, and which supported growth of H. influenzae in vitro. By contrast, certain strains of Streptococcus pyogenes (group A streptococcus or GAS) inhibited growth of H. influenzae in vitro by secreting NAD+-glycohydrolase (NADase), which degraded extracellular NAD+. Conversely, GAS strains that lacked enzymatically active NADase released extracellular NAD+, which could support H. influenzae growth. Our results suggest that many bacterial species, including normal flora of the upper airway, release NAD+ into the environment. GAS is distinctive in its ability to both release and degrade NAD+. Thus, colonization of the airway with H. influenzae may be promoted or restricted by co-colonization with GAS in a strain-specific manner that depends, respectively, on release of NAD+ or secretion of active NADase. We suggest that, in addition to its role as a cytotoxin for host cells, NADase may serve a separate function by restricting growth of H. influenzae in the human respiratory tract. | U44: No | V44: No | W44: No | X44: Does not report findings on novel strains or propose a therapy. It is a study on ecological and biochemical mechanisms in clinical microbiology.
A45: 35903351 | B45: Essential Role of the Innate Immune Adaptor RIP2 in the Response to Otitis Media | C45: Kurabi A, Lee J, Pak K, Leichtle A, Ryan AF. | D45: Front Genet. 2022 Jul 12 | E45: Kurabi A | F45: Front Genet | G45: 2022 | H45: 44771 | I45: PMC9315102 | K45: 10.3389/fgene.2022.893085 | L45: =IF(ISNUMBER(VLOOKUP(A45,EXCL,1,FALSE)),"Excluido",IF(ISNUMBER(VLOOKUP(A45,POST,1,FALSE)),"PostAlerta",IF(ISNUMBER(VLOOKUP(A45,PRE,1,FALSE)),"PreAlerta",""))) -> PostAlerta | M45: =IF(ISNUMBER(A45),(IF(ISNUMBER(VLOOKUP(A45,KEYWORDS,1,FALSE)),"C/PalabrasClaves","S/PalabrasClaves")),"") -> S/PalabrasClaves | N45: =IF(ISNUMBER(SEARCH("TREATMENT", B45)), "4) Nuevos tratamientos", "") | P45: 2022 Jul 12 | Q45: Excluir | R45: =LEFT(P45,4) -> 2022 | S45: Jul
A46: 36107979 | B46: Haemophilus influenzae serotype b seroprevalence in central Lao PDR before and after vaccine introduction | C46: Hefele L, Lai J, Vilivong K, Bounkhoun T, Chanthaluanglath V, Chanthongthip A, Balloch A, Black AP, Hübschen JM, Russell FM, Muller CP. | D46: PLoS One. 2022 Sep 15 | E46: Hefele L | F46: PLoS One | G46: 2022 | H46: 44819 | I46: PMC9477263 | K46: 10.1371/journal.pone.0274558 | L46: =IF(ISNUMBER(VLOOKUP(A46,EXCL,1,FALSE)),"Excluido",IF(ISNUMBER(VLOOKUP(A46,POST,1,FALSE)),"PostAlerta",IF(ISNUMBER(VLOOKUP(A46,PRE,1,FALSE)),"PreAlerta",""))) -> PostAlerta | M46: =IF(ISNUMBER(A46),(IF(ISNUMBER(VLOOKUP(A46,KEYWORDS,1,FALSE)),"C/PalabrasClaves","S/PalabrasClaves")),"") -> S/PalabrasClaves | N46: 3) Inmunización | P46: 2022 Sep 15 | Q46: Listo | R46: =LEFT(P46,4) -> 2022 | S46: Sep | T46: Introduction: Vaccination has dramatically reduced invasive Haemophilus influenzae type b (Hib) disease worldwide. Hib vaccination was introduced in the Lao PDR in 2009, as part of the pentavalent vaccine. To contribute to the understanding of the epidemiology of Hib in Lao PDR and the protection levels before and after the introduction of the vaccination, we tested serum samples from existing cohorts of vaccine age-eligible children and unvaccinated adolescents for antibodies against Hib. Methods: Serum samples from 296 adolescents born before vaccine introduction and from 1017 children under 5 years (vaccinated and unvaccinated) were tested for anti-Hib antibodies by ELISA. Bivariate analyses were performed to investigate factors associated with long-term protection. Results: The vast majority of all participants showed evidence of short- (42.7%) or long-term (56.1%) protection against Hib. Almost all of the unvaccinated adolescents had antibody titers indicating short-term protection and almost half (45.6%) were long-term protected. Nearly all children (>99.0%) were at least short-term protected, even those that were unvaccinated or whose vaccination status was unknown. Among vaccinated children, participants vaccinated more than 1 or 2 years ago and with a mid-upper arm circumference z-score < -2 were less likely to be long-term protected. Discussion: Nearly all adolescents born before the introduction of Hib vaccination in the Lao PDR had antibody titers corresponding to at least short-term protection, indicating a high burden of Hib disease at that time. After vaccine introduction, all but four children (>99%) showed at least short-term protection. Possible explanations for the proportion of protected, yet apparently unvaccinated children, may be past infections, cross-reacting antibodies or faulty vaccination documentation. Our results highlight the need for robust surveillance and reporting of invasive Hib disease to determine the burden of disease despite vaccination. | U46: No | V46: No | W46: Yes | X46: Evaluates Hib vaccine coverage in Laos, antibody levels and immune protection in different groups after the introduction of vaccination.
A47: 35836804 | B47: Essential role of IL-17 in acute exacerbation of pulmonary fibrosis induced by non-typeable Haemophilus influenzae | C47: Chen S, Zhang X, Yang C, Wang S, Shen H. | D47: Theranostics. 2022 Jul 4 | E47: Chen S | F47: Theranostics | G47: 2022 | H47: 44757 | I47: PMC9274745 | K47: 10.7150/thno.74809 | L47: =IF(ISNUMBER(VLOOKUP(A47,EXCL,1,FALSE)),"Excluido",IF(ISNUMBER(VLOOKUP(A47,POST,1,FALSE)),"PostAlerta",IF(ISNUMBER(VLOOKUP(A47,PRE,1,FALSE)),"PreAlerta",""))) -> PostAlerta | M47: =IF(ISNUMBER(A47),(IF(ISNUMBER(VLOOKUP(A47,KEYWORDS,1,FALSE)),"C/PalabrasClaves","S/PalabrasClaves")),"") -> S/PalabrasClaves | N47: =IF(ISNUMBER(SEARCH("TREATMENT", B47)), "4) Nuevos tratamientos", "") | P47: 2022 Jul 4 | Q47: Revisar | R47: =LEFT(P47,4) -> 2022 | S47: Jul
A48: 35183590 | B48: Recent advances and future perspectives on carbohydrate-based cancer vaccines and therapeutics | C48: Sorieul C, Papi F, Carboni F, Pecetta S, Phogat S, Adamo R. | D48: Pharmacol Ther. 2022 Jul | E48: Sorieul C | F48: Pharmacol Ther | G48: 2022 | H48: 44612 | K48: 10.1016/j.pharmthera.2022.108158 | L48: =IF(ISNUMBER(VLOOKUP(A48,EXCL,1,FALSE)),"Excluido",IF(ISNUMBER(VLOOKUP(A48,POST,1,FALSE)),"PostAlerta",IF(ISNUMBER(VLOOKUP(A48,PRE,1,FALSE)),"PreAlerta",""))) -> Excluido | M48: =IF(ISNUMBER(A48),(IF(ISNUMBER(VLOOKUP(A48,KEYWORDS,1,FALSE)),"C/PalabrasClaves","S/PalabrasClaves")),"") -> S/PalabrasClaves | N48: =IF(ISNUMBER(SEARCH("TREATMENT", B48)), "4) Nuevos tratamientos", "") | P48: 2022 Jul | Q48: Excluir | R48: =LEFT(P48,4) -> 2022 | S48: Jul
A49: 35167860 | B49: Managing Pulmonary Infection in Adults With Cystic Fibrosis: Adult Cystic Fibrosis Series | C49: Green HD, Jones AM. | D49: Chest. 2022 Jul | E49: Green HD | F49: Chest | G49: 2022 | H49: 44607 | K49: 10.1016/j.chest.2022.02.007 | L49: =IF(ISNUMBER(VLOOKUP(A49,EXCL,1,FALSE)),"Excluido",IF(ISNUMBER(VLOOKUP(A49,POST,1,FALSE)),"PostAlerta",IF(ISNUMBER(VLOOKUP(A49,PRE,1,FALSE)),"PreAlerta",""))) -> Excluido | M49: =IF(ISNUMBER(A49),(IF(ISNUMBER(VLOOKUP(A49,KEYWORDS,1,FALSE)),"C/PalabrasClaves","S/PalabrasClaves")),"") -> S/PalabrasClaves | N49: =IF(ISNUMBER(SEARCH("TREATMENT", B49)), "4) Nuevos tratamientos", "") | P49: 2022 Jul | Q49: Excluir | R49: =LEFT(P49,4) -> 2022 | S49: Jul
A50: 33682584 | B50: A systematic literature review of economic evaluations of pneumococcal conjugate vaccines in east and southeast Asia (2006-2019) | C50: Wang BC, Chaiyakunapruk N, Zhu S, Babigumira JB, Furnback W, Chitale R, Gamil A, Zhao K, Wasserman M. | D50: Expert Rev Vaccines. 2022 Jul | E50: Wang BC | F50: Expert Rev Vaccines | G50: 2022 | H50: 44263 | K50: 10.1080/14760584.2021.1894933 | L50: =IF(ISNUMBER(VLOOKUP(A50,EXCL,1,FALSE)),"Excluido",IF(ISNUMBER(VLOOKUP(A50,POST,1,FALSE)),"PostAlerta",IF(ISNUMBER(VLOOKUP(A50,PRE,1,FALSE)),"PreAlerta",""))) -> Excluido | M50: =IF(ISNUMBER(A50),(IF(ISNUMBER(VLOOKUP(A50,KEYWORDS,1,FALSE)),"C/PalabrasClaves","S/PalabrasClaves")),"") -> S/PalabrasClaves | N50: =IF(ISNUMBER(SEARCH("TREATMENT", B50)), "4) Nuevos tratamientos", "") | P50: 2022 Jul | Q50: Excluir | R50: =LEFT(P50,4) -> 2022 | S50: Jul
A51: 36159837 | B51: Cooperative action of SP-A and its trimeric recombinant fragment with polymyxins against Gram-negative respiratory bacteria | C51: Coya JM, Fraile-Ágreda V, de Tapia L, García-Fojeda B, Sáenz A, Bengoechea JA, Kronqvist N, Johansson J, Casals C. | D51: Front Immunol. 2022 Sep 7 | E51: Coya JM | F51: Front Immunol | G51: 2022 | H51: 44830 | I51: PMC9493720 | K51: 10.3389/fimmu.2022.927017 | L51: =IF(ISNUMBER(VLOOKUP(A51,EXCL,1,FALSE)),"Excluido",IF(ISNUMBER(VLOOKUP(A51,POST,1,FALSE)),"PostAlerta",IF(ISNUMBER(VLOOKUP(A51,PRE,1,FALSE)),"PreAlerta",""))) -> PostAlerta | M51: =IF(ISNUMBER(A51),(IF(ISNUMBER(VLOOKUP(A51,KEYWORDS,1,FALSE)),"C/PalabrasClaves","S/PalabrasClaves")),"") -> C/PalabrasClaves | N51: 2) Nuevos tratamientos | P51: 2022 Sep 7 | Q51: Listo | R51: =LEFT(P51,4) -> 2022 | S51: Sep | T51: The exploration of therapies combining antimicrobial lung proteins and conventional antibiotics is important due to the growing problem of multidrug-resistant bacteria. The aim of this study was to investigate whether human SP-A and a recombinant trimeric fragment (rfhSP-A) have cooperative antimicrobial activity with antibiotics against pathogenic Gram-negative bacteria. We found that SP-A bound the cationic peptide polymyxin B (PMB) with an apparent dissociation constant (K D) of 0.32 ± 0.04 µM. SP-A showed synergistic microbicidal activity with polymyxin B and E, but not with other antibiotics, against three SP-A-resistant pathogenic bacteria: Klebsiella pneumoniae, non-typable Haemophilus influenzae (NTHi), and Pseudomonas aeruginosa. SP-A was not able to bind to K. pneumoniae, NTHi, or to mutant strains thereof expressing long-chain lipopolysaccharides (or lipooligosaccharides) and/or polysaccharide capsules. In the presence of PMB, SP-A induced the formation of SP-A/PMB aggregates that enhance PMB-induced bacterial membrane permeabilization. Furthermore, SP-A bound to a molecular derivative of PMB lacking the acyl chain (PMBN) with a K D of 0.26 ± 0.02 μM, forming SP-A/PMBN aggregates. PMBN has no bactericidal activity but can bind to the outer membrane of Gram-negative bacteria. Surprisingly, SP-A and PMBN showed synergistic bactericidal activity against Gram-negative bacteria. Unlike native supratrimeric SP-A, the trimeric rfhSP-A fragment had small but significant direct bactericidal activity against K. pneumoniae, NTHi, and P. aeruginosa. rfhSP-A did not bind to PMB under physiological conditions but acted additively with PMB and other antibiotics against these pathogenic bacteria. In summary, our results significantly improve our understanding of the antimicrobial actions of SP-A and its synergistic action with PMB. A peptide based on SP-A may aid the therapeutic use of PMB, a relatively cytotoxic antibiotic that is currently being reintroduced into clinics due to the global problem of antibiotic resistance. Keywords: PMB nonapeptide; collectin SP-A; lung; microbial infection; multidrug-resistant bacteria; polymyxin B; recombinant trimeric fragment; synergy. | U51: No | V51: Yes | W51: No | X51: This work investigates the potential of a peptide based on SP-A to improve or facilitate the clinical use of the antibiotic colistin (PMB), in contexts of bacterial resistance.
A52: 33358259 | B52: Clinical profile and microbiological aetiology diagnosis in adult patients hospitalized with community-acquired pneumonia | C52: Costa MI, Cipriano A, Santos FV, Valdoleiros SR, Furtado I, Machado A, Abreu M, Bastos HN. | D52: Pulmonology. 2022 Sep-Oct | E52: Costa MI | F52: Pulmonology | G52: 2022 | H52: 44193 | K52: 10.1016/j.pulmoe.2020.11.003 | L52: =IF(ISNUMBER(VLOOKUP(A52,EXCL,1,FALSE)),"Excluido",IF(ISNUMBER(VLOOKUP(A52,POST,1,FALSE)),"PostAlerta",IF(ISNUMBER(VLOOKUP(A52,PRE,1,FALSE)),"PreAlerta",""))) -> PostAlerta | M52: =IF(ISNUMBER(A52),(IF(ISNUMBER(VLOOKUP(A52,KEYWORDS,1,FALSE)),"C/PalabrasClaves","S/PalabrasClaves")),"") -> S/PalabrasClaves | N52: 1) Reporte de cepas resistentes | P52: 2022 Sep-Oct | Q52: Revisar | R52: =LEFT(P52,4) -> 2022 | S52: Oct | T52: Early introduction of appropriate antibiotherapy is one of the major prognostic-modifying factors in community acquired pneumonia (CAP). Despite established guidelines for empirical therapy, several factors may influence etiology and, consequently, antibiotic choices. The aims of this study were to analyze the etiology of CAP in adults admitted to a northern Portugal University Hospital and evaluate the yield of the different methods used to reach an etiological diagnosis, as well as analyze of the impact of patient demographic and clinical features on CAP etiology. We retrospectively analyzed 1901 cases of CAP with hospitalization. The diagnostic performance increased significantly when blood and sputum cultures were combined with urinary antigen tests. The most frequent etiological agent was Streptococcus pneumoniae (45.7%), except in August, when it was overtaken by gram-negative bacilli (GNB) and Legionella pneumophila infections. Viral infections were almost exclusive to winter and spring. A negative microbiological result was associated with increasing age, non-smoking and lack of both blood/sputum cultures. Younger age was a predictor for S. pneumoniae, Influenza and L. pneumophila infections. Active smoking without any previously known respiratory disease was a risk factor for legionellosis. COPD was associated with Haemophilus influenzae cases, while dementia was typical in GNB and S. aureus patients. Diabetes mellitus (DM) and heart disease were negative predictors of S. pneumoniae and H. influenzae, respectively. P. aeruginosa was an independent risk factor for mortality (OR 13.02, 95% CI 2.94-57.7). This study highlights the importance of a comprehensive microbiological diagnostic workup and provides clues to predicting the most probable CAP causative agents, based on a patient's clinical profile. These may be taken into account when establishing first line antibiotherapy. Keywords: Antimicrobial treatment; Community-acquired pneumonia; Comorbidities; Etiology; Microbiology. | U52: No | V52: No | W52: No | X52: Its main focus is on epidemiology, etiology and clinical prediction.
A53: 35719354 | B53: Case Report: Whole-Genome Sequencing of Serially Collected Haemophilus influenzae From a Patient With Common Variable Immunodeficiency Reveals Within-Host Evolution of Resistance to Trimethoprim-Sulfamethoxazole and Azithromycin After Prolonged Treatment With These Antibiotics | C53: Lindemann PC, Mylvaganam H, Oppegaard O, Anthonisen IL, Zecic N, Skaare D. | D53: Front Cell Infect Microbiol. 2022 Jun 1 | E53: Lindemann PC | F53: Front Cell Infect Microbiol | G53: 2022 | H53: 44732 | I53: PMC9199433 | K53: 10.3389/fcimb.2022.896823 | L53: =IF(ISNUMBER(VLOOKUP(A53,EXCL,1,FALSE)),"Excluido",IF(ISNUMBER(VLOOKUP(A53,POST,1,FALSE)),"PostAlerta",IF(ISNUMBER(VLOOKUP(A53,PRE,1,FALSE)),"PreAlerta",""))) -> PostAlerta | M53: =IF(ISNUMBER(A53),(IF(ISNUMBER(VLOOKUP(A53,KEYWORDS,1,FALSE)),"C/PalabrasClaves","S/PalabrasClaves")),"") -> C/PalabrasClaves | P53: 2022 Jun 1 | R53: =LEFT(P53,4) -> 2022 | S53: Jun
A54: 35663786 | B54: First report on the prevalence of bacteria in cystic fibrosis patients (CF) in a tertiary care center in Saudi Arabia | C54: Banjar H, Ghawi A, AlMogarri I, Alhaider S, Alomran H, Hejazi A, Alfadhel A, Khanjar S, AlAshgar M, Alghazzi A, Abanemai L, AlFattani A. | D54: Int J Pediatr Adolesc Med. 2022 Jun | E54: Banjar H | F54: Int J Pediatr Adolesc Med | G54: 2022 | H54: 44718 | I54: PMC9152558 | K54: 10.1016/j.ijpam.2021.07.001 | L54: =IF(ISNUMBER(VLOOKUP(A54,EXCL,1,FALSE)),"Excluido",IF(ISNUMBER(VLOOKUP(A54,POST,1,FALSE)),"PostAlerta",IF(ISNUMBER(VLOOKUP(A54,PRE,1,FALSE)),"PreAlerta",""))) -> PostAlerta | M54: =IF(ISNUMBER(A54),(IF(ISNUMBER(VLOOKUP(A54,KEYWORDS,1,FALSE)),"C/PalabrasClaves","S/PalabrasClaves")),"") -> S/PalabrasClaves | N54: =IF(ISNUMBER(SEARCH("TREATMENT", B54)), "4) Nuevos tratamientos", "") | P54: 2022 Jun | Q54: Excluir | R54: =LEFT(P54,4) -> 2022 | S54: Jun
A55: 35171454 | B55: The impact of COVID-19 pandemic control on vaccine-preventable invasive bacterial diseases in Piedmont (Italy) | C55: Peradotto M, Bondi A, Lombardi D, Bottino P, Zanotto E, Barbui AM, Cavallo R. | D55: Infection. 2022 Jun | E55: Peradotto M | F55: Infection | G55: 2022 | H55: 44608 | I55: PMC8852962 | K55: 10.1007/s15010-022-01770-6 | L55: =IF(ISNUMBER(VLOOKUP(A55,EXCL,1,FALSE)),"Excluido",IF(ISNUMBER(VLOOKUP(A55,POST,1,FALSE)),"PostAlerta",IF(ISNUMBER(VLOOKUP(A55,PRE,1,FALSE)),"PreAlerta",""))) -> PostAlerta | M55: =IF(ISNUMBER(A55),(IF(ISNUMBER(VLOOKUP(A55,KEYWORDS,1,FALSE)),"C/PalabrasClaves","S/PalabrasClaves")),"") -> S/PalabrasClaves | N55: =IF(ISNUMBER(SEARCH("TREATMENT", B55)), "4) Nuevos tratamientos", "") | P55: 2022 Jun | Q55: Excluir | R55: =LEFT(P55,4) -> 2022 | S55: Jun
A56: 35170144 | B56: Randomised controlled trial of nebulised gentamicin in children with bronchiectasis | C56: Twiss J, Stewart A, Gilchrist CA, Keelan JA, Metcalfe R, Byrnes CA. | D56: J Paediatr Child Health. 2022 Jun | E56: Twiss J | F56: J Paediatr Child Health | G56: 2022 | H56: 44608 | I56: PMC9307025 | K56: 10.1111/jpc.15899 | L56: =IF(ISNUMBER(VLOOKUP(A56,EXCL,1,FALSE)),"Excluido",IF(ISNUMBER(VLOOKUP(A56,POST,1,FALSE)),"PostAlerta",IF(ISNUMBER(VLOOKUP(A56,PRE,1,FALSE)),"PreAlerta",""))) -> Excluido | M56: =IF(ISNUMBER(A56),(IF(ISNUMBER(VLOOKUP(A56,KEYWORDS,1,FALSE)),"C/PalabrasClaves","S/PalabrasClaves")),"") -> S/PalabrasClaves | N56: =IF(ISNUMBER(SEARCH("TREATMENT", B56)), "4) Nuevos tratamientos", "") | P56: 2022 Jun | Q56: Excluir | R56: =LEFT(P56,4) -> 2022 | S56: Jun
A57: 34788694 | B57: Pooled microbiological findings and efficacy outcomes by pathogen in adults with community-acquired bacterial pneumonia from the Lefamulin Evaluation Against Pneumonia (LEAP) 1 and LEAP 2 phase 3 trials of lefamulin versus moxifloxacin | C57: Paukner S, Goldberg L, Alexander E, Das AF, Heinrich S, Patel P, Moran GJ, Sandrock C, File TM Jr, Vidal JE, Waites KB, Gelone SP, Schranz J. | D57: J Glob Antimicrob Resist. 2022 Jun | E57: Paukner S | F57: J Glob Antimicrob Resist | G57: 2022 | H57: 44517 | K57: 10.1016/j.jgar.2021.10.021 | L57: =IF(ISNUMBER(VLOOKUP(A57,EXCL,1,FALSE)),"Excluido",IF(ISNUMBER(VLOOKUP(A57,POST,1,FALSE)),"PostAlerta",IF(ISNUMBER(VLOOKUP(A57,PRE,1,FALSE)),"PreAlerta",""))) -> Excluido | M57: =IF(ISNUMBER(A57),(IF(ISNUMBER(VLOOKUP(A57,KEYWORDS,1,FALSE)),"C/PalabrasClaves","S/PalabrasClaves")),"") -> S/PalabrasClaves | N57: =IF(ISNUMBER(SEARCH("TREATMENT", B57)), "4) Nuevos tratamientos", "") | P57: 2022 Jun | Q57: Excluir | R57: =LEFT(P57,4) -> 2022 | S57: Jun
A58: 36071818 | B58: Antimicrobial Resistance Trends of the Most Common Causative Pathogens Associated with Community-acquired Respiratory Infections in China: 2009-2018 | C58: Zhao C, Yang S, Zhang F, Wang Z, Zhang Y, Wang X, Li H, Chen H, Wang H. | D58: Infect Drug Resist. 2022 Aug 31 | E58: Zhao C | F58: Infect Drug Resist | G58: 2022 | H58: 44812 | I58: PMC9443291 | K58: 10.2147/IDR.S374805 | L58: =IF(ISNUMBER(VLOOKUP(A58,EXCL,1,FALSE)),"Excluido",IF(ISNUMBER(VLOOKUP(A58,POST,1,FALSE)),"PostAlerta",IF(ISNUMBER(VLOOKUP(A58,PRE,1,FALSE)),"PreAlerta",""))) -> PostAlerta | M58: =IF(ISNUMBER(A58),(IF(ISNUMBER(VLOOKUP(A58,KEYWORDS,1,FALSE)),"C/PalabrasClaves","S/PalabrasClaves")),"") -> S/PalabrasClaves | N58: 1) Reporte de cepas resistentes | P58: 2022 Aug 31 | Q58: Revisar | R58: =LEFT(P58,4) -> 2022 | S58: Aug | T58: Background: Emergence of antimicrobial resistance poses new challenges in the management of community acquired respiratory tract infections (CARTIs). Therefore, surveillance on the antimicrobial susceptibilities of common respiratory pathogens is valuable and guides empirical therapeutic choices in management of CARTIs. Objective: The objective of the current study is to summarize the antimicrobial resistance trends in common respiratory tract pathogens isolated from patients with CARTIs in China, over a 10-year period (2009-2018). Methods: Streptococcus pneumoniae, Haemophilus influenzae and Moraxella catarrhalis strains were collected from multicenter, and antimicrobial susceptibility testing was performed in the research central laboratory of each study period from 2009-2018. The pathogens that accounted for CARTIs in the adult population was considered and summarized. Results: From 2009-2018 a total of 3750 isolates were collected from 22 cities located across different regions of China. Among these the most common bacterial isolates include S. pneumoniae (53.7%) followed by H. influenza (32.4%), M. catarrhalis (13.9%). S. pneumoniae exhibited reduction in susceptibility and increase in resistance to penicillin, cephalosporins (cefaclor, cefuroxime, ceftriaxone) during the surveillance period. Invasive and noninvasive S. pneumoniae showed similar resistance. In the case of H. influenzae susceptibility to β-lactam and β-lactamase inhibitors (ampicillin, amoxicillin and AMC), SXT, clarithromycin and cephalosporins (cefuroxime, cefaclor, ceftazidime) was reduced over the past 10 years with an exception of ceftriaxone. Overall, moxifloxacin and levofloxacin have the highest susceptibility rates against S. pneumoniae (>95%) and H. influenza (>90%). M. catarrhalis exhibited susceptibility to almost all the tested antimicrobials. Conclusion: In China the 10-year trends showed a substantial increase in resistance to β-lactam drugs and reduction in sensitivity. However, certain antimicrobial agents namely fluoroquinolones including moxifloxacin and levofloxacin maintained low resistance rates with better susceptibility. Further, with few exceptions decline in susceptibility rates to macrolides and cephalosporins was observed among the tested pathogens. Keywords: Community-acquired respiratory tract infections; Haemophilus influenzae; Moraxella catarrhalis; Streptococcus pneumoniae; antimicrobial resistance; susceptibility. | U58: No | V58: No | W58: No | X58: It focuses on the decade-long trend of antibiotic resistance in common respiratory pathogens, with implications for the empirical management of community-acquired respiratory infections.
A59: 36106084 | B59: Molecular epidemiology and antibiotic resistance profiles of invasive Haemophilus influenzae from Norway 2017-2021 | C59: Tønnessen R, García I, Debech N, Lindstrøm JC, Wester AL, Skaare D. | D59: Front Microbiol. 2022 Aug 29 | E59: Tønnessen R | F59: Front Microbiol | G59: 2022 | H59: 44819 | I59: PMC9467436 | K59: 10.3389/fmicb.2022.973257 | L59: =IF(ISNUMBER(VLOOKUP(A59,EXCL,1,FALSE)),"Excluido",IF(ISNUMBER(VLOOKUP(A59,POST,1,FALSE)),"PostAlerta",IF(ISNUMBER(VLOOKUP(A59,PRE,1,FALSE)),"PreAlerta",""))) -> PostAlerta | M59: =IF(ISNUMBER(A59),(IF(ISNUMBER(VLOOKUP(A59,KEYWORDS,1,FALSE)),"C/PalabrasClaves","S/PalabrasClaves")),"") -> C/PalabrasClaves | N59: 1) Reporte de cepas resistentes | P59: 2022 Aug 29 | Q59: Listo | R59: =LEFT(P59,4) -> 2022 | S59: Aug | T59: Invasive Haemophilus influenzae (Hi) disease has decreased in countries that included Hi type b (Hib) vaccination in their childhood immunization programs in the 1990s. Non-typeable (NT) and non-b strains are now the leading causes of invasive Hi disease in Europe, with most cases reported in young children and the elderly. Concerningly, no vaccines toward such strains are available and beta-lactam resistance is increasing. We describe the epidemiology of invasive Hi disease reported to the Norwegian Surveillance System for Communicable Diseases (MSIS) (2017-2021, n = 407). Whole-genome sequencing (WGS) was performed on 245 isolates. We investigated the molecular epidemiology (core genome phylogeny) and the presence of antibiotic resistance markers (including chromosomal mutations associated with beta-lactam or quinolone resistance). For isolates characterized with both WGS and phenotypic antibiotic susceptibility testing (AST) (n = 113) we assessed correlation between resistance markers and susceptibility categorization by calculation of sensitivity, specificity, and predictive values. Incidence rates of invasive Hi disease in Norway ranged from 0.7 to 2.3 per 100,000 inhabitants/year (mean 1.5 per 100,000) and declined during the COVID-19 pandemic. The bacterial population consisted of two major phylogenetic groups with subclustering by serotype and multi-locus sequence type (ST). NTHi accounted for 71.8% (176). The distribution of STs was in line with previous European reports. We identified 13 clusters, including four encapsulated and three previously described international NTHi clones with bla TEM-1 (ST103) or altered PBP3 (rPBP3) (ST14/IIA and ST367/IIA). Resistance markers were detected in 25.3% (62/245) of the isolates, with bla TEM-1 (31, 50.0%) and rPBP3 (28, 45.2%) being the most frequent. All isolates categorized as resistant to aminopenicillins, tetracycline or chloramphenicol possessed relevant resistance markers, and the absence of relevant substitutions in PBP3 and GyrA/ParC predicted susceptibility to cefotaxime, ceftriaxone, meropenem and quinolones. Among the 132 WGS-only isolates, one isolate had PBP3 substitutions associated with resistance to third-generation cephalosporins, and one isolate had GyrA/ParC alterations associated with quinolone resistance. The detection of international virulent and resistant NTHi clones underlines the need for a global molecular surveillance system. WGS is a useful supplement to AST and should be performed on all invasive isolates. Keywords: Haemophilus influenzae (Hi); Norway; antibiotic resistance; epidemiology; invasive; surveillance; vaccine; whole-genome sequencing (WGS) | U59: Yes | V59: No | W59: No | X59: Describes resistant and virulent international clones, identified by WGS, as well as their genetic distribution and resistance. It is a study that provides information on the emergence and prevalence of new clinical and genetic variants of H. influenzae.
A60: 35877653 | B60: The central role of arginine in Haemophilus influenzae survival in a polymicrobial environment with Streptococcus pneumoniae and Moraxella catarrhalis | C60: Tikhomirova A, Zilm PS, Trappetti C, Paton JC, Kidd SP. | D60: PLoS One. 2022 Jul 25 | E60: Tikhomirova A | F60: PLoS One | G60: 2022 | H60: 44767 | I60: PMC9312370 | K60: 10.1371/journal.pone.0271912 | L60: =IF(ISNUMBER(VLOOKUP(A60,EXCL,1,FALSE)),"Excluido",IF(ISNUMBER(VLOOKUP(A60,POST,1,FALSE)),"PostAlerta",IF(ISNUMBER(VLOOKUP(A60,PRE,1,FALSE)),"PreAlerta",""))) -> PostAlerta | M60: =IF(ISNUMBER(A60),(IF(ISNUMBER(VLOOKUP(A60,KEYWORDS,1,FALSE)),"C/PalabrasClaves","S/PalabrasClaves")),"") -> S/PalabrasClaves | N60: 1) Reporte de cepas resistentes | P60: 2022 Jul 25 | Q60: Revisar | R60: =LEFT(P60,4) -> 2022 | S60: Jul | T60: Haemophilus influenzae, Streptococcus pneumoniae and Moraxella catarrhalis are bacterial species which frequently co-colonise the nasopharynx, but can also transit to the middle ear to cause otitis media. Chronic otitis media is often associated with a polymicrobial infection by these bacteria. However, despite being present in polymicrobial infections, the molecular interactions between these bacterial species remain poorly understood. We have previously reported competitive interactions driven by pH and growth phase between H. influenzae and S. pneumoniae. In this study, we have revealed competitive interactions between the three otopathogens, which resulted in reduction of H. influenzae viability in co-culture with S. pneumoniae and in triple-species culture. Transcriptomic analysis by mRNA sequencing identified a central role of arginine in mediating these interactions. Arginine supplementation was able to increase H. influenzae survival in a dual-species environment with S. pneumoniae, and in a triple-species environment. Arginine was used by H. influenzae for ATP production, and levels of ATP generated in dual- and triple-species co-culture at early stages of growth were significantly higher than the combined ATP levels of single-species cultures. These results indicate a central role for arginine-mediated ATP production by H. influenzae in the polymicrobial community | U60: No | V60: Yes | W60: No | X60: Reveals potential arginine-based therapeutic approach to improve bacterial viability in polymicrobial infections
A61: 35544535 | B61: Etiology of meningitis among adults in three quaternary hospitals in Mozambique, 2016-2017: The role of HIV | C61: Nhantumbo AA, Comé CE, Maholela PI, Munguambe AM, Costa PD, Mott M, Cunha GR, Chambal L, Dias C, Cantarelli VV, Gudo ES. | D61: PLoS One. 2022 May 11 | E61: Nhantumbo AA | F61: PLoS One | G61: 2022 | H61: 44692 | I61: PMC9094547 | K61: 10.1371/journal.pone.0267949 | L61: =IF(ISNUMBER(VLOOKUP(A61,EXCL,1,FALSE)),"Excluido",IF(ISNUMBER(VLOOKUP(A61,POST,1,FALSE)),"PostAlerta",IF(ISNUMBER(VLOOKUP(A61,PRE,1,FALSE)),"PreAlerta",""))) -> PostAlerta | M61: =IF(ISNUMBER(A61),(IF(ISNUMBER(VLOOKUP(A61,KEYWORDS,1,FALSE)),"C/PalabrasClaves","S/PalabrasClaves")),"") -> S/PalabrasClaves | N61: =IF(ISNUMBER(SEARCH("TREATMENT", B61)), "4) Nuevos tratamientos", "") | P61: 2022 May 11 | Q61: Excluir | R61: =LEFT(P61,4) -> 2022 | S61: May
A62: 35148524 | B62: Ventilator-Associated Lower Respiratory Tract Bacterial Infections in COVID-19 Compared With Non-COVID-19 Patients | C62: Hedberg P, Ternhag A, Giske CG, Strålin K, Özenci V, Johansson N, Spindler C, Hedlund J, Mårtensson J, Nauclér P. | D62: Crit Care Med. 2022 May 1 | E62: Hedberg P | F62: Crit Care Med | G62: 2022 | H62: 44603 | I62: PMC9005099 | K62: 10.1097/CCM.0000000000005462 | L62: =IF(ISNUMBER(VLOOKUP(A62,EXCL,1,FALSE)),"Excluido",IF(ISNUMBER(VLOOKUP(A62,POST,1,FALSE)),"PostAlerta",IF(ISNUMBER(VLOOKUP(A62,PRE,1,FALSE)),"PreAlerta",""))) -> PostAlerta | M62: =IF(ISNUMBER(A62),(IF(ISNUMBER(VLOOKUP(A62,KEYWORDS,1,FALSE)),"C/PalabrasClaves","S/PalabrasClaves")),"") -> S/PalabrasClaves | N62: =IF(ISNUMBER(SEARCH("TREATMENT", B62)), "4) Nuevos tratamientos", "") | P62: 2022 May 1 | Q62: Excluir | R62: =LEFT(P62,4) -> 2022 | S62: May
A63: 35026180 | B63: Non-typeable Haemophilus influenzae-Moraxella catarrhalis vaccine for the prevention of exacerbations in chronic obstructive pulmonary disease: a multicentre, randomised, placebo-controlled, observer-blinded, proof-of-concept, phase 2b trial | C63: Andreas S, Testa M, Boyer L, Brusselle G, Janssens W, Kerwin E, Papi A, Pek B, Puente-Maestu L, Saralaya D, Watz H, Wilkinson TMA, Casula D, Di Maro G, Lattanzi M, Moraschini L, Schoonbroodt S, Tasciotti A, Arora AK, Maltais F | E63: Lancet Respir Med. 2022 May | L63: =IF(ISNUMBER(VLOOKUP(A63,EXCL,1,FALSE)),"Excluido",IF(ISNUMBER(VLOOKUP(A63,POST,1,FALSE)),"PostAlerta",IF(ISNUMBER(VLOOKUP(A63,PRE,1,FALSE)),"PreAlerta",""))) -> Excluido | M63: =IF(ISNUMBER(A63),(IF(ISNUMBER(VLOOKUP(A63,KEYWORDS,1,FALSE)),"C/PalabrasClaves","S/PalabrasClaves")),"") -> S/PalabrasClaves | N63: 2) Nuevos tratamientos | Q63: Excluir | R63: =LEFT(P63,4) | T63: Antecedentes: Las exacerbaciones agudas de la enfermedad pulmonar obstructiva crónica (EAEPOC) se asocian con cambios en el microbioma del esputo, incluyendo una mayor prevalencia de bacterias patógenas. La vacunación contra las bacterias más frecuentes en la EAEPOC podría reducir la frecuencia de exacerbaciones. Evaluamos la eficacia, seguridad e inmunogenicidad de una vacuna candidata que contiene proteínas de superficie de Haemophilus influenzae no tipificable (NTHi) y Moraxella catarrhalis (Mcat) en pacientes con EPOC. Métodos: Este ensayo multicéntrico, aleatorizado, ciego para el observador, controlado con placebo, de prueba de concepto, de fase 2b reclutó pacientes con EPOC estable, limitación del flujo aéreo de moderada a muy grave (Iniciativa Global para la Enfermedad Pulmonar Obstructiva Crónica [GOLD] estadio 2, 3 o 4), en 67 centros clínicos en Bélgica, Canadá, Francia, Alemania, Italia, España, Reino Unido y EE. UU. Los pacientes elegibles tenían entre 40 y 80 años y antecedentes de al menos una exacerbación moderada o grave en el año anterior. Los pacientes fueron asignados (1:1) mediante un algoritmo de minimización para recibir dos inyecciones intramusculares de la vacuna NTHi-Mcat o placebo con 60 días de diferencia, además de la atención estándar. El algoritmo de asignación consideró la categoría de edad, el número de exacerbaciones previas, la gravedad de la EPOC al ingresar al estudio y el país como factores de minimización, para garantizar el equilibrio del tratamiento dentro de cada factor. Los receptores de la vacuna y los responsables de evaluar los criterios de valoración del estudio fueron enmascarados a la asignación del grupo. En el análisis de eficacia, el criterio principal de valoración fue la tasa de cualquier EAEPOC moderada o grave que se presentara en un período de un año, comenzando un mes después de la segunda dosis en pacientes que recibieron dos dosis de la vacuna (cohorte total vacunada modificada). La seguridad se evaluó en la cohorte total vacunada. El ensayo está registrado en ClinicalTrials.gov con el número NCT03281876 y ha finalizado. Resultados: Entre el 27 de noviembre de 2017 y el 30 de noviembre de 2018, se inscribieron 606 adultos y se incluyeron en la cohorte total vacunada (304 en el grupo de la vacuna NTHi-Mcat, 302 en el grupo placebo); 571 recibieron dos dosis y se incluyeron en el análisis de eficacia primaria (279 en el grupo de la vacuna NTHi-Mcat, 292 en el grupo placebo). 23 participantes abandonaron en el grupo de la vacuna NTHi-Mcat y 39 en el grupo placebo; esto incluyó 4 pacientes en el grupo de la vacuna NTHi-Mcat y 15 en el grupo placebo que se retiraron del estudio debido a un evento adverso. El análisis primario incluyó 340 exacerbaciones (en un tiempo de seguimiento de 102 123 días) en el grupo de la vacuna NTHi-Mcat y 333 (en 104 443 días) en el grupo placebo, con una tasa anual de AECOPD moderada o grave de 1,22 en el grupo de la vacuna NTHi-Mcat y 1,17 en el grupo placebo, estimándose que la eficacia de la vacuna para reducir la tasa anual de AECOPD moderada o grave fue cero (estimación puntual de la eficacia de la vacuna 2,26 % [IC del 87 %: -18,27 a 11,58]; p = 0,82). Los eventos adversos locales solicitados fueron más frecuentes en el grupo de la vacuna NTHi-Mcat (216 [72%] de 301 pacientes) que con placebo (34 [11%] de 299 pacientes), y la frecuencia de eventos adversos generales solicitados fue similar entre los grupos (239 [79%] de 301 frente a 235 [79%] de 299 pacientes). Hubo una muerte en el grupo de la vacuna NTHi-Mcat (insuficiencia respiratoria aguda, no relacionada con la vacunación) y diez en el grupo placebo (siete debido en parte a EPOC o insuficiencia respiratoria). Hubo 158 eventos adversos graves (89 [29%] de 304 pacientes) en el grupo de la vacuna NTHi-Mcat, no relacionados con la vacunación, y 214 (99 [33%] de 302 pacientes) en el grupo placebo. Interpretación: La vacuna NTHi-Mcat administrada a pacientes con EPOC no mostró eficacia para reducir la tasa anual de exacerbaciones moderadas o graves. No se identificaron problemas de seguridad. | U63: No | V63: No | W63: Yes | X63: Evaluates efficacy of a vaccine against NTHi and Mcat in COPD; although unsuccessful, it remains an immunization study.
A64: 34882256 | B64: Detection of bacteria via multiplex PCR in respiratory samples of critically ill COVID-19 patients with suspected HAP/VAP in the ICU | C64: Karolyi M, Pawelka E, Hind J, Baumgartner S, Friese E, Hoepler W, Neuhold S, Omid S, Seitz T, Traugott MT, Wenisch C, Zoufaly A. | D64: Wien Klin Wochenschr. 2022 May | E64: Karolyi M | F64: Wien Klin Wochenschr | G64: 2022 | H64: 44539 | I64: PMC8656439 | K64: 10.1007/s00508-021-01990-0 | L64: =IF(ISNUMBER(VLOOKUP(A64,EXCL,1,FALSE)),"Excluido",IF(ISNUMBER(VLOOKUP(A64,POST,1,FALSE)),"PostAlerta",IF(ISNUMBER(VLOOKUP(A64,PRE,1,FALSE)),"PreAlerta",""))) -> PostAlerta | M64: =IF(ISNUMBER(A64),(IF(ISNUMBER(VLOOKUP(A64,KEYWORDS,1,FALSE)),"C/PalabrasClaves","S/PalabrasClaves")),"") -> S/PalabrasClaves | N64: =IF(ISNUMBER(SEARCH("TREATMENT", B64)), "4) Nuevos tratamientos", "") | P64: 2020 May | Q64: Excluir | R64: =LEFT(P64,4) -> 2020 | S64: May
A65: 35935209 | B65: Characterization and Fitness Cost of Tn7100, a Novel Integrative and Conjugative Element Conferring Multidrug Resistance in Haemophilus influenzae | C65: Johannessen H, Anthonisen IL, Zecic N, Hegstad K, Ranheim TE, Skaare D. | D65: Front Microbiol. 2022 Jul 22 | E65: Johannessen H | F65: Front Microbiol | G65: 2022 | H65: 44781 | I65: PMC9355037 | K65: 10.3389/fmicb.2022.945411 | L65: =IF(ISNUMBER(VLOOKUP(A65,EXCL,1,FALSE)),"Excluido",IF(ISNUMBER(VLOOKUP(A65,POST,1,FALSE)),"PostAlerta",IF(ISNUMBER(VLOOKUP(A65,PRE,1,FALSE)),"PreAlerta",""))) -> PostAlerta | M65: =IF(ISNUMBER(A65),(IF(ISNUMBER(VLOOKUP(A65,KEYWORDS,1,FALSE)),"C/PalabrasClaves","S/PalabrasClaves")),"") -> C/PalabrasClaves | N65: 1) Reporte de cepas resistentes | P65: 2022 Jul 22 | Q65: Listo | R65: =LEFT(P65,4) -> 2022 | S65: Jul | T65: A multidrug-resistant (MDR) strain of Haemophilus influenzae, Hi-228, with phenotypic resistance toward ampicillin, cefotaxime, chloramphenicol, gentamicin, and azithromycin, was isolated in Oslo, Norway. The strain was part of a clonal outbreak (2016-2017) comprising five ST143 strains with identical resistotypes. Hi-228 carries a novel integrative and conjugative element (ICE), Tn7100, contributing to this remarkable and previously unreported MDR profile. Tn7100 contains the following resistance genes: bla TEM-1B, catA2, aac(6')-Im, aph(2″)-Ib, mef (E), and mel. The latter four are previously unreported or rarely reported in H. influenzae. In this study, we investigated the genetic environment, mechanisms of transfer, impact on phenotypic susceptibility, and fitness cost of this ICE. We found that Tn7100 has an overall structure similar to the previously described ICE Tn6686, with bla TEM-1B and catA2 carried by Tn3 and Tn10, respectively. The major difference between Tn7100 and Tn6686 is that Tn7100 lacks tet(B) but carries the resistance gene pairs aac(6')-Im and aph(2″)-Ib and mef (E) and mel. The gene pairs are located on the novel transposable elements Tn7470 and Tn7471, which have high sequence identities to a plasmid in Enterobacterales and an ICE in streptococcal species, respectively. Tn7100 does circularize and is transferable, however, at a low frequency. Head-to-head competition experiments showed that uptake of Tn7100 reduces bacterial fitness. Our study shows that MDR strains are capable of clonal spread and that the H. influenzae supragenome comprises an increasingly wide range of transferable resistance genes, with evidence of transfer from unrelated genera. The findings offer a glimpse into the genome dynamics of H. influenzae, highlighting the importance of rational antibiotic usage to contain antimicrobial resistance and the emergence of MDR strains in this important pathogen. | U65: Yes | V65: No | W65: No | X65: Describes an MDR strain with novel resistance genes and horizontal transfer
A66: 35572628 | B66: A New Vaccination Method Based on Phage NgoΦ6 and Its Phagemid Derivatives | C66: Piekarowicz A, Kłyż A, Stein DC. | D66: Front Microbiol. 2022 Apr 28 | E66: Piekarowicz A | F66: Front Microbiol | G66: 2022 | H66: 44697 | I66: PMC9096494 | K66: 10.3389/fmicb.2022.793205 | L66: =IF(ISNUMBER(VLOOKUP(A66,EXCL,1,FALSE)),"Excluido",IF(ISNUMBER(VLOOKUP(A66,POST,1,FALSE)),"PostAlerta",IF(ISNUMBER(VLOOKUP(A66,PRE,1,FALSE)),"PreAlerta",""))) -> PostAlerta | M66: =IF(ISNUMBER(A66),(IF(ISNUMBER(VLOOKUP(A66,KEYWORDS,1,FALSE)),"C/PalabrasClaves","S/PalabrasClaves")),"") -> S/PalabrasClaves | N66: =IF(ISNUMBER(SEARCH("TREATMENT", B66)), "4) Nuevos tratamientos", "") | P66: 2022 Apr 28 | Q66: Excluir | R66: =LEFT(P66,4) -> 2022 | S66: Apr
A67: 36845237 | B67: [Haemophilus influenzae type B (Hib) meningitis in older children: about a case] | C67: Trabelsi I, Ali MB, Romdhane MB, Smaoui H, Hadj IB, Boussetta K. | D67: Pan Afr Med J. 2022 Jul 20 | E67: Trabelsi I | F67: Pan Afr Med J | G67: 2022 | H67: 44984 | I67: PMC9949271 | K67: 10.11604/pamj.2022.42.220.35804 | L67: =IF(ISNUMBER(VLOOKUP(A67,EXCL,1,FALSE)),"Excluido",IF(ISNUMBER(VLOOKUP(A67,POST,1,FALSE)),"PostAlerta",IF(ISNUMBER(VLOOKUP(A67,PRE,1,FALSE)),"PreAlerta",""))) -> PostAlerta | M67: =IF(ISNUMBER(A67),(IF(ISNUMBER(VLOOKUP(A67,KEYWORDS,1,FALSE)),"C/PalabrasClaves","S/PalabrasClaves")),"") -> S/PalabrasClaves | N67: 3) Inmunización | P67: 2022 Jul 20 | Q67: Listo | R67: =LEFT(P67,4) -> 2022 | S67: Jul | T67: Since widespread vaccination, invasive Haemophilus influenzae type b (Hib) has become a rare infection. We here report the case of a 9-year-old boy admitted with seizures associated with fever and impaired general condition. First examination showed comatose child, Glasgow score 9/15, fever 38.2, deep tendon reflexes without frank meningeal syndrome. Laboratory tests showed polymorphonuclear neutrophils (PNN) with CRP 45.8. Cerebrospinal fluid (CSF) analysis revealed a cloudy appearance, pleiocytosis (6760 white blood cell count/ mm3) with neutrophil predominance (PNN = 90%, lymphocytes = 10%). Direct examination showed polymorphic bacilli, soluble antigen of Haemophilus influenzae type b, decreased glycorachy 0.04 mmol/L and hyper proteinorachie 4.097 g/L. MRI of the cerebellomedullary fissure revealed subtentorial and supratentorial encephalitis with bilateral parieto-occipital and cerebellar cortical and subcortical signal anomalies. The patient was treated with cefotaxime with favorable outcome. The patient had not been vaccinated against Hib in early childhood. After a 3-year follow-up, the patient was asymptomatic with no neurosensory sequelae. In subjects with severe Hib infection proof of vaccination or testing for underlying immunodeficiency are required. | U67: No | V67: No | W67: Yes | X67: Since widespread vaccination, invasive Haemophilus influenzae type b (Hib) has become a rare infection. We here report the case of a 9-year-old boy admitted with seizures associated with fever and impaired general condition. First examination showed comatose child, Glasgow score 9/15, fever 38.2, deep tendon reflexes without frank meningeal syndrome. Laboratory tests showed polymorphonuclear neutrophils (PNN) with CRP 45.8. Cerebrospinal fluid (CSF) analysis revealed a cloudy appearance, pleiocytosis (6760 white blood cell count/ mm3) with neutrophil predominance (PNN = 90%, lymphocytes = 10%). Direct examination showed polymorphic bacilli, soluble antigen of Haemophilus influenzae type b, decreased glycorachy 0.04 mmol/L and hyper proteinorachie 4.097 g/L. MRI of the cerebellomedullary fissure revealed subtentorial and supratentorial encephalitis with bilateral parieto-occipital and cerebellar cortical and subcortical signal anomalies. The patient was treated with cefotaxime with favorable outcome. The patient had not been vaccinated against Hib in early childhood. After a 3-year follow-up, the patient was asymptomatic with no neurosensory sequelae. In subjects with severe Hib infection proof of vaccination or testing for underlying immunodeficiency are required.
A68: 35195438 | B68: Functional and Structural Characterization of Diverse NfsB Chloramphenicol Reductase Enzymes from Human Pathogens | C68: Mullowney MW, Maltseva NI, Endres M, Kim Y, Joachimiak A, Crofts TS. | D68: Microbiol Spectr. 2022 Apr 27 | E68: Mullowney MW | F68: Microbiol Spectr | G68: 2022 | H68: 44615 | I68: PMC8941942 | K68: 10.1128/spectrum.00139-22 | L68: =IF(ISNUMBER(VLOOKUP(A68,EXCL,1,FALSE)),"Excluido",IF(ISNUMBER(VLOOKUP(A68,POST,1,FALSE)),"PostAlerta",IF(ISNUMBER(VLOOKUP(A68,PRE,1,FALSE)),"PreAlerta",""))) -> PostAlerta | M68: =IF(ISNUMBER(A68),(IF(ISNUMBER(VLOOKUP(A68,KEYWORDS,1,FALSE)),"C/PalabrasClaves","S/PalabrasClaves")),"") -> C/PalabrasClaves | N68: =IF(ISNUMBER(SEARCH("TREATMENT", B68)), "4) Nuevos tratamientos", "") | P68: 2022 Apr 27 | Q68: Excluir | R68: =LEFT(P68,4) -> 2022 | S68: Apr
A69: 35812707 | B69: Evaluation of the rate, pattern and appropriateness of antibiotic prescription in a cohort of pilgrims suffering from upper respiratory tract infection during the 2018 Hajj season | C69: Bokhary H, Research Team H, Barasheed O, Othman HB, Saha B, Rashid H, Hill-Cawthorne GA, Abd El Ghany M. | D69: Access Microbiol. 2022 Apr 25 | E69: Bokhary H | F69: Access Microbiol | G69: 2022 | H69: 44753 | I69: PMC9260093 | K69: 10.1099/acmi.0.000338 | L69: =IF(ISNUMBER(VLOOKUP(A69,EXCL,1,FALSE)),"Excluido",IF(ISNUMBER(VLOOKUP(A69,POST,1,FALSE)),"PostAlerta",IF(ISNUMBER(VLOOKUP(A69,PRE,1,FALSE)),"PreAlerta",""))) -> PostAlerta | M69: =IF(ISNUMBER(A69),(IF(ISNUMBER(VLOOKUP(A69,KEYWORDS,1,FALSE)),"C/PalabrasClaves","S/PalabrasClaves")),"") -> C/PalabrasClaves | N69: =IF(ISNUMBER(SEARCH("TREATMENT", B69)), "4) Nuevos tratamientos", "") | P69: 2022 Apr 25 | Q69: Excluir | R69: =LEFT(P69,4) -> 2022 | S69: Apr
A70: 35531333 | B70: Establishment and Clinical Application of a RPA-LFS Assay for Detection of Capsulated and Non-Capsulated Haemophilus influenzae | C70: Wang Y, Liu A, Fu M, Guo J, Wang L, Zuo X, Ma F. | D70: Front Cell Infect Microbiol. 2022 Apr 21 | E70: Wang Y | F70: Front Cell Infect Microbiol | G70: 2022 | H70: 44690 | I70: PMC9068959 | K70: 10.3389/fcimb.2022.878813 | L70: =IF(ISNUMBER(VLOOKUP(A70,EXCL,1,FALSE)),"Excluido",IF(ISNUMBER(VLOOKUP(A70,POST,1,FALSE)),"PostAlerta",IF(ISNUMBER(VLOOKUP(A70,PRE,1,FALSE)),"PreAlerta",""))) -> PostAlerta | M70: =IF(ISNUMBER(A70),(IF(ISNUMBER(VLOOKUP(A70,KEYWORDS,1,FALSE)),"C/PalabrasClaves","S/PalabrasClaves")),"") -> S/PalabrasClaves | N70: =IF(ISNUMBER(SEARCH("TREATMENT", B70)), "4) Nuevos tratamientos", "") | P70: 2022 Apr 21 | Q70: Excluir | R70: =LEFT(P70,4) -> 2022 | S70: Apr
A71: 35847562 | B71: The relationship between the gut microbiome and the risk of respiratory infections among newborns | C71: Moroishi Y, Gui J, Hoen AG, Morrison HG, Baker ER, Nadeau KC, Li H, Li Z, Madan JC, Karagas MR. | D71: Commun Med (Lond). 2022 Jul 14 | E71: Moroishi Y | F71: Commun Med (Lond) | G71: 2022 | H71: 44760 | I71: PMC9283516 | K71: 10.1038/s43856-022-00152-1 | L71: =IF(ISNUMBER(VLOOKUP(A71,EXCL,1,FALSE)),"Excluido",IF(ISNUMBER(VLOOKUP(A71,POST,1,FALSE)),"PostAlerta",IF(ISNUMBER(VLOOKUP(A71,PRE,1,FALSE)),"PreAlerta",""))) -> PostAlerta | M71: =IF(ISNUMBER(A71),(IF(ISNUMBER(VLOOKUP(A71,KEYWORDS,1,FALSE)),"C/PalabrasClaves","S/PalabrasClaves")),"") -> S/PalabrasClaves | N71: 3) Inmunización | P71: 2022 Jul 14 | Q71: Revisar | R71: =LEFT(P71,4) -> 2022 | S71: Jul | T71: Background: Emerging evidence points to a critical role of the developing gut microbiome in immune maturation and infant health; however, prospective studies are lacking. Methods: We examined the occurrence of infections and associated symptoms during the first year of life in relation to the infant gut microbiome at six weeks of age using bacterial 16S rRNA V4-V5 gene sequencing (N = 465) and shotgun metagenomics (N = 185). We used generalized estimating equations to assess the associations between longitudinal outcomes and 16S alpha diversity and metagenomics species. Results: Here we show higher infant gut microbiota alpha diversity was associated with an increased risk of infections or respiratory symptoms treated with a prescription medicine, and specifically upper respiratory tract infections. Among vaginally delivered infants, a higher alpha diversity was associated with an increased risk of all-cause wheezing treated with a prescription medicine and diarrhea involving a visit to a health care provider. Positive associations were specifically observed with Veillonella species among all deliveries and Haemophilus influenzae among cesarean-delivered infants. Conclusion: Our findings suggest that intestinal microbial diversity and the relative abundance of key taxa in early infancy may influence susceptibility to respiratory infection, wheezing, and diarrhea. | U71: No | V71: No | W71: Yes | X71: Study of how the microbiome influences immune maturation and susceptibility to infection in infancy key to prevention
A72: 35498792 | B72: BIGDATA: A Protocol to Create and Extend a 25-Year Clinical Trial and Observational Data Asset to Address Key Knowledge Gaps in Otitis Media and Hearing Loss in Australian Aboriginal and Non-Aboriginal Children | C72: Beissbarth J, Smith-Vaughan HC, Cheng AC, Morris PS, Leach AJ. | D72: Front Pediatr. 2022 Apr 14 | E72: Beissbarth J | F72: Front Pediatr | G72: 2022 | H72: 44683 | I72: PMC9047683 | K72: 10.3389/fped.2022.804373 | L72: =IF(ISNUMBER(VLOOKUP(A72,EXCL,1,FALSE)),"Excluido",IF(ISNUMBER(VLOOKUP(A72,POST,1,FALSE)),"PostAlerta",IF(ISNUMBER(VLOOKUP(A72,PRE,1,FALSE)),"PreAlerta",""))) -> PostAlerta | M72: =IF(ISNUMBER(A72),(IF(ISNUMBER(VLOOKUP(A72,KEYWORDS,1,FALSE)),"C/PalabrasClaves","S/PalabrasClaves")),"") -> C/PalabrasClaves | N72: =IF(ISNUMBER(SEARCH("TREATMENT", B72)), "4) Nuevos tratamientos", "") | P72: 2022 Apr 14 | Q72: Excluir | R72: =LEFT(P72,4) -> 2022 | S72: Apr
A73: 35404980 | B73: Outcome of acute bacterial meningitis among children in Kandahar, Afghanistan: A prospective observational cohort study | C73: Rahimi BA, Ishaq N, Mudaser GM, Taylor WR. | D73: PLoS One. 2022 Apr 11 | E73: Rahimi BA | F73: PLoS One | G73: 2022 | H73: 44662 | I73: PMC9000062 | K73: 10.1371/journal.pone.0265487 | L73: =IF(ISNUMBER(VLOOKUP(A73,EXCL,1,FALSE)),"Excluido",IF(ISNUMBER(VLOOKUP(A73,POST,1,FALSE)),"PostAlerta",IF(ISNUMBER(VLOOKUP(A73,PRE,1,FALSE)),"PreAlerta",""))) -> PostAlerta | M73: =IF(ISNUMBER(A73),(IF(ISNUMBER(VLOOKUP(A73,KEYWORDS,1,FALSE)),"C/PalabrasClaves","S/PalabrasClaves")),"") -> S/PalabrasClaves | N73: =IF(ISNUMBER(SEARCH("TREATMENT", B73)), "4) Nuevos tratamientos", "") | P73: 2022 Apr 11 | Q73: Excluir | R73: =LEFT(P73,4) -> 2022 | S73: Apr
A74: 35464398 | B74: Case Report: X-Linked SASH3 Deficiency Presenting as a Common Variable Immunodeficiency | C74: Labrador-Horrillo M, Franco-Jarava C, Garcia-Prat M, Parra-Martínez A, Antolín M, Salgado-Perandrés S, Aguiló-Cucurull A, Martinez-Gallo M, Colobran R. | D74: Front Immunol. 2022 Apr 8 | E74: Labrador-Horrillo M | F74: Front Immunol | G74: 2022 | H74: 44676 | I74: PMC9027814 | K74: 10.3389/fimmu.2022.881206 | L74: =IF(ISNUMBER(VLOOKUP(A74,EXCL,1,FALSE)),"Excluido",IF(ISNUMBER(VLOOKUP(A74,POST,1,FALSE)),"PostAlerta",IF(ISNUMBER(VLOOKUP(A74,PRE,1,FALSE)),"PreAlerta",""))) -> PostAlerta | M74: =IF(ISNUMBER(A74),(IF(ISNUMBER(VLOOKUP(A74,KEYWORDS,1,FALSE)),"C/PalabrasClaves","S/PalabrasClaves")),"") -> S/PalabrasClaves | N74: =IF(ISNUMBER(SEARCH("TREATMENT", B74)), "4) Nuevos tratamientos", "") | P74: 2022 Apr 8 | Q74: Excluir | R74: =LEFT(P74,4) -> 2022 | S74: Apr
A75: 35874779 | B75: Induction of Mucosal IgA-Mediated Protective Immunity Against Nontypeable Haemophilus influenzae Infection by a Cationic Nanogel-Based P6 Nasal Vaccine | C75: Nakahashi-Ouchida R, Mori H, Yuki Y, Umemoto S, Hirano T, Uchida Y, Machita T, Yamanoue T, Sawada SI, Suzuki M, Fujihashi K, Akiyoshi K, Kurono Y, Kiyono H. | D75: Front Immunol. 2022 Jul 6 | E75: Nakahashi-Ouchida R | F75: Front Immunol | G75: 2022 | H75: 44767 | I75: PMC9299436 | K75: 10.3389/fimmu.2022.819859 | L75: =IF(ISNUMBER(VLOOKUP(A75,EXCL,1,FALSE)),"Excluido",IF(ISNUMBER(VLOOKUP(A75,POST,1,FALSE)),"PostAlerta",IF(ISNUMBER(VLOOKUP(A75,PRE,1,FALSE)),"PreAlerta",""))) -> PostAlerta | M75: =IF(ISNUMBER(A75),(IF(ISNUMBER(VLOOKUP(A75,KEYWORDS,1,FALSE)),"C/PalabrasClaves","S/PalabrasClaves")),"") -> C/PalabrasClaves | N75: 2) Nuevos tratamientos | P75: 2022 Jul 6 | Q75: Listo | R75: =LEFT(P75,4) -> 2022 | S75: Jul | T75: Nontypeable Haemophilus influenzae (NTHi) strains form a major group of pathogenic bacteria that colonizes the nasopharynx and causes otitis media in young children. At present, there is no licensed vaccine for NTHi. Because NTHi colonizes the upper respiratory tract and forms biofilms that cause subsequent infectious events, a nasal vaccine that induces NTHi-specific secretory IgA capable of preventing biofilm formation in the respiratory tract is desirable. Here, we developed a cationic cholesteryl pullulan-based (cCHP nanogel) nasal vaccine containing the NTHi surface antigen P6 (cCHP-P6) as a universal vaccine antigen, because P6 expression is conserved among 90% of NTHi strains. Nasal immunization of mice with cCHP-P6 effectively induced P6-specific IgA in mucosal fluids, including nasal and middle ear washes. The vaccine-induced P6-specific IgA showed direct binding to the NTHi via the surface P6 proteins, resulting in the inhibition of NTHi biofilm formation. cCHP-P6 nasal vaccine thus protected mice from intranasal NTHi challenge by reducing NTHi colonization of nasal tissues and eventually eliminated the bacteria. In addition, the vaccine-induced IgA bound to different NTHi clinical isolates from patients with otitis media and inhibited NTHi attachment in a three-dimensional in vitro model of the human nasal epithelial surface. Therefore, the cCHP-P6 nanogel nasal vaccine induced effective protection in the airway mucosa, making it a strong vaccine candidate for preventing NTHi-induced infectious diseases, such as otitis media, sinusitis, and pneumonia. | U75: No | V75: Yes | W75: Yes | X75: It discusses the development of a cationic nasal vaccine based on cholesteryl pululanate (cCHP nanogel) and that nasal immunization of mice with cCHP-P6 induced P6-specific IgA.
A76: 35167935 | B76: In vitro and in silico evaluation of antimicrobial properties of Delphinium cashmerianum L., a medicinal herb growing in Kashmir, India | C76: Bhat BA, Mir WR, Sheikh BA, Rather MA, Dar TUH, Mir MA. | D76: J Ethnopharmacol. 2022 Jun 12 | E76: Bhat BA | F76: J Ethnopharmacol | G76: 2022 | H76: 44607 | K76: 10.1016/j.jep.2022.115046 | L76: =IF(ISNUMBER(VLOOKUP(A76,EXCL,1,FALSE)),"Excluido",IF(ISNUMBER(VLOOKUP(A76,POST,1,FALSE)),"PostAlerta",IF(ISNUMBER(VLOOKUP(A76,PRE,1,FALSE)),"PreAlerta",""))) -> PostAlerta | M76: =IF(ISNUMBER(A76),(IF(ISNUMBER(VLOOKUP(A76,KEYWORDS,1,FALSE)),"C/PalabrasClaves","S/PalabrasClaves")),"") -> C/PalabrasClaves | N76: 2) Nuevos tratamientos | P76: 2022 Jun 12 | Q76: Listo | R76: =LEFT(P76,4) -> 2022 | S76: Jun | T76: Ethnopharmacological relevance: Microorganisms are developing resistance to synthetic drugs. As a result, the search for novel antimicrobial compounds has become an urgent need. Medicinal plants are commonly used as traditional medicine and Delphinium is one of the prominent genus used in the treatment of several diseases. Aim of the study: The present study aimed to determine the in vitro and in silico antimicrobial activities of petroleum ether, ethyl acetate and methanol extracts from the leaf samples of plant (Delphinium cashmerianum L.) against various bacterial and fungal strains. Material and methods: Three extracts of Delphinium cashmerianum prepared and 88 bioactive compounds were analyzed through LC-MS data with the vast majority of them having therapeutic applications. These extracts have been screened for the antimicrobial activity against various bacterial (Escherichia coli, Micrococcus luteus, Klebsiella pneumoniae, Streptococcus pneumonia, Haemophilus influenzae, Neisseria mucosa) and fungal (Candida albicans, Candida glabrata, Candida paropsilosis) species through in silico molecular docking approach using autodock vina software, molecular dynamic simulation (MDS), in vitro disc diffusion and broth microdilution method for minimum inhibitory concentration (MIC) evaluation. Results: Our results demonstrated that all three extracts were active against the whole set of microorganisms. The ethyl acetate extract was the most active against S.pneumonia, K. pneumoniae and C. albicans with a minimum inhibitory concentration (MIC) value of 6.25, 25 and 50 μg/ml, respectively. The petroleum ether and methanol extracts were active against S.pneumonia and N.mucosa with MIC values of 25 and 50 μg/ml. Furthermore, we also performed the in silico virtual screening of all these compounds obtained from LC-MS data analysis against various known drug targets of bacterium and fungi. Upon analysis, we obtained 5 compounds that were efficiently binding to the drug targets. However, after performing exhaustive molecular docking and molecular dynamic simulation (MDS) analysis, it was observed that Daidzein compound is bound to drug targets more efficiently. Conclusion: The results showed that these plant extracts exhibit antimicrobial activity and ethyl acetate extract proved to exhibit the most effective antibacterial and antifungal properties. | U76: No | V76: Yes | W76: No | X76: Evaluates plant-derived compounds with antimicrobial potential as an alternative against drug resistance
A77: 35462885 | B77: Safety and immunogenicity of a hexavalent DTwP-IPV-HB-PRP∼T vaccine versus separate DTwP-HB-PRP∼T and IPV vaccines in healthy infants in India | C77: Mangarule S, Palkar S, Mitra M, Ravi MD, Dubey AP, Moureau A, Jayanth MV, Patel DM, Ravinuthala S, Jagga SR, Patnaik BN, Jordanov E, Noriega F. | D77: Vaccine X. 2022 Jan 10 | E77: Mangarule S | F77: Vaccine X | G77: 2022 | H77: 44676 | I77: PMC9019696 | K77: 10.1016/j.jvacx.2021.100137 | L77: =IF(ISNUMBER(VLOOKUP(A77,EXCL,1,FALSE)),"Excluido",IF(ISNUMBER(VLOOKUP(A77,POST,1,FALSE)),"PostAlerta",IF(ISNUMBER(VLOOKUP(A77,PRE,1,FALSE)),"PreAlerta",""))) -> PostAlerta | M77: =IF(ISNUMBER(A77),(IF(ISNUMBER(VLOOKUP(A77,KEYWORDS,1,FALSE)),"C/PalabrasClaves","S/PalabrasClaves")),"") -> S/PalabrasClaves | N77: =IF(ISNUMBER(SEARCH("TREATMENT", B77)), "4) Nuevos tratamientos", "") | P77: 2022 Jan 10 | Q77: Excluir | R77: =LEFT(P77,4) -> 2022 | S77: Jan
A78: 35419149 | B78: Delays in Diagnosis and Treatment of Bacterial Meningitis in NYC: Retrospective Cohort Analysis | C78: Torres SD, Kim CY, Das M, Ankam JV, Luche N, Harmon M, Schorr EM, Glassberg B, Morse SS, Weiss D, Gofshteyn JS, Yeshokumar AK, Thakur KT. | D78: Neurohospitalist. 2022 Apr | E78: Torres SD | F78: Neurohospitalist | G78: 2022 | H78: 44665 | I78: PMC8995590 | K78: 10.1177/19418744211037319 | L78: =IF(ISNUMBER(VLOOKUP(A78,EXCL,1,FALSE)),"Excluido",IF(ISNUMBER(VLOOKUP(A78,POST,1,FALSE)),"PostAlerta",IF(ISNUMBER(VLOOKUP(A78,PRE,1,FALSE)),"PreAlerta",""))) -> PostAlerta | M78: =IF(ISNUMBER(A78),(IF(ISNUMBER(VLOOKUP(A78,KEYWORDS,1,FALSE)),"C/PalabrasClaves","S/PalabrasClaves")),"") -> S/PalabrasClaves | P78: 2022 Apr | R78: =LEFT(P78,4) -> 2022 | S78: Apr
A79: 35113406 | B79: A Systematic Review of Multi-decade Antibiotic Resistance Data for Ocular Bacterial Pathogens in the United States | C79: Bispo PJM, Sahm DF, Asbell PA. | D79: Ophthalmol Ther. 2022 Apr | E79: Bispo PJM | F79: Ophthalmol Ther | G79: 2022 | H79: 44595 | I79: PMC8927494 | K79: 10.1007/s40123-021-00449-9 | L79: =IF(ISNUMBER(VLOOKUP(A79,EXCL,1,FALSE)),"Excluido",IF(ISNUMBER(VLOOKUP(A79,POST,1,FALSE)),"PostAlerta",IF(ISNUMBER(VLOOKUP(A79,PRE,1,FALSE)),"PreAlerta",""))) -> Excluido | M79: =IF(ISNUMBER(A79),(IF(ISNUMBER(VLOOKUP(A79,KEYWORDS,1,FALSE)),"C/PalabrasClaves","S/PalabrasClaves")),"") -> C/PalabrasClaves | N79: =IF(ISNUMBER(SEARCH("TREATMENT", B79)), "4) Nuevos tratamientos", "") | P79: 2022 Apr | Q79: Excluir | R79: =LEFT(P79,4) -> 2022 | S79: Apr
A80: 35094903 | B80: Predictors of early-onset neonatal sepsis in premature newborns: Case-control study | C80: Takassi OE, Atakouma YD, Desfrere L. | D80: Arch Pediatr. 2022 Apr | E80: Takassi OE | F80: Arch Pediatr | G80: 2022 | H80: 44592 | K80: 10.1016/j.arcped.2022.01.013 | L80: =IF(ISNUMBER(VLOOKUP(A80,EXCL,1,FALSE)),"Excluido",IF(ISNUMBER(VLOOKUP(A80,POST,1,FALSE)),"PostAlerta",IF(ISNUMBER(VLOOKUP(A80,PRE,1,FALSE)),"PreAlerta",""))) -> PostAlerta | M80: =IF(ISNUMBER(A80),(IF(ISNUMBER(VLOOKUP(A80,KEYWORDS,1,FALSE)),"C/PalabrasClaves","S/PalabrasClaves")),"") -> S/PalabrasClaves | N80: =IF(ISNUMBER(SEARCH("TREATMENT", B80)), "4) Nuevos tratamientos", "") | P80: 2022 Apr | Q80: Excluir | R80: =LEFT(P80,4) -> 2022 | S80: Apr
A81: 35358229 | B81: Assessment of genetic variation in Apis mellifera jemenitica (Hymenoptera: Apidae) based on mitochondrial Cytochrome Oxidase Subunit II and III | C81: Alattal Y, Algamdi A. | D81: PLoS One. 2022 Mar 31 | E81: Alattal Y | F81: PLoS One | G81: 2022 | H81: 44651 | I81: PMC8970473 | K81: 10.1371/journal.pone.0265454 | L81: =IF(ISNUMBER(VLOOKUP(A81,EXCL,1,FALSE)),"Excluido",IF(ISNUMBER(VLOOKUP(A81,POST,1,FALSE)),"PostAlerta",IF(ISNUMBER(VLOOKUP(A81,PRE,1,FALSE)),"PreAlerta",""))) -> PostAlerta | M81: =IF(ISNUMBER(A81),(IF(ISNUMBER(VLOOKUP(A81,KEYWORDS,1,FALSE)),"C/PalabrasClaves","S/PalabrasClaves")),"") -> S/PalabrasClaves | N81: =IF(ISNUMBER(SEARCH("TREATMENT", B81)), "4) Nuevos tratamientos", "") | P81: 2022 Mar 31 | Q81: Excluir | R81: =LEFT(P81,4) -> 2022 | S81: Mar
A82: 35368516 | B82: Distribution and Drug Resistance of Bacterial Pathogens Associated with Lower Respiratory Tract Infection in Children and the Effect of COVID-19 on the Distribution of Pathogens | C82: Zhu X, Ye T, Zhong H, Luo Y, Xu J, Zhang Q, Luo X, Wang Q, Zhang L, Song P, Zhang J. | D82: Can J Infect Dis Med Microbiol. 2022 Mar 29 | E82: Zhu X | F82: Can J Infect Dis Med Microbiol | G82: 2022 | H82: 44655 | I82: PMC8965734 | K82: 10.1155/2022/1181283 | L82: =IF(ISNUMBER(VLOOKUP(A82,EXCL,1,FALSE)),"Excluido",IF(ISNUMBER(VLOOKUP(A82,POST,1,FALSE)),"PostAlerta",IF(ISNUMBER(VLOOKUP(A82,PRE,1,FALSE)),"PreAlerta",""))) -> PostAlerta | M82: =IF(ISNUMBER(A82),(IF(ISNUMBER(VLOOKUP(A82,KEYWORDS,1,FALSE)),"C/PalabrasClaves","S/PalabrasClaves")),"") -> S/PalabrasClaves | N82: =IF(ISNUMBER(SEARCH("TREATMENT", B82)), "4) Nuevos tratamientos", "") | P82: 2022 Mar 29 | Q82: Excluir | R82: =LEFT(P82,4) -> 2022 | S82: Mar
A83: 35388353 | B83: Bacterial Culture of Tear Duct Infections Secondary to Congenital Nasolacrimal Duct Obstructions | C83: Yang W, Shen L, Wang A, Li M, Yang C. | D83: J Ophthalmol. 2022 Mar 28 | E83: Yang W | F83: J Ophthalmol | G83: 2022 | H83: 44658 | I83: PMC8979714 | K83: 10.1155/2022/9954634 | L83: =IF(ISNUMBER(VLOOKUP(A83,EXCL,1,FALSE)),"Excluido",IF(ISNUMBER(VLOOKUP(A83,POST,1,FALSE)),"PostAlerta",IF(ISNUMBER(VLOOKUP(A83,PRE,1,FALSE)),"PreAlerta",""))) -> PostAlerta | M83: =IF(ISNUMBER(A83),(IF(ISNUMBER(VLOOKUP(A83,KEYWORDS,1,FALSE)),"C/PalabrasClaves","S/PalabrasClaves")),"") -> S/PalabrasClaves | N83: =IF(ISNUMBER(SEARCH("TREATMENT", B83)), "4) Nuevos tratamientos", "") | P83: 2022 Mar 28 | Q83: Excluir | R83: =LEFT(P83,4) -> 2022 | S83: Mar
A84: 35378873 | B84: Prevalence of Moraxella Catarrhalis as a Nasal Flora among Healthy Kindergarten Children in Bhaktapur, Nepal | C84: Amatya N, Paudel G, Saud B, Wagle S, Shrestha V, Adhikari B. | D84: Interdiscip Perspect Infect Dis. 2022 Mar 26 | E84: Amatya N | F84: Interdiscip Perspect Infect Dis | G84: 2022 | H84: 44656 | I84: PMC8976674 | K84: 10.1155/2022/3989781 | L84: =IF(ISNUMBER(VLOOKUP(A84,EXCL,1,FALSE)),"Excluido",IF(ISNUMBER(VLOOKUP(A84,POST,1,FALSE)),"PostAlerta",IF(ISNUMBER(VLOOKUP(A84,PRE,1,FALSE)),"PreAlerta",""))) -> PostAlerta | M84: =IF(ISNUMBER(A84),(IF(ISNUMBER(VLOOKUP(A84,KEYWORDS,1,FALSE)),"C/PalabrasClaves","S/PalabrasClaves")),"") -> S/PalabrasClaves | N84: =IF(ISNUMBER(SEARCH("TREATMENT", B84)), "4) Nuevos tratamientos", "") | P84: 2022 Mar 26 | Q84: Excluir | R84: =LEFT(P84,4) -> 2022 | S84: Mar
A85: 35687548 | B85: Mucosal immunity of mannose-modified chitosan microspheres loaded with the nontyepable Haemophilus influenzae outer membrane protein P6 in BALB/c mice | C85: Ma Y, Zhao Y, Chen R, Sun W, Zhang Y, Qiao H, Chang Y, Kang S, Zhang Y. | D85: PLoS One. 2022 Jun 10 | E85: Ma Y | F85: PLoS One | G85: 2022 | H85: 44722 | I85: PMC9187061 | K85: 10.1371/journal.pone.0269153 | L85: =IF(ISNUMBER(VLOOKUP(A85,EXCL,1,FALSE)),"Excluido",IF(ISNUMBER(VLOOKUP(A85,POST,1,FALSE)),"PostAlerta",IF(ISNUMBER(VLOOKUP(A85,PRE,1,FALSE)),"PreAlerta",""))) -> PostAlerta | M85: =IF(ISNUMBER(A85),(IF(ISNUMBER(VLOOKUP(A85,KEYWORDS,1,FALSE)),"C/PalabrasClaves","S/PalabrasClaves")),"") -> S/PalabrasClaves | N85: 2) Nuevos tratamientos | P85: 2022 Jun 10 | Q85: Listo | R85: =LEFT(P85,4) -> 2022 | S85: Jun | T85: Nontypeable Haemophilus influenzae (NTHi) is a common opportunistic pathogen that colonizes the nasopharynx. NTHi infections result in enormous global morbidity in two clinical settings: otitis media in children and acute exacerbation of chronic obstructive pulmonary disease (COPD) in adults. Thus, there is an urgent need to design and develop effective vaccines to prevent morbidity and reduce antibiotic use. The NTHi outer membrane protein P6, a potential vaccine candidate, is highly conserved and effectively induces protective immunity. Here, to enhance mucosal immune responses, P6-loaded mannose-modified chitosan (MC) microspheres (P6-MCMs) were developed for mucosal delivery. MC (18.75%) was synthesized by the reductive amination reaction method using sodium cyanoborohydride (NaBH3CN), and P6-MCMs with an average size of 590.4±16.2 nm were successfully prepared via the tripolyphosphate (TPP) ionotropic gelation process. After intranasal immunization with P6-MCMs, evaluation of humoral immune responses indicated that P6-MCMs enhance both systemic and mucosal immune responses. Evaluation of cellular immune responses indicated that P6-MCMs enhance cellular immunity and trigger a mixed Th1/Th2-type immune response. Importantly, P6-MCMs also trigger a Th17-type immune response. They are effective in promoting lymphocyte proliferation and differentiation without toxicity in vitro. The results also demonstrate that P6-MCMs can effectively induce MHC class I- and II-restricted cross-presentation, promoting CD4+-mediated Th immune responses and CD8+-mediated cytotoxic T lymphocyte (CTL) immune responses. Evaluation of protective immunity indicated that immunization with P6-MCMs can reduce inflammation in the nasal mucosa and the lung and prevent NTHi infection. In conclusion, MCMs are a promising adjuvant-delivery system for vaccines against NTHi. | U85: No | V85: Yes | W85: Yes | X85: discusses immunization with P6-MCM can reduce inflammation in the nasal and pulmonary mucosa, and prevent NTHi infection.
A86: 35265810 | B86: Moraxella catarrhalis evades neutrophil oxidative stress responses providing a safer niche for nontypeable Haemophilus influenzae | C86: Nicchi S, Giusti F, Carello S, Utrio Lanfaloni S, Tavarini S, Frigimelica E, Ferlenghi I, Rossi Paccani S, Merola M, Delany I, Scarlato V, Maione D, Brettoni C. | D86: iScience. 2022 Feb 17 | E86: Nicchi S | F86: iScience | G86: 2022 | H86: 44630 | I86: PMC8899411 | K86: 10.1016/j.isci.2022.103931 | L86: =IF(ISNUMBER(VLOOKUP(A86,EXCL,1,FALSE)),"Excluido",IF(ISNUMBER(VLOOKUP(A86,POST,1,FALSE)),"PostAlerta",IF(ISNUMBER(VLOOKUP(A86,PRE,1,FALSE)),"PreAlerta",""))) -> PostAlerta | M86: =IF(ISNUMBER(A86),(IF(ISNUMBER(VLOOKUP(A86,KEYWORDS,1,FALSE)),"C/PalabrasClaves","S/PalabrasClaves")),"") -> S/PalabrasClaves | N86: =IF(ISNUMBER(SEARCH("TREATMENT", B86)), "4) Nuevos tratamientos", "") | P86: 2022 Feb 17 | Q86: Excluir | R86: =LEFT(P86,4) -> 2022 | S86: Feb
A87: 35369518 | B87: Corrigendum: Molecular Serotype-Specific Identification of Non-type b Haemophilus influenzae by Loop-Mediated Isothermal Amplification | C87: Takano C, Seki M, Kim DW, Kilgore PE, Fuwa K, Takahashi K, Inazaki T, Hayakawa S. | D87: Front Microbiol. 2022 Mar 14 | E87: Takano C | F87: Front Microbiol | G87: 2022 | H87: 44655 | I87: PMC8964425 | K87: 10.3389/fmicb.2022.870651 | L87: =IF(ISNUMBER(VLOOKUP(A87,EXCL,1,FALSE)),"Excluido",IF(ISNUMBER(VLOOKUP(A87,POST,1,FALSE)),"PostAlerta",IF(ISNUMBER(VLOOKUP(A87,PRE,1,FALSE)),"PreAlerta",""))) -> PostAlerta | M87: =IF(ISNUMBER(A87),(IF(ISNUMBER(VLOOKUP(A87,KEYWORDS,1,FALSE)),"C/PalabrasClaves","S/PalabrasClaves")),"") -> S/PalabrasClaves | N87: =IF(ISNUMBER(SEARCH("TREATMENT", B87)), "4) Nuevos tratamientos", "") | P87: 2022 Mar 14 | Q87: Excluir | R87: =LEFT(P87,4) -> 2022 | S87: Mar
A88: 35103473 | B88: Discovery of Small-Molecule VapC1 Nuclease Inhibitors by Virtual Screening and Scaffold Hopping from an Atomic Structure Revealing Protein-Protein Interactions with a Native VapB1 Inhibitor | C88: Sun H, Coussens NP, Danchik C, Wachsmuth LM, Henderson MJ, Patnaik S, Hall MD, Molinaro AL, Daines DA, Shen M. | D88: J Chem Inf Model. 2022 Mar 14 | E88: Sun H | F88: J Chem Inf Model | G88: 2022 | H88: 44593 | I88: PMC10041999 | J88: NIHMS1831763 | K88: 10.1021/acs.jcim.1c01188 | L88: =IF(ISNUMBER(VLOOKUP(A88,EXCL,1,FALSE)),"Excluido",IF(ISNUMBER(VLOOKUP(A88,POST,1,FALSE)),"PostAlerta",IF(ISNUMBER(VLOOKUP(A88,PRE,1,FALSE)),"PreAlerta",""))) -> PostAlerta | M88: =IF(ISNUMBER(A88),(IF(ISNUMBER(VLOOKUP(A88,KEYWORDS,1,FALSE)),"C/PalabrasClaves","S/PalabrasClaves")),"") -> C/PalabrasClaves | N88: =IF(ISNUMBER(SEARCH("TREATMENT", B88)), "4) Nuevos tratamientos", "") | P88: 2022 Mar 14 | Q88: Excluir | R88: =LEFT(P88,4) -> 2022 | S88: Mar
A89: 35360096 | B89: Predominant Bacterial and Viral Otopathogens Identified Within the Respiratory Tract and Middle Ear of Urban Australian Children Experiencing Otitis Media Are Diversely Distributed | C89: Ngo CC, Massa HM, McMonagle BA, Perry CF, Nissen MD, Sloots TP, Thornton RB, Cripps AW. | D89: Front Cell Infect Microbiol. 2022 Mar 11 | E89: Ngo CC | F89: Front Cell Infect Microbiol | G89: 2022 | H89: 44652 | I89: PMC8963760 | K89: 10.3389/fcimb.2022.775535 | L89: =IF(ISNUMBER(VLOOKUP(A89,EXCL,1,FALSE)),"Excluido",IF(ISNUMBER(VLOOKUP(A89,POST,1,FALSE)),"PostAlerta",IF(ISNUMBER(VLOOKUP(A89,PRE,1,FALSE)),"PreAlerta",""))) -> PostAlerta | M89: =IF(ISNUMBER(A89),(IF(ISNUMBER(VLOOKUP(A89,KEYWORDS,1,FALSE)),"C/PalabrasClaves","S/PalabrasClaves")),"") -> S/PalabrasClaves | N89: =IF(ISNUMBER(SEARCH("TREATMENT", B89)), "4) Nuevos tratamientos", "") | P89: 2022 Mar 11 | Q89: Excluir | R89: =LEFT(P89,4) -> 2022 | S89: Mar
A90: 35265327 | B90: Estimating the global and regional burden of meningitis in children caused by Haemophilus influenzae type b: A systematic review and meta-analysis | C90: Park JJ, Narayanan S, Tiefenbach J, Lukšić I, Ale BM, Adeloye D, Rudan I. | D90: J Glob Health. 2022 Mar 5 | E90: Park JJ | F90: J Glob Health | G90: 2022 | H90: 44630 | I90: PMC8893283 | K90: 10.7189/jogh.12.04014 | L90: =IF(ISNUMBER(VLOOKUP(A90,EXCL,1,FALSE)),"Excluido",IF(ISNUMBER(VLOOKUP(A90,POST,1,FALSE)),"PostAlerta",IF(ISNUMBER(VLOOKUP(A90,PRE,1,FALSE)),"PreAlerta",""))) -> Excluido | M90: =IF(ISNUMBER(A90),(IF(ISNUMBER(VLOOKUP(A90,KEYWORDS,1,FALSE)),"C/PalabrasClaves","S/PalabrasClaves")),"") -> S/PalabrasClaves | N90: =IF(ISNUMBER(SEARCH("TREATMENT", B90)), "4) Nuevos tratamientos", "") | P90: 2022 Mar 5 | Q90: Excluir | R90: =LEFT(P90,4) -> 2022 | S90: Mar
A91: 35146187 | B91: "Culture-positive exogenous endophthalmitis related to XEN45 gel stent implantation" | C91: Ng AW, Yip VC, Ang BC, Yip LW, Lim BA. | D91: Am J Ophthalmol Case Rep. 2022 Jan 29 | E91: Ng AW | F91: Am J Ophthalmol Case Rep | G91: 2022 | H91: 44603 | I91: PMC8818480 | K91: 10.1016/j.ajoc.2022.101291 | L91: =IF(ISNUMBER(VLOOKUP(A91,EXCL,1,FALSE)),"Excluido",IF(ISNUMBER(VLOOKUP(A91,POST,1,FALSE)),"PostAlerta",IF(ISNUMBER(VLOOKUP(A91,PRE,1,FALSE)),"PreAlerta",""))) -> PostAlerta | M91: =IF(ISNUMBER(A91),(IF(ISNUMBER(VLOOKUP(A91,KEYWORDS,1,FALSE)),"C/PalabrasClaves","S/PalabrasClaves")),"") -> S/PalabrasClaves | N91: =IF(ISNUMBER(SEARCH("TREATMENT", B91)), "4) Nuevos tratamientos", "") | P91: 2022 Jan 29 | Q91: Excluir | R91: =LEFT(P91,4) -> 2022 | S91: Jan
A92: 34838594 | B92: Surveillance and control of meningococcal disease in the COVID-19 era: A Global Meningococcal Initiative review | C92: Alderson MR, Arkwright PD, Bai X, Black S, Borrow R, Caugant DA, Dinleyici EC, Harrison LH, Lucidarme J, McNamara LA, Meiring S, Sáfadi MAP, Shao Z, Stephens DS, Taha MK, Vazquez J, Zhu B, Collaborators G. | D92: J Infect. 2022 Mar | E92: Alderson MR | F92: J Infect | G92: 2022 | H92: 44528 | I92: PMC8611823 | K92: 10.1016/j.jinf.2021.11.016 | L92: =IF(ISNUMBER(VLOOKUP(A92,EXCL,1,FALSE)),"Excluido",IF(ISNUMBER(VLOOKUP(A92,POST,1,FALSE)),"PostAlerta",IF(ISNUMBER(VLOOKUP(A92,PRE,1,FALSE)),"PreAlerta",""))) -> Excluido | M92: =IF(ISNUMBER(A92),(IF(ISNUMBER(VLOOKUP(A92,KEYWORDS,1,FALSE)),"C/PalabrasClaves","S/PalabrasClaves")),"") -> C/PalabrasClaves | N92: =IF(ISNUMBER(SEARCH("TREATMENT", B92)), "4) Nuevos tratamientos", "") | P92: 2022 Mar | Q92: Excluir | R92: =LEFT(P92,4) -> 2022 | S92: Mar
A93: 35613138 | B93: Multilevel analysis of predictors of multiple indicators of childhood vaccination in Nigeria | C93: Aheto JMK, Pannell O, Dotse-Gborgbortsi W, Trimner MK, Tatem AJ, Rhoda DA, Cutts FT, Utazi CE. | D93: PLoS One. 2022 May 25 | E93: Aheto JMK | F93: PLoS One | G93: 2022 | H93: 44706 | I93: PMC9132327 | K93: 10.1371/journal.pone.0269066 | L93: =IF(ISNUMBER(VLOOKUP(A93,EXCL,1,FALSE)),"Excluido",IF(ISNUMBER(VLOOKUP(A93,POST,1,FALSE)),"PostAlerta",IF(ISNUMBER(VLOOKUP(A93,PRE,1,FALSE)),"PreAlerta",""))) -> PostAlerta | M93: =IF(ISNUMBER(A93),(IF(ISNUMBER(VLOOKUP(A93,KEYWORDS,1,FALSE)),"C/PalabrasClaves","S/PalabrasClaves")),"") -> S/PalabrasClaves | N93: 3) Inmunización | P93: 2022 May 25 | Q93: Listo | R93: =LEFT(P93,4) -> 2022 | S93: May | T93: Background: Substantial inequalities exist in childhood vaccination coverage levels. To increase vaccine uptake, factors that predict vaccination coverage in children should be identified and addressed. Methods: Using data from the 2018 Nigeria Demographic and Health Survey and geospatial data sets, we fitted Bayesian multilevel binomial and multinomial logistic regression models to analyse independent predictors of three vaccination outcomes: receipt of the first dose of Pentavalent vaccine (containing diphtheria-tetanus-pertussis, Hemophilus influenzae type B and Hepatitis B vaccines) (PENTA1) (n = 6059) and receipt of the third dose having received the first (PENTA3/1) (n = 3937) in children aged 12-23 months, and receipt of measles vaccine (MV) (n = 11839) among children aged 12-35 months. Results: Factors associated with vaccination were broadly similar for documented versus recall evidence of vaccination. Based on any evidence of vaccination, we found that health card/document ownership, receipt of vitamin A and maternal educational level were significantly associated with each outcome. Although the coverage of each vaccine dose was higher in urban than rural areas, urban residence was not significant in multivariable analyses that included travel time. Indicators relating to socio-economic status, as well as ethnic group, skilled birth attendance, lower travel time to the nearest health facility and problems seeking health care were significantly associated with both PENTA1 and MV. Maternal religion was related to PENTA1 and PENTA3/1 and maternal age related to MV and PENTA3/1; other significant variables were associated with one outcome each. Substantial residual community level variances in different strata were observed in the fitted models for each outcome. Conclusion: Our analysis has highlighted socio-demographic and health care access factors that affect not only beginning but completing the vaccination series in Nigeria. Other factors not measured by the DHS such as health service quality and community attitudes should also be investigated and addressed to tackle inequities in coverage. | U93: No | V93: No | W93: Yes | X93: Identifies factors influencing childhood immunization coverage, key to improving immunization equity and effectiveness
A94: 34787536 | B94: Safety evaluation of the DTaP5-IPV-Hib-HepB vaccine: a review | C94: Fortunato F, Martinelli D, Lopalco PL, Prato R. | D94: Expert Opin Drug Saf. 2022 Mar | E94: Fortunato F | F94: Expert Opin Drug Saf | G94: 2022 | H94: 44517 | K94: 10.1080/14740338.2022.2007882 | L94: =IF(ISNUMBER(VLOOKUP(A94,EXCL,1,FALSE)),"Excluido",IF(ISNUMBER(VLOOKUP(A94,POST,1,FALSE)),"PostAlerta",IF(ISNUMBER(VLOOKUP(A94,PRE,1,FALSE)),"PreAlerta",""))) -> Excluido | M94: =IF(ISNUMBER(A94),(IF(ISNUMBER(VLOOKUP(A94,KEYWORDS,1,FALSE)),"C/PalabrasClaves","S/PalabrasClaves")),"") -> S/PalabrasClaves | N94: =IF(ISNUMBER(SEARCH("TREATMENT", B94)), "4) Nuevos tratamientos", "") | P94: 2022 Mar | Q94: Excluir | R94: =LEFT(P94,4) -> 2022 | S94: Mar
A95: 34606144 | B95: In vitro Inhibition of respiratory pathogens by lactobacillus and alpha haemolytic streptococci from Aboriginal and Torres Strait Islander children | C95: Coleman A, Håkansson A, Grahn Håkansson E, Cottrell K, Bialasiewicz S, Zaugg J, Cervin A. | D95: J Appl Microbiol. 2022 Mar | E95: Coleman A | F95: J Appl Microbiol | G95: 2022 | H95: 44473 | K95: 10.1111/jam.15320 | L95: =IF(ISNUMBER(VLOOKUP(A95,EXCL,1,FALSE)),"Excluido",IF(ISNUMBER(VLOOKUP(A95,POST,1,FALSE)),"PostAlerta",IF(ISNUMBER(VLOOKUP(A95,PRE,1,FALSE)),"PreAlerta",""))) -> PostAlerta | M95: =IF(ISNUMBER(A95),(IF(ISNUMBER(VLOOKUP(A95,KEYWORDS,1,FALSE)),"C/PalabrasClaves","S/PalabrasClaves")),"") -> C/PalabrasClaves | N95: =IF(ISNUMBER(SEARCH("TREATMENT", B95)), "4) Nuevos tratamientos", "") | P95: 2022 Mar | Q95: Excluir | R95: =LEFT(P95,4) -> 2022 | S95: Mar
A96: 34446339 | B96: RSV pneumonia with or without bacterial co-infection among healthy children | C96: Lin HC, Liu YC, Hsing TY, Chen LL, Liu YC, Yen TY, Lu CY, Chang LY, Chen JM, Lee PI, Huang LM, Lai FP. | D96: J Formos Med Assoc. 2022 Mar | E96: Lin HC | F96: J Formos Med Assoc | G96: 2022 | H96: 44435 | K96: 10.1016/j.jfma.2021.08.012 | L96: =IF(ISNUMBER(VLOOKUP(A96,EXCL,1,FALSE)),"Excluido",IF(ISNUMBER(VLOOKUP(A96,POST,1,FALSE)),"PostAlerta",IF(ISNUMBER(VLOOKUP(A96,PRE,1,FALSE)),"PreAlerta",""))) -> PostAlerta | M96: =IF(ISNUMBER(A96),(IF(ISNUMBER(VLOOKUP(A96,KEYWORDS,1,FALSE)),"C/PalabrasClaves","S/PalabrasClaves")),"") -> S/PalabrasClaves | N96: =IF(ISNUMBER(SEARCH("TREATMENT", B96)), "4) Nuevos tratamientos", "") | P96: 2022 Mar | Q96: Excluir | R96: =LEFT(P96,4) -> 2022 | S96: Mar
A97: 33356678 | B97: Utility of immunology, microbiology, and helminth investigations in clinical assessment of severe asthma | C97: Singer A, Ali FR, Quantrill S, North N, Stevens M, Lambourne J, Grigoriadou S, Pfeffer PE. | D97: J Asthma. 2022 Mar | E97: Singer A | F97: J Asthma | G97: 2022 | H97: 44193 | K97: 10.1080/02770903.2020.1868496 | L97: =IF(ISNUMBER(VLOOKUP(A97,EXCL,1,FALSE)),"Excluido",IF(ISNUMBER(VLOOKUP(A97,POST,1,FALSE)),"PostAlerta",IF(ISNUMBER(VLOOKUP(A97,PRE,1,FALSE)),"PreAlerta",""))) -> PostAlerta | M97: =IF(ISNUMBER(A97),(IF(ISNUMBER(VLOOKUP(A97,KEYWORDS,1,FALSE)),"C/PalabrasClaves","S/PalabrasClaves")),"") -> S/PalabrasClaves | N97: =IF(ISNUMBER(SEARCH("TREATMENT", B97)), "4) Nuevos tratamientos", "") | P97: 2022 Mar | Q97: Excluir | R97: =LEFT(P97,4) -> 2022 | S97: Mar
A98: 35295756 | B98: Sleep Disordered Breathing and Recurrent Tonsillitis Are Associated With Polymicrobial Bacterial Biofilm Infections Suggesting a Role for Anti-Biofilm Therapies | C98: Mateus T, Seppanen EJ, de Gier C, Clark S, Coates H, Vijayasekaran S, Prosser K, Wiertsema SP, Fuery A, Kirkham LS, Richmond PC, Thornton RB. | D98: Front Cell Infect Microbiol. 2022 Feb 28 | E98: Mateus T | F98: Front Cell Infect Microbiol | G98: 2022 | H98: 44637 | I98: PMC8918577 | K98: 10.3389/fcimb.2022.831887 | L98: =IF(ISNUMBER(VLOOKUP(A98,EXCL,1,FALSE)),"Excluido",IF(ISNUMBER(VLOOKUP(A98,POST,1,FALSE)),"PostAlerta",IF(ISNUMBER(VLOOKUP(A98,PRE,1,FALSE)),"PreAlerta",""))) -> PostAlerta | M98: =IF(ISNUMBER(A98),(IF(ISNUMBER(VLOOKUP(A98,KEYWORDS,1,FALSE)),"C/PalabrasClaves","S/PalabrasClaves")),"") -> C/PalabrasClaves | N98: =IF(ISNUMBER(SEARCH("TREATMENT", B98)), "4) Nuevos tratamientos", "") | P98: 2022 Feb 28 | Q98: Excluir | R98: =LEFT(P98,4) -> 2022 | S98: Feb
A99: 36304309 | B99: NCMW: A Python Package to Analyze Metabolic Interactions in the Nasal Microbiome | C99: Glöckler M, Dräger A, Mostolizadeh R. | D99: Front Bioinform. 2022 Feb 25 | E99: Glöckler M | F99: Front Bioinform | G99: 2022 | H99: 44862 | I99: PMC9580955 | K99: 10.3389/fbinf.2022.827024 | L99: =IF(ISNUMBER(VLOOKUP(A99,EXCL,1,FALSE)),"Excluido",IF(ISNUMBER(VLOOKUP(A99,POST,1,FALSE)),"PostAlerta",IF(ISNUMBER(VLOOKUP(A99,PRE,1,FALSE)),"PreAlerta",""))) -> PostAlerta | M99: =IF(ISNUMBER(A99),(IF(ISNUMBER(VLOOKUP(A99,KEYWORDS,1,FALSE)),"C/PalabrasClaves","S/PalabrasClaves")),"") -> S/PalabrasClaves | N99: =IF(ISNUMBER(SEARCH("TREATMENT", B99)), "4) Nuevos tratamientos", "") | P99: 2022 Feb 25 | Q99: Excluir | R99: =LEFT(P99,4) -> 2022 | S99: Feb
A100: 35210526 | B100: Comparative pangenome analysis of capsulated Haemophilus influenzae serotype f highlights their high genomic stability | C100: Gonzalez-Diaz A, Carrera-Salinas A, Pinto M, Cubero M, van der Ende A, Langereis JD, Domínguez MÁ, Ardanuy C, Bajanca-Lavado P, Marti S. | D100: Sci Rep. 2022 Feb 24 | E100: Gonzalez-Diaz A | F100: Sci Rep | G100: 2022 | H100: 44617 | I100: PMC8873416 | K100: 10.1038/s41598-022-07185-5 | L100: =IF(ISNUMBER(VLOOKUP(A100,EXCL,1,FALSE)),"Excluido",IF(ISNUMBER(VLOOKUP(A100,POST,1,FALSE)),"PostAlerta",IF(ISNUMBER(VLOOKUP(A100,PRE,1,FALSE)),"PreAlerta",""))) -> PostAlerta | M100: =IF(ISNUMBER(A100),(IF(ISNUMBER(VLOOKUP(A100,KEYWORDS,1,FALSE)),"C/PalabrasClaves","S/PalabrasClaves")),"") -> S/PalabrasClaves | N100: =IF(ISNUMBER(SEARCH("TREATMENT", B100)), "4) Nuevos tratamientos", "") | P100: 2022 Feb 24 | Q100: Revisar | R100: =LEFT(P100,4) -> 2022 | S100: Feb
...

Sheet Test
A1: PMID | B1: Title | C1: Categoria | D1: subcategoria | E1: Estado | F1: Abstract | G1: 1) Antimicrobial Resistance stain | H1: 2) New treatment | I1: 3) Immunization | J1: Human_summary
A2: 34362705 | B2: Septicemia and meningitis associated with Haemophilus influenzae type b vaccine failure | C2: 3) Inmunización | E2: Listo | F2: Septicemia and meningitis associated with Haemophilus influenzae type b vaccine failure | G2: No | H2: No | I2: Yes | J2: Describes a case of Hib septicemia and meningitis after vaccination, highlighting flaws in vaccine efficacy and the need for surveillance.
A3: 28506825 | B3: Multiple drug resistance in Haemophilus influenzae isolated from patients in Bangkok, Thailand | C3: 1) Reporte de cepas resistentes | E3: Listo | F3: Multiple drug resistance in Haemophilus influenzae isolated from patients in Bangkok, Thailand | G3: Yes | H3: No | I3: No | J3: The emergence of multi-resistant H. influenzae strains in Bangkok is documented, warning of the spread of antibiotic resistance.
A4: 27289531 | B4: Increasing resistance to fluoroquinolones among Haemophilus species in Southern Taiwan | C4: 1) Reporte de cepas resistentes | E4: Listo | F4: Increasing resistance to fluoroquinolones among Haemophilus species in Southern Taiwan | G4: Yes | H4: No | I4: No | J4: In southern Taiwan, Haemophilus spp. are showing increasing resistance to fluoroquinolones, compromising standard therapies.
A5: 28332810 | B5: Betalaktamresistens hos Haemophilus influenzae | C5: 1) Reporte de cepas resistentes | E5: Listo | F5: Betalaktamresistens hos Haemophilus influenzae | G5: Yes | H5: No | I5: No | J5: Describes the increase in H. influenzae strains with resistance to β-lactams.
A6: 27181174 | B6: Antimicrobial resistance in cystic fibrosis isolates of Haemophilus influenzae | C6: 1) Reporte de cepas resistentes | F6: Antimicrobial resistance in cystic fibrosis isolates of Haemophilus influenzae | G6: Yes | H6: No | I6: No | J6: Antimicrobial resistance in cystic fibrosis Haemophilus influenzae strains presents challenges in the treatment and management of pulmonary infections.
A7: 26369355 | B7: Acquired macrolide resistance genes in Haemophilus influenzae?-authors' response | C7: 1) Reporte de cepas resistentes | F7: Acquired macrolide resistance genes in Haemophilus influenzae?-authors' response | G7: Yes | H7: No | I7: No | J7: Describes acquired macrolide resistance genes in H. influenzae, key to monitoring and managing resistant strains
A8: 26318192 | B8: Comment on: Acquired macrolide resistance genes in Haemophilus influenzae? | C8: 1) Reporte de cepas resistentes | F8: Comment on: Acquired macrolide resistance genes in Haemophilus influenzae? | G8: Yes | H8: No | I8: No | J8: Analyzes acquired resistance genes, key to managing macrolide-resistant strains.
A9: 24826882 | B9: Beware and be aware, haemophilus influenzae betalactamase-negative-ampicillin-resistant is not rare | C9: 1) Reporte de cepas resistentes | F9: Beware and be aware, haemophilus influenzae betalactamase-negative-ampicillin-resistant is not rare | G9: Yes | H9: No | I9: No | J9: Warns about the resistance of Haemophilus influenzae to ampicillin, highlighting its prevalence despite the absence of beta-lactamase.
A10: 35192786 | B10: Product review on the IMD serogroup B vaccine Bexsero® | C10: 3) Inmunización | E10: Listo | F10: Bexsero® is a multicomponent vaccine composed of four major proteins of Neisseria meningitidis: the fHbp, NHBA, NadA and PorA. This vaccine was licensed against invasive meningococcal disease (IMD) due to serogroup B isolates. When administered alone, Bexsero® showed a safety profile similar to other childhood vaccines. It provides an excellent immunogenicity but that requires booster doses in infants and young children. Although the vaccine does not seem to impact on acquisition of carriage of serogroup B isolates, it confers protection against isolates of serogroup B harboring distinct but cross-reactive variants of fHbp, NadA and NHBA. Primary vaccination schemes in infancy underwent a rapid increase after a toddler booster suggesting an anamnestic response and the establishment of a memory response. As Bexsero® targets sub-capsular proteins that can be conserved regardless the capsule, the vaccine can be effective against non-B isolates such as isolates of serogroups W and X. | G10: No | H10: No | I10: Yes | J10: Because it describes the composition, efficacy, safety profile and immunological response of Bexsero®, a vaccine against invasive meningococcal disease caused by Neisseria meningitidis serogroup B, and its potential effectiveness against other serogroups through immunization directed at conserved subcapsular proteins
A11: 35108152 | B11: Surveillance on the adverse events following immunization with the pentavalent vaccine in Zhejiang, China | C11: 3) Inmunización | E11: Revisar | F11: Objectives: The aim of this study is to describe the reporting rate of adverse events following immunization (AEFI) with pentavalent vaccine: diphtheria-pertussis-tetanus-poliomyelitis-Haemophilus influenzae type b (DPT-IPV/Hib), and to determine whether the reporting rate of AEFI following DPT-IPV/Hib was higher than the average level of the other vaccines. Methods: Review and describe the AEFI reported to national adverse event following immunization surveillance system (NAEFISS) in Zhejiang province from 2015 to 2020. Reporting rates of AEFI were calculated by age, city, severity of AEFI, categories of AEFI, and reaction categories. The data mining algorithm used in this study was reporting odds ratio (ROR). A value of ROR‑1.96SE >1 (standard error [SE]) was considered as positive signal. Results: NAEFISS received 5726 AEFI reports following DTP-IPV/Hib, with a reporting rate of 20.01/10000 doses. Of the reported AEFI, 202 were serious vaccine product-related reactions, including two cases of anaphylactic shock, five cases of Guillain Barre Syndrome (GBS) and two cases of acute disseminated encephalomyelitis. The reporting rate of fever/redness/induration was the highest among all the clinical diagnosis (14.97/10000 doses). The positive signals were obtained for allergic rash (ROR-1.96SE: 1.36), febrile convulsion (ROR-1.96SE: 1.32) and GBS (ROR-1.96SE: 1.16). Conclusion: The present findings bolstered that the DTP-IPV/Hib administered as the four-dose schedule was generally well tolerated in Chinese infants as we did not identify any new/unexpected safety concern from the NAEFISS during a six-year timespan. Keywords: AEFI (adverse events following immunization); DPT-IPV/Hib(diphtheria-pertussis-tetanus-poliomyelitis-Hib combined vaccine); safety; surveillance; vaccination. | G11: No | H11: No | I11: Yes | J11: Study on safety and adverse event reporting after vaccine administration key to immunization programs
A12: 34319865 | B12: Impact of pneumococcal conjugate vaccines on healthcare utilization and direct costs for otitis media in children ≤2 years of age in two Swedish regions | C12: 3) Inmunización | E12: Listo | F12: In Sweden, the 7-valent pneumococcal conjugate vaccine (PCV7) was introduced in 2009 and replaced by the pneumococcal non-typeable Haemophilus influenzae protein D conjugate vaccine (PHiD-CV) or the 13- valent PCV (PCV13) from late 2009. We assessed the impact of PCVs on rates of antibiotic prescribing, tympanostomy tube placement (TTP), and healthcare resource utilization and direct costs of physician- diagnosed otitis media/acute otitis media (OM) in children ≤2 years of age living in Skåne (PCV7 then PHiD- CV) or Västra Götalandsregionen (VGR; PCV7 then PCV13). Retrospective cohort study using linked patient- level data from national and regional (Skåne and VGR) healthcare databases in Sweden from July 1, 2005, to December 31, 2013 (NCT02742753). Descriptive time-series analyses showed antibiotic prescriptions and TTP incidence declined after PHiD-CV/PCV13 introduction versus the pre-PCV period. The annualized mean frequencies of antibiotic use, primary care visits, outpatient visits, TTP and myringotomy procedures all decreased after PHiD-CV/PCV13 compared with pre-PCV cohorts. Annualized mean total OM-associated healthcare costs decreased in the PCV7 versus pre-PCV cohorts by 20.0% in Skåne and 10.2% in VGR, and further declined in the PHiD-CV and PCV13 cohorts (20.7% and 15.3%, respectively, relative to the PCV7 cohort), although the duration of PCV7 use differed between regions. Decreases in adjusted annualized cost ratios between cohorts per child susceptible to OM were statistically significant after PCV7 introduction and again with either PHiD-CV or PCV13 introduction in both regions. Following sequential PCV introduction, OM-related healthcare utilization and associated costs decreased in the study regions in Sweden. Plain language summary: What is the context?Otitis media is one of the most frequent reasons for healthcare visits and antibiotic use among young children. Although it is considered as a mild illness, the overall economic burden is substantial due to its high frequency.Otitis media can be caused by different bacteria including Streptococcus pneumoniae, which is also responsible for pneumonia and meningitis. Pneumococcal conjugate vaccines Prevenar (Pfizer Inc.), Synflorix (GSK), and Prevenar 13 (Pfizer Inc.) protect against pneumococcal diseases and reduce its occurrence.However, it is not known how the routine use of these vaccines may affect otitis media-related healthcare resources and costs.What is new?In this study, we assessed trends in rates of healthcare utilization and associated costs due to otitis media in young children before (2005-2008) and after (2009-2013) use of pneumococcal conjugate vaccines. The study was conducted in two Swedish regions; one used Prevenar then Synflorix, while the other used Prevenar then Prevenar 13.We found that compared to the period before pneumococcal conjugate vaccine implementation, the postpneumococcal conjugate vaccine period was associated with:What is the impact on current thinking?The use of pneumococcal conjugate vaccines effectively reduces healthcare utilization and resources associated with otitis mediaThis indirect effect on the reduction of otitis media burden provides further benefit to the implementation of pneumococcal vaccination. Keywords: Cost; Sweden; antibiotics; otitis media; pneumococcal conjugate vaccines. | G12: No | H12: No | I12: Yes | J12: This work is classified in immunization because it evaluates the impact of penumococcal vaccines on the reduction of infections and health resources in children.
A13: 33605846 | B13: Exploring the evidence behind the comparable impact of the pneumococcal conjugate vaccines PHiD-CV and PCV13 on overall pneumococcal disease | C13: 3) Inmunización | E13: Listo | F13: The worldwide implementation of pneumococcal conjugate vaccines (PCVs) in children has reduced the overall pneumococcal disease burden. Two PCVs are widely available for infant vaccination: the pneumococcal non-typeable Haemophilus influenzae protein D conjugate vaccine (PHiD-CV) and the 13-valent PCV (PCV13). While these PCVs differ in serotype composition (PCV13 includes polysaccharides of serotypes 3, 6A and 19A; PHiD-CV does not), their impact on the overall pneumococcal disease burden in children is comparable. This commentary summarizes the evidence of comparability between PHiD-CV and PCV13 and explores why differences in serotype composition may not necessarily translate into a differential clinical impact. Both vaccines confer similarly high protection against disease caused by vaccine serotypes and lead to a partial replacement by non-vaccine serotypes. PHiD-CV does not protect against serotype 3 disease (not included in the vaccine) and PCV13's effect on this serotype has been inconsistent. PHiD-CV provides some cross-protection against disease caused by vaccine-related serotype 19A but neither vaccine has fully controlled 19A disease. While protection against 19A is higher for PCV13 than PHiD-CV, replacement by non-PCV13 serotypes in settings with a PCV13 program appears to compensate for this difference. This results in a similar residual overall disease burden with both vaccines. Keywords: PCV10; PCV13; PHiD-CV; Pneumococcal conjugate vaccine; children; invasive pneumococcal disease; otitis media; pneumonia; replacement; serotypes. | G13: No | H13: No | I13: Yes | J13: This work is classified in immunization because it analyzes and compares the effectiveness of two pneumococcal conjugate vaccines, focusing on their impact on disease reduction and protection in children.
A14: 36578495 | B14: Inhibition of the different complement pathways has varying impacts on the serum bactericidal activity and opsonophagocytosis against Haemophilus influenzae type b | C14: 3) Inmunización | E14: Revisar | F14: Defense against Haemophilus influenzae type b (Hib) is dependent on antibodies and complement, which mediate both serum bactericidal activity (SBA) and opsonophagocytosis. Here we evaluated the influence of capsule-specific antibodies and complement inhibitors targeting the central component C3, the alternative pathway (AP; fB, fD), the lectin pathway (LP; MASP-2) and the terminal pathway (C5) on both effector functions. Findings may be relevant for the treatment of certain diseases caused by dysregulation of the complement system, where inhibitors of complement factors C3 or C5 are used. Inhibitors against other complement components are being evaluated as potential alternative treatment options that may carry a reduced risk of infection by encapsulated bacteria. Serum and reconstituted blood of healthy adults were tested for bactericidal activity before and after vaccination with the Hib capsule-conjugate vaccine ActHIB. Most sera had bactericidal activity prior to vaccination, but vaccination significantly enhanced SBA titers. Independently of the vaccination status, both C3 and C5 inhibition abrogated SBA, whereas inhibition of the LP had no effect. AP inhibition had a major inhibitory effect on SBA of pre- vaccination serum, but vaccination mitigated this inhibition for all disease isolates tested. Despite this, SBA-mediated killing of some Hib isolates remained retarded. Even for the most serum-resistant isolate, SBA was the dominating defense mechanism in reconstituted whole blood, as addition of blood cells to the serum did not enhance bacterial killing. Limited Fc receptor-mediated opsonophagocytosis was unmasked when bacterial killing by the membrane attack complex was blocked. In the presence of C3 or C5 inhibitors, addition of post-vaccination, but not of pre-vaccination serum to the blood cells triggered opsonophagocytosis, leading to suppression of bacterial multiplication. Taken together, our data indicate that for host defense against Hib, killing by SBA is more efficient than by blood cell opsonophagocytosis. However, additional defense mechanisms, such as bacterial clearance by spleen and liver, may play an important role in preventing Hib-mediated sepsis, in particular for Hib isolates with increased serum-resistance. Results indicate potentially improved safety profile of AP inhibitors over C3 and C5 inhibitors as alternative therapeutic agents in patients with increased susceptibility to Hib infection. Keywords: Haemophilus influenzae type b; alternative pathway (AP); complement inhibitors; immunotherapy; opsonophagocytosis; serum bactericidal activity (SBA); vaccination. | G14: No | H14: No | I14: Yes | J14: This work is classified in immunization because it analyzes how vaccination with Hib enhances the immune response, potentiating the antibody- and complement-mediated bactericidal activity against Haemophilus influenzae type b.
A15: 36530676 | B15: Molecular epidemiology and antimicrobial resistance of Haemophilus influenzae in Guiyang, Guizhou, China | C15: 1) Reporte de cepas resistentes | E15: Listo | F15: Background: The widespread use of antimicrobials and Haemophilus influenzae type b (Hib) vaccine worldwide has altered the epidemiological patterns of invasive H. influenzae. Nonetheless, little is currently known on the epidemiological characteristics of H. influenzae in Guiyang, Guizhou, China. Objective: To determine the serotype distribution, antimicrobial resistance and Multilocus Sequence Typing (MLST) of H. influenzae in hospitalized patients in Guiyang City. Methods: A total of 196 clinical isolates from hospitalized patients were collected. Serotypes were determined according to the specific capsule gene, bexA, amplified by PCR. According to the guidelines of Clinical and Laboratory Standards Institute (CLSI) 2020 drug susceptibility tested, and the results determined. The chromogenic cephalosporin nitrocefin method was used to detect β-lactamase production, β-lactamase negative, ampicillin-resistant (BLNAR) strains were detected by PCR amplification and sequencing of the penicillin-binding protein 3 (PBP3) locus of ftsI. Multilocus Sequence Typing was performed for molecular typing. Results: All isolates studied were non-typeable H. influenzae (NTHi). Most patients originated from the pediatrics department (78.6%, 154/196), and suffered from lung with respiratory tract infection (pneumonia and bronchitis, 68.4%, 134/196). The resistance rates of ampicillin, cefaclor and azithromycin were 71.4% (140/196), 36.7% (72/196) and 34.2% (67/196), respectively. 40.3% (79/196) of strains were β-lactamase positive ampicillin-resistant (BLPAR). All BLPAR carried the TEM-1 gene. 9.2% (18/196) were β-lactamase negative ampicillin-resistant strains (BLNAR). The PBP3 mutation was detected in the ampicillin-resistant strains (n = 113), of which 18 belonged to group IIa. A total of 49 sequence types (ST) and 23 clonal complexes (CC) were detected, among which CC107 (ST107, n = 27; ST1002, n = 5; ST1218, n = 5) was the most frequent clonal complexes. BLPAR isolates mostly belonged to ST107 (20/79), while BLNAR was predominantly distributed in ST12 (5/18). Conclusion: H. influenzae infections are predominately caused by genetically diverse NTHi among hospitalized patients in Guiyang. The prevalence of β-lactamase production and PBP3 mutation may contribute to the high local ampicillin resistance rate. Keywords: Haemophilus influenzae; antimicrobial resistance; ftsI gene; molecular epidemiology; multilocus sequence type | G15: Yes | H15: No | I15: No | J15: Analyzes resistance, genes and strain distribution, focused on clinical epidemiology, not on vaccine effects or immune responses.
A16: 36466507 | B16: Parental preference for Haemophilus influenzae type b vaccination in Zhejiang Province, China: A discrete choice experiment | C16: 3) Inmunización | E16: Listo | F16: Background: China is the only country in the world that has not included the Haemophilus influenzae type b (Hib) vaccine in its National Immunization Program, making it more difficult to eliminate Hib-related diseases through Hib vaccination. It is necessary to study parental preferences for Hib vaccination to optimize vaccine promotion strategies in China. Objective: This study aimed to investigate Chinese parental preference for five attributes of Hib vaccination, i.e., the place of origin, effectiveness, adverse event, doctors' recommendation, and the price of full vaccination when making a decision to vaccinate their children under 2 years old. Methods: A cross-sectional survey was conducted in two cities in Zhejiang Province from November to December in 2020 using a discrete choice experiment (DCE). A mixed logit model was used to estimate participating parents' preference for Hib vaccination attributes included in the DCE. Subgroup analysis and probability analysis were also conducted to capture the heterogeneity and trade-off of parental preference for Hib vaccination. Results: Data from 6,168 observations were included in the analyses. Parents of children are, on average, more likely to voice a positive preference for Hib vaccination. Such attributes of Hib vaccination as effectiveness and doctor's recommendation have a significant positive influence on parents' preference for Hib vaccination, while imported vaccines, adverse events, and the price of full vaccination have a significant negative influence on parents' preference. Parents with different demographic characteristics also existed heterogeneities in preference for Hib vaccination. Parents will make a trade-off on price if the Hib vaccine has a good performance on effectiveness and safety. Conclusion: The study found that, regardless of the place of origin of the Hib vaccine, parents with children under 2 years old prefer to compromise on price if the vaccine has a better effectiveness and safety profile. A proactive recommendation from doctors would strengthen their willingness for Hib vaccination. These findings help aid the development of communication strategies with parents for Hib vaccination in China. Keywords: Chinese parents; Hib vaccination; discrete choice experiment; immunization policy; mixed logit model; parental preference. | G16: No | H16: No | I16: Yes | J16: Informs on the preference or not of parents for the use of the vaccine against Haemophilus influenzae type b (Hib) in children under 2 years of age.
A17: 36170255 | B17: Streptococcus pyogenes can support or inhibit growth of Haemophilus influenzae by supplying or restricting extracellular NAD | C17: 1) Reporte de cepas resistentes | E17: Listo | F17: Nicotinamide adenine dinucleotide (NAD+) is an essential co-factor for cellular metabolism and serves as a substrate in enzymatic processes. NAD+ is produced by de novo synthesis or salvage pathways in nearly all bacterial species. Haemophilus influenzae lacks the capacity for de novo synthesis, so it is dependent on import of NAD+ from the external environment or salvage biosynthetic pathways for recycling of NAD+ precursors and breakdown products. However, the actual sources of NAD+ utilized by H. influenzae in the respiratory tract are not well defined. In this study, we found that a variety of bacteria, including species found in the upper airway of humans, released NAD+ that was readily detectable in extracellular culture fluid, and which supported growth of H. influenzae in vitro. By contrast, certain strains of Streptococcus pyogenes (group A streptococcus or GAS) inhibited growth of H. influenzae in vitro by secreting NAD+-glycohydrolase (NADase), which degraded extracellular NAD+. Conversely, GAS strains that lacked enzymatically active NADase released extracellular NAD+, which could support H. influenzae growth. Our results suggest that many bacterial species, including normal flora of the upper airway, release NAD+ into the environment. GAS is distinctive in its ability to both release and degrade NAD+. Thus, colonization of the airway with H. influenzae may be promoted or restricted by co-colonization with GAS in a strain-specific manner that depends, respectively, on release of NAD+ or secretion of active NADase. We suggest that, in addition to its role as a cytotoxin for host cells, NADase may serve a separate function by restricting growth of H. influenzae in the human respiratory tract. | G17: No | H17: No | I17: No | J17: Does not report findings on novel strains or propose a therapy. It is a study on ecological and biochemical mechanisms in clinical microbiology.
A18: 36107979 | B18: Haemophilus influenzae serotype b seroprevalence in central Lao PDR before and after vaccine introduction | C18: 3) Inmunización | E18: Listo | F18: Introduction: Vaccination has dramatically reduced invasive Haemophilus influenzae type b (Hib) disease worldwide. Hib vaccination was introduced in the Lao PDR in 2009, as part of the pentavalent vaccine. To contribute to the understanding of the epidemiology of Hib in Lao PDR and the protection levels before and after the introduction of the vaccination, we tested serum samples from existing cohorts of vaccine age-eligible children and unvaccinated adolescents for antibodies against Hib. Methods: Serum samples from 296 adolescents born before vaccine introduction and from 1017 children under 5 years (vaccinated and unvaccinated) were tested for anti-Hib antibodies by ELISA. Bivariate analyses were performed to investigate factors associated with long-term protection. Results: The vast majority of all participants showed evidence of short- (42.7%) or long-term (56.1%) protection against Hib. Almost all of the unvaccinated adolescents had antibody titers indicating short-term protection and almost half (45.6%) were long-term protected. Nearly all children (>99.0%) were at least short-term protected, even those that were unvaccinated or whose vaccination status was unknown. Among vaccinated children, participants vaccinated more than 1 or 2 years ago and with a mid-upper arm circumference z-score < -2 were less likely to be long-term protected. Discussion: Nearly all adolescents born before the introduction of Hib vaccination in the Lao PDR had antibody titers corresponding to at least short-term protection, indicating a high burden of Hib disease at that time. After vaccine introduction, all but four children (>99%) showed at least short-term protection. Possible explanations for the proportion of protected, yet apparently unvaccinated children, may be past infections, cross-reacting antibodies or faulty vaccination documentation. Our results highlight the need for robust surveillance and reporting of invasive Hib disease to determine the burden of disease despite vaccination. | G18: No | H18: No | I18: Yes | J18: Evaluates Hib vaccine coverage in Laos, antibody levels and immune protection in different groups after the introduction of vaccination.
A19: 36159837 | B19: Cooperative action of SP-A and its trimeric recombinant fragment with polymyxins against Gram-negative respiratory bacteria | C19: 2) Nuevos tratamientos | E19: Listo | F19: The exploration of therapies combining antimicrobial lung proteins and conventional antibiotics is important due to the growing problem of multidrug-resistant bacteria. The aim of this study was to investigate whether human SP-A and a recombinant trimeric fragment (rfhSP-A) have cooperative antimicrobial activity with antibiotics against pathogenic Gram-negative bacteria. We found that SP-A bound the cationic peptide polymyxin B (PMB) with an apparent dissociation constant (K D) of 0.32 ± 0.04 µM. SP-A showed synergistic microbicidal activity with polymyxin B and E, but not with other antibiotics, against three SP-A-resistant pathogenic bacteria: Klebsiella pneumoniae, non-typable Haemophilus influenzae (NTHi), and Pseudomonas aeruginosa. SP-A was not able to bind to K. pneumoniae, NTHi, or to mutant strains thereof expressing long-chain lipopolysaccharides (or lipooligosaccharides) and/or polysaccharide capsules. In the presence of PMB, SP-A induced the formation of SP-A/PMB aggregates that enhance PMB-induced bacterial membrane permeabilization. Furthermore, SP-A bound to a molecular derivative of PMB lacking the acyl chain (PMBN) with a K D of 0.26 ± 0.02 μM, forming SP-A/PMBN aggregates. PMBN has no bactericidal activity but can bind to the outer membrane of Gram-negative bacteria. Surprisingly, SP-A and PMBN showed synergistic bactericidal activity against Gram-negative bacteria. Unlike native supratrimeric SP-A, the trimeric rfhSP-A fragment had small but significant direct bactericidal activity against K. pneumoniae, NTHi, and P. aeruginosa. rfhSP-A did not bind to PMB under physiological conditions but acted additively with PMB and other antibiotics against these pathogenic bacteria. In summary, our results significantly improve our understanding of the antimicrobial actions of SP-A and its synergistic action with PMB. A peptide based on SP-A may aid the therapeutic use of PMB, a relatively cytotoxic antibiotic that is currently being reintroduced into clinics due to the global problem of antibiotic resistance. Keywords: PMB nonapeptide; collectin SP-A; lung; microbial infection; multidrug-resistant bacteria; polymyxin B; recombinant trimeric fragment; synergy. | G19: No | H19: Yes | I19: No | J19: This work investigates the potential of a peptide based on SP-A to improve or facilitate the clinical use of the antibiotic colistin (PMB), in contexts of bacterial resistance.
A20: 33358259 | B20: Clinical profile and microbiological aetiology diagnosis in adult patients hospitalized with community-acquired pneumonia | C20: 1) Reporte de cepas resistentes | E20: Revisar | F20: Early introduction of appropriate antibiotherapy is one of the major prognostic-modifying factors in community acquired pneumonia (CAP). Despite established guidelines for empirical therapy, several factors may influence etiology and, consequently, antibiotic choices. The aims of this study were to analyze the etiology of CAP in adults admitted to a northern Portugal University Hospital and evaluate the yield of the different methods used to reach an etiological diagnosis, as well as analyze of the impact of patient demographic and clinical features on CAP etiology. We retrospectively analyzed 1901 cases of CAP with hospitalization. The diagnostic performance increased significantly when blood and sputum cultures were combined with urinary antigen tests. The most frequent etiological agent was Streptococcus pneumoniae (45.7%), except in August, when it was overtaken by gram-negative bacilli (GNB) and Legionella pneumophila infections. Viral infections were almost exclusive to winter and spring. A negative microbiological result was associated with increasing age, non-smoking and lack of both blood/sputum cultures. Younger age was a predictor for S. pneumoniae, Influenza and L. pneumophila infections. Active smoking without any previously known respiratory disease was a risk factor for legionellosis. COPD was associated with Haemophilus influenzae cases, while dementia was typical in GNB and S. aureus patients. Diabetes mellitus (DM) and heart disease were negative predictors of S. pneumoniae and H. influenzae, respectively. P. aeruginosa was an independent risk factor for mortality (OR 13.02, 95% CI 2.94-57.7). This study highlights the importance of a comprehensive microbiological diagnostic workup and provides clues to predicting the most probable CAP causative agents, based on a patient's clinical profile. These may be taken into account when establishing first line antibiotherapy. Keywords: Antimicrobial treatment; Community-acquired pneumonia; Comorbidities; Etiology; Microbiology. | G20: No | H20: No | I20: No | J20: Its main focus is on epidemiology, etiology and clinical prediction.
A21: 36071818 | B21: Antimicrobial Resistance Trends of the Most Common Causative Pathogens Associated with Community-acquired Respiratory Infections in China: 2009-2018 | C21: 1) Reporte de cepas resistentes | E21: Revisar | F21: Background: Emergence of antimicrobial resistance poses new challenges in the management of community acquired respiratory tract infections (CARTIs). Therefore, surveillance on the antimicrobial susceptibilities of common respiratory pathogens is valuable and guides empirical therapeutic choices in management of CARTIs. Objective: The objective of the current study is to summarize the antimicrobial resistance trends in common respiratory tract pathogens isolated from patients with CARTIs in China, over a 10-year period (2009-2018). Methods: Streptococcus pneumoniae, Haemophilus influenzae and Moraxella catarrhalis strains were collected from multicenter, and antimicrobial susceptibility testing was performed in the research central laboratory of each study period from 2009-2018. The pathogens that accounted for CARTIs in the adult population was considered and summarized. Results: From 2009-2018 a total of 3750 isolates were collected from 22 cities located across different regions of China. Among these the most common bacterial isolates include S. pneumoniae (53.7%) followed by H. influenza (32.4%), M. catarrhalis (13.9%). S. pneumoniae exhibited reduction in susceptibility and increase in resistance to penicillin, cephalosporins (cefaclor, cefuroxime, ceftriaxone) during the surveillance period. Invasive and noninvasive S. pneumoniae showed similar resistance. In the case of H. influenzae susceptibility to β-lactam and β-lactamase inhibitors (ampicillin, amoxicillin and AMC), SXT, clarithromycin and cephalosporins (cefuroxime, cefaclor, ceftazidime) was reduced over the past 10 years with an exception of ceftriaxone. Overall, moxifloxacin and levofloxacin have the highest susceptibility rates against S. pneumoniae (>95%) and H. influenza (>90%). M. catarrhalis exhibited susceptibility to almost all the tested antimicrobials. Conclusion: In China the 10-year trends showed a substantial increase in resistance to β-lactam drugs and reduction in sensitivity. However, certain antimicrobial agents namely fluoroquinolones including moxifloxacin and levofloxacin maintained low resistance rates with better susceptibility. Further, with few exceptions decline in susceptibility rates to macrolides and cephalosporins was observed among the tested pathogens. Keywords: Community-acquired respiratory tract infections; Haemophilus influenzae; Moraxella catarrhalis; Streptococcus pneumoniae; antimicrobial resistance; susceptibility. | G21: No | H21: No | I21: No | J21: It focuses on the decade-long trend of antibiotic resistance in common respiratory pathogens, with implications for the empirical management of community-acquired respiratory infections.
... A79: 34469555 | B79: The Global Landscape of Pediatric Bacterial Meningitis Data Reported to the World Health Organization-Coordinated Invasive Bacterial Vaccine-Preventable Disease Surveillance Network, 2014-2019 | C79: 3) Inmunización | E79: Listo | F79: Background: The World Health Organization (WHO) coordinates the Global Invasive Bacterial Vaccine-Preventable Diseases (IB-VPD) Surveillance Network to support vaccine introduction decisions and use. The network was established to strengthen surveillance and laboratory confirmation of meningitis caused by Streptococcus pneumoniae, Haemophilus influenzae, and Neisseria meningitidis. Methods: Sentinel hospitals report cases of children <5 years of age hospitalized for suspected meningitis. Laboratories report confirmatory testing results and strain characterization tested by polymerase chain reaction. In 2019, the network included 123 laboratories that follow validated, standardized testing and reporting strategies. Results: From 2014 through 2019, >137 000 suspected meningitis cases were reported by 58 participating countries, with 44.6% (n = 61 386) reported from countries in the WHO African Region. More than half (56.6%, n = 77 873) were among children <1 year of age, and 4.0% (n = 4010) died among those with reported disease outcome. Among suspected meningitis cases, 8.6% (n = 11 798) were classified as probable bacterial meningitis. One of 3 bacterial pathogens was identified in 30.3% (n = 3576) of these cases, namely S. pneumoniae (n = 2177 [60.9%]), H. influenzae (n = 633 [17.7%]), and N. meningitidis (n = 766 [21.4%]). Among confirmed bacterial meningitis cases with outcome reported, 11.0% died; case fatality ratio varied by pathogen (S. pneumoniae, 12.2%; H. influenzae, 6.1%; N. meningitidis, 11.0%). Among the 277 children who died with confirmed bacterial meningitis, 189 (68.2%) had confirmed S. pneumoniae. The proportion of pneumococcal cases with pneumococcal conjugate vaccine (PCV) serotypes decreased as the number of countries implementing PCV increased, from 77.8% (n = 273) to 47.5% (n = 248). Of 397 H. influenzae specimens serotyped, 49.1% (n = 195) were type b. Predominant N. meningitidis serogroups varied by region. Conclusions: This multitier, global surveillance network has supported countries in detecting and serotyping the 3 principal invasive bacterial pathogens that cause pediatric meningitis. Streptococcus pneumoniae was the most common bacterial pathogen detected globally despite the growing number of countries that have nationally introduced PCV. The large proportions of deaths due to S. pneumoniae reflect the high proportion of meningitis cases caused by this pathogen. This global network demonstrated a strong correlation between PCV introduction status and reduction in the proportion of pneumococcal meningitis infections caused by vaccine serotypes. Maintaining case-based, active surveillance with laboratory confirmation for prioritized vaccine-preventable diseases remains a critical component of the global agenda in public health.The World Health Organization (WHO)-coordinated Invasive Bacterial Vaccine-Preventable Disease (IB-VPD) Surveillance Network reported data from 2014 to 2019, contributing to the estimates of the disease burden and serotypes of pediatric meningitis caused by Streptococcus pneumoniae, Haemophilus influenzae and Neisseria meningitidis. | G79: No | H79: No | I79: Yes | J79: Global surveillance of childhood meningitis shows reduction of S. pneumoniae and H. influenzae type b cases after use of conjugate vaccines.
A80: 33262614 | B80: Bacterial Isolates from CSF Samples and Their Antimicrobial Resistance Patterns Among Children Under Five Suspected to Have Meningitis in Dilla University Referral Hospital | C80: 1) Reporte de cepas resistentes | F80: Introduction: Bacterial meningitis is a medical emergency that requires immediate medical attention. It causes an estimated 288,649 deaths worldwide per year, of which 94,883 death occur among children under 5 years old. Up to 24% of survivors suffer from long-term sequelae such as epilepsy, mental disability, or sensorineural deafness, especially when the disease is contracted during early childhood. Objective: This study aimed to assess bacterial isolates of cerebrospinal fluid (CSF) samples and their antimicrobial resistance patterns among children under 5 years old in Dilla University Referral Hospital. Material and methods: Hospital-based cross-sectional study design was used to collect clinical data and CSF sample from children under 5 years old who were suspected for meningitis. Sediment of CSF samples was inoculated to blood agar plate, chocolate agar plate, and MacConkey agar for bacterial isolation and identification. Chemical analysis and cytological analysis were also conducted based on standard operating procedures. Results: From a total of 287 CSF samples cultured, causative bacteria were detected in 38 (13.2%). From culture positive cases, the most frequent isolate was Streptococcus pneumoniae (13 (34.2%)) followed by Staphylococcus aureas (7 (18.4%)), Neisseria meningitidis (6 (16%)) and Escherichia coli (6 (16%)). Haemophilus influenzae type b was isolated in 4 (10.5%) children with meningitis. Another cause of meningitis was Streptococcus agalactiae which accounted for 10.5%. Cryptococcus neoformans was detected in 4 (1.9%) cases of meningitis. Of all bacterial isolates, about 42.1% (16/38) were multi-drug resistant. About 38.5% of S. pneumoniae had multi-drug resistance, while about 33.3% of N. meningitidis, 50% of H. influenzae, 57.1% of S. aureas and 40% of E. coli showed multi-drug resistance. Conclusion: A high prevalence of bacterial meningitis and high rate of drug resistance were observed. Streptococcus pneumoniae was the leading cause of bacterial meningitis among children under 5 years old. | G80: Yes | H80: No | I80: No | J80: Study in Ethiopia: H. influenzae type b and other pediatric meningitis pathogens show high rates of multidrug resistance (42%).
A81: 33221736 | B81: Epidemiology and antibiotic resistance profile of bacterial meningitis in Morocco from 2015 to 2018 | C81: 1) Reporte de cepas resistentes | F81: Over a 4-year study period from 2015 to 2018, altogether 183 isolates of bacterial meningitis were collected from 12 hospitals covering the entire Moroccan territory. Neisseria meningitidis represented 58.5%, Streptococcus pneumoniae 35.5%, and Haemophilus influenzae type b 6%. H. influenzae type b mainly affected 5-year-olds and unvaccinated adults. N. meningitidis serogroup B represented 90.7% followed by serogroup W135 with 6.5%. Decreased susceptibility to penicillin G (DSPG) for all isolates accounted for 15.7%, with 11.6% being resistant to penicillin G (PG) and 4.1% decreased susceptibility. Cumulative results of all strains showed 2.7% decreased susceptibility to amoxicillin and 3.3% resistant, 2.2% of isolates were resistant to third-generation cephalosporin and 2.2% were decreased susceptible, 5.5% were resistant to chloramphenicol and 2.7% were resistant to rifampin. The frequency of DSPG observed in our study is more common in S. pneumoniae than in N. meningitidis (P < 0.05). These isolates have been found to be highly susceptible to antibiotics used for treatment and prophylaxis chemotherapy and the observed resistance remains rare. The impact of introduction of conjugate vaccines against H. influenzae type b and S. pneumoniae (PCVs) is an advantage in reducing meningitis cases due to these two species. | G81: No | H81: No | I81: Yes | J81: Shows reduction of Hib and pneumococcal cases after conjugate vaccination, assessing impact of immunization on meningitis in Morocco
A82: 33134136 | B82: Antibacterial oral sprays from kaffir lime (Citrus hystrix DC.) fruit peel oil and leaf oil and their activities against respiratory tract pathogens | C82: 2) Nuevos tratamientos | F82: Background and aim: Kaffir lime fruit peel oil and Kaffir lime leaf oil have been reported for their activities against respiratory tract pathogens. The purpose of the study was to develop clear oral sprays to be used as a first-defense oral spray. Experimental procedure: Clear antibacterial oral sprays were prepared and analyzed for their respective active major compounds, using GC-MS. The sprays were tested against a Gr. A streptococcal clinical isolate and 3 standard respiratory tract pathogens, using Broth microdilution method. A 4-month stability test was carried out as well. Results and conclusion: Six clear oral sprays, three formulae composed of Kaffir lime fruit peel oil (6, 10, 13%v/v KLO) and the other three formulae containing Kaffir lime leaf oil (4, 8, 12%v/v KLLO), were developed. The active compounds in KLO were α-terpineol and terpinene-4-ol whereas that in KLLO was citronellal. All oral sprays exhibited antibacterial activity against one Group A streptococcal clinical isolate and three respiratory pathogenic pathogens, Staphylococcus aureus ATCC 29213, Streptococcus pneumoniae ATCC 49619, and Haemophilus influenzae ATCC 49247, among which the strongest activity was against H. influenzae ATCC 49247. The antibacterial activity of all oral sprays remained unchanged in an accelerated stability test, at 4, 30, and 45 °C under 75% relative humidity, throughout the 4-month storage. Keywords: %v/v, percent in volume by volume; Alpha-terpineol; Citronellal; Essential oil; KLLO, Kaffir lime leaf oil; KLO, Kaffir lime oil; MBC, Minimal bactericidal concentration; MIC, Minimal inhibitory concentration; Pharyngitis; Sore throat; Terpinene-4-ol; g, gram; mg, milligram; min, minute; ml, milliliter; mm, millimeter; ppm, part per million; ˚C, Degree Celsius; μl, microliter; μm, micrometer. | G82: No | H82: Yes | I82: No | J82: Development of oral aerosols based on kaffir lime oils with antibacterial activity against respiratory pathogens, including H. influenzae.
A83: 32279472 | B83: Effects of Amniotic Membrane Extract on the Hyperplastic Response of the Middle Ear Mucosa in a Bacterially-Induced Otitis Media Rat Model: A Preliminary Study | C83: 2) Nuevos tratamientos | F83: Objectives: Human amniotic membrane extract (AME) is known to contain numerous bioactive factors and anti-inflammatory substances. However, the anti-inflammatory effects of AME on the middle ear (ME) mucosa are unclear. This study assessed the effects of AME on the growth of the ME mucosa in response to bacterially-induced otitis media (OM). Methods: OM was induced by inoculating nontypeable Haemophilus influenzae (NTHi) into the ME cavity of rats. ME mucosal explants were cultured in AME concentrations of 0, 5, 10, or 50 μg/mL. The area of explant outgrowth was measured in culture and analyzed at 1, 3, 5, and 7 days after explantation. The expression of Ki-67, mucin 5AC (MUC5AC), tumor necrosis factor-α (TNF-α), and interleukin-10 (IL-10) in the explants was also evaluated using quantitative polymerase chain reaction (PCR) and immunocytochemistry (ICC). Results: The NTHi-induced ME mucosa growth increased gradually over the 7-day culture period in all explants at different AME concentrations. There was a trend for mucosal growth inhibition at higher concentrations of AME, although the growth was not significantly different among the groups until day 5. The ME mucosal explants treated with the 50 μg/mL concentration of AME showed significantly suppressed growth on postexplantation day 7 compared with other explants on the same day. PCR and ICC staining revealed that the expression of Ki-67, MUC5AC, TNF-α, and IL-10 further decreased in the explants with higher concentrations of AME than in those with lower concentrations of AME. Conclusion: Our results showed that higher concentrations of AME reduced the mucosal proliferative response in bacterial OM in rats. These findings provide evidence that AME has an influence on the inflammatory and proliferative responses to NTHi infection in ME mucosa. | G83: No | H83: Yes | I83: No | J83: Amniotic membrane extract reduces the proliferative and inflammatory response in the middle ear mucosa induced by NTHi in rats.
A84: 32456442 | B84: Herbal Drug EPs 7630 versus Amoxicillin in Patients with Uncomplicated Acute Bacterial Rhinosinusitis: A Randomized, Open-Label Study | C84: 2) Nuevos tratamientos | F84: Objective: Previous investigations suggest the use of extract from the root of Pelargonium sidoides (EPs 7630) for the therapy of uncomplicated acute upper airway inflammations, due to its strong antimicrobial and immunomodulatory effect. We aimed to compare clinical efficacy, safety and bactericidal effect of EPs 7630 and amoxicillin monotherapy in treatment of patients with mild to moderate acute bacterial rhinosinusitis (ABRS). Methods: Fifty ABRS patients were divided into two groups by randomization. Group 1 (n = 25) received EPs 7630 tablets, 3 × 20 mg/day per os for 10 days. Group 2 (n = 25) received amoxicillin tablets 3 × 500 mg/day per os, for 10 days. We assessed total symptom score (TSS), individual symptom scores for each symptom (nasal obstruction, rhinorrhea, postnasal drip, facial pain/pressure, loss of the sense of smell), endoscopic findings, including total endoscopic score (TES) and individual endoscopic signs (mucosal edema, mucopurulent secretion), before and after treatment. Samples of discharge taken from the middle meatus of all patients were cultivated for bacteria before and after therapy. Results: Higher absolute improvement after treatment was found for TSS, nasal obstruction, facial pain/pressure, impaired sense of smell, TES, mucosal edema and mucopurulent secretion in EPs 7630 group compared to amoxicillin group (P < .001 for all parameters). However, there were no differences in absolute improvement of rhinorrhea score and postnasal drip score between groups (P = .248; P = .679, respectively). Fewer types of bacteria grew on culture from middle meatal samples in EPs 7630 group compared to amoxicillin group. There were no reported adverse events from patients from either group. Conclusion: Our results demonstrated better clinical and antimicrobial efficacy of EPs 7630 than amoxicillin. EPs 7630 was shown as a potent agent and good alternative to antibiotic treatment of uncomplicated ABRS. | G84: No | H84: Yes | I84: No | J84: EPs 7630 showed better clinical and antimicrobial efficacy than amoxicillin in the treatment of acute bacterial rhinosinusitis.
A85: 33014369 | B85: Mesenchymal stem cells prevent overwhelming inflammation and reduce infection severity via recruiting CXCR3(+) regulatory T cells | C85: 2) Nuevos tratamientos | F85: Objectives: Mesenchymal stem cells (MSCs) have shown great potential in treating autoimmune diseases (ADs). Unlike the traditional immunosuppressants, which inadvertently impair patients' antimicrobial immunity, MSCs reduce the incidence and duration of respiratory infection. However, the underlying mechanisms are unknown. Methods: To investigate how MSCs regulate the lung immunity and improve the defence against respiratory infection, we infected MSC-treated wild-type and lupus-prone mice with Haemophilus influenzae intranasally and determined the clearance of bacteria. Tissue damage and inflammatory cytokines were measured by H&E staining and ELISA separately. Immune cell subsets in the tissues were analysed by flow cytometry. Results: MSC pretreatment prevented overwhelming inflammation and accelerated bacterial clearance in both wild-type and lupus-prone mice. Tregs increased dramatically in the lung after MSC treatment. Adoptive transfer of Tregs isolated from MSC-treated mice offered similar protection, while deletion of Tregs abrogated the protective effects of MSCs. The majority of the intravenously injected MSCs were engulfed by lung phagocytes, which in turn produced CXCL9 and CXCL10 and recruited tremendous CXCR3+ Tregs into the lung. Compared with their CXCR3- counterparts, CXCR3+ Tregs displayed enhanced proliferation and stronger inhibitory functions. Neutralisation of CXCL9 and CXCL10 significantly downregulated the migration of CXCR3+ Tregs and eliminated the benefits of MSC pretreatment. Conclusion: Here, we showed that by recruiting CXCR3+ Tregs, MSC treatment restricted the overactivation of inflammatory responses and prevented severe symptoms caused by infection. By discovering this novel property of MSCs, our study sheds light on optimising long-term immunosuppressive regimen for autoimmune diseases and other immune disorders. | G85: No | H85: Yes | I85: No | J85: MSCs recruit CXCR3+ Tregs via CXCL9/10 to the lung, reduce inflammation and enhance H. influenzae clearance, proposing cellular immunotherapy.
A86: 33042095 | B86: In vitro Activity of Lefamulin Against the Common Respiratory Pathogens Isolated From Mainland China During 2017-2019 | C86: 2) Nuevos tratamientos | F86: Purpose: Lefamulin is a novel antibiotic approved by the U.S. Food and Drug Administration in 2019 for the treatment of community-acquired bacterial pneumonia (CABP). In this study we evaluated the in vitro antimicrobial activity of lefamulin in order to better understand its antibiogram. Methods: The test strains were isolated from patients across China during the period from 2017 to 2019, including 634 strains of respiratory pathogens. The minimum inhibitory concentrations (MICs) of lefamulin and comparators were determined by broth microdilution method. Results: Lefamulin showed potent activity against Streptococcus pneumoniae and Staphylococcus evidenced by 100% inhibition at 0.25 mg/L, and favorable MIC50/90 (0.125/0.125 mg/L) against S. pneumoniae (penicillin MIC ≥ 2 mg/L), MIC50/90 (≤0.015/0.125 mg/L) against methicillin-resistant S. aureus, and MIC50/90 (≤0.015/0.06 mg/L) against methicillin-resistant S. epidermidis. Lefamulin also had good activity against Streptococcus pyogenes and Streptococcus agalactia (MIC50/90: ≤0.015/≤0.015 mg/L), β-lactamase-producing Haemophilus influenzae (MIC50/90: 0.5/1 mg/L), β-lactamase-negative H. influenzae (MIC50/90: 1/1 mg/L), Moraxella catarrhalis (MIC50/90: 0.25/0.25 mg/L), and Mycoplasma pneumoniae (MIC50/90: 0.03/0.03 mg/L) regardless of resistance to azithromycin. Lefamulin was generally more active than the comparators against the test strains. Conclusion: In summary, lefamulin has good and broad-spectrum coverage of respiratory pathogens (methicillin-sensitive and -resistant Staphylococcus, S. pneumoniae, β-hemolytic Streptococcus, H. influenzae, M. catarrhalis and M. pneumoniae). In vitro activity supports the use of lefamulin in the treatment of CABP in China. | G86: No | H86: Yes | I86: No | J86: Lefamulin, a novel antibiotic, shows broad in vitro activity against respiratory pathogens (including H. influenzae), for CABP.
A87: 32653727 | B87: Whole-genome sequence of Haemophilus influenzae ST422 outbreak clone strain 2018-Y40 with low quinolone susceptibility isolated from a paediatric patient | C87: 1) Reporte de cepas resistentes | F87: Objectives: In recent years, Haemophilus influenzae strains with reduced susceptibility to quinolones have emerged and spread in Japan. In addition, an outbreak of isolates with low quinolone susceptibility among paediatric patients has also been reported. The aim of this study was to determine the molecular characteristics of an H. influenzae ST422 outbreak clone with low quinolone susceptibility isolated from a paediatric patient using whole-genome sequencing. Methods: The PacBio RS II platform was used for sequencing, and de novo assembly was performed using RS HGAP assembly version 3.0. The assembled sequences were annotated using DFAST version 1.1.15. Prophages were estimated using the PHASTER program. Results: Whole-genome sequencing of H. influenzae ST422 isolate 2018-Y40 revealed that the genome size was 1 957 393bp, comprising 1 926 protein-coding sequences, 19 rRNAs, and 57 tRNAs, with a guanine-cytosine (GC) content of 38.2%. This isolate had no relevant exogenous antimicrobial-resistant genes. However, amino acid substitutions were found in both GyrA and ParC, as well as at the 385th and 526th amino acid residues in penicillin-binding protein 3. In addition, four intact prophage regions and one incomplete prophage region were found. Conclusions: The whole-genome sequence of H. influenzae 2018-Y40 indicated that this clone emerged as a result of extensive genomic rearrangement by integration of multiple phages. As genomic rearrangement occasionally leads to a new phenotype, this clone could have acquired antimicrobial resistance and diversification via rearrangement events. These findings can form a basis to help clarify the mechanisms of low quinolone susceptibility and the spread of this outbreak clone. | G87: Yes | H87: No | I87: No | J87: WGS of paediatric H. influenzae clone ST422 reveals mutations in GyrA/ParC and PBP3, and phage-mediated rearrangement events.
A88: 32651162 | B88: Targeting a bacterial DNABII protein with a chimeric peptide immunogen or humanised monoclonal antibody to prevent or treat recalcitrant biofilm-mediated infections | C88: 2) Nuevos tratamientos | F88: Background: Chronic and recurrent bacterial diseases are recalcitrant to treatment due to the ability of the causative agents to establish biofilms, thus development of means to prevent or resolve these structures are greatly needed. Our approach targets the DNABII family of bacterial DNA-binding proteins, which serve as critical structural components within the extracellular DNA scaffold of biofilms formed by all bacterial species tested to date. DNABII-directed antibodies rapidly disrupt biofilms and release the resident bacteria which promote their subsequent clearance by either host immune effectors or antibiotics that are now effective at a notably reduced concentration. Methods: First, as a therapeutic approach, we used intact IgG or Fab fragments against a chimeric peptide immunogen designed to target protective epitopes within the DNA-binding tip domains of integration host factor to disrupt established biofilms in vitro and to mediate resolution of existing disease in vivo. Second, we performed preventative active immunisation with the chimeric peptide to induce the formation of antibody that blocks biofilm formation and disease development in a model of viral-bacterial superinfection. Further, toward the path for clinical use, we humanised a monoclonal antibody against the chimeric peptide immunogen, then characterised and validated that it maintained therapeutic efficacy. Findings: We demonstrated efficacy of each approach in two well-established pre-clinical models of otitis media induced by the prevalent respiratory tract pathogen nontypeable Haemophilus influenzae, a common biofilm disease. Interpretation: Collectively, our data revealed two approaches with substantive efficacy and potential for broad application to combat diseases with a biofilm component. Funding: Supported by R01 DC011818 to LOB and SDG. | G88: No | H88: Yes | I88: Yes | J88: DNABII antibodies dissolve NTHi biofilms in vitro and in vivo, proposing an innovative therapy for chronic otitis media.
A89: 32585694 | B89: Evaluation of the Haemophilus influenzae EUCAST and CLSI disc diffusion methods to recognize aminopenicillin and amoxicillin/clavulanate resistance | C89: 1) Reporte de cepas resistentes | F89: Objectives: Implementation of EUCAST susceptibility testing in an Australian hospital laboratory demonstrated higher rates of aminopenicillin and amoxicillin/clavulanate resistance in Haemophilus influenzae than previously recognized. This study aimed to better define the variability in the detection of β-lactam resistance based on EUCAST and CLSI disc diffusion (DD) methodology, by comparison with the recommended reference method, broth microdilution (BMD), and by concordance with genomic analysis. Methods: A total of 100 random H. influenzae isolates were assessed for ampicillin and amoxicillin/clavulanate susceptibility by EUCAST and CLSI DD and BMD. WGS was used to analyse the ftsI gene of a subset of isolates with β-lactam resistance, other than that due to isolated β-lactamase production. Results: Of the 100 isolates, 32 were categorized as either β-lactamase negative, ampicillin resistant (BLNAR) (n = 18) or β-lactamase positive, amoxicillin/clavulanate resistant (BLPACR) (n = 14) by EUCAST DD. All 18 EUCAST BLNAR isolates were genotypically confirmed by WGS. Five of 18 BLNAR isolates were concordant by CLSI DD, 12 by EUCAST BMD and 4 by CLSI BMD. Nine of 14 EUCAST BLPACR isolates were confirmed by WGS; the remaining 5 were 1 mm below the EUCAST DD breakpoint. Only one isolate was detected as BLPACR by CLSI DD. Group III mutations associated with high-level ampicillin resistance were identified in 10/32 isolates. Conclusions: The EUCAST DD susceptibility method is more reliable than either CLSI or BMD for the detection of genotypically defined BLNAR resistance. However, accurate categorization of amoxicillin/clavulanate resistance remains problematic. Continuous and reproducible surveillance of resistance is needed; for this to be possible, robust susceptibility methods are required. | G89: Yes | H89: No | I89: No | J89: EUCAST DD reliably detects BLNAR strains of H. influenzae better than CLSI/BMD, providing evidence of emerging resistance surveillance.
