Workbook
Name BD_aux: #REF!
Name categoria: categorias!$A:$A
Name Estado: categorias!$C$2:$C$65536
Name EXCL: Excluidas!$A:$K
Name EXCLUIDAS: Excluidas!$A$1:$K$463
Name KEYWORDS: 'Palabras claves'!$A:$K
Name NgonorreaePost: '2017-2022'!#REF!
Name NgonorreaePre: '2012-2017'!$A$1:$K$534
Name PalabrasClave: 'Palabras claves'!$K$1:$K$1371
Name POST: '2017-2022'!$A:$K
Name POSTALERTA: '2017-2022'!$A$1:$B$857
Name PRE: '2012-2017'!$A:$K
Name PREALERTA: '2012-2017'!$A$1:$O$540
Name SegmentaciónDeDatos_Alerta1: #REF!
Name SegmentaciónDeDatos_KeyWords: #REF!
Name SegmentaciónDeDatos_PubYear: #REF!
Name subcategoria: categorias!$B:$B
Name TablaNgonoreae: '2012-2022'!$A$1:$K$3740

Sheet DashBoard
C2: Neisseria gonorrhoeae 2012-2022
C3: Total de publicaciones de | F3: =C2 -> Neisseria gonorrhoeae 2012-2022 | G3: : | H3: =COUNTA('2012-2022'!A$1:A$869572)-1 -> 3740
D5: Publicaciones por Año | I5: Categorías y Subcategorías
D17: Publicaciones por mes

Sheet categorias
A1: Categorias | B1: Subcategorias | C1: Estados
A2: 1) Reporte de cepas resistentes | B2: 2a) Productos naturales | C2: Revisar
A3: 2) Nuevos tratamientos | B3: 2b) Péptidos | C3: Listo
A4: 3) Inmunizacióm | B4: 2c) Droga de diseño | C4: Excluir
A5: 4) otros | B5: 2d) Anticuerpos | C5: Otros-A
B6: 2e) Bacteriófagos | C6: Otros-B
B7: 2f) Estrategias antivirulencia | C7: Otros-C
B8: 2g) nueva combinación de ATB | C8: Otros-D

Sheet TablasDinamicas
B1: Etiquetas de fila | C1: Cuenta de Title | E1: Cuenta de Title | I1: Categoria | J1: subcategoria | K1: Cuenta de Title
B2: PreAlerta | C2: 1363 | E2: PubYear | F2: PubMonth | G2: Total | I2: 1) Interacción huésped-patógeno | J2: (en blanco) | K2: 1 | L2: 1) Interacción huésped-patógeno | M2: (en blanco) | N2: =GETPIVOTDATA("Title",$I$1,"Categoria",L2,"subcategoria",M2) -> #REF! | P2: Etiquetas de fila | Q2: Cuenta de Title | S2: Etiquetas de fila | T2: Cuenta de Title | V2: Etiquetas de fila | W2: Cuenta de Title
B3: PostAlerta | C3: 1915 | E3: 2017 | F3: Jan | G3: 18 | I3: Total 1) Interacción huésped-patógeno | K3: 1 | L3: 2) Reporte de cepas resistentes | M3: (en blanco) | N3: =GETPIVOTDATA("Title",$I$1,"Categoria",L3,"subcategoria",M3) -> #REF! | P3: (en blanco) | Q3: 3740 | S3: 2012 | T3: 139 | V3: S/PalabrasClaves | W3: 2369
B4: Excluido | C4: 461 | F4: Feb | G4: 27 | I4: (en blanco) | J4: (en blanco) | K4: 2368 | L4: 3) Casos clínicos | M4: (en blanco) | N4: =GETPIVOTDATA("Title",$I$1,"Categoria",L4,"subcategoria",M4) -> #REF! | P4: Total general | Q4: 3740 | S4: 2013 | T4: 216 | V4: Excluido | W4: 254
B5: Total general | C5: 3739 | F5: Mar | G5: 27 | I5: Total (en blanco) | K5: 2368 | L5: 4) Nuevos tratamientos | M5: 4a) Productos naturales | N5: =GETPIVOTDATA("Title",$I$1,"Categoria",L5,"subcategoria",M5) -> #REF! | S5: 2014 | T5: 213 | V5: PostAlerta | W5: 1186
F6: Apr | G6: 21 | I6: Total general | K6: 2369 | L6: 4) Nuevos tratamientos | M6: 4b) Péptidos | N6: =GETPIVOTDATA("Title",$I$1,"Categoria",L6,"subcategoria",M6) -> #REF! | S6: 2015 | T6: 222 | V6: PreAlerta | W6: 929
F7: May | G7: 24 | L7: 4) Nuevos tratamientos | M7: 4c) Droga de diseño | N7: =GETPIVOTDATA("Title",$I$1,"Categoria",L7,"subcategoria",M7) -> #REF! | S7: 2016 | T7: 204 | V7: Total general | W7: 2369
F8: Jun | G8: 35 | L8: 4) Nuevos tratamientos | M8: 4d) Anticuerpos | N8: =GETPIVOTDATA("Title",$I$1,"Categoria",L8,"subcategoria",M8) -> #REF! | S8: 2017 | T8: 198
F9: Jul | G9: 38 | L9: 4) Nuevos tratamientos | M9: 4e) Bacteriófagos | N9: =GETPIVOTDATA("Title",$I$1,"Categoria",L9,"subcategoria",M9) -> #REF! | S9: 2018 | T9: 227
F10: Aug | G10: 28 | L10: 4) Nuevos tratamientos | M10: 4f) Estrategias antivirulencia | N10: =GETPIVOTDATA("Title",$I$1,"Categoria",L10,"subcategoria",M10) -> #REF! | S10: 2019 | T10: 264
F11: Sep | G11: 34 | S11: 2020 | T11: 254
F12: Oct | G12: 24 | S12: 2021 | T12: 306
F13: Nov | G13: 23 | S13: 2022 | T13: 121
F14: Dec | G14: 27 | S14: 2023 | T14: 1
F15: (en blanco) | G15: 6 | S15: Live | T15: 4
E16: Total 2017 | G16: 332 | S16: Total general | T16: 2369
E17: (en blanco) | F17: Apr | G17: 1
F18: (en blanco)
E19: Total (en blanco) | G19: 1
E20: Live | F20: LiverTox | G20: 5
E21: Total Live | G21: 5
E22: Total general | G22: 338

Sheet 2012-2022
A1: PMID | B1: Title | C1: Authors | D1: Citation | E1: First Author | F1: Journal/Book | G1: Publication Year | H1: Create Date | I1: PMCID | J1: NIHMS ID | K1: DOI | L1: Alerta | M1: KeyWords | N1: Categoria | O1: subcategoria | P1: fecha de publicación | Q1: Estado | R1: PubYear | S1: PubMonth | T1: Abstract | U1: 1) Antimicrobial Resistance stain | V1: 2) New treatment | W1: 3) Immunization | X1: Human_summary
A2: 29430011 | B2: Neisseria gonorrhoeae host adaptation and pathogenesis | C2: Quillin SJ; Seifert HS. | D2: Nat Rev Microbiol. 2018 Apr;16(4):226-240. doi: 10.1038/nrmicro.2017.169. Epub 2018 Feb 12. | E2: Quillin SJ | F2: Nat Rev Microbiol | G2: 2018 | H2: 43144 | I2: PMC6329377 | J2: NIHMS1003492 | K2: 10.1038/nrmicro.2017.169 | L2: =IF(ISNUMBER(VLOOKUP(A2,EXCL,1,FALSE)),"Excluido",IF(ISNUMBER(VLOOKUP(A2,POST,1,FALSE)),"PostAlerta",IF(ISNUMBER(VLOOKUP(A2,PRE,1,FALSE)),"PreAlerta",""))) -> Excluido | M2: =IF(ISNUMBER(VLOOKUP(A2,KEYWORDS,1,FALSE)),"C/PalabrasClaves","S/PalabrasClaves") -> C/PalabrasClaves | N2: =IF(ISNUMBER(SEARCH("TREATMENT", B2)), "4) Nuevos tratamientos", "") | P2: 2018 Apr | R2: =LEFT('2012-2022'!$P2,4) -> 2018 | S2: Apr | T2: =IFERROR(VLOOKUP(A2,BD_aux,2,FALSE),"")
A3: 28991324 | B3: [Neisseria gonorrhoeae] | C3: García-Mendiola R, Aguilera-Arreola MG, Contreras-Rodríguez A. | D3: Rev Chilena Infectol. 2017 Jun;34(3):263-264. doi: 10.4067/S0716-10182017000300010. | E3: García-Mendiola R | F3: Rev Chilena Infectol | G3: 2017 | H3: 43018 | K3: 10.4067/S0716-10182017000300010 | L3: =IF(ISNUMBER(VLOOKUP(A3,EXCL,1,FALSE)),"Excluido",IF(ISNUMBER(VLOOKUP(A3,POST,1,FALSE)),"PostAlerta",IF(ISNUMBER(VLOOKUP(A3,PRE,1,FALSE)),"PreAlerta",""))) -> PostAlerta | M3: =IF(ISNUMBER(VLOOKUP(A3,KEYWORDS,1,FALSE)),"C/PalabrasClaves","S/PalabrasClaves") -> S/PalabrasClaves | N3: =IF(ISNUMBER(SEARCH("TREATMENT", B3)), "4) Nuevos tratamientos", "") | P3: 2017 Jun | R3: =LEFT('2012-2022'!$P3,4) -> 2017 | S3: Jun | T3: =IFERROR(VLOOKUP(A3,BD_aux,2,FALSE),"")
A4: 31119616 | B4: Antimicrobial Resistance in Neisseria gonorrhoeae and Treatment of Gonorrhea | C4: Unemo M, Golparian D, Eyre DW. | D4: Methods Mol Biol. 2019;1997:37-58. doi: 10.1007/978-1-4939-9496-0_3. | E4: Unemo M | F4: Methods Mol Biol | G4: 2019 | H4: 43609 | K4: 10.1007/978-1-4939-9496-0_3 | L4: =IF(ISNUMBER(VLOOKUP(A4,EXCL,1,FALSE)),"Excluido",IF(ISNUMBER(VLOOKUP(A4,POST,1,FALSE)),"PostAlerta",IF(ISNUMBER(VLOOKUP(A4,PRE,1,FALSE)),"PreAlerta",""))) -> PostAlerta | M4: =IF(ISNUMBER(A4),(IF(ISNUMBER(VLOOKUP(A4,KEYWORDS,1,FALSE)),"C/PalabrasClaves","S/PalabrasClaves")),"") -> C/PalabrasClaves | N4: 2) Nuevos tratamientos | O4: 2g) nueva combinación de ATB | P4: 2019 | R4: =LEFT('2012-2022'!$P4,4) -> 2019 | T4: This review highlights the global threat of antimicrobial-resistant Neisseria gonorrhoeae. | U4: Yes | V4: No | W4: No | X4: This review highlights the global threat of antimicrobial-resistant Neisseria gonorrhoeae. | Y4: =IFERROR(VLOOKUP(A2,BD_aux,3,FALSE),"")
A5: 31802195 | B5: Multiresistant Neisseria gonorrhoeae: a new threat in second decade of the XXI century | C5: Młynarczyk-Bonikowska B, Majewska A, Malejczyk M, Młynarczyk G, Majewski S. | D5: Med Microbiol Immunol. 2020 Apr;209(2):95-108. doi: 10.1007/s00430-019-00651-4. Epub 2019 Dec 4. | E5: Młynarczyk-Bonikowska B | F5: Med Microbiol Immunol | G5: 2020 | H5: 43805 | I5: PMC7125254 | K5: 10.1007/s00430-019-00651-4 | L5: =IF(ISNUMBER(VLOOKUP(A5,EXCL,1,FALSE)),"Excluido",IF(ISNUMBER(VLOOKUP(A5,POST,1,FALSE)),"PostAlerta",IF(ISNUMBER(VLOOKUP(A5,PRE,1,FALSE)),"PreAlerta",""))) -> Excluido | M5: =IF(ISNUMBER(A5),(IF(ISNUMBER(VLOOKUP(A5,KEYWORDS,1,FALSE)),"C/PalabrasClaves","S/PalabrasClaves")),"") -> C/PalabrasClaves | N5: =IF(ISNUMBER(SEARCH("TREATMENT", B5)), "4) Nuevos tratamientos", "") | O5: 4c) Droga de diseño | P5: 2020 Apr | R5: =LEFT('2012-2022'!$P5,4) -> 2020 | S5: Apr | T5: =IFERROR(VLOOKUP(A5,BD_aux,2,FALSE),"")
A6: 28754299 | B6: Antimicrobial resistance in Neisseria gonorrhoeae: history, molecular mechanisms and epidemiological aspects of an emerging global threat | C6: Costa-Lourenço APRD, Barros Dos Santos KT, Moreira BM, Fracalanzza SEL, Bonelli RR. | D6: Braz J Microbiol. 2017 Oct-Dec;48(4):617-628. doi: 10.1016/j.bjm.2017.06.001. Epub 2017 Jul 12. | E6: Costa-Lourenço APRD | F6: Braz J Microbiol | G6: 2017 | H6: 42946 | I6: PMC5628311 | K6: 10.1016/j.bjm.2017.06.001 | L6: =IF(ISNUMBER(VLOOKUP(A6,EXCL,1,FALSE)),"Excluido",IF(ISNUMBER(VLOOKUP(A6,POST,1,FALSE)),"PostAlerta",IF(ISNUMBER(VLOOKUP(A6,PRE,1,FALSE)),"PreAlerta",""))) -> Excluido | M6: =IF(ISNUMBER(A6),(IF(ISNUMBER(VLOOKUP(A6,KEYWORDS,1,FALSE)),"C/PalabrasClaves","S/PalabrasClaves")),"") -> C/PalabrasClaves | N6: =IF(ISNUMBER(SEARCH("TREATMENT", B6)), "4) Nuevos tratamientos", "") | O6: 4b) Péptidos | P6: 2017 Oct-Dec | R6: =LEFT('2012-2022'!$P6,4) -> 2017 | S6: Oct | T6: =IFERROR(VLOOKUP(A6,BD_aux,2,FALSE),"")
A7: 30900979 | B7: Identification of Internationally Disseminated Ceftriaxone-Resistant Neisseria gonorrhoeae Strain FC428, China | C7: Chen SC, Han Y, Yuan LF, Zhu XY, Yin YP. | D7: Emerg Infect Dis. 2019 Jul;25(7):1427-1429. doi: 10.3201/eid2507.190172. Epub 2019 Jul 17. | E7: Chen SC | F7: Emerg Infect Dis | G7: 2019 | H7: 43547 | I7: PMC6590750 | K7: 10.3201/eid2507.190172 | L7: =IF(ISNUMBER(VLOOKUP(A7,EXCL,1,FALSE)),"Excluido",IF(ISNUMBER(VLOOKUP(A7,POST,1,FALSE)),"PostAlerta",IF(ISNUMBER(VLOOKUP(A7,PRE,1,FALSE)),"PreAlerta",""))) -> PostAlerta | M7: =IF(ISNUMBER(A7),(IF(ISNUMBER(VLOOKUP(A7,KEYWORDS,1,FALSE)),"C/PalabrasClaves","S/PalabrasClaves")),"") -> C/PalabrasClaves | N7: 1) Reporte de cepas resistentes | P7: 2019 Jul | R7: =LEFT('2012-2022'!$P7,4) -> 2019 | S7: Jul | T7: In 2016, we identified a ceftriaxone-resistant Neisseria gonorrhoeae isolate in China. The strain genotype was identical to the resistant clone FC428 that originated in Japan. Enhanced international collaborative surveillance programs are crucial to track the transmission of the ceftriaxone-resistant clones. | U7: Yes | V7: No | W7: No | X7: Detect a ceftriaxone-resistant Neisseria gonorrhoeae strain in China. | Y7: =IFERROR(VLOOKUP(A5,BD_aux,3,FALSE),"")
A8: 31661379 | B8: Identification of multidrug-resistant Neisseria gonorrhoeae isolates with combined resistance to both ceftriaxone and azithromycin, China, 2017-2018 | C8: Yuan Q, Li Y, Xiu L, Zhang C, Fu Y, Jiang C, Tang L, Peng J. | D8: Emerg Microbes Infect. 2019;8(1):1546-1549. doi: 10.1080/22221751.2019.1681242. | E8: Yuan Q | F8: Emerg Microbes Infect | G8: 2019 | H8: 43768 | I8: PMC6830194 | K8: 10.1080/22221751.2019.1681242 | L8: =IF(ISNUMBER(VLOOKUP(A8,EXCL,1,FALSE)),"Excluido",IF(ISNUMBER(VLOOKUP(A8,POST,1,FALSE)),"PostAlerta",IF(ISNUMBER(VLOOKUP(A8,PRE,1,FALSE)),"PreAlerta",""))) -> PostAlerta | M8: =IF(ISNUMBER(A8),(IF(ISNUMBER(VLOOKUP(A8,KEYWORDS,1,FALSE)),"C/PalabrasClaves","S/PalabrasClaves")),"") -> C/PalabrasClaves | N8: 1) Reporte de cepas resistentes | P8: 2019 | R8: =LEFT('2012-2022'!$P8,4) -> 2019 | T8: The growing multidrug-resistant Neisseria gonorrhoeae is a serious global threat to gonococcal therapy. During 2017-2018, we identified a rare multidrug-resistant (ceftriaxone and azithromycin) strain (GC250) and four strains (GC185, GC195, GC196 and GC249) with both resistance to ceftriaxone and decreased susceptibility to azithromycin. All strains belonged to NG-STAR ST1143, including the mosaic penA-60.001, which is closely related to ceftriaxone resistance. The characterization of antimicrobial resistance (AMR) determinants and phylogenetic analysis showed these five strains were closely related to internationally spreading ceftriaxone-resistant N. gonorrhoeae FC428, but with higher azithromycin MIC. Findings here demonstrated that this clone not only initiated clonal expansion in China, but acquired azithromycin resistance. | U8: Yes | V8: No | W8: No | X8: This study identified five multidrug-resistant Neisseria gonorrhoeae strains in China | Y8: =IFERROR(VLOOKUP(A6,BD_aux,3,FALSE),"")
A9: 28210887 | B9: Drug-resistant Neisseria gonorrhoeae: latest developments | C9: Suay-García B, Pérez-Gracia MT. | D9: Eur J Clin Microbiol Infect Dis. 2017 Jul;36(7):1065-1071. doi: 10.1007/s10096-017-2931-x. Epub 2017 Feb 16. | E9: Suay-García B | F9: Eur J Clin Microbiol Infect Dis | G9: 2017 | H9: 42784 | K9: 10.1007/s10096-017-2931-x | L9: =IF(ISNUMBER(VLOOKUP(A9,EXCL,1,FALSE)),"Excluido",IF(ISNUMBER(VLOOKUP(A9,POST,1,FALSE)),"PostAlerta",IF(ISNUMBER(VLOOKUP(A9,PRE,1,FALSE)),"PreAlerta",""))) -> Excluido | M9: =IF(ISNUMBER(A9),(IF(ISNUMBER(VLOOKUP(A9,KEYWORDS,1,FALSE)),"C/PalabrasClaves","S/PalabrasClaves")),"") -> C/PalabrasClaves | N9: =IF(ISNUMBER(SEARCH("TREATMENT", B9)), "4) Nuevos tratamientos", "") | O9: 4e) Bacteriófagos | P9: 2017 Jul | R9: =LEFT('2012-2022'!$P9,4) -> 2017 | S9: Jul | T9: =IFERROR(VLOOKUP(A9,BD_aux,2,FALSE),"")
A10: 32119845 | B10: The frontiers of addressing antibiotic resistance in Neisseria gonorrhoeae | C10: Rubin DHF, Ross JDC, Grad YH. | D10: Transl Res. 2020 Jun;220:122-137. doi: 10.1016/j.trsl.2020.02.002. Epub 2020 Feb 29. | E10: Rubin DHF | F10: Transl Res | G10: 2020 | H10: 43893 | I10: PMC7293957 | J10: NIHMS1580697 | K10: 10.1016/j.trsl.2020.02.002 | L10: =IF(ISNUMBER(VLOOKUP(A10,EXCL,1,FALSE)),"Excluido",IF(ISNUMBER(VLOOKUP(A10,POST,1,FALSE)),"PostAlerta",IF(ISNUMBER(VLOOKUP(A10,PRE,1,FALSE)),"PreAlerta",""))) -> Excluido | M10: =IF(ISNUMBER(A10),(IF(ISNUMBER(VLOOKUP(A10,KEYWORDS,1,FALSE)),"C/PalabrasClaves","S/PalabrasClaves")),"") -> C/PalabrasClaves | N10: =IF(ISNUMBER(SEARCH("TREATMENT", B10)), "4) Nuevos tratamientos", "") | P10: 2020 Jun | R10: =LEFT('2012-2022'!$P10,4) -> 2020 | S10: Jun | T10: =IFERROR(VLOOKUP(A10,BD_aux,2,FALSE),"")
A11: 33720324 | B11: The Next-Generation of Neisseria gonorrhoeae Antimicrobial Resistance Testing | C11: Potter RF, Ransom EM, Burnham CD. | D11: Clin Chem. 2021 Mar 31;67(4):573-575. doi: 10.1093/clinchem/hvab026. | E11: Potter RF | F11: Clin Chem | G11: 2021 | H11: 44270 | K11: 10.1093/clinchem/hvab026 | L11: =IF(ISNUMBER(VLOOKUP(A11,EXCL,1,FALSE)),"Excluido",IF(ISNUMBER(VLOOKUP(A11,POST,1,FALSE)),"PostAlerta",IF(ISNUMBER(VLOOKUP(A11,PRE,1,FALSE)),"PreAlerta",""))) -> PostAlerta | M11: =IF(ISNUMBER(A11),(IF(ISNUMBER(VLOOKUP(A11,KEYWORDS,1,FALSE)),"C/PalabrasClaves","S/PalabrasClaves")),"") -> C/PalabrasClaves | N11: EDITORIAL | P11: 2021 Mar 31 | R11: =LEFT('2012-2022'!$P11,4) -> 2021 | S11: Mar
A12: 28645177 | B12: Mobile genetic elements in Neisseria gonorrhoeae: movement for change | C12: Cehovin A, Lewis SB. | D12: Pathog Dis. 2017 Aug 31;75(6). doi: 10.1093/femspd/ftx071. | E12: Cehovin A | F12: Pathog Dis | G12: 2017 | H12: 42911 | K12: 10.1093/femspd/ftx071 | L12: =IF(ISNUMBER(VLOOKUP(A12,EXCL,1,FALSE)),"Excluido",IF(ISNUMBER(VLOOKUP(A12,POST,1,FALSE)),"PostAlerta",IF(ISNUMBER(VLOOKUP(A12,PRE,1,FALSE)),"PreAlerta",""))) -> Excluido | M12: =IF(ISNUMBER(A12),(IF(ISNUMBER(VLOOKUP(A12,KEYWORDS,1,FALSE)),"C/PalabrasClaves","S/PalabrasClaves")),"") -> C/PalabrasClaves | N12: =IF(ISNUMBER(SEARCH("TREATMENT", B12)), "4) Nuevos tratamientos", "") | O12: 4c) Droga de diseño | P12: 2017 Aug 31 | R12: =LEFT('2012-2022'!$P12,4) -> 2017 | S12: Aug | T12: =IFERROR(VLOOKUP(A12,BD_aux,2,FALSE),"")
A13: 32779717 | B13: Establishing Novel Molecular Algorithms to Predict Decreased Susceptibility to Ceftriaxone in Neisseria gonorrhoeae Strains | C13: Lin EY, Adamson PC, Deng X, Klausner JD. | D13: J Infect Dis. 2021 Apr 8;223(7):1232-1240. doi: 10.1093/infdis/jiaa495. | E13: Lin EY | F13: J Infect Dis | G13: 2021 | H13: 44055 | I13: PMC8030720 | K13: 10.1093/infdis/jiaa495 | L13: =IF(ISNUMBER(VLOOKUP(A13,EXCL,1,FALSE)),"Excluido",IF(ISNUMBER(VLOOKUP(A13,POST,1,FALSE)),"PostAlerta",IF(ISNUMBER(VLOOKUP(A13,PRE,1,FALSE)),"PreAlerta",""))) -> Excluido | M13: =IF(ISNUMBER(A13),(IF(ISNUMBER(VLOOKUP(A13,KEYWORDS,1,FALSE)),"C/PalabrasClaves","S/PalabrasClaves")),"") -> C/PalabrasClaves | N13: =IF(ISNUMBER(SEARCH("TREATMENT", B13)), "4) Nuevos tratamientos", "") | P13: 2021 Apr 8 | R13: =LEFT('2012-2022'!$P13,4) -> 2021 | S13: Apr | T13: =IFERROR(VLOOKUP(A13,BD_aux,2,FALSE),"")
A14: 25410409 | B14: History and epidemiology of antibiotic susceptibilities of Neisseria gonorrhoeae | C14: Shigemura K, Fujisawa M. | D14: Curr Drug Targets. 2015;16(3):272-80. doi: 10.2174/1389450115666141120110724. | E14: Shigemura K | F14: Curr Drug Targets | G14: 2015 | H14: 41964 | K14: 10.2174/1389450115666141120110724 | L14: =IF(ISNUMBER(VLOOKUP(A14,EXCL,1,FALSE)),"Excluido",IF(ISNUMBER(VLOOKUP(A14,POST,1,FALSE)),"PostAlerta",IF(ISNUMBER(VLOOKUP(A14,PRE,1,FALSE)),"PreAlerta",""))) -> Excluido | M14: =IF(ISNUMBER(A14),(IF(ISNUMBER(VLOOKUP(A14,KEYWORDS,1,FALSE)),"C/PalabrasClaves","S/PalabrasClaves")),"") -> C/PalabrasClaves | N14: =IF(ISNUMBER(SEARCH("TREATMENT", B14)), "4) Nuevos tratamientos", "") | O14: 4c) Droga de diseño | P14: 2015 | R14: =LEFT('2012-2022'!$P14,4) -> 2015 | T14: =IFERROR(VLOOKUP(A14,BD_aux,2,FALSE),"")
A15: 34402689 | B15: Large Increase in Azithromycin-Resistant Neisseria gonorrhoeae in Northern Spain | C15: Carballo R, Povoa MC, Abad R, Navarro C, Martin E, Alvarez M, Salgado A, Potel C. | D15: Microb Drug Resist. 2022 Jan;28(1):81-86. doi: 10.1089/mdr.2020.0594. Epub 2021 Aug 16. | E15: Carballo R | F15: Microb Drug Resist | G15: 2022 | H15: 44425 | K15: 10.1089/mdr.2020.0594 | L15: =IF(ISNUMBER(VLOOKUP(A15,EXCL,1,FALSE)),"Excluido",IF(ISNUMBER(VLOOKUP(A15,POST,1,FALSE)),"PostAlerta",IF(ISNUMBER(VLOOKUP(A15,PRE,1,FALSE)),"PreAlerta",""))) -> PostAlerta | M15: =IF(ISNUMBER(A15),(IF(ISNUMBER(VLOOKUP(A15,KEYWORDS,1,FALSE)),"C/PalabrasClaves","S/PalabrasClaves")),"") -> C/PalabrasClaves | N15: 1) Reporte de cepas resistentes | P15: 2022 Jan | R15: =LEFT('2012-2022'!$P15,4) -> 2022 | S15: Jan | T15: The aim of this study was to characterize the evolution of gonorrhea in the general population by correlating epidemiological, genotypic, and antimicrobial resistance data of Neisseria gonorrhoeae isolates collected in northern Spain from 2014 to 2018. One hundred ninety-four strains underwent antimicrobial susceptibility testing and were genetically analyzed by N. gonorrhoeae multiantigen sequence typing. Increasing cases of gonococcal infections have been observed after 2015. Most occurred in male with urethritis. Sequence type (ST)-9972 and ST-1576, the predominant genotypes identified, have not been previously described as epidemic clones. Of great concern was the significant increase in azithromycin-resistant N. gonorrhoeae. More than 30% of these isolates were obtained from men who have sex with men (MSM). ST-12302 was the most prevalent clone among the azithromycin-resistant strains, and was also resistant to penicillin, ciprofloxacin, and tetracycline. This multidrug-resistant clone was exclusively isolated from MSM during 2018. The incidence rates of gonorrhea and azithromycin-resistant N. gonorrhoeae have significantly increased due to the emergence of new clones. ST-12302 has recently been recognized as an epidemic clone; therefore, its surveillance could be the key in controlling further dissemination of azithromycin resistance. These data highlight the need to perform local studies to update treatment guidelines and reinforce preventive measures against gonorrhea. | U15: Yes | V15: No | W15: No | X15: This study characterized the epidemiological and antimicrobial resistance trends of Neisseria gonorrhoeae in northern Spain The spread of ST-12302 and rising resistance rates stress the importance of local surveillance, updated treatment guidelines, and targeted prevention strategies. | Y15: =IFERROR(VLOOKUP(A13,BD_aux,3,FALSE),"")
A16: 31182853 | B16: Neisseria gonorrhoeae resistance driven by antibiotic use | C16: Dong HV, Klausner JD. | D16: Nat Rev Urol. 2019 Sep;16(9):509-510. doi: 10.1038/s41585-019-0206-2. | E16: Dong HV | F16: Nat Rev Urol | G16: 2019 | H16: 43628 | K16: 10.1038/s41585-019-0206-2 | L16: =IF(ISNUMBER(VLOOKUP(A16,EXCL,1,FALSE)),"Excluido",IF(ISNUMBER(VLOOKUP(A16,POST,1,FALSE)),"PostAlerta",IF(ISNUMBER(VLOOKUP(A16,PRE,1,FALSE)),"PreAlerta",""))) -> PostAlerta | M16: =IF(ISNUMBER(A16),(IF(ISNUMBER(VLOOKUP(A16,KEYWORDS,1,FALSE)),"C/PalabrasClaves","S/PalabrasClaves")),"") -> C/PalabrasClaves | N16: =IF(ISNUMBER(SEARCH("TREATMENT", B16)), "4) Nuevos tratamientos", "") | P16: 2019 Sep | R16: =LEFT('2012-2022'!$P16,4) -> 2019 | S16: Sep | T16: =IFERROR(VLOOKUP(A16,BD_aux,2,FALSE),"")
A17: 31378677 | B17: Commensal Neisseria Kill Neisseria gonorrhoeae through a DNA-Dependent Mechanism | C17: Kim WJ, Higashi D, Goytia M, Rendón MA, Pilligua-Lucas M, Bronnimann M, McLean JA, Duncan J, Trees D, Jerse AE, So M. | D17: Cell Host Microbe. 2019 Aug 14;26(2):228-239.e8. doi: 10.1016/j.chom.2019.07.003. Epub 2019 Aug 1. | E17: Kim WJ | F17: Cell Host Microbe | G17: 2019 | H17: 43683 | I17: PMC6728082 | J17: NIHMS1535495 | K17: 10.1016/j.chom.2019.07.003 | L17: =IF(ISNUMBER(VLOOKUP(A17,EXCL,1,FALSE)),"Excluido",IF(ISNUMBER(VLOOKUP(A17,POST,1,FALSE)),"PostAlerta",IF(ISNUMBER(VLOOKUP(A17,PRE,1,FALSE)),"PreAlerta",""))) -> PostAlerta | M17: =IF(ISNUMBER(A17),(IF(ISNUMBER(VLOOKUP(A17,KEYWORDS,1,FALSE)),"C/PalabrasClaves","S/PalabrasClaves")),"") -> C/PalabrasClaves | N17: =IF(ISNUMBER(SEARCH("TREATMENT", B17)), "4) Nuevos tratamientos", "") | P17: 2019 Aug 14 | R17: =LEFT('2012-2022'!$P17,4) -> 2019 | S17: Aug | T17: =IFERROR(VLOOKUP(A17,BD_aux,2,FALSE),"")
A18: 28387837 | B18: Genomic sequencing of Neisseria gonorrhoeae to respond to the urgent threat of antimicrobial-resistant gonorrhea | C18: Abrams AJ, Trees DL. | D18: Pathog Dis. 2017 Jun 1;75(4):10.1093/femspd/ftx041. doi: 10.1093/femspd/ftx041. | E18: Abrams AJ | F18: Pathog Dis | G18: 2017 | H18: 42833 | I18: PMC6956991 | J18: NIHMS1062768 | K18: 10.1093/femspd/ftx041 | L18: =IF(ISNUMBER(VLOOKUP(A18,EXCL,1,FALSE)),"Excluido",IF(ISNUMBER(VLOOKUP(A18,POST,1,FALSE)),"PostAlerta",IF(ISNUMBER(VLOOKUP(A18,PRE,1,FALSE)),"PreAlerta",""))) -> Excluido | M18: =IF(ISNUMBER(A18),(IF(ISNUMBER(VLOOKUP(A18,KEYWORDS,1,FALSE)),"C/PalabrasClaves","S/PalabrasClaves")),"") -> C/PalabrasClaves | N18: =IF(ISNUMBER(SEARCH("TREATMENT", B18)), "4) Nuevos tratamientos", "") | P18: 2017 Jun 1 | R18: =LEFT('2012-2022'!$P18,4) -> 2017 | S18: Jun | T18: =IFERROR(VLOOKUP(A18,BD_aux,2,FALSE),"")
A19: 29553336 | B19: Cephalosporin-Resistant Neisseria gonorrhoeae Clone, China | C19: Chen SC, Yin YP, Chen XS. | D19: Emerg Infect Dis. 2018 Apr;24(4):804-806. doi: 10.3201/eid2404.171817. | E19: Chen SC | F19: Emerg Infect Dis | G19: 2018 | H19: 43179 | I19: PMC5875255 | K19: 10.3201/eid2404.171817 | L19: =IF(ISNUMBER(VLOOKUP(A19,EXCL,1,FALSE)),"Excluido",IF(ISNUMBER(VLOOKUP(A19,POST,1,FALSE)),"PostAlerta",IF(ISNUMBER(VLOOKUP(A19,PRE,1,FALSE)),"PreAlerta",""))) -> PostAlerta | M19: =IF(ISNUMBER(A19),(IF(ISNUMBER(VLOOKUP(A19,KEYWORDS,1,FALSE)),"C/PalabrasClaves","S/PalabrasClaves")),"") -> C/PalabrasClaves | N19: 1) Reporte de cepas resistentes | P19: 2018 Apr | R19: =LEFT('2012-2022'!$P19,4) -> 2018 | S19: Apr | T19: Cephalosporin-resistant Neisseria gonorrhoeae is a major public health concern. N. gonorrhoeae of multiantigen sequence type G1407 and multilocus sequence type 1901 is an internationally spreading cephalosporin-resistant clone. We detected 4 cases of infection with this clone in China and analyzed resistance determinants by using N. gonorrhoeae sequence typing for antimicrobial resistance. | U19: Yes | V19: No | W19: No | X19: This report describes 4 cases in China of Neisseria gonorrhoeae infection caused by the cephalosporin-resistant international clone G1407 (MLST ST1901). | Y19: =IFERROR(VLOOKUP(A17,BD_aux,3,FALSE),"")
A20: 33245688 | B20: Neisseria gonorrhoeae clustering to reveal major European whole-genome-sequencing-based genogroups in association with antimicrobial resistance | C20: Pinto M, Borges V, Isidro J, Rodrigues JC, Vieira L, Borrego MJ, Gomes JP. | D20: Microb Genom. 2021 Feb;7(2):000481. doi: 10.1099/mgen.0.000481. | E20: Pinto M | F20: Microb Genom | G20: 2021 | H20: 44162 | I20: PMC8208699 | K20: 10.1099/mgen.0.000481 | L20: =IF(ISNUMBER(VLOOKUP(A20,EXCL,1,FALSE)),"Excluido",IF(ISNUMBER(VLOOKUP(A20,POST,1,FALSE)),"PostAlerta",IF(ISNUMBER(VLOOKUP(A20,PRE,1,FALSE)),"PreAlerta",""))) -> PostAlerta | M20: =IF(ISNUMBER(A20),(IF(ISNUMBER(VLOOKUP(A20,KEYWORDS,1,FALSE)),"C/PalabrasClaves","S/PalabrasClaves")),"") -> C/PalabrasClaves | N20: =IF(ISNUMBER(SEARCH("TREATMENT", B20)), "4) Nuevos tratamientos", "") | P20: 2021 Feb | R20: =LEFT('2012-2022'!$P20,4) -> 2021 | S20: Feb | T20: =IFERROR(VLOOKUP(A20,BD_aux,2,FALSE),"")
A21: 24275696 | B21: Global resistance of Neisseria gonorrhoeae: when theory becomes reality | C21: Lewis DA. | D21: Curr Opin Infect Dis. 2014 Feb;27(1):62-7. doi: 10.1097/QCO.0000000000000025. | E21: Lewis DA | F21: Curr Opin Infect Dis | G21: 2014 | H21: 41605 | K21: 10.1097/QCO.0000000000000025 | L21: =IF(ISNUMBER(VLOOKUP(A21,EXCL,1,FALSE)),"Excluido",IF(ISNUMBER(VLOOKUP(A21,POST,1,FALSE)),"PostAlerta",IF(ISNUMBER(VLOOKUP(A21,PRE,1,FALSE)),"PreAlerta",""))) -> Excluido | M21: =IF(ISNUMBER(A21),(IF(ISNUMBER(VLOOKUP(A21,KEYWORDS,1,FALSE)),"C/PalabrasClaves","S/PalabrasClaves")),"") -> C/PalabrasClaves | N21: =IF(ISNUMBER(SEARCH("TREATMENT", B21)), "4) Nuevos tratamientos", "") | P21: 2014 Feb | R21: =LEFT('2012-2022'!$P21,4) -> 2014 | S21: Feb | T21: =IFERROR(VLOOKUP(A21,BD_aux,2,FALSE),"")
A22: 34094619 | B22: Genomic surveillance of Neisseria gonorrhoeae in the Philippines, 2013-2014 | C22: Jamoralin MC Jr, Argimón S, Lagrada ML, Villamin AS, Masim ML, Gayeta JM, Boehme KD, Olorosa AM, Sia SB, Hufano CM, Cohen V, Hernandez LT, Jeffrey B, Abudahab K, Stelling J, Holden MTG, Aanensenb DM; e,*; Carlosa CC; Philippines Antimicrobial Resistance Surveillance Program. | D22: Western Pac Surveill Response J. 2021 Feb 26;12(1):17-25. doi: 10.5365/wpsar.2020.11.1.005. eCollection 2021 Jan-Mar. | E22: Jamoralin MC Jr | F22: Western Pac Surveill Response J | G22: 2021 | H22: 44354 | I22: PMC8143934 | K22: 10.5365/wpsar.2020.11.1.005 | L22: =IF(ISNUMBER(VLOOKUP(A22,EXCL,1,FALSE)),"Excluido",IF(ISNUMBER(VLOOKUP(A22,POST,1,FALSE)),"PostAlerta",IF(ISNUMBER(VLOOKUP(A22,PRE,1,FALSE)),"PreAlerta",""))) -> PostAlerta | M22: =IF(ISNUMBER(A22),(IF(ISNUMBER(VLOOKUP(A22,KEYWORDS,1,FALSE)),"C/PalabrasClaves","S/PalabrasClaves")),"") -> S/PalabrasClaves | N22: =IF(ISNUMBER(SEARCH("TREATMENT", B22)), "4) Nuevos tratamientos", "") | P22: 2021 Feb 26 | R22: =LEFT('2012-2022'!$P22,4) -> 2021 | S22: Feb | T22: =IFERROR(VLOOKUP(A22,BD_aux,2,FALSE),"")
A23: 31119637 | B23: Female Mouse Model of Neisseria gonorrhoeae Infection | C23: Raterman EL, Jerse AE. | D23: Methods Mol Biol. 2019;1997:413-429. doi: 10.1007/978-1-4939-9496-0_24. | E23: Raterman EL | F23: Methods Mol Biol | G23: 2019 | H23: 43609 | K23: 10.1007/978-1-4939-9496-0_24 | L23: =IF(ISNUMBER(VLOOKUP(A23,EXCL,1,FALSE)),"Excluido",IF(ISNUMBER(VLOOKUP(A23,POST,1,FALSE)),"PostAlerta",IF(ISNUMBER(VLOOKUP(A23,PRE,1,FALSE)),"PreAlerta",""))) -> PostAlerta | M23: =IF(ISNUMBER(A23),(IF(ISNUMBER(VLOOKUP(A23,KEYWORDS,1,FALSE)),"C/PalabrasClaves","S/PalabrasClaves")),"") -> C/PalabrasClaves | N23: =IF(ISNUMBER(SEARCH("TREATMENT", B23)), "4) Nuevos tratamientos", "") | P23: 2019 | R23: =LEFT('2012-2022'!$P23,4) -> 2019 | T23: =IFERROR(VLOOKUP(A23,BD_aux,2,FALSE),"")
A24: 34060328 | B24: Challenges and Controversies Concerning Neisseria gonorrhoeae-Neutrophil Interactions in Pathogenesis | C24: Criss AK, Genco CA, Gray-Owen SD, Jerse AE, Seifert HS. | D24: mBio. 2021 Jun 29;12(3):e0072121. doi: 10.1128/mBio.00721-21. Epub 2021 Jun 1. | E24: Criss AK | F24: mBio | G24: 2021 | H24: 44348 | I24: PMC8262874 | K24: 10.1128/mBio.00721-21 | L24: =IF(ISNUMBER(VLOOKUP(A24,EXCL,1,FALSE)),"Excluido",IF(ISNUMBER(VLOOKUP(A24,POST,1,FALSE)),"PostAlerta",IF(ISNUMBER(VLOOKUP(A24,PRE,1,FALSE)),"PreAlerta",""))) -> PostAlerta | M24: =IF(ISNUMBER(A24),(IF(ISNUMBER(VLOOKUP(A24,KEYWORDS,1,FALSE)),"C/PalabrasClaves","S/PalabrasClaves")),"") -> S/PalabrasClaves | N24: =IF(ISNUMBER(SEARCH("TREATMENT", B24)), "4) Nuevos tratamientos", "") | P24: 2021 Jun 29 | R24: =LEFT('2012-2022'!$P24,4) -> 2021 | S24: Jun | T24: =IFERROR(VLOOKUP(A24,BD_aux,2,FALSE),"")
A25: 34871932 | B25: Antimicrobial susceptibility testing of Neisseria gonorrhoeae using a phenotypic-molecular assay and lyophilized antimicrobials | C25: Melendez JH, Chen FE, Wang TH. | D25: Diagn Microbiol Infect Dis. 2022 Feb;102(2):115590. doi: 10.1016/j.diagmicrobio.2021.115590. Epub 2021 Oct 29. | E25: Melendez JH | F25: Diagn Microbiol Infect Dis | G25: 2022 | H25: 44536 | I25: PMC9241851 | J25: NIHMS1806938 | K25: 10.1016/j.diagmicrobio.2021.115590 | L25: =IF(ISNUMBER(VLOOKUP(A25,EXCL,1,FALSE)),"Excluido",IF(ISNUMBER(VLOOKUP(A25,POST,1,FALSE)),"PostAlerta",IF(ISNUMBER(VLOOKUP(A25,PRE,1,FALSE)),"PreAlerta",""))) -> PostAlerta | M25: =IF(ISNUMBER(A25),(IF(ISNUMBER(VLOOKUP(A25,KEYWORDS,1,FALSE)),"C/PalabrasClaves","S/PalabrasClaves")),"") -> C/PalabrasClaves | N25: 2) Nuevos tratamientos | O25: 2g) nueva combinación de ATB | P25: 2022 Feb | R25: =LEFT('2012-2022'!$P25,4) -> 2022 | S25: Feb | T25: Gonorrhea is an urgent global public health threat as Neisseria gonorrhoeae (Ng) has progressively developed resistance to all antibiotics commonly used for treatment. Surveillance of antimicrobial susceptibility trends is critical to monitor the emergence and spread of antimicrobial resistance. The gold standard methods for antimicrobial susceptibility testing (AST) of Ng are laborious and time-consuming. We evaluated a phenotypic molecular approach, involving a short cultivation step and quantitative PCR, with lyophilized antimicrobials to characterize antimicrobial susceptibility in Ng. There was excellent concordance between AST performed with liquid and lyophilized ciprofloxacin, penicillin, and tetracycline using the pheno-molecular assay, following a 4-hour incubation step. The categorical agreement between the pheno-molecular assay and the gold standard AST results was 92.4% for characterization of antimicrobial susceptibility. Essential agreement between the 2 methods was 91.9%. Characterization of ceftriaxone susceptibility in Ng using the pheno-molecular assay required a 6-hour incubation step. | U25: No | V25: No | W25: No | X25: This study assessed a rapid phenotypic molecular assay to test antimicrobial susceptibility in Neisseria gonorrhoeae, combining short incubation and qPCR with lyophilized antibiotics. | Y25: =IFERROR(VLOOKUP(A23,BD_aux,3,FALSE),"")
A26: 33536323 | B26: Comprehensive Bioinformatic Assessments of the Variability of Neisseria gonorrhoeae Vaccine Candidates | C26: Baarda BI, Zielke RA, Holm AK, Sikora AE. | D26: mSphere. 2021 Feb 3;6(1):e00977-20. doi: 10.1128/mSphere.00977-20. | E26: Baarda BI | F26: mSphere | G26: 2021 | H26: 44231 | I26: PMC7860988 | K26: 10.1128/mSphere.00977-20 | L26: =IF(ISNUMBER(VLOOKUP(A26,EXCL,1,FALSE)),"Excluido",IF(ISNUMBER(VLOOKUP(A26,POST,1,FALSE)),"PostAlerta",IF(ISNUMBER(VLOOKUP(A26,PRE,1,FALSE)),"PreAlerta",""))) -> PostAlerta | M26: =IF(ISNUMBER(A26),(IF(ISNUMBER(VLOOKUP(A26,KEYWORDS,1,FALSE)),"C/PalabrasClaves","S/PalabrasClaves")),"") -> C/PalabrasClaves | N26: =IF(ISNUMBER(SEARCH("TREATMENT", B26)), "4) Nuevos tratamientos", "") | P26: 2021 Feb 3 | R26: =LEFT('2012-2022'!$P26,4) -> 2021 | S26: Feb | T26: =IFERROR(VLOOKUP(A26,BD_aux,2,FALSE),"")
A27: 28407640 | B27: Wild-Type Gyrase A Genotype of Neisseria gonorrhoeae Predicts In Vitro Susceptibility to Ciprofloxacin: A Systematic Review of the Literature and Meta-Analysis | C27: Allan-Blitz LT, Wang X, Klausner JD. | D27: Sex Transm Dis. 2017 May;44(5):261-265. doi: 10.1097/OLQ.0000000000000591. | E27: Allan-Blitz LT | F27: Sex Transm Dis | G27: 2017 | H27: 42839 | I27: PMC5407314 | J27: NIHMS841754 | K27: 10.1097/OLQ.0000000000000591 | L27: =IF(ISNUMBER(VLOOKUP(A27,EXCL,1,FALSE)),"Excluido",IF(ISNUMBER(VLOOKUP(A27,POST,1,FALSE)),"PostAlerta",IF(ISNUMBER(VLOOKUP(A27,PRE,1,FALSE)),"PreAlerta",""))) -> Excluido | M27: =IF(ISNUMBER(A27),(IF(ISNUMBER(VLOOKUP(A27,KEYWORDS,1,FALSE)),"C/PalabrasClaves","S/PalabrasClaves")),"") -> C/PalabrasClaves | N27: =IF(ISNUMBER(SEARCH("TREATMENT", B27)), "4) Nuevos tratamientos", "") | P27: 2017 May | R27: =LEFT('2012-2022'!$P27,4) -> 2017 | S27: May | T27: =IFERROR(VLOOKUP(A27,BD_aux,2,FALSE),"")
A28: 27337478 | B28: Antimicrobial Resistance Expressed by Neisseria gonorrhoeae: A Major Global Public Health Problem in the 21st Century | C28: Unemo M, Del Rio C, Shafer WM. | D28: Microbiol Spectr. 2016 Jun;4(3):10.1128/microbiolspec.EI10-0009-2015. doi: 10.1128/microbiolspec.EI10-0009-2015. | E28: Unemo M | F28: Microbiol Spectr | G28: 2016 | H28: 42545 | I28: PMC4920088 | J28: NIHMS752938 | K28: 10.1128/microbiolspec.EI10-0009-2015 | L28: =IF(ISNUMBER(VLOOKUP(A28,EXCL,1,FALSE)),"Excluido",IF(ISNUMBER(VLOOKUP(A28,POST,1,FALSE)),"PostAlerta",IF(ISNUMBER(VLOOKUP(A28,PRE,1,FALSE)),"PreAlerta",""))) -> Excluido | M28: =IF(ISNUMBER(A28),(IF(ISNUMBER(VLOOKUP(A28,KEYWORDS,1,FALSE)),"C/PalabrasClaves","S/PalabrasClaves")),"") -> C/PalabrasClaves | N28: =IF(ISNUMBER(SEARCH("TREATMENT", B28)), "4) Nuevos tratamientos", "") | P28: 2016 Jun | R28: =LEFT('2012-2022'!$P28,4) -> 2016 | S28: Jun | T28: =IFERROR(VLOOKUP(A28,BD_aux,2,FALSE),"")
A29: 32149957 | B29: Reconsidering Presumptive Neisseria gonorrhoeae Treatment For Women With Cervicitis | C29: Nsuami MJ, Lillis RA, Martin DH. | D29: Sex Transm Dis. 2020 Jun;47(6):383-386. doi: 10.1097/OLQ.0000000000001156. | E29: Nsuami MJ | F29: Sex Transm Dis | G29: 2020 | H29: 43900 | K29: 10.1097/OLQ.0000000000001156 | L29: =IF(ISNUMBER(VLOOKUP(A29,EXCL,1,FALSE)),"Excluido",IF(ISNUMBER(VLOOKUP(A29,POST,1,FALSE)),"PostAlerta",IF(ISNUMBER(VLOOKUP(A29,PRE,1,FALSE)),"PreAlerta",""))) -> PostAlerta | M29: =IF(ISNUMBER(A29),(IF(ISNUMBER(VLOOKUP(A29,KEYWORDS,1,FALSE)),"C/PalabrasClaves","S/PalabrasClaves")),"") -> S/PalabrasClaves | N29: 2) Nuevos tratamientos | O29: change treatment | P29: 2020 Jun | R29: =LEFT('2012-2022'!$P29,4) -> 2020 | S29: Jun | T29: - | U29: No | V29: No | W29: No | X29: Not available | Y29: =IFERROR(VLOOKUP(A27,BD_aux,3,FALSE),"")
A30: 31119619 | B30: Preparation of Lipooligosaccharide (LOS) from Neisseria gonorrhoeae | C30: Christodoulides M. | D30: Methods Mol Biol. 2019;1997:87-96. doi: 10.1007/978-1-4939-9496-0_6. | E30: Christodoulides M | F30: Methods Mol Biol | G30: 2019 | H30: 43609 | K30: 10.1007/978-1-4939-9496-0_6 | L30: =IF(ISNUMBER(VLOOKUP(A30,EXCL,1,FALSE)),"Excluido",IF(ISNUMBER(VLOOKUP(A30,POST,1,FALSE)),"PostAlerta",IF(ISNUMBER(VLOOKUP(A30,PRE,1,FALSE)),"PreAlerta",""))) -> PostAlerta | M30: =IF(ISNUMBER(A30),(IF(ISNUMBER(VLOOKUP(A30,KEYWORDS,1,FALSE)),"C/PalabrasClaves","S/PalabrasClaves")),"") -> S/PalabrasClaves | N30: =IF(ISNUMBER(SEARCH("TREATMENT", B30)), "4) Nuevos tratamientos", "") | P30: 2019 | R30: =LEFT('2012-2022'!$P30,4) -> 2019 | T30: =IFERROR(VLOOKUP(A30,BD_aux,2,FALSE),"")
A31: 32091356 | B31: Genomic and Phenotypic Variability in Neisseria gonorrhoeae Antimicrobial Susceptibility, England | C31: Town K, Harris S, Sánchez-Busó L, Cole MJ, Pitt R, Fifer H, Mohammed H, Field N, Hughes G. | D31: Emerg Infect Dis. 2020 Mar;26(3):505-515. doi: 10.3201/eid2603.190732. | E31: Town K | F31: Emerg Infect Dis | G31: 2020 | H31: 43886 | I31: PMC7045833 | K31: 10.3201/eid2603.190732 | L31: =IF(ISNUMBER(VLOOKUP(A31,EXCL,1,FALSE)),"Excluido",IF(ISNUMBER(VLOOKUP(A31,POST,1,FALSE)),"PostAlerta",IF(ISNUMBER(VLOOKUP(A31,PRE,1,FALSE)),"PreAlerta",""))) -> PostAlerta | M31: =IF(ISNUMBER(A31),(IF(ISNUMBER(VLOOKUP(A31,KEYWORDS,1,FALSE)),"C/PalabrasClaves","S/PalabrasClaves")),"") -> C/PalabrasClaves | N31: =IF(ISNUMBER(SEARCH("TREATMENT", B31)), "4) Nuevos tratamientos", "") | P31: 2020 Mar | R31: =LEFT('2012-2022'!$P31,4) -> 2020 | S31: Mar | T31: =IFERROR(VLOOKUP(A31,BD_aux,2,FALSE),"")
A32: 32530860 | B32: Cephalosporin-Resistant Neisseria gonorrhoeae Isolated in Portugal, 2019 | C32: Pinto M, Matias R, Rodrigues JC, Duarte S, Vieira L, Gonçalves I, Gonçalves MJ, Ramos MH, Gomes JP, Borrego MJ. | D32: Sex Transm Dis. 2020 Nov;47(11):e54-e56. doi: 10.1097/OLQ.0000000000001218. | E32: Pinto M | F32: Sex Transm Dis | G32: 2020 | H32: 43995 | K32: 10.1097/OLQ.0000000000001218 | L32: =IF(ISNUMBER(VLOOKUP(A32,EXCL,1,FALSE)),"Excluido",IF(ISNUMBER(VLOOKUP(A32,POST,1,FALSE)),"PostAlerta",IF(ISNUMBER(VLOOKUP(A32,PRE,1,FALSE)),"PreAlerta",""))) -> PostAlerta | M32: =IF(ISNUMBER(A32),(IF(ISNUMBER(VLOOKUP(A32,KEYWORDS,1,FALSE)),"C/PalabrasClaves","S/PalabrasClaves")),"") -> C/PalabrasClaves | N32: 1) Reporte de cepas resistentes | P32: 2020 Nov | R32: =LEFT('2012-2022'!$P32,4) -> 2020 | S32: Nov | T32: We report a multidrug-resistant Neisseria gonorrhoeae exhibiting resistance to ceftriaxone and cefixime, isolated in Portugal in 2019. Whole-genome sequencing was performed for typing and identification of genetic determinants of antimicrobial resistance. Because of its antimicrobial susceptibility profile, awareness should be raised for the circulation of this strain. | U32: Yes | V32: No | W32: No | X32: This study reports a multidrug-resistant Neisseria gonorrhoeae strain isolated in Portugal in 2019, resistant to ceftriaxone and cefixime. | Y32: =IFERROR(VLOOKUP(A30,BD_aux,3,FALSE),"")
A33: 29131780 | B33: Ceftriaxone-Resistant Neisseria gonorrhoeae, Canada, 2017 | C33: Lefebvre B, Martin I, Demczuk W, Deshaies L, Michaud S, Labbé AC, Beaudoin MC, Longtin J. | D33: Emerg Infect Dis. 2018 Feb;24(2):381-3. doi: 10.3201/eid2402.171756. Epub 2018 Feb 17. | E33: Lefebvre B | F33: Emerg Infect Dis | G33: 2018 | H33: 43053 | I33: PMC5782888 | K33: 10.3201/eid2402.171756 | L33: =IF(ISNUMBER(VLOOKUP(A33,EXCL,1,FALSE)),"Excluido",IF(ISNUMBER(VLOOKUP(A33,POST,1,FALSE)),"PostAlerta",IF(ISNUMBER(VLOOKUP(A33,PRE,1,FALSE)),"PreAlerta",""))) -> PostAlerta | M33: =IF(ISNUMBER(A33),(IF(ISNUMBER(VLOOKUP(A33,KEYWORDS,1,FALSE)),"C/PalabrasClaves","S/PalabrasClaves")),"") -> C/PalabrasClaves | N33: =IF(ISNUMBER(SEARCH("TREATMENT", B33)), "4) Nuevos tratamientos", "") | P33: 2018 Feb | R33: =LEFT('2012-2022'!$P33,4) -> 2018 | S33: Feb | T33: =IFERROR(VLOOKUP(A33,BD_aux,2,FALSE),"")
A34: 33807121 | B34: Neisseria gonorrhoeae Multivalent Maxibody with a Broad Spectrum of Strain Specificity and Sensitivity for Gonorrhea Diagnosis | C34: Jeong J, Kim JS, Lee J, Seo YR, Yi EC, Kim KM. | D34: Biomolecules. 2021 Mar 23;11(3):484. doi: 10.3390/biom11030484. | E34: Jeong J | F34: Biomolecules | G34: 2021 | H34: 44289 | I34: PMC8004885 | K34: 10.3390/biom11030484 | L34: =IF(ISNUMBER(VLOOKUP(A34,EXCL,1,FALSE)),"Excluido",IF(ISNUMBER(VLOOKUP(A34,POST,1,FALSE)),"PostAlerta",IF(ISNUMBER(VLOOKUP(A34,PRE,1,FALSE)),"PreAlerta",""))) -> PostAlerta | M34: =IF(ISNUMBER(A34),(IF(ISNUMBER(VLOOKUP(A34,KEYWORDS,1,FALSE)),"C/PalabrasClaves","S/PalabrasClaves")),"") -> C/PalabrasClaves | N34: =IF(ISNUMBER(SEARCH("TREATMENT", B34)), "4) Nuevos tratamientos", "") | P34: 2021 Mar 23 | R34: =LEFT('2012-2022'!$P34,4) -> 2021 | S34: Mar | T34: =IFERROR(VLOOKUP(A34,BD_aux,2,FALSE),"")
A35: 30629196 | B35: Photoinactivation of Neisseria gonorrhoeae: A Paradigm-Changing Approach for Combating Antibiotic-Resistant Gonococcal Infection | C35: Wang Y, Ferrer-Espada R, Baglo Y, Goh XS, Held KD, Grad YH, Gu Y, Gelfand JA, Dai T. | D35: J Infect Dis. 2019 Jul 31;220(5):873-881. doi: 10.1093/infdis/jiz018. | E35: Wang Y | F35: J Infect Dis | G35: 2019 | H35: 43476 | I35: PMC6667797 | K35: 10.1093/infdis/jiz018 | L35: =IF(ISNUMBER(VLOOKUP(A35,EXCL,1,FALSE)),"Excluido",IF(ISNUMBER(VLOOKUP(A35,POST,1,FALSE)),"PostAlerta",IF(ISNUMBER(VLOOKUP(A35,PRE,1,FALSE)),"PreAlerta",""))) -> PostAlerta | M35: =IF(ISNUMBER(A35),(IF(ISNUMBER(VLOOKUP(A35,KEYWORDS,1,FALSE)),"C/PalabrasClaves","S/PalabrasClaves")),"") -> C/PalabrasClaves | N35: 2) Nuevos tratamientos | O35: No farmacológico (UV) | P35: 2019 Jul 31 | R35: =LEFT('2012-2022'!$P35,4) -> 2019 | S35: Jul | T35: Antimicrobial resistance in Neisseria gonorrhoeae is a major issue of public health, and there is a critical need for the development of new antigonococcal strategies. In this study, we investigated the effectiveness of antimicrobial blue light (aBL; wavelength, 405 nm), an innovative nonpharmacological approach, for the inactivation of N. gonorrhoeae. Our findings indicated that aBL preferentially inactivated N. gonorrhoeae, including antibiotic-resistant strains, over human vaginal epithelial cells in vitro. Furthermore, no aBL-induced genotoxicity to the vaginal epithelial cells was observed at the radiant exposure used to inactivate N. gonorrhoeae. aBL also effectively inactivated N. gonorrhoeae that had attached to and invaded into the vaginal epithelial cells in their cocultures. No gonococcal resistance to aBL developed after 15 successive cycles of inactivation induced by subtherapeutic exposure to aBL. Endogenous aBL-activatable photosensitizing porphyrins in N. gonorrhoeae were identified and quantified using ultraperformance liquid chromatography, with coproporphyrin being the most abundant species in all N. gonorrhoeae strains studied. Singlet oxygen was involved in aBL inactivation of N. gonorrhoeae. Together, these findings show that aBL represents a potential potent treatment for antibiotic-resistant gonococcal infection. | U35: No | V35: Yes | W35: No | X35: This study explored the efficacy of antimicrobial blue light (aBL, 405 nm) as a non-antibiotic treatment for Neisseria gonorrhoeae, including drug-resistant strains. aBL is a promising, resistance-proof therapeutic for gonorrhea, especially against antibiotic-resistant strains. | Y35: =IFERROR(VLOOKUP(A33,BD_aux,3,FALSE),"")
A36: 27551020 | B36: Neisseria gonorrhoeae Crippled Its Peptidoglycan Fragment Permease To Facilitate Toxic Peptidoglycan Monomer Release | C36: Chan JM, Dillard JP. | D36: J Bacteriol. 2016 Oct 7;198(21):3029-3040. doi: 10.1128/JB.00437-16. Print 2016 Nov 1. | E36: Chan JM | F36: J Bacteriol | G36: 2016 | H36: 42606 | I36: PMC5055606 | K36: 10.1128/JB.00437-16 | L36: =IF(ISNUMBER(VLOOKUP(A36,EXCL,1,FALSE)),"Excluido",IF(ISNUMBER(VLOOKUP(A36,POST,1,FALSE)),"PostAlerta",IF(ISNUMBER(VLOOKUP(A36,PRE,1,FALSE)),"PreAlerta",""))) -> PreAlerta | M36: =IF(ISNUMBER(A36),(IF(ISNUMBER(VLOOKUP(A36,KEYWORDS,1,FALSE)),"C/PalabrasClaves","S/PalabrasClaves")),"") -> S/PalabrasClaves | N36: =IF(ISNUMBER(SEARCH("TREATMENT", B36)), "4) Nuevos tratamientos", "") | P36: 2016 Oct 7 | R36: =LEFT('2012-2022'!$P36,4) -> 2016 | S36: Oct | T36: =IFERROR(VLOOKUP(A36,BD_aux,2,FALSE),"")
A37: 26063097 | B37: Review of 2005 Public Health Laboratory Network Neisseria gonorrhoeae nucleic acid amplification tests guidelines | C37: Whiley DM, Lahra MM; National Neisseria Network. | D37: Commun Dis Intell Q Rep. 2015 Mar 31;39(1):E42-5. | E37: Whiley DM | F37: Commun Dis Intell Q Rep | G37: 2015 | H37: 42167 | L37: =IF(ISNUMBER(VLOOKUP(A37,EXCL,1,FALSE)),"Excluido",IF(ISNUMBER(VLOOKUP(A37,POST,1,FALSE)),"PostAlerta",IF(ISNUMBER(VLOOKUP(A37,PRE,1,FALSE)),"PreAlerta",""))) -> Excluido | M37: =IF(ISNUMBER(A37),(IF(ISNUMBER(VLOOKUP(A37,KEYWORDS,1,FALSE)),"C/PalabrasClaves","S/PalabrasClaves")),"") -> S/PalabrasClaves | N37: =IF(ISNUMBER(SEARCH("TREATMENT", B37)), "4) Nuevos tratamientos", "") | P37: 2015 Mar 31 | R37: =LEFT('2012-2022'!$P37,4) -> 2015 | S37: Mar | T37: =IFERROR(VLOOKUP(A37,BD_aux,2,FALSE),"")
A38: 24074904 | B38: [Multiresistant Neisseria gonorrhoeae: back to the past?] | C38: Otero Guerra L, Vazquez F. | D38: Enferm Infecc Microbiol Clin. 2013 Nov;31(9):565-7. doi: 10.1016/j.eimc.2013.07.002. Epub 2013 Sep 26. | E38: Otero Guerra L | F38: Enferm Infecc Microbiol Clin | G38: 2013 | H38: 41548 | K38: 10.1016/j.eimc.2013.07.002 | L38: =IF(ISNUMBER(VLOOKUP(A38,EXCL,1,FALSE)),"Excluido",IF(ISNUMBER(VLOOKUP(A38,POST,1,FALSE)),"PostAlerta",IF(ISNUMBER(VLOOKUP(A38,PRE,1,FALSE)),"PreAlerta",""))) -> PreAlerta | M38: =IF(ISNUMBER(A38),(IF(ISNUMBER(VLOOKUP(A38,KEYWORDS,1,FALSE)),"C/PalabrasClaves","S/PalabrasClaves")),"") -> C/PalabrasClaves | N38: 1) Reporte de cepas resistentes | P38: 2013 Nov | Q38: Excluir | R38: =LEFT('2012-2022'!$P38,4) -> 2013 | S38: Nov | T38: - | U38: No | V38: No | W38: No | X38: Editorial | Y38: =IFERROR(VLOOKUP(A36,BD_aux,3,FALSE),"")
A39: 31289109 | B39: Disentangling the tangled web of Neisseria gonorrhoeae transmission: how important are oropharyngeal infections? | C39: Lewis DA. | D39: Sex Transm Infect. 2019 Sep;95(6):395-396. doi: 10.1136/sextrans-2019-054030. Epub 2019 Jul 9. | E39: Lewis DA | F39: Sex Transm Infect | G39: 2019 | H39: 43657 | K39: 10.1136/sextrans-2019-054030 | L39: =IF(ISNUMBER(VLOOKUP(A39,EXCL,1,FALSE)),"Excluido",IF(ISNUMBER(VLOOKUP(A39,POST,1,FALSE)),"PostAlerta",IF(ISNUMBER(VLOOKUP(A39,PRE,1,FALSE)),"PreAlerta",""))) -> PostAlerta | M39: =IF(ISNUMBER(A39),(IF(ISNUMBER(VLOOKUP(A39,KEYWORDS,1,FALSE)),"C/PalabrasClaves","S/PalabrasClaves")),"") -> S/PalabrasClaves | N39: =IF(ISNUMBER(SEARCH("TREATMENT", B39)), "4) Nuevos tratamientos", "") | P39: 2019 Sep | R39: =LEFT('2012-2022'!$P39,4) -> 2019 | S39: Sep | T39: =IFERROR(VLOOKUP(A39,BD_aux,2,FALSE),"")
A40: 26426083 | B40: Neisseria gonorrhoeae survives within and modulates apoptosis and inflammatory cytokine production of human macrophages | C40: Château A, Seifert HS. | D40: Cell Microbiol. 2016 Apr;18(4):546-60. doi: 10.1111/cmi.12529. Epub 2015 Oct 26. | E40: Château A | F40: Cell Microbiol | G40: 2016 | H40: 42279 | I40: PMC5240846 | J40: NIHMS841362 | K40: 10.1111/cmi.12529 | L40: =IF(ISNUMBER(VLOOKUP(A40,EXCL,1,FALSE)),"Excluido",IF(ISNUMBER(VLOOKUP(A40,POST,1,FALSE)),"PostAlerta",IF(ISNUMBER(VLOOKUP(A40,PRE,1,FALSE)),"PreAlerta",""))) -> PreAlerta | M40: =IF(ISNUMBER(A40),(IF(ISNUMBER(VLOOKUP(A40,KEYWORDS,1,FALSE)),"C/PalabrasClaves","S/PalabrasClaves")),"") -> S/PalabrasClaves | N40: =IF(ISNUMBER(SEARCH("TREATMENT", B40)), "4) Nuevos tratamientos", "") | P40: 2016 Apr | R40: =LEFT('2012-2022'!$P40,4) -> 2016 | S40: Apr | T40: =IFERROR(VLOOKUP(A40,BD_aux,2,FALSE),"")
A41: 34927774 | B41: Culture-free genotyping of Neisseria gonorrhoeae from urogenital samples in a high-density urban area in the North of Italy | C41: Gaspari V, Morselli S, Foschi C, Marangoni A. | D41: J Eur Acad Dermatol Venereol. 2022 Apr;36(4):e295-e297. doi: 10.1111/jdv.17882. Epub 2021 Dec 28. | E41: Gaspari V | F41: J Eur Acad Dermatol Venereol | G41: 2022 | H41: 44550 | K41: 10.1111/jdv.17882 | L41: =IF(ISNUMBER(VLOOKUP(A41,EXCL,1,FALSE)),"Excluido",IF(ISNUMBER(VLOOKUP(A41,POST,1,FALSE)),"PostAlerta",IF(ISNUMBER(VLOOKUP(A41,PRE,1,FALSE)),"PreAlerta",""))) -> PostAlerta | M41: =IF(ISNUMBER(A41),(IF(ISNUMBER(VLOOKUP(A41,KEYWORDS,1,FALSE)),"C/PalabrasClaves","S/PalabrasClaves")),"") -> S/PalabrasClaves | N41: =IF(ISNUMBER(SEARCH("TREATMENT", B41)), "4) Nuevos tratamientos", "") | P41: 2022 Apr | R41: =LEFT('2012-2022'!$P41,4) -> 2022 | S41: Apr | T41: =IFERROR(VLOOKUP(A41,BD_aux,2,FALSE),"")
A42: 29883770 | B42: Tetracycline resistance of Neisseria gonorrhoeae in Russia, 2015-2017 | C42: Shaskolskiy B, Dementieva E, Leinsoo A, Petrova N, Chestkov A, Kubanov A, Deryabin D, Gryadunov D. | D42: Infect Genet Evol. 2018 Sep;63:236-242. doi: 10.1016/j.meegid.2018.06.003. Epub 2018 Jun 5. | E42: Shaskolskiy B | F42: Infect Genet Evol | G42: 2018 | H42: 43260 | K42: 10.1016/j.meegid.2018.06.003 | L42: =IF(ISNUMBER(VLOOKUP(A42,EXCL,1,FALSE)),"Excluido",IF(ISNUMBER(VLOOKUP(A42,POST,1,FALSE)),"PostAlerta",IF(ISNUMBER(VLOOKUP(A42,PRE,1,FALSE)),"PreAlerta",""))) -> PostAlerta | M42: =IF(ISNUMBER(A42),(IF(ISNUMBER(VLOOKUP(A42,KEYWORDS,1,FALSE)),"C/PalabrasClaves","S/PalabrasClaves")),"") -> C/PalabrasClaves | N42: 1) Reporte de cepas resistentes | P42: 2018 Sep | R42: =LEFT('2012-2022'!$P42,4) -> 2018 | S42: Sep | T42: The objective of this study was to estimate the tetracycline resistance level in the modern population of Neisseria gonorrhoeae in the Russian Federation, where this drug was removed from the treatment regimen for gonococcal infections in 2003. A total of 401 isolates collected between 2015 and 2017 were analyzed for genetic markers (chromosomal porB, rpsJ and mtrR gene mutations and the plasmid-located tetM gene) involved in tetracycline resistance. Antibiotic susceptibility testing revealed that 19% of the strains were tetracycline resistant (MIC > 1 mg/L) and that 10% of the strains had intermediate susceptibility (0.5 < MIC ≤ 1 mg/L). Various combinations of mutations identified in the rpsJ (Val57Met/Leu), porB (Gly120Lys/Asp/Asn/Thr and Ala121/Asp/Asn/Gly), and mtrR (-35 del A) genes resulted in MIC increases of up to 1.47 mg/L (geometric mean value). The presence of the tetM gene was detected in 29 strains, including 18 tetM genes of the American type and 11 of the Dutch type. The tetM gene was associated with a strong increase in resistance (MIC > 8 mg/L). One N. gonorrhoeae isolate was found to carry a defective tetM gene with an AG deletion at position 1239-1240, а new stop codon was introduced that caused a defect in TetM protein synthesis and decrease in the tetracycline resistance. Phylogenetic trees constructed using N. gonorrhoeae NG-MAST and tetM loci were compared. Complex relationship was observed between the N. gonorrhoeae sequence type and the tetM plasmid type. Partial recovery of N. gonorrhoeae tetracycline susceptibility was observed relative to the proportion of isolates with resistance detected ten years ago (75%). However, the current levels of tetracycline resistance still preclude the renewed use of these drugs for gonococcal infection therapy. | U42: Yes | V42: No | W42: No | X42: This study assessed tetracycline resistance in Neisseria gonorrhoeae isolates in Russia after its removal from treatment protocols in 2003 | Y42: =IFERROR(VLOOKUP(A40,BD_aux,3,FALSE),"")
A43: 24498212 | B43: Worldwide susceptibility rates of Neisseria gonorrhoeae isolates to cefixime and cefpodoxime: a systematic review and meta-analysis | C43: Yu RX, Yin Y, Wang GQ, Chen SC, Zheng BJ, Dai XQ, Han Y, Li Q, Zhang GY, Chen X. | D43: PLoS One. 2014 Jan 31;9(1):e87849. doi: 10.1371/journal.pone.0087849. eCollection 2014. | E43: Yu RX | F43: PLoS One | G43: 2014 | H43: 41676 | I43: PMC3909252 | K43: 10.1371/journal.pone.0087849 | L43: =IF(ISNUMBER(VLOOKUP(A43,EXCL,1,FALSE)),"Excluido",IF(ISNUMBER(VLOOKUP(A43,POST,1,FALSE)),"PostAlerta",IF(ISNUMBER(VLOOKUP(A43,PRE,1,FALSE)),"PreAlerta",""))) -> Excluido | M43: =IF(ISNUMBER(A43),(IF(ISNUMBER(VLOOKUP(A43,KEYWORDS,1,FALSE)),"C/PalabrasClaves","S/PalabrasClaves")),"") -> C/PalabrasClaves | N43: =IF(ISNUMBER(SEARCH("TREATMENT", B43)), "4) Nuevos tratamientos", "") | P43: 2014 Jan 31 | R43: =LEFT('2012-2022'!$P43,4) -> 2014 | S43: Jan | T43: =IFERROR(VLOOKUP(A43,BD_aux,2,FALSE),"")
A44: 32163574 | B44: The Goldilocks Zone: Searching for a Phylogenetic Approach for the Recombinogenic Neisseria gonorrhoeae | C44: Kahler CM. | D44: J Infect Dis. 2020 Nov 9;222(11):1762-1763. doi: 10.1093/infdis/jiaa079. | E44: Kahler CM | F44: J Infect Dis | G44: 2020 | H44: 43903 | K44: 10.1093/infdis/jiaa079 | L44: =IF(ISNUMBER(VLOOKUP(A44,EXCL,1,FALSE)),"Excluido",IF(ISNUMBER(VLOOKUP(A44,POST,1,FALSE)),"PostAlerta",IF(ISNUMBER(VLOOKUP(A44,PRE,1,FALSE)),"PreAlerta",""))) -> PostAlerta | M44: =IF(ISNUMBER(A44),(IF(ISNUMBER(VLOOKUP(A44,KEYWORDS,1,FALSE)),"C/PalabrasClaves","S/PalabrasClaves")),"") -> S/PalabrasClaves | N44: =IF(ISNUMBER(SEARCH("TREATMENT", B44)), "4) Nuevos tratamientos", "") | P44: 2020 Nov 9 | R44: =LEFT('2012-2022'!$P44,4) -> 2020 | S44: Nov | T44: =IFERROR(VLOOKUP(A44,BD_aux,2,FALSE),"")
A45: 33109763 | B45: Discovery of a New Neisseria gonorrhoeae Type IV Pilus Assembly Factor, TfpC | C45: Hu LI, Yin S, Ozer EA, Sewell L, Rehman S, Garnett JA, Seifert HS. | D45: mBio. 2020 Oct 27;11(5):e02528-20. doi: 10.1128/mBio.02528-20. | E45: Hu LI | F45: mBio | G45: 2020 | H45: 44132 | I45: PMC7593972 | K45: 10.1128/mBio.02528-20 | L45: =IF(ISNUMBER(VLOOKUP(A45,EXCL,1,FALSE)),"Excluido",IF(ISNUMBER(VLOOKUP(A45,POST,1,FALSE)),"PostAlerta",IF(ISNUMBER(VLOOKUP(A45,PRE,1,FALSE)),"PreAlerta",""))) -> PostAlerta | M45: =IF(ISNUMBER(A45),(IF(ISNUMBER(VLOOKUP(A45,KEYWORDS,1,FALSE)),"C/PalabrasClaves","S/PalabrasClaves")),"") -> S/PalabrasClaves | N45: =IF(ISNUMBER(SEARCH("TREATMENT", B45)), "4) Nuevos tratamientos", "") | P45: 2020 Oct 27 | R45: =LEFT('2012-2022'!$P45,4) -> 2020 | S45: Oct | T45: =IFERROR(VLOOKUP(A45,BD_aux,2,FALSE),"")
A46: 31972174 | B46: Identification of potential therapeutic targets in Neisseria gonorrhoeae by an in-silico approach | C46: Tanwer P, Kolora SRR, Babbar A, Saluja D, Chaudhry U. | D46: J Theor Biol. 2020 Apr 7;490:110172. doi: 10.1016/j.jtbi.2020.110172. Epub 2020 Jan 20. | E46: Tanwer P | F46: J Theor Biol | G46: 2020 | H46: 43854 | K46: 10.1016/j.jtbi.2020.110172 | L46: =IF(ISNUMBER(VLOOKUP(A46,EXCL,1,FALSE)),"Excluido",IF(ISNUMBER(VLOOKUP(A46,POST,1,FALSE)),"PostAlerta",IF(ISNUMBER(VLOOKUP(A46,PRE,1,FALSE)),"PreAlerta",""))) -> PostAlerta | M46: =IF(ISNUMBER(A46),(IF(ISNUMBER(VLOOKUP(A46,KEYWORDS,1,FALSE)),"C/PalabrasClaves","S/PalabrasClaves")),"") -> C/PalabrasClaves | N46: 2) Nuevos tratamientos | O46: in silico | P46: 2020 Apr 7 | R46: =LEFT('2012-2022'!$P46,4) -> 2020 | S46: Apr | T46: Neisseria gonorrhoeae is a gram negative diplococcus bacterium and the causative agent of the sexually transmitted disease Gonorrhea. It has been recently given the status of "superbug" by World Health Organization because of the increasing antibiotic resistance and unavailability of a viable vaccine candidate. Over recent years, there have been increasing reports about the use of subtractive genomics to identify potential drug and vaccine targets. Our study utilizes codon biasing, a tool to identify the essential genes, in N. gonorrhoeae that could be utilized as novel therapeutic targets for drug or vaccine development. Through the screening of 2350 total genes, we present a list of 29 such drug candidate genes based on codon adaptation. Through the data-mining with BLAST2GO and InterProScan databases, we could predict the function of these 29 genes. These genes are involved in pivotal cellular functions like DNA replication, energy synthesis and metabolites production. This study also shortlists the essential genes of N. gonorrhoeae that could be used to target Neisseria. We identified a molecule/drug which can be used to target essential protein DapD (succinyltransferase). | U46: No | V46: Yes | W46: No | X46: Essential genes identified via codon bias in N. gonorrhoeae suggest novel targets for drugs or vaccines, including DapD protein. | Y46: =IFERROR(VLOOKUP(A44,BD_aux,3,FALSE),"")
A47: 31978578 | B47: Genetic diversity of Neisseria gonorrhoeae multi-antigen sequence types in Russia and Europe | C47: Shaskolskiy B, Dementieva E, Kandinov I, Chestkov A, Kubanov A, Deryabin D, Gryadunov D. | D47: Int J Infect Dis. 2020 Apr;93:1-8. doi: 10.1016/j.ijid.2020.01.020. Epub 2020 Jan 21. | E47: Shaskolskiy B | F47: Int J Infect Dis | G47: 2020 | H47: 43855 | K47: 10.1016/j.ijid.2020.01.020 | L47: =IF(ISNUMBER(VLOOKUP(A47,EXCL,1,FALSE)),"Excluido",IF(ISNUMBER(VLOOKUP(A47,POST,1,FALSE)),"PostAlerta",IF(ISNUMBER(VLOOKUP(A47,PRE,1,FALSE)),"PreAlerta",""))) -> PostAlerta | M47: =IF(ISNUMBER(A47),(IF(ISNUMBER(VLOOKUP(A47,KEYWORDS,1,FALSE)),"C/PalabrasClaves","S/PalabrasClaves")),"") -> S/PalabrasClaves | N47: =IF(ISNUMBER(SEARCH("TREATMENT", B47)), "4) Nuevos tratamientos", "") | P47: 2020 Apr | R47: =LEFT('2012-2022'!$P47,4) -> 2020 | S47: Apr | T47: =IFERROR(VLOOKUP(A47,BD_aux,2,FALSE),"")
A48: 30787927 | B48: The Neisseria gonorrhoeae Methionine Sulfoxide Reductase (MsrA/B) Is a Surface Exposed, Immunogenic, Vaccine Candidate | C48: Jen FE, Semchenko EA, Day CJ, Seib KL, Jennings MP. | D48: Front Immunol. 2019 Feb 6;10:137. doi: 10.3389/fimmu.2019.00137. eCollection 2019. | E48: Jen FE | F48: Front Immunol | G48: 2019 | H48: 43518 | I48: PMC6372556 | K48: 10.3389/fimmu.2019.00137 | L48: =IF(ISNUMBER(VLOOKUP(A48,EXCL,1,FALSE)),"Excluido",IF(ISNUMBER(VLOOKUP(A48,POST,1,FALSE)),"PostAlerta",IF(ISNUMBER(VLOOKUP(A48,PRE,1,FALSE)),"PreAlerta",""))) -> PostAlerta | M48: =IF(ISNUMBER(A48),(IF(ISNUMBER(VLOOKUP(A48,KEYWORDS,1,FALSE)),"C/PalabrasClaves","S/PalabrasClaves")),"") -> S/PalabrasClaves | N48: 3) Inmunizacióm | P48: 2019 Feb 6 | R48: =LEFT('2012-2022'!$P48,4) -> 2019 | S48: Feb | T48: Control of the sexually transmitted infection gonorrhea is a major public health challenge, due to the recent emergence of multidrug resistant strains of Neisseria gonorrhoeae, and there is an urgent need for novel therapies or a vaccine to prevent gonococcal disease. In this study, we evaluated the methionine sulfoxide reductase (MsrA/B) of N. gonorrhoeae as a potential vaccine candidate, in terms of its expression, sequence conservation, localization, immunogenicity, and the functional activity of antibodies raised to it. Gonococcal MsrA/B has previously been shown to reduce methionine sulfoxide [Met(O)] to methionine (Met) in oxidized proteins and protect against oxidative stress. Here we have shown that the gene encoding MsrA/B is present, highly conserved, and expressed in all N. gonorrhoeae strains investigated, and we determined that MsrA/B is surface is exposed on N. gonorrhoeae. Recombinant MsrA/B is immunogenic, and mice immunized with MsrA/B and either aluminum hydroxide gel adjuvant or Freund's adjuvant generated a humoral immune response, with predominantly IgG1 antibodies. Higher titers of IgG2a, IgG2b, and IgG3 were detected in mice immunized with MsrA/B-Freund's adjuvant compared to MsrA/B-aluminum hydroxide adjuvant, while IgM titers were similar for both adjuvants. Antibodies generated by MsrA/B-Freund's in mice mediated bacterial killing via both serum bactericidal activity and opsonophagocytic activity. Anti-MsrA/B was also able to functionally block the activity of MsrA/B by inhibiting binding to its substrate, Met(O). We propose that recombinant MsrA/B is a promising vaccine antigen for N. gonorrhoeae. | U48: No | V48: No | W48: Yes | X48: MsrA/B protein is conserved, surface-exposed, immunogenic, and elicits bactericidal antibodies, supporting its use as a vaccine antigen. | Y48: =IFERROR(VLOOKUP(A46,BD_aux,3,FALSE),"")
A49: 32873606 | B49: High precision Neisseria gonorrhoeae variant and antimicrobial resistance calling from metagenomic Nanopore sequencing | C49: Sanderson ND, Swann J, Barker L, Kavanagh J, Hoosdally S, Crook D; GonFast Investigators Group; Street TL, Eyre DW. | D49: Genome Res. 2020 Sep;30(9):1354-1363. doi: 10.1101/gr.262865.120. Epub 2020 Sep 1. | E49: Sanderson ND | F49: Genome Res | G49: 2020 | H49: 44077 | I49: PMC7545138 | K49: 10.1101/gr.262865.120 | L49: =IF(ISNUMBER(VLOOKUP(A49,EXCL,1,FALSE)),"Excluido",IF(ISNUMBER(VLOOKUP(A49,POST,1,FALSE)),"PostAlerta",IF(ISNUMBER(VLOOKUP(A49,PRE,1,FALSE)),"PreAlerta",""))) -> PostAlerta | M49: =IF(ISNUMBER(A49),(IF(ISNUMBER(VLOOKUP(A49,KEYWORDS,1,FALSE)),"C/PalabrasClaves","S/PalabrasClaves")),"") -> C/PalabrasClaves | N49: =IF(ISNUMBER(SEARCH("TREATMENT", B49)), "4) Nuevos tratamientos", "") | P49: 2020 Sep | R49: =LEFT('2012-2022'!$P49,4) -> 2020 | S49: Sep | T49: =IFERROR(VLOOKUP(A49,BD_aux,2,FALSE),"")
A50: 23093736 | B50: Point-of-care tests for the diagnosis of Neisseria gonorrhoeae infection: a systematic review of operational and performance characteristics | C50: Watchirs Smith LA, Hillman R, Ward J, Whiley DM, Causer L, Skov S, Donovan B, Kaldor J, Guy R. | D50: Sex Transm Infect. 2013 Jun;89(4):320-6. doi: 10.1136/sextrans-2012-050656. Epub 2012 Oct 23. | E50: Watchirs Smith LA | F50: Sex Transm Infect | G50: 2013 | H50: 41207 | K50: 10.1136/sextrans-2012-050656 | L50: =IF(ISNUMBER(VLOOKUP(A50,EXCL,1,FALSE)),"Excluido",IF(ISNUMBER(VLOOKUP(A50,POST,1,FALSE)),"PostAlerta",IF(ISNUMBER(VLOOKUP(A50,PRE,1,FALSE)),"PreAlerta",""))) -> Excluido | M50: =IF(ISNUMBER(A50),(IF(ISNUMBER(VLOOKUP(A50,KEYWORDS,1,FALSE)),"C/PalabrasClaves","S/PalabrasClaves")),"") -> S/PalabrasClaves | N50: =IF(ISNUMBER(SEARCH("TREATMENT", B50)), "4) Nuevos tratamientos", "") | P50: 2013 Jun | R50: =LEFT('2012-2022'!$P50,4) -> 2013 | S50: Jun | T50: =IFERROR(VLOOKUP(A50,BD_aux,2,FALSE),"")
A51: 30239814 | B51: Azithromycin Susceptibility Among Neisseria gonorrhoeae Isolates and Seasonal Macrolide Use | C51: Olesen SW, Torrone EA, Papp JR, Kirkcaldy RD, Lipsitch M, Grad YH. | D51: J Infect Dis. 2019 Jan 29;219(4):619-623. doi: 10.1093/infdis/jiy551. | E51: Olesen SW | F51: J Infect Dis | G51: 2019 | H51: 43365 | I51: PMC6350947 | K51: 10.1093/infdis/jiy551 | L51: =IF(ISNUMBER(VLOOKUP(A51,EXCL,1,FALSE)),"Excluido",IF(ISNUMBER(VLOOKUP(A51,POST,1,FALSE)),"PostAlerta",IF(ISNUMBER(VLOOKUP(A51,PRE,1,FALSE)),"PreAlerta",""))) -> PostAlerta | M51: =IF(ISNUMBER(A51),(IF(ISNUMBER(VLOOKUP(A51,KEYWORDS,1,FALSE)),"C/PalabrasClaves","S/PalabrasClaves")),"") -> C/PalabrasClaves | N51: 1) Reporte de cepas resistentes | P51: 2019 Jan 29 | R51: =LEFT('2012-2022'!$P51,4) -> 2019 | S51: Jan | T51: Rising azithromycin nonsusceptibility among Neisseria gonorrhoeae isolates threatens current treatment recommendations, but the cause of this rise is not well understood. We performed an ecological study of seasonal patterns in macrolide use and azithromycin resistance in N. gonorrhoeae, finding that population-wide macrolide use is associated with increased azithromycin nonsusceptibility. These results, indicative of bystander selection, have implications for antibiotic prescribing guidelines. | U51: Yes | V51: No | W51: No | X51: Increased macrolide use correlates with azithromycin nonsusceptibility in N. gonorrhoeae | Y51: =IFERROR(VLOOKUP(A49,BD_aux,3,FALSE),"")
A52: 25480491 | B52: Neisseria gonorrhoeae isolates with high-level resistance to azithromycin in Australia | C52: Stevens K, Zaia A, Tawil S, Bates J, Hicks V, Whiley D, Limnios A, Lahra MM, Howden BP. | D52: J Antimicrob Chemother. 2015 Apr;70(4):1267-8. doi: 10.1093/jac/dku490. Epub 2014 Dec 4. | E52: Stevens K | F52: J Antimicrob Chemother | G52: 2015 | H52: 41980 | K52: 10.1093/jac/dku490 | L52: =IF(ISNUMBER(VLOOKUP(A52,EXCL,1,FALSE)),"Excluido",IF(ISNUMBER(VLOOKUP(A52,POST,1,FALSE)),"PostAlerta",IF(ISNUMBER(VLOOKUP(A52,PRE,1,FALSE)),"PreAlerta",""))) -> PreAlerta | M52: =IF(ISNUMBER(A52),(IF(ISNUMBER(VLOOKUP(A52,KEYWORDS,1,FALSE)),"C/PalabrasClaves","S/PalabrasClaves")),"") -> C/PalabrasClaves | N52: 1) Reporte de cepas resistentes | P52: 2015 Apr | R52: =LEFT('2012-2022'!$P52,4) -> 2015 | S52: Apr | T52: Antimicrobial resistance in Neisseria gonorrhoeae is a major public health concern globally. Over time, gonococci have developed resistance to most antimicrobial agents used for first-line treatment and declining susceptibility to the extended-spectrum cephalosporins is emerging worldwide.1–3 Consequently, dual antimicrobial therapy consisting of ceftriaxone (250 or 500 mg by intramuscular injection) together with azithromycin (1 or 2 g orally) is now recommended as standard treatment for gonorrhoea in the USA, the UK and Europe and is now gradually being adopted in major clinics throughout Australia.4–7 Monotherapy with 2 g of azithromycin is an alternative treatment in patients who are allergic to cephalosporins.4 These treatment regimens are threatened by the emergence of azithromycin resistance in gonococci, particularly high-level azithromycin resistance. High-level azithromycin resistance in N. gonorrhoeae, defined by an azithromycin MIC >256 mg/L, is associated with mutations in the peptidyltransferase loop in domain V of the 23S rRNA gene, principally A2059G, and a single base pair deletion (A) in the promoter region of the mtrR gene.8,9 Isolates of gonococci displaying high-level azithromycin resistance have been reported from the UK, Italy, Argentina, the USA and Sweden.10–14 Here, we provide the first report of gonococci in Australia with high-level azithromycin resistance. | U52: Yes | V52: No | W52: No | X52: High-level azithromycin-resistant N. gonorrhoeae with key 23S rRNA and mtrR mutations is now reported for the first time in Australia. | Y52: =IFERROR(VLOOKUP(A50,BD_aux,3,FALSE),"")
A53: 29581317 | B53: The Brief Case: Disseminated Neisseria gonorrhoeae in an 18-Year-Old Female | C53: Burns JE, Graf EH. | D53: J Clin Microbiol. 2018 Mar 26;56(4):e00932-17. doi: 10.1128/JCM.00932-17. Print 2018 Apr. | E53: Burns JE | F53: J Clin Microbiol | G53: 2018 | H53: 43187 | I53: PMC5869837 | K53: 10.1128/JCM.00932-17 | L53: =IF(ISNUMBER(VLOOKUP(A53,EXCL,1,FALSE)),"Excluido",IF(ISNUMBER(VLOOKUP(A53,POST,1,FALSE)),"PostAlerta",IF(ISNUMBER(VLOOKUP(A53,PRE,1,FALSE)),"PreAlerta",""))) -> PostAlerta | M53: =IF(ISNUMBER(A53),(IF(ISNUMBER(VLOOKUP(A53,KEYWORDS,1,FALSE)),"C/PalabrasClaves","S/PalabrasClaves")),"") -> S/PalabrasClaves | N53: =IF(ISNUMBER(SEARCH("TREATMENT", B53)), "4) Nuevos tratamientos", "") | P53: 2018 Mar 26 | R53: =LEFT('2012-2022'!$P53,4) -> 2018 | S53: Mar | T53: =IFERROR(VLOOKUP(A53,BD_aux,2,FALSE),"")
A54: 28520925 | B54: The ironclad truth: how in vivo transcriptomics and in vitro mechanistic studies shape our understanding of Neisseria gonorrhoeae gene regulation during mucosal infection | C54: Moreau MR, Massari P, Genco CA. | D54: Pathog Dis. 2017 Jul 31;75(5):ftx057. doi: 10.1093/femspd/ftx057. | E54: Moreau MR | F54: Pathog Dis | G54: 2017 | H54: 42874 | I54: PMC5808646 | K54: 10.1093/femspd/ftx057 | L54: =IF(ISNUMBER(VLOOKUP(A54,EXCL,1,FALSE)),"Excluido",IF(ISNUMBER(VLOOKUP(A54,POST,1,FALSE)),"PostAlerta",IF(ISNUMBER(VLOOKUP(A54,PRE,1,FALSE)),"PreAlerta",""))) -> Excluido | M54: =IF(ISNUMBER(A54),(IF(ISNUMBER(VLOOKUP(A54,KEYWORDS,1,FALSE)),"C/PalabrasClaves","S/PalabrasClaves")),"") -> C/PalabrasClaves | P54: 2017 Jul 31 | R54: =LEFT('2012-2022'!$P54,4) -> 2017 | S54: Jul | T54: =IFERROR(VLOOKUP(A54,BD_aux,2,FALSE),"") | X54: =IFERROR(VLOOKUP(A54,BD_aux,4,FALSE),"") | Y54: =IFERROR(VLOOKUP(A52,BD_aux,3,FALSE),"")
A55: 32366604 | B55: Molecular epidemiology of Neisseria gonorrhoeae clinical isolates in Reunion and Mayotte | C55: Jacquier H, Miltgen G, Hoarau D, Kumanski S, Rollot O, Bruniquet S, Ndeikoundam N, Li Pat-Yuen G, Belmonte O, Bercot B, Roquebert B. | D55: Sex Transm Infect. 2020 Nov;96(7):478-479. doi: 10.1136/sextrans-2019-054374. Epub 2020 May 4. | E55: Jacquier H | F55: Sex Transm Infect | G55: 2020 | H55: 43957 | K55: 10.1136/sextrans-2019-054374 | L55: =IF(ISNUMBER(VLOOKUP(A55,EXCL,1,FALSE)),"Excluido",IF(ISNUMBER(VLOOKUP(A55,POST,1,FALSE)),"PostAlerta",IF(ISNUMBER(VLOOKUP(A55,PRE,1,FALSE)),"PreAlerta",""))) -> PostAlerta | M55: =IF(ISNUMBER(A55),(IF(ISNUMBER(VLOOKUP(A55,KEYWORDS,1,FALSE)),"C/PalabrasClaves","S/PalabrasClaves")),"") -> C/PalabrasClaves | N55: =IF(ISNUMBER(SEARCH("TREATMENT", B55)), "4) Nuevos tratamientos", "") | P55: 2020 Nov | R55: =LEFT('2012-2022'!$P55,4) -> 2020 | S55: Nov | T55: =IFERROR(VLOOKUP(A55,BD_aux,2,FALSE),"")
A56: 22492861 | B56: Fluoroquinolone resistance in Neisseria gonorrhoeae: fitness cost or benefit? | C56: Dillon JA, Parti RP. | D56: J Infect Dis. 2012 Jun 15;205(12):1775-7. doi: 10.1093/infdis/jis281. Epub 2012 Apr 5. | E56: Dillon JA | F56: J Infect Dis | G56: 2012 | H56: 41011 | K56: 10.1093/infdis/jis281 | L56: =IF(ISNUMBER(VLOOKUP(A56,EXCL,1,FALSE)),"Excluido",IF(ISNUMBER(VLOOKUP(A56,POST,1,FALSE)),"PostAlerta",IF(ISNUMBER(VLOOKUP(A56,PRE,1,FALSE)),"PreAlerta",""))) -> PreAlerta | M56: =IF(ISNUMBER(A56),(IF(ISNUMBER(VLOOKUP(A56,KEYWORDS,1,FALSE)),"C/PalabrasClaves","S/PalabrasClaves")),"") -> C/PalabrasClaves | N56: 1) Reporte de cepas resistentes | P56: 2012 Jun 15 | R56: =LEFT('2012-2022'!$P56,4) -> 2012 | S56: Jun | T56: The successful treatment of gonorrhea, presently the second most prevalent bacterial sexually transmitted infection worldwide, has historically taken full advantage of the introduction of successive new categories of antimicrobial agents to successfully eliminate the microorganism causing this disease, Neisseria gonorrhoeae. New antibiotics have replaced older ones for treatment because N. gonorrhoeae has progressively developed resistance to each class introduced; first to sulphonamides, then to penicillins, tetracyclines, and then quinolones and macrolides [1, 2]. While the last class of antimicrobial effective for the treatment of gonorrhea is the third-generation cephalosporins, more and more reports are emerging of in vitro decreased susceptibility and treatment failures to the oral cephalosporins, such as cefixime, coupled with recent reports of strains with high-level resistance to ceftriaxone [3–5]. The strains with high-level resistance to cephalosporins also exhibited resistance or reduced susceptibility to several other antibiotics. Thus, there is a great concern that gonorrhea has become an untreatable superbug in certain instances, and the search for effective alternative treatment strategies and therapies, possibly a combination of antibiotics, is urgent [5, 6]. | U56: Yes | V56: No | W56: No | X56: This review highlights the global threat of antimicrobial-resistant Neisseria gonorrhoeae. | Y56: =IFERROR(VLOOKUP(A54,BD_aux,3,FALSE),"")
A57: 31356532 | B57: Neisseria gonorrhoeae as a Rare Cause of Preseptal Cellulitis | C57: Adamson PC, Judson SD, Klausner JD, Kelesidis T. | D57: Sex Transm Dis. 2019 Dec;46(12):813-815. doi: 10.1097/OLQ.0000000000001055. | E57: Adamson PC | F57: Sex Transm Dis | G57: 2019 | H57: 43676 | I57: PMC8077177 | J57: NIHMS1691326 | K57: 10.1097/OLQ.0000000000001055 | L57: =IF(ISNUMBER(VLOOKUP(A57,EXCL,1,FALSE)),"Excluido",IF(ISNUMBER(VLOOKUP(A57,POST,1,FALSE)),"PostAlerta",IF(ISNUMBER(VLOOKUP(A57,PRE,1,FALSE)),"PreAlerta",""))) -> PostAlerta | M57: =IF(ISNUMBER(A57),(IF(ISNUMBER(VLOOKUP(A57,KEYWORDS,1,FALSE)),"C/PalabrasClaves","S/PalabrasClaves")),"") -> S/PalabrasClaves | N57: =IF(ISNUMBER(SEARCH("TREATMENT", B57)), "4) Nuevos tratamientos", "") | P57: 2019 Dec | R57: =LEFT('2012-2022'!$P57,4) -> 2019 | S57: Dec | T57: =IFERROR(VLOOKUP(A57,BD_aux,2,FALSE),"")
A58: 35061686 | B58: 72-Hour transport recovery of antimicrobial resistant Neisseria gonorrhoeae isolates using the InTray® GC method | C58: Paris KS, Font B, Mehta SR, Huerta I, Bristow CC. | D58: PLoS One. 2022 Jan 21;17(1):e0259668. doi: 10.1371/journal.pone.0259668. eCollection 2022. | E58: Paris KS | F58: PLoS One | G58: 2022 | H58: 44582 | I58: PMC8782362 | K58: 10.1371/journal.pone.0259668 | L58: =IF(ISNUMBER(VLOOKUP(A58,EXCL,1,FALSE)),"Excluido",IF(ISNUMBER(VLOOKUP(A58,POST,1,FALSE)),"PostAlerta",IF(ISNUMBER(VLOOKUP(A58,PRE,1,FALSE)),"PreAlerta",""))) -> PostAlerta | M58: =IF(ISNUMBER(A58),(IF(ISNUMBER(VLOOKUP(A58,KEYWORDS,1,FALSE)),"C/PalabrasClaves","S/PalabrasClaves")),"") -> C/PalabrasClaves | N58: =IF(ISNUMBER(SEARCH("TREATMENT", B58)), "4) Nuevos tratamientos", "") | P58: 2022 Jan 21 | R58: =LEFT('2012-2022'!$P58,4) -> 2022 | S58: Jan | T58: =IFERROR(VLOOKUP(A58,BD_aux,2,FALSE),"")
A59: 27274027 | B59: Seminal Plasma Promotes Neisseria gonorrhoeae Aggregation and Biofilm Formation | C59: Anderson MT, Byerly L, Apicella MA, Seifert HS. | D59: J Bacteriol. 2016 Jul 28;198(16):2228-35. doi: 10.1128/JB.00165-16. Print 2016 Aug 15. | E59: Anderson MT | F59: J Bacteriol | G59: 2016 | H59: 42530 | I59: PMC4966444 | K59: 10.1128/JB.00165-16 | L59: =IF(ISNUMBER(VLOOKUP(A59,EXCL,1,FALSE)),"Excluido",IF(ISNUMBER(VLOOKUP(A59,POST,1,FALSE)),"PostAlerta",IF(ISNUMBER(VLOOKUP(A59,PRE,1,FALSE)),"PreAlerta",""))) -> PreAlerta | M59: =IF(ISNUMBER(A59),(IF(ISNUMBER(VLOOKUP(A59,KEYWORDS,1,FALSE)),"C/PalabrasClaves","S/PalabrasClaves")),"") -> S/PalabrasClaves | N59: =IF(ISNUMBER(SEARCH("TREATMENT", B59)), "4) Nuevos tratamientos", "") | P59: 2016 Jul 28 | R59: =LEFT('2012-2022'!$P59,4) -> 2016 | S59: Jul | T59: =IFERROR(VLOOKUP(A59,BD_aux,2,FALSE),"")
A60: 34138928 | B60: Visible colorimetric growth indicators of Neisseria gonorrhoeae for low-cost diagnostic applications | C60: Oeschger TM, Erickson DC. | D60: PLoS One. 2021 Jun 17;16(6):e0252961. doi: 10.1371/journal.pone.0252961. eCollection 2021. | E60: Oeschger TM | F60: PLoS One | G60: 2021 | H60: 44364 | I60: PMC8211239 | K60: 10.1371/journal.pone.0252961 | L60: =IF(ISNUMBER(VLOOKUP(A60,EXCL,1,FALSE)),"Excluido",IF(ISNUMBER(VLOOKUP(A60,POST,1,FALSE)),"PostAlerta",IF(ISNUMBER(VLOOKUP(A60,PRE,1,FALSE)),"PreAlerta",""))) -> PostAlerta | M60: =IF(ISNUMBER(A60),(IF(ISNUMBER(VLOOKUP(A60,KEYWORDS,1,FALSE)),"C/PalabrasClaves","S/PalabrasClaves")),"") -> C/PalabrasClaves | N60: =IF(ISNUMBER(SEARCH("TREATMENT", B60)), "4) Nuevos tratamientos", "") | P60: 2021 Jun 17 | R60: =LEFT('2012-2022'!$P60,4) -> 2021 | S60: Jun | T60: =IFERROR(VLOOKUP(A60,BD_aux,2,FALSE),"")
A61: 31740492 | B61: Antigenic Variation in Neisseria gonorrhoeae Occurs Independently of RecQ-Mediated Unwinding of the pilE G Quadruplex | C61: Voter AF, Callaghan MM, Tippana R, Myong S, Dillard JP, Keck JL. | D61: J Bacteriol. 2020 Jan 15;202(3):e00607-19. doi: 10.1128/JB.00607-19. Print 2020 Jan 15. | E61: Voter AF | F61: J Bacteriol | G61: 2020 | H61: 43789 | I61: PMC6964745 | K61: 10.1128/JB.00607-19 | L61: =IF(ISNUMBER(VLOOKUP(A61,EXCL,1,FALSE)),"Excluido",IF(ISNUMBER(VLOOKUP(A61,POST,1,FALSE)),"PostAlerta",IF(ISNUMBER(VLOOKUP(A61,PRE,1,FALSE)),"PreAlerta",""))) -> PostAlerta | M61: =IF(ISNUMBER(A61),(IF(ISNUMBER(VLOOKUP(A61,KEYWORDS,1,FALSE)),"C/PalabrasClaves","S/PalabrasClaves")),"") -> S/PalabrasClaves | N61: =IF(ISNUMBER(SEARCH("TREATMENT", B61)), "4) Nuevos tratamientos", "") | P61: 2020 Jan 15 | R61: =LEFT('2012-2022'!$P61,4) -> 2020 | S61: Jan | T61: =IFERROR(VLOOKUP(A61,BD_aux,2,FALSE),"")
A62: 33590810 | B62: Computational identification of potential lead molecules targeting rho receptor of Neisseria gonorrhoeae | C62: Rajamanikandan S, Soundarya S, Paramasivam A, Prabhu D, Jeyakanthan J, Ramasamy V. | D62: J Biomol Struct Dyn. 2022 Sep;40(14):6415-6425. doi: 10.1080/07391102.2021.1885491. Epub 2021 Feb 16. | E62: Rajamanikandan S | F62: J Biomol Struct Dyn | G62: 2022 | H62: 44243 | K62: 10.1080/07391102.2021.1885491 | L62: =IF(ISNUMBER(VLOOKUP(A62,EXCL,1,FALSE)),"Excluido",IF(ISNUMBER(VLOOKUP(A62,POST,1,FALSE)),"PostAlerta",IF(ISNUMBER(VLOOKUP(A62,PRE,1,FALSE)),"PreAlerta",""))) -> PostAlerta | M62: =IF(ISNUMBER(A62),(IF(ISNUMBER(VLOOKUP(A62,KEYWORDS,1,FALSE)),"C/PalabrasClaves","S/PalabrasClaves")),"") -> S/PalabrasClaves | N62: =IF(ISNUMBER(SEARCH("TREATMENT", B62)), "4) Nuevos tratamientos", "") | P62: 2022 Sep | R62: =LEFT('2012-2022'!$P62,4) -> 2022 | S62: Sep | T62: =IFERROR(VLOOKUP(A62,BD_aux,2,FALSE),"")
A63: 31658968 | B63: A Loop-Mediated Isothermal Amplification Assay Targeting Neisseria gonorrhoeae penA-60.001 | C63: Shimuta K, Nakayama SI, Takahashi H, Ohnishi M. | D63: Antimicrob Agents Chemother. 2019 Dec 20;64(1):e01663-19. doi: 10.1128/AAC.01663-19. Print 2019 Dec 20. | E63: Shimuta K | F63: Antimicrob Agents Chemother | G63: 2019 | H63: 43768 | I63: PMC7187580 | K63: 10.1128/AAC.01663-19 | L63: =IF(ISNUMBER(VLOOKUP(A63,EXCL,1,FALSE)),"Excluido",IF(ISNUMBER(VLOOKUP(A63,POST,1,FALSE)),"PostAlerta",IF(ISNUMBER(VLOOKUP(A63,PRE,1,FALSE)),"PreAlerta",""))) -> PostAlerta | M63: =IF(ISNUMBER(A63),(IF(ISNUMBER(VLOOKUP(A63,KEYWORDS,1,FALSE)),"C/PalabrasClaves","S/PalabrasClaves")),"") -> C/PalabrasClaves | N63: =IF(ISNUMBER(SEARCH("TREATMENT", B63)), "4) Nuevos tratamientos", "") | P63: 2019 Dec 20 | R63: =LEFT('2012-2022'!$P63,4) -> 2019 | S63: Dec | T63: =IFERROR(VLOOKUP(A63,BD_aux,2,FALSE),"")
A64: 31289181 | B64: Glycointeractome of Neisseria gonorrhoeae: Identification of Host Glycans Targeted by the Gonococcus To Facilitate Adherence to Cervical and Urethral Epithelial Cells | C64: Semchenko EA, Everest-Dass AV, Jen FE, Mubaiwa TD, Day CJ, Seib KL. | D64: mBio. 2019 Jul 9;10(4):e01339-19. doi: 10.1128/mBio.01339-19. | E64: Semchenko EA | F64: mBio | G64: 2019 | H64: 43657 | I64: PMC6747729 | K64: 10.1128/mBio.01339-19 | L64: =IF(ISNUMBER(VLOOKUP(A64,EXCL,1,FALSE)),"Excluido",IF(ISNUMBER(VLOOKUP(A64,POST,1,FALSE)),"PostAlerta",IF(ISNUMBER(VLOOKUP(A64,PRE,1,FALSE)),"PreAlerta",""))) -> PostAlerta | M64: =IF(ISNUMBER(A64),(IF(ISNUMBER(VLOOKUP(A64,KEYWORDS,1,FALSE)),"C/PalabrasClaves","S/PalabrasClaves")),"") -> S/PalabrasClaves | N64: =IF(ISNUMBER(SEARCH("TREATMENT", B64)), "4) Nuevos tratamientos", "") | P64: 2019 Jul 9 | R64: =LEFT('2012-2022'!$P64,4) -> 2019 | S64: Jul | T64: =IFERROR(VLOOKUP(A64,BD_aux,2,FALSE),"")
A65: 29698633 | B65: Neisseria gonorrhoeae molecular typing for understanding sexual networks and antimicrobial resistance transmission: A systematic review | C65: Town K, Bolt H, Croxford S, Cole M, Harris S, Field N, Hughes G. | D65: J Infect. 2018 Jun;76(6):507-514. doi: 10.1016/j.jinf.2018.02.011. Epub 2018 Apr 24. | E65: Town K | F65: J Infect | G65: 2018 | H65: 43217 | I65: PMC5999358 | K65: 10.1016/j.jinf.2018.02.011 | L65: =IF(ISNUMBER(VLOOKUP(A65,EXCL,1,FALSE)),"Excluido",IF(ISNUMBER(VLOOKUP(A65,POST,1,FALSE)),"PostAlerta",IF(ISNUMBER(VLOOKUP(A65,PRE,1,FALSE)),"PreAlerta",""))) -> Excluido | M65: =IF(ISNUMBER(A65),(IF(ISNUMBER(VLOOKUP(A65,KEYWORDS,1,FALSE)),"C/PalabrasClaves","S/PalabrasClaves")),"") -> C/PalabrasClaves | N65: =IF(ISNUMBER(SEARCH("TREATMENT", B65)), "4) Nuevos tratamientos", "") | P65: 2018 Jun | R65: =LEFT('2012-2022'!$P65,4) -> 2018 | S65: Jun | T65: =IFERROR(VLOOKUP(A65,BD_aux,2,FALSE),"")
A66: 27608066 | B66: Neisseria gonorrhoeae isolated from an unexpected site | C66: Pendle S, Barnes T. | D66: Sex Health. 2016 Nov;13(6):593-594. doi: 10.1071/SH16124. | E66: Pendle S | F66: Sex Health | G66: 2016 | H66: 42622 | K66: 10.1071/SH16124 | L66: =IF(ISNUMBER(VLOOKUP(A66,EXCL,1,FALSE)),"Excluido",IF(ISNUMBER(VLOOKUP(A66,POST,1,FALSE)),"PostAlerta",IF(ISNUMBER(VLOOKUP(A66,PRE,1,FALSE)),"PreAlerta",""))) -> PreAlerta | M66: =IF(ISNUMBER(A66),(IF(ISNUMBER(VLOOKUP(A66,KEYWORDS,1,FALSE)),"C/PalabrasClaves","S/PalabrasClaves")),"") -> S/PalabrasClaves | N66: =IF(ISNUMBER(SEARCH("TREATMENT", B66)), "4) Nuevos tratamientos", "") | P66: 2016 Nov | R66: =LEFT('2012-2022'!$P66,4) -> 2016 | S66: Nov | T66: =IFERROR(VLOOKUP(A66,BD_aux,2,FALSE),"")
A67: 30858209 | B67: First Case of Ceftriaxone-Resistant Multidrug-Resistant Neisseria gonorrhoeae in Singapore | C67: Ko KKK, Chio MTW, Goh SS, Tan AL, Koh TH, Abdul Rahman NB. | D67: Antimicrob Agents Chemother. 2019 Apr 25;63(5):e02624-18. doi: 10.1128/AAC.02624-18. Print 2019 May. | E67: Ko KKK | F67: Antimicrob Agents Chemother | G67: 2019 | H67: 43537 | I67: PMC6496044 | K67: 10.1128/AAC.02624-18 | L67: =IF(ISNUMBER(VLOOKUP(A67,EXCL,1,FALSE)),"Excluido",IF(ISNUMBER(VLOOKUP(A67,POST,1,FALSE)),"PostAlerta",IF(ISNUMBER(VLOOKUP(A67,PRE,1,FALSE)),"PreAlerta",""))) -> PostAlerta | M67: =IF(ISNUMBER(A67),(IF(ISNUMBER(VLOOKUP(A67,KEYWORDS,1,FALSE)),"C/PalabrasClaves","S/PalabrasClaves")),"") -> C/PalabrasClaves | N67: 1) Reporte de cepas resistentes | P67: 2019 Apr 25 | R67: =LEFT('2012-2022'!$P67,4) -> 2019 | S67: Apr | T67: - | U67: No | V67: No | W67: No | X67: Not available | Y67: =IFERROR(VLOOKUP(A65,BD_aux,3,FALSE),"")
A68: 30552033 | B68: In vitro activity of EDTA and TOL-463 against Neisseria gonorrhoeae | C68: Nash EE, Henning TC, Pham CD, Pettus K, Sharpe S, Kersh EN. | D68: Diagn Microbiol Infect Dis. 2019 Apr;93(4):369-371. doi: 10.1016/j.diagmicrobio.2018.10.021. Epub 2018 Nov 10. | E68: Nash EE | F68: Diagn Microbiol Infect Dis | G68: 2019 | H68: 43450 | I68: PMC6519449 | J68: NIHMS1028006 | K68: 10.1016/j.diagmicrobio.2018.10.021 | L68: =IF(ISNUMBER(VLOOKUP(A68,EXCL,1,FALSE)),"Excluido",IF(ISNUMBER(VLOOKUP(A68,POST,1,FALSE)),"PostAlerta",IF(ISNUMBER(VLOOKUP(A68,PRE,1,FALSE)),"PreAlerta",""))) -> PostAlerta | M68: =IF(ISNUMBER(A68),(IF(ISNUMBER(VLOOKUP(A68,KEYWORDS,1,FALSE)),"C/PalabrasClaves","S/PalabrasClaves")),"") -> C/PalabrasClaves | N68: 2) Nuevos tratamientos | O68: 2c) Droga de diseño | P68: 2019 Apr | R68: =LEFT('2012-2022'!$P68,4) -> 2019 | S68: Apr | T68: Neisseria gonorrhoeae quickly develops drug resistance. Time-kill curves revealed that EDTA and TOL-463 inhibit growth similar to penicillin, ciprofloxacin, and azithromycin. Furthermore, synergistic and additive antimicrobial interactions occurred when EDTA and TOL-463 were combined with penicillin or azithromycin, respectively, suggesting that further investigations into these unconventional antimicrobials may be advantageous. | U68: No | V68: Yes | W68: No | X68: This study suggests EDTA and TOL-463 show antimicrobial activity and synergy with current drugs, supporting exploration of new therapies. | Y68: =IFERROR(VLOOKUP(A66,BD_aux,3,FALSE),"")
A69: 32163577 | B69: Association of Neisseria gonorrhoeae Plasmids With Distinct Lineages and The Economic Status of Their Country of Origin | C69: Cehovin A, Jolley KA, Maiden MCJ, Harrison OB, Tang CM. | D69: J Infect Dis. 2020 Nov 9;222(11):1826-1836. doi: 10.1093/infdis/jiaa003. | E69: Cehovin A | F69: J Infect Dis | G69: 2020 | H69: 43903 | I69: PMC7653084 | K69: 10.1093/infdis/jiaa003 | L69: =IF(ISNUMBER(VLOOKUP(A69,EXCL,1,FALSE)),"Excluido",IF(ISNUMBER(VLOOKUP(A69,POST,1,FALSE)),"PostAlerta",IF(ISNUMBER(VLOOKUP(A69,PRE,1,FALSE)),"PreAlerta",""))) -> PostAlerta | M69: =IF(ISNUMBER(A69),(IF(ISNUMBER(VLOOKUP(A69,KEYWORDS,1,FALSE)),"C/PalabrasClaves","S/PalabrasClaves")),"") -> C/PalabrasClaves | N69: =IF(ISNUMBER(SEARCH("TREATMENT", B69)), "4) Nuevos tratamientos", "") | P69: 2020 Nov 9 | R69: =LEFT('2012-2022'!$P69,4) -> 2020 | S69: Nov | T69: =IFERROR(VLOOKUP(A69,BD_aux,2,FALSE),"")
A70: 29581189 | B70: Identification and Characterization of the Neisseria gonorrhoeae MscS-Like Mechanosensitive Channel | C70: Wang Z, Wang X, Lu P, Ni C, Li Y, van der Veen S. | D70: Infect Immun. 2018 May 22;86(6):e00090-18. doi: 10.1128/IAI.00090-18. Print 2018 Jun. | E70: Wang Z | F70: Infect Immun | G70: 2018 | H70: 43187 | I70: PMC5964504 | K70: 10.1128/IAI.00090-18 | L70: =IF(ISNUMBER(VLOOKUP(A70,EXCL,1,FALSE)),"Excluido",IF(ISNUMBER(VLOOKUP(A70,POST,1,FALSE)),"PostAlerta",IF(ISNUMBER(VLOOKUP(A70,PRE,1,FALSE)),"PreAlerta",""))) -> PostAlerta | M70: =IF(ISNUMBER(A70),(IF(ISNUMBER(VLOOKUP(A70,KEYWORDS,1,FALSE)),"C/PalabrasClaves","S/PalabrasClaves")),"") -> C/PalabrasClaves | N70: =IF(ISNUMBER(SEARCH("TREATMENT", B70)), "4) Nuevos tratamientos", "") | P70: 2018 May 22 | R70: =LEFT('2012-2022'!$P70,4) -> 2018 | S70: May | T70: =IFERROR(VLOOKUP(A70,BD_aux,2,FALSE),"")
A71: 31225605 | B71: Detection of tet(M) in high-level tetracycline-resistant Neisseria gonorrhoeae | C71: Pitt R, Sadouki Z, Town K, Fifer H, Mohammed H, Hughes G, Woodford N, Cole MJ. | D71: J Antimicrob Chemother. 2019 Jul 1;74(7):2115-2116. doi: 10.1093/jac/dkz130. | E71: Pitt R | F71: J Antimicrob Chemother | G71: 2019 | H71: 43638 | K71: 10.1093/jac/dkz130 | L71: =IF(ISNUMBER(VLOOKUP(A71,EXCL,1,FALSE)),"Excluido",IF(ISNUMBER(VLOOKUP(A71,POST,1,FALSE)),"PostAlerta",IF(ISNUMBER(VLOOKUP(A71,PRE,1,FALSE)),"PreAlerta",""))) -> PostAlerta | M71: =IF(ISNUMBER(A71),(IF(ISNUMBER(VLOOKUP(A71,KEYWORDS,1,FALSE)),"C/PalabrasClaves","S/PalabrasClaves")),"") -> C/PalabrasClaves | N71: =IF(ISNUMBER(SEARCH("TREATMENT", B71)), "4) Nuevos tratamientos", "") | P71: 2019 Jul 1 | R71: =LEFT('2012-2022'!$P71,4) -> 2019 | S71: Jul | T71: =IFERROR(VLOOKUP(A71,BD_aux,2,FALSE),"")
A72: 31340021 | B72: Improved determination of Neisseria gonorrhoeae gyrase A genotype results in clinical specimens | C72: Allan-Blitz LT, Ellis OL, Wee R, Truong A, Ebeyan SM, Tan LY, Mokany E, Flynn R, Klausner JD. | D72: J Antimicrob Chemother. 2019 Oct 1;74(10):2913-2915. doi: 10.1093/jac/dkz292. | E72: Allan-Blitz LT | F72: J Antimicrob Chemother | G72: 2019 | H72: 43671 | I72: PMC8420954 | K72: 10.1093/jac/dkz292 | L72: =IF(ISNUMBER(VLOOKUP(A72,EXCL,1,FALSE)),"Excluido",IF(ISNUMBER(VLOOKUP(A72,POST,1,FALSE)),"PostAlerta",IF(ISNUMBER(VLOOKUP(A72,PRE,1,FALSE)),"PreAlerta",""))) -> PostAlerta | M72: =IF(ISNUMBER(A72),(IF(ISNUMBER(VLOOKUP(A72,KEYWORDS,1,FALSE)),"C/PalabrasClaves","S/PalabrasClaves")),"") -> C/PalabrasClaves | N72: =IF(ISNUMBER(SEARCH("TREATMENT", B72)), "4) Nuevos tratamientos", "") | P72: 2019 Oct 1 | R72: =LEFT('2012-2022'!$P72,4) -> 2019 | S72: Oct | T72: =IFERROR(VLOOKUP(A72,BD_aux,2,FALSE),"")
A73: 31119626 | B73: Phenotypic MicroArray Screening of Neisseria gonorrhoeae in Chemically Defined Liquid Medium | C73: Baarda BI, Sikora AE. | D73: Methods Mol Biol. 2019;1997:207-216. doi: 10.1007/978-1-4939-9496-0_13. | E73: Baarda BI | F73: Methods Mol Biol | G73: 2019 | H73: 43609 | K73: 10.1007/978-1-4939-9496-0_13 | L73: =IF(ISNUMBER(VLOOKUP(A73,EXCL,1,FALSE)),"Excluido",IF(ISNUMBER(VLOOKUP(A73,POST,1,FALSE)),"PostAlerta",IF(ISNUMBER(VLOOKUP(A73,PRE,1,FALSE)),"PreAlerta",""))) -> PostAlerta | M73: =IF(ISNUMBER(A73),(IF(ISNUMBER(VLOOKUP(A73,KEYWORDS,1,FALSE)),"C/PalabrasClaves","S/PalabrasClaves")),"") -> S/PalabrasClaves | N73: =IF(ISNUMBER(SEARCH("TREATMENT", B73)), "4) Nuevos tratamientos", "") | P73: 2019 | R73: =LEFT('2012-2022'!$P73,4) -> 2019 | T73: =IFERROR(VLOOKUP(A73,BD_aux,2,FALSE),"")
A74: 33784401 | B74: Structures of Neisseria gonorrhoeae MtrR-operator complexes reveal molecular mechanisms of DNA recognition and antibiotic resistance-conferring clinical mutations | C74: Beggs GA, Ayala JC, Kavanaugh LG, Read TD, Hooks GM, Schumacher MA, Shafer WM, Brennan RG. | D74: Nucleic Acids Res. 2021 Apr 19;49(7):4155-4170. doi: 10.1093/nar/gkab213. | E74: Beggs GA | F74: Nucleic Acids Res | G74: 2021 | H74: 44285 | I74: PMC8053128 | K74: 10.1093/nar/gkab213 | L74: =IF(ISNUMBER(VLOOKUP(A74,EXCL,1,FALSE)),"Excluido",IF(ISNUMBER(VLOOKUP(A74,POST,1,FALSE)),"PostAlerta",IF(ISNUMBER(VLOOKUP(A74,PRE,1,FALSE)),"PreAlerta",""))) -> PostAlerta | M74: =IF(ISNUMBER(A74),(IF(ISNUMBER(VLOOKUP(A74,KEYWORDS,1,FALSE)),"C/PalabrasClaves","S/PalabrasClaves")),"") -> C/PalabrasClaves | N74: =IF(ISNUMBER(SEARCH("TREATMENT", B74)), "4) Nuevos tratamientos", "") | P74: 2021 Apr 19 | R74: =LEFT('2012-2022'!$P74,4) -> 2021 | S74: Apr | T74: =IFERROR(VLOOKUP(A74,BD_aux,2,FALSE),"")
A75: 29553335 | B75: Cooperative Recognition of Internationally Disseminated Ceftriaxone-Resistant Neisseria gonorrhoeae Strain | C75: Lahra MM, Martin I, Demczuk W, Jennison AV, Lee KI, Nakayama SI, Lefebvre B, Longtin J, Ward A, Mulvey MR, Wi T, Ohnishi M, Whiley D. | D75: Emerg Infect Dis. 2018 Apr;24(4):735-40. doi: 10.3201/eid2404.171873. | E75: Lahra MM | F75: Emerg Infect Dis | G75: 2018 | H75: 43179 | I75: PMC5875269 | K75: 10.3201/eid2404.171873 | L75: =IF(ISNUMBER(VLOOKUP(A75,EXCL,1,FALSE)),"Excluido",IF(ISNUMBER(VLOOKUP(A75,POST,1,FALSE)),"PostAlerta",IF(ISNUMBER(VLOOKUP(A75,PRE,1,FALSE)),"PreAlerta",""))) -> PostAlerta | M75: =IF(ISNUMBER(A75),(IF(ISNUMBER(VLOOKUP(A75,KEYWORDS,1,FALSE)),"C/PalabrasClaves","S/PalabrasClaves")),"") -> C/PalabrasClaves | N75: 1) Reporte de cepas resistentes | P75: 2018 Apr | R75: =LEFT('2012-2022'!$P75,4) -> 2018 | S75: Apr | T75: Ceftriaxone remains a first-line treatment for patients infected by Neisseria gonorrhoeae in most settings. We investigated the possible spread of a ceftriaxone-resistant FC428 N. gonorrhoeae clone in Japan after recent isolation of similar strains in Denmark (GK124) and Canada (47707). We report 2 instances of the FC428 clone in Australia in heterosexual men traveling from Asia. Our bioinformatic analyses included core single-nucleotide variation phylogeny and in silico molecular typing; phylogenetic analysis showed close genetic relatedness among all 5 isolates. Results showed multilocus sequence type 1903; N. gonorrhoeae sequence typing for antimicrobial resistance (NG-STAR) 233; and harboring of mosaic penA allele encoding alterations A311V and T483S (penA-60.001), associated with ceftriaxone resistance. Our results provide further evidence of international transmission of ceftriaxone-resistant N. gonorrhoeae. We recommend increasing awareness of international spread of this drug-resistant strain, strengthening surveillance to include identifying treatment failures and contacts, and strengthening international sharing of data. | U75: Yes | V75: No | W75: No | X75: This report highlights international spread of ceftriaxone-resistant N. gonorrhoeae FC428 clone, emphasizing need for global surveillance. | Y75: =IFERROR(VLOOKUP(A73,BD_aux,3,FALSE),"")
A76: 29924264 | B76: [Antimicrobial resistance of Neisseria gonorrhoeae in Peru] | C76: Jorge-Berrocal A, Mayta-Barrios M, Fiestas-Solórzano V. | D76: Rev Peru Med Exp Salud Publica. 2018 Jan-Mar;35(1):155-156. doi: 10.17843/rpmesp.2018.351.3552. | E76: Jorge-Berrocal A | F76: Rev Peru Med Exp Salud Publica | G76: 2018 | H76: 43272 | K76: 10.17843/rpmesp.2018.351.3552 | L76: =IF(ISNUMBER(VLOOKUP(A76,EXCL,1,FALSE)),"Excluido",IF(ISNUMBER(VLOOKUP(A76,POST,1,FALSE)),"PostAlerta",IF(ISNUMBER(VLOOKUP(A76,PRE,1,FALSE)),"PreAlerta",""))) -> PostAlerta | M76: =IF(ISNUMBER(A76),(IF(ISNUMBER(VLOOKUP(A76,KEYWORDS,1,FALSE)),"C/PalabrasClaves","S/PalabrasClaves")),"") -> C/PalabrasClaves | N76: 1) Reporte de cepas resistentes | P76: 2018 Jan-Mar | R76: =LEFT('2012-2022'!$P76,4) -> 2018 | S76: Jan | T76: Gonorrhea is a sexually transmitted infection (STI) caused by Neisseria gonorrhoeae. It manifests as urethritis in men and mucopurulent cervicitis in women, with complications including pelvic inflammatory disease, ectopic pregnancy, infertility, increased HIV transmission, and gonococcal conjunctivitis, which may lead to blindness in newborns. An estimated 78 million new cases of gonococcal infection occurred worldwide among people aged 15 to 49 years in 2012. According to data from the World Health Organization’s Global Gonococcal Antimicrobial Surveillance Programme (WHO GASP) between 2009 and 2014, widespread resistance to antimicrobials such as penicillin, tetracycline, and ciprofloxacin has been documented, along with increasing resistance to azithromycin and emerging resistance to extended-spectrum cephalosporins. In Peru, a resistance evaluation report of strains isolated from various regions during 1998–1999 showed 100% sensitivity to antimicrobials such as ciprofloxacin, spectinomycin, ceftriaxone, and cefotaxime. Later, an analysis of strains isolated from STI-risk populations between 2010 and 2013 revealed 23% resistance to ciprofloxacin. As part of the sentinel surveillance for Neisseria gonorrhoeae implemented in 12 health facilities across seven Peruvian regions (Lima, Callao, Ancash, Ayacucho, Madre de Dios, Loreto, and Ucayali), isolates were sent to the National Institute of Health (Lima, Peru) for biochemical identification using carbohydrate tests on cystine tryptic agar or API®NH, and for antimicrobial susceptibility testing through agar dilution minimum inhibitory concentration (MIC), following Clinical Laboratory Standards Institute (CLSI) guidelines. We analyzed 96 strains from October 2016 to November 2017 and found resistance proportions per antimicrobial: ciprofloxacin 82.3%, tetracycline 54.2%, penicillin 51%, azithromycin 15.6%, and, for the first time, four strains with decreased sensitivity to ceftriaxone (4.2%) reported through the National Focal Point (Table 1). The most frequent resistance phenotypes were: CMTR/QRNG 15.6% (chromosomal resistance to tetracycline/ciprofloxacin), CMRNG/QRNG 12.5% (chromosomal resistance to penicillin and tetracycline/ciprofloxacin), CMPR/QRNG 11.5% (chromosomal resistance to penicillin/ciprofloxacin), and QRNG only 10.4% (ciprofloxacin resistance). Thus, high levels of resistance to ciprofloxacin (82.3%) are reported in Peru for the first time, confirming WHO GASP’s findings. This evidence should support the revision of the current national treatment guideline for gonorrhea. On the other hand, although an increase in azithromycin resistance (15.6%) and, for the first time, decreased sensitivity to ceftriaxone (4.2%) were observed, the dual therapy with ceftriaxone and azithromycin (as recommended by WHO) would remain the most effective. However, it is necessary to continue monitoring gonococcal resistance at the national level to identify strains with reduced susceptibility to extended-spectrum cephalosporins (currently the only available antibiotic class). Detection of such strains must be reported to the National Focal Point under the International Health Regulations. Therefore, the national surveillance system should be strengthened (especially in cases of treatment failure), as well as laboratory capacity through quality assurance and molecular studies to determine the corresponding resistance mechanisms. | U76: Yes | V76: No | W76: No | X76: High ciprofloxacin resistance (82.3%), increased azithromycin resistance (15.6%) and first ceftriaxone reduced susceptibility (4.2%) reported in Peru. | Y76: =IFERROR(VLOOKUP(A74,BD_aux,3,FALSE),"")
A77: 28540875 | B77: A study on various Neisseria gonorrhoeae phenotypes circulating in Tripura | C77: Mullick JB, Majumdar T, Bir R, Hore S, Sil SK. | D77: Indian J Dermatol Venereol Leprol. 2017 Jul-Aug;83(4):499-501. doi: 10.4103/ijdvl.IJDVL_607_16. | E77: Mullick JB | F77: Indian J Dermatol Venereol Leprol | G77: 2017 | H77: 42881 | K77: 10.4103/ijdvl.IJDVL_607_16 | L77: =IF(ISNUMBER(VLOOKUP(A77,EXCL,1,FALSE)),"Excluido",IF(ISNUMBER(VLOOKUP(A77,POST,1,FALSE)),"PostAlerta",IF(ISNUMBER(VLOOKUP(A77,PRE,1,FALSE)),"PreAlerta",""))) -> PostAlerta | M77: =IF(ISNUMBER(A77),(IF(ISNUMBER(VLOOKUP(A77,KEYWORDS,1,FALSE)),"C/PalabrasClaves","S/PalabrasClaves")),"") -> S/PalabrasClaves | N77: =IF(ISNUMBER(SEARCH("TREATMENT", B77)), "4) Nuevos tratamientos", "") | P77: 2017 Jul-Aug | R77: =LEFT('2012-2022'!$P77,4) -> 2017 | S77: Jul | T77: =IFERROR(VLOOKUP(A77,BD_aux,2,FALSE),"")
A78: 29976521 | B78: Genetic characterisation of Neisseria gonorrhoeae resistant to both ceftriaxone and azithromycin | C78: Whiley DM, Jennison A, Pearson J, Lahra MM. | D78: Lancet Infect Dis. 2018 Jul;18(7):717-718. doi: 10.1016/S1473-3099(18)30340-2. | E78: Whiley DM | F78: Lancet Infect Dis | G78: 2018 | H78: 43288 | K78: 10.1016/S1473-3099(18)30340-2 | L78: =IF(ISNUMBER(VLOOKUP(A78,EXCL,1,FALSE)),"Excluido",IF(ISNUMBER(VLOOKUP(A78,POST,1,FALSE)),"PostAlerta",IF(ISNUMBER(VLOOKUP(A78,PRE,1,FALSE)),"PreAlerta",""))) -> PostAlerta | M78: =IF(ISNUMBER(A78),(IF(ISNUMBER(VLOOKUP(A78,KEYWORDS,1,FALSE)),"C/PalabrasClaves","S/PalabrasClaves")),"") -> C/PalabrasClaves | N78: 4) otros | O78: Caracterización | P78: 2018 Jul | R78: =LEFT('2012-2022'!$P78,4) -> 2018 | S78: Jul | T78: =IFERROR(VLOOKUP(A78,BD_aux,2,FALSE),"")
A79: 30047666 | B79: Neisseria gonorrhoeae susceptibility to ciprofloxacin | C79: Allan-Blitz LT, Klausne JD. | D79: MLO Med Lab Obs. 2016 Dec;48(12):30. | E79: Allan-Blitz LT | F79: MLO Med Lab Obs | G79: 2016 | H79: 43308 | L79: =IF(ISNUMBER(VLOOKUP(A79,EXCL,1,FALSE)),"Excluido",IF(ISNUMBER(VLOOKUP(A79,POST,1,FALSE)),"PostAlerta",IF(ISNUMBER(VLOOKUP(A79,PRE,1,FALSE)),"PreAlerta",""))) -> PreAlerta | M79: =IF(ISNUMBER(A79),(IF(ISNUMBER(VLOOKUP(A79,KEYWORDS,1,FALSE)),"C/PalabrasClaves","S/PalabrasClaves")),"") -> C/PalabrasClaves | N79: 1) Reporte de cepas resistentes | P79: 2016 Dec | R79: =LEFT('2012-2022'!$P79,4) -> 2016 | S79: Dec | T79: - | U79: No | V79: No | W79: No | X79: Not available | Y79: =IFERROR(VLOOKUP(A77,BD_aux,3,FALSE),"")
A80: 27191699 | B80: Neisseria gonorrhoeae Resistant to Ceftriaxone and Cefixime, Argentina | C80: Gianecini R, Oviedo C, Stafforini G, Galarza P. | D80: Emerg Infect Dis. 2016 Jun;22(6):1139-41. doi: 10.3201/eid2206.152091. | E80: Gianecini R | F80: Emerg Infect Dis | G80: 2016 | H80: 42509 | I80: PMC4880066 | K80: 10.3201/eid2206.152091 | L80: =IF(ISNUMBER(VLOOKUP(A80,EXCL,1,FALSE)),"Excluido",IF(ISNUMBER(VLOOKUP(A80,POST,1,FALSE)),"PostAlerta",IF(ISNUMBER(VLOOKUP(A80,PRE,1,FALSE)),"PreAlerta",""))) -> PreAlerta | M80: =IF(ISNUMBER(A80),(IF(ISNUMBER(VLOOKUP(A80,KEYWORDS,1,FALSE)),"C/PalabrasClaves","S/PalabrasClaves")),"") -> C/PalabrasClaves | N80: 1) Reporte de cepas resistentes | P80: 2016 Jun | R80: =LEFT('2012-2022'!$P80,4) -> 2016 | S80: Jun | T80: Antimicrobial resistance in Neisseria gonorrhoeae is increasing worldwide. In recent years, gonococcal strains resistant to extended-spectrum cephalosporin (ESC) ceftriaxone have been reported in many countries (1). In South America, seven ceftriaxone-resistant strains (MIC >0.25 μg/mL) were reported in Brazil in 2007; however, these isolates were not characterized (2). The emergence of cefalosporin-resistant gonorrhea would significantly limit treatment options and pose a major public health issue. We report an isolation of N. gonorrhoeae in Argentina that was resistant to both ceftriaxone and cefixime. In September 2014, a 19-year-old heterosexual male without underlying disease presented to the emergency department of a hospital in Río Negro, Argentina. Physical examination showed purulent urethral discharge. He reported having engaged in unprotected vaginal insertive intercourse with multiple partners in the past few months. The patient denied recent travel outside of Argentina. He had a history of gonococcal urethritis (March 2014), treated with a single dose (500 mg) of ceftriaxone; however, a gonococcal isolate obtained at that time was not sent to a reference laboratory as part of the Argentine Gonococcal Antimicrobial Sensitivity Surveillance Program for antimicrobial susceptibility profiling. Upon admission, we obtained and cultured a urethral swab sample and identified the isolate as N. gonorrhoeae by conventional methods (3). The isolate was sent to a reference laboratory, and its identity was confirmed by the Phadebact GC monoclonal test (MKL Diagnostic AB, Sollentuna, Sweden) and time-of-flight mass spectrometry with matrix-assisted laser desorption/ionization (Bruker Daltonik GmbH, Bremen, Germany). The patient received a single dose (500 mg) of ceftriaxone. Five days later, the patient returned for a clinical evaluation, and symptoms had resolved. No cure test culture was performed. Minimum inhibitory concentrations (MICs) were determined for penicillin, cefixime, ceftriaxone, tetracycline, ciprofloxacin, and azithromycin by the agar dilution method according to the Clinical Laboratory Standards Institute (CLSI) guidelines (4). Results were interpreted based on these guidelines, except for azithromycin, where the European Committee on Antimicrobial Susceptibility Testing (http://www.eucast.org/) cut-offs were applied. This isolate was resistant to ceftriaxone and cefixime (MIC 0.5 μg/mL), penicillin (8 μg/mL), tetracycline (8 μg/mL), and azithromycin (1 μg/mL). However, the isolate was susceptible to ciprofloxacin (0.03 μg/mL). The β-lactamase test by nitrocefin chromogenic disk assay (Becton Dickinson, Franklin Lakes, NJ, USA) was negative. Resistance determinants involved in ceftriaxone resistance were amplified by PCR and sequenced as described (5, 6). We then analyzed the complete sequences of the penA and pilQ genes, along with other genetic determinants such as the mtrR, penB, and ponA genes. PCR products were purified and sequenced with an ABI 3500 genetic analyzer (Applied Biosystems, Foster City, CA, USA), and epidemiological molecular characterization was carried out using multi-antigen sequence typing of N. gonorrhoeae (http://www.ng-mast.net). The analysis of the penA gene sequence, which encodes penicillin-binding protein 2 (PBP2), identified a non-mosaic PBP2 IX allele. The analysis of the mtrR gene and its promoter identified a single nucleotide deletion (A) in the inverted repeat of the promoter region and a single amino acid substitution at position H105 (H→Y). Amino acid substitutions were found in the porB1b gene at positions G120 (G→K) and A121 (A→D). The ponA gene, which encodes PBP1, exhibited an amino acid substitution at position L421 (L→P), and the complete amino acid sequence of PilQ showed sequence type VI. The isolate was assigned to the PorB1b serogroup (WII/III), and multi-antigen sequence typing of N. gonorrhoeae showed a new sequence type ST13064 (porB -7592 and tbpB -33). Mosaic PBP2 alleles have been strongly associated with reduced susceptibility or resistance to ESCs (7). However, the isolate we obtained had a non-mosaic PBP IX allele, which contains the P551L substitution that has been associated with higher MICs for ESCs (8). The association of the non-mosaic PBP IX allele, most likely with mutations in the mtrR, penB, and ponA genes, could be involved in resistance to ESCs (9). Although Whiley et al. (6) did not report an association between sequence type VI and ESC resistance, the contribution of this sequence type to ESC resistance requires further studies. In Argentina, isolates with reduced susceptibility and resistance to ESCs have emerged (10), increasing from 1.1% in 2011 to 5.6% in 2014 (Argentine Gonococcal Antimicrobial Sensitivity Surveillance Program, unpublished data). Treatment failures and isolates with reduced susceptibility and resistance to ESCs have been reported (9). However, syndromic management of gonorrhea in Argentina has resulted in suboptimal diagnosis and a lack of samples for culture to distinguish between treatment failure and reinfection. Syndromic management represents a significant problem, not only compromising the surveillance program but also increasing selective pressure and facilitating the development of antimicrobial resistance. Consequently, surveillance should be strengthened to support the detection and verification of asymptomatic infections and treatment failures, identify high-risk communities, and trace sexual contacts. These efforts should be used in public health responses to mitigate the emergence and spread of ESC-resistant gonococci. | U80: Yes | V80: No | W80: No | X80: Resistance to ceftriaxone (ESC) linked to non-mosaic PBP2 allele and genetic mutations in Argentin | Y80: =IFERROR(VLOOKUP(A78,BD_aux,3,FALSE),"")
A81: 25253760 | B81: Ceftriaxone-resistant Neisseria gonorrhoeae, Puerto Rico | C81: Scharbaai-Vázquez R, González-Caraballo AL, Torres-Bauzá LJ. | D81: Sex Transm Infect. 2015 Mar;91(2):99. doi: 10.1136/sextrans-2014-051716. Epub 2014 Sep 24. | E81: Scharbaai-Vázquez R | F81: Sex Transm Infect | G81: 2015 | H81: 41908 | K81: 10.1136/sextrans-2014-051716 | L81: This review highlights the global threat of antimicrobial-resistant Neisseria gonorrhoeae. | M81: =IF(ISNUMBER(A81),(IF(ISNUMBER(VLOOKUP(A81,KEYWORDS,1,FALSE)),"C/PalabrasClaves","S/PalabrasClaves")),"") -> C/PalabrasClaves | N81: 1) Reporte de cepas resistentes | P81: 2015 Mar | R81: =LEFT('2012-2022'!$P81,4) -> 2015 | S81: Mar | T81: Emergence and spread of multidrug-resistant Neisseria gonorrhoeae is a global threat. The aetiological agent of gonorrhoea has developed resistance to first-line treatments, such as sulfanilamides, penicillins, tetracyclines, macrolides, and fluoroquinolones1 The extended-spectrum cephalosporins are now the only antibiotics recommended for treatment of gonorrhoea in the USA and many countries.2 ,3 Unfortunately, susceptibility to these antimicrobials has also decreased.4–7 This trend has made the Centers for Disease Control (CDC) to recently classify N. gonorrhoeae as an urgent public health threat.8 | U81: Yes | V81: No | W81: No | X81: Not available | Y81: =IFERROR(VLOOKUP(A79,BD_aux,3,FALSE),"")
A82: 33367585 | B82: Multiplex PCR and Nanopore Sequencing of Genes Associated with Antimicrobial Resistance in Neisseria gonorrhoeae Directly from Clinical Samples | C82: Zhang C, Xiu L, Li Y, Sun L, Li Y, Zeng Y, Wang F, Peng J. | D82: Clin Chem. 2021 Mar 31;67(4):610-620. doi: 10.1093/clinchem/hvaa306. | E82: Zhang C | F82: Clin Chem | G82: 2021 | H82: 44193 | K82: 10.1093/clinchem/hvaa306 | L82: =IF(ISNUMBER(VLOOKUP(A82,EXCL,1,FALSE)),"Excluido",IF(ISNUMBER(VLOOKUP(A82,POST,1,FALSE)),"PostAlerta",IF(ISNUMBER(VLOOKUP(A82,PRE,1,FALSE)),"PreAlerta",""))) -> PostAlerta | M82: =IF(ISNUMBER(A82),(IF(ISNUMBER(VLOOKUP(A82,KEYWORDS,1,FALSE)),"C/PalabrasClaves","S/PalabrasClaves")),"") -> C/PalabrasClaves | N82: =IF(ISNUMBER(SEARCH("TREATMENT", B82)), "4) Nuevos tratamientos", "") | P82: 2021 Mar 31 | R82: =LEFT('2012-2022'!$P82,4) -> 2021 | S82: Mar | T82: =IFERROR(VLOOKUP(A82,BD_aux,2,FALSE),"")
A83: 27088665 | B83: Technological Solutions to Address Drug-Resistant Neisseria gonorrhoeae | C83: Bristow CC, Dong H, Klausner JD. | D83: Emerg Infect Dis. 2016 May;22(5):939-40. doi: 10.3201/eid2205.160083. | E83: Bristow CC | F83: Emerg Infect Dis | G83: 2016 | H83: 42479 | I83: PMC4861538 | K83: 10.3201/eid2205.160083 | L83: =IF(ISNUMBER(VLOOKUP(A83,EXCL,1,FALSE)),"Excluido",IF(ISNUMBER(VLOOKUP(A83,POST,1,FALSE)),"PostAlerta",IF(ISNUMBER(VLOOKUP(A83,PRE,1,FALSE)),"PreAlerta",""))) -> PreAlerta | M83: =IF(ISNUMBER(A83),(IF(ISNUMBER(VLOOKUP(A83,KEYWORDS,1,FALSE)),"C/PalabrasClaves","S/PalabrasClaves")),"") -> C/PalabrasClaves | N83: =IF(ISNUMBER(SEARCH("TREATMENT", B83)), "4) Nuevos tratamientos", "") | P83: 2016 May | R83: =LEFT('2012-2022'!$P83,4) -> 2016 | S83: May | T83: =IFERROR(VLOOKUP(A83,BD_aux,2,FALSE),"")
A84: 28069643 | B84: In Vitro Activity of Gepotidacin (GSK2140944) against Neisseria gonorrhoeae | C84: Farrell DJ, Sader HS, Rhomberg PR, Scangarella-Oman NE, Flamm RK. | D84: Antimicrob Agents Chemother. 2017 Feb 23;61(3):e02047-16. doi: 10.1128/AAC.02047-16. Print 2017 Mar. | E84: Farrell DJ | F84: Antimicrob Agents Chemother | G84: 2017 | H84: 42746 | I84: PMC5328517 | K84: 10.1128/AAC.02047-16 | L84: =IF(ISNUMBER(VLOOKUP(A84,EXCL,1,FALSE)),"Excluido",IF(ISNUMBER(VLOOKUP(A84,POST,1,FALSE)),"PostAlerta",IF(ISNUMBER(VLOOKUP(A84,PRE,1,FALSE)),"PreAlerta",""))) -> PostAlerta | M84: =IF(ISNUMBER(A84),(IF(ISNUMBER(VLOOKUP(A84,KEYWORDS,1,FALSE)),"C/PalabrasClaves","S/PalabrasClaves")),"") -> C/PalabrasClaves | N84: 2) Nuevos tratamientos | O84: 2c) Droga de diseño | P84: 2017 Feb 23 | R84: =LEFT('2012-2022'!$P84,4) -> 2017 | S84: Feb | T84: Gepotidacin (formerly GSK2140944) is a novel, first-in-class, triazaacenaphthylene antibacterial that inhibits bacterial DNA gyrase and topoisomerase IV via a unique mechanism and has demonstrated in vitro activity against Neisseria gonorrhoeae, including drug-resistant strains, and also targets pathogens associated with other conventional and biothreat infections. Broth microdilution was used to evaluate the MIC and minimum bactericidal concentration (MBC) activity of gepotidacin and comparators against 25 N. gonorrhoeae strains (including five ciprofloxacin-nonsusceptible strains). Gepotidacin activity was also evaluated against three N. gonorrhoeae strains (including a ciprofloxacin-nonsusceptible strain) for resistance development, against three N. gonorrhoeae strains (including two tetracycline- and azithromycin-nonsusceptible strains) using time-kill kinetics and checkerboard methods, and against two N. gonorrhoeae strains for the investigation of postantibiotic (PAE) and subinhibitory (PAE-SME) effects. The MIC50 and MIC90 for gepotidacin against the 25 N. gonorrhoeae isolates tested were 0.12 and 0.25 μg/ml, respectively. The MBC50 and MBC90 for gepotidacin were 0.25 and 0.5 μg/ml, respectively. Gepotidacin was bactericidal, and single-step resistance selection studies did not recover any mutants, indicating a low rate of spontaneous single-step resistance. For combinations of gepotidacin and comparators tested using checkerboard methods, there were no instances where antagonism occurred and only one instance of synergy (with moxifloxacin; fractional inhibitory concentration, 0.375). This was not confirmed by in vitro time-kill studies. The PAE for gepotidacin against the wild-type strain ranged from 0.5 to >2.5 h, and the PAE-SME was >2.5 h. These in vitro data indicate that further study of gepotidacin is warranted for potential use in treating infections caused by N. gonorrhoeae. | U84: No | V84: Yes | W84: No | X84: This study supports gepotidacin as a promising new antimicrobial for treating drug-resistant Neisseria gonorrhoeae infections. | Y84: =IFERROR(VLOOKUP(A82,BD_aux,3,FALSE),"")
A85: 30629964 | B85: Comparison of Neisseria gonorrhoeae minimum inhibitory concentrations obtained using agar dilution versus microbroth dilution methods | C85: Jacobson RK, Notaro MJ, Carr GJ. | D85: J Microbiol Methods. 2019 Feb;157:93-99. doi: 10.1016/j.mimet.2019.01.001. Epub 2019 Jan 7. | E85: Jacobson RK | F85: J Microbiol Methods | G85: 2019 | H85: 43476 | K85: 10.1016/j.mimet.2019.01.001 | L85: =IF(ISNUMBER(VLOOKUP(A85,EXCL,1,FALSE)),"Excluido",IF(ISNUMBER(VLOOKUP(A85,POST,1,FALSE)),"PostAlerta",IF(ISNUMBER(VLOOKUP(A85,PRE,1,FALSE)),"PreAlerta",""))) -> PostAlerta | M85: =IF(ISNUMBER(A85),(IF(ISNUMBER(VLOOKUP(A85,KEYWORDS,1,FALSE)),"C/PalabrasClaves","S/PalabrasClaves")),"") -> C/PalabrasClaves | N85: =IF(ISNUMBER(SEARCH("TREATMENT", B85)), "4) Nuevos tratamientos", "") | P85: 2019 Feb | R85: =LEFT('2012-2022'!$P85,4) -> 2019 | S85: Feb | T85: =IFERROR(VLOOKUP(A85,BD_aux,2,FALSE),"")
A86: 32228159 | B86: Repeat symptomatic Neisseria gonorrhoeae infections among men who have sex with men in Bangkok, Thailand, 2006-2016 | C86: Pattanasin S, Holtz TH, Ungsedhapand C, Tongtoyai J, Chonwattana W, Sukwicha W, Sirivongrangson P, Mock PA, Chitwarakorn A, Dunne EF. | D86: Int J STD AIDS. 2020 May;31(6):533-540. doi: 10.1177/0956462420906763. Epub 2020 Mar 30. | E86: Pattanasin S | F86: Int J STD AIDS | G86: 2020 | H86: 43923 | K86: 10.1177/0956462420906763 | L86: =IF(ISNUMBER(VLOOKUP(A86,EXCL,1,FALSE)),"Excluido",IF(ISNUMBER(VLOOKUP(A86,POST,1,FALSE)),"PostAlerta",IF(ISNUMBER(VLOOKUP(A86,PRE,1,FALSE)),"PreAlerta",""))) -> PostAlerta | M86: =IF(ISNUMBER(A86),(IF(ISNUMBER(VLOOKUP(A86,KEYWORDS,1,FALSE)),"C/PalabrasClaves","S/PalabrasClaves")),"") -> S/PalabrasClaves | N86: =IF(ISNUMBER(SEARCH("TREATMENT", B86)), "4) Nuevos tratamientos", "") | P86: 2020 May | R86: =LEFT('2012-2022'!$P86,4) -> 2020 | S86: May | T86: =IFERROR(VLOOKUP(A86,BD_aux,2,FALSE),"")
A87: 27489119 | B87: Recovery of Neisseria gonorrhoeae from 4 commercially available transport systems | C87: Papp JR, Henning T, Khubbar M, Kalve V, Bhattacharyya S, Travanty E, Xavier K, Jones K, Rudrik JT, Gaynor A, Hagan C. | D87: Diagn Microbiol Infect Dis. 2016 Oct;86(2):144-7. doi: 10.1016/j.diagmicrobio.2016.06.019. Epub 2016 Jun 24. | E87: Papp JR | F87: Diagn Microbiol Infect Dis | G87: 2016 | H87: 42587 | I87: PMC6739837 | J87: NIHMS1049717 | K87: 10.1016/j.diagmicrobio.2016.06.019 | L87: =IF(ISNUMBER(VLOOKUP(A87,EXCL,1,FALSE)),"Excluido",IF(ISNUMBER(VLOOKUP(A87,POST,1,FALSE)),"PostAlerta",IF(ISNUMBER(VLOOKUP(A87,PRE,1,FALSE)),"PreAlerta",""))) -> PreAlerta | M87: =IF(ISNUMBER(A87),(IF(ISNUMBER(VLOOKUP(A87,KEYWORDS,1,FALSE)),"C/PalabrasClaves","S/PalabrasClaves")),"") -> S/PalabrasClaves | N87: =IF(ISNUMBER(SEARCH("TREATMENT", B87)), "4) Nuevos tratamientos", "") | P87: 2016 Oct | R87: =LEFT('2012-2022'!$P87,4) -> 2016 | S87: Oct | T87: =IFERROR(VLOOKUP(A87,BD_aux,2,FALSE),"")
A88: 25639637 | B88: [Antimicrobal resistance of Neisseria gonorrhoeae strains in Hungary] | C88: Nemes-Nikodém É, Brunner A, Tóth B, Tóth V, Bánvölgyi A, Ostorházi E. | D88: Orv Hetil. 2015 Feb 8;156(6):226-9. doi: 10.1556/OH.2015.30079. | E88: Nemes-Nikodém É | F88: Orv Hetil | G88: 2015 | H88: 42038 | K88: 10.1556/OH.2015.30079 | L88: =IF(ISNUMBER(VLOOKUP(A88,EXCL,1,FALSE)),"Excluido",IF(ISNUMBER(VLOOKUP(A88,POST,1,FALSE)),"PostAlerta",IF(ISNUMBER(VLOOKUP(A88,PRE,1,FALSE)),"PreAlerta",""))) -> PreAlerta | M88: =IF(ISNUMBER(A88),(IF(ISNUMBER(VLOOKUP(A88,KEYWORDS,1,FALSE)),"C/PalabrasClaves","S/PalabrasClaves")),"") -> C/PalabrasClaves | N88: 1) Reporte de cepas resistentes | P88: 2015 Feb 8 | R88: =LEFT('2012-2022'!$P88,4) -> 2015 | S88: Feb | T88: Introduction: European guidelines on the treatment of Neisseria gonorrhoeae are based mostly on Western European data, although these recommendations may not be optimised for the circumstances in Hungary. Aim: The aim of the authors was to assess current antimicrobial resistance of Neisseria gonorrhoeae strains in order to enhance gonococcal antimicrobial surveillance in Hungary. Neisseria gonorrhoeae strains were isolated at the National Center of Sexually Transmitted Infections at the Department of Dermatology, Venerology and Dermatooncology of Semmelweis University in the period between January 2011 and June 2014. Method: Antimicrobial resistance was determined with minimum inhibitory concentration measurement. Neisseria gonorrhoeae Multiantigen Sequence typing was used as molecular typing method. Results: Resistance to the currently recommended extended spectrum cephalosporins is rare in Hungary, but there is an emerging azithromycin resistance among the Neisseria gonorrhoeae strains. Conclusions: Revision of the national treatment guideline must consider that the most frequent sequence types of Neisseria gonorrhoeae strains causing infections in Hungary are mainly resistant to azithromycin. | U88: Yes | V88: No | W88: No | X88: This study reports emerging azithromycin resistance in N. gonorrhoeae strains in Hungary, prompting review of national treatment guidelines. | Y88: =IFERROR(VLOOKUP(A86,BD_aux,3,FALSE),"")
A89: 29233095 | B89: The distinctive cell division interactome of Neisseria gonorrhoeae | C89: Zou Y, Li Y, Dillon JR. | D89: BMC Microbiol. 2017 Dec 12;17(1):232. doi: 10.1186/s12866-017-1140-1. | E89: Zou Y | F89: BMC Microbiol | G89: 2017 | H89: 43083 | I89: PMC5727935 | K89: 10.1186/s12866-017-1140-1 | L89: =IF(ISNUMBER(VLOOKUP(A89,EXCL,1,FALSE)),"Excluido",IF(ISNUMBER(VLOOKUP(A89,POST,1,FALSE)),"PostAlerta",IF(ISNUMBER(VLOOKUP(A89,PRE,1,FALSE)),"PreAlerta",""))) -> PostAlerta | M89: =IF(ISNUMBER(A89),(IF(ISNUMBER(VLOOKUP(A89,KEYWORDS,1,FALSE)),"C/PalabrasClaves","S/PalabrasClaves")),"") -> S/PalabrasClaves | N89: =IF(ISNUMBER(SEARCH("TREATMENT", B89)), "4) Nuevos tratamientos", "") | P89: 2017 Dec 12 | R89: =LEFT('2012-2022'!$P89,4) -> 2017 | S89: Dec | T89: =IFERROR(VLOOKUP(A89,BD_aux,2,FALSE),"")
A90: 33785063 | B90: Emergence and evolution of antimicrobial resistance genes and mutations in Neisseria gonorrhoeae | C90: Yahara K, Ma KC, Mortimer TD, Shimuta K, Nakayama SI, Hirabayashi A, Suzuki M, Jinnai M, Ohya H, Kuroki T, Watanabe Y, Yasuda M, Deguchi T, Eldholm V, Harrison OB, Maiden MCJ, Grad YH, Ohnishi M. | D90: Genome Med. 2021 Mar 30;13(1):51. doi: 10.1186/s13073-021-00860-8. | E90: Yahara K | F90: Genome Med | G90: 2021 | H90: 44286 | I90: PMC8008663 | K90: 10.1186/s13073-021-00860-8 | L90: =IF(ISNUMBER(VLOOKUP(A90,EXCL,1,FALSE)),"Excluido",IF(ISNUMBER(VLOOKUP(A90,POST,1,FALSE)),"PostAlerta",IF(ISNUMBER(VLOOKUP(A90,PRE,1,FALSE)),"PreAlerta",""))) -> PostAlerta | M90: =IF(ISNUMBER(A90),(IF(ISNUMBER(VLOOKUP(A90,KEYWORDS,1,FALSE)),"C/PalabrasClaves","S/PalabrasClaves")),"") -> C/PalabrasClaves | N90: 4) otros | O90: Caracterización | P90: 2021 Mar 30 | R90: =LEFT('2012-2022'!$P90,4) -> 2021 | S90: Mar | T90: =IFERROR(VLOOKUP(A90,BD_aux,2,FALSE),"")
A91: 24489950 | B91: Neisseria gonorrhoeae modulates iron-limiting innate immune defenses in macrophages | C91: Zughaier SM, Kandler JL, Shafer WM. | D91: PLoS One. 2014 Jan 28;9(1):e87688. doi: 10.1371/journal.pone.0087688. eCollection 2014. | E91: Zughaier SM | F91: PLoS One | G91: 2014 | H91: 41674 | I91: PMC3905030 | K91: 10.1371/journal.pone.0087688 | L91: =IF(ISNUMBER(VLOOKUP(A91,EXCL,1,FALSE)),"Excluido",IF(ISNUMBER(VLOOKUP(A91,POST,1,FALSE)),"PostAlerta",IF(ISNUMBER(VLOOKUP(A91,PRE,1,FALSE)),"PreAlerta",""))) -> PreAlerta | M91: =IF(ISNUMBER(A91),(IF(ISNUMBER(VLOOKUP(A91,KEYWORDS,1,FALSE)),"C/PalabrasClaves","S/PalabrasClaves")),"") -> S/PalabrasClaves | N91: =IF(ISNUMBER(SEARCH("TREATMENT", B91)), "4) Nuevos tratamientos", "") | P91: 2014 Jan 28 | R91: =LEFT('2012-2022'!$P91,4) -> 2014 | S91: Jan | T91: =IFERROR(VLOOKUP(A91,BD_aux,2,FALSE),"")
A92: 27185804 | B92: Antimicrobial Susceptibility of Neisseria gonorrhoeae in Bangladesh (2014 Update) | C92: Khanam R, Ahmed D, Rahman M, Alam MS, Amin M, Khan SI, Mayer KH, Azim T. | D92: Antimicrob Agents Chemother. 2016 Jun 20;60(7):4418-9. doi: 10.1128/AAC.00223-16. Print 2016 Jul. | E92: Khanam R | F92: Antimicrob Agents Chemother | G92: 2016 | H92: 42508 | I92: PMC4914670 | K92: 10.1128/AAC.00223-16 | L92: =IF(ISNUMBER(VLOOKUP(A92,EXCL,1,FALSE)),"Excluido",IF(ISNUMBER(VLOOKUP(A92,POST,1,FALSE)),"PostAlerta",IF(ISNUMBER(VLOOKUP(A92,PRE,1,FALSE)),"PreAlerta",""))) -> PreAlerta | M92: =IF(ISNUMBER(A92),(IF(ISNUMBER(VLOOKUP(A92,KEYWORDS,1,FALSE)),"C/PalabrasClaves","S/PalabrasClaves")),"") -> C/PalabrasClaves | N92: 1) Reporte de cepas resistentes | P92: 2016 Jun 20 | R92: =LEFT('2012-2022'!$P92,4) -> 2016 | S92: Jun | T92: Documentation of Neisseria gonorrhoeae resistance to multiple antibiotics globally has given rise to major concerns regarding a future of untreatable gonorrhea (1, 2). In Bangladesh, N. gonorrhoeae antimicrobial susceptibility was last examined between 1997 to 2006 in female sex workers (FSWs), males having sex with males (MSMs), patients with sexually transmitted infections (STIs), and truckers, and resistance to ciprofloxacin, penicillin, and tetracycline with reduced susceptibility to cefixime as well as multidrug resistance were reported (3–5). The present analysis was conducted to update these data so as to inform guidelines on syndromic management of sexually transmitted infections (STIs) developed in 2006 (6) that are currently being used in Bangladesh and to enhance global surveillance by the World Health Organization. The current report presents data on antimicrobial resistance of N. gonorrhoeae from a cross-sectional bio-behavioral survey of STIs conducted among key populations (KPs) at risk of HIV in Dhaka, Bangladesh, between August and November 2014. The KPs included FSWs (n = 700), females who injected drugs (FWIDs; n = 177), male sex workers (MSWs; n = 227), and transgender women known as Hijras (n = 169). All were adults (≥18 years) and were enrolled on a first-come, first-served basis from drop in centers (DICs) under the Global Fund Program for HIV, which provides STI prevention services to enlisted KPs. Individuals were enrolled only if they provided written informed consent for their participation in the study. The study was approved by the Research and Ethical Review Committees of the International Centre for Diarrhoeal Disease Research, Bangladesh (icddr,b). Study physicians conducted physical examinations and collected cervical swabs under speculum examination (FSWs and FWIDs) and anorectal swabs (MSWs and Hijras) using aseptic techniques. All swabs were transported to icddr,b in Amies charcoal transport medium within 6 to 8 h of collection. Swabs were cultured for identification of N. gonorrhoeae, and antibiotic susceptibility testing was carried out for positive isolates. Anorectal swabs were directly inoculated onto modified Thayer-Martin (MTM) agar containing vancomycin, colistin, nystatin, and trimethoprim. Cervical swabs were inoculated onto MTM agar, blood agar, and chocolate agar media. After inoculation, all plates were incubated under microaerophilic conditions (5% O2) at 35°C for at least 48 h. The identity of N. gonorrhoeae was confirmed by Gram stain, oxidase test, and Neisseria sugar test (carbohydrate degradation test). Antimicrobial susceptibility testing (AST) was performed by the Kirby-Bauer method (disc diffusion), breakpoints of sensitive, intermediate, and resistant were interpreted following Clinical and Laboratory Standards Institute (CLSI) guidelines (7), and N. gonorrhoeae reference strain ATCC 49226 was used as a standard. Of the 1,273 samples, 21 (5 anorectal and 16 cervical) tested positive for N. gonorrhoeae by culture. This low isolation rate (1.6%) can be explained by the fact that antibiotics were frequently given to our study participants through the HIV/STI prevention program that might have caused a reduction in the bacterial load such that it was undetectable in culture. All N. gonorrhoea cultures were tested for AST, and the results are shown in Table 1. Ceftriaxone and spectinomycin were the antibiotics to which all isolates were susceptible. The next most sensitive antibiotic was azithromycin (90.5%), followed by cefixime (85.7%). None of the isolates were sensitive to ciprofloxacin, to which resistance was found in 95.2% and intermediate resistance in 4.8% of isolates. More than 90% of the isolates were resistant to doxycycline. Multidrug resistance (against three or more antibacterial agents) was identified in 48% of isolates. Antibiotic resistance data obtained from this study are comparable to data from an earlier study (5). In this study, all participants diagnosed with STIs were provided treatment using the national STI management guidelines. The possibility of treatment failure remains given the antimicrobial resistance profile. Extrapolation of these study findings to all of Bangladesh is not possible as the study was conducted only among those KPs who were receiving STI services from DICs. Approximately half of the study participants were diagnosed with STIs previously (data not shown), using the syndromic approach, and many had received antimicrobial therapy, which could be the reason for the low recovery of N. gonorrhoeae strains. This is of relevance as the national syndromic guidelines for STI management in Bangladesh recommend treating gonorrhea and chlamydia with cefixime and azithromycin (6). However, with emerging resistance of N. gonorrhoeae to cefixime and ceftriaxone (8, 9), gonorrhea management guidelines are under scrutiny globally (10, 11). These current data from Bangladesh add to the global antimicrobial resistance data on N. gonorrhoeae and highlight the need to update the national guidelines for STI management in Bangladesh. | U92: Yes | V92: No | W92: No | X92: Multidrug resistance in N. gonorrhoeae in Bangladesh, including resistance to cefixime and ciprofloxacin, underscores the need for updated treatment guidelines. | Y92: =IFERROR(VLOOKUP(A90,BD_aux,3,FALSE),"")
A93: 32457249 | B93: Molecular Insight into TdfH-Mediated Zinc Piracy from Human Calprotectin by Neisseria gonorrhoeae | C93: Kammerman MT, Bera A, Wu R, Harrison SA, Maxwell CN, Lundquist K, Noinaj N, Chazin WJ, Cornelissen CN. | D93: mBio. 2020 May 26;11(3):e00949-20. doi: 10.1128/mBio.00949-20. | E93: Kammerman MT | F93: mBio | G93: 2020 | H93: 43979 | I93: PMC7251212 | K93: 10.1128/mBio.00949-20 | L93: =IF(ISNUMBER(VLOOKUP(A93,EXCL,1,FALSE)),"Excluido",IF(ISNUMBER(VLOOKUP(A93,POST,1,FALSE)),"PostAlerta",IF(ISNUMBER(VLOOKUP(A93,PRE,1,FALSE)),"PreAlerta",""))) -> PostAlerta | M93: =IF(ISNUMBER(A93),(IF(ISNUMBER(VLOOKUP(A93,KEYWORDS,1,FALSE)),"C/PalabrasClaves","S/PalabrasClaves")),"") -> S/PalabrasClaves | N93: =IF(ISNUMBER(SEARCH("TREATMENT", B93)), "4) Nuevos tratamientos", "") | P93: 2020 May 26 | R93: =LEFT('2012-2022'!$P93,4) -> 2020 | S93: May | T93: =IFERROR(VLOOKUP(A93,BD_aux,2,FALSE),"")
A94: 33200978 | B94: Sudden emergence of a Neisseria gonorrhoeae clade with reduced susceptibility to extended-spectrum cephalosporins, Norway | C94: Osnes MN, Didelot X, Korne-Elenbaas J, Alfsnes K, Brynildsrud OB, Syversen G, Nilsen ØJ, De Blasio BF, Caugant DA, Eldholm V. | D94: Microb Genom. 2020 Dec;6(12):mgen000480. doi: 10.1099/mgen.0.000480. Epub 2020 Nov 17. | E94: Osnes MN | F94: Microb Genom | G94: 2020 | H94: 44152 | I94: PMC8116678 | K94: 10.1099/mgen.0.000480 | L94: =IF(ISNUMBER(VLOOKUP(A94,EXCL,1,FALSE)),"Excluido",IF(ISNUMBER(VLOOKUP(A94,POST,1,FALSE)),"PostAlerta",IF(ISNUMBER(VLOOKUP(A94,PRE,1,FALSE)),"PreAlerta",""))) -> PostAlerta | M94: =IF(ISNUMBER(A94),(IF(ISNUMBER(VLOOKUP(A94,KEYWORDS,1,FALSE)),"C/PalabrasClaves","S/PalabrasClaves")),"") -> C/PalabrasClaves | N94: 1) Reporte de cepas resistentes | P94: 2020 Dec | R94: =LEFT('2012-2022'!$P94,4) -> 2020 | S94: Dec | T94: Neisseria gonorrhoeae multilocus sequence type (ST)-7827 emerged in a dramatic fashion in Norway in the period 2016-2018. Here, we aim to shed light on the provenance and expansion of this ST. ST-7827 was found to be polyphyletic, but the majority of members belonged to a monophyletic clade we termed PopPUNK cluster 7827 (PC-7827). In Norway, both PC-7827 and ST-7827 isolates were almost exclusively isolated from men. Phylogeographical analyses demonstrated an Asian origin of the genogroup, with multiple inferred exports to Europe and the USA. The genogroup was uniformly resistant to fluoroquinolones, and associated with reduced susceptibility to both azithromycin and the extended-spectrum cephalosporins (ESCs) cefixime and ceftriaxone. From a genetic background including the penA allele 13.001, associated with reduced ESC susceptibility, we identified repeated events of acquisition of porB alleles associated with further reduction in ceftriaxone susceptibility. Transmission of the strain was significantly reduced in Norway in 2019, but our results indicate the existence of a recently established global reservoir. The worrisome drug-resistance profile and rapid emergence of PC-7827 calls for close monitoring of the situation. | U94: Yes | V94: No | W94: No | X94: ST-7827 N. gonorrhoeae, likely from Asia, spread globally with resistance to fluoroquinolones and reduced ESC susceptibility. | Y94: =IFERROR(VLOOKUP(A92,BD_aux,3,FALSE),"")
A95: 25605868 | B95: A thermonuclease of Neisseria gonorrhoeae enhances bacterial escape from killing by neutrophil extracellular traps | C95: Juneau RA, Stevens JS, Apicella MA, Criss AK. | D95: J Infect Dis. 2015 Jul 15;212(2):316-24. doi: 10.1093/infdis/jiv031. Epub 2015 Jan 20. | E95: Juneau RA | F95: J Infect Dis | G95: 2015 | H95: 42026 | I95: PMC4490236 | K95: 10.1093/infdis/jiv031 | L95: =IF(ISNUMBER(VLOOKUP(A95,EXCL,1,FALSE)),"Excluido",IF(ISNUMBER(VLOOKUP(A95,POST,1,FALSE)),"PostAlerta",IF(ISNUMBER(VLOOKUP(A95,PRE,1,FALSE)),"PreAlerta",""))) -> PreAlerta | M95: =IF(ISNUMBER(A95),(IF(ISNUMBER(VLOOKUP(A95,KEYWORDS,1,FALSE)),"C/PalabrasClaves","S/PalabrasClaves")),"") -> S/PalabrasClaves | N95: =IF(ISNUMBER(SEARCH("TREATMENT", B95)), "4) Nuevos tratamientos", "") | P95: 2015 Jul 15 | R95: =LEFT('2012-2022'!$P95,4) -> 2015 | S95: Jul | T95: =IFERROR(VLOOKUP(A95,BD_aux,2,FALSE),"")
A96: 30909866 | B96: Development of flow cytometry based adherence assay for Neisseria gonorrhoeae using 5'-carboxyfluorosceinsuccidyl ester | C96: Thakur SD, Obradovic M, Dillon JR, Ng SH, Wilson HL. | D96: BMC Microbiol. 2019 Mar 25;19(1):67. doi: 10.1186/s12866-019-1438-2. | E96: Thakur SD | F96: BMC Microbiol | G96: 2019 | H96: 43551 | I96: PMC6434840 | K96: 10.1186/s12866-019-1438-2 | L96: =IF(ISNUMBER(VLOOKUP(A96,EXCL,1,FALSE)),"Excluido",IF(ISNUMBER(VLOOKUP(A96,POST,1,FALSE)),"PostAlerta",IF(ISNUMBER(VLOOKUP(A96,PRE,1,FALSE)),"PreAlerta",""))) -> PostAlerta | M96: =IF(ISNUMBER(A96),(IF(ISNUMBER(VLOOKUP(A96,KEYWORDS,1,FALSE)),"C/PalabrasClaves","S/PalabrasClaves")),"") -> S/PalabrasClaves | N96: =IF(ISNUMBER(SEARCH("TREATMENT", B96)), "4) Nuevos tratamientos", "") | P96: 2019 Mar 25 | R96: =LEFT('2012-2022'!$P96,4) -> 2019 | S96: Mar | T96: =IFERROR(VLOOKUP(A96,BD_aux,2,FALSE),"")
A97: 22693236 | B97: Distinct Neisseria gonorrhoeae transmission networks among men who have sex with men in Amsterdam, The Netherlands | C97: Heymans R, A Matser A, Bruisten SM, Heijman T, Geskus RB, Speksnijder AG, Davidovich U, de Vries HJ, Coutinho RA, Schim van der Loeff MF. | D97: J Infect Dis. 2012 Aug 15;206(4):596-605. doi: 10.1093/infdis/jis399. Epub 2012 Jun 12. | E97: Heymans R | F97: J Infect Dis | G97: 2012 | H97: 41074 | K97: 10.1093/infdis/jis399 | L97: =IF(ISNUMBER(VLOOKUP(A97,EXCL,1,FALSE)),"Excluido",IF(ISNUMBER(VLOOKUP(A97,POST,1,FALSE)),"PostAlerta",IF(ISNUMBER(VLOOKUP(A97,PRE,1,FALSE)),"PreAlerta",""))) -> PreAlerta | M97: =IF(ISNUMBER(A97),(IF(ISNUMBER(VLOOKUP(A97,KEYWORDS,1,FALSE)),"C/PalabrasClaves","S/PalabrasClaves")),"") -> S/PalabrasClaves | N97: =IF(ISNUMBER(SEARCH("TREATMENT", B97)), "4) Nuevos tratamientos", "") | P97: 2012 Aug 15 | R97: =LEFT('2012-2022'!$P97,4) -> 2012 | S97: Aug | T97: =IFERROR(VLOOKUP(A97,BD_aux,2,FALSE),"")
A98: 28633281 | B98: The sweet side of the pathogenic Neisseria: the role of glycan interactions in colonisation and disease | C98: Mubaiwa TD, Semchenko EA, Hartley-Tassell LE, Day CJ, Jennings MP, Seib KL. | D98: Pathog Dis. 2017 Jul 31;75(5):ftx063. doi: 10.1093/femspd/ftx063. | E98: Mubaiwa TD | F98: Pathog Dis | G98: 2017 | H98: 42908 | I98: PMC5808653 | K98: 10.1093/femspd/ftx063 | L98: =IF(ISNUMBER(VLOOKUP(A98,EXCL,1,FALSE)),"Excluido",IF(ISNUMBER(VLOOKUP(A98,POST,1,FALSE)),"PostAlerta",IF(ISNUMBER(VLOOKUP(A98,PRE,1,FALSE)),"PreAlerta",""))) -> Excluido | M98: =IF(ISNUMBER(A98),(IF(ISNUMBER(VLOOKUP(A98,KEYWORDS,1,FALSE)),"C/PalabrasClaves","S/PalabrasClaves")),"") -> S/PalabrasClaves | N98: =IF(ISNUMBER(SEARCH("TREATMENT", B98)), "4) Nuevos tratamientos", "") | P98: 2017 Jul 31 | R98: =LEFT('2012-2022'!$P98,4) -> 2017 | S98: Jul | T98: =IFERROR(VLOOKUP(A98,BD_aux,2,FALSE),"")
A99: 31119632 | B99: Protocols to Interrogate the Interactions Between Neisseria gonorrhoeae and Primary Human Neutrophils | C99: Ragland SA, Criss AK. | D99: Methods Mol Biol. 2019;1997:319-345. doi: 10.1007/978-1-4939-9496-0_19. | E99: Ragland SA | F99: Methods Mol Biol | G99: 2019 | H99: 43609 | I99: PMC6731993 | J99: NIHMS1048319 | K99: 10.1007/978-1-4939-9496-0_19 | L99: =IF(ISNUMBER(VLOOKUP(A99,EXCL,1,FALSE)),"Excluido",IF(ISNUMBER(VLOOKUP(A99,POST,1,FALSE)),"PostAlerta",IF(ISNUMBER(VLOOKUP(A99,PRE,1,FALSE)),"PreAlerta",""))) -> PostAlerta | M99: =IF(ISNUMBER(A99),(IF(ISNUMBER(VLOOKUP(A99,KEYWORDS,1,FALSE)),"C/PalabrasClaves","S/PalabrasClaves")),"") -> S/PalabrasClaves | N99: =IF(ISNUMBER(SEARCH("TREATMENT", B99)), "4) Nuevos tratamientos", "") | P99: 2019 | R99: =LEFT('2012-2022'!$P99,4) -> 2019 | T99: =IFERROR(VLOOKUP(A99,BD_aux,2,FALSE),"")
A100: 32762194 | B100: [Biochemical atypia in the modern russian strains of Neisseria gonorrhoeae.] | C100: Plakhova XI, Petrova NP, Nikonorov AA, Kubanov AA. | D100: Klin Lab Diagn. 2020 Jul 20;65(8):507-511. doi: 10.18821/0869-2084-2020-65-8-507-511. | E100: Plakhova XI | F100: Klin Lab Diagn | G100: 2020 | H100: 44051 | K100: 10.18821/0869-2084-2020-65-8-507-511 | L100: =IF(ISNUMBER(VLOOKUP(A100,EXCL,1,FALSE)),"Excluido",IF(ISNUMBER(VLOOKUP(A100,POST,1,FALSE)),"PostAlerta",IF(ISNUMBER(VLOOKUP(A100,PRE,1,FALSE)),"PreAlerta",""))) -> PostAlerta | M100: =IF(ISNUMBER(A100),(IF(ISNUMBER(VLOOKUP(A100,KEYWORDS,1,FALSE)),"C/PalabrasClaves","S/PalabrasClaves")),"") -> S/PalabrasClaves | N100: =IF(ISNUMBER(SEARCH("TREATMENT", B100)), "4) Nuevos tratamientos", "") | P100: 2020 Jul 20 | R100: =LEFT('2012-2022'!$P100,4) -> 2020 | S100: Jul | T100: =IFERROR(VLOOKUP(A100,BD_aux,2,FALSE),"")
...

Sheet Test
A1: PMID | B1: Title | C1: Categoria | D1: subcategoria | E1: Estado | F1: Abstract | G1: 1) Antimicrobial Resistance stain | H1: 2) New treatment | I1: 3) Immunization | J1: Human_summary
A2: 31119616 | B2: Antimicrobial Resistance in Neisseria gonorrhoeae and Treatment of Gonorrhea | C2: 2) Nuevos tratamientos | D2: 2g) nueva combinación de ATB | F2: This review highlights the global threat of antimicrobial-resistant Neisseria gonorrhoeae. | G2: Yes | H2: No | I2: No | J2: This review highlights the global threat of antimicrobial-resistant Neisseria gonorrhoeae.
A3: 30900979 | B3: Identification of Internationally Disseminated Ceftriaxone-Resistant Neisseria gonorrhoeae Strain FC428, China | C3: 1) Reporte de cepas resistentes | F3: In 2016, we identified a ceftriaxone-resistant Neisseria gonorrhoeae isolate in China. The strain genotype was identical to the resistant clone FC428 that originated in Japan. Enhanced international collaborative surveillance programs are crucial to track the transmission of the ceftriaxone-resistant clones. | G3: Yes | H3: No | I3: No | J3: Detect a ceftriaxone-resistant Neisseria gonorrhoeae strain in China.
A4: 31661379 | B4: Identification of multidrug-resistant Neisseria gonorrhoeae isolates with combined resistance to both ceftriaxone and azithromycin, China, 2017-2018 | C4: 1) Reporte de cepas resistentes | F4: The growing multidrug-resistant Neisseria gonorrhoeae is a serious global threat to gonococcal therapy. During 2017-2018, we identified a rare multidrug-resistant (ceftriaxone and azithromycin) strain (GC250) and four strains (GC185, GC195, GC196 and GC249) with both resistance to ceftriaxone and decreased susceptibility to azithromycin. All strains belonged to NG-STAR ST1143, including the mosaic penA-60.001, which is closely related to ceftriaxone resistance. The characterization of antimicrobial resistance (AMR) determinants and phylogenetic analysis showed these five strains were closely related to internationally spreading ceftriaxone-resistant N. gonorrhoeae FC428, but with higher azithromycin MIC. Findings here demonstrated that this clone not only initiated clonal expansion in China, but acquired azithromycin resistance. | G4: Yes | H4: No | I4: No | J4: This study identified five multidrug-resistant Neisseria gonorrhoeae strains in China
A5: 34402689 | B5: Large Increase in Azithromycin-Resistant Neisseria gonorrhoeae in Northern Spain | C5: 1) Reporte de cepas resistentes | F5: The aim of this study was to characterize the evolution of gonorrhea in the general population by correlating epidemiological, genotypic, and antimicrobial resistance data of Neisseria gonorrhoeae isolates collected in northern Spain from 2014 to 2018. One hundred ninety-four strains underwent antimicrobial susceptibility testing and were genetically analyzed by N. gonorrhoeae multiantigen sequence typing. Increasing cases of gonococcal infections have been observed after 2015. Most occurred in male with urethritis. Sequence type (ST)-9972 and ST-1576, the predominant genotypes identified, have not been previously described as epidemic clones. Of great concern was the significant increase in azithromycin-resistant N. gonorrhoeae. More than 30% of these isolates were obtained from men who have sex with men (MSM). ST-12302 was the most prevalent clone among the azithromycin-resistant strains, and was also resistant to penicillin, ciprofloxacin, and tetracycline. This multidrug-resistant clone was exclusively isolated from MSM during 2018. The incidence rates of gonorrhea and azithromycin-resistant N. gonorrhoeae have significantly increased due to the emergence of new clones. ST-12302 has recently been recognized as an epidemic clone; therefore, its surveillance could be the key in controlling further dissemination of azithromycin resistance. These data highlight the need to perform local studies to update treatment guidelines and reinforce preventive measures against gonorrhea. | G5: Yes | H5: No | I5: No | J5: This study characterized the epidemiological and antimicrobial resistance trends of Neisseria gonorrhoeae in northern Spain The spread of ST-12302 and rising resistance rates stress the importance of local surveillance, updated treatment guidelines, and targeted prevention strategies.
A6: 29553336 | B6: Cephalosporin-Resistant Neisseria gonorrhoeae Clone, China | C6: 1) Reporte de cepas resistentes | F6: Cephalosporin-resistant Neisseria gonorrhoeae is a major public health concern. N. gonorrhoeae of multiantigen sequence type G1407 and multilocus sequence type 1901 is an internationally spreading cephalosporin-resistant clone. We detected 4 cases of infection with this clone in China and analyzed resistance determinants by using N. gonorrhoeae sequence typing for antimicrobial resistance. | G6: Yes | H6: No | I6: No | J6: This report describes 4 cases in China of Neisseria gonorrhoeae infection caused by the cephalosporin-resistant international clone G1407 (MLST ST1901).
A7: 34871932 | B7: Antimicrobial susceptibility testing of Neisseria gonorrhoeae using a phenotypic-molecular assay and lyophilized antimicrobials | C7: 2) Nuevos tratamientos | D7: 2g) nueva combinación de ATB | F7: Gonorrhea is an urgent global public health threat as Neisseria gonorrhoeae (Ng) has progressively developed resistance to all antibiotics commonly used for treatment. Surveillance of antimicrobial susceptibility trends is critical to monitor the emergence and spread of antimicrobial resistance. The gold standard methods for antimicrobial susceptibility testing (AST) of Ng are laborious and time-consuming. We evaluated a phenotypic molecular approach, involving a short cultivation step and quantitative PCR, with lyophilized antimicrobials to characterize antimicrobial susceptibility in Ng. There was excellent concordance between AST performed with liquid and lyophilized ciprofloxacin, penicillin, and tetracycline using the pheno-molecular assay, following a 4-hour incubation step. The categorical agreement between the pheno-molecular assay and the gold standard AST results was 92.4% for characterization of antimicrobial susceptibility. Essential agreement between the 2 methods was 91.9%. Characterization of ceftriaxone susceptibility in Ng using the pheno-molecular assay required a 6-hour incubation step. | G7: No | H7: No | I7: No | J7: This study assessed a rapid phenotypic molecular assay to test antimicrobial susceptibility in Neisseria gonorrhoeae, combining short incubation and qPCR with lyophilized antibiotics.
A8: 32149957 | B8: Reconsidering Presumptive Neisseria gonorrhoeae Treatment For Women With Cervicitis | C8: 2) Nuevos tratamientos | D8: change treatment | F8: - | G8: No | H8: No | I8: No | J8: Not available
A9: 32530860 | B9: Cephalosporin-Resistant Neisseria gonorrhoeae Isolated in Portugal, 2019 | C9: 1) Reporte de cepas resistentes | F9: We report a multidrug-resistant Neisseria gonorrhoeae exhibiting resistance to ceftriaxone and cefixime, isolated in Portugal in 2019. Whole-genome sequencing was performed for typing and identification of genetic determinants of antimicrobial resistance. Because of its antimicrobial susceptibility profile, awareness should be raised for the circulation of this strain. | G9: Yes | H9: No | I9: No | J9: This study reports a multidrug-resistant Neisseria gonorrhoeae strain isolated in Portugal in 2019, resistant to ceftriaxone and cefixime.
A10: 30629196 | B10: Photoinactivation of Neisseria gonorrhoeae: A Paradigm-Changing Approach for Combating Antibiotic-Resistant Gonococcal Infection | C10: 2) Nuevos tratamientos | D10: No farmacológico (UV) | F10: Antimicrobial resistance in Neisseria gonorrhoeae is a major issue of public health, and there is a critical need for the development of new antigonococcal strategies. In this study, we investigated the effectiveness of antimicrobial blue light (aBL; wavelength, 405 nm), an innovative nonpharmacological approach, for the inactivation of N. gonorrhoeae. Our findings indicated that aBL preferentially inactivated N. gonorrhoeae, including antibiotic-resistant strains, over human vaginal epithelial cells in vitro. Furthermore, no aBL-induced genotoxicity to the vaginal epithelial cells was observed at the radiant exposure used to inactivate N. gonorrhoeae. aBL also effectively inactivated N. gonorrhoeae that had attached to and invaded into the vaginal epithelial cells in their cocultures. No gonococcal resistance to aBL developed after 15 successive cycles of inactivation induced by subtherapeutic exposure to aBL. Endogenous aBL-activatable photosensitizing porphyrins in N. gonorrhoeae were identified and quantified using ultraperformance liquid chromatography, with coproporphyrin being the most abundant species in all N. gonorrhoeae strains studied. Singlet oxygen was involved in aBL inactivation of N. gonorrhoeae. Together, these findings show that aBL represents a potential potent treatment for antibiotic-resistant gonococcal infection. | G10: No | H10: Yes | I10: No | J10: This study explored the efficacy of antimicrobial blue light (aBL, 405 nm) as a non-antibiotic treatment for Neisseria gonorrhoeae, including drug-resistant strains. aBL is a promising, resistance-proof therapeutic for gonorrhea, especially against antibiotic-resistant strains.
A11: 24074904 | B11: [Multiresistant Neisseria gonorrhoeae: back to the past?] | C11: 1) Reporte de cepas resistentes | E11: Excluir | F11: - | G11: No | H11: No | I11: No | J11: Editorial
A12: 29883770 | B12: Tetracycline resistance of Neisseria gonorrhoeae in Russia, 2015-2017 | C12: 1) Reporte de cepas resistentes | F12: The objective of this study was to estimate the tetracycline resistance level in the modern population of Neisseria gonorrhoeae in the Russian Federation, where this drug was removed from the treatment regimen for gonococcal infections in 2003. A total of 401 isolates collected between 2015 and 2017 were analyzed for genetic markers (chromosomal porB, rpsJ and mtrR gene mutations and the plasmid-located tetM gene) involved in tetracycline resistance. Antibiotic susceptibility testing revealed that 19% of the strains were tetracycline resistant (MIC > 1 mg/L) and that 10% of the strains had intermediate susceptibility (0.5 < MIC ≤ 1 mg/L). Various combinations of mutations identified in the rpsJ (Val57Met/Leu), porB (Gly120Lys/Asp/Asn/Thr and Ala121/Asp/Asn/Gly), and mtrR (-35 del A) genes resulted in MIC increases of up to 1.47 mg/L (geometric mean value). The presence of the tetM gene was detected in 29 strains, including 18 tetM genes of the American type and 11 of the Dutch type. The tetM gene was associated with a strong increase in resistance (MIC > 8 mg/L). One N. gonorrhoeae isolate was found to carry a defective tetM gene with an AG deletion at position 1239-1240, а new stop codon was introduced that caused a defect in TetM protein synthesis and decrease in the tetracycline resistance. Phylogenetic trees constructed using N. gonorrhoeae NG-MAST and tetM loci were compared. Complex relationship was observed between the N. gonorrhoeae sequence type and the tetM plasmid type. Partial recovery of N. gonorrhoeae tetracycline susceptibility was observed relative to the proportion of isolates with resistance detected ten years ago (75%). However, the current levels of tetracycline resistance still preclude the renewed use of these drugs for gonococcal infection therapy. | G12: Yes | H12: No | I12: No | J12: This study assessed tetracycline resistance in Neisseria gonorrhoeae isolates in Russia after its removal from treatment protocols in 2003
A13: 31972174 | B13: Identification of potential therapeutic targets in Neisseria gonorrhoeae by an in-silico approach | C13: 2) Nuevos tratamientos | D13: in silico | F13: Neisseria gonorrhoeae is a gram negative diplococcus bacterium and the causative agent of the sexually transmitted disease Gonorrhea. It has been recently given the status of "superbug" by World Health Organization because of the increasing antibiotic resistance and unavailability of a viable vaccine candidate. Over recent years, there have been increasing reports about the use of subtractive genomics to identify potential drug and vaccine targets. Our study utilizes codon biasing, a tool to identify the essential genes, in N. gonorrhoeae that could be utilized as novel therapeutic targets for drug or vaccine development. Through the screening of 2350 total genes, we present a list of 29 such drug candidate genes based on codon adaptation. Through the data-mining with BLAST2GO and InterProScan databases, we could predict the function of these 29 genes. These genes are involved in pivotal cellular functions like DNA replication, energy synthesis and metabolites production. This study also shortlists the essential genes of N. gonorrhoeae that could be used to target Neisseria. We identified a molecule/drug which can be used to target essential protein DapD (succinyltransferase). | G13: No | H13: Yes | I13: No | J13: Essential genes identified via codon bias in N. gonorrhoeae suggest novel targets for drugs or vaccines, including DapD protein.
A14: 30787927 | B14: The Neisseria gonorrhoeae Methionine Sulfoxide Reductase (MsrA/B) Is a Surface Exposed, Immunogenic, Vaccine Candidate | C14: 3) Inmunizacióm | F14: Control of the sexually transmitted infection gonorrhea is a major public health challenge, due to the recent emergence of multidrug resistant strains of Neisseria gonorrhoeae, and there is an urgent need for novel therapies or a vaccine to prevent gonococcal disease. In this study, we evaluated the methionine sulfoxide reductase (MsrA/B) of N. gonorrhoeae as a potential vaccine candidate, in terms of its expression, sequence conservation, localization, immunogenicity, and the functional activity of antibodies raised to it. Gonococcal MsrA/B has previously been shown to reduce methionine sulfoxide [Met(O)] to methionine (Met) in oxidized proteins and protect against oxidative stress. Here we have shown that the gene encoding MsrA/B is present, highly conserved, and expressed in all N. gonorrhoeae strains investigated, and we determined that MsrA/B is surface is exposed on N. gonorrhoeae. Recombinant MsrA/B is immunogenic, and mice immunized with MsrA/B and either aluminum hydroxide gel adjuvant or Freund's adjuvant generated a humoral immune response, with predominantly IgG1 antibodies. Higher titers of IgG2a, IgG2b, and IgG3 were detected in mice immunized with MsrA/B-Freund's adjuvant compared to MsrA/B-aluminum hydroxide adjuvant, while IgM titers were similar for both adjuvants. Antibodies generated by MsrA/B-Freund's in mice mediated bacterial killing via both serum bactericidal activity and opsonophagocytic activity. Anti-MsrA/B was also able to functionally block the activity of MsrA/B by inhibiting binding to its substrate, Met(O). We propose that recombinant MsrA/B is a promising vaccine antigen for N. gonorrhoeae. | G14: No | H14: No | I14: Yes | J14: MsrA/B protein is conserved, surface-exposed, immunogenic, and elicits bactericidal antibodies, supporting its use as a vaccine antigen.
A15: 30239814 | B15: Azithromycin Susceptibility Among Neisseria gonorrhoeae Isolates and Seasonal Macrolide Use | C15: 1) Reporte de cepas resistentes | F15: Rising azithromycin nonsusceptibility among Neisseria gonorrhoeae isolates threatens current treatment recommendations, but the cause of this rise is not well understood. We performed an ecological study of seasonal patterns in macrolide use and azithromycin resistance in N. gonorrhoeae, finding that population-wide macrolide use is associated with increased azithromycin nonsusceptibility. These results, indicative of bystander selection, have implications for antibiotic prescribing guidelines. | G15: Yes | H15: No | I15: No | J15: Increased macrolide use correlates with azithromycin nonsusceptibility in N. gonorrhoeae
A16: 25480491 | B16: Neisseria gonorrhoeae isolates with high-level resistance to azithromycin in Australia | C16: 1) Reporte de cepas resistentes | F16: Antimicrobial resistance in Neisseria gonorrhoeae is a major public health concern globally. Over time, gonococci have developed resistance to most antimicrobial agents used for first-line treatment and declining susceptibility to the extended-spectrum cephalosporins is emerging worldwide.1–3 Consequently, dual antimicrobial therapy consisting of ceftriaxone (250 or 500 mg by intramuscular injection) together with azithromycin (1 or 2 g orally) is now recommended as standard treatment for gonorrhoea in the USA, the UK and Europe and is now gradually being adopted in major clinics throughout Australia.4–7 Monotherapy with 2 g of azithromycin is an alternative treatment in patients who are allergic to cephalosporins.4 These treatment regimens are threatened by the emergence of azithromycin resistance in gonococci, particularly high-level azithromycin resistance. High-level azithromycin resistance in N. gonorrhoeae, defined by an azithromycin MIC >256 mg/L, is associated with mutations in the peptidyltransferase loop in domain V of the 23S rRNA gene, principally A2059G, and a single base pair deletion (A) in the promoter region of the mtrR gene.8,9 Isolates of gonococci displaying high-level azithromycin resistance have been reported from the UK, Italy, Argentina, the USA and Sweden.10–14 Here, we provide the first report of gonococci in Australia with high-level azithromycin resistance. | G16: Yes | H16: No | I16: No | J16: High-level azithromycin-resistant N. gonorrhoeae with key 23S rRNA and mtrR mutations is now reported for the first time in Australia.
A17: 22492861 | B17: Fluoroquinolone resistance in Neisseria gonorrhoeae: fitness cost or benefit? | C17: 1) Reporte de cepas resistentes | F17: The successful treatment of gonorrhea, presently the second most prevalent bacterial sexually transmitted infection worldwide, has historically taken full advantage of the introduction of successive new categories of antimicrobial agents to successfully eliminate the microorganism causing this disease, Neisseria gonorrhoeae. New antibiotics have replaced older ones for treatment because N. gonorrhoeae has progressively developed resistance to each class introduced; first to sulphonamides, then to penicillins, tetracyclines, and then quinolones and macrolides [1, 2]. While the last class of antimicrobial effective for the treatment of gonorrhea is the third-generation cephalosporins, more and more reports are emerging of in vitro decreased susceptibility and treatment failures to the oral cephalosporins, such as cefixime, coupled with recent reports of strains with high-level resistance to ceftriaxone [3–5]. The strains with high-level resistance to cephalosporins also exhibited resistance or reduced susceptibility to several other antibiotics. Thus, there is a great concern that gonorrhea has become an untreatable superbug in certain instances, and the search for effective alternative treatment strategies and therapies, possibly a combination of antibiotics, is urgent [5, 6]. | G17: Yes | H17: No | I17: No | J17: This review highlights the global threat of antimicrobial-resistant Neisseria gonorrhoeae.
A18: 30858209 | B18: First Case of Ceftriaxone-Resistant Multidrug-Resistant Neisseria gonorrhoeae in Singapore | C18: 1) Reporte de cepas resistentes | F18: - | G18: No | H18: No | I18: No | J18: Not available
A19: 30552033 | B19: In vitro activity of EDTA and TOL-463 against Neisseria gonorrhoeae | C19: 2) Nuevos tratamientos | D19: 2c) Droga de diseño | F19: Neisseria gonorrhoeae quickly develops drug resistance. Time-kill curves revealed that EDTA and TOL-463 inhibit growth similar to penicillin, ciprofloxacin, and azithromycin. Furthermore, synergistic and additive antimicrobial interactions occurred when EDTA and TOL-463 were combined with penicillin or azithromycin, respectively, suggesting that further investigations into these unconventional antimicrobials may be advantageous. | G19: No | H19: Yes | I19: No | J19: This study suggests EDTA and TOL-463 show antimicrobial activity and synergy with current drugs, supporting exploration of new therapies.
A20: 29553335 | B20: Cooperative Recognition of Internationally Disseminated Ceftriaxone-Resistant Neisseria gonorrhoeae Strain | C20: 1) Reporte de cepas resistentes | F20: Ceftriaxone remains a first-line treatment for patients infected by Neisseria gonorrhoeae in most settings. We investigated the possible spread of a ceftriaxone-resistant FC428 N. gonorrhoeae clone in Japan after recent isolation of similar strains in Denmark (GK124) and Canada (47707). We report 2 instances of the FC428 clone in Australia in heterosexual men traveling from Asia. Our bioinformatic analyses included core single-nucleotide variation phylogeny and in silico molecular typing; phylogenetic analysis showed close genetic relatedness among all 5 isolates. Results showed multilocus sequence type 1903; N. gonorrhoeae sequence typing for antimicrobial resistance (NG-STAR) 233; and harboring of mosaic penA allele encoding alterations A311V and T483S (penA-60.001), associated with ceftriaxone resistance. Our results provide further evidence of international transmission of ceftriaxone-resistant N. gonorrhoeae. We recommend increasing awareness of international spread of this drug-resistant strain, strengthening surveillance to include identifying treatment failures and contacts, and strengthening international sharing of data. | G20: Yes | H20: No | I20: No | J20: This report highlights international spread of ceftriaxone-resistant N. gonorrhoeae FC428 clone, emphasizing need for global surveillance.
A21: 29924264 | B21: [Antimicrobial resistance of Neisseria gonorrhoeae in Peru] | C21: 1) Reporte de cepas resistentes | F21: Gonorrhea is a sexually transmitted infection (STI) caused by Neisseria gonorrhoeae. It manifests as urethritis in men and mucopurulent cervicitis in women, with complications including pelvic inflammatory disease, ectopic pregnancy, infertility, increased HIV transmission, and gonococcal conjunctivitis, which may lead to blindness in newborns. An estimated 78 million new cases of gonococcal infection occurred worldwide among people aged 15 to 49 years in 2012. According to data from the World Health Organization’s Global Gonococcal Antimicrobial Surveillance Programme (WHO GASP) between 2009 and 2014, widespread resistance to antimicrobials such as penicillin, tetracycline, and ciprofloxacin has been documented, along with increasing resistance to azithromycin and emerging resistance to extended-spectrum cephalosporins. In Peru, a resistance evaluation report of strains isolated from various regions during 1998–1999 showed 100% sensitivity to antimicrobials such as ciprofloxacin, spectinomycin, ceftriaxone, and cefotaxime. Later, an analysis of strains isolated from STI-risk populations between 2010 and 2013 revealed 23% resistance to ciprofloxacin. As part of the sentinel surveillance for Neisseria gonorrhoeae implemented in 12 health facilities across seven Peruvian regions (Lima, Callao, Ancash, Ayacucho, Madre de Dios, Loreto, and Ucayali), isolates were sent to the National Institute of Health (Lima, Peru) for biochemical identification using carbohydrate tests on cystine tryptic agar or API®NH, and for antimicrobial susceptibility testing through agar dilution minimum inhibitory concentration (MIC), following Clinical Laboratory Standards Institute (CLSI) guidelines. We analyzed 96 strains from October 2016 to November 2017 and found resistance proportions per antimicrobial: ciprofloxacin 82.3%, tetracycline 54.2%, penicillin 51%, azithromycin 15.6%, and, for the first time, four strains with decreased sensitivity to ceftriaxone (4.2%) reported through the National Focal Point (Table 1). The most frequent resistance phenotypes were: CMTR/QRNG 15.6% (chromosomal resistance to tetracycline/ciprofloxacin), CMRNG/QRNG 12.5% (chromosomal resistance to penicillin and tetracycline/ciprofloxacin), CMPR/QRNG 11.5% (chromosomal resistance to penicillin/ciprofloxacin), and QRNG only 10.4% (ciprofloxacin resistance). Thus, high levels of resistance to ciprofloxacin (82.3%) are reported in Peru for the first time, confirming WHO GASP’s findings. This evidence should support the revision of the current national treatment guideline for gonorrhea. On the other hand, although an increase in azithromycin resistance (15.6%) and, for the first time, decreased sensitivity to ceftriaxone (4.2%) were observed, the dual therapy with ceftriaxone and azithromycin (as recommended by WHO) would remain the most effective. However, it is necessary to continue monitoring gonococcal resistance at the national level to identify strains with reduced susceptibility to extended-spectrum cephalosporins (currently the only available antibiotic class). Detection of such strains must be reported to the National Focal Point under the International Health Regulations. Therefore, the national surveillance system should be strengthened (especially in cases of treatment failure), as well as laboratory capacity through quality assurance and molecular studies to determine the corresponding resistance mechanisms. | G21: Yes | H21: No | I21: No | J21: High ciprofloxacin resistance (82.3%), increased azithromycin resistance (15.6%) and first ceftriaxone reduced susceptibility (4.2%) reported in Peru.
A22: 30047666 | B22: Neisseria gonorrhoeae susceptibility to ciprofloxacin | C22: 1) Reporte de cepas resistentes | F22: - | G22: No | H22: No | I22: No | J22: Not available
A23: 27191699 | B23: Neisseria gonorrhoeae Resistant to Ceftriaxone and Cefixime, Argentina | C23: 1) Reporte de cepas resistentes | F23: Antimicrobial resistance in Neisseria gonorrhoeae is increasing worldwide. In recent years, gonococcal strains resistant to extended-spectrum cephalosporin (ESC) ceftriaxone have been reported in many countries (1). In South America, seven ceftriaxone-resistant strains (MIC >0.25 μg/mL) were reported in Brazil in 2007; however, these isolates were not characterized (2). The emergence of cefalosporin-resistant gonorrhea would significantly limit treatment options and pose a major public health issue. We report an isolation of N. gonorrhoeae in Argentina that was resistant to both ceftriaxone and cefixime. In September 2014, a 19-year-old heterosexual male without underlying disease presented to the emergency department of a hospital in Río Negro, Argentina. Physical examination showed purulent urethral discharge. He reported having engaged in unprotected vaginal insertive intercourse with multiple partners in the past few months. The patient denied recent travel outside of Argentina. He had a history of gonococcal urethritis (March 2014), treated with a single dose (500 mg) of ceftriaxone; however, a gonococcal isolate obtained at that time was not sent to a reference laboratory as part of the Argentine Gonococcal Antimicrobial Sensitivity Surveillance Program for antimicrobial susceptibility profiling. Upon admission, we obtained and cultured a urethral swab sample and identified the isolate as N. gonorrhoeae by conventional methods (3). The isolate was sent to a reference laboratory, and its identity was confirmed by the Phadebact GC monoclonal test (MKL Diagnostic AB, Sollentuna, Sweden) and time-of-flight mass spectrometry with matrix-assisted laser desorption/ionization (Bruker Daltonik GmbH, Bremen, Germany). The patient received a single dose (500 mg) of ceftriaxone. Five days later, the patient returned for a clinical evaluation, and symptoms had resolved. No cure test culture was performed. Minimum inhibitory concentrations (MICs) were determined for penicillin, cefixime, ceftriaxone, tetracycline, ciprofloxacin, and azithromycin by the agar dilution method according to the Clinical Laboratory Standards Institute (CLSI) guidelines (4). Results were interpreted based on these guidelines, except for azithromycin, where the European Committee on Antimicrobial Susceptibility Testing (http://www.eucast.org/) cut-offs were applied. This isolate was resistant to ceftriaxone and cefixime (MIC 0.5 μg/mL), penicillin (8 μg/mL), tetracycline (8 μg/mL), and azithromycin (1 μg/mL). However, the isolate was susceptible to ciprofloxacin (0.03 μg/mL). The β-lactamase test by nitrocefin chromogenic disk assay (Becton Dickinson, Franklin Lakes, NJ, USA) was negative. Resistance determinants involved in ceftriaxone resistance were amplified by PCR and sequenced as described (5, 6). We then analyzed the complete sequences of the penA and pilQ genes, along with other genetic determinants such as the mtrR, penB, and ponA genes. PCR products were purified and sequenced with an ABI 3500 genetic analyzer (Applied Biosystems, Foster City, CA, USA), and epidemiological molecular characterization was carried out using multi-antigen sequence typing of N. gonorrhoeae (http://www.ng-mast.net). The analysis of the penA gene sequence, which encodes penicillin-binding protein 2 (PBP2), identified a non-mosaic PBP2 IX allele. The analysis of the mtrR gene and its promoter identified a single nucleotide deletion (A) in the inverted repeat of the promoter region and a single amino acid substitution at position H105 (H→Y). Amino acid substitutions were found in the porB1b gene at positions G120 (G→K) and A121 (A→D). The ponA gene, which encodes PBP1, exhibited an amino acid substitution at position L421 (L→P), and the complete amino acid sequence of PilQ showed sequence type VI. The isolate was assigned to the PorB1b serogroup (WII/III), and multi-antigen sequence typing of N. gonorrhoeae showed a new sequence type ST13064 (porB -7592 and tbpB -33). Mosaic PBP2 alleles have been strongly associated with reduced susceptibility or resistance to ESCs (7). However, the isolate we obtained had a non-mosaic PBP IX allele, which contains the P551L substitution that has been associated with higher MICs for ESCs (8). The association of the non-mosaic PBP IX allele, most likely with mutations in the mtrR, penB, and ponA genes, could be involved in resistance to ESCs (9). Although Whiley et al. (6) did not report an association between sequence type VI and ESC resistance, the contribution of this sequence type to ESC resistance requires further studies. In Argentina, isolates with reduced susceptibility and resistance to ESCs have emerged (10), increasing from 1.1% in 2011 to 5.6% in 2014 (Argentine Gonococcal Antimicrobial Sensitivity Surveillance Program, unpublished data). Treatment failures and isolates with reduced susceptibility and resistance to ESCs have been reported (9). However, syndromic management of gonorrhea in Argentina has resulted in suboptimal diagnosis and a lack of samples for culture to distinguish between treatment failure and reinfection. Syndromic management represents a significant problem, not only compromising the surveillance program but also increasing selective pressure and facilitating the development of antimicrobial resistance. Consequently, surveillance should be strengthened to support the detection and verification of asymptomatic infections and treatment failures, identify high-risk communities, and trace sexual contacts. These efforts should be used in public health responses to mitigate the emergence and spread of ESC-resistant gonococci. | G23: Yes | H23: No | I23: No | J23: Resistance to ceftriaxone (ESC) linked to non-mosaic PBP2 allele and genetic mutations in Argentin
A24: 25253760 | B24: Ceftriaxone-resistant Neisseria gonorrhoeae, Puerto Rico | C24: 1) Reporte de cepas resistentes | F24: Emergence and spread of multidrug-resistant Neisseria gonorrhoeae is a global threat. The aetiological agent of gonorrhoea has developed resistance to first-line treatments, such as sulfanilamides, penicillins, tetracyclines, macrolides, and fluoroquinolones1 The extended-spectrum cephalosporins are now the only antibiotics recommended for treatment of gonorrhoea in the USA and many countries.2 ,3 Unfortunately, susceptibility to these antimicrobials has also decreased.4–7 This trend has made the Centers for Disease Control (CDC) to recently classify N. gonorrhoeae as an urgent public health threat.8 | G24: Yes | H24: No | I24: No | J24: Not available
A25: 28069643 | B25: In Vitro Activity of Gepotidacin (GSK2140944) against Neisseria gonorrhoeae | C25: 2) Nuevos tratamientos | D25: 2c) Droga de diseño | F25: Gepotidacin (formerly GSK2140944) is a novel, first-in-class, triazaacenaphthylene antibacterial that inhibits bacterial DNA gyrase and topoisomerase IV via a unique mechanism and has demonstrated in vitro activity against Neisseria gonorrhoeae, including drug-resistant strains, and also targets pathogens associated with other conventional and biothreat infections. Broth microdilution was used to evaluate the MIC and minimum bactericidal concentration (MBC) activity of gepotidacin and comparators against 25 N. gonorrhoeae strains (including five ciprofloxacin-nonsusceptible strains). Gepotidacin activity was also evaluated against three N. gonorrhoeae strains (including a ciprofloxacin-nonsusceptible strain) for resistance development, against three N. gonorrhoeae strains (including two tetracycline- and azithromycin-nonsusceptible strains) using time-kill kinetics and checkerboard methods, and against two N. gonorrhoeae strains for the investigation of postantibiotic (PAE) and subinhibitory (PAE-SME) effects. The MIC50 and MIC90 for gepotidacin against the 25 N. gonorrhoeae isolates tested were 0.12 and 0.25 μg/ml, respectively. The MBC50 and MBC90 for gepotidacin were 0.25 and 0.5 μg/ml, respectively. Gepotidacin was bactericidal, and single-step resistance selection studies did not recover any mutants, indicating a low rate of spontaneous single-step resistance. For combinations of gepotidacin and comparators tested using checkerboard methods, there were no instances where antagonism occurred and only one instance of synergy (with moxifloxacin; fractional inhibitory concentration, 0.375). This was not confirmed by in vitro time-kill studies. The PAE for gepotidacin against the wild-type strain ranged from 0.5 to >2.5 h, and the PAE-SME was >2.5 h. These in vitro data indicate that further study of gepotidacin is warranted for potential use in treating infections caused by N. gonorrhoeae. | G25: No | H25: Yes | I25: No | J25: This study supports gepotidacin as a promising new antimicrobial for treating drug-resistant Neisseria gonorrhoeae infections.
A26: 25639637 | B26: [Antimicrobal resistance of Neisseria gonorrhoeae strains in Hungary] | C26: 1) Reporte de cepas resistentes | F26: Introduction: European guidelines on the treatment of Neisseria gonorrhoeae are based mostly on Western European data, although these recommendations may not be optimised for the circumstances in Hungary. Aim: The aim of the authors was to assess current antimicrobial resistance of Neisseria gonorrhoeae strains in order to enhance gonococcal antimicrobial surveillance in Hungary. Neisseria gonorrhoeae strains were isolated at the National Center of Sexually Transmitted Infections at the Department of Dermatology, Venerology and Dermatooncology of Semmelweis University in the period between January 2011 and June 2014. Method: Antimicrobial resistance was determined with minimum inhibitory concentration measurement. Neisseria gonorrhoeae Multiantigen Sequence typing was used as molecular typing method. Results: Resistance to the currently recommended extended spectrum cephalosporins is rare in Hungary, but there is an emerging azithromycin resistance among the Neisseria gonorrhoeae strains. Conclusions: Revision of the national treatment guideline must consider that the most frequent sequence types of Neisseria gonorrhoeae strains causing infections in Hungary are mainly resistant to azithromycin. | G26: Yes | H26: No | I26: No | J26: This study reports emerging azithromycin resistance in N. gonorrhoeae strains in Hungary, prompting review of national treatment guidelines.
A27: 27185804 | B27: Antimicrobial Susceptibility of Neisseria gonorrhoeae in Bangladesh (2014 Update) | C27: 1) Reporte de cepas resistentes | F27: Documentation of Neisseria gonorrhoeae resistance to multiple antibiotics globally has given rise to major concerns regarding a future of untreatable gonorrhea (1, 2). In Bangladesh, N. gonorrhoeae antimicrobial susceptibility was last examined between 1997 to 2006 in female sex workers (FSWs), males having sex with males (MSMs), patients with sexually transmitted infections (STIs), and truckers, and resistance to ciprofloxacin, penicillin, and tetracycline with reduced susceptibility to cefixime as well as multidrug resistance were reported (3–5). The present analysis was conducted to update these data so as to inform guidelines on syndromic management of sexually transmitted infections (STIs) developed in 2006 (6) that are currently being used in Bangladesh and to enhance global surveillance by the World Health Organization. The current report presents data on antimicrobial resistance of N. gonorrhoeae from a cross-sectional bio-behavioral survey of STIs conducted among key populations (KPs) at risk of HIV in Dhaka, Bangladesh, between August and November 2014. The KPs included FSWs (n = 700), females who injected drugs (FWIDs; n = 177), male sex workers (MSWs; n = 227), and transgender women known as Hijras (n = 169). All were adults (≥18 years) and were enrolled on a first-come, first-served basis from drop in centers (DICs) under the Global Fund Program for HIV, which provides STI prevention services to enlisted KPs. Individuals were enrolled only if they provided written informed consent for their participation in the study. The study was approved by the Research and Ethical Review Committees of the International Centre for Diarrhoeal Disease Research, Bangladesh (icddr,b). Study physicians conducted physical examinations and collected cervical swabs under speculum examination (FSWs and FWIDs) and anorectal swabs (MSWs and Hijras) using aseptic techniques. All swabs were transported to icddr,b in Amies charcoal transport medium within 6 to 8 h of collection. Swabs were cultured for identification of N. gonorrhoeae, and antibiotic susceptibility testing was carried out for positive isolates. Anorectal swabs were directly inoculated onto modified Thayer-Martin (MTM) agar containing vancomycin, colistin, nystatin, and trimethoprim. Cervical swabs were inoculated onto MTM agar, blood agar, and chocolate agar media. After inoculation, all plates were incubated under microaerophilic conditions (5% O2) at 35°C for at least 48 h. The identity of N. gonorrhoeae was confirmed by Gram stain, oxidase test, and Neisseria sugar test (carbohydrate degradation test). Antimicrobial susceptibility testing (AST) was performed by the Kirby-Bauer method (disc diffusion), breakpoints of sensitive, intermediate, and resistant were interpreted following Clinical and Laboratory Standards Institute (CLSI) guidelines (7), and N. gonorrhoeae reference strain ATCC 49226 was used as a standard. Of the 1,273 samples, 21 (5 anorectal and 16 cervical) tested positive for N. gonorrhoeae by culture. This low isolation rate (1.6%) can be explained by the fact that antibiotics were frequently given to our study participants through the HIV/STI prevention program that might have caused a reduction in the bacterial load such that it was undetectable in culture. All N. gonorrhoea cultures were tested for AST, and the results are shown in Table 1. Ceftriaxone and spectinomycin were the antibiotics to which all isolates were susceptible. The next most sensitive antibiotic was azithromycin (90.5%), followed by cefixime (85.7%). None of the isolates were sensitive to ciprofloxacin, to which resistance was found in 95.2% and intermediate resistance in 4.8% of isolates. More than 90% of the isolates were resistant to doxycycline. Multidrug resistance (against three or more antibacterial agents) was identified in 48% of isolates. Antibiotic resistance data obtained from this study are comparable to data from an earlier study (5). In this study, all participants diagnosed with STIs were provided treatment using the national STI management guidelines. The possibility of treatment failure remains given the antimicrobial resistance profile. Extrapolation of these study findings to all of Bangladesh is not possible as the study was conducted only among those KPs who were receiving STI services from DICs. Approximately half of the study participants were diagnosed with STIs previously (data not shown), using the syndromic approach, and many had received antimicrobial therapy, which could be the reason for the low recovery of N. gonorrhoeae strains. This is of relevance as the national syndromic guidelines for STI management in Bangladesh recommend treating gonorrhea and chlamydia with cefixime and azithromycin (6). However, with emerging resistance of N. gonorrhoeae to cefixime and ceftriaxone (8, 9), gonorrhea management guidelines are under scrutiny globally (10, 11). These current data from Bangladesh add to the global antimicrobial resistance data on N. gonorrhoeae and highlight the need to update the national guidelines for STI management in Bangladesh. | G27: Yes | H27: No | I27: No | J27: Multidrug resistance in N. gonorrhoeae in Bangladesh, including resistance to cefixime and ciprofloxacin, underscores the need for updated treatment guidelines.
A28: 33200978 | B28: Sudden emergence of a Neisseria gonorrhoeae clade with reduced susceptibility to extended-spectrum cephalosporins, Norway | C28: 1) Reporte de cepas resistentes | F28: Neisseria gonorrhoeae multilocus sequence type (ST)-7827 emerged in a dramatic fashion in Norway in the period 2016-2018. Here, we aim to shed light on the provenance and expansion of this ST. ST-7827 was found to be polyphyletic, but the majority of members belonged to a monophyletic clade we termed PopPUNK cluster 7827 (PC-7827). In Norway, both PC-7827 and ST-7827 isolates were almost exclusively isolated from men. Phylogeographical analyses demonstrated an Asian origin of the genogroup, with multiple inferred exports to Europe and the USA. The genogroup was uniformly resistant to fluoroquinolones, and associated with reduced susceptibility to both azithromycin and the extended-spectrum cephalosporins (ESCs) cefixime and ceftriaxone. From a genetic background including the penA allele 13.001, associated with reduced ESC susceptibility, we identified repeated events of acquisition of porB alleles associated with further reduction in ceftriaxone susceptibility. Transmission of the strain was significantly reduced in Norway in 2019, but our results indicate the existence of a recently established global reservoir. The worrisome drug-resistance profile and rapid emergence of PC-7827 calls for close monitoring of the situation. | G28: Yes | H28: No | I28: No | J28: ST-7827 N. gonorrhoeae, likely from Asia, spread globally with resistance to fluoroquinolones and reduced ESC susceptibility.
A29: 31157931 | B29: Antimicrobial Blue Light Inactivation of Neisseria gonorrhoeae: Roles of Wavelength, Endogenous Photosensitizer, Oxygen, and Reactive Oxygen Species | C29: 2) Nuevos tratamientos | D29: No farmacológico (UV) | F29: Background and objectives: The aim of this study was to investigate the efficacy, safety, and mechanism of action of antimicrobial blue light (aBL) for the inactivation of Neisseria gonorrhoeae, the etiological agent of gonorrhea. Study design/materials and methods: The susceptibilities of N. gonorrhoeae (ATCC 700825) in planktonic suspensions to aBL at 405- and 470-nm wavelengths were compared. The roles of oxygen in the anti-gonococcal activity of aBL were studied by examining the effects of hypoxic condition (blowing N2 ) on the anti-gonococcal efficiency of 405-nm aBL. The presence, identification, and quantification of endogenous photosensitizers in N. gonorrhoeae cells and human vaginal epithelial cells (VK2/E6E7 cells) were determined using fluorescence spectroscopy and ultra-performance liquid chromatography (UPLC). Finally, the selectivity of aBL inactivation of N. gonorrhoeae over the host cells were investigated by irradiating the co-cultures of N. gonorrhoeae and human vaginal epithelial cells using 405-nm aBL. Results: About 3.12-log10 reduction of bacterial colony forming units (CFU) was achieved by 27 J/cm 2 exposure at 405 nm, while about 3.70-log10 reduction of bacterial CFU was achieved by 234 J/cm2 exposure at 470 nm. The anti-gonococcal efficacy of 405-nm aBL was significantly suppressed under hypoxic condition. Spectroscopic and UPLC analyses revealed the presence of endogenous porphyrins and flavins in N. gonorrhoeae. The concentrations of endogenous photosensitizers in N. gonorrhoeae (ATCC 700825) cells were more than 10 times higher than those in the VK2/E6E7 cells. In the co-cultures of N. gonorrhoeae and VK2/E6E7 cells, 405-nm aBL at 108 J/cm2 preferentially inactivated N. gonorrhoeae cells while sparing the vaginal epithelial cells. Conclusions: aBL at 405-nm wavelength is more effective than 470-nm wavelength in inactivating N. gonorrhoeae while sparing the vaginal epithelial cells. Reactive oxygen species generated from the photochemical reactions between aBL and endogenous photosensitizers play a vital role in the anti-gonococcal activity of 405-nm aBL. Lasers Surg. Med. © 2019 Wiley Periodicals, Inc. | G29: No | H29: Yes | I29: No | J29: aBL at 405-nm wavelength inactivates N. gonorrhoeae effectively while sparing host cells, utilizing reactive oxygen species
A30: 32661900 | B30: Machine Learning Platform to Discover Novel Growth Inhibitors of Neisseria gonorrhoeae | C30: 2) Nuevos tratamientos | D30: in silico | F30: Purpose: To advance fundamental biological and translational research with the bacterium Neisseria gonorrhoeae through the prediction of novel small molecule growth inhibitors via naïve Bayesian modeling methodology. Methods: Inspection and curation of data from the publicly available ChEMBL web site for small molecule growth inhibition data of the bacterium Neisseria gonorrhoeae resulted in a training set for the construction of machine learning models. A naïve Bayesian model for bacterial growth inhibition was utilized in a workflow to predict novel antibacterial agents against this bacterium of global health relevance from a commercial library of >105 drug-like small molecules. Follow-up efforts involved empirical assessment of the predictions and validation of the hits. Results: Specifically, two small molecules were found that exhibited promising activity profiles and represent novel chemotypes for agents against N. gonorrrhoeae. Conclusions: This represents, to the best of our knowledge, the first machine learning approach to successfully predict novel growth inhibitors of this bacterium. To assist the chemical tool and drug discovery fields, we have made our curated training set available as part of the Supplementary Material and the Bayesian model is accessible via the web. Graphical Abstract. | G30: No | H30: Yes | I30: No | J30: Machine learning predicts novel small molecules as potential growth inhibitors against Neisseria gonorrhoeae, expanding therapeutic options.
A31: 32966677 | B31: Antimicrobial activity of enacyloxin IIa and gladiolin against the urogenital pathogens Neisseria gonorrhoeae and Ureaplasma spp | C31: 2) Nuevos tratamientos | D31: 2g) nueva combinación de ATB | F31: Aims: To determine the antimicrobial activity of enacyloxin IIa and gladiolin against Neisseria gonorrhoeae and Ureaplasma spp. Methods and results: The Burkholderia polyketide antibiotics enacyloxin IIa and gladiolin were tested against 14 N. gonorrhoeae and 10 Ureaplasma spp. isolates including multidrug-resistant N. gonorrhoeae isolates WHO V, WHO X and WHO Z as well as macrolide, tetracycline and ciprofloxacin-resistant ureaplasmas. Susceptibility testing of N. gonorrhoeae was carried out by agar dilution, whereas broth micro-dilution and growth kinetic assays were used for Ureaplasma spp. The MIC range for enacyloxin IIa and gladiolin against N. gonorrhoeae was 0·015-0·06 mg l-1 and 1-2 mg l-1 respectively. The presence of resistance to front line antibiotics had no effect on MIC values. The MIC range for enacyloxin IIa against Ureaplasma spp. was 4-32 mg l-1 with a clear dose-dependent effect when observed using a growth kinetic assay. Gladiolin had no antimicrobial activity on Ureaplasma spp. at 32 mg l-1 and limited impact on growth kinetics. Conclusions: Enacyloxin IIa and gladiolin antibiotics have antimicrobial activity against a range of antibiotic susceptible and resistant N. gonorrhoeae and Ureaplasma isolates. Significance and impact of the study: This study highlights the potential for a new class of antimicrobial against pathogens in which limited antibiotics are available. Development of these compounds warrants further investigation in the face of emerging extensively drug-resistant strains. | G31: No | H31: Yes | I31: No | J31: This study tested enacyloxin IIa and gladiolin, two polyketide antibiotics, against Neisseria gonorrhoeae and Ureaplasma spp., including multi-drug resistant strains.
A32: 30234796 | B32: Antimicrobial Susceptibility of Neisseria gonorrhoeae Isolates in Yaoundé, Cameroon From 2009 to 2014 | C32: 1) Reporte de cepas resistentes | F32: We investigated the antimicrobial resistance in gonococci 2009 to 2014 in Yaoundé, Cameroon, and recommend revisions of the Cameroonian treatment guideline. We observed a high resistance to ciprofloxacin (17.6%) but no ceftriaxone resistance. Ceftriaxone should replace ciprofloxacin as the recommended first-line treatment for urethral/vaginal discharge. Enhanced resistance surveillance in Africa is essential. | G32: Yes | H32: No | I32: No | J32: The study investigated the antimicrobial resistance in gonococci 2009 to 2014 in Yaoundé, Cameroon, and recommend revisions of the Cameroonian treatment guideline
A33: 27451856 | B33: Antibacterial activity of resazurin-based compounds against Neisseria gonorrhoeae in vitro and in vivo | C33: 2) Nuevos tratamientos | D33: 2c) Droga de diseño | F33: Neisseria gonorrhoeae is the cause of the second most common sexually transmitted bacterial infection, with ca. 80 million new cases of gonorrhoea reported annually. The recent emergence of clinical isolates resistant to the last monotherapy against this bacterium, the cephalosporins, illustrates the need for new antigonococcal agents. Here we have characterised a new group of antimicrobials based on the compound resazurin that exhibits robust activity against N. gonorrhoeae in vitro. Resazurin inhibits the growth of a broad range of N. gonorrhoeae isolates, including those resistant to multiple antibiotics. Furthermore, treatment of human endometrial cells infected with N. gonorrhoeae with resazurin significantly reduces the number of intracellular bacteria. Whilst resazurin exhibited potent in vitro antimicrobial activity, in vivo resazurin did not limit the colonisation of mice with N. gonorrhoeae following vaginal infection. The ineffectiveness of resazurin in vivo is likely due to its interaction with serum albumin, which completely diminishes its antimicrobial activity. However, treatment of mice with a resazurin analogue (resorufin pentyl ether) that maintains its antimicrobial activity in the presence of serum albumin approached a significant decrease in the percentage of mice vaginally colonised. This treatment also decreased vaginal colonisation by N. gonorrhoeae over time. Together, these data suggest that resazurin derivatives have potential for the treatment of gonorrhoea. | G33: No | H33: Yes | I33: No | J33: This study explore resazurina as a new treatment
A34: 34668731 | B34: In Vitro Efficacy of Gentamicin Alone and in Combination with Ceftriaxone, Ertapenem, and Azithromycin against Multidrug-Resistant Neisseria gonorrhoeae | C34: 2) Nuevos tratamientos | D34: 2g) nueva combinación de ATB | F34: This study was conducted to determine the in vitro activities of gentamicin alone and in combination with ceftriaxone, ertapenem, and azithromycin against multidrug-resistant (MDR) Neisseria gonorrhoeae isolates. A total of 407 clinical isolates from Nanjing, China, obtained in 2016 to 2017, had MICs determined for gentamicin using the agar dilution method. MDR status was ascribed to 97 strains that displayed decreased susceptibility or resistance to extended-spectrum cephalosporins (ESCs) (ceftriaxone [MIC, ≥0.125 mg/liter] and cefixime [MIC, ≥0.25 mg/liter]), plus resistance to at least two of the following antimicrobials: penicillin (MIC, ≥2 mg/liter), ciprofloxacin (MIC, ≥1 mg/liter), and azithromycin (MIC, ≥1 mg/liter). MDR strains underwent MIC determinations for antimicrobial combinations using the antimicrobial gradient epsilometer test (Etest). Results that ranged from synergy to antagonism were interpreted using the fractional inhibitory concentration (FICI). All 407 gonococcal isolates were susceptible to gentamicin; MICs ranged from 2 mg/liter to 16 mg/liter. Synergy was demonstrated in 16.5% (16/97), 27.8% (27/97), and 8.2% (8/97) of MDR strains when gentamicin was combined with ceftriaxone (geometric mean [GM] FICI, 0.747), ertapenem (GM FICI, 0.662), and azithromycin (GM FICI, 1.021), respectively. No antimicrobial antagonism was observed with any combination tested against MDR strains; overall, antimicrobial combinations were indifferent. The GM MICs of gentamicin were reduced by 2.63-, 3.80-, and 1.98-fold when tested in combination with ceftriaxone, ertapenem, and azithromycin, respectively. The GM MICs of the three additional antimicrobials individually were reduced by 3-, 2.57-, and 1.98-fold, respectively, when each was tested in combination with gentamicin. Gentamicin alone was effective in vitro against N. gonorrhoeae, including MDR isolates. Combination testing of MDR strains showed lower MICs against gentamicin and each of three antimicrobials (ceftriaxone, ertapenem, and azithromycin) when used in combination. IMPORTANCE Antimicrobial-resistant Neisseria gonorrhoeae is a major global public health concern. New treatment options are urgently needed to successfully treat multidrug-resistant (MDR) Neisseria gonorrhoeae infections. This study showed that gentamicin maintained excellent in vitro susceptibility against clinical gonococcal isolates collected in 2016 and 2017, including MDR isolates. Combinations of gentamicin plus ertapenem, ceftriaxone, and azithromycin produced synergistic effects against certain MDR isolates. No antagonism was observed in any of the antimicrobial combinations, which may prove useful to guide clinical testing of combination therapies. | G34: No | H34: Yes | I34: No | J34: This study assessed gentamicin alone and in combination with ceftriaxone, ertapenem, and azithromycin against multidrug-resistant Neisseria gonorrhoeae (MDR) isolates from Nanjing, China (2016–2017). Among 407 clinical strains tested, 97 were MDR.
A35: 30448519 | B35: Antimicrobial resistance and molecular characterisation of Neisseria gonorrhoeae isolates in Fukuoka, Japan, 1996-2016 | C35: 1) Reporte de cepas resistentes | F35: Objectives: Antimicrobial resistance and molecular characteristics of Neisseria gonorrhoeae isolates obtained from 1996-2005 (n=200) and 2008-2016 (n=200) in Fukuoka, Japan, were examined. Methods: MICs were determined by agar dilution. Sequence types (STs) were examined using N. gonorrhoeae multiantigen sequence typing (NG-MAST). Sequencing of major extended-spectrum cephalosporin (ESC) resistance determinants (penA, mtrR and ponA) was performed. Results: Increases in the proportion of gonococci with decreased susceptibility or resistance to cefixime (from 18.0% in 1996-2005 to 46.0% in 2008-2016) and ceftriaxone (from 2.5% to 4.0%) were observed. Gonococcal isolates also showed increased resistance to ciprofloxacin and azithromycin. The four most prevalent NG-MAST STs with a multidrug-resistant phenotype were ST2958 (n=18), ST1407 (n=14), ST6798 (n=12) and ST4015 (n=10). The number of isolates belonging to these four STs rose between the first and second period. Among the 54 isolates belonging to the four major STs, 42 (77.8%) contained a penA mosaic allele and 12 (22.2%) contained a penA non-mosaic allele. The sequence pattern types in the 42 isolates with a penA mosaic allele included type X (64.3%), type XXXIV (33.3%) and a novel pattern type (2.4%). In contrast, all 12 isolates with the penA non-mosaic allele included the sequence pattern type V. Conclusion: Neisseria gonorrhoeae isolates with decreased susceptibility or resistance to ESC have increased over the years. Four major STs with a multidrug-resistant phenotype were identified. These isolates contained a penA mosaic allele or a non-mosaic allele. | G35: Yes | H35: No | I35: No | J35: To assess the antimicrobial resistance and molecular characteristics of Neisseria gonorrhoeae isolates in Fukuoka, Japan, comparing two periods: 1996–2005 and 2008–2016 (200 isolates each).
A36: 34118893 | B36: Antimicrobial resistance and molecular epidemiological typing of Neisseria gonorrhoeae isolates from Kyrgyzstan in Central Asia, 2012 and 2017 | C36: 1) Reporte de cepas resistentes | F36: Background: Gonorrhoea and antimicrobial resistance (AMR) in Neisseria gonorrhoeae are significant public health concerns globally. Nearly no gonococcal AMR data are available from Central Asia, and no data from Kyrgyzstan has been published. We examined, for the first time, AMR and molecular epidemiology of N. gonorrhoeae isolates cultured in Kyrgyzstan in 2012 and 2017, in order to inform refinements of the Kyrgyz national gonorrhoea management guidelines. Methods: N. gonorrhoeae isolates cultured in 2012 (n = 84) and 2017 (n = 72) in Kyrgyzstan were examined. MICs of nine antimicrobials were determined using Etest and, where available, clinical breakpoints from the EUCAST were applied. N. gonorrhoeae multiantigen sequence typing (NG-MAST) was also performed. Results: The overall resistance levels were high to ciprofloxacin (88.5%), tetracycline (56.9%), benzylpenicillin (39.1%), and kanamycin (4.7%). Resistance to cefixime (0.6%, n = 1 isolate), azithromycin (0.6%, n = 1), and gentamicin (0.6%, n = 1) was rare. No resistance to ceftriaxone or spectinomycin was found. However, the proportion of isolates with decreased susceptibility (MIC = 0.125 mg/L) to ceftriaxone and cefixime was 12.8 and 11.5%, respectively. Gonococcal isolates were assigned 69 sequence types, of which 52 (75.4%) were new. Conclusions: The gonococcal population in Kyrgyzstan in 2012 and 2017 showed a high genetic diversity. Ceftriaxone, 500-1000 mg, in combination with azithromycin 2 g or doxycycline, particularly when chlamydial infection has not been excluded, should be recommended as empiric first-line treatment. Spectinomycin 2 g could be an alternative treatment, and given with azithromycin 2 g if pharyngeal gonorrhoea has not been excluded. Fluoroquinolones, aminoglycosides, benzylpenicillin, or tetracyclines should not be used for empiric treatment of gonorrhoea in Kyrgyzstan. Timely updating and high compliance to national gonorrhoea treatment guidelines based on quality-assured AMR data is imperative. Expanded and improved gonococcal AMR surveillance in Kyrgyzstan is crucial. | G36: Yes | H36: No | I36: No | J36: This is the first study reporting AMR and molecular epidemiology data from Kyrgyzstan.
A37: 30657464 | B37: Resistance Profile of Neisseria gonorrhoeae in KwaZulu-Natal, South Africa Questioning the Effect of the Currently Advocated Dual Therapy | C37: 1) Reporte de cepas resistentes | F37: Background: We report on the antimicrobial resistance profile of Neisseria gonorrhoeae isolates and the distribution of tetM genes in isolates with high-level tetracycline resistance in KwaZulu-Natal, South Africa. Methods: Male and female patients presenting with urethral and/or vaginal discharge were recruited into the study. Urethral and cervical secretions were cultured on New York City agar. Confirmatory tests for N. gonorrhoeae included Gram stain, catalase, oxidase, and carbohydrate utilization tests. Beta-lactamase was tested by means of the chromogenic cephalosporin test. Minimum inhibitory concentrations were determined using agar dilution with multipoint inoculation. Polymerase chain reaction with gel electrophoresis was used to detect the presence and type of the tetM gene. Results: N. gonorrhoeae was isolated from the specimens of 319 (26%) of the 1220 recruited patients. Of these 319 isolates, 71% were resistant to 3 or more drugs. Resistance to azithromycin was found in 68% of the isolates. All isolates showed high-level tetracycline resistance with minimum inhibitory concentration values of 16 and 32 mg/mL. The tetM gene was present in 293 (92%). The American type was found in 264 (90%) and the Dutch type in 29 (10%). Twenty-six (8%) did not carry a tetM gene. Conclusions: The current syndromic management with dual ceftriaxone and azithromycin is due to the high level of azithromycin resistance factually single-drug therapy. High-level tetracycline resistance based on a resistance mechanism other than ribosome protection by the tetM gene product is present in N. gonorrhoeae infecting South African patients. | G37: Yes | H37: No | I37: No | J37: This study assessed the antimicrobial resistance of Neisseria gonorrhoeae and distribution of tetM genes in isolates with high-level tetracycline resistance in KwaZulu-Natal, South Africa
A38: 30727713 | B38: Typing and antimicrobial susceptibility of 134 Neisseria gonorrhoeae strains from Southern Spain | C38: 1) Reporte de cepas resistentes | F38: Objective: Last guidelines have recommended the introduction of dual antimicrobial therapy in order to avoid treatment failure. In the present report, the susceptibility to some antibiotics was evaluated, and the typing of Neisseria gonorrhoeae strains was performed. Methods: Gonococcal isolates were tested for susceptibility according to the recommendations of both CLSI and EUCAST. A total of 134 isolates were typed by the NG-MAST technique. Results: Seventy-two different N. gonorrhoeae types were found, and the most frequent types obtained were ST 1407, ST 14958, ST 7192, ST 13251 and ST 5405. If CLSI/EUCAST criteria were applied, a ST 9807 type was found nonsusceptible to ceftriaxone and cefixime (MIC 0.5 mg/L), and a ST 12800 type was found nonsusceptible only to cefixime (MIC 0.25 mg/L). When only EUCAST breakpoints were taken into account, three strains were also resistant to cefixime (MIC 0.25 mg/L) and three isolates were resistant to ceftriaxone (MIC 0.19, 0.16 and 0.25 mg/L, respectively). The majority of strains were resistant to ciprofloxacin (68.6%), and all N. gonorrhoeae strains were susceptible to spectinomycin; 9.7% of isolates were resistant to azithromycin. Conclusions: Molecular typing may be a useful tool to predict antimicrobial resistance. High rates of resistance to penicillin, tetracycline and ciprofloxacin were found in this area. It is highly recommended to carry out antimicrobial susceptibility in all gonorrhoea cases and to identify treatment failures to verify emerging resistance. | G38: Yes | H38: No | I38: No | J38: To assess the antimicrobial susceptibility and molecular typing of Neisseria gonorrhoeae strains in light of updated guidelines recommending dual therapy to prevent treatment failure.
A39: 30789143 | B39: Emergence and Spread of Cephalosporin-Resistant Neisseria gonorrhoeae with Mosaic penA Alleles, South Korea, 2012-2017 | C39: 1) Reporte de cepas resistentes | F39: In South Korea, surveillance of antimicrobial drug resistance in Neisseria gonorrhoeae is extremely limited. We describe the emergence and subsequent national spread of N. gonorrhoeae strains with mosaic penA alleles associated with decreased susceptibility and resistance to extended-spectrum cephalosporins. From 2012 through 2017, the proportion of mosaic penA alleles in gonococcal-positive nucleic acid amplification test (NAAT) specimens across South Korea increased from 1.1% to 23.9%. Gonococcal strains with mosaic penA alleles emerged in the international hubs of Seoul in Gyeonggi Province and Busan in South Gyeongsang Province and subsequently spread across South Korea. Most common was mosaic penA-10.001 (n = 572 isolates; 94.7%), which is associated with cefixime resistance. We also identified mosaic penA-34.001 and penA-60.001, both of which are associated with multidrug-resistant gonococcal strains and spread of cefixime and ceftriaxone resistance. Implementation of molecular resistance prediction from N. gonorrhoeae-positive nucleic acid amplification test specimens is imperative in South Korea and internationally. | G39: Yes | H39: No | I39: No | J39: Spread of mosaic penA alleles linked to cephalosporin resistance in South Korea highlights need for molecular resistance monitoring
A40: 27499432 | B40: In vitro growth of multidrug-resistant Neisseria gonorrhoeae isolates is inhibited by ETX0914, a novel spiropyrimidinetrione | C40: 2) Nuevos tratamientos | D40: 2c) Droga de diseño | F40: Antimicrobial resistance in Neisseria gonorrhoeae has severely limited the number of treatment options, and the emergence of extended-spectrum cephalosporin resistance threatens the effectiveness of the last remaining recommended treatment regimen. This study assessed the in vitro susceptibility of N. gonorrhoeae to ETX0914, a novel spiropyrimidinetrione that inhibits DNA biosynthesis. In vitro activity was determined by agar dilution against 100 N. gonorrhoeae isolates collected from men presenting with urethritis in the USA during 2012-2013 through the Gonococcal Isolate Surveillance Project. The minimum inhibitory concentration (MIC) that inhibited growth in 50% (MIC50) and 90% (MIC90) of isolates was calculated for each antimicrobial agent. ETX0914 demonstrated a high level of antimicrobial activity against N. gonorrhoeae, including isolates with decreased susceptibility or resistance to currently available agents. The ability of ETX0914 to inhibit the growth of N. gonorrhoeae was similar to ceftriaxone, which is currently recommended in combination with azithromycin to treat gonorrhoea. The data presented in this study strongly suggest that ETX0914 should be evaluated in a clinical trial for the treatment of N. gonorrhoeae. | G40: No | H40: Yes | I40: No | J40: ETX0914 showed strong in vitro activity vs. N. gonorrhoeae, including resistant strains, suggesting potential for clinical evaluation
A41: 31407661 | B41: Genetic Characterization and Enhanced Surveillance of Ceftriaxone-Resistant Neisseria gonorrhoeae Strain, Alberta, Canada, 2018 | C41: 1) Reporte de cepas resistentes | F41: In July 2018, a case of Neisseria gonorrhoeae associated with ceftriaxone treatment failure was identified in Alberta, Canada. We identified the isolate and nucleic acid amplification testing (NAAT) specimen as the ceftriaxone-resistant strain multilocus sequence type 1903/NG-MAST 3435/NG-STAR 233, originally identified in Japan (FC428), with the same penA 60.001 mosaic allele and genetic resistance determinants. Core single-nucleotide variant (SNV) analysis identified 13 SNVs between this isolate and FC428. Culture-independent surveillance by PCR for the A311V mutation in the penA allele and N. gonorrhoeae multiantigen sequence typing directly from NAAT transport media positive for N. gonorrhoeae by NAAT did not detect spread of the strain. We identified multiple sequence types not previously detected in Alberta by routine surveillance. This case demonstrates the benefit of using culture-independent methods to enhance detection, public health investigations, and surveillance to address this global threat. | G41: Yes | H41: No | I41: No | J41: Ceftriaxone-resistant FC428 strain detected in Canada; genetic analysis confirmed match to original Japan isolate with penA 60.001 allele
