Workbook
Name categoria: categorias!$A:$A
Name Estado: categorias!$C$2:$C$65536
Name EXCL: Excluidas!$A:$K
Name EXCLUIDAS: Excluidas!$A$1:$K$463
Name KEYWORDS: 'Palabras claves'!$A:$K
Name NgonorreaePost: '2017-2022'!#REF!
Name NgonorreaePre: '2012-2017'!$A$1:$K$534
Name PalabrasClave: 'Palabras claves'!$K$1:$K$1371
Name POST: '2017-2022'!$A:$K
Name POSTALERTA: '2017-2022'!$A$1:$B$857
Name PRE: '2012-2017'!$A:$K
Name PREALERTA: '2012-2017'!$A$1:$O$540
Name SegmentaciónDeDatos_Alerta1: #REF!
Name SegmentaciónDeDatos_KeyWords: #REF!
Name SegmentaciónDeDatos_PubYear: #REF!
Name subcategoria: categorias!$B:$B
Name TablaNgonoreae: '2012-2022'!$A$1:$K$4211

Sheet DashBoard
C2: Shigella spp 2012-2022
C3: Total de publicaciones de | F3: =C2 -> Shigella spp 2012-2022 | G3: : | H3: =COUNTA('2012-2022'!A$1:A$5016)-1 -> 5015
D5: Publicaciones por Año | I5: Categorías y Subcategorías
D17: Publicaciones por mes
C35: =IFERROR(__xludf.DUMMYFUNCTION("UNIQUE('2012-2022'!N:N)"),"Categoria") -> Categoria
C36: =IFERROR(__xludf.DUMMYFUNCTION("""COMPUTED_VALUE"""),"2) Nuevos tratamientos ") -> 2) Nuevos tratamientos | F36: =COUNTIF('2012-2022'!N:N,C36) -> 71
C37: =IFERROR(__xludf.DUMMYFUNCTION("""COMPUTED_VALUE"""),"")
C39: =IFERROR(__xludf.DUMMYFUNCTION("""COMPUTED_VALUE""")," 1) Reporte de cepas resistentes") -> 1) Reporte de cepas resistentes | F39: =COUNTIF('2012-2022'!N:N,C39) -> 29
C40: =IFERROR(__xludf.DUMMYFUNCTION("""COMPUTED_VALUE"""),"4) otros") -> 4) otros | F40: =COUNTIF('2012-2022'!N:N,C40) -> 29
C41: =IFERROR(__xludf.DUMMYFUNCTION("""COMPUTED_VALUE"""),"3) Inmunizacióm") -> 3) Inmunizacióm | F41: =COUNTIF('2012-2022'!N:N,C41) -> 12

Sheet categorias
A1: Categorias | B1: Subcategorias | C1: Estados
A2: 1) Reporte de cepas resistentes | B2: 2a) Productos naturales | C2: Revisar
A3: 2) Nuevos tratamientos | B3: 2b) Péptidos | C3: Listo
A4: 3) Inmunizacióm | B4: 2c) Droga de diseño | C4: Excluir
A5: 4) otros | B5: 2d) Anticuerpos | C5: Otros-A
B6: 2e) Bacteriófagos | C6: Otros-B
B7: 2f) Estrategias antivirulencia | C7: Otros-C
B8: 2g) nueva combinación de ATB | C8: Otros-D

Sheet TablasDinamicas
B1: Etiquetas de fila | C1: Cuenta de Title | E1: Cuenta de Title | I1: Categoria | J1: subcategoria | K1: Cuenta de Title
B2: PreAlerta | C2: 1822 | E2: PubYear | F2: PubMonth | G2: Total | I2: 1) Interacción huésped-patógeno | J2: (en blanco) | K2: 2 | L2: 1) Interacción huésped-patógeno | M2: (en blanco) | N2: =GETPIVOTDATA("Title",$I$1,"Categoria",L2,"subcategoria",M2) -> #REF! | P2: Etiquetas de fila | Q2: Cuenta de Title | S2: Etiquetas de fila | T2: Cuenta de Title | V2: Etiquetas de fila | W2: Cuenta de Title
B3: PostAlerta | C3: 2711 | E3: 2013 | F3: Jan | G3: 34 | I3: Total 1) Interacción huésped-patógeno | K3: 2 | L3: 2) Reporte de cepas resistentes | M3: (en blanco) | N3: =GETPIVOTDATA("Title",$I$1,"Categoria",L3,"subcategoria",M3) -> #REF! | P3: (en blanco) | Q3: 5015 | S3: 2012 | T3: 217 | V3: S/PalabrasClaves | W3: 3858
B4: Excluido | C4: 482 | F4: Feb | G4: 23 | I4: 2) Reporte de cepas resistentes | J4: (en blanco) | K4: 2 | L4: 3) Casos clínicos | M4: (en blanco) | N4: =GETPIVOTDATA("Title",$I$1,"Categoria",L4,"subcategoria",M4) -> #REF! | P4: Total general | Q4: 5015 | S4: 2013 | T4: 343 | V4: Excluido | W4: 364
B5: Total general | C5: 5015 | F5: Mar | G5: 40 | I5: Total 2) Reporte de cepas resistentes | K5: 2 | L5: 4) Nuevos tratamientos | M5: 4a) Productos naturales | N5: =GETPIVOTDATA("Title",$I$1,"Categoria",L5,"subcategoria",M5) -> #REF! | S5: 2014 | T5: 316 | V5: PostAlerta | W5: 2095
F6: Apr | G6: 28 | I6: 3) Casos clínicos | J6: (en blanco) | K6: 1 | L6: 4) Nuevos tratamientos | M6: 4b) Péptidos | N6: =GETPIVOTDATA("Title",$I$1,"Categoria",L6,"subcategoria",M6) -> #REF! | S6: 2015 | T6: 297 | V6: PreAlerta | W6: 1399
F7: May | G7: 29 | I7: Total 3) Casos clínicos | K7: 1 | L7: 4) Nuevos tratamientos | M7: 4c) Droga de diseño | N7: =GETPIVOTDATA("Title",$I$1,"Categoria",L7,"subcategoria",M7) -> #REF! | S7: 2016 | T7: 314 | V7: Total general | W7: 3858
F8: Jun | G8: 24 | I8: 4) Nuevos tratamientos | J8: 4a) Productos naturales | K8: 1 | L8: 4) Nuevos tratamientos | M8: 4d) Anticuerpos | N8: =GETPIVOTDATA("Title",$I$1,"Categoria",L8,"subcategoria",M8) -> #REF! | S8: 2017 | T8: 337
F9: Jul | G9: 33 | J9: 4b) Péptidos | K9: 1 | L9: 4) Nuevos tratamientos | M9: 4e) Bacteriófagos | N9: =GETPIVOTDATA("Title",$I$1,"Categoria",L9,"subcategoria",M9) -> #REF! | S9: 2018 | T9: 346
F10: Aug | G10: 42 | J10: 4c) Droga de diseño | K10: 2 | L10: 4) Nuevos tratamientos | M10: 4f) Estrategias antivirulencia | N10: =GETPIVOTDATA("Title",$I$1,"Categoria",L10,"subcategoria",M10) -> #REF! | S10: 2019 | T10: 392
F11: Sep | G11: 30 | J11: 4d) Anticuerpos | K11: 1 | S11: 2020 | T11: 454
F12: Oct | G12: 36 | J12: 4e) Bacteriófagos | K12: 1 | S12: 2021 | T12: 536
F13: Nov | G13: 23 | I13: Total 4) Nuevos tratamientos | K13: 6 | S13: 2022 | T13: 293
F14: Dec | G14: 51 | I14: (en blanco) | J14: (en blanco) | K14: 3847 | S14: 2023 | T14: 13
F15: (en blanco) | G15: 35 | I15: Total (en blanco) | K15: 3847 | S15: Total general | T15: 3858
F16: Summer | G16: 1 | I16: Total general | K16: 3858
F17: Autumn | G17: 1
E18: Total 2013 | G18: 430
E19: Total general | G19: 430

Sheet 2012-2022
A1: PMID | B1: Title | C1: Authors | D1: Citation | E1: First Author | F1: Journal/Book | G1: Publication Year | H1: Create Date | I1: PMCID | J1: NIHMS ID | K1: DOI | L1: Alerta | M1: KeyWords | N1: Categoria | O1: Subcategorias | P1: fecha de publicación | Q1: Estado | R1: PubYear | S1: PubMonth | T1: Abstract | U1: 1) Antimicrobial Resistance stain | V1: 2) New treatment | W1: 3) Immunization | X1: Human_summary
A2: 35174771 | B2: In vitro and in silico screening of novel typhoid drugs from endangered herb (Enicostema axillare) | C2: Perumal S, Gopal Samy M, Subramanian D. | D2: J Biomol Struct Dyn. 2023 Apr;41(7):2926-2936. doi: 10.1080/07391102.2022.2041488. Epub 2022 Feb 17. | E2: Perumal S | F2: J Biomol Struct Dyn | G2: 2023 | H2: 44609 | K2: 10.1080/07391102.2022.2041488 | L2: =IF(ISNUMBER(VLOOKUP(A2,EXCL,1,FALSE)),"Excluido",IF(ISNUMBER(VLOOKUP(A2,POST,1,FALSE)),"PostAlerta",IF(ISNUMBER(VLOOKUP(A2,PRE,1,FALSE)),"PreAlerta",""))) -> PostAlerta | M2: =IF(ISNUMBER(VLOOKUP(A2,KEYWORDS,1,FALSE)),"C/PalabrasClaves","S/PalabrasClaves") -> S/PalabrasClaves | N2: 2) Nuevos tratamientos | O2: 2a) Productos naturales | P2: 2023 Apr | Q2: Listo | R2: =LEFT(P2,4) -> 2023 | S2: Apr | T2: In the present study, antibacterial activity of swertiamarin from Enicostema axillare (Lam) was checked against three different human gram-negative pathogens namely Salmonella typhi, Klebsiella pneumoniae and Shigella flexneri. Minimum inhibitory concentration assay revealed low dose and efficient activity of swertiamarin on the above said pathogens. Though swertiamarin is a well-studied and characterized compound, there is no experimental proof available for its antibacterial activity. To gain more insight about the antibacterial efficiency of swertiamarin against typhoid causing S. typhi, a comparative molecular docking of S. typhi OmpF (3NSG) was performed with swertiamarin and other typhoid drugs available in the market which exposed better activity strength of swertiamarin compared with that of the other drugs. Further, molecular dynamics of S. typhi OmpF-swertiamarin shows good flexibility and stability at 100 ns. The outcome of this work will definitely provide an idea of using very low dose of swertiamarin as a potent and promising drug against typhoid fever.Communicated by Ramaswamy H. Sarma. | U2: No | V2: Yes | W2: No | X2: The study evaluates the antibacterial activity of swertiamarin as a potential drug against human pathogens, especially Salmonella typhi. | Y2: =IF(ISNUMBER(SEARCH("combination", B2)), "combination ", "")
A3: 36908341 | B3: Freeze dried probiotic carrot juice powder for better storage stability of probiotic | C3: Rishabh D, Athira A, Preetha R, Nagamaniammai G. | D3: J Food Sci Technol. 2023 Mar;60(3):916-924. doi: 10.1007/s13197-021-05259-2. Epub 2021 Sep 6. | E3: Rishabh D | F3: J Food Sci Technol | G3: 2023 | H3: 44998 | I3: PMC9998781 | K3: 10.1007/s13197-021-05259-2 | L3: =IF(ISNUMBER(VLOOKUP(A3,EXCL,1,FALSE)),"Excluido",IF(ISNUMBER(VLOOKUP(A3,POST,1,FALSE)),"PostAlerta",IF(ISNUMBER(VLOOKUP(A3,PRE,1,FALSE)),"PreAlerta",""))) -> PostAlerta | M3: =IF(ISNUMBER(VLOOKUP(A3,KEYWORDS,1,FALSE)),"C/PalabrasClaves","S/PalabrasClaves") -> S/PalabrasClaves | N3: =IF(ISNUMBER(SEARCH("TREATMENT", B3)), "4) Nuevos tratamientos", "") | P3: 2023 Mar | Q3: Excluir | R3: =LEFT(P3,4) -> 2023 | S3: Mar | Y3: =IF(ISNUMBER(SEARCH("combination", B3)), "combination ", "")
A4: 34453485 | B4: Green synthesis and characterization of Solanum xanthocarpum capped silver nanoparticles and its antimicrobial effect on multidrug-resistant bacterial (MDR) isolates | C4: Pungle R, Nile SH, Kharat AS. | D4: Chem Biol Drug Des. 2023 Mar;101(3):469-478. doi: 10.1111/cbdd.13945. Epub 2021 Oct 1. | E4: Pungle R | F4: Chem Biol Drug Des | G4: 2023 | H4: 44436 | K4: 10.1111/cbdd.13945 | L4: =IF(ISNUMBER(VLOOKUP(A4,EXCL,1,FALSE)),"Excluido",IF(ISNUMBER(VLOOKUP(A4,POST,1,FALSE)),"PostAlerta",IF(ISNUMBER(VLOOKUP(A4,PRE,1,FALSE)),"PreAlerta",""))) -> PostAlerta | M4: =IF(ISNUMBER(A4),(IF(ISNUMBER(VLOOKUP(A4,KEYWORDS,1,FALSE)),"C/PalabrasClaves","S/PalabrasClaves")),"") -> C/PalabrasClaves | N4: 2) Nuevos tratamientos | O4: 2b) Péptidos | P4: 2023 Mar | Q4: Listo | R4: =LEFT(P4,4) -> 2023 | S4: Mar | T4: Plant extracts and their bioactive compounds are considered as the promising options for green synthesis of nanoparticles instead expensive and hazardous materials. Here, Solanum xanthocarpum fruit was used for synthesis of silver nanoparticles (AgNP). The synthesized AgNPs were characterized by using chromatographic and spectroscopic analytical methods. AgNPs were confirmed by UV-visible absorbance at 420-470 nm. TEM analysis showed AgNP with 22.45 nm average size. X-ray diffraction studies revealed the crystalline and face central cubic nature of AgNPs. FTIR analysis revealed functional group present over AgNPs. The aminodiphenyl acetic acid, clomipramine, and fonisopril from fruit extracts were found to be major capping agents on AgNPs as a result of analysis by HRLC-MS. All clinical isolates showed resistance for ampicilline, amoxyclav, niladixic acid, and sulphafurazole, suggesting multidrug resistance. The results showed that all isolates were sensitive to AgNPs synthesized fruit extracts. On the contrary, all isolates were resistant to whole S. xanthocarpum fruit extracts alone. The antimicrobial activity of AgNP was explored against multidrug-resistant (MDR) Gram-negative clinical isolates including Escherichia coli, Shigella spp., Aeronomonas spp. and Pseudomonas spp. MIC values ranged between 1.25 mg/ml and 2.5 mg/ml at 8 McFarland's standards. Minimum bactericidal concentration was found to be in between 2.5 mg/ml to 5 mg/ml. Nanoparticles synthesized from fruit extract of S. xanthocarpum containing aminodiphenyl acetic acid, clomipramine, and fonisopril metabolites exhibit promising antimicrobial activity against MDR Gram-negative clinical isolates. | U4: No | V4: Yes | W4: No | X4: Silver nanoparticles synthesized from Solanum xanthocarpum fruit show promising antimicrobial activity against multidrug-resistant Gram-negative isolates. | Y4: =IF(ISNUMBER(SEARCH("combination", B4)), "combination ", "")
A5: 36817108 | B5: Analysis of microbial diversity in the feces of Arborophila rufipectus | C5: Ma X, Li J, Chen B, Li X, Ling Z, Feng S, Cao S, Zuo Z, Deng J, Huang X, Cai D, Wen Y, Zhao Q, Wang Y, Zhong Z, Peng G, Jiang Y, Gu Y. | D5: Front Microbiol. 2023 Feb 2;13:1075041. doi: 10.3389/fmicb.2022.1075041. eCollection 2022. | E5: Ma X | F5: Front Microbiol | G5: 2023 | H5: 44980 | I5: PMC9932278 | K5: 10.3389/fmicb.2022.1075041 | L5: =IF(ISNUMBER(VLOOKUP(A5,EXCL,1,FALSE)),"Excluido",IF(ISNUMBER(VLOOKUP(A5,POST,1,FALSE)),"PostAlerta",IF(ISNUMBER(VLOOKUP(A5,PRE,1,FALSE)),"PreAlerta",""))) -> PostAlerta | M5: =IF(ISNUMBER(A5),(IF(ISNUMBER(VLOOKUP(A5,KEYWORDS,1,FALSE)),"C/PalabrasClaves","S/PalabrasClaves")),"") -> S/PalabrasClaves | N5: =IF(ISNUMBER(SEARCH("TREATMENT", B5)), "4) Nuevos tratamientos", "") | P5: 2023 Feb 2 | Q5: Excluir | R5: =LEFT(P5,4) -> 2023 | S5: Feb | Y5: =IF(ISNUMBER(SEARCH("combination", B5)), "combination ", "")
A6: 36776392 | B6: Recent updates on correlates of vaccine-induced protection | C6: Plotkin SA. | D6: Front Immunol. 2023 Jan 27;13:1081107. doi: 10.3389/fimmu.2022.1081107. eCollection 2022. | E6: Plotkin SA | F6: Front Immunol | G6: 2023 | H6: 44970 | I6: PMC9912984 | K6: 10.3389/fimmu.2022.1081107 | L6: =IF(ISNUMBER(VLOOKUP(A6,EXCL,1,FALSE)),"Excluido",IF(ISNUMBER(VLOOKUP(A6,POST,1,FALSE)),"PostAlerta",IF(ISNUMBER(VLOOKUP(A6,PRE,1,FALSE)),"PreAlerta",""))) -> PostAlerta | M6: =IF(ISNUMBER(A6),(IF(ISNUMBER(VLOOKUP(A6,KEYWORDS,1,FALSE)),"C/PalabrasClaves","S/PalabrasClaves")),"") -> S/PalabrasClaves | P6: 2023 Jan 27 | Q6: Excluir | R6: =LEFT(P6,4) -> 2023 | S6: Jan | Y6: =IF(ISNUMBER(SEARCH("combination", B6)), "combination ", "")
A7: 36755580 | B7: Dysbiosis of gut microbiota and decreased propionic acid associated with metabolic abnormality in Cushing's syndrome | C7: Zhang Q, Hu WM, Deng YL, Wan JJ, Wang YJ, Jin P. | D7: Front Endocrinol (Lausanne). 2023 Jan 23;13:1095438. doi: 10.3389/fendo.2022.1095438. eCollection 2022. | E7: Zhang Q | F7: Front Endocrinol (Lausanne) | G7: 2023 | H7: 44966 | I7: PMC9901362 | K7: 10.3389/fendo.2022.1095438 | L7: =IF(ISNUMBER(VLOOKUP(A7,EXCL,1,FALSE)),"Excluido",IF(ISNUMBER(VLOOKUP(A7,POST,1,FALSE)),"PostAlerta",IF(ISNUMBER(VLOOKUP(A7,PRE,1,FALSE)),"PreAlerta",""))) -> PostAlerta | M7: =IF(ISNUMBER(A7),(IF(ISNUMBER(VLOOKUP(A7,KEYWORDS,1,FALSE)),"C/PalabrasClaves","S/PalabrasClaves")),"") -> S/PalabrasClaves | N7: =IF(ISNUMBER(SEARCH("TREATMENT", B7)), "4) Nuevos tratamientos", "") | P7: 2023 Jan 23 | Q7: Excluir | R7: =LEFT(P7,4) -> 2023 | S7: Jan | Y7: =IF(ISNUMBER(SEARCH("combination", B7)), "combination ", "")
A8: 36741899 | B8: Metagenomic insights into the relationship between gut microbiota and residual feed intake of small-sized meat ducks | C8: Bai H, Shi L, Guo Q, Jiang Y, Li X, Geng D, Wang C, Bi Y, Wang Z, Chen G, Xue F, Chang G. | D8: Front Microbiol. 2023 Jan 18;13:1075610. doi: 10.3389/fmicb.2022.1075610. eCollection 2022. | E8: Bai H | F8: Front Microbiol | G8: 2023 | H8: 44963 | I8: PMC9889972 | K8: 10.3389/fmicb.2022.1075610 | L8: =IF(ISNUMBER(VLOOKUP(A8,EXCL,1,FALSE)),"Excluido",IF(ISNUMBER(VLOOKUP(A8,POST,1,FALSE)),"PostAlerta",IF(ISNUMBER(VLOOKUP(A8,PRE,1,FALSE)),"PreAlerta",""))) -> PostAlerta | M8: =IF(ISNUMBER(A8),(IF(ISNUMBER(VLOOKUP(A8,KEYWORDS,1,FALSE)),"C/PalabrasClaves","S/PalabrasClaves")),"") -> S/PalabrasClaves | N8: =IF(ISNUMBER(SEARCH("TREATMENT", B8)), "4) Nuevos tratamientos", "") | P8: 2023 Jan 18 | Q8: Excluir | R8: =LEFT(P8,4) -> 2023 | S8: Jan | Y8: =IF(ISNUMBER(SEARCH("combination", B8)), "combination ", "")
A9: 36713461 | B9: Fecal microbiota transplantation and short-chain fatty acids reduce sepsis mortality by remodeling antibiotic-induced gut microbiota disturbances | C9: Lou X, Xue J, Shao R, Yang Y, Ning D, Mo C, Wang F, Chen G. | D9: Front Immunol. 2023 Jan 11;13:1063543. doi: 10.3389/fimmu.2022.1063543. eCollection 2022. | E9: Lou X | F9: Front Immunol | G9: 2023 | H9: 44956 | I9: PMC9874322 | K9: 10.3389/fimmu.2022.1063543 | L9: =IF(ISNUMBER(VLOOKUP(A9,EXCL,1,FALSE)),"Excluido",IF(ISNUMBER(VLOOKUP(A9,POST,1,FALSE)),"PostAlerta",IF(ISNUMBER(VLOOKUP(A9,PRE,1,FALSE)),"PreAlerta",""))) -> PostAlerta | M9: =IF(ISNUMBER(A9),(IF(ISNUMBER(VLOOKUP(A9,KEYWORDS,1,FALSE)),"C/PalabrasClaves","S/PalabrasClaves")),"") -> C/PalabrasClaves | N9: =IF(ISNUMBER(SEARCH("TREATMENT", B9)), "4) Nuevos tratamientos", "") | P9: 2023 Jan 11 | Q9: Excluir | R9: =LEFT(P9,4) -> 2023 | S9: Jan | Y9: =IF(ISNUMBER(SEARCH("combination", B9)), "combination ", "")
A10: 36713168 | B10: Altered intestinal microbiota composition with epilepsy and concomitant diarrhea and potential indicator biomarkers in infants | C10: Liu T, Jia F, Guo Y, Wang Q, Zhang X, Chang F, Xie Y. | D10: Front Microbiol. 2023 Jan 11;13:1081591. doi: 10.3389/fmicb.2022.1081591. eCollection 2022. | E10: Liu T | F10: Front Microbiol | G10: 2023 | H10: 44956 | I10: PMC9874329 | K10: 10.3389/fmicb.2022.1081591 | L10: =IF(ISNUMBER(VLOOKUP(A10,EXCL,1,FALSE)),"Excluido",IF(ISNUMBER(VLOOKUP(A10,POST,1,FALSE)),"PostAlerta",IF(ISNUMBER(VLOOKUP(A10,PRE,1,FALSE)),"PreAlerta",""))) -> PostAlerta | M10: =IF(ISNUMBER(A10),(IF(ISNUMBER(VLOOKUP(A10,KEYWORDS,1,FALSE)),"C/PalabrasClaves","S/PalabrasClaves")),"") -> S/PalabrasClaves | N10: =IF(ISNUMBER(SEARCH("TREATMENT", B10)), "4) Nuevos tratamientos", "") | P10: 2023 Jan 11 | Q10: Excluir | R10: =LEFT(P10,4) -> 2023 | S10: Jan | Y10: =IF(ISNUMBER(SEARCH("combination", B10)), "combination ", "")
A11: 36704458 | B11: Alteration of the gut microbiota and metabolite phenylacetylglutamine in patients with severe chronic heart failure | C11: Zhang Z, Cai B, Sun Y, Deng H, Wang H, Qiao Z. | D11: Front Cardiovasc Med. 2023 Jan 10;9:1076806. doi: 10.3389/fcvm.2022.1076806. eCollection 2022. | E11: Zhang Z | F11: Front Cardiovasc Med | G11: 2023 | H11: 44953 | I11: PMC9871785 | K11: 10.3389/fcvm.2022.1076806 | L11: =IF(ISNUMBER(VLOOKUP(A11,EXCL,1,FALSE)),"Excluido",IF(ISNUMBER(VLOOKUP(A11,POST,1,FALSE)),"PostAlerta",IF(ISNUMBER(VLOOKUP(A11,PRE,1,FALSE)),"PreAlerta",""))) -> PostAlerta | M11: =IF(ISNUMBER(A11),(IF(ISNUMBER(VLOOKUP(A11,KEYWORDS,1,FALSE)),"C/PalabrasClaves","S/PalabrasClaves")),"") -> S/PalabrasClaves | N11: =IF(ISNUMBER(SEARCH("TREATMENT", B11)), "4) Nuevos tratamientos", "") | P11: 2023 Jan 10 | Q11: Excluir | R11: =LEFT(P11,4) -> 2023 | S11: Jan | Y11: =IF(ISNUMBER(SEARCH("combination", B11)), "combination ", "")
A12: 36704106 | B12: Gut microbiota signatures in tissues of the colorectal polyp and normal colorectal mucosa, and faeces | C12: Zhong X, Wang Y, Xu J, Cao H, Zhang F, Wang X. | D12: Front Cell Infect Microbiol. 2023 Jan 10;12:1054808. doi: 10.3389/fcimb.2022.1054808. eCollection 2022. | E12: Zhong X | F12: Front Cell Infect Microbiol | G12: 2023 | H12: 44953 | I12: PMC9871776 | K12: 10.3389/fcimb.2022.1054808 | L12: =IF(ISNUMBER(VLOOKUP(A12,EXCL,1,FALSE)),"Excluido",IF(ISNUMBER(VLOOKUP(A12,POST,1,FALSE)),"PostAlerta",IF(ISNUMBER(VLOOKUP(A12,PRE,1,FALSE)),"PreAlerta",""))) -> Excluido | M12: =IF(ISNUMBER(A12),(IF(ISNUMBER(VLOOKUP(A12,KEYWORDS,1,FALSE)),"C/PalabrasClaves","S/PalabrasClaves")),"") -> S/PalabrasClaves | N12: =IF(ISNUMBER(SEARCH("TREATMENT", B12)), "4) Nuevos tratamientos", "") | P12: 2023 Jan 10 | Q12: Excluir | R12: =LEFT(P12,4) -> 2023 | S12: Jan | Y12: =IF(ISNUMBER(SEARCH("combination", B12)), "combination ", "")
A13: 36687653 | B13: Traditional Chinese medicine improves myasthenia gravis by regulating the symbiotic homeostasis of the intestinal microbiota and host | C13: Zhao M, Liu L, Liu F, Liu L, Liu Z, Gao Y, Cao J. | D13: Front Microbiol. 2023 Jan 6;13:1082565. doi: 10.3389/fmicb.2022.1082565. eCollection 2022. | E13: Zhao M | F13: Front Microbiol | G13: 2023 | H13: 44949 | I13: PMC9852828 | K13: 10.3389/fmicb.2022.1082565 | L13: =IF(ISNUMBER(VLOOKUP(A13,EXCL,1,FALSE)),"Excluido",IF(ISNUMBER(VLOOKUP(A13,POST,1,FALSE)),"PostAlerta",IF(ISNUMBER(VLOOKUP(A13,PRE,1,FALSE)),"PreAlerta",""))) -> PostAlerta | M13: =IF(ISNUMBER(A13),(IF(ISNUMBER(VLOOKUP(A13,KEYWORDS,1,FALSE)),"C/PalabrasClaves","S/PalabrasClaves")),"") -> S/PalabrasClaves | N13: =IF(ISNUMBER(SEARCH("TREATMENT", B13)), "4) Nuevos tratamientos", "") | P13: 2023 Jan 6 | Q13: Excluir | R13: =LEFT(P13,4) -> 2023 | S13: Jan | Y13: =IF(ISNUMBER(SEARCH("combination", B13)), "combination ", "")
A14: 36687673 | B14: Lacticaseibacillus rhamnosus Hao9 exerts antidiabetic effects by regulating gut microbiome, glucagon metabolism, and insulin levels in type 2 diabetic mice | C14: Han M, Liao W, Dong Y, Bai C, Gai Z. | D14: Front Nutr. 2023 Jan 5;9:1081778. doi: 10.3389/fnut.2022.1081778. eCollection 2022. | E14: Han M | F14: Front Nutr | G14: 2023 | H14: 44949 | I14: PMC9849894 | K14: 10.3389/fnut.2022.1081778 | L14: =IF(ISNUMBER(VLOOKUP(A14,EXCL,1,FALSE)),"Excluido",IF(ISNUMBER(VLOOKUP(A14,POST,1,FALSE)),"PostAlerta",IF(ISNUMBER(VLOOKUP(A14,PRE,1,FALSE)),"PreAlerta",""))) -> PostAlerta | M14: =IF(ISNUMBER(A14),(IF(ISNUMBER(VLOOKUP(A14,KEYWORDS,1,FALSE)),"C/PalabrasClaves","S/PalabrasClaves")),"") -> S/PalabrasClaves | N14: =IF(ISNUMBER(SEARCH("TREATMENT", B14)), "4) Nuevos tratamientos", "") | P14: 2023 Jan 5 | Q14: Excluir | R14: =LEFT(P14,4) -> 2023 | S14: Jan | Y14: =IF(ISNUMBER(SEARCH("combination", B14)), "combination ", "")
A15: 36686167 | B15: Pueraria lobata polysaccharides alleviate neonatal calf diarrhea by modulating gut microbiota and metabolites | C15: Shen L, Shen Y, You L, Zhang Y, Su Z, Peng G, Deng J, Zuo Z, Zhong Z, Ren Z, Yu S, Zong X, Zhu Y, Cao S. | D15: Front Vet Sci. 2023 Jan 4;9:1024392. doi: 10.3389/fvets.2022.1024392. eCollection 2022. | E15: Shen L | F15: Front Vet Sci | G15: 2023 | H15: 44949 | I15: PMC9845628 | K15: 10.3389/fvets.2022.1024392 | L15: =IF(ISNUMBER(VLOOKUP(A15,EXCL,1,FALSE)),"Excluido",IF(ISNUMBER(VLOOKUP(A15,POST,1,FALSE)),"PostAlerta",IF(ISNUMBER(VLOOKUP(A15,PRE,1,FALSE)),"PreAlerta",""))) -> PostAlerta | M15: =IF(ISNUMBER(A15),(IF(ISNUMBER(VLOOKUP(A15,KEYWORDS,1,FALSE)),"C/PalabrasClaves","S/PalabrasClaves")),"") -> S/PalabrasClaves | N15: 2) Nuevos tratamientos | O15: 2b) Péptidos | P15: 2023 Jan 4 | Q15: Listo | R15: =LEFT(P15,4) -> 2023 | S15: Jan | T15: Introduction: Neonatal calf diarrhea (NCD) is still one of the most critical diseases in calf rearing. Studies have shown that Pueraria lobata polysaccharides (PLP) have intense antioxidant and immunomodulatory activity and modulate gut microbiota. This randomized clinical trial aimed to determine the effect of PLP on the neonatal calf with diarrhea. Methods: In this study, we recorded the fecal score of experimental calves, and calves with fecal scores ≥ 2 were determined as diarrhea and assessed their serum concentrations of inflammatory cytokines and oxidative damage-related indices. Fecal microbiota and metabolomics of diarrheal calves were further investigated. Results: Results showed that treatment with PLP decreased the fecal score of diarrheal calves, serum concentrations of IL-1β, TNF-γ, and malondialdehyde, and also elevated the level of superoxide dismutase. In addition, PLP treatment altered the gut microbiota, significantly increased the relative abundances of beneficial bacteria, including the phyla Bacteroidetes and Actinobacteria, the genus Collinsella, Megamonas, and Bifidobacterium; decreased the relative abundances of pathogenetic or diarrhea related bacteria, such as Proteobacteria, Fusobacteria, Clostridium_sensu_stricto_1, and Escherichia_Shigella. Moreover, PLP can increase the fecal concentrations of isobutyric acid, propionic acid, and pantothenate; lower the levels of PC [18:0/18:1(9Z)], arachidonic acid, and docosahexaenoic acid. Discussion: Thus, the results suggested that the PLP may perform the therapeutic activity via alleviating intestinal inflammation and regulating gut microbiota, avoiding further dysbiosis to restore the metabolism of gut microbiota, and finally promoting the recovery of diarrhea. The change further mitigated intestinal inflammation and oxidative damage in diarrheal calves. This indicated that PLP might be a promising treatment to attenuate diarrhea in neonatal calves. | U15: No | V15: Yes | W15: No | X15: PLP treatment reduced diarrhea, inflammation, and oxidative damage in neonatal calves by regulating gut microbiota and improving metabolism. | Y15: =IF(ISNUMBER(SEARCH("combination", B15)), "combination ", "")
A16: 34998646 | B16: An in vivo acute toxicity and anti-shigellosis effect of designed formulation on rat | C16: Singh D, Agarwal V. | D16: J Ayurveda Integr Med. 2023 Jan-Feb;14(1):100536. doi: 10.1016/j.jaim.2021.100536. Epub 2022 Jan 5. | E16: Singh D | F16: J Ayurveda Integr Med | G16: 2023 | H16: 44570 | I16: PMC10105236 | K16: 10.1016/j.jaim.2021.100536 | L16: =IF(ISNUMBER(VLOOKUP(A16,EXCL,1,FALSE)),"Excluido",IF(ISNUMBER(VLOOKUP(A16,POST,1,FALSE)),"PostAlerta",IF(ISNUMBER(VLOOKUP(A16,PRE,1,FALSE)),"PreAlerta",""))) -> PostAlerta | M16: =IF(ISNUMBER(A16),(IF(ISNUMBER(VLOOKUP(A16,KEYWORDS,1,FALSE)),"C/PalabrasClaves","S/PalabrasClaves")),"") -> S/PalabrasClaves | N16: 2) Nuevos tratamientos | O16: 2c) Droga de diseño | P16: 2023 Jan-Feb | Q16: Listo | R16: =LEFT(P16,4) -> 2023 | S16: Feb | T16: Introduction: Shigellosis is an intestinal disease and is one of the main causes of morbidity and mortality among children in India. The study aims to analyze the effect of the designed formulation on the hematological parameters in shigellosis-induced rats and assess the in vivo toxicity of this formulation. Methods: Male Wistar rats were housed in different groups. Group 1 is normal control; group 2 is diseased control; group 3 and group 4 diseased rats received 250 mg/kg formulation and 20 mg/kg body weight norfloxacin, respectively, orally once a day. Shigellosis was induced by a single intraperitoneal injection of Shigella flexneri, and bacterial load was calculated using the Shigella agar plate. On completion of the study, blood was collected for hematological as well as electrolyte analysis. Results: The in vivo acute toxicity results indicate that the formulation is safe up to 2000 mg/kg. Furthermore, formulation significantly (p < 0.05) decreases the bacterial load and increases the RBC, WBC, MCHC, platelet, hemoglobin, and electrolytes (Ca++, K+, and Na+) compared to diseased control. Conclusion: The results support the designed formulation's safety and therapeutic effects and support its use as an alternative medicine for treating shigellosis. | U16: No | V16: Yes | W16: No | X16: The formulation reduced bacterial load and improved RBC, WBC, MCHC, platelets, hemoglobin, and electrolytes in shigellosis-induced rats. | Y16: =IF(ISNUMBER(SEARCH("combination", B16)), "combination ", "")
A17: 36643973 | B17: Gut microbiota mediates positive effects of liraglutide on dyslipidemia in mice fed a high-fat diet | C17: Zhao L, Qiu Y, Zhang P, Wu X, Zhao Z, Deng X, Yang L, Wang D, Yuan G. | D17: Front Nutr. 2022 Dec 29;9:1048693. doi: 10.3389/fnut.2022.1048693. eCollection 2022. | E17: Zhao L | F17: Front Nutr | G17: 2022 | H17: 44942 | I17: PMC9835552 | K17: 10.3389/fnut.2022.1048693 | L17: =IF(ISNUMBER(VLOOKUP(A17,EXCL,1,FALSE)),"Excluido",IF(ISNUMBER(VLOOKUP(A17,POST,1,FALSE)),"PostAlerta",IF(ISNUMBER(VLOOKUP(A17,PRE,1,FALSE)),"PreAlerta",""))) -> PostAlerta | M17: =IF(ISNUMBER(A17),(IF(ISNUMBER(VLOOKUP(A17,KEYWORDS,1,FALSE)),"C/PalabrasClaves","S/PalabrasClaves")),"") -> S/PalabrasClaves | N17: =IF(ISNUMBER(SEARCH("TREATMENT", B17)), "4) Nuevos tratamientos", "") | P17: 2022 Dec 29 | Q17: Excluir | R17: =LEFT(P17,4) -> 2022 | S17: Dec | Y17: =IF(ISNUMBER(SEARCH("combination", B17)), "combination ", "")
A18: 36601354 | B18: Gut Microbiota Signature of Obese Adults Across Different Classifications | C18: Hu J, Guo P, Mao R, Ren Z, Wen J, Yang Q, Yan T, Yu J, Zhang T, Liu Y. | D18: Diabetes Metab Syndr Obes. 2022 Dec 29;15:3933-3947. doi: 10.2147/DMSO.S387523. eCollection 2022. | E18: Hu J | F18: Diabetes Metab Syndr Obes | G18: 2022 | H18: 44931 | I18: PMC9807070 | K18: 10.2147/DMSO.S387523 | L18: =IF(ISNUMBER(VLOOKUP(A18,EXCL,1,FALSE)),"Excluido",IF(ISNUMBER(VLOOKUP(A18,POST,1,FALSE)),"PostAlerta",IF(ISNUMBER(VLOOKUP(A18,PRE,1,FALSE)),"PreAlerta",""))) -> PostAlerta | M18: =IF(ISNUMBER(A18),(IF(ISNUMBER(VLOOKUP(A18,KEYWORDS,1,FALSE)),"C/PalabrasClaves","S/PalabrasClaves")),"") -> S/PalabrasClaves | N18: =IF(ISNUMBER(SEARCH("TREATMENT", B18)), "4) Nuevos tratamientos", "") | P18: 2022 Dec 29 | Q18: Excluir | R18: =LEFT(P18,4) -> 2022 | S18: Dec | Y18: =IF(ISNUMBER(SEARCH("combination", B18)), "combination ", "")
A19: 36632531 | B19: Digyalipopeptide A, an antiparasitic cyclic peptide from the Ghanaian Bacillus sp. strain DE2B | C19: Nartey AP, Dofuor AK, Owusu KBA, Camas AS, Deng H, Jaspars M, Kyeremeh K. | D19: Beilstein J Org Chem. 2022 Dec 28;18:1763-1771. doi: 10.3762/bjoc.18.185. eCollection 2022. | E19: Nartey AP | F19: Beilstein J Org Chem | G19: 2022 | H19: 44938 | I19: PMC9811306 | K19: 10.3762/bjoc.18.185 | L19: =IF(ISNUMBER(VLOOKUP(A19,EXCL,1,FALSE)),"Excluido",IF(ISNUMBER(VLOOKUP(A19,POST,1,FALSE)),"PostAlerta",IF(ISNUMBER(VLOOKUP(A19,PRE,1,FALSE)),"PreAlerta",""))) -> PostAlerta | M19: =IF(ISNUMBER(A19),(IF(ISNUMBER(VLOOKUP(A19,KEYWORDS,1,FALSE)),"C/PalabrasClaves","S/PalabrasClaves")),"") -> S/PalabrasClaves | N19: =IF(ISNUMBER(SEARCH("TREATMENT", B19)), "4) Nuevos tratamientos", "") | P19: 2022 Dec 28 | Q19: Excluir | R19: =LEFT(P19,4) -> 2022 | S19: Dec | Y19: =IF(ISNUMBER(SEARCH("combination", B19)), "combination ", "")
A20: 36619987 | B20: Epidemiological investigations of diarrhea in children in Praia city, Cape Verde | C20: Colito DA, Dorta-Guerra R, Da Costa Lima HS, Pina C, Gonçalves D, Valladares B, Foronda P. | D20: Front Microbiol. 2022 Dec 22;13:1059431. doi: 10.3389/fmicb.2022.1059431. eCollection 2022. | E20: Colito DA | F20: Front Microbiol | G20: 2022 | H20: 44935 | I20: PMC9814011 | K20: 10.3389/fmicb.2022.1059431 | L20: =IF(ISNUMBER(VLOOKUP(A20,EXCL,1,FALSE)),"Excluido",IF(ISNUMBER(VLOOKUP(A20,POST,1,FALSE)),"PostAlerta",IF(ISNUMBER(VLOOKUP(A20,PRE,1,FALSE)),"PreAlerta",""))) -> PostAlerta | M20: =IF(ISNUMBER(A20),(IF(ISNUMBER(VLOOKUP(A20,KEYWORDS,1,FALSE)),"C/PalabrasClaves","S/PalabrasClaves")),"") -> S/PalabrasClaves | P20: 2022 Dec 22 | Q20: Excluir | R20: =LEFT(P20,4) -> 2022 | S20: Dec | Y20: =IF(ISNUMBER(SEARCH("combination", B20)), "combination ", "")
A21: 36618686 | B21: Anti-diabetic prospects of dietary bio-actives of millets and the significance of the gut microbiota: A case of finger millet | C21: Singh V, Lee G, Son H, Amani S, Baunthiyal M, Shin JH. | D21: Front Nutr. 2022 Dec 22;9:1056445. doi: 10.3389/fnut.2022.1056445. eCollection 2022. | E21: Singh V | F21: Front Nutr | G21: 2022 | H21: 44935 | I21: PMC9815516 | K21: 10.3389/fnut.2022.1056445 | L21: =IF(ISNUMBER(VLOOKUP(A21,EXCL,1,FALSE)),"Excluido",IF(ISNUMBER(VLOOKUP(A21,POST,1,FALSE)),"PostAlerta",IF(ISNUMBER(VLOOKUP(A21,PRE,1,FALSE)),"PreAlerta",""))) -> Excluido | M21: =IF(ISNUMBER(A21),(IF(ISNUMBER(VLOOKUP(A21,KEYWORDS,1,FALSE)),"C/PalabrasClaves","S/PalabrasClaves")),"") -> S/PalabrasClaves | P21: 2022 Dec 22 | Q21: Excluir | R21: =LEFT(P21,4) -> 2022 | S21: Dec | Y21: =IF(ISNUMBER(SEARCH("combination", B21)), "combination ", "")
A22: 34931711 | B22: BCL-2-family protein tBID can act as a BAX-like effector of apoptosis | C22: Flores-Romero H, Hohorst L, John M, Albert MC, King LE, Beckmann L, Szabo T, Hertlein V, Luo X, Villunger A, Frenzel LP, Kashkar H, Garcia-Saez AJ. | D22: EMBO J. 2022 Dec 17;41(2):e108690. doi: 10.15252/embj.2021108690. Epub 2021 Dec 21. | E22: Flores-Romero H | F22: EMBO J | G22: 2022 | H22: 44551 | I22: PMC8762556 | K22: 10.15252/embj.2021108690 | L22: =IF(ISNUMBER(VLOOKUP(A22,EXCL,1,FALSE)),"Excluido",IF(ISNUMBER(VLOOKUP(A22,POST,1,FALSE)),"PostAlerta",IF(ISNUMBER(VLOOKUP(A22,PRE,1,FALSE)),"PreAlerta",""))) -> PostAlerta | M22: =IF(ISNUMBER(A22),(IF(ISNUMBER(VLOOKUP(A22,KEYWORDS,1,FALSE)),"C/PalabrasClaves","S/PalabrasClaves")),"") -> S/PalabrasClaves | N22: 2) Nuevos tratamientos | O22: 2b) Péptidos | P22: 2022 Dec 17 | Q22: Listo | R22: =LEFT(P22,4) -> 2022 | S22: Dec | T22: During apoptosis, the BCL-2-family protein tBID promotes mitochondrial permeabilization by activating BAX and BAK and by blocking anti-apoptotic BCL-2 members. Here, we report that tBID can also mediate mitochondrial permeabilization by itself, resulting in release of cytochrome c and mitochondrial DNA, caspase activation and apoptosis even in absence of BAX and BAK. This previously unrecognized activity of tBID depends on helix 6, homologous to the pore-forming regions of BAX and BAK, and can be blocked by pro-survival BCL-2 proteins. Importantly, tBID-mediated mitochondrial permeabilization independent of BAX and BAK is physiologically relevant for SMAC release in the immune response against Shigella infection. Furthermore, it can be exploited to kill leukaemia cells with acquired venetoclax resistance due to lack of active BAX and BAK. Our findings define tBID as an effector of mitochondrial permeabilization in apoptosis and provide a new paradigm for BCL-2 proteins, with implications for anti-bacterial immunity and cancer therapy. | U22: No | V22: Yes | W22: No | X22: tBID mediates mitochondrial permeabilization independent of BAX and BAK, impacting SMAC release in immune response and leukemia therapy. | Y22: =IF(ISNUMBER(SEARCH("combination", B22)), "combination ", "")
A23: 36589853 | B23: Sacubitril/Valsartan contributes to improving the diabetic kidney disease and regulating the gut microbiota in mice | C23: Wang P, Guo R, Bai X, Cui W, Zhang Y, Li H, Shang J, Zhao Z. | D23: Front Endocrinol (Lausanne). 2022 Dec 16;13:1034818. doi: 10.3389/fendo.2022.1034818. eCollection 2022. | E23: Wang P | F23: Front Endocrinol (Lausanne) | G23: 2022 | H23: 44928 | I23: PMC9802116 | K23: 10.3389/fendo.2022.1034818 | L23: =IF(ISNUMBER(VLOOKUP(A23,EXCL,1,FALSE)),"Excluido",IF(ISNUMBER(VLOOKUP(A23,POST,1,FALSE)),"PostAlerta",IF(ISNUMBER(VLOOKUP(A23,PRE,1,FALSE)),"PreAlerta",""))) -> PostAlerta | M23: =IF(ISNUMBER(A23),(IF(ISNUMBER(VLOOKUP(A23,KEYWORDS,1,FALSE)),"C/PalabrasClaves","S/PalabrasClaves")),"") -> C/PalabrasClaves | P23: 2022 Dec 16 | Q23: Excluir | R23: =LEFT(P23,4) -> 2022 | S23: Dec | Y23: =IF(ISNUMBER(SEARCH("combination", B23)), "combination ", "")
A24: 36589940 | B24: Review of major meat-borne zoonotic bacterial pathogens | C24: Ali S, Alsayeqh AF. | D24: Front Public Health. 2022 Dec 15;10:1045599. doi: 10.3389/fpubh.2022.1045599. eCollection 2022. | E24: Ali S | F24: Front Public Health | G24: 2022 | H24: 44928 | I24: PMC9799061 | K24: 10.3389/fpubh.2022.1045599 | L24: =IF(ISNUMBER(VLOOKUP(A24,EXCL,1,FALSE)),"Excluido",IF(ISNUMBER(VLOOKUP(A24,POST,1,FALSE)),"PostAlerta",IF(ISNUMBER(VLOOKUP(A24,PRE,1,FALSE)),"PreAlerta",""))) -> Excluido | M24: =IF(ISNUMBER(A24),(IF(ISNUMBER(VLOOKUP(A24,KEYWORDS,1,FALSE)),"C/PalabrasClaves","S/PalabrasClaves")),"") -> C/PalabrasClaves | P24: 2022 Dec 15 | Q24: Excluir | R24: =LEFT(P24,4) -> 2022 | S24: Dec | Y24: =IF(ISNUMBER(SEARCH("combination", B24)), "combination ", "")
A25: 36591266 | B25: New insights into β-glucan-enhanced immunity in largemouth bass Micropterus salmoides by transcriptome and intestinal microbial composition | C25: Zhang Y, Guo M, Li N, Dong Z, Cai L, Wu B, Xie J, Liu L, Ren L, Shi B. | D25: Front Immunol. 2022 Dec 14;13:1086103. doi: 10.3389/fimmu.2022.1086103. eCollection 2022. | E25: Zhang Y | F25: Front Immunol | G25: 2022 | H25: 44928 | I25: PMC9794605 | K25: 10.3389/fimmu.2022.1086103 | L25: =IF(ISNUMBER(VLOOKUP(A25,EXCL,1,FALSE)),"Excluido",IF(ISNUMBER(VLOOKUP(A25,POST,1,FALSE)),"PostAlerta",IF(ISNUMBER(VLOOKUP(A25,PRE,1,FALSE)),"PreAlerta",""))) -> PostAlerta | M25: =IF(ISNUMBER(A25),(IF(ISNUMBER(VLOOKUP(A25,KEYWORDS,1,FALSE)),"C/PalabrasClaves","S/PalabrasClaves")),"") -> S/PalabrasClaves | P25: 2022 Dec 14 | Q25: Excluir | R25: =LEFT(P25,4) -> 2022 | S25: Dec | Y25: =IF(ISNUMBER(SEARCH("combination", B25)), "combination ", "")
A26: 36508428 | B26: Development of a recombinase polymerase amplification assay with lateral flow dipstick (RPA-LFD) for rapid detection of Shigella spp. and enteroinvasive Escherichia coli | C26: Bian Z, Liu W, Jin J, Hao Y, Jiang L, Xie Y, Zhang H. | D26: PLoS One. 2022 Dec 12;17(12):e0278869. doi: 10.1371/journal.pone.0278869. eCollection 2022. | E26: Bian Z | F26: PLoS One | G26: 2022 | H26: 44907 | I26: PMC9744308 | K26: 10.1371/journal.pone.0278869 | L26: =IF(ISNUMBER(VLOOKUP(A26,EXCL,1,FALSE)),"Excluido",IF(ISNUMBER(VLOOKUP(A26,POST,1,FALSE)),"PostAlerta",IF(ISNUMBER(VLOOKUP(A26,PRE,1,FALSE)),"PreAlerta",""))) -> PostAlerta | M26: =IF(ISNUMBER(A26),(IF(ISNUMBER(VLOOKUP(A26,KEYWORDS,1,FALSE)),"C/PalabrasClaves","S/PalabrasClaves")),"") -> S/PalabrasClaves | P26: 2022 Dec 12 | Q26: Excluir | R26: =LEFT(P26,4) -> 2022 | S26: Dec | Y26: =IF(ISNUMBER(SEARCH("combination", B26)), "combination ", "")
A27: 36477445 | B27: Using runaway replication to express polyhydroxyalkanoic acid (pha) genes from a novel marine bacterium in enteric bacteria: The influence of temperature and phasins on PHA accumulation | C27: Kolibachuk D, Ryder BJ, Lyons ER, Woolsey A, Lopes MK, Thakkar K, Pacheco Nunez M, Duquenoy M, Valente NR, Nieves A. | D27: PLoS One. 2022 Dec 7;17(12):e0275597. doi: 10.1371/journal.pone.0275597. eCollection 2022. | E27: Kolibachuk D | F27: PLoS One | G27: 2022 | H27: 44903 | I27: PMC9728866 | K27: 10.1371/journal.pone.0275597 | L27: =IF(ISNUMBER(VLOOKUP(A27,EXCL,1,FALSE)),"Excluido",IF(ISNUMBER(VLOOKUP(A27,POST,1,FALSE)),"PostAlerta",IF(ISNUMBER(VLOOKUP(A27,PRE,1,FALSE)),"PreAlerta",""))) -> PostAlerta | M27: =IF(ISNUMBER(A27),(IF(ISNUMBER(VLOOKUP(A27,KEYWORDS,1,FALSE)),"C/PalabrasClaves","S/PalabrasClaves")),"") -> S/PalabrasClaves | P27: 2022 Dec 7 | Q27: Excluir | R27: =LEFT(P27,4) -> 2022 | S27: Dec | Y27: =IF(ISNUMBER(SEARCH("combination", B27)), "combination ", "")
A28: 36506782 | B28: Effects of Gabexate Mesylate on the Gut Microbiota and Metabolomics in Rats with Sepsis | C28: Sun W, Cui Y, Zhang X, Wang Y, Zhang Z, Ding X, Liang H, Wang D, Sun Y, Liu S, Duan X, Lu Y, Sun T. | D28: J Inflamm Res. 2022 Dec 5;15:6581-6594. doi: 10.2147/JIR.S392060. eCollection 2022. | E28: Sun W | F28: J Inflamm Res | G28: 2022 | H28: 44907 | I28: PMC9733569 | K28: 10.2147/JIR.S392060 | L28: =IF(ISNUMBER(VLOOKUP(A28,EXCL,1,FALSE)),"Excluido",IF(ISNUMBER(VLOOKUP(A28,POST,1,FALSE)),"PostAlerta",IF(ISNUMBER(VLOOKUP(A28,PRE,1,FALSE)),"PreAlerta",""))) -> PostAlerta | M28: =IF(ISNUMBER(A28),(IF(ISNUMBER(VLOOKUP(A28,KEYWORDS,1,FALSE)),"C/PalabrasClaves","S/PalabrasClaves")),"") -> S/PalabrasClaves | P28: 2022 Dec 5 | Q28: Excluir | R28: =LEFT(P28,4) -> 2022 | S28: Dec | Y28: =IF(ISNUMBER(SEARCH("combination", B28)), "combination ", "")
A29: 35149579 | B29: Shigella is common in symptomatic and asymptomatic men who have sex with men visiting a sexual health clinic in Amsterdam | C29: Braam JF, Bruisten SM, Hoogeland M, de Vries HJC, Schim van der Loeff MF, van Dam AP. | D29: Sex Transm Infect. 2022 Dec;98(8):564-569. doi: 10.1136/sextrans-2021-055274. Epub 2022 Feb 11. | E29: Braam JF | F29: Sex Transm Infect | G29: 2022 | H29: 44604 | K29: 10.1136/sextrans-2021-055274 | L29: =IF(ISNUMBER(VLOOKUP(A29,EXCL,1,FALSE)),"Excluido",IF(ISNUMBER(VLOOKUP(A29,POST,1,FALSE)),"PostAlerta",IF(ISNUMBER(VLOOKUP(A29,PRE,1,FALSE)),"PreAlerta",""))) -> PostAlerta | M29: =IF(ISNUMBER(A29),(IF(ISNUMBER(VLOOKUP(A29,KEYWORDS,1,FALSE)),"C/PalabrasClaves","S/PalabrasClaves")),"") -> S/PalabrasClaves | P29: 2022 Dec | Q29: Excluir | R29: =LEFT(P29,4) -> 2022 | S29: Dec | Y29: =IF(ISNUMBER(SEARCH("combination", B29)), "combination ", "")
A30: 35147277 | B30: Synthesis and biological activity profile of novel triazole/quinoline hybrids | C30: Jamshidi H, Naimi-Jamal MR, Safavi M, RayatSanati K, Azerang P, Tahghighi A. | D30: Chem Biol Drug Des. 2022 Dec;100(6):935-946. doi: 10.1111/cbdd.14031. Epub 2022 Feb 21. | E30: Jamshidi H | F30: Chem Biol Drug Des | G30: 2022 | H30: 44603 | K30: 10.1111/cbdd.14031 | L30: =IF(ISNUMBER(VLOOKUP(A30,EXCL,1,FALSE)),"Excluido",IF(ISNUMBER(VLOOKUP(A30,POST,1,FALSE)),"PostAlerta",IF(ISNUMBER(VLOOKUP(A30,PRE,1,FALSE)),"PreAlerta",""))) -> PostAlerta | M30: =IF(ISNUMBER(A30),(IF(ISNUMBER(VLOOKUP(A30,KEYWORDS,1,FALSE)),"C/PalabrasClaves","S/PalabrasClaves")),"") -> S/PalabrasClaves | N30: 2) Nuevos tratamientos | O30: 2g) nueva combinación de ATB | P30: 2022 Dec | Q30: Listo | R30: =LEFT(P30,4) -> 2022 | S30: Dec | T30: Based on the significant and diverse pharmacophore features of triazole ring and considering the potent antimicrobial properties of quinoline scaffold, a novel series of 1,2,3-triazole-based polyaromatic compounds containing chloroquinoline moiety were synthesized through a well-established synthetic methodology, named click chemistry. The structure of the synthetic compounds was characterized by various spectroscopic methods. The final products of triazole/quinoline hybrids and ((prop-2-yn-1-yloxy)methyl)benzene intermediates were screened for their antibacterial (Staphylococcus aureus, Escherichia coli, Shigella flexneri, and Salmonella enterica), antifungal (Candida albicans, Saccharomyces cerevisiae, and Aspergillus fumigatus), and cytotoxic activities. The best antifungal compounds exhibited minimum inhibitory concentration (MIC), in the range of 0.35-0.63 µM, against S. cerevisiae without any cytotoxic effect. These compounds can be selected as the potential candidates for treating invasive fungal infections caused by S. cerevisiae, after further investigation. Preliminary in silico ADME studies also predicted the favorable pharmacokinetic attributes of most compounds. | U30: No | V30: Yes | W30: No | X30: Triazole/quinoline hybrids showed potent antifungal activity against S. cerevisiae with no cytotoxicity, supporting their use as new treatments. | Y30: =IF(ISNUMBER(SEARCH("combination", B30)), "combination ", "")
A31: 34458959 | B31: In Vitro and In Vivo Evaluation of Lacticaseibacillus rhamnosus GG and Bifidobacterium lactis Bb12 Against Avian Pathogenic Escherichia coli and Identification of Novel Probiotic-Derived Bioactive Peptides | C31: Kathayat D, Closs G Jr, Helmy YA, Deblais L, Srivastava V, Rajashekara G. | D31: Probiotics Antimicrob Proteins. 2022 Dec;14(6):1012-1028. doi: 10.1007/s12602-021-09840-1. Epub 2021 Aug 30. | E31: Kathayat D | F31: Probiotics Antimicrob Proteins | G31: 2022 | H31: 44438 | K31: 10.1007/s12602-021-09840-1 | L31: =IF(ISNUMBER(VLOOKUP(A31,EXCL,1,FALSE)),"Excluido",IF(ISNUMBER(VLOOKUP(A31,POST,1,FALSE)),"PostAlerta",IF(ISNUMBER(VLOOKUP(A31,PRE,1,FALSE)),"PreAlerta",""))) -> PostAlerta | M31: =IF(ISNUMBER(A31),(IF(ISNUMBER(VLOOKUP(A31,KEYWORDS,1,FALSE)),"C/PalabrasClaves","S/PalabrasClaves")),"") -> C/PalabrasClaves | P31: 2022 Dec | Q31: Excluir | R31: =LEFT(P31,4) -> 2022 | S31: Dec | Y31: =IF(ISNUMBER(SEARCH("combination", B31)), "combination ", "")
A32: 34058958 | B32: Bacterial endotoxin-induced maternal inflammation leads to fetal intestinal injury and affects microbial colonization in the neonatal period | C32: Huang Q, Lu S, Zhu Y, Wei B, Chen Y, Bai F. | D32: J Matern Fetal Neonatal Med. 2022 Dec;35(25):6917-6927. doi: 10.1080/14767058.2021.1931101. Epub 2021 May 31. | E32: Huang Q | F32: J Matern Fetal Neonatal Med | G32: 2022 | H32: 44348 | K32: 10.1080/14767058.2021.1931101 | L32: =IF(ISNUMBER(VLOOKUP(A32,EXCL,1,FALSE)),"Excluido",IF(ISNUMBER(VLOOKUP(A32,POST,1,FALSE)),"PostAlerta",IF(ISNUMBER(VLOOKUP(A32,PRE,1,FALSE)),"PreAlerta",""))) -> PostAlerta | M32: =IF(ISNUMBER(A32),(IF(ISNUMBER(VLOOKUP(A32,KEYWORDS,1,FALSE)),"C/PalabrasClaves","S/PalabrasClaves")),"") -> S/PalabrasClaves | P32: 2022 Dec | Q32: Excluir | R32: =LEFT(P32,4) -> 2022 | S32: Dec | Y32: =IF(ISNUMBER(SEARCH("combination", B32)), "combination ", "")
A33: 36532479 | B33: Nourishing neonatal piglets with synthetic milk and Lactobacillus sp. at birth highly modifies the gut microbial communities at the post-weaning stage | C33: Sampath V, Song JH, Jeong J, Mun S, Han K, Kim IH. | D33: Front Microbiol. 2022 Nov 30;13:1044256. doi: 10.3389/fmicb.2022.1044256. eCollection 2022. | E33: Sampath V | F33: Front Microbiol | G33: 2022 | H33: 44914 | I33: PMC9748437 | K33: 10.3389/fmicb.2022.1044256 | L33: =IF(ISNUMBER(VLOOKUP(A33,EXCL,1,FALSE)),"Excluido",IF(ISNUMBER(VLOOKUP(A33,POST,1,FALSE)),"PostAlerta",IF(ISNUMBER(VLOOKUP(A33,PRE,1,FALSE)),"PreAlerta",""))) -> PostAlerta | M33: =IF(ISNUMBER(A33),(IF(ISNUMBER(VLOOKUP(A33,KEYWORDS,1,FALSE)),"C/PalabrasClaves","S/PalabrasClaves")),"") -> S/PalabrasClaves | P33: 2022 Nov 30 | Q33: Excluir | R33: =LEFT(P33,4) -> 2022 | S33: Nov | Y33: =IF(ISNUMBER(SEARCH("combination", B33)), "combination ", "")
A34: 36467878 | B34: The Antibacterial Effects of Cocktail and Single Forms of Lytic Phages Belonging to Podoviridae and Myoviridae Families from Sewage against Shigella sonnei and Shigella flexneri | C34: Jokar J, Rahimian N, Ghasemian A, Najafipour S. | D34: Biomed Res Int. 2022 Nov 25;2022:7833565. doi: 10.1155/2022/7833565. eCollection 2022. | E34: Jokar J | F34: Biomed Res Int | G34: 2022 | H34: 44900 | I34: PMC9718628 | K34: 10.1155/2022/7833565 | L34: =IF(ISNUMBER(VLOOKUP(A34,EXCL,1,FALSE)),"Excluido",IF(ISNUMBER(VLOOKUP(A34,POST,1,FALSE)),"PostAlerta",IF(ISNUMBER(VLOOKUP(A34,PRE,1,FALSE)),"PreAlerta",""))) -> PostAlerta | M34: =IF(ISNUMBER(A34),(IF(ISNUMBER(VLOOKUP(A34,KEYWORDS,1,FALSE)),"C/PalabrasClaves","S/PalabrasClaves")),"") -> C/PalabrasClaves | P34: 2022 Nov 25 | Q34: Excluir | R34: =LEFT(P34,4) -> 2022 | S34: Nov | Y34: =IF(ISNUMBER(SEARCH("combination", B34)), "combination ", "")
A35: 36504960 | B35: Analysis of the gut microbiome in obese native Tibetan children living at different altitudes: A case-control study | C35: Du W, Liu L, Ma Y, Zhu Q, Jia R, Han Y, Wu Z, Yan X, Ailizire A, Zhang W. | D35: Front Public Health. 2022 Nov 24;10:963202. doi: 10.3389/fpubh.2022.963202. eCollection 2022. | E35: Du W | F35: Front Public Health | G35: 2022 | H35: 44907 | I35: PMC9731119 | K35: 10.3389/fpubh.2022.963202 | L35: =IF(ISNUMBER(VLOOKUP(A35,EXCL,1,FALSE)),"Excluido",IF(ISNUMBER(VLOOKUP(A35,POST,1,FALSE)),"PostAlerta",IF(ISNUMBER(VLOOKUP(A35,PRE,1,FALSE)),"PreAlerta",""))) -> PostAlerta | M35: =IF(ISNUMBER(A35),(IF(ISNUMBER(VLOOKUP(A35,KEYWORDS,1,FALSE)),"C/PalabrasClaves","S/PalabrasClaves")),"") -> S/PalabrasClaves | P35: 2022 Nov 24 | Q35: Excluir | R35: =LEFT(P35,4) -> 2022 | S35: Nov | Y35: =IF(ISNUMBER(SEARCH("combination", B35)), "combination ", "")
A36: 36466967 | B36: Prevalence of Multiple Drug-Resistant Bacteria in the Main Campus Wastewater Treatment Plant of Wolaita Sodo University, Southern Ethiopia | C36: Adugna C, Sivalingam KM. | D36: Int J Microbiol. 2022 Nov 23;2022:1781518. doi: 10.1155/2022/1781518. eCollection 2022. | E36: Adugna C | F36: Int J Microbiol | G36: 2022 | H36: 44900 | I36: PMC9711955 | K36: 10.1155/2022/1781518 | L36: =IF(ISNUMBER(VLOOKUP(A36,EXCL,1,FALSE)),"Excluido",IF(ISNUMBER(VLOOKUP(A36,POST,1,FALSE)),"PostAlerta",IF(ISNUMBER(VLOOKUP(A36,PRE,1,FALSE)),"PreAlerta",""))) -> PostAlerta | M36: =IF(ISNUMBER(A36),(IF(ISNUMBER(VLOOKUP(A36,KEYWORDS,1,FALSE)),"C/PalabrasClaves","S/PalabrasClaves")),"") -> C/PalabrasClaves | P36: 2022 Nov 23 | Q36: Excluir | R36: =LEFT(P36,4) -> 2022 | S36: Nov | Y36: =IF(ISNUMBER(SEARCH("combination", B36)), "combination ", "")
A37: 36478676 | B37: Do we need to change our perspective about gut biomarkers? A public data mining approach to identify differentially abundant bacteria in intestinal inflammatory diseases | C37: Vega L, Bohórquez L, Ramírez JD, Muñoz M. | D37: Front Cell Infect Microbiol. 2022 Nov 21;12:918237. doi: 10.3389/fcimb.2022.918237. eCollection 2022. | E37: Vega L | F37: Front Cell Infect Microbiol | G37: 2022 | H37: 44903 | I37: PMC9719923 | K37: 10.3389/fcimb.2022.918237 | L37: =IF(ISNUMBER(VLOOKUP(A37,EXCL,1,FALSE)),"Excluido",IF(ISNUMBER(VLOOKUP(A37,POST,1,FALSE)),"PostAlerta",IF(ISNUMBER(VLOOKUP(A37,PRE,1,FALSE)),"PreAlerta",""))) -> PostAlerta | M37: =IF(ISNUMBER(A37),(IF(ISNUMBER(VLOOKUP(A37,KEYWORDS,1,FALSE)),"C/PalabrasClaves","S/PalabrasClaves")),"") -> S/PalabrasClaves | P37: 2022 Nov 21 | Q37: Excluir | R37: =LEFT(P37,4) -> 2022 | S37: Nov | Y37: =IF(ISNUMBER(SEARCH("combination", B37)), "combination ", "")
A38: 36409683 | B38: Antimicrobial resistance in shigellosis: A surveillance study among urban and rural children over 20 years in Bangladesh | C38: Nuzhat S, Das R, Das S, Islam SB, Palit P, Haque MA, Chakraborty S, Khan SH, Ahmed D, Alam B, Ahmed T, Chisti MJ, Faruque ASG. | D38: PLoS One. 2022 Nov 21;17(11):e0277574. doi: 10.1371/journal.pone.0277574. eCollection 2022. | E38: Nuzhat S | F38: PLoS One | G38: 2022 | H38: 44886 | I38: PMC9678309 | K38: 10.1371/journal.pone.0277574 | L38: =IF(ISNUMBER(VLOOKUP(A38,EXCL,1,FALSE)),"Excluido",IF(ISNUMBER(VLOOKUP(A38,POST,1,FALSE)),"PostAlerta",IF(ISNUMBER(VLOOKUP(A38,PRE,1,FALSE)),"PreAlerta",""))) -> PostAlerta | M38: =IF(ISNUMBER(A38),(IF(ISNUMBER(VLOOKUP(A38,KEYWORDS,1,FALSE)),"C/PalabrasClaves","S/PalabrasClaves")),"") -> C/PalabrasClaves | N38: 1) Reporte de cepas resistentes | P38: 2022 Nov 21 | Q38: Listo | R38: =LEFT(P38,4) -> 2022 | S38: Nov | T38: Antimicrobial resistance against shigellosis is increasingly alarming. However, evidence-based knowledge gaps regarding the changing trends of shigellosis in Bangladesh exist due to the scarcity of longitudinal data on antimicrobial resistance. Our study evaluated the last 20 years antimicrobial resistance patterns against shigellosis among under-5 children in the urban and rural sites of Bangladesh. Data were extracted from the Diarrheal Disease Surveillance System (DDSS) of Dhaka Hospital (urban site) and Matlab Hospital (rural site) of the International Centre for Diarrheal Disease Research, Bangladesh (icddr,b) between January 2001 and December 2020. We studied culture-confirmed shigellosis cases from urban Dhaka Hospital (n = 883) and rural Matlab Hospital (n = 1263). Since 2001, a declining percentage of shigellosis in children observed in urban and rural sites. Moreover, higher isolation rates of Shigella were found in the rural site [1263/15684 (8.1%)] compared to the urban site [883/26804 (3.3%)] in the last 20 years. In both areas, S. flexneri was the predominant species. The upward trend of S. sonnei in both the study sites was statistically significant after adjusting for age and sex. WHO-recommended 1st line antibiotic ciprofloxacin resistance gradually reached more than 70% in both the urban and rural site by 2020. In multiple logistic regression after adjusting for age and sex, ciprofloxacin, azithromycin, mecillinam, ceftriaxone, and multidrug resistance (resistance to any two of these four drugs) among under-5 children were found to be increasing significantly (p<0.01) in the last 20 years in both sites. The study results underscore the importance of therapeutic interventions for shigellosis by appropriate drugs based on their current antibiogram for under-5 children. These observations may help policymakers in formulating better case management strategies for shigellosis. | U38: Yes | V38: No | W38: No | X38: Ciprofloxacin and multidrug resistance in Shigella from under-5 children rose >70% in 20 years in Bangladesh, revealing resistant strains. | Y38: =IF(ISNUMBER(SEARCH("combination", B38)), "combination ", "")
A39: 36452327 | B39: Cocultivation of Chinese prescription and intestine microbiota: SJZD alleviated the major symptoms of IBS-D subjects by tuning neurotransmitter metabolism | C39: Xia X, Xie Y, Chen Q, Ding D, Wang Z, Xu Y, Wang Y, Wang X, Ding W. | D39: Front Endocrinol (Lausanne). 2022 Nov 14;13:1053103. doi: 10.3389/fendo.2022.1053103. eCollection 2022. | E39: Xia X | F39: Front Endocrinol (Lausanne) | G39: 2022 | H39: 44896 | I39: PMC9704418 | K39: 10.3389/fendo.2022.1053103 | L39: =IF(ISNUMBER(VLOOKUP(A39,EXCL,1,FALSE)),"Excluido",IF(ISNUMBER(VLOOKUP(A39,POST,1,FALSE)),"PostAlerta",IF(ISNUMBER(VLOOKUP(A39,PRE,1,FALSE)),"PreAlerta",""))) -> PostAlerta | M39: =IF(ISNUMBER(A39),(IF(ISNUMBER(VLOOKUP(A39,KEYWORDS,1,FALSE)),"C/PalabrasClaves","S/PalabrasClaves")),"") -> S/PalabrasClaves | P39: 2022 Nov 14 | Q39: Excluir | R39: =LEFT(P39,4) -> 2022 | S39: Nov | Y39: =IF(ISNUMBER(SEARCH("combination", B39)), "combination ", "")
A40: 36425784 | B40: Reprogrammed fecal and mucosa-associated intestinal microbiota and weakened mucus layer in intestinal goblet cell- specific Piezo1-deficient mice | C40: Liu Y, Fang F, Xiong Y, Wu J, Li X, Li G, Bai T, Hou X, Song J. | D40: Front Cell Infect Microbiol. 2022 Nov 8;12:1035386. doi: 10.3389/fcimb.2022.1035386. eCollection 2022. | E40: Liu Y | F40: Front Cell Infect Microbiol | G40: 2022 | H40: 44890 | I40: PMC9679152 | K40: 10.3389/fcimb.2022.1035386 | L40: =IF(ISNUMBER(VLOOKUP(A40,EXCL,1,FALSE)),"Excluido",IF(ISNUMBER(VLOOKUP(A40,POST,1,FALSE)),"PostAlerta",IF(ISNUMBER(VLOOKUP(A40,PRE,1,FALSE)),"PreAlerta",""))) -> PostAlerta | M40: =IF(ISNUMBER(A40),(IF(ISNUMBER(VLOOKUP(A40,KEYWORDS,1,FALSE)),"C/PalabrasClaves","S/PalabrasClaves")),"") -> S/PalabrasClaves | P40: 2022 Nov 8 | Q40: Excluir | R40: =LEFT(P40,4) -> 2022 | S40: Nov | Y40: =IF(ISNUMBER(SEARCH("combination", B40)), "combination ", "")
A41: 35600002 | B41: Detection of pathogens associated with early-onset neonatal sepsis in cord blood at birth using quantitative PCR | C41: Obiero CW, Gumbi W, Mwakio S, Mwangudzah H, Seale AC, Taniuchi M, Liu J, Houpt E, Berkley JA. | D41: Wellcome Open Res. 2022 Nov 8;7:3. doi: 10.12688/wellcomeopenres.17386.3. eCollection 2022. | E41: Obiero CW | F41: Wellcome Open Res | G41: 2022 | H41: 44886 | I41: PMC9114825 | K41: 10.12688/wellcomeopenres.17386.3 | L41: =IF(ISNUMBER(VLOOKUP(A41,EXCL,1,FALSE)),"Excluido",IF(ISNUMBER(VLOOKUP(A41,POST,1,FALSE)),"PostAlerta",IF(ISNUMBER(VLOOKUP(A41,PRE,1,FALSE)),"PreAlerta",""))) -> PostAlerta | M41: =IF(ISNUMBER(A41),(IF(ISNUMBER(VLOOKUP(A41,KEYWORDS,1,FALSE)),"C/PalabrasClaves","S/PalabrasClaves")),"") -> S/PalabrasClaves | P41: 2022 Nov 8 | Q41: Excluir | R41: =LEFT(P41,4) -> 2022 | S41: Nov | Y41: =IF(ISNUMBER(SEARCH("combination", B41)), "combination ", "")
A42: 36419726 | B42: Antibiotic removal does not affect cecal microbiota balance and productive parameters in LP robust rabbit line | C42: Montoro-Dasi L, Lorenzo-Rebenaque L, Ramon-Moragues A, Pérez-Gracia MT, de Toro M, Marin C, Villagra A. | D42: Front Vet Sci. 2022 Nov 7;9:1038218. doi: 10.3389/fvets.2022.1038218. eCollection 2022. | E42: Montoro-Dasi L | F42: Front Vet Sci | G42: 2022 | H42: 44889 | I42: PMC9676498 | K42: 10.3389/fvets.2022.1038218 | L42: =IF(ISNUMBER(VLOOKUP(A42,EXCL,1,FALSE)),"Excluido",IF(ISNUMBER(VLOOKUP(A42,POST,1,FALSE)),"PostAlerta",IF(ISNUMBER(VLOOKUP(A42,PRE,1,FALSE)),"PreAlerta",""))) -> PostAlerta | M42: =IF(ISNUMBER(A42),(IF(ISNUMBER(VLOOKUP(A42,KEYWORDS,1,FALSE)),"C/PalabrasClaves","S/PalabrasClaves")),"") -> C/PalabrasClaves | P42: 2022 Nov 7 | Q42: Excluir | R42: =LEFT(P42,4) -> 2022 | S42: Nov | Y42: =IF(ISNUMBER(SEARCH("combination", B42)), "combination ", "")
A43: 36406086 | B43: Seasonal dynamics in bacterial communities of closed-cage broiler houses | C43: Chen H, Yan H, Xiu Y, Jiang L, Zhang J, Chen G, Yu X, Zhu H, Zhao X, Li Y, Tang W, Zhang X. | D43: Front Vet Sci. 2022 Nov 7;9:1019005. doi: 10.3389/fvets.2022.1019005. eCollection 2022. | E43: Chen H | F43: Front Vet Sci | G43: 2022 | H43: 44886 | I43: PMC9669973 | K43: 10.3389/fvets.2022.1019005 | L43: =IF(ISNUMBER(VLOOKUP(A43,EXCL,1,FALSE)),"Excluido",IF(ISNUMBER(VLOOKUP(A43,POST,1,FALSE)),"PostAlerta",IF(ISNUMBER(VLOOKUP(A43,PRE,1,FALSE)),"PreAlerta",""))) -> PostAlerta | M43: =IF(ISNUMBER(A43),(IF(ISNUMBER(VLOOKUP(A43,KEYWORDS,1,FALSE)),"C/PalabrasClaves","S/PalabrasClaves")),"") -> S/PalabrasClaves | P43: 2022 Nov 7 | Q43: Excluir | R43: =LEFT(P43,4) -> 2022 | S43: Nov | Y43: =IF(ISNUMBER(SEARCH("combination", B43)), "combination ", "")
A44: 36342937 | B44: Estimating the burden of foodborne gastroenteritis due to nontyphoidal Salmonella enterica, Shigella and Vibrio parahaemolyticus in China | C44: Li YJ, Yang YF, Zhou YJ, Zhang RH, Liu CW, Liu H, Li XG, Chen W, Chen Y, Wu YN. | D44: PLoS One. 2022 Nov 7;17(11):e0277203. doi: 10.1371/journal.pone.0277203. eCollection 2022. | E44: Li YJ | F44: PLoS One | G44: 2022 | H44: 44872 | I44: PMC9639838 | K44: 10.1371/journal.pone.0277203 | L44: =IF(ISNUMBER(VLOOKUP(A44,EXCL,1,FALSE)),"Excluido",IF(ISNUMBER(VLOOKUP(A44,POST,1,FALSE)),"PostAlerta",IF(ISNUMBER(VLOOKUP(A44,PRE,1,FALSE)),"PreAlerta",""))) -> PostAlerta | M44: =IF(ISNUMBER(A44),(IF(ISNUMBER(VLOOKUP(A44,KEYWORDS,1,FALSE)),"C/PalabrasClaves","S/PalabrasClaves")),"") -> S/PalabrasClaves | P44: 2022 Nov 7 | Q44: Excluir | R44: =LEFT(P44,4) -> 2022 | S44: Nov | Y44: =IF(ISNUMBER(SEARCH("combination", B44)), "combination ", "")
A45: 36405958 | B45: Changes and significance of gut microbiota in children with focal epilepsy before and after treatment | C45: Zhou C, Gong S, Xiang S, Liang L, Hu X, Huang R, Liao Z, Ma Y, Xiao Z, Qiu J. | D45: Front Cell Infect Microbiol. 2022 Nov 3;12:965471. doi: 10.3389/fcimb.2022.965471. eCollection 2022. | E45: Zhou C | F45: Front Cell Infect Microbiol | G45: 2022 | H45: 44886 | I45: PMC9671114 | K45: 10.3389/fcimb.2022.965471 | L45: =IF(ISNUMBER(VLOOKUP(A45,EXCL,1,FALSE)),"Excluido",IF(ISNUMBER(VLOOKUP(A45,POST,1,FALSE)),"PostAlerta",IF(ISNUMBER(VLOOKUP(A45,PRE,1,FALSE)),"PreAlerta",""))) -> PostAlerta | M45: =IF(ISNUMBER(A45),(IF(ISNUMBER(VLOOKUP(A45,KEYWORDS,1,FALSE)),"C/PalabrasClaves","S/PalabrasClaves")),"") -> S/PalabrasClaves | P45: 2022 Nov 3 | Q45: Excluir | R45: =LEFT(P45,4) -> 2022 | S45: Nov | Y45: =IF(ISNUMBER(SEARCH("combination", B45)), "combination ", "")
A46: 36439824 | B46: Vancomycin-induced gut microbiota dysbiosis aggravates allergic rhinitis in mice by altered short-chain fatty acids | C46: Chen Z, Xu Q, Liu Y, Wei Y, He S, Lin W, Wang Y, Li L, Xu Y. | D46: Front Microbiol. 2022 Nov 1;13:1002084. doi: 10.3389/fmicb.2022.1002084. eCollection 2022. | E46: Chen Z | F46: Front Microbiol | G46: 2022 | H46: 44893 | I46: PMC9687373 | K46: 10.3389/fmicb.2022.1002084 | L46: =IF(ISNUMBER(VLOOKUP(A46,EXCL,1,FALSE)),"Excluido",IF(ISNUMBER(VLOOKUP(A46,POST,1,FALSE)),"PostAlerta",IF(ISNUMBER(VLOOKUP(A46,PRE,1,FALSE)),"PreAlerta",""))) -> PostAlerta | M46: =IF(ISNUMBER(A46),(IF(ISNUMBER(VLOOKUP(A46,KEYWORDS,1,FALSE)),"C/PalabrasClaves","S/PalabrasClaves")),"") -> S/PalabrasClaves | P46: 2022 Nov 1 | Q46: Excluir | R46: =LEFT(P46,4) -> 2022 | S46: Nov | Y46: =IF(ISNUMBER(SEARCH("combination", B46)), "combination ", "")
A47: 36386617 | B47: Difference analysis of intestinal microbiota and metabolites in piglets of different breeds exposed to porcine epidemic diarrhea virus infection | C47: Li Z, Zhang W, Su L, Huang Z, Zhang W, Ma L, Sun J, Guo J, Wen F, Mei K, El-Ashram S, Huang S, Zhao Y. | D47: Front Microbiol. 2022 Nov 1;13:990642. doi: 10.3389/fmicb.2022.990642. eCollection 2022. | E47: Li Z | F47: Front Microbiol | G47: 2022 | H47: 44882 | I47: PMC9665409 | K47: 10.3389/fmicb.2022.990642 | L47: =IF(ISNUMBER(VLOOKUP(A47,EXCL,1,FALSE)),"Excluido",IF(ISNUMBER(VLOOKUP(A47,POST,1,FALSE)),"PostAlerta",IF(ISNUMBER(VLOOKUP(A47,PRE,1,FALSE)),"PreAlerta",""))) -> PostAlerta | M47: =IF(ISNUMBER(A47),(IF(ISNUMBER(VLOOKUP(A47,KEYWORDS,1,FALSE)),"C/PalabrasClaves","S/PalabrasClaves")),"") -> C/PalabrasClaves | P47: 2022 Nov 1 | Q47: Excluir | R47: =LEFT(P47,4) -> 2022 | S47: Nov | Y47: =IF(ISNUMBER(SEARCH("combination", B47)), "combination ", "")
A48: 36335456 | B48: Study of The specificity of gut microbiota in adult patients with delayed-onset of atopic dermatitis | C48: Liu T, Yang C, He J, Wang Y, Hu T, Zhang X. | D48: Allergol Immunopathol (Madr). 2022 Nov 1;50(6):128-136. doi: 10.15586/aei.v50i6.705. eCollection 2022. | E48: Liu T | F48: Allergol Immunopathol (Madr) | G48: 2022 | H48: 44871 | K48: 10.15586/aei.v50i6.705 | L48: =IF(ISNUMBER(VLOOKUP(A48,EXCL,1,FALSE)),"Excluido",IF(ISNUMBER(VLOOKUP(A48,POST,1,FALSE)),"PostAlerta",IF(ISNUMBER(VLOOKUP(A48,PRE,1,FALSE)),"PreAlerta",""))) -> PostAlerta | M48: =IF(ISNUMBER(A48),(IF(ISNUMBER(VLOOKUP(A48,KEYWORDS,1,FALSE)),"C/PalabrasClaves","S/PalabrasClaves")),"") -> S/PalabrasClaves | P48: 2022 Nov 1 | Q48: Excluir | R48: =LEFT(P48,4) -> 2022 | S48: Nov | Y48: =IF(ISNUMBER(SEARCH("combination", B48)), "combination ", "")
A49: 34979272 | B49: Urinary microbiota and bladder cancer: A systematic review and a focus on uropathogens | C49: Yacouba A, Tidjani Alou M, Lagier JC, Dubourg G, Raoult D. | D49: Semin Cancer Biol. 2022 Nov;86(Pt 3):875-884. doi: 10.1016/j.semcancer.2021.12.010. Epub 2022 Jan 1. | E49: Yacouba A | F49: Semin Cancer Biol | G49: 2022 | H49: 44564 | K49: 10.1016/j.semcancer.2021.12.010 | L49: =IF(ISNUMBER(VLOOKUP(A49,EXCL,1,FALSE)),"Excluido",IF(ISNUMBER(VLOOKUP(A49,POST,1,FALSE)),"PostAlerta",IF(ISNUMBER(VLOOKUP(A49,PRE,1,FALSE)),"PreAlerta",""))) -> Excluido | M49: =IF(ISNUMBER(A49),(IF(ISNUMBER(VLOOKUP(A49,KEYWORDS,1,FALSE)),"C/PalabrasClaves","S/PalabrasClaves")),"") -> S/PalabrasClaves | P49: 2022 Nov | Q49: Excluir | R49: =LEFT(P49,4) -> 2022 | S49: Nov | Y49: =IF(ISNUMBER(SEARCH("combination", B49)), "combination ", "")
A50: 34184617 | B50: Removal of harmful algae by Shigella sp. H3 and Alcaligenes sp. H5: algicidal pathways and characteristics | C50: Xue G, Wang X, Xu C, Song B, Chen H. | D50: Environ Technol. 2022 Nov;43(27):4341-4353. doi: 10.1080/09593330.2021.1949047. Epub 2021 Jul 8. | E50: Xue G | F50: Environ Technol | G50: 2022 | H50: 44376 | K50: 10.1080/09593330.2021.1949047 | L50: =IF(ISNUMBER(VLOOKUP(A50,EXCL,1,FALSE)),"Excluido",IF(ISNUMBER(VLOOKUP(A50,POST,1,FALSE)),"PostAlerta",IF(ISNUMBER(VLOOKUP(A50,PRE,1,FALSE)),"PreAlerta",""))) -> PostAlerta | M50: =IF(ISNUMBER(A50),(IF(ISNUMBER(VLOOKUP(A50,KEYWORDS,1,FALSE)),"C/PalabrasClaves","S/PalabrasClaves")),"") -> S/PalabrasClaves | P50: 2022 Nov | Q50: Excluir | R50: =LEFT(P50,4) -> 2022 | S50: Nov | Y50: =IF(ISNUMBER(SEARCH("combination", B50)), "combination ", "")
A51: 36386655 | B51: A novel T4- and λ-based receptor binding protein family for bacteriophage therapy host range engineering | C51: Magaziner SJ, Salmond GPC. | D51: Front Microbiol. 2022 Oct 31;13:1010330. doi: 10.3389/fmicb.2022.1010330. eCollection 2022. | E51: Magaziner SJ | F51: Front Microbiol | G51: 2022 | H51: 44882 | I51: PMC9659904 | K51: 10.3389/fmicb.2022.1010330 | L51: =IF(ISNUMBER(VLOOKUP(A51,EXCL,1,FALSE)),"Excluido",IF(ISNUMBER(VLOOKUP(A51,POST,1,FALSE)),"PostAlerta",IF(ISNUMBER(VLOOKUP(A51,PRE,1,FALSE)),"PreAlerta",""))) -> PostAlerta | M51: =IF(ISNUMBER(A51),(IF(ISNUMBER(VLOOKUP(A51,KEYWORDS,1,FALSE)),"C/PalabrasClaves","S/PalabrasClaves")),"") -> S/PalabrasClaves | P51: 2022 Oct 31 | Q51: Excluir | R51: =LEFT(P51,4) -> 2022 | S51: Oct | Y51: =IF(ISNUMBER(SEARCH("combination", B51)), "combination ", "")
A52: 36386709 | B52: Sodium acetate/sodium butyrate alleviates lipopolysaccharide-induced diarrhea in mice via regulating the gut microbiota, inflammatory cytokines, antioxidant levels, and NLRP3/Caspase-1 signaling | C52: Chen X, Kong Q, Zhao X, Zhao C, Hao P, Irshad I, Lei H, Kulyar MF, Bhutta ZA, Ashfaq H, Sha Q, Li K, Wu Y. | D52: Front Microbiol. 2022 Oct 28;13:1036042. doi: 10.3389/fmicb.2022.1036042. eCollection 2022. | E52: Chen X | F52: Front Microbiol | G52: 2022 | H52: 44882 | I52: PMC9664939 | K52: 10.3389/fmicb.2022.1036042 | L52: =IF(ISNUMBER(VLOOKUP(A52,EXCL,1,FALSE)),"Excluido",IF(ISNUMBER(VLOOKUP(A52,POST,1,FALSE)),"PostAlerta",IF(ISNUMBER(VLOOKUP(A52,PRE,1,FALSE)),"PreAlerta",""))) -> PostAlerta | M52: =IF(ISNUMBER(A52),(IF(ISNUMBER(VLOOKUP(A52,KEYWORDS,1,FALSE)),"C/PalabrasClaves","S/PalabrasClaves")),"") -> S/PalabrasClaves | P52: 2022 Oct 28 | Q52: Excluir | R52: =LEFT(P52,4) -> 2022 | S52: Oct | Y52: =IF(ISNUMBER(SEARCH("combination", B52)), "combination ", "")
A53: 36386704 | B53: Oral polio revaccination is associated with changes in gut and upper respiratory microbiomes of infants | C53: Medeiros MM, Ingham AC, Nanque LM, Correia C, Stegger M, Andersen PS, Fisker AB, Benn CS, Lanaspa M, Silveira H, Abrantes P. | D53: Front Microbiol. 2022 Oct 28;13:1016220. doi: 10.3389/fmicb.2022.1016220. eCollection 2022. | E53: Medeiros MM | F53: Front Microbiol | G53: 2022 | H53: 44882 | I53: PMC9649904 | K53: 10.3389/fmicb.2022.1016220 | L53: =IF(ISNUMBER(VLOOKUP(A53,EXCL,1,FALSE)),"Excluido",IF(ISNUMBER(VLOOKUP(A53,POST,1,FALSE)),"PostAlerta",IF(ISNUMBER(VLOOKUP(A53,PRE,1,FALSE)),"PreAlerta",""))) -> PostAlerta | M53: =IF(ISNUMBER(A53),(IF(ISNUMBER(VLOOKUP(A53,KEYWORDS,1,FALSE)),"C/PalabrasClaves","S/PalabrasClaves")),"") -> S/PalabrasClaves | P53: 2022 Oct 28 | Q53: Excluir | R53: =LEFT(P53,4) -> 2022 | S53: Oct | Y53: =IF(ISNUMBER(SEARCH("combination", B53)), "combination ", "")
A54: 36389142 | B54: Modification of phosphoinositides by the Shigella effector IpgD during host cell infection | C54: Tran Van Nhieu G, Latour-Lambert P, Enninga J. | D54: Front Cell Infect Microbiol. 2022 Oct 27;12:1012533. doi: 10.3389/fcimb.2022.1012533. eCollection 2022. | E54: Tran Van Nhieu G | F54: Front Cell Infect Microbiol | G54: 2022 | H54: 44882 | I54: PMC9647168 | K54: 10.3389/fcimb.2022.1012533 | L54: =IF(ISNUMBER(VLOOKUP(A54,EXCL,1,FALSE)),"Excluido",IF(ISNUMBER(VLOOKUP(A54,POST,1,FALSE)),"PostAlerta",IF(ISNUMBER(VLOOKUP(A54,PRE,1,FALSE)),"PreAlerta",""))) -> Excluido | M54: =IF(ISNUMBER(A54),(IF(ISNUMBER(VLOOKUP(A54,KEYWORDS,1,FALSE)),"C/PalabrasClaves","S/PalabrasClaves")),"") -> S/PalabrasClaves | P54: 2022 Oct 27 | Q54: Excluir | R54: =LEFT(P54,4) -> 2022 | S54: Oct | Y54: =IF(ISNUMBER(SEARCH("combination", B54)), "combination ", "")
A55: 36389137 | B55: Comprehensive evaluation of the mechanism of Gastrodia elata Blume in ameliorating cerebral ischemia-reperfusion injury based on integrating fecal metabonomics and 16S rDNA sequencing | C55: Ding X, Liu Z, Liu Y, Xu B, Chen J, Pu J, Wu D, Yu H, Jin C, Wang X. | D55: Front Cell Infect Microbiol. 2022 Oct 27;12:1026627. doi: 10.3389/fcimb.2022.1026627. eCollection 2022. | E55: Ding X | F55: Front Cell Infect Microbiol | G55: 2022 | H55: 44882 | I55: PMC9648199 | K55: 10.3389/fcimb.2022.1026627 | L55: =IF(ISNUMBER(VLOOKUP(A55,EXCL,1,FALSE)),"Excluido",IF(ISNUMBER(VLOOKUP(A55,POST,1,FALSE)),"PostAlerta",IF(ISNUMBER(VLOOKUP(A55,PRE,1,FALSE)),"PreAlerta",""))) -> PostAlerta | M55: =IF(ISNUMBER(A55),(IF(ISNUMBER(VLOOKUP(A55,KEYWORDS,1,FALSE)),"C/PalabrasClaves","S/PalabrasClaves")),"") -> C/PalabrasClaves | P55: 2022 Oct 27 | Q55: Excluir | R55: =LEFT(P55,4) -> 2022 | S55: Oct | Y55: =IF(ISNUMBER(SEARCH("combination", B55)), "combination ", "")
A56: 36339339 | B56: Alterations in the gut microbiota of AIDS patients with pneumocystis pneumonia and correlations with the lung microbiota | C56: Zhu M, Liu S, Zhao C, Shi J, Li C, Ling S, Cheng J, Dong W, Xu J. | D56: Front Cell Infect Microbiol. 2022 Oct 21;12:1033427. doi: 10.3389/fcimb.2022.1033427. eCollection 2022. | E56: Zhu M | F56: Front Cell Infect Microbiol | G56: 2022 | H56: 44872 | I56: PMC9634167 | K56: 10.3389/fcimb.2022.1033427 | L56: =IF(ISNUMBER(VLOOKUP(A56,EXCL,1,FALSE)),"Excluido",IF(ISNUMBER(VLOOKUP(A56,POST,1,FALSE)),"PostAlerta",IF(ISNUMBER(VLOOKUP(A56,PRE,1,FALSE)),"PreAlerta",""))) -> PostAlerta | M56: =IF(ISNUMBER(A56),(IF(ISNUMBER(VLOOKUP(A56,KEYWORDS,1,FALSE)),"C/PalabrasClaves","S/PalabrasClaves")),"") -> S/PalabrasClaves | P56: 2022 Oct 21 | Q56: Excluir | R56: =LEFT(P56,4) -> 2022 | S56: Oct | Y56: =IF(ISNUMBER(SEARCH("combination", B56)), "combination ", "")
A57: 36339345 | B57: Development of multiplex cross displacement amplification combined with lateral flow biosensor assay for detection of virulent shigella sonnei | C57: Wang Y, He Z, Ablimit P, Ji S, Jin D. | D57: Front Cell Infect Microbiol. 2022 Oct 19;12:1012105. doi: 10.3389/fcimb.2022.1012105. eCollection 2022. | E57: Wang Y | F57: Front Cell Infect Microbiol | G57: 2022 | H57: 44872 | I57: PMC9627043 | K57: 10.3389/fcimb.2022.1012105 | L57: =IF(ISNUMBER(VLOOKUP(A57,EXCL,1,FALSE)),"Excluido",IF(ISNUMBER(VLOOKUP(A57,POST,1,FALSE)),"PostAlerta",IF(ISNUMBER(VLOOKUP(A57,PRE,1,FALSE)),"PreAlerta",""))) -> PostAlerta | M57: =IF(ISNUMBER(A57),(IF(ISNUMBER(VLOOKUP(A57,KEYWORDS,1,FALSE)),"C/PalabrasClaves","S/PalabrasClaves")),"") -> S/PalabrasClaves | P57: 2022 Oct 19 | Q57: Excluir | R57: =LEFT(P57,4) -> 2022 | S57: Oct | Y57: =IF(ISNUMBER(SEARCH("combination", B57)), "combination ", "")
A58: 36338103 | B58: Dietary rosemary extract modulated gut microbiota and influenced the growth, meat quality, serum biochemistry, antioxidant, and immune capacities of broilers | C58: Liu Y, Li C, Huang X, Zhang X, Deng P, Jiang G, Dai Q. | D58: Front Microbiol. 2022 Oct 19;13:1024682. doi: 10.3389/fmicb.2022.1024682. eCollection 2022. | E58: Liu Y | F58: Front Microbiol | G58: 2022 | H58: 44872 | I58: PMC9626529 | K58: 10.3389/fmicb.2022.1024682 | L58: =IF(ISNUMBER(VLOOKUP(A58,EXCL,1,FALSE)),"Excluido",IF(ISNUMBER(VLOOKUP(A58,POST,1,FALSE)),"PostAlerta",IF(ISNUMBER(VLOOKUP(A58,PRE,1,FALSE)),"PreAlerta",""))) -> PostAlerta | M58: =IF(ISNUMBER(A58),(IF(ISNUMBER(VLOOKUP(A58,KEYWORDS,1,FALSE)),"C/PalabrasClaves","S/PalabrasClaves")),"") -> S/PalabrasClaves | P58: 2022 Oct 19 | Q58: Excluir | R58: =LEFT(P58,4) -> 2022 | S58: Oct | Y58: =IF(ISNUMBER(SEARCH("combination", B58)), "combination ", "")
A59: 36329847 | B59: The change of plasma metabolic profile and gut microbiome dysbiosis in patients with rheumatoid arthritis | C59: Zhu J, Wang T, Lin Y, Xiong M, Chen J, Jian C, Zhang J, Xie H, Zeng F, Huang Q, Su J, Zhao Y, Li S, Zeng F. | D59: Front Microbiol. 2022 Oct 18;13:931431. doi: 10.3389/fmicb.2022.931431. eCollection 2022. | E59: Zhu J | F59: Front Microbiol | G59: 2022 | H59: 44869 | I59: PMC9623673 | K59: 10.3389/fmicb.2022.931431 | L59: =IF(ISNUMBER(VLOOKUP(A59,EXCL,1,FALSE)),"Excluido",IF(ISNUMBER(VLOOKUP(A59,POST,1,FALSE)),"PostAlerta",IF(ISNUMBER(VLOOKUP(A59,PRE,1,FALSE)),"PreAlerta",""))) -> PostAlerta | M59: =IF(ISNUMBER(A59),(IF(ISNUMBER(VLOOKUP(A59,KEYWORDS,1,FALSE)),"C/PalabrasClaves","S/PalabrasClaves")),"") -> S/PalabrasClaves | P59: 2022 Oct 18 | Q59: Excluir | R59: =LEFT(P59,4) -> 2022 | S59: Oct | Y59: =IF(ISNUMBER(SEARCH("combination", B59)), "combination ", "")
A60: 36310877 | B60: Antimicrobial peptide human β-defensin-2 improves in vitro cellular viability and reduces pro-inflammatory effects induced by enteroinvasive Escherichia coli in Caco-2 cells by inhibiting invasion and virulence factors' expression | C60: Fusco A, Savio V, Perfetto B, Mattina R, Donnarumma G. | D60: Front Cell Infect Microbiol. 2022 Oct 13;12:1009415. doi: 10.3389/fcimb.2022.1009415. eCollection 2022. | E60: Fusco A | F60: Front Cell Infect Microbiol | G60: 2022 | H60: 44865 | I60: PMC9606569 | K60: 10.3389/fcimb.2022.1009415 | L60: =IF(ISNUMBER(VLOOKUP(A60,EXCL,1,FALSE)),"Excluido",IF(ISNUMBER(VLOOKUP(A60,POST,1,FALSE)),"PostAlerta",IF(ISNUMBER(VLOOKUP(A60,PRE,1,FALSE)),"PreAlerta",""))) -> PostAlerta | M60: =IF(ISNUMBER(A60),(IF(ISNUMBER(VLOOKUP(A60,KEYWORDS,1,FALSE)),"C/PalabrasClaves","S/PalabrasClaves")),"") -> C/PalabrasClaves | P60: 2022 Oct 13 | Q60: Excluir | R60: =LEFT(P60,4) -> 2022 | S60: Oct | Y60: =IF(ISNUMBER(SEARCH("combination", B60)), "combination ", "")
A61: 36277127 | B61: Prevalence and Associated Risk Factors of Intestinal Parasites and Enteric Bacterial Infections among Selected Region Food Handlers of Ethiopia during 2014-2022: A Systematic Review and Meta-Analysis | C61: Girma A, Aemiro A. | D61: ScientificWorldJournal. 2022 Oct 12;2022:7786036. doi: 10.1155/2022/7786036. eCollection 2022. | E61: Girma A | F61: ScientificWorldJournal | G61: 2022 | H61: 44858 | I61: PMC9581692 | K61: 10.1155/2022/7786036 | L61: =IF(ISNUMBER(VLOOKUP(A61,EXCL,1,FALSE)),"Excluido",IF(ISNUMBER(VLOOKUP(A61,POST,1,FALSE)),"PostAlerta",IF(ISNUMBER(VLOOKUP(A61,PRE,1,FALSE)),"PreAlerta",""))) -> Excluido | M61: =IF(ISNUMBER(A61),(IF(ISNUMBER(VLOOKUP(A61,KEYWORDS,1,FALSE)),"C/PalabrasClaves","S/PalabrasClaves")),"") -> S/PalabrasClaves | P61: 2022 Oct 12 | Q61: Excluir | R61: =LEFT(P61,4) -> 2022 | S61: Oct | Y61: =IF(ISNUMBER(SEARCH("combination", B61)), "combination ", "")
A62: 36275026 | B62: The oral-gut axis: Salivary and fecal microbiome dysbiosis in patients with inflammatory bowel disease | C62: Abdelbary MMH, Hatting M, Bott A, Dahlhausen A, Keller D, Trautwein C, Conrads G. | D62: Front Cell Infect Microbiol. 2022 Oct 7;12:1010853. doi: 10.3389/fcimb.2022.1010853. eCollection 2022. | E62: Abdelbary MMH | F62: Front Cell Infect Microbiol | G62: 2022 | H62: 44858 | I62: PMC9585322 | K62: 10.3389/fcimb.2022.1010853 | L62: =IF(ISNUMBER(VLOOKUP(A62,EXCL,1,FALSE)),"Excluido",IF(ISNUMBER(VLOOKUP(A62,POST,1,FALSE)),"PostAlerta",IF(ISNUMBER(VLOOKUP(A62,PRE,1,FALSE)),"PreAlerta",""))) -> PostAlerta | M62: =IF(ISNUMBER(A62),(IF(ISNUMBER(VLOOKUP(A62,KEYWORDS,1,FALSE)),"C/PalabrasClaves","S/PalabrasClaves")),"") -> S/PalabrasClaves | P62: 2022 Oct 7 | Q62: Excluir | R62: =LEFT(P62,4) -> 2022 | S62: Oct | Y62: =IF(ISNUMBER(SEARCH("combination", B62)), "combination ", "")
A63: 36274738 | B63: Artificial rearing alters intestinal microbiota and induces inflammatory response in piglets | C63: Han Q, Zhang X, Nian H, Liu H, Li X, Zhang R, Bao J. | D63: Front Microbiol. 2022 Oct 6;13:1002738. doi: 10.3389/fmicb.2022.1002738. eCollection 2022. | E63: Han Q | F63: Front Microbiol | G63: 2022 | H63: 44858 | I63: PMC9584613 | K63: 10.3389/fmicb.2022.1002738 | L63: =IF(ISNUMBER(VLOOKUP(A63,EXCL,1,FALSE)),"Excluido",IF(ISNUMBER(VLOOKUP(A63,POST,1,FALSE)),"PostAlerta",IF(ISNUMBER(VLOOKUP(A63,PRE,1,FALSE)),"PreAlerta",""))) -> PostAlerta | M63: =IF(ISNUMBER(A63),(IF(ISNUMBER(VLOOKUP(A63,KEYWORDS,1,FALSE)),"C/PalabrasClaves","S/PalabrasClaves")),"") -> S/PalabrasClaves | P63: 2022 Oct 6 | Q63: Excluir | R63: =LEFT(P63,4) -> 2022 | S63: Oct | Y63: =IF(ISNUMBER(SEARCH("combination", B63)), "combination ", "")
A64: 36274686 | B64: Green synthesis of biogenetic Te(0) nanoparticles by high tellurite tolerance fungus Mortierella sp. AB1 with antibacterial activity | C64: Ao B, He F, Lv J, Tu J, Tan Z, Jiang H, Shi X, Li J, Hou J, Hu Y, Xia X. | D64: Front Microbiol. 2022 Oct 5;13:1020179. doi: 10.3389/fmicb.2022.1020179. eCollection 2022. | E64: Ao B | F64: Front Microbiol | G64: 2022 | H64: 44858 | I64: PMC9581301 | K64: 10.3389/fmicb.2022.1020179 | L64: =IF(ISNUMBER(VLOOKUP(A64,EXCL,1,FALSE)),"Excluido",IF(ISNUMBER(VLOOKUP(A64,POST,1,FALSE)),"PostAlerta",IF(ISNUMBER(VLOOKUP(A64,PRE,1,FALSE)),"PreAlerta",""))) -> PostAlerta | M64: =IF(ISNUMBER(A64),(IF(ISNUMBER(VLOOKUP(A64,KEYWORDS,1,FALSE)),"C/PalabrasClaves","S/PalabrasClaves")),"") -> S/PalabrasClaves | N64: 2) Nuevos tratamientos | O64: 2b) Péptidos | P64: 2022 Oct 5 | Q64: Listo | R64: =LEFT(P64,4) -> 2022 | S64: Oct | T64: Tellurite [Te(IV)] is a high-toxicity metalloid. In this study, a fungus with high Te(IV) resistance was isolated. Strain AB1 could efficiently reduce highly toxic Te(IV) to less toxic Te(0). The reduced products formed rod-shaped biogenetic Te(0) nanoparticles (Bio-TeNPs) intracellularly. Further TEM-element mapping, FTIR, and XPS analysis showed that the extracted Bio-TeNPs ranged from 100 to 500 nm and consisted of Te(0), proteins, lipids, aromatic compounds, and carbohydrates. Moreover, Bio-TeNPs exhibited excellent antibacterial ability against Shigella dysenteriae, Escherichia coli, Enterobacter sakazakii, and Salmonella typhimurium according to inhibition zone tests. Further growth and live/dead staining experiments showed that E. coli and S. typhimurium were significantly inhibited by Bio-TeNPs, and cells were broken or shriveled after treatment with Bio-TeNPs based on SEM observation. Additionally, the antioxidant and cytotoxicity tests showed that the Bio-TeNPs exhibited excellent antioxidant capacity with no cytotoxicity. All these results suggested that strain AB1 showed great potential in bioremediation and Bio-TeNPs were excellent antibacterial nanomaterials with no cytotoxicity. | U64: No | V64: Yes | W64: No | X64: Bio-TeNPs from strain AB1 showed strong antibacterial activity against pathogens with no cytotoxicity, suggesting potential new treatments. | Y64: =IF(ISNUMBER(SEARCH("combination", B64)), "combination ", "")
A65: 36267185 | B65: Effects of glucose oxidase on growth performance, clinical symptoms, serum parameters, and intestinal health in piglets challenged by enterotoxigenic Escherichia coli | C65: Wang W, Xie R, Cao Q, Ye H, Zhang C, Dong Z, Feng D, Zuo J. | D65: Front Microbiol. 2022 Oct 3;13:994151. doi: 10.3389/fmicb.2022.994151. eCollection 2022. | E65: Wang W | F65: Front Microbiol | G65: 2022 | H65: 44855 | I65: PMC9578003 | K65: 10.3389/fmicb.2022.994151 | L65: =IF(ISNUMBER(VLOOKUP(A65,EXCL,1,FALSE)),"Excluido",IF(ISNUMBER(VLOOKUP(A65,POST,1,FALSE)),"PostAlerta",IF(ISNUMBER(VLOOKUP(A65,PRE,1,FALSE)),"PreAlerta",""))) -> PostAlerta | M65: =IF(ISNUMBER(A65),(IF(ISNUMBER(VLOOKUP(A65,KEYWORDS,1,FALSE)),"C/PalabrasClaves","S/PalabrasClaves")),"") -> S/PalabrasClaves | P65: 2022 Oct 3 | Q65: Excluir | R65: =LEFT(P65,4) -> 2022 | S65: Oct | Y65: =IF(ISNUMBER(SEARCH("combination", B65)), "combination ", "")
A66: 36204123 | B66: An Evaluation of the Antibacterial Activity of Pterocarpus tinctorius Bark Extract against Enteric Bacteria That Cause Gastroenteritis | C66: Mphande I, Kataba A, Muzandu K, Gono-Bwalya A. | D66: Evid Based Complement Alternat Med. 2022 Sep 27;2022:7973942. doi: 10.1155/2022/7973942. eCollection 2022. | E66: Mphande I | F66: Evid Based Complement Alternat Med | G66: 2022 | H66: 44841 | I66: PMC9532075 | K66: 10.1155/2022/7973942 | L66: =IF(ISNUMBER(VLOOKUP(A66,EXCL,1,FALSE)),"Excluido",IF(ISNUMBER(VLOOKUP(A66,POST,1,FALSE)),"PostAlerta",IF(ISNUMBER(VLOOKUP(A66,PRE,1,FALSE)),"PreAlerta",""))) -> PostAlerta | M66: =IF(ISNUMBER(A66),(IF(ISNUMBER(VLOOKUP(A66,KEYWORDS,1,FALSE)),"C/PalabrasClaves","S/PalabrasClaves")),"") -> S/PalabrasClaves | N66: 2) Nuevos tratamientos | O66: 2a) Productos naturales | P66: 2022 Sep 27 | Q66: Listo | R66: =LEFT(P66,4) -> 2022 | S66: Sep | T66: Enteric bacteria are the leading cause of bacterial gastroenteritis worldwide, particularly in low-income countries. The bark decoction of Pterocarpus tinctorius (Fabaceae) has traditionally been used to treat bacterial gastroenteritis. However, studies reporting the antibacterial activity of Pterocarpus tinctorius are rare. Therefore, this study aimed to evaluate the antibacterial activity of stem bark extract of Pterocarpus tinctorius against Escherichia coli, Salmonella typhi, and Shigella dysenteriae. The powdered bark extract was successively extracted with methanol using the cold continuous maceration method, followed by partitioning the crude methanolic extract to obtain methanolic, hexane, and chloroform subextracts. Three fractions were isolated from the methanolic subextract using ordinary normal phase column chromatography. The antibacterial activity of the extracts and fractions was performed using the agar well diffusion method. The minimum inhibitory concentration (MIC) was determined using the agar well diffusion method. While, minimum bactericidal concentration (MBC) was obtained by the subculturing method. The methanolic subextract was the only extract that showed antibacterial activity against the tested bacteria, and its activity was highest on Shigella dysenteriae followed by Salmonella typhi and was least active on Escherichia coli, with mean inhibition zones of 14.3 ± 0.2, 13.7 ± 0.3, and 12.2 ± 0.1 at 200 mg/mL, respectively. Chloroform subextract showed antibacterial activity only on Shigella dysenteriae, while hexane subextract did not show antibacterial activity against all bacteria tested at 100 mg/mL and 200 mg/mL. Among the three subfractions of methanolic subextract, only one subfraction was active and had both mean minimum inhibitory concentration and a minimum bactericidal concentration against Escherichia coli at 1.25 mg/mL, Salmonella typhi at 1.25 mg/mL, and Shigella dysenteriae at 0.6 mg/mL. The findings of this study support the use of Pterocarpus tinctorius in traditional medicine. Therefore, purification and structural elucidation studies are highly recommended. | U66: No | V66: Yes | W66: No | X66: Methanolic extract of P. tinctorius bark showed antibacterial activity against S. dysenteriae, S. typhi and E. coli, supporting traditional use. | Y66: =IF(ISNUMBER(SEARCH("combination", B66)), "combination ", "")
A67: 36225368 | B67: Relationship between gut microbiota and lymphocyte subsets in Chinese Han patients with spinal cord injury | C67: Pang R, Wang J, Xiong Y, Liu J, Ma X, Gou X, He X, Cheng C, Wang W, Zheng J, Sun M, Bai X, Bai L, Zhang A. | D67: Front Microbiol. 2022 Sep 26;13:986480. doi: 10.3389/fmicb.2022.986480. eCollection 2022. | E67: Pang R | F67: Front Microbiol | G67: 2022 | H67: 44847 | I67: PMC9549169 | K67: 10.3389/fmicb.2022.986480 | L67: =IF(ISNUMBER(VLOOKUP(A67,EXCL,1,FALSE)),"Excluido",IF(ISNUMBER(VLOOKUP(A67,POST,1,FALSE)),"PostAlerta",IF(ISNUMBER(VLOOKUP(A67,PRE,1,FALSE)),"PreAlerta",""))) -> PostAlerta | M67: =IF(ISNUMBER(A67),(IF(ISNUMBER(VLOOKUP(A67,KEYWORDS,1,FALSE)),"C/PalabrasClaves","S/PalabrasClaves")),"") -> S/PalabrasClaves | P67: 2022 Sep 26 | Q67: Excluir | R67: =LEFT(P67,4) -> 2022 | S67: Sep | Y67: =IF(ISNUMBER(SEARCH("combination", B67)), "combination ", "")
A68: 36245565 | B68: Bacteriological Quality of Table Eggs in Moroccan Formal and Informal Sector | C68: El Ftouhy FZ, Nassik S, Nacer S, Kadiri A, Charrat N, Attrassi K, Fagrach A, Bahir MA, Derqaoui S, Hmyene A. | D68: Int J Food Sci. 2022 Sep 24;2022:6223404. doi: 10.1155/2022/6223404. eCollection 2022. | E68: El Ftouhy FZ | F68: Int J Food Sci | G68: 2022 | H68: 44851 | I68: PMC9553687 | K68: 10.1155/2022/6223404 | L68: =IF(ISNUMBER(VLOOKUP(A68,EXCL,1,FALSE)),"Excluido",IF(ISNUMBER(VLOOKUP(A68,POST,1,FALSE)),"PostAlerta",IF(ISNUMBER(VLOOKUP(A68,PRE,1,FALSE)),"PreAlerta",""))) -> PostAlerta | M68: =IF(ISNUMBER(A68),(IF(ISNUMBER(VLOOKUP(A68,KEYWORDS,1,FALSE)),"C/PalabrasClaves","S/PalabrasClaves")),"") -> S/PalabrasClaves | P68: 2022 Sep 24 | Q68: Excluir | R68: =LEFT(P68,4) -> 2022 | S68: Sep | Y68: =IF(ISNUMBER(SEARCH("combination", B68)), "combination ", "")
A69: 36211338 | B69: Bacteroides fragilis ameliorates Cronobacter malonaticus lipopolysaccharide-induced pathological injury through modulation of the intestinal microbiota | C69: Ling N, Zhang X, Forsythe S, Zhang D, Shen Y, Zhang J, Ding Y, Wang J, Wu Q, Ye Y. | D69: Front Immunol. 2022 Sep 22;13:931871. doi: 10.3389/fimmu.2022.931871. eCollection 2022. | E69: Ling N | F69: Front Immunol | G69: 2022 | H69: 44844 | I69: PMC9536467 | K69: 10.3389/fimmu.2022.931871 | L69: =IF(ISNUMBER(VLOOKUP(A69,EXCL,1,FALSE)),"Excluido",IF(ISNUMBER(VLOOKUP(A69,POST,1,FALSE)),"PostAlerta",IF(ISNUMBER(VLOOKUP(A69,PRE,1,FALSE)),"PreAlerta",""))) -> PostAlerta | M69: =IF(ISNUMBER(A69),(IF(ISNUMBER(VLOOKUP(A69,KEYWORDS,1,FALSE)),"C/PalabrasClaves","S/PalabrasClaves")),"") -> S/PalabrasClaves | P69: 2022 Sep 22 | Q69: Excluir | R69: =LEFT(P69,4) -> 2022 | S69: Sep | Y69: =IF(ISNUMBER(SEARCH("combination", B69)), "combination ", "")
A70: 36212487 | B70: Lung microbiome in children with hematological malignancies and lower respiratory tract infections | C70: Zhang Y, Ning H, Zheng W, Liu J, Li F, Chen J. | D70: Front Oncol. 2022 Sep 21;12:932709. doi: 10.3389/fonc.2022.932709. eCollection 2022. | E70: Zhang Y | F70: Front Oncol | G70: 2022 | H70: 44844 | I70: PMC9533145 | K70: 10.3389/fonc.2022.932709 | L70: =IF(ISNUMBER(VLOOKUP(A70,EXCL,1,FALSE)),"Excluido",IF(ISNUMBER(VLOOKUP(A70,POST,1,FALSE)),"PostAlerta",IF(ISNUMBER(VLOOKUP(A70,PRE,1,FALSE)),"PreAlerta",""))) -> PostAlerta | M70: =IF(ISNUMBER(A70),(IF(ISNUMBER(VLOOKUP(A70,KEYWORDS,1,FALSE)),"C/PalabrasClaves","S/PalabrasClaves")),"") -> C/PalabrasClaves | P70: 2022 Sep 21 | Q70: Excluir | R70: =LEFT(P70,4) -> 2022 | S70: Sep | Y70: =IF(ISNUMBER(SEARCH("combination", B70)), "combination ", "")
A71: 36204629 | B71: Regulation of the cecal microbiota community and the fatty liver deposition by the addition of brewers' spent grain to feed of Landes geese | C71: Xu P, Hong Y, Chen P, Wang X, Li S, Wang J, Meng F, Zhou Z, Shi D, Li Z, Cao S, Xiao Y. | D71: Front Microbiol. 2022 Sep 20;13:970563. doi: 10.3389/fmicb.2022.970563. eCollection 2022. | E71: Xu P | F71: Front Microbiol | G71: 2022 | H71: 44841 | I71: PMC9530188 | K71: 10.3389/fmicb.2022.970563 | L71: =IF(ISNUMBER(VLOOKUP(A71,EXCL,1,FALSE)),"Excluido",IF(ISNUMBER(VLOOKUP(A71,POST,1,FALSE)),"PostAlerta",IF(ISNUMBER(VLOOKUP(A71,PRE,1,FALSE)),"PreAlerta",""))) -> PostAlerta | M71: =IF(ISNUMBER(A71),(IF(ISNUMBER(VLOOKUP(A71,KEYWORDS,1,FALSE)),"C/PalabrasClaves","S/PalabrasClaves")),"") -> S/PalabrasClaves | P71: 2022 Sep 20 | Q71: Excluir | R71: =LEFT(P71,4) -> 2022 | S71: Sep | Y71: =IF(ISNUMBER(SEARCH("combination", B71)), "combination ", "")
A72: 36204615 | B72: Controlled human infectious models, a path forward in uncovering immunological correlates of protection: Lessons from enteric fevers studies | C72: Sztein MB, Booth JS. | D72: Front Microbiol. 2022 Sep 20;13:983403. doi: 10.3389/fmicb.2022.983403. eCollection 2022. | E72: Sztein MB | F72: Front Microbiol | G72: 2022 | H72: 44841 | I72: PMC9530043 | K72: 10.3389/fmicb.2022.983403 | L72: =IF(ISNUMBER(VLOOKUP(A72,EXCL,1,FALSE)),"Excluido",IF(ISNUMBER(VLOOKUP(A72,POST,1,FALSE)),"PostAlerta",IF(ISNUMBER(VLOOKUP(A72,PRE,1,FALSE)),"PreAlerta",""))) -> Excluido | M72: =IF(ISNUMBER(A72),(IF(ISNUMBER(VLOOKUP(A72,KEYWORDS,1,FALSE)),"C/PalabrasClaves","S/PalabrasClaves")),"") -> C/PalabrasClaves | P72: 2022 Sep 20 | Q72: Excluir | R72: =LEFT(P72,4) -> 2022 | S72: Sep | Y72: =IF(ISNUMBER(SEARCH("combination", B72)), "combination ", "")
A73: 36187995 | B73: Association between body weight and distal gut microbes in Hainan black goats at weaning age | C73: Li L, Li K, Bian Z, Chen Z, Li B, Cui K, Wang F. | D73: Front Microbiol. 2022 Sep 16;13:951473. doi: 10.3389/fmicb.2022.951473. eCollection 2022. | E73: Li L | F73: Front Microbiol | G73: 2022 | H73: 44837 | I73: PMC9523243 | K73: 10.3389/fmicb.2022.951473 | L73: =IF(ISNUMBER(VLOOKUP(A73,EXCL,1,FALSE)),"Excluido",IF(ISNUMBER(VLOOKUP(A73,POST,1,FALSE)),"PostAlerta",IF(ISNUMBER(VLOOKUP(A73,PRE,1,FALSE)),"PreAlerta",""))) -> PostAlerta | M73: =IF(ISNUMBER(A73),(IF(ISNUMBER(VLOOKUP(A73,KEYWORDS,1,FALSE)),"C/PalabrasClaves","S/PalabrasClaves")),"") -> S/PalabrasClaves | P73: 2022 Sep 16 | Q73: Excluir | R73: =LEFT(P73,4) -> 2022 | S73: Sep | Y73: =IF(ISNUMBER(SEARCH("combination", B73)), "combination ", "")
A74: 36187958 | B74: pH mediated assemblage of carbon, nitrogen, and sulfur related microbial communities in petroleum reservoirs | C74: Li Y, Zhang Y, Xue S. | D74: Front Microbiol. 2022 Sep 14;13:952285. doi: 10.3389/fmicb.2022.952285. eCollection 2022. | E74: Li Y | F74: Front Microbiol | G74: 2022 | H74: 44837 | I74: PMC9515653 | K74: 10.3389/fmicb.2022.952285 | L74: =IF(ISNUMBER(VLOOKUP(A74,EXCL,1,FALSE)),"Excluido",IF(ISNUMBER(VLOOKUP(A74,POST,1,FALSE)),"PostAlerta",IF(ISNUMBER(VLOOKUP(A74,PRE,1,FALSE)),"PreAlerta",""))) -> PostAlerta | M74: =IF(ISNUMBER(A74),(IF(ISNUMBER(VLOOKUP(A74,KEYWORDS,1,FALSE)),"C/PalabrasClaves","S/PalabrasClaves")),"") -> S/PalabrasClaves | P74: 2022 Sep 14 | Q74: Excluir | R74: =LEFT(P74,4) -> 2022 | S74: Sep | Y74: =IF(ISNUMBER(SEARCH("combination", B74)), "combination ", "")
A75: 36203568 | B75: Complement-mediated serum bactericidal activity of antibodies elicited by the Shigella sonnei GMMA vaccine in adults from a shigellosis-endemic country: Exploratory analysis of a Phase 2a randomized study | C75: Kapulu MC, Nakakana U, Sciré AS, Sarakinou E, Conti V, Rossi O, Acquaviva A, Necchi F, Obiero CW, Martin LB, Bejon P, Njuguna P, Micoli F, Podda A. | D75: Front Immunol. 2022 Sep 9;13:971866. doi: 10.3389/fimmu.2022.971866. eCollection 2022. | E75: Kapulu MC | F75: Front Immunol | G75: 2022 | H75: 44841 | I75: PMC9531247 | K75: 10.3389/fimmu.2022.971866 | L75: =IF(ISNUMBER(VLOOKUP(A75,EXCL,1,FALSE)),"Excluido",IF(ISNUMBER(VLOOKUP(A75,POST,1,FALSE)),"PostAlerta",IF(ISNUMBER(VLOOKUP(A75,PRE,1,FALSE)),"PreAlerta",""))) -> Excluido | M75: =IF(ISNUMBER(A75),(IF(ISNUMBER(VLOOKUP(A75,KEYWORDS,1,FALSE)),"C/PalabrasClaves","S/PalabrasClaves")),"") -> S/PalabrasClaves | P75: 2022 Sep 9 | Q75: Excluir | R75: =LEFT(P75,4) -> 2022 | S75: Sep | Y75: =IF(ISNUMBER(SEARCH("combination", B75)), "combination ", "")
A76: 36159472 | B76: Maternal resveratrol regulates the growth performance, antioxidant capacity, and intestinal health of suckling piglets through intestinal microorganisms at high summer temperatures | C76: Zhao Y, Huang Y, Gao K, Wen X, Hu S, Wang L, Jiang Z, Xiao H. | D76: Front Nutr. 2022 Sep 9;9:971496. doi: 10.3389/fnut.2022.971496. eCollection 2022. | E76: Zhao Y | F76: Front Nutr | G76: 2022 | H76: 44830 | I76: PMC9501877 | K76: 10.3389/fnut.2022.971496 | L76: =IF(ISNUMBER(VLOOKUP(A76,EXCL,1,FALSE)),"Excluido",IF(ISNUMBER(VLOOKUP(A76,POST,1,FALSE)),"PostAlerta",IF(ISNUMBER(VLOOKUP(A76,PRE,1,FALSE)),"PreAlerta",""))) -> PostAlerta | M76: =IF(ISNUMBER(A76),(IF(ISNUMBER(VLOOKUP(A76,KEYWORDS,1,FALSE)),"C/PalabrasClaves","S/PalabrasClaves")),"") -> S/PalabrasClaves | N76: 4) otros | O76: 2a) Productos naturales | P76: 2022 Sep 9 | Q76: Listo | R76: =LEFT(P76,4) -> 2022 | S76: Sep | Y76: =IF(ISNUMBER(SEARCH("combination", B76)), "combination ", "")
A77: 36157193 | B77: Characterization of gut microbiota dysbiosis of diarrheic adult yaks through 16S rRNA gene sequences | C77: Wu ZL, Wei R, Tan X, Yang D, Liu D, Zhang J, Wang W. | D77: Front Vet Sci. 2022 Sep 9;9:946906. doi: 10.3389/fvets.2022.946906. eCollection 2022. | E77: Wu ZL | F77: Front Vet Sci | G77: 2022 | H77: 44830 | I77: PMC9500532 | K77: 10.3389/fvets.2022.946906 | L77: =IF(ISNUMBER(VLOOKUP(A77,EXCL,1,FALSE)),"Excluido",IF(ISNUMBER(VLOOKUP(A77,POST,1,FALSE)),"PostAlerta",IF(ISNUMBER(VLOOKUP(A77,PRE,1,FALSE)),"PreAlerta",""))) -> PostAlerta | M77: =IF(ISNUMBER(A77),(IF(ISNUMBER(VLOOKUP(A77,KEYWORDS,1,FALSE)),"C/PalabrasClaves","S/PalabrasClaves")),"") -> S/PalabrasClaves | P77: 2022 Sep 9 | Q77: Excluir | R77: =LEFT(P77,4) -> 2022 | S77: Sep | Y77: =IF(ISNUMBER(SEARCH("combination", B77)), "combination ", "")
A78: 36160211 | B78: Detection of Escherichia coli, Pseudomonas aeruginosa, Salmonella paratyphoid B, and Shigella dysentery in live Bacillus licheniformis products using propidium monoazide-real-time-quantitative polymerase chain reaction | C78: Zheng X, Wang Y, Gong W, Cai Q, Li J, Wu J. | D78: Front Microbiol. 2022 Sep 8;13:996794. doi: 10.3389/fmicb.2022.996794. eCollection 2022. | E78: Zheng X | F78: Front Microbiol | G78: 2022 | H78: 44830 | I78: PMC9493680 | K78: 10.3389/fmicb.2022.996794 | L78: =IF(ISNUMBER(VLOOKUP(A78,EXCL,1,FALSE)),"Excluido",IF(ISNUMBER(VLOOKUP(A78,POST,1,FALSE)),"PostAlerta",IF(ISNUMBER(VLOOKUP(A78,PRE,1,FALSE)),"PreAlerta",""))) -> PostAlerta | M78: =IF(ISNUMBER(A78),(IF(ISNUMBER(VLOOKUP(A78,KEYWORDS,1,FALSE)),"C/PalabrasClaves","S/PalabrasClaves")),"") -> S/PalabrasClaves | P78: 2022 Sep 8 | Q78: Excluir | R78: =LEFT(P78,4) -> 2022 | S78: Sep | Y78: =IF(ISNUMBER(SEARCH("combination", B78)), "combination ", "")
A79: 36067170 | B79: Longitudinal analysis of the rectal microbiome in dogs with diabetes mellitus after initiation of insulin therapy | C79: Laia NL, Barko PC, Sullivan DR, McMichael MA, Williams DA, Reinhart JM. | D79: PLoS One. 2022 Sep 6;17(9):e0273792. doi: 10.1371/journal.pone.0273792. eCollection 2022. | E79: Laia NL | F79: PLoS One | G79: 2022 | H79: 44810 | I79: PMC9447884 | K79: 10.1371/journal.pone.0273792 | L79: =IF(ISNUMBER(VLOOKUP(A79,EXCL,1,FALSE)),"Excluido",IF(ISNUMBER(VLOOKUP(A79,POST,1,FALSE)),"PostAlerta",IF(ISNUMBER(VLOOKUP(A79,PRE,1,FALSE)),"PreAlerta",""))) -> PostAlerta | M79: =IF(ISNUMBER(A79),(IF(ISNUMBER(VLOOKUP(A79,KEYWORDS,1,FALSE)),"C/PalabrasClaves","S/PalabrasClaves")),"") -> S/PalabrasClaves | P79: 2022 Sep 6 | Q79: Excluir | R79: =LEFT(P79,4) -> 2022 | S79: Sep | Y79: =IF(ISNUMBER(SEARCH("combination", B79)), "combination ", "")
A80: 36133313 | B80: Specific gut bacterial and fungal microbiota pattern in the first half of pregnancy is linked to the development of gestational diabetes mellitus in the cohort including obese women | C80: Vavreckova M, Galanova N, Kostovcik M, Krystynik O, Ivanovova E, Roubalova R, Jiraskova Zakostelska Z, Friedecky D, Friedecka J, Haluzik M, Karasek D, Kostovcikova K. | D80: Front Endocrinol (Lausanne). 2022 Sep 5;13:970825. doi: 10.3389/fendo.2022.970825. eCollection 2022. | E80: Vavreckova M | F80: Front Endocrinol (Lausanne) | G80: 2022 | H80: 44826 | I80: PMC9484836 | K80: 10.3389/fendo.2022.970825 | L80: =IF(ISNUMBER(VLOOKUP(A80,EXCL,1,FALSE)),"Excluido",IF(ISNUMBER(VLOOKUP(A80,POST,1,FALSE)),"PostAlerta",IF(ISNUMBER(VLOOKUP(A80,PRE,1,FALSE)),"PreAlerta",""))) -> PostAlerta | M80: =IF(ISNUMBER(A80),(IF(ISNUMBER(VLOOKUP(A80,KEYWORDS,1,FALSE)),"C/PalabrasClaves","S/PalabrasClaves")),"") -> S/PalabrasClaves | P80: 2022 Sep 5 | Q80: Excluir | R80: =LEFT(P80,4) -> 2022 | S80: Sep | Y80: =IF(ISNUMBER(SEARCH("combination", B80)), "combination ", "")
A81: 36118024 | B81: Impact of gut microbiome on dyslipidemia in japanese adults: Assessment of the Shika-machi super preventive health examination results for causal inference | C81: Miyajima Y, Karashima S, Ogai K, Taniguchi K, Ogura K, Kawakami M, Nambo H, Kometani M, Aono D, Demura M, Yoneda T, Tsujiguchi H, Hara A, Nakamura H, Okamoto S. | D81: Front Cell Infect Microbiol. 2022 Sep 2;12:908997. doi: 10.3389/fcimb.2022.908997. eCollection 2022. | E81: Miyajima Y | F81: Front Cell Infect Microbiol | G81: 2022 | H81: 44823 | I81: PMC9479221 | K81: 10.3389/fcimb.2022.908997 | L81: =IF(ISNUMBER(VLOOKUP(A81,EXCL,1,FALSE)),"Excluido",IF(ISNUMBER(VLOOKUP(A81,POST,1,FALSE)),"PostAlerta",IF(ISNUMBER(VLOOKUP(A81,PRE,1,FALSE)),"PreAlerta",""))) -> PostAlerta | M81: =IF(ISNUMBER(A81),(IF(ISNUMBER(VLOOKUP(A81,KEYWORDS,1,FALSE)),"C/PalabrasClaves","S/PalabrasClaves")),"") -> S/PalabrasClaves | P81: 2022 Sep 2 | Q81: Excluir | R81: =LEFT(P81,4) -> 2022 | S81: Sep | Y81: =IF(ISNUMBER(SEARCH("combination", B81)), "combination ", "")
A82: 36048838 | B82: Bacteriological quality and antimicrobial susceptibility profiles of isolates of ready-to-eat raw minced meat from hotels and restaurants in Arba Minch, Ethiopia | C82: Tonjo T, Manilal A, Seid M. | D82: PLoS One. 2022 Sep 1;17(9):e0273790. doi: 10.1371/journal.pone.0273790. eCollection 2022. | E82: Tonjo T | F82: PLoS One | G82: 2022 | H82: 44805 | I82: PMC9436051 | K82: 10.1371/journal.pone.0273790 | L82: =IF(ISNUMBER(VLOOKUP(A82,EXCL,1,FALSE)),"Excluido",IF(ISNUMBER(VLOOKUP(A82,POST,1,FALSE)),"PostAlerta",IF(ISNUMBER(VLOOKUP(A82,PRE,1,FALSE)),"PreAlerta",""))) -> PostAlerta | M82: =IF(ISNUMBER(A82),(IF(ISNUMBER(VLOOKUP(A82,KEYWORDS,1,FALSE)),"C/PalabrasClaves","S/PalabrasClaves")),"") -> S/PalabrasClaves | P82: 2022 Sep 1 | Q82: Excluir | R82: =LEFT(P82,4) -> 2022 | S82: Sep | Y82: =IF(ISNUMBER(SEARCH("combination", B82)), "combination ", "")
A83: 34727811 | B83: A new antimicrobial nor-friedelane-type triterpenoid and other constituents from Plectranthus glandulosus Hook. f. (Lamiaceae) | C83: Tedonkeu AT, Tamokou JD, Mpetga JDS, Nzogong RT, Kengne IC, Hao XJ, Tene M. | D83: Nat Prod Res. 2022 Sep;36(18):4587-4596. doi: 10.1080/14786419.2021.1999946. Epub 2021 Nov 2. | E83: Tedonkeu AT | F83: Nat Prod Res | G83: 2022 | H83: 44503 | K83: 10.1080/14786419.2021.1999946 | L83: =IF(ISNUMBER(VLOOKUP(A83,EXCL,1,FALSE)),"Excluido",IF(ISNUMBER(VLOOKUP(A83,POST,1,FALSE)),"PostAlerta",IF(ISNUMBER(VLOOKUP(A83,PRE,1,FALSE)),"PreAlerta",""))) -> PostAlerta | M83: =IF(ISNUMBER(A83),(IF(ISNUMBER(VLOOKUP(A83,KEYWORDS,1,FALSE)),"C/PalabrasClaves","S/PalabrasClaves")),"") -> S/PalabrasClaves | N83: 2) Nuevos tratamientos | O83: 2a) Productos naturales | P83: 2022 Sep | Q83: Listo | R83: =LEFT(P83,4) -> 2022 | S83: Sep | T83: Chemical investigation of the ethanol extract from the whole plant of Plectranthus glandulosus led to the isolation of a new nor-triterpenoid (1) along with seventeen known compounds (2-18) including seven triterpenoids, nine flavonoids and one steroid. Their structures were established on the basis of 1D- and 2D-NMR, IR, and MS experiments, and by comparison of their spectroscopic data with those of similar compounds reported in the literature. The EtOH extract and some isolated triterpenoids (1-4 and 13) were subjected to in vitro antimicrobial assays against a panel of pathogenic microorganisms, including Gram-positive and Gram-negative bacteria, and fungi using broth microdilution method. The EtOH extract displayed moderate activity (MIC = 512 µg/mL) against Staphylococcus aureus MSSA1, Shigella flexneri SDINT and Cryptococcus neoformans H99. Compounds 1, 4 and 13 showed the most potent antimicrobial effect with MICs of 32-256 µg/mL. | U83: No | V83: Yes | W83: No | X83: EtOH extract and triterpenoids from P. glandulosus showed antimicrobial activity against S. aureus, S. flexneri and C. neoformans. | Y83: =IF(ISNUMBER(SEARCH("combination", B83)), "combination ", "")
A84: 36118208 | B84: Correlation in endophytic fungi community diversity and bioactive compounds of Sophora alopecuroides | C84: Ju M, Zhang Q, Wang R, Yan S, Li Z, Li P, Gu P. | D84: Front Microbiol. 2022 Aug 31;13:955647. doi: 10.3389/fmicb.2022.955647. eCollection 2022. | E84: Ju M | F84: Front Microbiol | G84: 2022 | H84: 44823 | I84: PMC9475766 | K84: 10.3389/fmicb.2022.955647 | L84: =IF(ISNUMBER(VLOOKUP(A84,EXCL,1,FALSE)),"Excluido",IF(ISNUMBER(VLOOKUP(A84,POST,1,FALSE)),"PostAlerta",IF(ISNUMBER(VLOOKUP(A84,PRE,1,FALSE)),"PreAlerta",""))) -> PostAlerta | M84: =IF(ISNUMBER(A84),(IF(ISNUMBER(VLOOKUP(A84,KEYWORDS,1,FALSE)),"C/PalabrasClaves","S/PalabrasClaves")),"") -> S/PalabrasClaves | P84: 2022 Aug 31 | Q84: Excluir | R84: =LEFT(P84,4) -> 2022 | S84: Aug | Y84: =IF(ISNUMBER(SEARCH("combination", B84)), "combination ", "")
A85: 36091586 | B85: Antidiarrheal and Antibacterial Activities of Calpurnia aurea: Benth Seed Different Extracts | C85: Bogale A, Alemayehu H, Nedi T, Engidawork E. | D85: Evid Based Complement Alternat Med. 2022 Aug 31;2022:9582687. doi: 10.1155/2022/9582687. eCollection 2022. | E85: Bogale A | F85: Evid Based Complement Alternat Med | G85: 2022 | H85: 44816 | I85: PMC9451978 | K85: 10.1155/2022/9582687 | L85: =IF(ISNUMBER(VLOOKUP(A85,EXCL,1,FALSE)),"Excluido",IF(ISNUMBER(VLOOKUP(A85,POST,1,FALSE)),"PostAlerta",IF(ISNUMBER(VLOOKUP(A85,PRE,1,FALSE)),"PreAlerta",""))) -> PostAlerta | M85: =IF(ISNUMBER(A85),(IF(ISNUMBER(VLOOKUP(A85,KEYWORDS,1,FALSE)),"C/PalabrasClaves","S/PalabrasClaves")),"") -> S/PalabrasClaves | N85: 2) Nuevos tratamientos | O85: 2a) Productos naturales | P85: 2022 Aug 31 | Q85: Listo | R85: =LEFT(P85,4) -> 2022 | S85: Aug | T85: Background: Calpurnia aurea is believed to have antidiarrheal potential but with limited scientific evidence. This study aimed investigating antidiarrheal and antibacterial activity of aqueous and 80% methanol seed extracts of the plant in mice and selected diarrhea-causing bacterial strains, respectively. Methods: Castor oil-induced diarrhea, prostaglandin-induced enteropooling, and castor oil-induced charcoal meal test models in mice of either sex using three dose levels (60, 120, and 240 mg/kg) were applied to evaluate antidiarrheal activity. Parameters, including onset, number, wet stool weight, weight and volume of secretion, and intestinal motility, were taken into consideration. The antibacterial activity was assessed on Shigella soni, Salmonella typhimurium, Escherichia coli, Staphylococcus aureus, and Pseudomonas aeruginosa using disk diffusion and microdilution techniques. Results: Compared to controls, pretreatment of mice at the graded dose (60, 120, and 240 mg/kg) resulted in a significant (p < 0.05) drop in frequency of wet stools and watery content of diarrhea as well as in delaying onset of diarrhea. Both extracts exhibited inhibition of diarrhea in a dose-dependent manner in all models used. The extracts also showed significant (p < 0.05) reduction in intestinal motility in castor oil-induced models. Both extracts showed a marginal activity against the selected bacterial strains; a better effect was seen with 80% methanol seed extract. Conclusion: Both extracts of the plant have beneficial effect in controlling diarrhea. This finding supports the use of the plant as a traditional antidiarrheal remedy. | U85: No | V85: Yes | W85: No | X85: Calpurnia aurea extracts showed significant antidiarrheal effects in mice, supporting its use as a traditional remedy for diarrhea. | Y85: =IF(ISNUMBER(SEARCH("combination", B85)), "combination ", "")
A86: 36093192 | B86: The relationship between the number of stenotic coronary arteries and the gut microbiome in coronary heart disease patients | C86: Yu H, Li L, Deng Y, Zhang G, Jiang M, Huang H, Li C, Lv Z, Zhou Y, Liu X. | D86: Front Cell Infect Microbiol. 2022 Aug 26;12:903828. doi: 10.3389/fcimb.2022.903828. eCollection 2022. | E86: Yu H | F86: Front Cell Infect Microbiol | G86: 2022 | H86: 44816 | I86: PMC9458979 | K86: 10.3389/fcimb.2022.903828 | L86: =IF(ISNUMBER(VLOOKUP(A86,EXCL,1,FALSE)),"Excluido",IF(ISNUMBER(VLOOKUP(A86,POST,1,FALSE)),"PostAlerta",IF(ISNUMBER(VLOOKUP(A86,PRE,1,FALSE)),"PreAlerta",""))) -> PostAlerta | M86: =IF(ISNUMBER(A86),(IF(ISNUMBER(VLOOKUP(A86,KEYWORDS,1,FALSE)),"C/PalabrasClaves","S/PalabrasClaves")),"") -> S/PalabrasClaves | P86: 2022 Aug 26 | Q86: Excluir | R86: =LEFT(P86,4) -> 2022 | S86: Aug | Y86: =IF(ISNUMBER(SEARCH("combination", B86)), "combination ", "")
A87: 36090116 | B87: Distinguishing the milk microbiota of healthy goats and goats diagnosed with subclinical mastitis, clinical mastitis, and gangrenous mastitis | C87: Polveiro RC, Vidigal PMP, de Oliveira Mendes TA, Yamatogi RS, da Silva LS, Fujikura JM, Da Costa MM, Moreira MAS. | D87: Front Microbiol. 2022 Aug 25;13:918706. doi: 10.3389/fmicb.2022.918706. eCollection 2022. | E87: Polveiro RC | F87: Front Microbiol | G87: 2022 | H87: 44816 | I87: PMC9453028 | K87: 10.3389/fmicb.2022.918706 | L87: =IF(ISNUMBER(VLOOKUP(A87,EXCL,1,FALSE)),"Excluido",IF(ISNUMBER(VLOOKUP(A87,POST,1,FALSE)),"PostAlerta",IF(ISNUMBER(VLOOKUP(A87,PRE,1,FALSE)),"PreAlerta",""))) -> PostAlerta | M87: =IF(ISNUMBER(A87),(IF(ISNUMBER(VLOOKUP(A87,KEYWORDS,1,FALSE)),"C/PalabrasClaves","S/PalabrasClaves")),"") -> S/PalabrasClaves | P87: 2022 Aug 25 | Q87: Excluir | R87: =LEFT(P87,4) -> 2022 | S87: Aug | Y87: =IF(ISNUMBER(SEARCH("combination", B87)), "combination ", "")
A88: 36090066 | B88: The response of cecal microbiota to inflammatory state induced by Salmonella enterica serovar Enteritidis | C88: Hu G, Liu L, Miao X, Zhao Y, Peng Y, Liu L, Li X. | D88: Front Microbiol. 2022 Aug 25;13:963678. doi: 10.3389/fmicb.2022.963678. eCollection 2022. | E88: Hu G | F88: Front Microbiol | G88: 2022 | H88: 44816 | I88: PMC9453680 | K88: 10.3389/fmicb.2022.963678 | L88: =IF(ISNUMBER(VLOOKUP(A88,EXCL,1,FALSE)),"Excluido",IF(ISNUMBER(VLOOKUP(A88,POST,1,FALSE)),"PostAlerta",IF(ISNUMBER(VLOOKUP(A88,PRE,1,FALSE)),"PreAlerta",""))) -> PostAlerta | M88: =IF(ISNUMBER(A88),(IF(ISNUMBER(VLOOKUP(A88,KEYWORDS,1,FALSE)),"C/PalabrasClaves","S/PalabrasClaves")),"") -> S/PalabrasClaves | P88: 2022 Aug 25 | Q88: Excluir | R88: =LEFT(P88,4) -> 2022 | S88: Aug | Y88: =IF(ISNUMBER(SEARCH("combination", B88)), "combination ", "")
A89: 36046765 | B89: Antimicrobial Resistance Profile of Enterobacteriaceae and Drinking Water Quality Among Households in Bule Hora Town, South Ethiopia | C89: Dhengesu D, Lemma H, Asefa L, Tilahun D. | D89: Risk Manag Healthc Policy. 2022 Aug 25;15:1569-1580. doi: 10.2147/RMHP.S370149. eCollection 2022. | E89: Dhengesu D | F89: Risk Manag Healthc Policy | G89: 2022 | H89: 44805 | I89: PMC9423114 | K89: 10.2147/RMHP.S370149 | L89: =IF(ISNUMBER(VLOOKUP(A89,EXCL,1,FALSE)),"Excluido",IF(ISNUMBER(VLOOKUP(A89,POST,1,FALSE)),"PostAlerta",IF(ISNUMBER(VLOOKUP(A89,PRE,1,FALSE)),"PreAlerta",""))) -> PostAlerta | M89: =IF(ISNUMBER(A89),(IF(ISNUMBER(VLOOKUP(A89,KEYWORDS,1,FALSE)),"C/PalabrasClaves","S/PalabrasClaves")),"") -> C/PalabrasClaves | P89: 2022 Aug 25 | Q89: Excluir | R89: =LEFT(P89,4) -> 2022 | S89: Aug | Y89: =IF(ISNUMBER(SEARCH("combination", B89)), "combination ", "")
A90: 36093202 | B90: Human circulating bacteria and dysbiosis in non-infectious diseases | C90: Goraya MU, Li R, Mannan A, Gu L, Deng H, Wang G. | D90: Front Cell Infect Microbiol. 2022 Aug 24;12:932702. doi: 10.3389/fcimb.2022.932702. eCollection 2022. | E90: Goraya MU | F90: Front Cell Infect Microbiol | G90: 2022 | H90: 44816 | I90: PMC9448904 | K90: 10.3389/fcimb.2022.932702 | L90: =IF(ISNUMBER(VLOOKUP(A90,EXCL,1,FALSE)),"Excluido",IF(ISNUMBER(VLOOKUP(A90,POST,1,FALSE)),"PostAlerta",IF(ISNUMBER(VLOOKUP(A90,PRE,1,FALSE)),"PreAlerta",""))) -> Excluido | M90: =IF(ISNUMBER(A90),(IF(ISNUMBER(VLOOKUP(A90,KEYWORDS,1,FALSE)),"C/PalabrasClaves","S/PalabrasClaves")),"") -> S/PalabrasClaves | P90: 2022 Aug 24 | Q90: Excluir | R90: =LEFT(P90,4) -> 2022 | S90: Aug | Y90: =IF(ISNUMBER(SEARCH("combination", B90)), "combination ", "")
A91: 36093113 | B91: Acupuncture ameliorates breast cancer-related fatigue by regulating the gut microbiota-gut-brain axis | C91: Lv Z, Liu R, Su K, Gu Y, Fang L, Fan Y, Gao J, Ruan X, Feng X. | D91: Front Endocrinol (Lausanne). 2022 Aug 24;13:921119. doi: 10.3389/fendo.2022.921119. eCollection 2022. | E91: Lv Z | F91: Front Endocrinol (Lausanne) | G91: 2022 | H91: 44816 | I91: PMC9449876 | K91: 10.3389/fendo.2022.921119 | L91: =IF(ISNUMBER(VLOOKUP(A91,EXCL,1,FALSE)),"Excluido",IF(ISNUMBER(VLOOKUP(A91,POST,1,FALSE)),"PostAlerta",IF(ISNUMBER(VLOOKUP(A91,PRE,1,FALSE)),"PreAlerta",""))) -> PostAlerta | M91: =IF(ISNUMBER(A91),(IF(ISNUMBER(VLOOKUP(A91,KEYWORDS,1,FALSE)),"C/PalabrasClaves","S/PalabrasClaves")),"") -> S/PalabrasClaves | P91: 2022 Aug 24 | Q91: Excluir | R91: =LEFT(P91,4) -> 2022 | S91: Aug | Y91: =IF(ISNUMBER(SEARCH("combination", B91)), "combination ", "")
A92: 36090083 | B92: Characteristics of gut microbiota of term small gestational age infants within 1 week and their relationship with neurodevelopment at 6 months | C92: Chen X, Yan Z, Liu L, Zhang R, Zhang X, Peng C, Geng Y, Zhou F, Han Y, Hou X. | D92: Front Microbiol. 2022 Aug 24;13:912968. doi: 10.3389/fmicb.2022.912968. eCollection 2022. | E92: Chen X | F92: Front Microbiol | G92: 2022 | H92: 44816 | I92: PMC9449527 | K92: 10.3389/fmicb.2022.912968 | L92: =IF(ISNUMBER(VLOOKUP(A92,EXCL,1,FALSE)),"Excluido",IF(ISNUMBER(VLOOKUP(A92,POST,1,FALSE)),"PostAlerta",IF(ISNUMBER(VLOOKUP(A92,PRE,1,FALSE)),"PreAlerta",""))) -> PostAlerta | M92: =IF(ISNUMBER(A92),(IF(ISNUMBER(VLOOKUP(A92,KEYWORDS,1,FALSE)),"C/PalabrasClaves","S/PalabrasClaves")),"") -> S/PalabrasClaves | P92: 2022 Aug 24 | Q92: Excluir | R92: =LEFT(P92,4) -> 2022 | S92: Aug | Y92: =IF(ISNUMBER(SEARCH("combination", B92)), "combination ", "")
A93: 36071958 | B93: Integrative analysis of gut microbiota and fecal metabolites in metabolic associated fatty liver disease patients | C93: Yang L, Dai Y, He H, Liu Z, Liao S, Zhang Y, Liao G, An Z. | D93: Front Microbiol. 2022 Aug 22;13:969757. doi: 10.3389/fmicb.2022.969757. eCollection 2022. | E93: Yang L | F93: Front Microbiol | G93: 2022 | H93: 44812 | I93: PMC9441872 | K93: 10.3389/fmicb.2022.969757 | L93: =IF(ISNUMBER(VLOOKUP(A93,EXCL,1,FALSE)),"Excluido",IF(ISNUMBER(VLOOKUP(A93,POST,1,FALSE)),"PostAlerta",IF(ISNUMBER(VLOOKUP(A93,PRE,1,FALSE)),"PreAlerta",""))) -> PostAlerta | M93: =IF(ISNUMBER(A93),(IF(ISNUMBER(VLOOKUP(A93,KEYWORDS,1,FALSE)),"C/PalabrasClaves","S/PalabrasClaves")),"") -> S/PalabrasClaves | P93: 2022 Aug 22 | Q93: Excluir | R93: =LEFT(P93,4) -> 2022 | S93: Aug | Y93: =IF(ISNUMBER(SEARCH("combination", B93)), "combination ", "")
A94: 36061858 | B94: Liujunanwei decoction attenuates cisplatin-induced nausea and vomiting in a Rat-Pica model partially mediated by modulating the gut micsrobiome | C94: Chen D, Guo Y, Yang Y. | D94: Front Cell Infect Microbiol. 2022 Aug 19;12:876781. doi: 10.3389/fcimb.2022.876781. eCollection 2022. | E94: Chen D | F94: Front Cell Infect Microbiol | G94: 2022 | H94: 44809 | I94: PMC9437319 | K94: 10.3389/fcimb.2022.876781 | L94: =IF(ISNUMBER(VLOOKUP(A94,EXCL,1,FALSE)),"Excluido",IF(ISNUMBER(VLOOKUP(A94,POST,1,FALSE)),"PostAlerta",IF(ISNUMBER(VLOOKUP(A94,PRE,1,FALSE)),"PreAlerta",""))) -> PostAlerta | M94: =IF(ISNUMBER(A94),(IF(ISNUMBER(VLOOKUP(A94,KEYWORDS,1,FALSE)),"C/PalabrasClaves","S/PalabrasClaves")),"") -> S/PalabrasClaves | P94: 2022 Aug 19 | Q94: Excluir | R94: =LEFT(P94,4) -> 2022 | S94: Aug | Y94: =IF(ISNUMBER(SEARCH("combination", B94)), "combination ", "")
A95: 36051771 | B95: Host species and habitats shape the bacterial community of gut microbiota of three non-human primates: Siamangs, white-handed gibbons, and Bornean orangutans | C95: Ying C, Siao YS, Chen WJ, Chen YT, Chen SL, Chen YL, Hsu JT. | D95: Front Microbiol. 2022 Aug 16;13:920190. doi: 10.3389/fmicb.2022.920190. eCollection 2022. | E95: Ying C | F95: Front Microbiol | G95: 2022 | H95: 44806 | I95: PMC9424820 | K95: 10.3389/fmicb.2022.920190 | L95: =IF(ISNUMBER(VLOOKUP(A95,EXCL,1,FALSE)),"Excluido",IF(ISNUMBER(VLOOKUP(A95,POST,1,FALSE)),"PostAlerta",IF(ISNUMBER(VLOOKUP(A95,PRE,1,FALSE)),"PreAlerta",""))) -> PostAlerta | M95: =IF(ISNUMBER(A95),(IF(ISNUMBER(VLOOKUP(A95,KEYWORDS,1,FALSE)),"C/PalabrasClaves","S/PalabrasClaves")),"") -> S/PalabrasClaves | P95: 2022 Aug 16 | Q95: Excluir | R95: =LEFT(P95,4) -> 2022 | S95: Aug | Y95: =IF(ISNUMBER(SEARCH("combination", B95)), "combination ", "")
A96: 36046136 | B96: Milk fat globule membrane supplementation to obese rats during pregnancy and lactation promotes neurodevelopment in offspring via modulating gut microbiota | C96: Yuan Q, Gong H, Du M, Li T, Mao X. | D96: Front Nutr. 2022 Aug 15;9:945052. doi: 10.3389/fnut.2022.945052. eCollection 2022. | E96: Yuan Q | F96: Front Nutr | G96: 2022 | H96: 44805 | I96: PMC9421050 | K96: 10.3389/fnut.2022.945052 | L96: =IF(ISNUMBER(VLOOKUP(A96,EXCL,1,FALSE)),"Excluido",IF(ISNUMBER(VLOOKUP(A96,POST,1,FALSE)),"PostAlerta",IF(ISNUMBER(VLOOKUP(A96,PRE,1,FALSE)),"PreAlerta",""))) -> PostAlerta | M96: =IF(ISNUMBER(A96),(IF(ISNUMBER(VLOOKUP(A96,KEYWORDS,1,FALSE)),"C/PalabrasClaves","S/PalabrasClaves")),"") -> S/PalabrasClaves | P96: 2022 Aug 15 | Q96: Excluir | R96: =LEFT(P96,4) -> 2022 | S96: Aug | Y96: =IF(ISNUMBER(SEARCH("combination", B96)), "combination ", "")
A97: 36045690 | B97: Correlation between altered gut microbiota and elevated inflammation markers in patients with Crohn's disease | C97: Hu J, Cheng S, Yao J, Lin X, Li Y, Wang W, Weng J, Zou Y, Zhu L, Zhi M. | D97: Front Immunol. 2022 Aug 15;13:947313. doi: 10.3389/fimmu.2022.947313. eCollection 2022. | E97: Hu J | F97: Front Immunol | G97: 2022 | H97: 44805 | I97: PMC9420857 | K97: 10.3389/fimmu.2022.947313 | L97: =IF(ISNUMBER(VLOOKUP(A97,EXCL,1,FALSE)),"Excluido",IF(ISNUMBER(VLOOKUP(A97,POST,1,FALSE)),"PostAlerta",IF(ISNUMBER(VLOOKUP(A97,PRE,1,FALSE)),"PreAlerta",""))) -> PostAlerta | M97: =IF(ISNUMBER(A97),(IF(ISNUMBER(VLOOKUP(A97,KEYWORDS,1,FALSE)),"C/PalabrasClaves","S/PalabrasClaves")),"") -> S/PalabrasClaves | P97: 2022 Aug 15 | Q97: Excluir | R97: =LEFT(P97,4) -> 2022 | S97: Aug | Y97: =IF(ISNUMBER(SEARCH("combination", B97)), "combination ", "")
... A103: 35979485 | B103: The integrase of genomic island GIsul2 mediates the mobilization of GIsul2 and ISCR-related element CR2-sul2 unit through site-specific recombination | C103: Zhang G, Cui Q, Li J, Guo R, Leclercq SO, Du L, Tang N, Song Y, Wang C, Zhao F, Feng J. | D103: Front Microbiol. 2022 Aug 1;13:905865. doi: 10.3389/fmicb.2022.905865. eCollection 2022. | E103: Zhang G | F103: Front Microbiol | G103: 2022 | H103: 44791 | I103: PMC9376610 | K103: 10.3389/fmicb.2022.905865 | L103: =IF(ISNUMBER(VLOOKUP(A103,EXCL,1,FALSE)),"Excluido",IF(ISNUMBER(VLOOKUP(A103,POST,1,FALSE)),"PostAlerta",IF(ISNUMBER(VLOOKUP(A103,PRE,1,FALSE)),"PreAlerta",""))) -> PostAlerta | M103: =IF(ISNUMBER(A103),(IF(ISNUMBER(VLOOKUP(A103,KEYWORDS,1,FALSE)),"C/PalabrasClaves","S/PalabrasClaves")),"") -> C/PalabrasClaves | P103: 2022 Aug 1 | Q103: Excluir | R103: =LEFT(P103,4) -> 2022 | S103: Aug | Y103: =IF(ISNUMBER(SEARCH("combination", B103)), "combination ", "") -> combination
A104: 35979220 | B104: Clonal serotype 1c multidrug-resistant Shigella flexneri detected in multiple institutions by sentinel-site sequencing | C104: Ko KKK, Chu JJK, Lim KM, Yingtaweesittikul H, Huang W, Tan SYL, Goh KCM, Tan SH, Ng TY, Maiwald M, Chia JWZ, Cao DY, Tan YE, Sim JHC, Koh TH, Nagarajan N, Suphavilai C. | D104: Front Med (Lausanne). 2022 Aug 1;9:964640. doi: 10.3389/fmed.2022.964640. eCollection 2022. | E104: Ko KKK | F104: Front Med (Lausanne) | G104: 2022 | H104: 44791 | I104: PMC9376355 | K104: 10.3389/fmed.2022.964640 | L104: =IF(ISNUMBER(VLOOKUP(A104,EXCL,1,FALSE)),"Excluido",IF(ISNUMBER(VLOOKUP(A104,POST,1,FALSE)),"PostAlerta",IF(ISNUMBER(VLOOKUP(A104,PRE,1,FALSE)),"PreAlerta",""))) -> PostAlerta | M104: =IF(ISNUMBER(A104),(IF(ISNUMBER(VLOOKUP(A104,KEYWORDS,1,FALSE)),"C/PalabrasClaves","S/PalabrasClaves")),"") -> S/PalabrasClaves | N104: 2) Nuevos tratamientos | P104: 2022 Aug 1 | Q104: Listo | R104: =LEFT(P104,4) -> 2022 | S104: Aug | T104: Shigella flexneri is a major diarrhoeal pathogen, and the emergence of multidrug-resistant S. flexneri is of public health concern. We report the detection of a clonal cluster of multidrug-resistant serotype 1c (7a) S. flexneri in Singapore in April 2022. Long-read whole-genome sequence analysis found five S. flexneri isolates to be clonal and harboring the extended-spectrum β-lactamases bla CTX-M-15 and bla TEM-1. The isolates were phenotypically resistant to ceftriaxone and had intermediate susceptibility to ciprofloxacin. The S. flexneri clonal cluster was first detected in a tertiary hospital diagnostic laboratory (sentinel-site), to which the S. flexneri isolates were sent from other hospitals for routine serogrouping. Long-read whole-genome sequence analysis was performed in the sentinel-site near real-time in view of the unusually high number of S. flexneri isolates received within a short time frame. This study demonstrates that near real-time sentinel-site sequence-based surveillance of convenience samples can detect possible clonal outbreak clusters and may provide alerts useful for public health mitigations at the earliest possible opportunity. | U104: Yes | V104: No | W104: No | X104: Multidrug-resistant S. flexneri serotype 1c detected in Singapore, highlighting the value of real-time genomic surveillance for outbreaks. | Y104: =IF(ISNUMBER(SEARCH("combination", B104)), "combination ", "")
A105: 34781820 | B105: Dysregulated endolysosomal trafficking in cells arrested in the G(1) phase of the host cell cycle impairs Salmonella vacuolar replication | C105: Lisowski C, Dias J, Costa S, Silva RJ, Mano M, Eulalio A. | D105: Autophagy. 2022 Aug;18(8):1785-1800. doi: 10.1080/15548627.2021.1999561. Epub 2021 Nov 15. | E105: Lisowski C | F105: Autophagy | G105: 2022 | H105: 44516 | I105: PMC9450962 | K105: 10.1080/15548627.2021.1999561 | L105: =IF(ISNUMBER(VLOOKUP(A105,EXCL,1,FALSE)),"Excluido",IF(ISNUMBER(VLOOKUP(A105,POST,1,FALSE)),"PostAlerta",IF(ISNUMBER(VLOOKUP(A105,PRE,1,FALSE)),"PreAlerta",""))) -> PostAlerta | M105: =IF(ISNUMBER(A105),(IF(ISNUMBER(VLOOKUP(A105,KEYWORDS,1,FALSE)),"C/PalabrasClaves","S/PalabrasClaves")),"") -> S/PalabrasClaves | P105: 2022 Aug | Q105: Excluir | R105: =LEFT(P105,4) -> 2022 | S105: Aug | Y105: =IF(ISNUMBER(SEARCH("combination", B105)), "combination ", "")
...

Sheet Test
A1: PMID | B1: Title | C1: Categoria | D1: Subcategorias | E1: Estado | F1: PubYear | G1: Abstract | H1: 1) Antimicrobial Resistance stain | I1: 2) New treatment | J1: 3) Immunization | K1: Human_summary
A2: 35174771 | B2: In vitro and in silico screening of novel typhoid drugs from endangered herb (Enicostema axillare) | C2: 2) Nuevos tratamientos | D2: 2a) Productos naturales | E2: Listo | F2: 2023 | G2: In the present study, antibacterial activity of swertiamarin from Enicostema axillare (Lam) was checked against three different human gram-negative pathogens namely Salmonella typhi, Klebsiella pneumoniae and Shigella flexneri. Minimum inhibitory concentration assay revealed low dose and efficient activity of swertiamarin on the above said pathogens. Though swertiamarin is a well-studied and characterized compound, there is no experimental proof available for its antibacterial activity. To gain more insight about the antibacterial efficiency of swertiamarin against typhoid causing S. typhi, a comparative molecular docking of S. typhi OmpF (3NSG) was performed with swertiamarin and other typhoid drugs available in the market which exposed better activity strength of swertiamarin compared with that of the other drugs. Further, molecular dynamics of S. typhi OmpF-swertiamarin shows good flexibility and stability at 100 ns. The outcome of this work will definitely provide an idea of using very low dose of swertiamarin as a potent and promising drug against typhoid fever.Communicated by Ramaswamy H. Sarma. | H2: No | I2: Yes | J2: No | K2: The study evaluates the antibacterial activity of swertiamarin as a potential drug against human pathogens, especially Salmonella typhi.
A3: 34453485 | B3: Green synthesis and characterization of Solanum xanthocarpum capped silver nanoparticles and its antimicrobial effect on multidrug-resistant bacterial (MDR) isolates | C3: 2) Nuevos tratamientos | D3: 2b) Péptidos | E3: Listo | F3: 2023 | G3: Plant extracts and their bioactive compounds are considered as the promising options for green synthesis of nanoparticles instead expensive and hazardous materials. Here, Solanum xanthocarpum fruit was used for synthesis of silver nanoparticles (AgNP). The synthesized AgNPs were characterized by using chromatographic and spectroscopic analytical methods. AgNPs were confirmed by UV-visible absorbance at 420-470 nm. TEM analysis showed AgNP with 22.45 nm average size. X-ray diffraction studies revealed the crystalline and face central cubic nature of AgNPs. FTIR analysis revealed functional group present over AgNPs. The aminodiphenyl acetic acid, clomipramine, and fonisopril from fruit extracts were found to be major capping agents on AgNPs as a result of analysis by HRLC-MS. All clinical isolates showed resistance for ampicilline, amoxyclav, niladixic acid, and sulphafurazole, suggesting multidrug resistance. The results showed that all isolates were sensitive to AgNPs synthesized fruit extracts. On the contrary, all isolates were resistant to whole S. xanthocarpum fruit extracts alone. The antimicrobial activity of AgNP was explored against multidrug-resistant (MDR) Gram-negative clinical isolates including Escherichia coli, Shigella spp., Aeronomonas spp. and Pseudomonas spp. MIC values ranged between 1.25 mg/ml and 2.5 mg/ml at 8 McFarland's standards. Minimum bactericidal concentration was found to be in between 2.5 mg/ml to 5 mg/ml. Nanoparticles synthesized from fruit extract of S. xanthocarpum containing aminodiphenyl acetic acid, clomipramine, and fonisopril metabolites exhibit promising antimicrobial activity against MDR Gram-negative clinical isolates. | H3: No | I3: Yes | J3: No | K3: Silver nanoparticles synthesized from Solanum xanthocarpum fruit show promising antimicrobial activity against multidrug-resistant Gram-negative isolates.
A4: 36686167 | B4: Pueraria lobata polysaccharides alleviate neonatal calf diarrhea by modulating gut microbiota and metabolites | C4: 2) Nuevos tratamientos | D4: 2b) Péptidos | E4: Listo | F4: 2023 | G4: Introduction: Neonatal calf diarrhea (NCD) is still one of the most critical diseases in calf rearing. Studies have shown that Pueraria lobata polysaccharides (PLP) have intense antioxidant and immunomodulatory activity and modulate gut microbiota. This randomized clinical trial aimed to determine the effect of PLP on the neonatal calf with diarrhea. Methods: In this study, we recorded the fecal score of experimental calves, and calves with fecal scores ≥ 2 were determined as diarrhea and assessed their serum concentrations of inflammatory cytokines and oxidative damage-related indices. Fecal microbiota and metabolomics of diarrheal calves were further investigated. Results: Results showed that treatment with PLP decreased the fecal score of diarrheal calves, serum concentrations of IL-1β, TNF-γ, and malondialdehyde, and also elevated the level of superoxide dismutase. In addition, PLP treatment altered the gut microbiota, significantly increased the relative abundances of beneficial bacteria, including the phyla Bacteroidetes and Actinobacteria, the genus Collinsella, Megamonas, and Bifidobacterium; decreased the relative abundances of pathogenetic or diarrhea related bacteria, such as Proteobacteria, Fusobacteria, Clostridium_sensu_stricto_1, and Escherichia_Shigella. Moreover, PLP can increase the fecal concentrations of isobutyric acid, propionic acid, and pantothenate; lower the levels of PC [18:0/18:1(9Z)], arachidonic acid, and docosahexaenoic acid. Discussion: Thus, the results suggested that the PLP may perform the therapeutic activity via alleviating intestinal inflammation and regulating gut microbiota, avoiding further dysbiosis to restore the metabolism of gut microbiota, and finally promoting the recovery of diarrhea. The change further mitigated intestinal inflammation and oxidative damage in diarrheal calves. This indicated that PLP might be a promising treatment to attenuate diarrhea in neonatal calves. | H4: No | I4: Yes | J4: No | K4: PLP treatment reduced diarrhea, inflammation, and oxidative damage in neonatal calves by regulating gut microbiota and improving metabolism.
A5: 34998646 | B5: An in vivo acute toxicity and anti-shigellosis effect of designed formulation on rat | C5: 2) Nuevos tratamientos | D5: 2c) Droga de diseño | E5: Listo | F5: 2023 | G5: Introduction: Shigellosis is an intestinal disease and is one of the main causes of morbidity and mortality among children in India. The study aims to analyze the effect of the designed formulation on the hematological parameters in shigellosis-induced rats and assess the in vivo toxicity of this formulation. Methods: Male Wistar rats were housed in different groups. Group 1 is normal control; group 2 is diseased control; group 3 and group 4 diseased rats received 250 mg/kg formulation and 20 mg/kg body weight norfloxacin, respectively, orally once a day. Shigellosis was induced by a single intraperitoneal injection of Shigella flexneri, and bacterial load was calculated using the Shigella agar plate. On completion of the study, blood was collected for hematological as well as electrolyte analysis. Results: The in vivo acute toxicity results indicate that the formulation is safe up to 2000 mg/kg. Furthermore, formulation significantly (p < 0.05) decreases the bacterial load and increases the RBC, WBC, MCHC, platelet, hemoglobin, and electrolytes (Ca++, K+, and Na+) compared to diseased control. Conclusion: The results support the designed formulation's safety and therapeutic effects and support its use as an alternative medicine for treating shigellosis. | H5: No | I5: Yes | J5: No | K5: The formulation reduced bacterial load and improved RBC, WBC, MCHC, platelets, hemoglobin, and electrolytes in shigellosis-induced rats.
A6: 34931711 | B6: BCL-2-family protein tBID can act as a BAX-like effector of apoptosis | C6: 2) Nuevos tratamientos | D6: 2b) Péptidos | E6: Listo | F6: 2022 | G6: During apoptosis, the BCL-2-family protein tBID promotes mitochondrial permeabilization by activating BAX and BAK and by blocking anti-apoptotic BCL-2 members. Here, we report that tBID can also mediate mitochondrial permeabilization by itself, resulting in release of cytochrome c and mitochondrial DNA, caspase activation and apoptosis even in absence of BAX and BAK. This previously unrecognized activity of tBID depends on helix 6, homologous to the pore-forming regions of BAX and BAK, and can be blocked by pro-survival BCL-2 proteins. Importantly, tBID-mediated mitochondrial permeabilization independent of BAX and BAK is physiologically relevant for SMAC release in the immune response against Shigella infection. Furthermore, it can be exploited to kill leukaemia cells with acquired venetoclax resistance due to lack of active BAX and BAK. Our findings define tBID as an effector of mitochondrial permeabilization in apoptosis and provide a new paradigm for BCL-2 proteins, with implications for anti-bacterial immunity and cancer therapy. | H6: No | I6: Yes | J6: No | K6: tBID mediates mitochondrial permeabilization independent of BAX and BAK, impacting SMAC release in immune response and leukemia therapy.
A7: 35147277 | B7: Synthesis and biological activity profile of novel triazole/quinoline hybrids | C7: 2) Nuevos tratamientos | D7: 2g) nueva combinación de ATB | E7: Listo | F7: 2022 | G7: Based on the significant and diverse pharmacophore features of triazole ring and considering the potent antimicrobial properties of quinoline scaffold, a novel series of 1,2,3-triazole-based polyaromatic compounds containing chloroquinoline moiety were synthesized through a well-established synthetic methodology, named click chemistry. The structure of the synthetic compounds was characterized by various spectroscopic methods. The final products of triazole/quinoline hybrids and ((prop-2-yn-1-yloxy)methyl)benzene intermediates were screened for their antibacterial (Staphylococcus aureus, Escherichia coli, Shigella flexneri, and Salmonella enterica), antifungal (Candida albicans, Saccharomyces cerevisiae, and Aspergillus fumigatus), and cytotoxic activities. The best antifungal compounds exhibited minimum inhibitory concentration (MIC), in the range of 0.35-0.63 µM, against S. cerevisiae without any cytotoxic effect. These compounds can be selected as the potential candidates for treating invasive fungal infections caused by S. cerevisiae, after further investigation. Preliminary in silico ADME studies also predicted the favorable pharmacokinetic attributes of most compounds. | H7: No | I7: Yes | J7: No | K7: Triazole/quinoline hybrids showed potent antifungal activity against S. cerevisiae with no cytotoxicity, supporting their use as new treatments.
A8: 36409683 | B8: Antimicrobial resistance in shigellosis: A surveillance study among urban and rural children over 20 years in Bangladesh | C8: 1) Reporte de cepas resistentes | E8: Listo | F8: 2022 | G8: Antimicrobial resistance against shigellosis is increasingly alarming. However, evidence-based knowledge gaps regarding the changing trends of shigellosis in Bangladesh exist due to the scarcity of longitudinal data on antimicrobial resistance. Our study evaluated the last 20 years antimicrobial resistance patterns against shigellosis among under-5 children in the urban and rural sites of Bangladesh. Data were extracted from the Diarrheal Disease Surveillance System (DDSS) of Dhaka Hospital (urban site) and Matlab Hospital (rural site) of the International Centre for Diarrheal Disease Research, Bangladesh (icddr,b) between January 2001 and December 2020. We studied culture-confirmed shigellosis cases from urban Dhaka Hospital (n = 883) and rural Matlab Hospital (n = 1263). Since 2001, a declining percentage of shigellosis in children observed in urban and rural sites. Moreover, higher isolation rates of Shigella were found in the rural site [1263/15684 (8.1%)] compared to the urban site [883/26804 (3.3%)] in the last 20 years. In both areas, S. flexneri was the predominant species. The upward trend of S. sonnei in both the study sites was statistically significant after adjusting for age and sex. WHO-recommended 1st line antibiotic ciprofloxacin resistance gradually reached more than 70% in both the urban and rural site by 2020. In multiple logistic regression after adjusting for age and sex, ciprofloxacin, azithromycin, mecillinam, ceftriaxone, and multidrug resistance (resistance to any two of these four drugs) among under-5 children were found to be increasing significantly (p<0.01) in the last 20 years in both sites. The study results underscore the importance of therapeutic interventions for shigellosis by appropriate drugs based on their current antibiogram for under-5 children. These observations may help policymakers in formulating better case management strategies for shigellosis. | H8: Yes | I8: No | J8: No | K8: Ciprofloxacin and multidrug resistance in Shigella from under-5 children rose >70% in 20 years in Bangladesh, revealing resistant strains.
A9: 36274686 | B9: Green synthesis of biogenetic Te(0) nanoparticles by high tellurite tolerance fungus Mortierella sp. AB1 with antibacterial activity | C9: 2) Nuevos tratamientos | D9: 2b) Péptidos | E9: Listo | F9: 2022 | G9: Tellurite [Te(IV)] is a high-toxicity metalloid. In this study, a fungus with high Te(IV) resistance was isolated. Strain AB1 could efficiently reduce highly toxic Te(IV) to less toxic Te(0). The reduced products formed rod-shaped biogenetic Te(0) nanoparticles (Bio-TeNPs) intracellularly. Further TEM-element mapping, FTIR, and XPS analysis showed that the extracted Bio-TeNPs ranged from 100 to 500 nm and consisted of Te(0), proteins, lipids, aromatic compounds, and carbohydrates. Moreover, Bio-TeNPs exhibited excellent antibacterial ability against Shigella dysenteriae, Escherichia coli, Enterobacter sakazakii, and Salmonella typhimurium according to inhibition zone tests. Further growth and live/dead staining experiments showed that E. coli and S. typhimurium were significantly inhibited by Bio-TeNPs, and cells were broken or shriveled after treatment with Bio-TeNPs based on SEM observation. Additionally, the antioxidant and cytotoxicity tests showed that the Bio-TeNPs exhibited excellent antioxidant capacity with no cytotoxicity. All these results suggested that strain AB1 showed great potential in bioremediation and Bio-TeNPs were excellent antibacterial nanomaterials with no cytotoxicity. | H9: No | I9: Yes | J9: No | K9: Bio-TeNPs from strain AB1 showed strong antibacterial activity against pathogens with no cytotoxicity, suggesting potential new treatments.
A10: 36204123 | B10: An Evaluation of the Antibacterial Activity of Pterocarpus tinctorius Bark Extract against Enteric Bacteria That Cause Gastroenteritis | C10: 2) Nuevos tratamientos | D10: 2a) Productos naturales | E10: Listo | F10: 2022 | G10: Enteric bacteria are the leading cause of bacterial gastroenteritis worldwide, particularly in low-income countries. The bark decoction of Pterocarpus tinctorius (Fabaceae) has traditionally been used to treat bacterial gastroenteritis. However, studies reporting the antibacterial activity of Pterocarpus tinctorius are rare. Therefore, this study aimed to evaluate the antibacterial activity of stem bark extract of Pterocarpus tinctorius against Escherichia coli, Salmonella typhi, and Shigella dysenteriae. The powdered bark extract was successively extracted with methanol using the cold continuous maceration method, followed by partitioning the crude methanolic extract to obtain methanolic, hexane, and chloroform subextracts. Three fractions were isolated from the methanolic subextract using ordinary normal phase column chromatography. The antibacterial activity of the extracts and fractions was performed using the agar well diffusion method. The minimum inhibitory concentration (MIC) was determined using the agar well diffusion method. While, minimum bactericidal concentration (MBC) was obtained by the subculturing method. The methanolic subextract was the only extract that showed antibacterial activity against the tested bacteria, and its activity was highest on Shigella dysenteriae followed by Salmonella typhi and was least active on Escherichia coli, with mean inhibition zones of 14.3 ± 0.2, 13.7 ± 0.3, and 12.2 ± 0.1 at 200 mg/mL, respectively. Chloroform subextract showed antibacterial activity only on Shigella dysenteriae, while hexane subextract did not show antibacterial activity against all bacteria tested at 100 mg/mL and 200 mg/mL. Among the three subfractions of methanolic subextract, only one subfraction was active and had both mean minimum inhibitory concentration and a minimum bactericidal concentration against Escherichia coli at 1.25 mg/mL, Salmonella typhi at 1.25 mg/mL, and Shigella dysenteriae at 0.6 mg/mL. The findings of this study support the use of Pterocarpus tinctorius in traditional medicine. Therefore, purification and structural elucidation studies are highly recommended. | H10: No | I10: Yes | J10: No | K10: Methanolic extract of P. tinctorius bark showed antibacterial activity against S. dysenteriae, S. typhi and E. coli, supporting traditional use.
A11: 34727811 | B11: A new antimicrobial nor-friedelane-type triterpenoid and other constituents from Plectranthus glandulosus Hook. f. (Lamiaceae) | C11: 2) Nuevos tratamientos | D11: 2a) Productos naturales | E11: Listo | F11: 2022 | G11: Chemical investigation of the ethanol extract from the whole plant of Plectranthus glandulosus led to the isolation of a new nor-triterpenoid (1) along with seventeen known compounds (2-18) including seven triterpenoids, nine flavonoids and one steroid. Their structures were established on the basis of 1D- and 2D-NMR, IR, and MS experiments, and by comparison of their spectroscopic data with those of similar compounds reported in the literature. The EtOH extract and some isolated triterpenoids (1-4 and 13) were subjected to in vitro antimicrobial assays against a panel of pathogenic microorganisms, including Gram-positive and Gram-negative bacteria, and fungi using broth microdilution method. The EtOH extract displayed moderate activity (MIC = 512 µg/mL) against Staphylococcus aureus MSSA1, Shigella flexneri SDINT and Cryptococcus neoformans H99. Compounds 1, 4 and 13 showed the most potent antimicrobial effect with MICs of 32-256 µg/mL. | H11: No | I11: Yes | J11: No | K11: EtOH extract and triterpenoids from P. glandulosus showed antimicrobial activity against S. aureus, S. flexneri and C. neoformans.
A12: 36091586 | B12: Antidiarrheal and Antibacterial Activities of Calpurnia aurea: Benth Seed Different Extracts | C12: 2) Nuevos tratamientos | D12: 2a) Productos naturales | E12: Listo | F12: 2022 | G12: Background: Calpurnia aurea is believed to have antidiarrheal potential but with limited scientific evidence. This study aimed investigating antidiarrheal and antibacterial activity of aqueous and 80% methanol seed extracts of the plant in mice and selected diarrhea-causing bacterial strains, respectively. Methods: Castor oil-induced diarrhea, prostaglandin-induced enteropooling, and castor oil-induced charcoal meal test models in mice of either sex using three dose levels (60, 120, and 240 mg/kg) were applied to evaluate antidiarrheal activity. Parameters, including onset, number, wet stool weight, weight and volume of secretion, and intestinal motility, were taken into consideration. The antibacterial activity was assessed on Shigella soni, Salmonella typhimurium, Escherichia coli, Staphylococcus aureus, and Pseudomonas aeruginosa using disk diffusion and microdilution techniques. Results: Compared to controls, pretreatment of mice at the graded dose (60, 120, and 240 mg/kg) resulted in a significant (p < 0.05) drop in frequency of wet stools and watery content of diarrhea as well as in delaying onset of diarrhea. Both extracts exhibited inhibition of diarrhea in a dose-dependent manner in all models used. The extracts also showed significant (p < 0.05) reduction in intestinal motility in castor oil-induced models. Both extracts showed a marginal activity against the selected bacterial strains; a better effect was seen with 80% methanol seed extract. Conclusion: Both extracts of the plant have beneficial effect in controlling diarrhea. This finding supports the use of the plant as a traditional antidiarrheal remedy. | H12: No | I12: Yes | J12: No | K12: Calpurnia aurea extracts showed significant antidiarrheal effects in mice, supporting its use as a traditional remedy for diarrhea.
A13: 35979220 | B13: Clonal serotype 1c multidrug-resistant Shigella flexneri detected in multiple institutions by sentinel-site sequencing | C13: 2) Nuevos tratamientos | E13: Listo | F13: 2022 | G13: Shigella flexneri is a major diarrhoeal pathogen, and the emergence of multidrug-resistant S. flexneri is of public health concern. We report the detection of a clonal cluster of multidrug-resistant serotype 1c (7a) S. flexneri in Singapore in April 2022. Long-read whole-genome sequence analysis found five S. flexneri isolates to be clonal and harboring the extended-spectrum β-lactamases bla CTX-M-15 and bla TEM-1. The isolates were phenotypically resistant to ceftriaxone and had intermediate susceptibility to ciprofloxacin. The S. flexneri clonal cluster was first detected in a tertiary hospital diagnostic laboratory (sentinel-site), to which the S. flexneri isolates were sent from other hospitals for routine serogrouping. Long-read whole-genome sequence analysis was performed in the sentinel-site near real-time in view of the unusually high number of S. flexneri isolates received within a short time frame. This study demonstrates that near real-time sentinel-site sequence-based surveillance of convenience samples can detect possible clonal outbreak clusters and may provide alerts useful for public health mitigations at the earliest possible opportunity. | H13: Yes | I13: No | J13: No | K13: Multidrug-resistant S. flexneri serotype 1c detected in Singapore, highlighting the value of real-time genomic surveillance for outbreaks.
A14: 35935215 | B14: Early life administration of Bifidobacterium bifidum BD-1 alleviates long-term colitis by remodeling the gut microbiota and promoting intestinal barrier development | C14: 2) Nuevos tratamientos | D14: 2g) nueva combinación de ATB | E14: Listo | F14: 2022 | G14: Inflammatory bowel disease (IBD) is a chronic intestinal disease characterized by microbiota disturbance and intestinal mucosal damage. The current study aimed to investigate the preventive effects of Bifidobacterium bifidum BD-1 (BD-1) against long-term IBD and possible mechanism by which it alters the gut microbiota, immune response, and mucosal barrier. Our study found that early treatment of BD-1 + Ceftri (ceftriaxone followed by BD-1) and BD-1 confers a certain protective effect against the occurrence of long-term Dextran sulfate sodium-induced colitis, which manifests as a decrease in inflammation scores and MPO activity levels, as well as a relatively intact intestinal epithelial structure. Moreover, compared to BD-1, Ceftri, and NS, early treatment with BD-1 + Ceftri promoted greater expression levels of mucosal barrier-related proteins [KI67, MUC2, ZO-1, secretory immunoglobulin A (slgA), Clauding-1, and Occludin], better local immune responses activation, and moderately better modulation of systemic immune responses during long-term colitis. This may be due to the fact that BD-1 + Ceftri can deliberately prolong the colonization time of some beneficial microbiota (e.g., Bifidobacterium) and reduce the relative abundance of inflammation-related microbiota (e.g., Escherichia/Shigella and Ruminococcus). Interestingly, we found that the changes in the gut barrier and immunity were already present immediately after early intervention with BD-1 + Ceftri, implying that early effects can persist with appropriate intervention. Furthermore, intervention with BD-1 alone in early life confers an anti-inflammatory effect to a certain degree in the long-term, which may be due to the interaction between BD-1 and the host's native gut microbiota affecting intestinal metabolites. In conclusion, BD-1 was not as effective as BD-1 + Ceftri in early life, perhaps due to its failure to fully play the role of the strain itself under the influence of the host's complex microbiota. Therefore, further research is needed to explore specific mechanisms for single strain and native microbiota or the combination between probiotics and antibiotics. | H14: No | I14: Yes | J14: No | K14: BD-1 + Ceftri reduces inflammation, promotes mucosal barrier proteins, and modulates gut microbiota, offering protective effects in IBD.
A15: 35903471 | B15: A Selective Medium for Screening Ceftazidime/Avibactam Resistance in Carbapenem-Resistant Enterobacterales | C15: 1) Reporte de cepas resistentes | D15: 2g) nueva combinación de ATB | E15: Listo | F15: 2022 | G15: Ceftazidime/avibactam (CZA) is an alternative antibiotic used for the treatment of infections caused by carbapenem-resistant Enterobacterales (CRE). However, the CZA-resistant CRE strains have been detected worldwide. Therefore, it is critical to screen CZA-resistant CRE strains in colonized patients or a specific population so as to rapidly implement infection control measures to limit their transmission. In this study, we developed a Salmonella-Shigella (SS) CZA-selective medium and assessed its performance to screen for clinical CZA-resistant CRE isolates in both pure-strain specimens and stool samples. A total of 150 non-duplicated isolates, including 75 CZA-susceptible and 75 CZA-resistant CRE pathogens, were tested by using the broth microdilution method and the SS CZA medium, respectively. The bacterial suspensions were serially diluted in the SS CZA medium, which showed excellent screening performance in both pure CZA-resistant CRE strain and the stool samples with the lowest detection limit of 101-102 and 101-103 CFU/ml, respectively. Notably, none of the susceptible isolates showed growth even at the highest dilution concentration of 108 CFU/ml. Most importantly, the SS CZA medium demonstrated excellent performance in screening simulated clinical polymicrobial specimens. Moreover, its screening performance was unaffected by the different resistance determinants for tested isolates. Cumulatively, our data suggest that the SS CZA medium can be used as a promising selective medium to screen CZA-resistant CRE, irrespective of their resistance mechanisms. | H15: Yes | I15: No | J15: No | K15: SS CZA medium accurately detects ceftazidime/avibactam-resistant CRE in pure and stool samples, aiding early containment.
A16: 35903457 | B16: Preventive Effects of Long-Term Intake of Plant Oils With Different Linoleic Acid/Alpha-Linolenic Acid Ratios on Acute Colitis Mouse Model | C16: 2) Nuevos tratamientos | D16: 2a) Productos naturales | E16: Listo | F16: 2022 | G16: Objective: To investigate the preventive effects of plant oils with different linoleic acid/alpha-linolenic acid (LA/ALA) ratios against colitis symptoms, and dysbiosis of gut microbiota in acute colitis mouse model. Methods: Sixty male C57BL/6 mice were assigned into six groups (n = 10): three groups were fed low-fat diets with low, medium, and high LA/ALA ratios; and three groups were fed with high-fat diets with low, medium, and high LA/ALA ratios. After 3 months of diet, the mice were exposed to dextran sodium sulfate solution to induce acute colitis. The severity of colitis was estimated by disease activity index (DAI) and histopathological examination. 16S rRNA gene sequencing was used for the analysis of gut microbiota. Results: Plant oils with a lower LA/ALA ratio showed higher alleviating effects on the symptoms of colitis, which were accompanied by the better prebiotic characteristics manifested as effectively inhibiting the abnormal expansion of phylum Proteobacteria and genus Escherichia-Shigella in the gut microbiota of colitis mouse models. Conclusion: A potential IBD prevention strategy of reducing the LA/ALA ratio in the daily consumed plant oils was proposed in this study. Furthermore, based on the optimized LA/ALA ratio, this preventive effect might not be weakened by the high intake of plant oils. | H16: No | I16: Yes | J16: No | K16: Low LA/ALA ratio in plant oils alleviated colitis symptoms and reduced Escherichia-Shigella, suggesting dietary prevention of IBD.
A17: 35873583 | B17: Capsaicin Inhibits Shigella flexneri Intracellular Growth by Inducing Autophagy | C17: 2) Nuevos tratamientos | D17: 2a) Productos naturales | E17: Listo | F17: 2022 | G17: Antibiotic treatment plays an essential role in preventing Shigella infection. However, incidences of global rise in antibiotic resistance create a major challenge to treat bacterial infection. In this context, there is an urgent need for newer approaches to reduce S. flexneri burden. This study largely focuses on the role of the herbal compound capsaicin (Caps) in inhibiting S. flexneri growth and evaluating the molecular mechanism behind bacterial clearance. Here, we show for the first time that Caps inhibits intracellular S. flexneri growth by inducing autophagy. Activation of autophagy by Caps is mediated through transcription factor TFEB, a master regulator of autophagosome biogenesis. Caps induced the nuclear localization of TFEB. Activation of TFEB further induces the gene transcription of autophagosomal genes. Our findings revealed that the inhibition of autophagy by silencing TFEB and Atg5 induces bacterial growth. Hence, Caps-induced autophagy is one of the key factors responsible for bacterial clearance. Moreover, Caps restricted the intracellular proliferation of S. flexneri-resistant strain. The efficacy of Caps in reducing S. flexneri growth was confirmed by an animal model. This study showed for the first time that S. flexneri infection can be inhibited by inducing autophagy. Overall observations suggest that Caps activates TFEB to induce autophagy and thereby combat S. flexneri infection. | H17: No | I17: Yes | J17: No | K17: Capsaicin inhibits S. flexneri growth by inducing TFEB-mediated autophagy; efficacy confirmed in animal model.
A18: 35859755 | B18: Effects of Zymosan on Short-Chain Fatty Acid and Gas Production in in vitro Fermentation Models of the Human Intestinal Microbiota | C18: 2) Nuevos tratamientos | D18: 2a) Productos naturales | E18: Listo | F18: 2022 | G18: In this study, the effects of zymosan (HG, hydrolyzed glucan) on the structure and metabolism of fecal microbiota in Chinese healthy people was investigated by an in vitro simulated intestinal microecology fermentation model. We found that HG significantly regulated fecal microbiota composition, including the increase of Bifidobacterium, Faecalibacterium, Prevotella and the decrease of Escherichia-Shigella. Moreover, HG significantly increased the total production of short chain fatty acids (SCFAs) and gases, in which the production of Acetic acid, Propionic acid, CO2, and H2 significantly increased while the production of Isovaleric acid and NH3 significantly decreased. Additionally, the supplement of HG showed certain differences in the regulation of microbiota from four groups. HG significantly increased the relative abundance of Bifidobacterium and significantly decreased the relative abundance of Escherichia-Shigella excluding the older men group. Meanwhile, and the relative abundance of Lactobacillus was significantly increased in young populations. And the relative abundance of Bacteroides was significantly decreased only in the young women. Furthermore, HG significantly increased H2 concentration only in older men. These findings suggest that HG, as a new generation of prebiotics, could regulate the structure of fecal microbiota and its metabolites in a better direction, but when HG participates in precision nutrition formula, it may be necessary to consider the differences in the utilization of different populations. | H18: No | I18: Yes | J18: No | K18: Hydrolyzed glucan modulates gut microbiota and metabolites, with variable effects across different age and sex groups.
A19: 35218055 | B19: The underlying mechanism of A-type procyanidins from peanut skin on DSS-induced ulcerative colitis mice by regulating gut microbiota and metabolism | C19: 2) Nuevos tratamientos | D19: 2a) Productos naturales | E19: Listo | F19: 2022 | G19: Ulcerative colitis (UC) is a kind of inflammatory bowel disease. Procyanidins have been found to prevent UC. However, most research has been focused on the alleviation effect of B-type procyanidins on UC and ignored those of A-type procyanidins. Hence, this study aims to investigate the anti-UC effect and the potential mechanism of A-type procyanidins by combining gut microbiome and metabolic profile. UC was induced by dextran sulfate sodium (DSS) in Balb/c mice, and then the mice were administrated with peanut skin procyanidins (PSP; rich in A-type procyanidins) for 9 days. Administration of PSP can ameliorate DSS-induced UC by mediating the intestinal barrier, the expression of inflammatory cytokines (TNF-α, IL-β, IL-6, and IL-10) and oxidative stress (MDA, T-SOD, NO, and iNOS) in mice. We observed that PSP affects the gut microbiota and colon metabolomic patterns of mice. The 16S rDNA sequencing showed increase in abundance of Lachnospiraceae_NK4A136_group, Oscillibacter and Roseburia and decrease of Bacteroides, Helicobacter, Parabacteroides, Escherichia-Shigella, and Enterobacter after PSP treatment. The colon tissue metabolome was significantly altered, as reflected by regulating taste transduction, mTOR signaling pathway, PI3K-Akt signaling pathway, and FoxO signaling pathway to improve the protection against UC. PRACTICAL APPLICATIONS: We investigated the anti-ulcerative colitis (UC) effect and its potential mechanism of peanut skin procyanidins (PSP). This suggests that PSP with abundant A-type procyanidins may be an effective candidate for dietary supplementation to alleviate the symptoms of UC by regulating gut microbiota and metabolism. | H19: No | I19: Yes | J19: No | K19: A-type procyanidins from peanut skin improve UC by modulating gut microbiota, metabolism, inflammation, and oxidative stress.
A20: 35845772 | B20: A Class IIb Bacteriocin Plantaricin NC8 Modulates Gut Microbiota of Different Enterotypes in vitro | C20: 2) Nuevos tratamientos | D20: 2b) Péptidos | E20: Listo | F20: 2022 | G20: The gut microbiota is engaged in multiple interactions affecting host health. Bacteriocins showed the ability of impeding the growth of intestinal pathogenic bacteria and modulating gut microbiota in animals. Few studies have also discovered their regulation on human intestinal flora using an in vitro simulated system. However, little is known about their effect on gut microbiota of different enterotypes of human. This work evaluated the modification of the gut microbiota of two enterotypes (ET B and ET P) by the class IIb bacteriocin plantaricin NC8 (PLNC8) by using an in vitro fermentation model of the intestine. Gas chromatography results revealed that PLNC8 had no influence on the gut microbiota's production of short-chain fatty acids in the subjects' samples. PLNC8 lowered the Shannon index of ET B' gut microbiota and the Simpson index of ET P' gut microbiota, according to 16S rDNA sequencing. In ET B, PLNC8 enhanced the abundance of Bacteroides, Bifidobacterium, Megamonas, Escherichia-Shigella, Parabacteroides, and Lactobacillus while decreasing the abundance of Streptococcus. Prevotella_9, Bifidobacterium, Escherichia-Shigella, Mitsuokella, and Collinsella were found more abundant in ET P. The current study adds to our understanding of the impact of PLNC8 on the human gut microbiota and lays the groundwork for future research into PLNC8's effects on human intestinal disease. | H20: No | I20: Yes | J20: No | K20: PLNC8 modulates gut microbiota composition across enterotypes, suggesting potential to influence human intestinal disease.
A21: 35837289 | B21: Shen-Ling-Bai-Zhu-San (SL) and SL Derived-Polysaccharide (PL) Ameliorate the Severity of Diarrhea-Induced by High Lactose via Modification of Colonic Fermentation | C21: 2) Nuevos tratamientos | D21: 2a) Productos naturales | E21: Listo | F21: 2022 | G21: In our previous study, we demonstrated that Shen-ling-bai-zhu-san (SL), a classical Chinese herbal formula, could alleviate lactose-induced diarrhea. However, little is known about the mechanism underlying SL action or the efficacy of the polysaccharide (PL) derived from SL. In this study, we investigated the effect of SL and PL on improving the dysregulated luminal and mucosal microbiota in rats with high lactose diet using 16S rRNA analysis. The concentrations of lactose, lactic acid in cecum and short-chain fatty acids (SCFAs) in cecum and portal vein were measured, meanwhile the expression of ion transporters were ascertained. Our data suggest that the SL, PL and cecal microbiota transplantation (CMT) significantly decreased fecal water content and water intake. In the luminal microbiota there was a significant increase in Akkermansia, Bifidobacterium and Blautia and a lower abundance of Lactobacillus, Escherichia-Shigella, and Dubosiella, while the mucosal microbiota showed a significant increase in Bifidobacterium, Akkermansia, Albaculum, Bilophila, and Coriobacteriaceae_UCG-002 and a lower abundance of Enterococcus, Helicobacter, Dubosiella, and Collinsella. Furthermore, the treatments enhanced lactose fermentation and SCFA production, which may be related to the modulation of the luminal microbial community. A lower ratio of phosphorylation Na/H exchanger3/Na/H exchanger3 (pNHE3/NHE3) and a higher sodium monocarboxylate1 (sMCT1) expression were found in the treatment group than in the model group, which may be related to the changes in the mucosal microbial community. Also, the treatments may restore the impacted metabolic pathways of gut microbiota. These results provide an important foundation for mechanism of SL action and developing PL-based treatment for lactose-induced diarrhea. | H21: No | I21: Yes | J21: No | K21: SL and its polysaccharide regulate luminal/mucosal microbiota and SCFA metabolism to relieve lactose-induced diarrhea in rats.
A22: 35795854 | B22: Green Synthesis of Silver Nanoparticles Using the Tridax procumbens Plant Extract and Screening of Its Antimicrobial and Anticancer Activities | C22: 2) Nuevos tratamientos | D22: 2b) Péptidos | E22: Listo | F22: 2022 | G22: In this study, we report the green synthesis of silver nanoparticles (AgNPs) using the aqueous leaf extract of Tridax procumbens (TNP), which acts as the source of the reducing and capping agent. The distinctive absorption at 370 nm suggested synthesis of TNPs, which was confirmed by TEM, with a size in the range of 11.1 nm to 45.4 nm and a spherical shape, having a face-centered cubic structure, analyzed by XRD, and a Zeta potential of -20.7 mV, which indicated a moderate stability of TNP. The FTIR analysis revealed the presence of amines and hydroxyl groups with fluoro compounds over the TNPs. The HRLC-MS analysis of TNPs suggested the presence of a major capping agent such as fosinopril and reducing agents such as peptides (Gln Gly Ala, Ser Pro Asn, and Leu Met), terpenoids (lupanyl acid, tiamulin), polyphenol (peucenin), and alkaloids (8',10'-dihydroxydihydroergotamine, carteolol). The synthesized silver nanoparticles exhibited antimicrobial activity against multidrug-resistant (MDR) clinical isolates (Escherichia coli, Shigella spp., Aeromonas spp., Pseudomonas aeruginosa, and Candida tropicalis) and had anticancer activity against A459 (IC50 42.70 μg/ml). The extraction of partially purified aqueous leaf extracts by silica gel column chromatography followed by HPLC to synthesize silver nanoparticles (TNP11) and analyzed by HRLC-MS suggested that dipeptides were involved in the reduction of Ag+ to Ag0. Overall, the results showed that the green silver nanoparticles of T. procumbens could be safe, as they are endowed with potential antimicrobial activity against MDR clinical isolates and human lung carcinoma cells. | H22: No | I22: Yes | J22: No | K22: Green AgNPs from T. procumbens showed antimicrobial activity against MDR strains and anticancer activity on A459 cells.
A23: 35814680 | B23: Microbial Antagonism in Food-Enrichment Culture: Inhibition of Shiga Toxin-Producing Escherichia coli and Shigella Species | C23: 1) Reporte de cepas resistentes | E23: Listo | F23: 2022 | G23: Bacterial pathogens, such as Shiga toxin-producing Escherichia coli (STEC) and Shigella spp., are important causes of foodborne illness internationally. Recovery of these organisms from foods is critical for food safety investigations to support attribution of illnesses to specific food commodities; however, isolation of bacterial cultures can be challenging. Methods for the isolation of STEC and Shigella spp. from foods typically require enrichment to amplify target organisms to detectable levels. Yet, during enrichment, target organisms can be outcompeted by other bacteria in food matrices due to faster growth rates, or through production of antimicrobial agents such as bacteriocins or bacteriophages. The purpose of this study was to evaluate the occurrence of Shigella and STEC inhibitors produced by food microbiota. The production of antimicrobial compounds in cell-free extracts from 200 bacterial strains and 332 food-enrichment broths was assessed. Cell-free extracts produced by 23 (11.5%) of the strains tested inhibited growth of at least one of the five Shigella and seven STEC indicator strains used in this study. Of the 332 enrichment broths tested, cell-free extracts from 25 (7.5%) samples inhibited growth of at least one of the indicator strains tested. Inhibition was most commonly associated with E. coli recovered from meat products. Most of the inhibiting compounds were determined to be proteinaceous (34 of the 48 positive samples, 71%; including 17 strains, 17 foods) based on inactivation by proteolytic enzymes, indicating presence of bacteriocins. The cell-free extracts from 13 samples (27%, eight strains, five foods) were determined to contain bacteriophages based on the observation of plaques in diluted extracts and/or resistance to proteolytic enzymes. These results indicate that the production of inhibitors by food microbiota may be an important challenge for the recovery of foodborne pathogens, particularly for Shigella sonnei. The performance of enrichment media for recovery of Shigella and STEC could be improved by mitigating the impact of inhibitors produced by food microbiota during the enrichment process. | H23: No | I23: No | J23: No
A24: 35774450 | B24: Akkermansia muciniphila Alters Gut Microbiota and Immune System to Improve Cardiovascular Diseases in Murine Model | C24: 2) Nuevos tratamientos | D24: 2a) Productos naturales | E24: Listo | F24: 2022 | G24: The gut microbiota plays an important role in a variety of cardiovascular diseases. The probiotics screened based on microbiota can effectively improve metabolism and immune function of the body, which is of great value in the field of cardiovascular disease treatment. Abdominal aortic aneurysms (AAA) refer to the lesion or injury of the abdominal aortic wall resulting in a localized bulge, which is one of the cardiovascular diseases with pulsing mass as the main clinical symptom. Previous studies have confirmed that A. muciniphila was depleted in the guts of AAA patients or mice. A. muciniphila is a potential probiotic for the treatment of intestinal microbiome-related diseases. Therefore, this study aims to investigate the effects of A. muciniphila on gut microbiota and disease-related biomarkers in AAA mice. C57BL/6J mice were used to construct the AAA model and treated with A. muciniphila. Aortic aneurysm formation in the AAA group is associated with the increased diameter of the abdominal aorta and inflammatory infiltration. A. muciniphila inhibited the formation of AAA and repaired tissue damage. The number of gut microbiota and α diversity index were decreased in the model group. A. muciniphila increased the number of gut microbiota and α diversity in AAA mice. The abundance of uncultured bacterium and Lactobacillus were increased, while the abundance of the Lachnospiraceae NK4A136 group was reduced in the AAA group. Compared with the control group, the levels of MMP-1, MMP-9, IL-33, CTSB, and CTSL in tissue and the levels of IL-6, IFN-γ, and CRP in blood were significantly increased, and the levels of IL-4, IL-10, and IL-17A in blood were significantly decreased in the AAA group. The intervention of A. muciniphila reversed these changes. The gut microbiota function prediction showed changes in E. coli, Clostridium, and Lactobacillus metabolism-related functional pathways. Akkermansia was negatively correlated with Helicobacter and Lactobacillus and positively correlated with Clostridium_sensu_stricto_1 and Escherichia shigella at the genus level. In conclusion, A. muciniphila inhibited the formation of AAA by restoring gut microbiota diversity, altering the expression of peripheral immune factors, and the functions of E. coli, Clostridium, and Lactobacillus, which may provide a new theoretical basis for the application of probiotics in cardiovascular diseases. | H24: No | I24: Yes | J24: No | K24: A. muciniphila prevents AAA formation by restoring gut microbiota diversity and modulating immune factors and metabolism pathways.
A25: 35774407 | B25: Therapeutic Effect of Buyang Huanwu Decoction on the Gut Microbiota and Hippocampal Metabolism in a Rat Model of Cerebral Ischemia | C25: 2) Nuevos tratamientos | D25: 2a) Productos naturales | E25: Listo | F25: 2022 | G25: Buyang Huanwu decoction (BHD) is a well-known Chinese herbal prescription. It has been widely used in the clinical treatment of cerebral ischemia (CI) in China. However, the mechanism underlying the treatment of CI with BHD remains to be elucidated. In this study, we combined microbiomic and metabolomic strategies to explore the therapeutic effects of BHD on middle cerebral artery occlusion (MCAO) in rats. Our results showed that BHD could effectively improve neurological severity scores and alleviate neuronal damage in rats with MCAO. BHD could also reduce the level of peripheral proinflammatory cytokines and inhibit neuroinflammation. 16S rRNA sequencing showed that BHD could increase the relative abundances of the genera Lactobacillus, Faecalibacterium, Ruminococcaceae_UCG-002, etc., while decreasing the relative abundances of the genera Escherichia-Shigella, Klebsiella, Streptococcus, Coprococcus_2, Enterococcus, etc. Untargeted metabolomic analysis of hippocampal samples showed that 17 significantly differentially abundant metabolites and 9 enriched metabolic pathways were linked with BHD treatment. We also found that the regulatory effects of BHD on metabolites were correlated with the differentially abundant microbial taxa. The predicted function of the gut microbiota and the metabolic pathway enrichment results showed that purine metabolism, glutamatergic synapses, arginine and proline metabolism, and alanine, aspartic acid and glutamate metabolism were involved in the effects of BHD. These pathways may be related to pathological processes such as excitotoxicity, neuroinflammation, and energy metabolism disorder in CI. In summary, these findings suggest that regulation of hippocampal metabolism and of the composition and function of the gut microbiota may be important mechanisms underlying the effect of BHD in the treatment of CI. | H25: No | I25: Yes | J25: No | K25: BHD alleviates CI by regulating hippocampal metabolism and gut microbiota, supporting its use as a novel treatment.
A26: 35769459 | B26: Oral Administration of a Shigella 2aT32-Based Vaccine Expressing UreB-HspA Fusion Antigen With and Without Parenteral rUreB-HspA Boost Confers Protection Against Helicobacter pylori in Mice Model | C26: 3) Inmunizacióm | D26: 2b) Péptidos | E26: Listo | F26: 2022 | G26: Helicobacter pylori (H. pylori) is a gram-negative pathogen classified as a class I carcinogen. The H. pylori urease B subunit (UreB) and heat shock protein A (HspA) are two important vaccine candidate antigens. In this study, we evaluated the immunogenicity and immunoprotective effect of the attenuated Shigella vector vaccine SH02 expressing the UreB-HspA fusion protein of H. pylori in a mouse model. Oral SH02 with or without subcutaneous injection of rUreB-HspA induced antigen-specific serum IgG, mucosal sIgA, and T cells immune response. Subcutaneous injection of the candidate antigen rUreB-HspA enhanced the level of serum antigen-specific IgG antibodies (p < 0.0001) and the levels of IgG1/IgG2a/IgG2b subtypes. In addition, injection boost also increased the proportion of spleen antigen-specific CD4+CD154+ T cells (p < 0.001), and the proportion of CD4+CD154+ T cells that secrete IFN-γ and IL-17A. Following the H. pylori challenge, the levels of H. pylori colonization in the two experimental groups (Groups A and B) significantly reduced compared with the control group (p < 0.001), indicating that the candidate vaccine yielded a preventive effect of anti-H.pylori infection. Compared with the non-subcutaneous booster injection group (Group A), the subcutaneous booster injection group (Group B) exhibited less gastric inflammation, but there was no significant difference in the level of colonization (p > 0.05). These results lay a foundation for the development of a vaccine against H. pylori and the optimization of immunization methods and procedures to prevent H. pylori infection. | H26: No | I26: No | J26: Yes | K26: SH02-UreB-HspA vaccine reduced H. pylori colonization and inflammation, supporting its use for immunization against infection.
A27: 34933656 | B27: Multicenter surveillance of in vitro activities of cefepime-zidebactam, cefepime-enmetazobactam, omadacycline, eravacycline, and comparator antibiotics against Enterobacterales, Pseudomonas aeruginosa, and Acinetobacter baumannii complex causing bloodstream infection in Taiwan, 2020 | C27: 1) Reporte de cepas resistentes | D27: 2g) nueva combinación de ATB | E27: Listo | F27: 2022 | G27: Objectives: To determine the in vitro activities of novel and comparator antibiotics against Gram-negative bacteria (GNB) in Taiwan. Methods: Isolates of Escherichia coli (n = 335), Klebsiella pneumoniae (n = 316; 144 isolates with hyperviscosity characteristics), Pseudomonas aeruginosa (n = 271), Acinetobacter baumannii complex (n = 187), and non-typhoidal Salmonella species (n = 226), Shigella species (n = 13) from miscellaneous culture sources were collected in 2020 in Taiwan. The MICs of the isolates to test antibiotics were determined using the broth microdilution method. GeneXpert was used to detect genes encoding carbapenemases among the carbapenem-non-susceptible (NS) Enterobacterales isolates. Results: The MIC values of the cefepime-enmetazobactam combination against extended-spectrum β-lactamase-producing E. coli and K. pneumoniae isolates (MIC90 ≤ 0.5 mg/L), blaKPC-harboring E. coli isolates (0.25 mg/L; n = 2), and 80% of blaOXA-48-like gene-harboring K. pneumoniae isolates (≤2 mg/L) were low. The MIC ranges of the cefepime-zidebactam against carbapenemase-producing Enterobacterales isolates (irrespective of the carbapenemase type [MIC90 ≤ 4 mg/L]) and carbapenem-NS or ceftolozane-tazobactam-NS P. aeruginosa isolates (MIC90 value, 8 mg/L) were significantly lower than those of the cefepime-enmetazobactam. Conclusions: The efficacy of novel antibiotics against important drug-resistant GNB must be monitored and validated during the clinical treatment of patients. | H27: Yes | I27: No | J27: No | K27: New antibiotic efficacy against drug-resistant GNB must be monitored and validated during clinical treatment, as the study emphasizes.
A28: 35669115 | B28: In Vitro Hepatoprotective and Human Gut Microbiota Modulation of Polysaccharide-Peptides in Pleurotus citrinopileatus | C28: 2) Nuevos tratamientos | D28: 2a) Productos naturales | E28: Listo | F28: 2022 | G28: Pleurotus citrinopileatus, a golden oyster mushroom, is popular in Asia and has pharmacological functions. However, the effects of polysaccharide-peptides extracted from Pleurotus citrinopileatus and underlying mechanism on digestive systme have not yet been clarified. Here, we determined the composition of two polysaccharide-peptides (PSI and PSII) from P. citrinopileatus and investigated the protective effects of on hepatoprotective and gut microbiota. The results showed that PSI and PSII were made up of similar monosaccharide moieties, except for the varying ratios. Furthermore, PSI and PSII showed that they have the hepatoprotective effects and significantly increased the viabilities and cellular total superoxide dismutase activities increased significantly in HepG2 cells. Intracellular triglyceride content and extracellular alanine aminotransferase and aspartate transaminase contents markedly decreased following treatment with 40 and 50 μg/mL PSI and PSII, respectively. Moreover, PSI and PSII activated the adiponectin pathway and reduced lipid accumulation in liver cells. PSI and PSII elevated short-chain fatty acid concentrations, especially butyric and acetic acids. 16S rRNA gene sequencing analysis showed that PSI promoted the relative abundances of Bifidobacteria, Lactobacillus, Faecalibacterium, as well as Prevotella generas in the gut. PSII markedly suppressed the relative abundances of Escherichia-Shigella and Bacteroides generas. We speculate that the PSI and PSII play a role through liver-gut axis system. Polysaccharide-peptides metabolize by gut microbiota to produce short-chain fatty acids (SCFAs) and in turn influence liver functions. | H28: No | I28: Yes | J28: No | K28: Polysaccharide-peptides from Pleurotus citrinopileatus improve liver function and modulate gut microbiota, supporting digestive health.
A29: 35663873 | B29: Diarrhea-Causing Bacteria and Their Antibiotic Resistance Patterns Among Diarrhea Patients From Ghana | C29: 1) Reporte de cepas resistentes | E29: Listo | F29: 2022 | G29: Diarrheal disease remains a major global health problem particularly in children under 5 years and the emergence of antibiotic-resistant strains of causative pathogens could slow control efforts, particularly in settings where treatment options are limited. This surveillance study conducted in Ghana aimed to determine the prevalence and antimicrobial susceptibility profile of diarrhea-causing bacteria. This was a cross-sectional study carried out in five health facilities in the Ga West Municipality of Ghana between 2017 and 2021. Diarrheic stool samples from patients were collected and cultured on standard differential/selective media and isolates identified by standard biochemical tests, MALDI-TOF assay, and serological analysis. The antibiogram was determined using Kirby-Bauer disk diffusion and Microscan autoScan4 MIC panels which were used for extended-spectrum beta-lactamase (ESBL) detection. Bacteria were isolated from 97.5% (772/792) of stool samples, and 167 of the isolates were diarrheagenic and met our inclusion criteria for antimicrobial resistance (AMR) analysis. These included Escherichia coli (49.1%, 82/167), Salmonella species (23.9%, 40/167), Vibrio species (16.8%, 28/167), and Shigella species (10.2%, 17/167). Among 24 Vibrio species, we observed resistances to cefotaxime (21/24, 87.5%), ceftriaxone (20/24, 83.3%), and ciprofloxacin (6/24, 25%), including four multi-drug resistant isolates. All 13 Vibrio parahaemolyticus isolates were resistant to cefazolin. All 17 Shigella isolates were resistant to tetracycline with resistance to shigellosis drugs such as norfloxacin and ciprofloxacin. Salmonella isolates were highly susceptible to norfloxacin (40/40, 100%) and tetracycline (12/34, 35%). Two ESBL-producing E. coli were also identified with marked susceptibility to gentamicin (66/72, 91.7%) and amikacin (57/72, 79.2%) prescribed in the treatment of E. coli infections. This study showed the different bacteria implicated in diarrhea cases in Ghana and the need for differential diagnoses for better treatment outcomes. Escherichia coli, Shigella, Salmonella, and Vibrio have all been implicated in diarrhea cases in Ghana. The highest prevalence was E. coli and Salmonella with Shigella the least prevalent. Resistance to commonly used drugs found in these isolates may render bacteria infection treatment in the near future nearly impossible. Routine antimicrobial susceptibility testing, effective monitoring, and nationwide surveillance of AMR pathogens should be implemented to curb the increase of antimicrobial resistance in Ghana. | H29: Yes | I29: No | J29: No | K29: Diarrheagenic bacteria in Ghana showed high resistance to antibiotics, emphasizing the need for better surveillance and treatment strategies.
A30: 35646734 | B30: In Vitro Activity of MRX-8 and Comparators Against Clinical Isolated Gram-Negative Bacilli in China | C30: 2) Nuevos tratamientos | D30: 2c) Droga de diseño | E30: Listo | F30: 2022 | G30: To evaluate in vitro antibacterial activity of MRX-8 against gram-negative bacteria recently isolated from China, 765 clinical isolates were collected randomly from 2017 to 2020, including Enterobacterales and P. aeruginosa and A. baumannii, S. maltophilia, B. cepacia, Alcaligenes app. and Haemophilus spp. isolates. All strains were performed with antimicrobial susceptibility testing by broth microdilution method according to the CLSI 2021. Antimicrobial agents included MRX-8, polymyxin B, colistin, amikacin, ceftriaxone, ceftazidime, cefepime, ceftazidime-avibactam, cefoperazone-sulbactam, meropenem, ciprofloxacin, ampicillin, ampicillin-sulbactam and levofloxacin. For carbapenem-susceptible and carbapenem-resistant E.coli isolates, the MIC50/90 of MRX-8 was 0.125/0.25 mg/L and 0.06/0.125 mg/L, respectively. For carbapenem-susceptible and carbapenem-resistant K. pneumoniae isolates, the MIC50/90 of MRX-8 was 0.25/0.5 mg/L and 0.125/0.5 mg/L, respectively. For polymyxins (polymyxin B and colistin)-resistant E. coli and K. pneumoniae, MIC50 of MRX-8 was 4-16 mg/L and MIC90 was >32 mg/L. The MIC50 and MIC90 of MRX-8 for other Klebsiella spp. except K. pneumoniae, Citrobacter spp., S. enterica and Shigella spp. isolates ranged 0.06-0.125 mg/L and 0.06-0.25mg/L, respectively. For Morganella spp., Proteus spp., Providencia spp., Serratia spp., S. maltophilia and B. cepacia, all MIC50 of MRX-8 was >32mg/L. For carbapenem susceptible and resistant P. aeruginosa, the MIC50 and MIC90 of MRX-8 was both 1mg/L, and that for A. baumannii was 0.5mg/L and 0.5-1mg/L. For Alcaligenes spp. and Haemophilus spp., MIC50/90 was 1/4 mg/L and 0.25/0.5 mg/L. MRX-8 was more effective against most clinically isolated gram-negative isolates, including carbapenem-resistant E. coli, K. pneumoniae, P. aeruginosa and A. baumannii, highlighting its potential as valuable therapeutics. | H30: No | I30: Yes | J30: No | K30: MRX-8 showed effectiveness against carbapenem-resistant E. coli, K. pneumoniae, P. aeruginosa, and A. baumannii, indicating its potential as a new therapeutic.
A31: 35812262 | B31: Characterization and drug susceptibility pattern of Salmonella and Shigella in children below five years: a cross-sectional study conducted in Lodwar, Turkana County, in Northern Kenya | C31: 1) Reporte de cepas resistentes | E31: Listo | F31: 2022 | G31: Introduction: Salmonella and Shigella infections are waterborne associated infections globally known to cause serious illnesses in all age groups, but can be more devastating in children below five years. Antimicrobial resistance has been known to worsen the existing challenge in the management of Salmonella and Shigella infections. The aim is to isolate and identify Salmonella and Shigella among children less than five years with diarrhea and to determine resistance to commonly prescribed drugs at the Lodwar County and Referral Hospital in Northern Kenya. Methods: using a cross-sectional study design, a descriptive experimental study was conducted on 196 children with diarrhea using rectal swabs. A structured questionnaire was used to collect sociodemographic information. Samples were then received in the microbiology laboratory, and macroscopic and microscopic examinations were done before culture on specific selective media. Thereafter, biochemical confirmation of the growths done then confirmed results tabulated before analysis. Results: from the total samples collected (196) Shigella dysenteriae cases were 4 (5%), while Shigella Flexneri were 7 (9%), Shigella sonnei were 3 (4%), Shigella boydii were 4 (5%) and Salmonella typhimurium were 2 (2.4%). From these, about 70% of the isolated Salmonella and Shigella demonstrated high antibiotic resistance to Amoxilliclav and Ampicillin, both with high minimum inhibitory concentrations (MICs) values of about 8ug/ml. While over 80% drug susceptibility was noted in Amikacin (1ug/ml), Ciprofloxacin (2ug/ml), Ceftriaxone (4ug/ml) and Ceftazidime (4ug/ml). Conclusion: Salmonella and Shigella are among the common contributors of diarrhea among children less than five years. Drug resistance among the commonly used antibiotics is a serious indicator that possible misuse of antibiotics especially the beta lactam penicillin's. | H31: Yes | I31: No | J31: No | K31: High antibiotic resistance in Salmonella and Shigella isolates from children under five years highlights the need for better management of infections.
A32: 35601674 | B32: Gancao Xiexin Decoction Ameliorates Ulcerative Colitis in Mice via Modulating Gut Microbiota and Metabolites | C32: 2) Nuevos tratamientos | D32: 2a) Productos naturales | E32: Listo | F32: 2022 | G32: Purpose: Ulcerative colitis (UC) is a chronic inflammatory bowel disease that starts with mucosal inflammation of the rectum and extends proximally in the colon in a continuous manner over a variable distance. Although it is more common in North America and Western Europe, its incidence is also increasing in Asia. Despite the introduction of several different classes of medications, the treatment options for UC may be insufficiently effective and burdened with significant side effects. In the present study, the therapeutic effects of Gancao Xiexin decoction (GCXX) were investigated on mice with dextran sulfate sodium (DSS)-induced colitis with exploration of the underlying mechanisms. Methods: Colitis was induced in C57BL/6 mice by administering 3% DSS in drinking water for 7 days. GCXX and (or) the standard of care anti-inflammatory drug, mesalazine (5-aminosalicylic acid) were then administered for 7 days. The gut microbiota was characterized by 16S rDNA high-throughput gene sequencing and gut metabolites were detected by untargeted metabolomics. Germ-free mice were subsequently used to determine whether GCXX ameliorated UC principally through modulation of the gut microbiota. Results: GCXX treatment was demonstrated to significantly reduce disease activity index (DAI) scores, prevent colonic shortening, ameliorate colonic tissue damage and reduce the levels of pro-inflammatory cytokines. Furthermore, analysis of the gut microbiota showed that GCXX-treated mice had higher relative quantity of Dubosiella (P<0.05) and lower relative quantity of Escherichia-Shigella (P<0.05). Metabolomics analysis indicated that GCXX could reduce the level of linoleic acid (P<0.05) and regulate its metabolism pathway. Moreover, in germ-free mice, GCXX failed to increase body weight, reduce DAI scores, or alleviate either colonic shortening or colonic damage. Conclusion: The present study demonstrated that GCXX ameliorated DSS-induced colitis principally through modulating the gut microbiota and metabolites. This information should be integrated into the overall mechanisms of GCXX treatment of UC. | H32: No | I32: Yes | J32: No | K32: GCXX treatment showed potential in ameliorating ulcerative colitis by modulating gut microbiota and metabolites, highlighting a novel therapeutic approach.
A33: 35600873 | B33: Lactobacillus acidophilus and HKL Suspension Alleviates Ulcerative Colitis in Rats by Regulating Gut Microbiota, Suppressing TLR9, and Promoting Metabolism | C33: 2) Nuevos tratamientos | D33: 2a) Productos naturales | E33: Listo | F33: 2022 | G33: Ulcerative colitis (UC) is a chronic non-specific inflammatory bowel disease with complex pathogenesis. The intestinal flora disturbance affects the homeostasis of the intestinal environment, leading to metabolic imbalance and immune abnormalities of the host, contributing to the perpetuation of intestinal inflammation. We suggest that the combination of anti-inflammatory therapy and the regulation of intestinal flora balance may help in the treatment process. Previously, we used a combination treatment consisting of Lactobacillus acidophilus (Lac) and Chinese medicine Huan Kui Le (HKL) suspension in a UC rat model, where the combined intervention was more effective than either treatment alone. Herein, the mechanism of action of this combined treatment has been investigated using 16S rRNA sequencing, immunohistochemistry, and ELISA methods in the colon, and untargeted metabolomics profiling in serum. Colon protein expression levels of IL-13 and TGF-β were upregulated, whereas those of TLR9 and TLR4 were downregulated, consistent with an anti-inflammatory effect. In addition, gut microbiota structure changed, shown by a decrease in opportunistic pathogens correlated with intestinal inflammation, such as Klebsiella and Escherichia-Shigella, and an increase in beneficial bacteria such as Bifidobacterium. The latter correlated positively with IL-13 and TGF-β and negatively with IFN-γ. Finally, this treatment alleviated the disruption of the metabolic profile observed in UC rats by increasing short-chain fatty acid (SCFA)-producing bacteria in the colonic epithelium. This combination treatment also affected the metabolism of lactic acid, creatine, and glycine and inhibited the growth of Klebsiella. Overall, we suggest that treatment combining probiotics and traditional Chinese medicine is a novel strategy beneficial in UC that acts by modulating gut microbiota and its metabolites, TLR9, and cytokines in different pathways. | H33: No | I33: Yes | J33: No | K33: The combination of Lactobacillus and Chinese medicine modulated gut microbiota and metabolites, offering a new strategy for ulcerative colitis treatment.
A34: 35571919 | B34: In vitro Study of Bifidobacterium lactis BL-99 With Fructooligosaccharide Synbiotics Effected on the Intestinal Microbiota | C34: 2) Nuevos tratamientos | D34: 2a) Productos naturales | E34: Listo | F34: 2022 | G34: Probiotics and prebiotics relieve constipation by altering the composition of the intestinal microbiota. However, their synergistic mechanism of action remains unclear. Herein, an in vitro fermentation model was constructed to examine the synergistic effects of Bifidobacterium lactis BL-99 and fructooligosaccharide (FOS) on the regulation of intestinal microbiota from a population with constipation. The utilization of FOS was promoted by BL-99, and the increase rate being 22.33%. Relative to the BL-99 and the FOS groups, the BL-99_FOS group showed a highly significant increase in acetic acid content (P < 0.01) and a marked decrease in CO2 and H2S contents (P < 0.01) in the fermentation broth. In addition, the BL-99_FOS combination significantly changed the structure of the intestinal microbiota, enhanced the relative abundances of beneficial bacteria that relieved constipation, including Bifidobacterium, Fecalibacterium, Lactobacillus, Subdoligranulum, and Blautia, and decreased those of the harmful bacteria, including Bilophila and Escherichia-Shigella. These findings suggested that BL-99 and FOS synergistically regulated the composition and structure of the intestinal microbiota from the population with constipation and increased acetic acid and decreased CO2 and H2S levels, thereby providing a theoretical basis for the application of synbiotics. | H34: No | I34: Yes | J34: No | K34: The combination of Bifidobacterium lactis and fructooligosaccharide synergistically altered gut microbiota to relieve constipation, supporting synbiotics use.
A35: 35571952 | B35: Gallnut Tannic Acid Exerts Anti-stress Effects on Stress-Induced Inflammatory Response, Dysbiotic Gut Microbiota, and Alterations of Serum Metabolic Profile in Beagle Dogs | C35: 2) Nuevos tratamientos | D35: 2a) Productos naturales | E35: Listo | F35: 2022 | G35: Stress exposure is a potential threat to humans who live or work in extreme environments, often leading to oxidative stress, inflammatory response, intestinal dysbiosis, and metabolic disorders. Gallnut tannic acid (TA), a naturally occurring polyphenolic compound, has become a compelling source due to its favorable anti-diarrheal, anti-oxidative, anti-inflammatory, and anti-microbial activities. Thus, this study aimed to evaluate the anti-stress effects of gallnut TA on the stress-induced inflammatory response, dysbiotic gut microbiota, and alterations of serum metabolic profile using beagle models. A total of 13 beagle dogs were randomly divided into the stress (ST) and ST + TA groups. Dietary supplementation with TA at 2.5 g/kg was individually fed to each dog in the ST + TA group for 14 consecutive days. On day 7, all dogs were transported for 3 h from a stressful environment (days 1-7) to a livable site (days 8-14). In our results, TA relieved environmental stress-induced diarrheal symptoms in dogs and were shown to protect from myocardial injury and help improve immunity by serum biochemistry and hematology analysis. Also, TA inhibited the secretion of serum hormones [cortisol (COR), glucocorticoid (GC), and adrenocorticotropic hormone (ACTH)] and the expression of heat shock protein (HSP) 70 to protect dogs from stress-induced injury, thereby relieving oxidative stress and inflammatory response. Fecal 16S rRNA gene sequencing revealed that TA stimulated the growth of beneficial bacteria (Allobaculum, Dubosiella, Coriobacteriaceae_UCG-002, and Faecalibaculum) and suppressed the growth of pathogenic bacteria (Escherichia-Shigella and Streptococcus), thereby increasing fecal butyrate levels. Serum metabolomics further showed that phytosphingosine, indoleacetic acid, arachidonic acid, and biotin, related to the metabolism of sphingolipid, tryptophan, arachidonic acid, and biotin, respectively, could serve as potential biomarkers of stress exposure. Furthermore, Spearman's correlation analysis showed strong relationships between the four potential serum biomarkers and differential bacteria. Overall, gallnut TA may be a potential prebiotic for the prevention and treatment of stress-induced metabolic disorders by targeting intestinal microbiota. | H35: No | I35: Yes | J35: No | K35: Gallnut tannic acid alleviated stress-induced dysbiosis and metabolic disorders, indicating its potential as a prebiotic for stress-related conditions.
A36: 35559259 | B36: Codonopsis pilosula Polysaccharide Improved Spleen Deficiency in Mice by Modulating Gut Microbiota and Energy Related Metabolisms | C36: 2) Nuevos tratamientos | D36: 2a) Productos naturales | E36: Listo | F36: 2022 | G36: Codonopsis Radix (CR) is an important traditional Chinese medicine used for the treatment of spleen deficiency syndrome (SDS). Codonopsis pilosula polysaccharides (CPP) in CR are considered to be responsible for tonifying the spleen function; however, the mechanisms of the polysaccharides have remained unclear. This study aimed to investigate the treatment mechanisms of CPP in SDS mice using a combinational strategy of 16S rRNA gene sequencing and targeted metabolomics. Here, studies demonstrated that CPP had invigorating effect in vivo in Sennae Folium-induced SDS in mice by organ indexes, D-xylose determination, gastrointestinal hormones levels and goblet cells observation. Antibiotic treatment revealed that the intestinal microbiota was required for the invigorating spleen effect of CPP. Furthermore, gut microbiota analysis found that CPP significantly enriched probiotic Lactobacillus and decreased the abundance of some opportunistic pathogens, such as Enterococcus and Shigella. The metabolic profile analysis of the colonic content revealed that 25 chemicals were altered significantly by CPP, including amino acids, organic acids, fatty acids, carbohydrates and carnitine etc., which are mainly related to "energy conversion" related processes such as amino acids metabolism, tricarboxylic acid cycle, and nitrogen metabolism. Spearman's correlation assays displayed there were strong correlations among biochemical indicators-gut microbiota-metabolomics. In summary, these results provided a new perspective for CPP improving SDS by regulating energy metabolism related bacteria and pathways. | H36: No | I36: Yes | J36: No | K36: CPP improved SDS by modulating gut microbiota and energy metabolism pathways, reducing Shigella and enriching Lactobacillus in mice.
A37: 35652042 | B37: Xuedan Sustained Release Pellets Ameliorate Dextran Sulfate Sodium-Induced Ulcerative Colitis in Rats by Targeting Gut Microbiota and MAPK Signaling Pathways | C37: 2) Nuevos tratamientos | D37: 2a) Productos naturales | E37: Listo | F37: 2022 | G37: Cucurbitacins have a variety of bioactivities, such as anticancer, anti-inflammatory, antidepressant-like, and antiviral effects, but their pharmacological effect in ulcerative colitis (UC) has not been reported until now. Thus, this study aims to investigate the preventive effects of Xuedan sustained release pellets (XSPs) on UC rats and the underlying mechanisms. XSPs were prepared by extracting cucurbitacins from Hemsleya. Experimental UC rats were induced by the intake of 4% dextran sulfate sodium (DSS) for a week and treated with different doses of XSP (0.95, 1.90, and 3.8 mg/kg). The body weight, colon length, disease activity index (DAI), and histological changes of colonic tissue were measured. In addition, the expressions of pro-inflammatory cytokines were detected by using the enzyme-linked immunosorbent assay. Pathways involved in the intestinal inflammation were targeted by RNA-sequencing. Moreover, the changes of gut microbial diversity and composition were analyzed by the 16SrNA analysis and the contents of short-chain fatty acids (SCFAs) were detected by GC-MS. The results revealed that XSP intervention greatly restored the weight loss and colonic shortening (p < 0.05) and reduced the raised DAI scores, myeloperoxidase, and nitric oxide activities in UC in rats (p < 0.05). XSP administration also downregulated the protein levels of pro-inflammatory factors IL-1β, IL-6, and TNF-α. Notably, it was found that XSP considerably suppressed the activation of the MAPK signaling pathway. In addition, XSP treatment improved the balance of gut microbiota that was disturbed by DSS. The beneficial bacteria Lachnospiraceae_NK4A136 group and Lactobacillus at the genus level significantly increased in the XSP group, which had decreased with the use of DSS (p < 0.05). Pathogenic bacteria including Escherichia-Shigella and Bacteroides in UC in rats were reduced by XSP intervention. Furthermore, XSP significantly elevated the production of SCFAs in UC in rats (p < 0.05). These alterations in inflammatory status were accompanied with changes in gut microbiota diversity and SCFA production. In conclusion, XSP exhibited protective effects against DSS-induced UC in rats. XSP treatment decreased inflammation via modulation of gut microbiota composition and SCFA production. | H37: No | I37: Yes | J37: No | K37: XSP prevented DSS-induced UC in rats by reducing inflammation, modulating gut microbiota, and increasing SCFA production.
A38: 35464096 | B38: Dietary Inclusion of Seabuckthorn (Hippophae rhamnoides) Mitigates Foodborne Enteritis in Zebrafish Through the Gut-Liver Immune Axis | C38: 2) Nuevos tratamientos | D38: 2a) Productos naturales | E38: Listo | F38: 2022 | G38: To help prevent foodborne enteritis in aquaculture, several feed additives, such as herbal medicine, have been added to fish diets. Predictions of effective herb medicines for treating fish foodborne enteritis from key regulated DEGs (differentially expressed genes) in transcriptomic data can aid in the development of feed additives using the Traditional Chinese Medicine Integrated Database. Seabuckthorn has been assessed as a promising candidate for treating grass carp soybean-induced enteritis (SBMIE). In the present study, the SBMIE zebrafish model was used to assess seabuckthorn's therapeutic or preventative effects. The results showed that intestinal and hepatic inflammation was reduced when seabuckthorn was added, either pathologically (improved intestinal villi morphology, less oil-drops) or growth-related (body fat deposition). Moreover, seabuckthorn may block the intestinal p53 signaling pathway, while activating the PPAR signaling pathway and fatty acid metabolism in the liver. 16S rRNA gene sequencing results also indicated a significant increase in OTU numbers and skewed overlapping with the fish meal group following the addition of seabuckthorn. Additionally, there were signs of altered gut microbiota taxa composition, particularly for reduced TM7, Sphingomonas, and Shigella, following the addition of seabuckthorn. Hindgut imaging of fluorescent immune cells in SBMIE larvae revealed the immune regulatory mechanisms at the cellular level. Seabuckthorn may significantly inhibit the inflammatory gathering of neutrophils, macrophages, and mature T cells, as well as cellular protrusions' formation. On the other hand, in larvae, seabuckthorn inhibited the inflammatory aggregation of lck+ T cells but not immature lymphocytes, indicating that it affected intestinal adaptive immunity. Although seabuckthorn did not affect the distribution of intestinal CD4+ cells, the number of hepatic CD4+ cells were reduced in fish from the seabuckthorn supplementation group. Thus, the current data indicate that seabuckthorn may alleviate foodborne gut-liver symptoms by enhancing intestinal mucosal immunity and microbiota while simultaneously inhibiting hepatic adipose disposition, making it a potential additive for preventing fish foodborne gut-liver symptoms. | H38: No | I38: Yes | J38: No | K38: Seabuckthorn alleviated fish gut-liver inflammation, modulated microbiota, and immunity, showing promise as a preventive feed additive.
A39: 35337591 | B39: Comprehensive analysis of Sparassis crispa polysaccharide characteristics during the in vitro digestion and fermentation model | C39: 2) Nuevos tratamientos | D39: 2a) Productos naturales | E39: Listo | F39: 2022 | G39: Sparassis crispa (S.crispa), an edible mushroom, is widely used as a natural medicine due to its excellent pharmacological activities, including antitumor, anti-angiogenic, and immunomodulatory activities. In the current study, the digestion and fermentation characteristics of an S.crispa polysaccharide (SCP-1) were investigated by the in vitro simulated models. Our results revealed that SCP-1 was not degraded during the simulated gastrointestinal tract. However, it was consumed by human intestinal microbiota, which was characterized by enhancing the production of short-chain fatty acids (such as acetate, propionate, and butyrate), and modifying the gut microbiota composition through promoting beneficial genera (Prevotella 9, Dialister, Megamonas, and Megasphaera) and inhibiting proliferation of some harmful bacteria (i.e., Escherichia/Shigella). The PICRUSt prediction analysis indicated that SCP-1 significantly increased carbohydrate, energy, and amino acid metabolism. These results suggest that SCP-1 could be developed as a prebiotic addition and may improve host health by regulating gut microbiota. | H39: No | I39: Yes | J39: No | K39: SCP-1 modulated microbiota and SCFA production, inhibiting harmful bacteria, supporting its potential as a prebiotic for host health improvement.
A40: 35042282 | B40: Chemical composition and antibacterial activity of 12 medicinal plant ethyl acetate extracts using LC-MS feature-based molecular networking | C40: 2) Nuevos tratamientos | D40: 2a) Productos naturales | E40: Listo | F40: 2022 | G40: Introduction: Widespread use of antibiotics has led to an increase in bacterial multiple drug resistance, thereby searching for natural antimicrobial agents from plants becomes an effective and alternative approach. In the present study, we selected six foodborne bacteria to evaluate the antibacterial activities of 12 medicinal plants ethyl acetate (EA) extracts. Objective: This study aims to search for natural antibiotic substitutes from plant extracts. The antibacterial components were further discussed through chemometric and mass spectroscopic analyses. Methodology: Agar well diffusion and the microdilution methods were used to test the antibacterial activity. Total phenolic content (TPC) and total flavonoid content (TFC) were used to judge the active phytochemicals. To further characterise the potential antibacterial components, an ultra-performance liquid chromatography-quadrupole-time of flight-mass spectrometry (UPLC-Q-TOF-MS) coupled with Pearson correlation and feature-based molecular network (FBMN) were proposed. Results: Most of the plant extracts possessed antibacterial activity against Bacillus subtilis and Salmonella typhi. Toona sinensis shoots and Firmiana simplex barks showed high inhibitory activities against Staphylococcus aureus, Shigella dysenteriae, and Escherichia coli strains with minimum inhibitory concentrations (MICs) of 1.56, 0.78, and 0.39 mg/mL, respectively. Salmonella typhi was highly sensitive to Firmiana simplex barks with an inhibitory diameter up to 21.67 ± 0.95 mm, and MIC at 0.78 mg/mL. Moreover, Toona sinensis shoots and Firmiana simplex barks had the highest TPCs. Conclusion: Our results indicated that Toona sinensis shoots, Koelreuteria paniculate seeds, and Firmiana simplex barks could be supplied as potential sources of antimicrobial agents. Furthermore, 36 potential bioactive compounds were identified mainly as polyphenols, glycosides, and terpenoids. | H40: No | I40: Yes | J40: No | K40: Plant extracts inhibited foodborne pathogens; bioactive compounds identified, supporting novel natural antimicrobial use.
